Workbook

Sheet 渠道充值成功率-统整
B1: Date | C1: jiliarena | D1: GCash | E1: QRPH | F1: GCashQR | G1: Maya | H1: GRABPAY | I1: Online Banking | J1: USDT | K1: GOTYME | L1: GCASHPAY
A2: =B2 -> 46082 | B2: 46082 | C2: 申请笔数 | D2: =SUMIFS('渠道充值成功率_底稿'!$C:$C,'渠道充值成功率_底稿'!$A:$A,$A2,'渠道充值成功率_底稿'!$B:$B,D$1) -> 1458 | E2: =SUMIFS('渠道充值成功率_底稿'!$C:$C,'渠道充值成功率_底稿'!$A:$A,$A2,'渠道充值成功率_底稿'!$B:$B,E$1) -> 32 | F2: =SUMIFS('渠道充值成功率_底稿'!$C:$C,'渠道充值成功率_底稿'!$A:$A,$A2,'渠道充值成功率_底稿'!$B:$B,F$1) -> 61 | G2: =SUMIFS('渠道充值成功率_底稿'!$C:$C,'渠道充值成功率_底稿'!$A:$A,$A2,'渠道充值成功率_底稿'!$B:$B,G$1) -> 146 | H2: =SUMIFS('渠道充值成功率_底稿'!$C:$C,'渠道充值成功率_底稿'!$A:$A,$A2,'渠道充值成功率_底稿'!$B:$B,H$1) -> 0 | I2: =SUMIFS('渠道充值成功率_底稿'!$C:$C,'渠道充值成功率_底稿'!$A:$A,$A2,'渠道充值成功率_底稿'!$B:$B,I$1) -> 0 | J2: =SUMIFS('渠道充值成功率_底稿'!$C:$C,'渠道充值成功率_底稿'!$A:$A,$A2,'渠道充值成功率_底稿'!$B:$B,J$1) -> 0 | K2: =SUMIFS('渠道充值成功率_底稿'!$C:$C,'渠道充值成功率_底稿'!$A:$A,$A2,'渠道充值成功率_底稿'!$B:$B,K$1) -> 6 | L2: =SUMIFS('渠道充值成功率_底稿'!$C:$C,'渠道充值成功率_底稿'!$A:$A,$A2,'渠道充值成功率_底稿'!$B:$B,L$1) -> 0
A3: =B2 -> 46082 | C3: 到账笔数 | D3: =SUMIFS('渠道充值成功率_底稿'!$F:$F,'渠道充值成功率_底稿'!$A:$A,$A3,'渠道充值成功率_底稿'!$B:$B,D$1) -> 1065 | E3: =SUMIFS('渠道充值成功率_底稿'!$F:$F,'渠道充值成功率_底稿'!$A:$A,$A3,'渠道充值成功率_底稿'!$B:$B,E$1) -> 24 | F3: =SUMIFS('渠道充值成功率_底稿'!$F:$F,'渠道充值成功率_底稿'!$A:$A,$A3,'渠道充值成功率_底稿'!$B:$B,F$1) -> 41 | G3: =SUMIFS('渠道充值成功率_底稿'!$F:$F,'渠道充值成功率_底稿'!$A:$A,$A3,'渠道充值成功率_底稿'!$B:$B,G$1) -> 117 | H3: =SUMIFS('渠道充值成功率_底稿'!$F:$F,'渠道充值成功率_底稿'!$A:$A,$A3,'渠道充值成功率_底稿'!$B:$B,H$1) -> 0 | I3: =SUMIFS('渠道充值成功率_底稿'!$F:$F,'渠道充值成功率_底稿'!$A:$A,$A3,'渠道充值成功率_底稿'!$B:$B,I$1) -> 0 | J3: =SUMIFS('渠道充值成功率_底稿'!$F:$F,'渠道充值成功率_底稿'!$A:$A,$A3,'渠道充值成功率_底稿'!$B:$B,J$1) -> 0 | K3: =SUMIFS('渠道充值成功率_底稿'!$F:$F,'渠道充值成功率_底稿'!$A:$A,$A3,'渠道充值成功率_底稿'!$B:$B,K$1) -> 4 | L3: =SUMIFS('渠道充值成功率_底稿'!$F:$F,'渠道充值成功率_底稿'!$A:$A,$A3,'渠道充值成功率_底稿'!$B:$B,L$1) -> 0
A4: =B2 -> 46082 | C4: 笔数成功率 | D4: =IFERROR(ROUND(D3/D2,6),"0") -> 0.730453 | E4: =IFERROR(ROUND(E3/E2,6),"0") -> 0.75 | F4: =IFERROR(ROUND(F3/F2,6),"0") -> 0.672131 | G4: =IFERROR(ROUND(G3/G2,6),"0") -> 0.80137 | H4: =IFERROR(ROUND(H3/H2,6),"0") -> 0 | I4: =IFERROR(ROUND(I3/I2,6),"0") -> 0 | J4: =IFERROR(ROUND(J3/J2,6),"0") -> 0 | K4: =IFERROR(ROUND(K3/K2,6),"0") -> 0.666667 | L4: =IFERROR(ROUND(L3/L2,6),"0") -> 0
A5: =B2 -> 46082 | C5: 申请金额 | D5: =SUMIFS('渠道充值成功率_底稿'!$D:$D,'渠道充值成功率_底稿'!$A:$A,$A6,'渠道充值成功率_底稿'!$B:$B,D$1) -> 201674 | E5: =SUMIFS('渠道充值成功率_底稿'!$D:$D,'渠道充值成功率_底稿'!$A:$A,$A5,'渠道充值成功率_底稿'!$B:$B,E$1) -> 5860 | F5: =SUMIFS('渠道充值成功率_底稿'!$D:$D,'渠道充值成功率_底稿'!$A:$A,$A5,'渠道充值成功率_底稿'!$B:$B,F$1) -> 8630 | G5: =SUMIFS('渠道充值成功率_底稿'!$D:$D,'渠道充值成功率_底稿'!$A:$A,$A5,'渠道充值成功率_底稿'!$B:$B,G$1) -> 18592 | H5: =SUMIFS('渠道充值成功率_底稿'!$D:$D,'渠道充值成功率_底稿'!$A:$A,$A5,'渠道充值成功率_底稿'!$B:$B,H$1) -> 0 | I5: =SUMIFS('渠道充值成功率_底稿'!$D:$D,'渠道充值成功率_底稿'!$A:$A,$A5,'渠道充值成功率_底稿'!$B:$B,I$1) -> 0 | J5: =SUMIFS('渠道充值成功率_底稿'!$D:$D,'渠道充值成功率_底稿'!$A:$A,$A5,'渠道充值成功率_底稿'!$B:$B,J$1) -> 0 | K5: =SUMIFS('渠道充值成功率_底稿'!$D:$D,'渠道充值成功率_底稿'!$A:$A,$A5,'渠道充值成功率_底稿'!$B:$B,K$1) -> 900 | L5: =SUMIFS('渠道充值成功率_底稿'!$D:$D,'渠道充值成功率_底稿'!$A:$A,$A5,'渠道充值成功率_底稿'!$B:$B,L$1) -> 0
A6: =B2 -> 46082 | C6: 到账金额 | D6: =SUMIFS('渠道充值成功率_底稿'!$G:$G,'渠道充值成功率_底稿'!$A:$A,$A7,'渠道充值成功率_底稿'!$B:$B,D$1) -> 162179 | E6: =SUMIFS('渠道充值成功率_底稿'!$G:$G,'渠道充值成功率_底稿'!$A:$A,$A6,'渠道充值成功率_底稿'!$B:$B,E$1) -> 4610 | F6: =SUMIFS('渠道充值成功率_底稿'!$G:$G,'渠道充值成功率_底稿'!$A:$A,$A6,'渠道充值成功率_底稿'!$B:$B,F$1) -> 5980 | G6: =SUMIFS('渠道充值成功率_底稿'!$G:$G,'渠道充值成功率_底稿'!$A:$A,$A6,'渠道充值成功率_底稿'!$B:$B,G$1) -> 13472 | H6: =SUMIFS('渠道充值成功率_底稿'!$G:$G,'渠道充值成功率_底稿'!$A:$A,$A6,'渠道充值成功率_底稿'!$B:$B,H$1) -> 0 | I6: =SUMIFS('渠道充值成功率_底稿'!$G:$G,'渠道充值成功率_底稿'!$A:$A,$A6,'渠道充值成功率_底稿'!$B:$B,I$1) -> 0 | J6: =SUMIFS('渠道充值成功率_底稿'!$G:$G,'渠道充值成功率_底稿'!$A:$A,$A6,'渠道充值成功率_底稿'!$B:$B,J$1) -> 0 | K6: =SUMIFS('渠道充值成功率_底稿'!$G:$G,'渠道充值成功率_底稿'!$A:$A,$A6,'渠道充值成功率_底稿'!$B:$B,K$1) -> 700 | L6: =SUMIFS('渠道充值成功率_底稿'!$G:$G,'渠道充值成功率_底稿'!$A:$A,$A6,'渠道充值成功率_底稿'!$B:$B,L$1) -> 0
A7: =B2 -> 46082 | C7: 金额成功率 | D7: =IFERROR(ROUND(D6/D5,6),"0") -> 0.804164 | E7: =IFERROR(ROUND(E6/E5,6),"0") -> 0.786689 | F7: =IFERROR(ROUND(F6/F5,6),"0") -> 0.692932 | G7: =IFERROR(ROUND(G6/G5,6),"0") -> 0.724613 | H7: =IFERROR(ROUND(H6/H5,6),"0") -> 0 | I7: =IFERROR(ROUND(I6/I5,6),"0") -> 0 | J7: =IFERROR(ROUND(J6/J5,6),"0") -> 0 | K7: =IFERROR(ROUND(K6/K5,6),"0") -> 0.777778 | L7: =IFERROR(ROUND(L6/L5,6),"0") -> 0
A8: =B8 -> 46083 | B8: =B2+1 -> 46083 | C8: 申请笔数 | D8: =SUMIFS('渠道充值成功率_底稿'!$C:$C,'渠道充值成功率_底稿'!$A:$A,$A8,'渠道充值成功率_底稿'!$B:$B,D$1) -> 611 | E8: =SUMIFS('渠道充值成功率_底稿'!$C:$C,'渠道充值成功率_底稿'!$A:$A,$A8,'渠道充值成功率_底稿'!$B:$B,E$1) -> 14 | F8: =SUMIFS('渠道充值成功率_底稿'!$C:$C,'渠道充值成功率_底稿'!$A:$A,$A8,'渠道充值成功率_底稿'!$B:$B,F$1) -> 30 | G8: =SUMIFS('渠道充值成功率_底稿'!$C:$C,'渠道充值成功率_底稿'!$A:$A,$A8,'渠道充值成功率_底稿'!$B:$B,G$1) -> 81 | H8: =SUMIFS('渠道充值成功率_底稿'!$C:$C,'渠道充值成功率_底稿'!$A:$A,$A8,'渠道充值成功率_底稿'!$B:$B,H$1) -> 0 | I8: =SUMIFS('渠道充值成功率_底稿'!$C:$C,'渠道充值成功率_底稿'!$A:$A,$A8,'渠道充值成功率_底稿'!$B:$B,I$1) -> 0 | J8: =SUMIFS('渠道充值成功率_底稿'!$C:$C,'渠道充值成功率_底稿'!$A:$A,$A8,'渠道充值成功率_底稿'!$B:$B,J$1) -> 0 | K8: =SUMIFS('渠道充值成功率_底稿'!$C:$C,'渠道充值成功率_底稿'!$A:$A,$A8,'渠道充值成功率_底稿'!$B:$B,K$1) -> 14 | L8: =SUMIFS('渠道充值成功率_底稿'!$C:$C,'渠道充值成功率_底稿'!$A:$A,$A8,'渠道充值成功率_底稿'!$B:$B,L$1) -> 0
A9: =B8 -> 46083 | C9: 到账笔数 | D9: =SUMIFS('渠道充值成功率_底稿'!$F:$F,'渠道充值成功率_底稿'!$A:$A,$A9,'渠道充值成功率_底稿'!$B:$B,D$1) -> 492 | E9: =SUMIFS('渠道充值成功率_底稿'!$F:$F,'渠道充值成功率_底稿'!$A:$A,$A9,'渠道充值成功率_底稿'!$B:$B,E$1) -> 13 | F9: =SUMIFS('渠道充值成功率_底稿'!$F:$F,'渠道充值成功率_底稿'!$A:$A,$A9,'渠道充值成功率_底稿'!$B:$B,F$1) -> 24 | G9: =SUMIFS('渠道充值成功率_底稿'!$F:$F,'渠道充值成功率_底稿'!$A:$A,$A9,'渠道充值成功率_底稿'!$B:$B,G$1) -> 57 | H9: =SUMIFS('渠道充值成功率_底稿'!$F:$F,'渠道充值成功率_底稿'!$A:$A,$A9,'渠道充值成功率_底稿'!$B:$B,H$1) -> 0 | I9: =SUMIFS('渠道充值成功率_底稿'!$F:$F,'渠道充值成功率_底稿'!$A:$A,$A9,'渠道充值成功率_底稿'!$B:$B,I$1) -> 0 | J9: =SUMIFS('渠道充值成功率_底稿'!$F:$F,'渠道充值成功率_底稿'!$A:$A,$A9,'渠道充值成功率_底稿'!$B:$B,J$1) -> 0 | K9: =SUMIFS('渠道充值成功率_底稿'!$F:$F,'渠道充值成功率_底稿'!$A:$A,$A9,'渠道充值成功率_底稿'!$B:$B,K$1) -> 13 | L9: =SUMIFS('渠道充值成功率_底稿'!$F:$F,'渠道充值成功率_底稿'!$A:$A,$A9,'渠道充值成功率_底稿'!$B:$B,L$1) -> 0
A10: =B8 -> 46083 | C10: 笔数成功率 | D10: =IFERROR(ROUND(D9/D8,6),"0") -> 0.805237 | E10: =IFERROR(ROUND(E9/E8,6),"0") -> 0.928571 | F10: =IFERROR(ROUND(F9/F8,6),"0") -> 0.8 | G10: =IFERROR(ROUND(G9/G8,6),"0") -> 0.703704 | H10: =IFERROR(ROUND(H9/H8,6),"0") -> 0 | I10: =IFERROR(ROUND(I9/I8,6),"0") -> 0 | J10: =IFERROR(ROUND(J9/J8,6),"0") -> 0 | K10: =IFERROR(ROUND(K9/K8,6),"0") -> 0.928571 | L10: =IFERROR(ROUND(L9/L8,6),"0") -> 0
A11: =B8 -> 46083 | C11: 申请金额 | D11: =SUMIFS('渠道充值成功率_底稿'!$D:$D,'渠道充值成功率_底稿'!$A:$A,$A12,'渠道充值成功率_底稿'!$B:$B,D$1) -> 97556 | E11: =SUMIFS('渠道充值成功率_底稿'!$D:$D,'渠道充值成功率_底稿'!$A:$A,$A11,'渠道充值成功率_底稿'!$B:$B,E$1) -> 2325 | F11: =SUMIFS('渠道充值成功率_底稿'!$D:$D,'渠道充值成功率_底稿'!$A:$A,$A11,'渠道充值成功率_底稿'!$B:$B,F$1) -> 4167 | G11: =SUMIFS('渠道充值成功率_底稿'!$D:$D,'渠道充值成功率_底稿'!$A:$A,$A11,'渠道充值成功率_底稿'!$B:$B,G$1) -> 9777 | H11: =SUMIFS('渠道充值成功率_底稿'!$D:$D,'渠道充值成功率_底稿'!$A:$A,$A11,'渠道充值成功率_底稿'!$B:$B,H$1) -> 0 | I11: =SUMIFS('渠道充值成功率_底稿'!$D:$D,'渠道充值成功率_底稿'!$A:$A,$A11,'渠道充值成功率_底稿'!$B:$B,I$1) -> 0 | J11: =SUMIFS('渠道充值成功率_底稿'!$D:$D,'渠道充值成功率_底稿'!$A:$A,$A11,'渠道充值成功率_底稿'!$B:$B,J$1) -> 0 | K11: =SUMIFS('渠道充值成功率_底稿'!$D:$D,'渠道充值成功率_底稿'!$A:$A,$A11,'渠道充值成功率_底稿'!$B:$B,K$1) -> 3110 | L11: =SUMIFS('渠道充值成功率_底稿'!$D:$D,'渠道充值成功率_底稿'!$A:$A,$A11,'渠道充值成功率_底稿'!$B:$B,L$1) -> 0
A12: =B8 -> 46083 | C12: 到账金额 | D12: =SUMIFS('渠道充值成功率_底稿'!$G:$G,'渠道充值成功率_底稿'!$A:$A,$A13,'渠道充值成功率_底稿'!$B:$B,D$1) -> 76391 | E12: =SUMIFS('渠道充值成功率_底稿'!$G:$G,'渠道充值成功率_底稿'!$A:$A,$A12,'渠道充值成功率_底稿'!$B:$B,E$1) -> 2225 | F12: =SUMIFS('渠道充值成功率_底稿'!$G:$G,'渠道充值成功率_底稿'!$A:$A,$A12,'渠道充值成功率_底稿'!$B:$B,F$1) -> 3467 | G12: =SUMIFS('渠道充值成功率_底稿'!$G:$G,'渠道充值成功率_底稿'!$A:$A,$A12,'渠道充值成功率_底稿'!$B:$B,G$1) -> 5458 | H12: =SUMIFS('渠道充值成功率_底稿'!$G:$G,'渠道充值成功率_底稿'!$A:$A,$A12,'渠道充值成功率_底稿'!$B:$B,H$1) -> 0 | I12: =SUMIFS('渠道充值成功率_底稿'!$G:$G,'渠道充值成功率_底稿'!$A:$A,$A12,'渠道充值成功率_底稿'!$B:$B,I$1) -> 0 | J12: =SUMIFS('渠道充值成功率_底稿'!$G:$G,'渠道充值成功率_底稿'!$A:$A,$A12,'渠道充值成功率_底稿'!$B:$B,J$1) -> 0 | K12: =SUMIFS('渠道充值成功率_底稿'!$G:$G,'渠道充值成功率_底稿'!$A:$A,$A12,'渠道充值成功率_底稿'!$B:$B,K$1) -> 2910 | L12: =SUMIFS('渠道充值成功率_底稿'!$G:$G,'渠道充值成功率_底稿'!$A:$A,$A12,'渠道充值成功率_底稿'!$B:$B,L$1) -> 0
A13: =B8 -> 46083 | C13: 金额成功率 | D13: =IFERROR(ROUND(D12/D11,6),"0") -> 0.783048 | E13: =IFERROR(ROUND(E12/E11,6),"0") -> 0.956989 | F13: =IFERROR(ROUND(F12/F11,6),"0") -> 0.832013 | G13: =IFERROR(ROUND(G12/G11,6),"0") -> 0.558249 | H13: =IFERROR(ROUND(H12/H11,6),"0") -> 0 | I13: =IFERROR(ROUND(I12/I11,6),"0") -> 0 | J13: =IFERROR(ROUND(J12/J11,6),"0") -> 0 | K13: =IFERROR(ROUND(K12/K11,6),"0") -> 0.935691 | L13: =IFERROR(ROUND(L12/L11,6),"0") -> 0
A14: =B14 -> 46084 | B14: =B8+1 -> 46084 | C14: 申请笔数 | D14: =SUMIFS('渠道充值成功率_底稿'!$C:$C,'渠道充值成功率_底稿'!$A:$A,$A14,'渠道充值成功率_底稿'!$B:$B,D$1) -> 563 | E14: =SUMIFS('渠道充值成功率_底稿'!$C:$C,'渠道充值成功率_底稿'!$A:$A,$A14,'渠道充值成功率_底稿'!$B:$B,E$1) -> 22 | F14: =SUMIFS('渠道充值成功率_底稿'!$C:$C,'渠道充值成功率_底稿'!$A:$A,$A14,'渠道充值成功率_底稿'!$B:$B,F$1) -> 26 | G14: =SUMIFS('渠道充值成功率_底稿'!$C:$C,'渠道充值成功率_底稿'!$A:$A,$A14,'渠道充值成功率_底稿'!$B:$B,G$1) -> 59 | H14: =SUMIFS('渠道充值成功率_底稿'!$C:$C,'渠道充值成功率_底稿'!$A:$A,$A14,'渠道充值成功率_底稿'!$B:$B,H$1) -> 0 | I14: =SUMIFS('渠道充值成功率_底稿'!$C:$C,'渠道充值成功率_底稿'!$A:$A,$A14,'渠道充值成功率_底稿'!$B:$B,I$1) -> 0 | J14: =SUMIFS('渠道充值成功率_底稿'!$C:$C,'渠道充值成功率_底稿'!$A:$A,$A14,'渠道充值成功率_底稿'!$B:$B,J$1) -> 0 | K14: =SUMIFS('渠道充值成功率_底稿'!$C:$C,'渠道充值成功率_底稿'!$A:$A,$A14,'渠道充值成功率_底稿'!$B:$B,K$1) -> 11 | L14: =SUMIFS('渠道充值成功率_底稿'!$C:$C,'渠道充值成功率_底稿'!$A:$A,$A14,'渠道充值成功率_底稿'!$B:$B,L$1) -> 0
A15: =B14 -> 46084 | C15: 到账笔数 | D15: =SUMIFS('渠道充值成功率_底稿'!$F:$F,'渠道充值成功率_底稿'!$A:$A,$A15,'渠道充值成功率_底稿'!$B:$B,D$1) -> 435 | E15: =SUMIFS('渠道充值成功率_底稿'!$F:$F,'渠道充值成功率_底稿'!$A:$A,$A15,'渠道充值成功率_底稿'!$B:$B,E$1) -> 21 | F15: =SUMIFS('渠道充值成功率_底稿'!$F:$F,'渠道充值成功率_底稿'!$A:$A,$A15,'渠道充值成功率_底稿'!$B:$B,F$1) -> 18 | G15: =SUMIFS('渠道充值成功率_底稿'!$F:$F,'渠道充值成功率_底稿'!$A:$A,$A15,'渠道充值成功率_底稿'!$B:$B,G$1) -> 48 | H15: =SUMIFS('渠道充值成功率_底稿'!$F:$F,'渠道充值成功率_底稿'!$A:$A,$A15,'渠道充值成功率_底稿'!$B:$B,H$1) -> 0 | I15: =SUMIFS('渠道充值成功率_底稿'!$F:$F,'渠道充值成功率_底稿'!$A:$A,$A15,'渠道充值成功率_底稿'!$B:$B,I$1) -> 0 | J15: =SUMIFS('渠道充值成功率_底稿'!$F:$F,'渠道充值成功率_底稿'!$A:$A,$A15,'渠道充值成功率_底稿'!$B:$B,J$1) -> 0 | K15: =SUMIFS('渠道充值成功率_底稿'!$F:$F,'渠道充值成功率_底稿'!$A:$A,$A15,'渠道充值成功率_底稿'!$B:$B,K$1) -> 6 | L15: =SUMIFS('渠道充值成功率_底稿'!$F:$F,'渠道充值成功率_底稿'!$A:$A,$A15,'渠道充值成功率_底稿'!$B:$B,L$1) -> 0
A16: =B14 -> 46084 | C16: 笔数成功率 | D16: =IFERROR(ROUND(D15/D14,6),"0") -> 0.772647 | E16: =IFERROR(ROUND(E15/E14,6),"0") -> 0.954545 | F16: =IFERROR(ROUND(F15/F14,6),"0") -> 0.692308 | G16: =IFERROR(ROUND(G15/G14,6),"0") -> 0.813559 | H16: =IFERROR(ROUND(H15/H14,6),"0") -> 0 | I16: =IFERROR(ROUND(I15/I14,6),"0") -> 0 | J16: =IFERROR(ROUND(J15/J14,6),"0") -> 0 | K16: =IFERROR(ROUND(K15/K14,6),"0") -> 0.545455 | L16: =IFERROR(ROUND(L15/L14,6),"0") -> 0
A17: =B14 -> 46084 | C17: 申请金额 | D17: =SUMIFS('渠道充值成功率_底稿'!$D:$D,'渠道充值成功率_底稿'!$A:$A,$A18,'渠道充值成功率_底稿'!$B:$B,D$1) -> 89488 | E17: =SUMIFS('渠道充值成功率_底稿'!$D:$D,'渠道充值成功率_底稿'!$A:$A,$A17,'渠道充值成功率_底稿'!$B:$B,E$1) -> 3250 | F17: =SUMIFS('渠道充值成功率_底稿'!$D:$D,'渠道充值成功率_底稿'!$A:$A,$A17,'渠道充值成功率_底稿'!$B:$B,F$1) -> 3975 | G17: =SUMIFS('渠道充值成功率_底稿'!$D:$D,'渠道充值成功率_底稿'!$A:$A,$A17,'渠道充值成功率_底稿'!$B:$B,G$1) -> 10480 | H17: =SUMIFS('渠道充值成功率_底稿'!$D:$D,'渠道充值成功率_底稿'!$A:$A,$A17,'渠道充值成功率_底稿'!$B:$B,H$1) -> 0 | I17: =SUMIFS('渠道充值成功率_底稿'!$D:$D,'渠道充值成功率_底稿'!$A:$A,$A17,'渠道充值成功率_底稿'!$B:$B,I$1) -> 0 | J17: =SUMIFS('渠道充值成功率_底稿'!$D:$D,'渠道充值成功率_底稿'!$A:$A,$A17,'渠道充值成功率_底稿'!$B:$B,J$1) -> 0 | K17: =SUMIFS('渠道充值成功率_底稿'!$D:$D,'渠道充值成功率_底稿'!$A:$A,$A17,'渠道充值成功率_底稿'!$B:$B,K$1) -> 2100 | L17: =SUMIFS('渠道充值成功率_底稿'!$D:$D,'渠道充值成功率_底稿'!$A:$A,$A17,'渠道充值成功率_底稿'!$B:$B,L$1) -> 0
A18: =B14 -> 46084 | C18: 到账金额 | D18: =SUMIFS('渠道充值成功率_底稿'!$G:$G,'渠道充值成功率_底稿'!$A:$A,$A19,'渠道充值成功率_底稿'!$B:$B,D$1) -> 71452 | E18: =SUMIFS('渠道充值成功率_底稿'!$G:$G,'渠道充值成功率_底稿'!$A:$A,$A18,'渠道充值成功率_底稿'!$B:$B,E$1) -> 3050 | F18: =SUMIFS('渠道充值成功率_底稿'!$G:$G,'渠道充值成功率_底稿'!$A:$A,$A18,'渠道充值成功率_底稿'!$B:$B,F$1) -> 2925 | G18: =SUMIFS('渠道充值成功率_底稿'!$G:$G,'渠道充值成功率_底稿'!$A:$A,$A18,'渠道充值成功率_底稿'!$B:$B,G$1) -> 8681 | H18: =SUMIFS('渠道充值成功率_底稿'!$G:$G,'渠道充值成功率_底稿'!$A:$A,$A18,'渠道充值成功率_底稿'!$B:$B,H$1) -> 0 | I18: =SUMIFS('渠道充值成功率_底稿'!$G:$G,'渠道充值成功率_底稿'!$A:$A,$A18,'渠道充值成功率_底稿'!$B:$B,I$1) -> 0 | J18: =SUMIFS('渠道充值成功率_底稿'!$G:$G,'渠道充值成功率_底稿'!$A:$A,$A18,'渠道充值成功率_底稿'!$B:$B,J$1) -> 0 | K18: =SUMIFS('渠道充值成功率_底稿'!$G:$G,'渠道充值成功率_底稿'!$A:$A,$A18,'渠道充值成功率_底稿'!$B:$B,K$1) -> 1200 | L18: =SUMIFS('渠道充值成功率_底稿'!$G:$G,'渠道充值成功率_底稿'!$A:$A,$A18,'渠道充值成功率_底稿'!$B:$B,L$1) -> 0
A19: =B14 -> 46084 | C19: 金额成功率 | D19: =IFERROR(ROUND(D18/D17,6),"0") -> 0.798453 | E19: =IFERROR(ROUND(E18/E17,6),"0") -> 0.938462 | F19: =IFERROR(ROUND(F18/F17,6),"0") -> 0.735849 | G19: =IFERROR(ROUND(G18/G17,6),"0") -> 0.82834 | H19: =IFERROR(ROUND(H18/H17,6),"0") -> 0 | I19: =IFERROR(ROUND(I18/I17,6),"0") -> 0 | J19: =IFERROR(ROUND(J18/J17,6),"0") -> 0 | K19: =IFERROR(ROUND(K18/K17,6),"0") -> 0.571429 | L19: =IFERROR(ROUND(L18/L17,6),"0") -> 0
A20: =B20 -> 46085 | B20: =B14+1 -> 46085 | C20: 申请笔数 | D20: =SUMIFS('渠道充值成功率_底稿'!$C:$C,'渠道充值成功率_底稿'!$A:$A,$A20,'渠道充值成功率_底稿'!$B:$B,D$1) -> 495 | E20: =SUMIFS('渠道充值成功率_底稿'!$C:$C,'渠道充值成功率_底稿'!$A:$A,$A20,'渠道充值成功率_底稿'!$B:$B,E$1) -> 15 | F20: =SUMIFS('渠道充值成功率_底稿'!$C:$C,'渠道充值成功率_底稿'!$A:$A,$A20,'渠道充值成功率_底稿'!$B:$B,F$1) -> 28 | G20: =SUMIFS('渠道充值成功率_底稿'!$C:$C,'渠道充值成功率_底稿'!$A:$A,$A20,'渠道充值成功率_底稿'!$B:$B,G$1) -> 54 | H20: =SUMIFS('渠道充值成功率_底稿'!$C:$C,'渠道充值成功率_底稿'!$A:$A,$A20,'渠道充值成功率_底稿'!$B:$B,H$1) -> 0 | I20: =SUMIFS('渠道充值成功率_底稿'!$C:$C,'渠道充值成功率_底稿'!$A:$A,$A20,'渠道充值成功率_底稿'!$B:$B,I$1) -> 0 | J20: =SUMIFS('渠道充值成功率_底稿'!$C:$C,'渠道充值成功率_底稿'!$A:$A,$A20,'渠道充值成功率_底稿'!$B:$B,J$1) -> 0 | K20: =SUMIFS('渠道充值成功率_底稿'!$C:$C,'渠道充值成功率_底稿'!$A:$A,$A20,'渠道充值成功率_底稿'!$B:$B,K$1) -> 2 | L20: =SUMIFS('渠道充值成功率_底稿'!$C:$C,'渠道充值成功率_底稿'!$A:$A,$A20,'渠道充值成功率_底稿'!$B:$B,L$1) -> 0
A21: =B20 -> 46085 | C21: 到账笔数 | D21: =SUMIFS('渠道充值成功率_底稿'!$F:$F,'渠道充值成功率_底稿'!$A:$A,$A21,'渠道充值成功率_底稿'!$B:$B,D$1) -> 427 | E21: =SUMIFS('渠道充值成功率_底稿'!$F:$F,'渠道充值成功率_底稿'!$A:$A,$A21,'渠道充值成功率_底稿'!$B:$B,E$1) -> 7 | F21: =SUMIFS('渠道充值成功率_底稿'!$F:$F,'渠道充值成功率_底稿'!$A:$A,$A21,'渠道充值成功率_底稿'!$B:$B,F$1) -> 19 | G21: =SUMIFS('渠道充值成功率_底稿'!$F:$F,'渠道充值成功率_底稿'!$A:$A,$A21,'渠道充值成功率_底稿'!$B:$B,G$1) -> 49 | H21: =SUMIFS('渠道充值成功率_底稿'!$F:$F,'渠道充值成功率_底稿'!$A:$A,$A21,'渠道充值成功率_底稿'!$B:$B,H$1) -> 0 | I21: =SUMIFS('渠道充值成功率_底稿'!$F:$F,'渠道充值成功率_底稿'!$A:$A,$A21,'渠道充值成功率_底稿'!$B:$B,I$1) -> 0 | J21: =SUMIFS('渠道充值成功率_底稿'!$F:$F,'渠道充值成功率_底稿'!$A:$A,$A21,'渠道充值成功率_底稿'!$B:$B,J$1) -> 0 | K21: =SUMIFS('渠道充值成功率_底稿'!$F:$F,'渠道充值成功率_底稿'!$A:$A,$A21,'渠道充值成功率_底稿'!$B:$B,K$1) -> 2 | L21: =SUMIFS('渠道充值成功率_底稿'!$F:$F,'渠道充值成功率_底稿'!$A:$A,$A21,'渠道充值成功率_底稿'!$B:$B,L$1) -> 0
A22: =B20 -> 46085 | C22: 笔数成功率 | D22: =IFERROR(ROUND(D21/D20,6),"0") -> 0.862626 | E22: =IFERROR(ROUND(E21/E20,6),"0") -> 0.466667 | F22: =IFERROR(ROUND(F21/F20,6),"0") -> 0.678571 | G22: =IFERROR(ROUND(G21/G20,6),"0") -> 0.907407 | H22: =IFERROR(ROUND(H21/H20,6),"0") -> 0 | I22: =IFERROR(ROUND(I21/I20,6),"0") -> 0 | J22: =IFERROR(ROUND(J21/J20,6),"0") -> 0 | K22: =IFERROR(ROUND(K21/K20,6),"0") -> 1 | L22: =IFERROR(ROUND(L21/L20,6),"0") -> 0
A23: =B20 -> 46085 | C23: 申请金额 | D23: =SUMIFS('渠道充值成功率_底稿'!$D:$D,'渠道充值成功率_底稿'!$A:$A,$A24,'渠道充值成功率_底稿'!$B:$B,D$1) -> 75867 | E23: =SUMIFS('渠道充值成功率_底稿'!$D:$D,'渠道充值成功率_底稿'!$A:$A,$A23,'渠道充值成功率_底稿'!$B:$B,E$1) -> 3270 | F23: =SUMIFS('渠道充值成功率_底稿'!$D:$D,'渠道充值成功率_底稿'!$A:$A,$A23,'渠道充值成功率_底稿'!$B:$B,F$1) -> 4140 | G23: =SUMIFS('渠道充值成功率_底稿'!$D:$D,'渠道充值成功率_底稿'!$A:$A,$A23,'渠道充值成功率_底稿'!$B:$B,G$1) -> 12150 | H23: =SUMIFS('渠道充值成功率_底稿'!$D:$D,'渠道充值成功率_底稿'!$A:$A,$A23,'渠道充值成功率_底稿'!$B:$B,H$1) -> 0 | I23: =SUMIFS('渠道充值成功率_底稿'!$D:$D,'渠道充值成功率_底稿'!$A:$A,$A23,'渠道充值成功率_底稿'!$B:$B,I$1) -> 0 | J23: =SUMIFS('渠道充值成功率_底稿'!$D:$D,'渠道充值成功率_底稿'!$A:$A,$A23,'渠道充值成功率_底稿'!$B:$B,J$1) -> 0 | K23: =SUMIFS('渠道充值成功率_底稿'!$D:$D,'渠道充值成功率_底稿'!$A:$A,$A23,'渠道充值成功率_底稿'!$B:$B,K$1) -> 330 | L23: =SUMIFS('渠道充值成功率_底稿'!$D:$D,'渠道充值成功率_底稿'!$A:$A,$A23,'渠道充值成功率_底稿'!$B:$B,L$1) -> 0
A24: =B20 -> 46085 | C24: 到账金额 | D24: =SUMIFS('渠道充值成功率_底稿'!$G:$G,'渠道充值成功率_底稿'!$A:$A,$A25,'渠道充值成功率_底稿'!$B:$B,D$1) -> 68188 | E24: =SUMIFS('渠道充值成功率_底稿'!$G:$G,'渠道充值成功率_底稿'!$A:$A,$A24,'渠道充值成功率_底稿'!$B:$B,E$1) -> 1570 | F24: =SUMIFS('渠道充值成功率_底稿'!$G:$G,'渠道充值成功率_底稿'!$A:$A,$A24,'渠道充值成功率_底稿'!$B:$B,F$1) -> 2440 | G24: =SUMIFS('渠道充值成功率_底稿'!$G:$G,'渠道充值成功率_底稿'!$A:$A,$A24,'渠道充值成功率_底稿'!$B:$B,G$1) -> 10700 | H24: =SUMIFS('渠道充值成功率_底稿'!$G:$G,'渠道充值成功率_底稿'!$A:$A,$A24,'渠道充值成功率_底稿'!$B:$B,H$1) -> 0 | I24: =SUMIFS('渠道充值成功率_底稿'!$G:$G,'渠道充值成功率_底稿'!$A:$A,$A24,'渠道充值成功率_底稿'!$B:$B,I$1) -> 0 | J24: =SUMIFS('渠道充值成功率_底稿'!$G:$G,'渠道充值成功率_底稿'!$A:$A,$A24,'渠道充值成功率_底稿'!$B:$B,J$1) -> 0 | K24: =SUMIFS('渠道充值成功率_底稿'!$G:$G,'渠道充值成功率_底稿'!$A:$A,$A24,'渠道充值成功率_底稿'!$B:$B,K$1) -> 330 | L24: =SUMIFS('渠道充值成功率_底稿'!$G:$G,'渠道充值成功率_底稿'!$A:$A,$A24,'渠道充值成功率_底稿'!$B:$B,L$1) -> 0
A25: =B20 -> 46085 | C25: 金额成功率 | D25: =IFERROR(ROUND(D24/D23,6),"0") -> 0.898783 | E25: =IFERROR(ROUND(E24/E23,6),"0") -> 0.480122 | F25: =IFERROR(ROUND(F24/F23,6),"0") -> 0.589372 | G25: =IFERROR(ROUND(G24/G23,6),"0") -> 0.880658 | H25: =IFERROR(ROUND(H24/H23,6),"0") -> 0 | I25: =IFERROR(ROUND(I24/I23,6),"0") -> 0 | J25: =IFERROR(ROUND(J24/J23,6),"0") -> 0 | K25: =IFERROR(ROUND(K24/K23,6),"0") -> 1 | L25: =IFERROR(ROUND(L24/L23,6),"0") -> 0
A26: =B26 -> 46086 | B26: =B20+1 -> 46086 | C26: 申请笔数 | D26: =SUMIFS('渠道充值成功率_底稿'!$C:$C,'渠道充值成功率_底稿'!$A:$A,$A26,'渠道充值成功率_底稿'!$B:$B,D$1) -> 746 | E26: =SUMIFS('渠道充值成功率_底稿'!$C:$C,'渠道充值成功率_底稿'!$A:$A,$A26,'渠道充值成功率_底稿'!$B:$B,E$1) -> 25 | F26: =SUMIFS('渠道充值成功率_底稿'!$C:$C,'渠道充值成功率_底稿'!$A:$A,$A26,'渠道充值成功率_底稿'!$B:$B,F$1) -> 66 | G26: =SUMIFS('渠道充值成功率_底稿'!$C:$C,'渠道充值成功率_底稿'!$A:$A,$A26,'渠道充值成功率_底稿'!$B:$B,G$1) -> 80 | H26: =SUMIFS('渠道充值成功率_底稿'!$C:$C,'渠道充值成功率_底稿'!$A:$A,$A26,'渠道充值成功率_底稿'!$B:$B,H$1) -> 0 | I26: =SUMIFS('渠道充值成功率_底稿'!$C:$C,'渠道充值成功率_底稿'!$A:$A,$A26,'渠道充值成功率_底稿'!$B:$B,I$1) -> 0 | J26: =SUMIFS('渠道充值成功率_底稿'!$C:$C,'渠道充值成功率_底稿'!$A:$A,$A26,'渠道充值成功率_底稿'!$B:$B,J$1) -> 0 | K26: =SUMIFS('渠道充值成功率_底稿'!$C:$C,'渠道充值成功率_底稿'!$A:$A,$A26,'渠道充值成功率_底稿'!$B:$B,K$1) -> 21 | L26: =SUMIFS('渠道充值成功率_底稿'!$C:$C,'渠道充值成功率_底稿'!$A:$A,$A26,'渠道充值成功率_底稿'!$B:$B,L$1) -> 0
A27: =B26 -> 46086 | C27: 到账笔数 | D27: =SUMIFS('渠道充值成功率_底稿'!$F:$F,'渠道充值成功率_底稿'!$A:$A,$A27,'渠道充值成功率_底稿'!$B:$B,D$1) -> 494 | E27: =SUMIFS('渠道充值成功率_底稿'!$F:$F,'渠道充值成功率_底稿'!$A:$A,$A27,'渠道充值成功率_底稿'!$B:$B,E$1) -> 24 | F27: =SUMIFS('渠道充值成功率_底稿'!$F:$F,'渠道充值成功率_底稿'!$A:$A,$A27,'渠道充值成功率_底稿'!$B:$B,F$1) -> 30 | G27: =SUMIFS('渠道充值成功率_底稿'!$F:$F,'渠道充值成功率_底稿'!$A:$A,$A27,'渠道充值成功率_底稿'!$B:$B,G$1) -> 66 | H27: =SUMIFS('渠道充值成功率_底稿'!$F:$F,'渠道充值成功率_底稿'!$A:$A,$A27,'渠道充值成功率_底稿'!$B:$B,H$1) -> 0 | I27: =SUMIFS('渠道充值成功率_底稿'!$F:$F,'渠道充值成功率_底稿'!$A:$A,$A27,'渠道充值成功率_底稿'!$B:$B,I$1) -> 0 | J27: =SUMIFS('渠道充值成功率_底稿'!$F:$F,'渠道充值成功率_底稿'!$A:$A,$A27,'渠道充值成功率_底稿'!$B:$B,J$1) -> 0 | K27: =SUMIFS('渠道充值成功率_底稿'!$F:$F,'渠道充值成功率_底稿'!$A:$A,$A27,'渠道充值成功率_底稿'!$B:$B,K$1) -> 15 | L27: =SUMIFS('渠道充值成功率_底稿'!$F:$F,'渠道充值成功率_底稿'!$A:$A,$A27,'渠道充值成功率_底稿'!$B:$B,L$1) -> 0
A28: =B26 -> 46086 | C28: 笔数成功率 | D28: =IFERROR(ROUND(D27/D26,6),"0") -> 0.662198 | E28: =IFERROR(ROUND(E27/E26,6),"0") -> 0.96 | F28: =IFERROR(ROUND(F27/F26,6),"0") -> 0.454545 | G28: =IFERROR(ROUND(G27/G26,6),"0") -> 0.825 | H28: =IFERROR(ROUND(H27/H26,6),"0") -> 0 | I28: =IFERROR(ROUND(I27/I26,6),"0") -> 0 | J28: =IFERROR(ROUND(J27/J26,6),"0") -> 0 | K28: =IFERROR(ROUND(K27/K26,6),"0") -> 0.714286 | L28: =IFERROR(ROUND(L27/L26,6),"0") -> 0
A29: =B26 -> 46086 | C29: 申请金额 | D29: =SUMIFS('渠道充值成功率_底稿'!$D:$D,'渠道充值成功率_底稿'!$A:$A,$A30,'渠道充值成功率_底稿'!$B:$B,D$1) -> 129434 | E29: =SUMIFS('渠道充值成功率_底稿'!$D:$D,'渠道充值成功率_底稿'!$A:$A,$A29,'渠道充值成功率_底稿'!$B:$B,E$1) -> 4680 | F29: =SUMIFS('渠道充值成功率_底稿'!$D:$D,'渠道充值成功率_底稿'!$A:$A,$A29,'渠道充值成功率_底稿'!$B:$B,F$1) -> 10670 | G29: =SUMIFS('渠道充值成功率_底稿'!$D:$D,'渠道充值成功率_底稿'!$A:$A,$A29,'渠道充值成功率_底稿'!$B:$B,G$1) -> 28649 | H29: =SUMIFS('渠道充值成功率_底稿'!$D:$D,'渠道充值成功率_底稿'!$A:$A,$A29,'渠道充值成功率_底稿'!$B:$B,H$1) -> 0 | I29: =SUMIFS('渠道充值成功率_底稿'!$D:$D,'渠道充值成功率_底稿'!$A:$A,$A29,'渠道充值成功率_底稿'!$B:$B,I$1) -> 0 | J29: =SUMIFS('渠道充值成功率_底稿'!$D:$D,'渠道充值成功率_底稿'!$A:$A,$A29,'渠道充值成功率_底稿'!$B:$B,J$1) -> 0 | K29: =SUMIFS('渠道充值成功率_底稿'!$D:$D,'渠道充值成功率_底稿'!$A:$A,$A29,'渠道充值成功率_底稿'!$B:$B,K$1) -> 4550 | L29: =SUMIFS('渠道充值成功率_底稿'!$D:$D,'渠道充值成功率_底稿'!$A:$A,$A29,'渠道充值成功率_底稿'!$B:$B,L$1) -> 0
A30: =B26 -> 46086 | C30: 到账金额 | D30: =SUMIFS('渠道充值成功率_底稿'!$G:$G,'渠道充值成功率_底稿'!$A:$A,$A31,'渠道充值成功率_底稿'!$B:$B,D$1) -> 89429 | E30: =SUMIFS('渠道充值成功率_底稿'!$G:$G,'渠道充值成功率_底稿'!$A:$A,$A30,'渠道充值成功率_底稿'!$B:$B,E$1) -> 4480 | F30: =SUMIFS('渠道充值成功率_底稿'!$G:$G,'渠道充值成功率_底稿'!$A:$A,$A30,'渠道充值成功率_底稿'!$B:$B,F$1) -> 4183 | G30: =SUMIFS('渠道充值成功率_底稿'!$G:$G,'渠道充值成功率_底稿'!$A:$A,$A30,'渠道充值成功率_底稿'!$B:$B,G$1) -> 22356 | H30: =SUMIFS('渠道充值成功率_底稿'!$G:$G,'渠道充值成功率_底稿'!$A:$A,$A30,'渠道充值成功率_底稿'!$B:$B,H$1) -> 0 | I30: =SUMIFS('渠道充值成功率_底稿'!$G:$G,'渠道充值成功率_底稿'!$A:$A,$A30,'渠道充值成功率_底稿'!$B:$B,I$1) -> 0 | J30: =SUMIFS('渠道充值成功率_底稿'!$G:$G,'渠道充值成功率_底稿'!$A:$A,$A30,'渠道充值成功率_底稿'!$B:$B,J$1) -> 0 | K30: =SUMIFS('渠道充值成功率_底稿'!$G:$G,'渠道充值成功率_底稿'!$A:$A,$A30,'渠道充值成功率_底稿'!$B:$B,K$1) -> 2250 | L30: =SUMIFS('渠道充值成功率_底稿'!$G:$G,'渠道充值成功率_底稿'!$A:$A,$A30,'渠道充值成功率_底稿'!$B:$B,L$1) -> 0
A31: =B26 -> 46086 | C31: 金额成功率 | D31: =IFERROR(ROUND(D30/D29,6),"0") -> 0.690924 | E31: =IFERROR(ROUND(E30/E29,6),"0") -> 0.957265 | F31: =IFERROR(ROUND(F30/F29,6),"0") -> 0.392034 | G31: =IFERROR(ROUND(G30/G29,6),"0") -> 0.780341 | H31: =IFERROR(ROUND(H30/H29,6),"0") -> 0 | I31: =IFERROR(ROUND(I30/I29,6),"0") -> 0 | J31: =IFERROR(ROUND(J30/J29,6),"0") -> 0 | K31: =IFERROR(ROUND(K30/K29,6),"0") -> 0.494505 | L31: =IFERROR(ROUND(L30/L29,6),"0") -> 0
A32: =B32 -> 46087 | B32: =B26+1 -> 46087 | C32: 申请笔数 | D32: =SUMIFS('渠道充值成功率_底稿'!$C:$C,'渠道充值成功率_底稿'!$A:$A,$A32,'渠道充值成功率_底稿'!$B:$B,D$1) -> 731 | E32: =SUMIFS('渠道充值成功率_底稿'!$C:$C,'渠道充值成功率_底稿'!$A:$A,$A32,'渠道充值成功率_底稿'!$B:$B,E$1) -> 36 | F32: =SUMIFS('渠道充值成功率_底稿'!$C:$C,'渠道充值成功率_底稿'!$A:$A,$A32,'渠道充值成功率_底稿'!$B:$B,F$1) -> 60 | G32: =SUMIFS('渠道充值成功率_底稿'!$C:$C,'渠道充值成功率_底稿'!$A:$A,$A32,'渠道充值成功率_底稿'!$B:$B,G$1) -> 90 | H32: =SUMIFS('渠道充值成功率_底稿'!$C:$C,'渠道充值成功率_底稿'!$A:$A,$A32,'渠道充值成功率_底稿'!$B:$B,H$1) -> 0 | I32: =SUMIFS('渠道充值成功率_底稿'!$C:$C,'渠道充值成功率_底稿'!$A:$A,$A32,'渠道充值成功率_底稿'!$B:$B,I$1) -> 0 | J32: =SUMIFS('渠道充值成功率_底稿'!$C:$C,'渠道充值成功率_底稿'!$A:$A,$A32,'渠道充值成功率_底稿'!$B:$B,J$1) -> 0 | K32: =SUMIFS('渠道充值成功率_底稿'!$C:$C,'渠道充值成功率_底稿'!$A:$A,$A32,'渠道充值成功率_底稿'!$B:$B,K$1) -> 8 | L32: =SUMIFS('渠道充值成功率_底稿'!$C:$C,'渠道充值成功率_底稿'!$A:$A,$A32,'渠道充值成功率_底稿'!$B:$B,L$1) -> 0
A33: =B32 -> 46087 | C33: 到账笔数 | D33: =SUMIFS('渠道充值成功率_底稿'!$F:$F,'渠道充值成功率_底稿'!$A:$A,$A33,'渠道充值成功率_底稿'!$B:$B,D$1) -> 400 | E33: =SUMIFS('渠道充值成功率_底稿'!$F:$F,'渠道充值成功率_底稿'!$A:$A,$A33,'渠道充值成功率_底稿'!$B:$B,E$1) -> 29 | F33: =SUMIFS('渠道充值成功率_底稿'!$F:$F,'渠道充值成功率_底稿'!$A:$A,$A33,'渠道充值成功率_底稿'!$B:$B,F$1) -> 26 | G33: =SUMIFS('渠道充值成功率_底稿'!$F:$F,'渠道充值成功率_底稿'!$A:$A,$A33,'渠道充值成功率_底稿'!$B:$B,G$1) -> 69 | H33: =SUMIFS('渠道充值成功率_底稿'!$F:$F,'渠道充值成功率_底稿'!$A:$A,$A33,'渠道充值成功率_底稿'!$B:$B,H$1) -> 0 | I33: =SUMIFS('渠道充值成功率_底稿'!$F:$F,'渠道充值成功率_底稿'!$A:$A,$A33,'渠道充值成功率_底稿'!$B:$B,I$1) -> 0 | J33: =SUMIFS('渠道充值成功率_底稿'!$F:$F,'渠道充值成功率_底稿'!$A:$A,$A33,'渠道充值成功率_底稿'!$B:$B,J$1) -> 0 | K33: =SUMIFS('渠道充值成功率_底稿'!$F:$F,'渠道充值成功率_底稿'!$A:$A,$A33,'渠道充值成功率_底稿'!$B:$B,K$1) -> 7 | L33: =SUMIFS('渠道充值成功率_底稿'!$F:$F,'渠道充值成功率_底稿'!$A:$A,$A33,'渠道充值成功率_底稿'!$B:$B,L$1) -> 0
A34: =B32 -> 46087 | C34: 笔数成功率 | D34: =IFERROR(ROUND(D33/D32,6),"0") -> 0.547196 | E34: =IFERROR(ROUND(E33/E32,6),"0") -> 0.805556 | F34: =IFERROR(ROUND(F33/F32,6),"0") -> 0.433333 | G34: =IFERROR(ROUND(G33/G32,6),"0") -> 0.766667 | H34: =IFERROR(ROUND(H33/H32,6),"0") -> 0 | I34: =IFERROR(ROUND(I33/I32,6),"0") -> 0 | J34: =IFERROR(ROUND(J33/J32,6),"0") -> 0 | K34: =IFERROR(ROUND(K33/K32,6),"0") -> 0.875 | L34: =IFERROR(ROUND(L33/L32,6),"0") -> 0
A35: =B32 -> 46087 | C35: 申请金额 | D35: =SUMIFS('渠道充值成功率_底稿'!$D:$D,'渠道充值成功率_底稿'!$A:$A,$A36,'渠道充值成功率_底稿'!$B:$B,D$1) -> 123829 | E35: =SUMIFS('渠道充值成功率_底稿'!$D:$D,'渠道充值成功率_底稿'!$A:$A,$A35,'渠道充值成功率_底稿'!$B:$B,E$1) -> 9587 | F35: =SUMIFS('渠道充值成功率_底稿'!$D:$D,'渠道充值成功率_底稿'!$A:$A,$A35,'渠道充值成功率_底稿'!$B:$B,F$1) -> 13060 | G35: =SUMIFS('渠道充值成功率_底稿'!$D:$D,'渠道充值成功率_底稿'!$A:$A,$A35,'渠道充值成功率_底稿'!$B:$B,G$1) -> 9860 | H35: =SUMIFS('渠道充值成功率_底稿'!$D:$D,'渠道充值成功率_底稿'!$A:$A,$A35,'渠道充值成功率_底稿'!$B:$B,H$1) -> 0 | I35: =SUMIFS('渠道充值成功率_底稿'!$D:$D,'渠道充值成功率_底稿'!$A:$A,$A35,'渠道充值成功率_底稿'!$B:$B,I$1) -> 0 | J35: =SUMIFS('渠道充值成功率_底稿'!$D:$D,'渠道充值成功率_底稿'!$A:$A,$A35,'渠道充值成功率_底稿'!$B:$B,J$1) -> 0 | K35: =SUMIFS('渠道充值成功率_底稿'!$D:$D,'渠道充值成功率_底稿'!$A:$A,$A35,'渠道充值成功率_底稿'!$B:$B,K$1) -> 2020 | L35: =SUMIFS('渠道充值成功率_底稿'!$D:$D,'渠道充值成功率_底稿'!$A:$A,$A35,'渠道充值成功率_底稿'!$B:$B,L$1) -> 0
A36: =B32 -> 46087 | C36: 到账金额 | D36: =SUMIFS('渠道充值成功率_底稿'!$G:$G,'渠道充值成功率_底稿'!$A:$A,$A37,'渠道充值成功率_底稿'!$B:$B,D$1) -> 62040 | E36: =SUMIFS('渠道充值成功率_底稿'!$G:$G,'渠道充值成功率_底稿'!$A:$A,$A36,'渠道充值成功率_底稿'!$B:$B,E$1) -> 6087 | F36: =SUMIFS('渠道充值成功率_底稿'!$G:$G,'渠道充值成功率_底稿'!$A:$A,$A36,'渠道充值成功率_底稿'!$B:$B,F$1) -> 5460 | G36: =SUMIFS('渠道充值成功率_底稿'!$G:$G,'渠道充值成功率_底稿'!$A:$A,$A36,'渠道充值成功率_底稿'!$B:$B,G$1) -> 7338 | H36: =SUMIFS('渠道充值成功率_底稿'!$G:$G,'渠道充值成功率_底稿'!$A:$A,$A36,'渠道充值成功率_底稿'!$B:$B,H$1) -> 0 | I36: =SUMIFS('渠道充值成功率_底稿'!$G:$G,'渠道充值成功率_底稿'!$A:$A,$A36,'渠道充值成功率_底稿'!$B:$B,I$1) -> 0 | J36: =SUMIFS('渠道充值成功率_底稿'!$G:$G,'渠道充值成功率_底稿'!$A:$A,$A36,'渠道充值成功率_底稿'!$B:$B,J$1) -> 0 | K36: =SUMIFS('渠道充值成功率_底稿'!$G:$G,'渠道充值成功率_底稿'!$A:$A,$A36,'渠道充值成功率_底稿'!$B:$B,K$1) -> 1520 | L36: =SUMIFS('渠道充值成功率_底稿'!$G:$G,'渠道充值成功率_底稿'!$A:$A,$A36,'渠道充值成功率_底稿'!$B:$B,L$1) -> 0
A37: =B32 -> 46087 | C37: 金额成功率 | D37: =IFERROR(ROUND(D36/D35,6),"0") -> 0.501013 | E37: =IFERROR(ROUND(E36/E35,6),"0") -> 0.634922 | F37: =IFERROR(ROUND(F36/F35,6),"0") -> 0.41807 | G37: =IFERROR(ROUND(G36/G35,6),"0") -> 0.744219 | H37: =IFERROR(ROUND(H36/H35,6),"0") -> 0 | I37: =IFERROR(ROUND(I36/I35,6),"0") -> 0 | J37: =IFERROR(ROUND(J36/J35,6),"0") -> 0 | K37: =IFERROR(ROUND(K36/K35,6),"0") -> 0.752475 | L37: =IFERROR(ROUND(L36/L35,6),"0") -> 0
A38: =B38 -> 46088 | B38: =B32+1 -> 46088 | C38: 申请笔数 | D38: =SUMIFS('渠道充值成功率_底稿'!$C:$C,'渠道充值成功率_底稿'!$A:$A,$A38,'渠道充值成功率_底稿'!$B:$B,D$1) -> 465 | E38: =SUMIFS('渠道充值成功率_底稿'!$C:$C,'渠道充值成功率_底稿'!$A:$A,$A38,'渠道充值成功率_底稿'!$B:$B,E$1) -> 11 | F38: =SUMIFS('渠道充值成功率_底稿'!$C:$C,'渠道充值成功率_底稿'!$A:$A,$A38,'渠道充值成功率_底稿'!$B:$B,F$1) -> 34 | G38: =SUMIFS('渠道充值成功率_底稿'!$C:$C,'渠道充值成功率_底稿'!$A:$A,$A38,'渠道充值成功率_底稿'!$B:$B,G$1) -> 43 | H38: =SUMIFS('渠道充值成功率_底稿'!$C:$C,'渠道充值成功率_底稿'!$A:$A,$A38,'渠道充值成功率_底稿'!$B:$B,H$1) -> 0 | I38: =SUMIFS('渠道充值成功率_底稿'!$C:$C,'渠道充值成功率_底稿'!$A:$A,$A38,'渠道充值成功率_底稿'!$B:$B,I$1) -> 0 | J38: =SUMIFS('渠道充值成功率_底稿'!$C:$C,'渠道充值成功率_底稿'!$A:$A,$A38,'渠道充值成功率_底稿'!$B:$B,J$1) -> 0 | K38: =SUMIFS('渠道充值成功率_底稿'!$C:$C,'渠道充值成功率_底稿'!$A:$A,$A38,'渠道充值成功率_底稿'!$B:$B,K$1) -> 5 | L38: =SUMIFS('渠道充值成功率_底稿'!$C:$C,'渠道充值成功率_底稿'!$A:$A,$A38,'渠道充值成功率_底稿'!$B:$B,L$1) -> 0
A39: =B38 -> 46088 | C39: 到账笔数 | D39: =SUMIFS('渠道充值成功率_底稿'!$F:$F,'渠道充值成功率_底稿'!$A:$A,$A39,'渠道充值成功率_底稿'!$B:$B,D$1) -> 388 | E39: =SUMIFS('渠道充值成功率_底稿'!$F:$F,'渠道充值成功率_底稿'!$A:$A,$A39,'渠道充值成功率_底稿'!$B:$B,E$1) -> 10 | F39: =SUMIFS('渠道充值成功率_底稿'!$F:$F,'渠道充值成功率_底稿'!$A:$A,$A39,'渠道充值成功率_底稿'!$B:$B,F$1) -> 21 | G39: =SUMIFS('渠道充值成功率_底稿'!$F:$F,'渠道充值成功率_底稿'!$A:$A,$A39,'渠道充值成功率_底稿'!$B:$B,G$1) -> 38 | H39: =SUMIFS('渠道充值成功率_底稿'!$F:$F,'渠道充值成功率_底稿'!$A:$A,$A39,'渠道充值成功率_底稿'!$B:$B,H$1) -> 0 | I39: =SUMIFS('渠道充值成功率_底稿'!$F:$F,'渠道充值成功率_底稿'!$A:$A,$A39,'渠道充值成功率_底稿'!$B:$B,I$1) -> 0 | J39: =SUMIFS('渠道充值成功率_底稿'!$F:$F,'渠道充值成功率_底稿'!$A:$A,$A39,'渠道充值成功率_底稿'!$B:$B,J$1) -> 0 | K39: =SUMIFS('渠道充值成功率_底稿'!$F:$F,'渠道充值成功率_底稿'!$A:$A,$A39,'渠道充值成功率_底稿'!$B:$B,K$1) -> 3 | L39: =SUMIFS('渠道充值成功率_底稿'!$F:$F,'渠道充值成功率_底稿'!$A:$A,$A39,'渠道充值成功率_底稿'!$B:$B,L$1) -> 0
A40: =B38 -> 46088 | C40: 笔数成功率 | D40: =IFERROR(ROUND(D39/D38,6),"0") -> 0.834409 | E40: =IFERROR(ROUND(E39/E38,6),"0") -> 0.909091 | F40: =IFERROR(ROUND(F39/F38,6),"0") -> 0.617647 | G40: =IFERROR(ROUND(G39/G38,6),"0") -> 0.883721 | H40: =IFERROR(ROUND(H39/H38,6),"0") -> 0 | I40: =IFERROR(ROUND(I39/I38,6),"0") -> 0 | J40: =IFERROR(ROUND(J39/J38,6),"0") -> 0 | K40: =IFERROR(ROUND(K39/K38,6),"0") -> 0.6 | L40: =IFERROR(ROUND(L39/L38,6),"0") -> 0
A41: =B38 -> 46088 | C41: 申请金额 | D41: =SUMIFS('渠道充值成功率_底稿'!$D:$D,'渠道充值成功率_底稿'!$A:$A,$A42,'渠道充值成功率_底稿'!$B:$B,D$1) -> 80552 | E41: =SUMIFS('渠道充值成功率_底稿'!$D:$D,'渠道充值成功率_底稿'!$A:$A,$A41,'渠道充值成功率_底稿'!$B:$B,E$1) -> 2150 | F41: =SUMIFS('渠道充值成功率_底稿'!$D:$D,'渠道充值成功率_底稿'!$A:$A,$A41,'渠道充值成功率_底稿'!$B:$B,F$1) -> 5543 | G41: =SUMIFS('渠道充值成功率_底稿'!$D:$D,'渠道充值成功率_底稿'!$A:$A,$A41,'渠道充值成功率_底稿'!$B:$B,G$1) -> 4750 | H41: =SUMIFS('渠道充值成功率_底稿'!$D:$D,'渠道充值成功率_底稿'!$A:$A,$A41,'渠道充值成功率_底稿'!$B:$B,H$1) -> 0 | I41: =SUMIFS('渠道充值成功率_底稿'!$D:$D,'渠道充值成功率_底稿'!$A:$A,$A41,'渠道充值成功率_底稿'!$B:$B,I$1) -> 0 | J41: =SUMIFS('渠道充值成功率_底稿'!$D:$D,'渠道充值成功率_底稿'!$A:$A,$A41,'渠道充值成功率_底稿'!$B:$B,J$1) -> 0 | K41: =SUMIFS('渠道充值成功率_底稿'!$D:$D,'渠道充值成功率_底稿'!$A:$A,$A41,'渠道充值成功率_底稿'!$B:$B,K$1) -> 921 | L41: =SUMIFS('渠道充值成功率_底稿'!$D:$D,'渠道充值成功率_底稿'!$A:$A,$A41,'渠道充值成功率_底稿'!$B:$B,L$1) -> 0
A42: =B38 -> 46088 | C42: 到账金额 | D42: =SUMIFS('渠道充值成功率_底稿'!$G:$G,'渠道充值成功率_底稿'!$A:$A,$A43,'渠道充值成功率_底稿'!$B:$B,D$1) -> 68301 | E42: =SUMIFS('渠道充值成功率_底稿'!$G:$G,'渠道充值成功率_底稿'!$A:$A,$A42,'渠道充值成功率_底稿'!$B:$B,E$1) -> 2000 | F42: =SUMIFS('渠道充值成功率_底稿'!$G:$G,'渠道充值成功率_底稿'!$A:$A,$A42,'渠道充值成功率_底稿'!$B:$B,F$1) -> 3623 | G42: =SUMIFS('渠道充值成功率_底稿'!$G:$G,'渠道充值成功率_底稿'!$A:$A,$A42,'渠道充值成功率_底稿'!$B:$B,G$1) -> 3829 | H42: =SUMIFS('渠道充值成功率_底稿'!$G:$G,'渠道充值成功率_底稿'!$A:$A,$A42,'渠道充值成功率_底稿'!$B:$B,H$1) -> 0 | I42: =SUMIFS('渠道充值成功率_底稿'!$G:$G,'渠道充值成功率_底稿'!$A:$A,$A42,'渠道充值成功率_底稿'!$B:$B,I$1) -> 0 | J42: =SUMIFS('渠道充值成功率_底稿'!$G:$G,'渠道充值成功率_底稿'!$A:$A,$A42,'渠道充值成功率_底稿'!$B:$B,J$1) -> 0 | K42: =SUMIFS('渠道充值成功率_底稿'!$G:$G,'渠道充值成功率_底稿'!$A:$A,$A42,'渠道充值成功率_底稿'!$B:$B,K$1) -> 500 | L42: =SUMIFS('渠道充值成功率_底稿'!$G:$G,'渠道充值成功率_底稿'!$A:$A,$A42,'渠道充值成功率_底稿'!$B:$B,L$1) -> 0
A43: =B38 -> 46088 | C43: 金额成功率 | D43: =IFERROR(ROUND(D42/D41,6),"0") -> 0.847912 | E43: =IFERROR(ROUND(E42/E41,6),"0") -> 0.930233 | F43: =IFERROR(ROUND(F42/F41,6),"0") -> 0.653617 | G43: =IFERROR(ROUND(G42/G41,6),"0") -> 0.806105 | H43: =IFERROR(ROUND(H42/H41,6),"0") -> 0 | I43: =IFERROR(ROUND(I42/I41,6),"0") -> 0 | J43: =IFERROR(ROUND(J42/J41,6),"0") -> 0 | K43: =IFERROR(ROUND(K42/K41,6),"0") -> 0.542888 | L43: =IFERROR(ROUND(L42/L41,6),"0") -> 0
A44: =B44 -> 46089 | B44: =B38+1 -> 46089 | C44: 申请笔数 | D44: =SUMIFS('渠道充值成功率_底稿'!$C:$C,'渠道充值成功率_底稿'!$A:$A,$A44,'渠道充值成功率_底稿'!$B:$B,D$1) -> 477 | E44: =SUMIFS('渠道充值成功率_底稿'!$C:$C,'渠道充值成功率_底稿'!$A:$A,$A44,'渠道充值成功率_底稿'!$B:$B,E$1) -> 16 | F44: =SUMIFS('渠道充值成功率_底稿'!$C:$C,'渠道充值成功率_底稿'!$A:$A,$A44,'渠道充值成功率_底稿'!$B:$B,F$1) -> 39 | G44: =SUMIFS('渠道充值成功率_底稿'!$C:$C,'渠道充值成功率_底稿'!$A:$A,$A44,'渠道充值成功率_底稿'!$B:$B,G$1) -> 57 | H44: =SUMIFS('渠道充值成功率_底稿'!$C:$C,'渠道充值成功率_底稿'!$A:$A,$A44,'渠道充值成功率_底稿'!$B:$B,H$1) -> 0 | I44: =SUMIFS('渠道充值成功率_底稿'!$C:$C,'渠道充值成功率_底稿'!$A:$A,$A44,'渠道充值成功率_底稿'!$B:$B,I$1) -> 0 | J44: =SUMIFS('渠道充值成功率_底稿'!$C:$C,'渠道充值成功率_底稿'!$A:$A,$A44,'渠道充值成功率_底稿'!$B:$B,J$1) -> 0 | K44: =SUMIFS('渠道充值成功率_底稿'!$C:$C,'渠道充值成功率_底稿'!$A:$A,$A44,'渠道充值成功率_底稿'!$B:$B,K$1) -> 0 | L44: =SUMIFS('渠道充值成功率_底稿'!$C:$C,'渠道充值成功率_底稿'!$A:$A,$A44,'渠道充值成功率_底稿'!$B:$B,L$1) -> 0
A45: =B44 -> 46089 | C45: 到账笔数 | D45: =SUMIFS('渠道充值成功率_底稿'!$F:$F,'渠道充值成功率_底稿'!$A:$A,$A45,'渠道充值成功率_底稿'!$B:$B,D$1) -> 370 | E45: =SUMIFS('渠道充值成功率_底稿'!$F:$F,'渠道充值成功率_底稿'!$A:$A,$A45,'渠道充值成功率_底稿'!$B:$B,E$1) -> 13 | F45: =SUMIFS('渠道充值成功率_底稿'!$F:$F,'渠道充值成功率_底稿'!$A:$A,$A45,'渠道充值成功率_底稿'!$B:$B,F$1) -> 24 | G45: =SUMIFS('渠道充值成功率_底稿'!$F:$F,'渠道充值成功率_底稿'!$A:$A,$A45,'渠道充值成功率_底稿'!$B:$B,G$1) -> 45 | H45: =SUMIFS('渠道充值成功率_底稿'!$F:$F,'渠道充值成功率_底稿'!$A:$A,$A45,'渠道充值成功率_底稿'!$B:$B,H$1) -> 0 | I45: =SUMIFS('渠道充值成功率_底稿'!$F:$F,'渠道充值成功率_底稿'!$A:$A,$A45,'渠道充值成功率_底稿'!$B:$B,I$1) -> 0 | J45: =SUMIFS('渠道充值成功率_底稿'!$F:$F,'渠道充值成功率_底稿'!$A:$A,$A45,'渠道充值成功率_底稿'!$B:$B,J$1) -> 0 | K45: =SUMIFS('渠道充值成功率_底稿'!$F:$F,'渠道充值成功率_底稿'!$A:$A,$A45,'渠道充值成功率_底稿'!$B:$B,K$1) -> 0 | L45: =SUMIFS('渠道充值成功率_底稿'!$F:$F,'渠道充值成功率_底稿'!$A:$A,$A45,'渠道充值成功率_底稿'!$B:$B,L$1) -> 0
A46: =B44 -> 46089 | C46: 笔数成功率 | D46: =IFERROR(ROUND(D45/D44,6),"0") -> 0.775681 | E46: =IFERROR(ROUND(E45/E44,6),"0") -> 0.8125 | F46: =IFERROR(ROUND(F45/F44,6),"0") -> 0.615385 | G46: =IFERROR(ROUND(G45/G44,6),"0") -> 0.789474 | H46: =IFERROR(ROUND(H45/H44,6),"0") -> 0 | I46: =IFERROR(ROUND(I45/I44,6),"0") -> 0 | J46: =IFERROR(ROUND(J45/J44,6),"0") -> 0 | K46: =IFERROR(ROUND(K45/K44,6),"0") -> 0 | L46: =IFERROR(ROUND(L45/L44,6),"0") -> 0
A47: =B44 -> 46089 | C47: 申请金额 | D47: =SUMIFS('渠道充值成功率_底稿'!$D:$D,'渠道充值成功率_底稿'!$A:$A,$A48,'渠道充值成功率_底稿'!$B:$B,D$1) -> 76396 | E47: =SUMIFS('渠道充值成功率_底稿'!$D:$D,'渠道充值成功率_底稿'!$A:$A,$A47,'渠道充值成功率_底稿'!$B:$B,E$1) -> 3452 | F47: =SUMIFS('渠道充值成功率_底稿'!$D:$D,'渠道充值成功率_底稿'!$A:$A,$A47,'渠道充值成功率_底稿'!$B:$B,F$1) -> 6753 | G47: =SUMIFS('渠道充值成功率_底稿'!$D:$D,'渠道充值成功率_底稿'!$A:$A,$A47,'渠道充值成功率_底稿'!$B:$B,G$1) -> 6354 | H47: =SUMIFS('渠道充值成功率_底稿'!$D:$D,'渠道充值成功率_底稿'!$A:$A,$A47,'渠道充值成功率_底稿'!$B:$B,H$1) -> 0 | I47: =SUMIFS('渠道充值成功率_底稿'!$D:$D,'渠道充值成功率_底稿'!$A:$A,$A47,'渠道充值成功率_底稿'!$B:$B,I$1) -> 0 | J47: =SUMIFS('渠道充值成功率_底稿'!$D:$D,'渠道充值成功率_底稿'!$A:$A,$A47,'渠道充值成功率_底稿'!$B:$B,J$1) -> 0 | K47: =SUMIFS('渠道充值成功率_底稿'!$D:$D,'渠道充值成功率_底稿'!$A:$A,$A47,'渠道充值成功率_底稿'!$B:$B,K$1) -> 0 | L47: =SUMIFS('渠道充值成功率_底稿'!$D:$D,'渠道充值成功率_底稿'!$A:$A,$A47,'渠道充值成功率_底稿'!$B:$B,L$1) -> 0
A48: =B44 -> 46089 | C48: 到账金额 | D48: =SUMIFS('渠道充值成功率_底稿'!$G:$G,'渠道充值成功率_底稿'!$A:$A,$A49,'渠道充值成功率_底稿'!$B:$B,D$1) -> 62867 | E48: =SUMIFS('渠道充值成功率_底稿'!$G:$G,'渠道充值成功率_底稿'!$A:$A,$A48,'渠道充值成功率_底稿'!$B:$B,E$1) -> 2752 | F48: =SUMIFS('渠道充值成功率_底稿'!$G:$G,'渠道充值成功率_底稿'!$A:$A,$A48,'渠道充值成功率_底稿'!$B:$B,F$1) -> 4021 | G48: =SUMIFS('渠道充值成功率_底稿'!$G:$G,'渠道充值成功率_底稿'!$A:$A,$A48,'渠道充值成功率_底稿'!$B:$B,G$1) -> 4554 | H48: =SUMIFS('渠道充值成功率_底稿'!$G:$G,'渠道充值成功率_底稿'!$A:$A,$A48,'渠道充值成功率_底稿'!$B:$B,H$1) -> 0 | I48: =SUMIFS('渠道充值成功率_底稿'!$G:$G,'渠道充值成功率_底稿'!$A:$A,$A48,'渠道充值成功率_底稿'!$B:$B,I$1) -> 0 | J48: =SUMIFS('渠道充值成功率_底稿'!$G:$G,'渠道充值成功率_底稿'!$A:$A,$A48,'渠道充值成功率_底稿'!$B:$B,J$1) -> 0 | K48: =SUMIFS('渠道充值成功率_底稿'!$G:$G,'渠道充值成功率_底稿'!$A:$A,$A48,'渠道充值成功率_底稿'!$B:$B,K$1) -> 0 | L48: =SUMIFS('渠道充值成功率_底稿'!$G:$G,'渠道充值成功率_底稿'!$A:$A,$A48,'渠道充值成功率_底稿'!$B:$B,L$1) -> 0
A49: =B44 -> 46089 | C49: 金额成功率 | D49: =IFERROR(ROUND(D48/D47,6),"0") -> 0.82291 | E49: =IFERROR(ROUND(E48/E47,6),"0") -> 0.797219 | F49: =IFERROR(ROUND(F48/F47,6),"0") -> 0.595439 | G49: =IFERROR(ROUND(G48/G47,6),"0") -> 0.716714 | H49: =IFERROR(ROUND(H48/H47,6),"0") -> 0 | I49: =IFERROR(ROUND(I48/I47,6),"0") -> 0 | J49: =IFERROR(ROUND(J48/J47,6),"0") -> 0 | K49: =IFERROR(ROUND(K48/K47,6),"0") -> 0 | L49: =IFERROR(ROUND(L48/L47,6),"0") -> 0
A50: =B50 -> 46090 | B50: =B44+1 -> 46090 | C50: 申请笔数 | D50: =SUMIFS('渠道充值成功率_底稿'!$C:$C,'渠道充值成功率_底稿'!$A:$A,$A50,'渠道充值成功率_底稿'!$B:$B,D$1) -> 293 | E50: =SUMIFS('渠道充值成功率_底稿'!$C:$C,'渠道充值成功率_底稿'!$A:$A,$A50,'渠道充值成功率_底稿'!$B:$B,E$1) -> 4 | F50: =SUMIFS('渠道充值成功率_底稿'!$C:$C,'渠道充值成功率_底稿'!$A:$A,$A50,'渠道充值成功率_底稿'!$B:$B,F$1) -> 16 | G50: =SUMIFS('渠道充值成功率_底稿'!$C:$C,'渠道充值成功率_底稿'!$A:$A,$A50,'渠道充值成功率_底稿'!$B:$B,G$1) -> 53 | H50: =SUMIFS('渠道充值成功率_底稿'!$C:$C,'渠道充值成功率_底稿'!$A:$A,$A50,'渠道充值成功率_底稿'!$B:$B,H$1) -> 0 | I50: =SUMIFS('渠道充值成功率_底稿'!$C:$C,'渠道充值成功率_底稿'!$A:$A,$A50,'渠道充值成功率_底稿'!$B:$B,I$1) -> 0 | J50: =SUMIFS('渠道充值成功率_底稿'!$C:$C,'渠道充值成功率_底稿'!$A:$A,$A50,'渠道充值成功率_底稿'!$B:$B,J$1) -> 0 | K50: =SUMIFS('渠道充值成功率_底稿'!$C:$C,'渠道充值成功率_底稿'!$A:$A,$A50,'渠道充值成功率_底稿'!$B:$B,K$1) -> 4 | L50: =SUMIFS('渠道充值成功率_底稿'!$C:$C,'渠道充值成功率_底稿'!$A:$A,$A50,'渠道充值成功率_底稿'!$B:$B,L$1) -> 0
A51: =B50 -> 46090 | C51: 到账笔数 | D51: =SUMIFS('渠道充值成功率_底稿'!$F:$F,'渠道充值成功率_底稿'!$A:$A,$A51,'渠道充值成功率_底稿'!$B:$B,D$1) -> 235 | E51: =SUMIFS('渠道充值成功率_底稿'!$F:$F,'渠道充值成功率_底稿'!$A:$A,$A51,'渠道充值成功率_底稿'!$B:$B,E$1) -> 4 | F51: =SUMIFS('渠道充值成功率_底稿'!$F:$F,'渠道充值成功率_底稿'!$A:$A,$A51,'渠道充值成功率_底稿'!$B:$B,F$1) -> 10 | G51: =SUMIFS('渠道充值成功率_底稿'!$F:$F,'渠道充值成功率_底稿'!$A:$A,$A51,'渠道充值成功率_底稿'!$B:$B,G$1) -> 48 | H51: =SUMIFS('渠道充值成功率_底稿'!$F:$F,'渠道充值成功率_底稿'!$A:$A,$A51,'渠道充值成功率_底稿'!$B:$B,H$1) -> 0 | I51: =SUMIFS('渠道充值成功率_底稿'!$F:$F,'渠道充值成功率_底稿'!$A:$A,$A51,'渠道充值成功率_底稿'!$B:$B,I$1) -> 0 | J51: =SUMIFS('渠道充值成功率_底稿'!$F:$F,'渠道充值成功率_底稿'!$A:$A,$A51,'渠道充值成功率_底稿'!$B:$B,J$1) -> 0 | K51: =SUMIFS('渠道充值成功率_底稿'!$F:$F,'渠道充值成功率_底稿'!$A:$A,$A51,'渠道充值成功率_底稿'!$B:$B,K$1) -> 4 | L51: =SUMIFS('渠道充值成功率_底稿'!$F:$F,'渠道充值成功率_底稿'!$A:$A,$A51,'渠道充值成功率_底稿'!$B:$B,L$1) -> 0
A52: =B50 -> 46090 | C52: 笔数成功率 | D52: =IFERROR(ROUND(D51/D50,6),"0") -> 0.802048 | E52: =IFERROR(ROUND(E51/E50,6),"0") -> 1 | F52: =IFERROR(ROUND(F51/F50,6),"0") -> 0.625 | G52: =IFERROR(ROUND(G51/G50,6),"0") -> 0.90566 | H52: =IFERROR(ROUND(H51/H50,6),"0") -> 0 | I52: =IFERROR(ROUND(I51/I50,6),"0") -> 0 | J52: =IFERROR(ROUND(J51/J50,6),"0") -> 0 | K52: =IFERROR(ROUND(K51/K50,6),"0") -> 1 | L52: =IFERROR(ROUND(L51/L50,6),"0") -> 0
A53: =B50 -> 46090 | C53: 申请金额 | D53: =SUMIFS('渠道充值成功率_底稿'!$D:$D,'渠道充值成功率_底稿'!$A:$A,$A54,'渠道充值成功率_底稿'!$B:$B,D$1) -> 43671 | E53: =SUMIFS('渠道充值成功率_底稿'!$D:$D,'渠道充值成功率_底稿'!$A:$A,$A53,'渠道充值成功率_底稿'!$B:$B,E$1) -> 600 | F53: =SUMIFS('渠道充值成功率_底稿'!$D:$D,'渠道充值成功率_底稿'!$A:$A,$A53,'渠道充值成功率_底稿'!$B:$B,F$1) -> 1833 | G53: =SUMIFS('渠道充值成功率_底稿'!$D:$D,'渠道充值成功率_底稿'!$A:$A,$A53,'渠道充值成功率_底稿'!$B:$B,G$1) -> 9036 | H53: =SUMIFS('渠道充值成功率_底稿'!$D:$D,'渠道充值成功率_底稿'!$A:$A,$A53,'渠道充值成功率_底稿'!$B:$B,H$1) -> 0 | I53: =SUMIFS('渠道充值成功率_底稿'!$D:$D,'渠道充值成功率_底稿'!$A:$A,$A53,'渠道充值成功率_底稿'!$B:$B,I$1) -> 0 | J53: =SUMIFS('渠道充值成功率_底稿'!$D:$D,'渠道充值成功率_底稿'!$A:$A,$A53,'渠道充值成功率_底稿'!$B:$B,J$1) -> 0 | K53: =SUMIFS('渠道充值成功率_底稿'!$D:$D,'渠道充值成功率_底稿'!$A:$A,$A53,'渠道充值成功率_底稿'!$B:$B,K$1) -> 920 | L53: =SUMIFS('渠道充值成功率_底稿'!$D:$D,'渠道充值成功率_底稿'!$A:$A,$A53,'渠道充值成功率_底稿'!$B:$B,L$1) -> 0
A54: =B50 -> 46090 | C54: 到账金额 | D54: =SUMIFS('渠道充值成功率_底稿'!$G:$G,'渠道充值成功率_底稿'!$A:$A,$A55,'渠道充值成功率_底稿'!$B:$B,D$1) -> 32246 | E54: =SUMIFS('渠道充值成功率_底稿'!$G:$G,'渠道充值成功率_底稿'!$A:$A,$A54,'渠道充值成功率_底稿'!$B:$B,E$1) -> 600 | F54: =SUMIFS('渠道充值成功率_底稿'!$G:$G,'渠道充值成功率_底稿'!$A:$A,$A54,'渠道充值成功率_底稿'!$B:$B,F$1) -> 1224 | G54: =SUMIFS('渠道充值成功率_底稿'!$G:$G,'渠道充值成功率_底稿'!$A:$A,$A54,'渠道充值成功率_底稿'!$B:$B,G$1) -> 8535 | H54: =SUMIFS('渠道充值成功率_底稿'!$G:$G,'渠道充值成功率_底稿'!$A:$A,$A54,'渠道充值成功率_底稿'!$B:$B,H$1) -> 0 | I54: =SUMIFS('渠道充值成功率_底稿'!$G:$G,'渠道充值成功率_底稿'!$A:$A,$A54,'渠道充值成功率_底稿'!$B:$B,I$1) -> 0 | J54: =SUMIFS('渠道充值成功率_底稿'!$G:$G,'渠道充值成功率_底稿'!$A:$A,$A54,'渠道充值成功率_底稿'!$B:$B,J$1) -> 0 | K54: =SUMIFS('渠道充值成功率_底稿'!$G:$G,'渠道充值成功率_底稿'!$A:$A,$A54,'渠道充值成功率_底稿'!$B:$B,K$1) -> 920 | L54: =SUMIFS('渠道充值成功率_底稿'!$G:$G,'渠道充值成功率_底稿'!$A:$A,$A54,'渠道充值成功率_底稿'!$B:$B,L$1) -> 0
A55: =B50 -> 46090 | C55: 金额成功率 | D55: =IFERROR(ROUND(D54/D53,6),"0") -> 0.738385 | E55: =IFERROR(ROUND(E54/E53,6),"0") -> 1 | F55: =IFERROR(ROUND(F54/F53,6),"0") -> 0.667758 | G55: =IFERROR(ROUND(G54/G53,6),"0") -> 0.944555 | H55: =IFERROR(ROUND(H54/H53,6),"0") -> 0 | I55: =IFERROR(ROUND(I54/I53,6),"0") -> 0 | J55: =IFERROR(ROUND(J54/J53,6),"0") -> 0 | K55: =IFERROR(ROUND(K54/K53,6),"0") -> 1 | L55: =IFERROR(ROUND(L54/L53,6),"0") -> 0
A56: =B56 -> 46091 | B56: =B50+1 -> 46091 | C56: 申请笔数 | D56: =SUMIFS('渠道充值成功率_底稿'!$C:$C,'渠道充值成功率_底稿'!$A:$A,$A56,'渠道充值成功率_底稿'!$B:$B,D$1) -> 357 | E56: =SUMIFS('渠道充值成功率_底稿'!$C:$C,'渠道充值成功率_底稿'!$A:$A,$A56,'渠道充值成功率_底稿'!$B:$B,E$1) -> 12 | F56: =SUMIFS('渠道充值成功率_底稿'!$C:$C,'渠道充值成功率_底稿'!$A:$A,$A56,'渠道充值成功率_底稿'!$B:$B,F$1) -> 19 | G56: =SUMIFS('渠道充值成功率_底稿'!$C:$C,'渠道充值成功率_底稿'!$A:$A,$A56,'渠道充值成功率_底稿'!$B:$B,G$1) -> 58 | H56: =SUMIFS('渠道充值成功率_底稿'!$C:$C,'渠道充值成功率_底稿'!$A:$A,$A56,'渠道充值成功率_底稿'!$B:$B,H$1) -> 0 | I56: =SUMIFS('渠道充值成功率_底稿'!$C:$C,'渠道充值成功率_底稿'!$A:$A,$A56,'渠道充值成功率_底稿'!$B:$B,I$1) -> 0 | J56: =SUMIFS('渠道充值成功率_底稿'!$C:$C,'渠道充值成功率_底稿'!$A:$A,$A56,'渠道充值成功率_底稿'!$B:$B,J$1) -> 0 | K56: =SUMIFS('渠道充值成功率_底稿'!$C:$C,'渠道充值成功率_底稿'!$A:$A,$A56,'渠道充值成功率_底稿'!$B:$B,K$1) -> 0 | L56: =SUMIFS('渠道充值成功率_底稿'!$C:$C,'渠道充值成功率_底稿'!$A:$A,$A56,'渠道充值成功率_底稿'!$B:$B,L$1) -> 0
A57: =B56 -> 46091 | C57: 到账笔数 | D57: =SUMIFS('渠道充值成功率_底稿'!$F:$F,'渠道充值成功率_底稿'!$A:$A,$A57,'渠道充值成功率_底稿'!$B:$B,D$1) -> 278 | E57: =SUMIFS('渠道充值成功率_底稿'!$F:$F,'渠道充值成功率_底稿'!$A:$A,$A57,'渠道充值成功率_底稿'!$B:$B,E$1) -> 11 | F57: =SUMIFS('渠道充值成功率_底稿'!$F:$F,'渠道充值成功率_底稿'!$A:$A,$A57,'渠道充值成功率_底稿'!$B:$B,F$1) -> 11 | G57: =SUMIFS('渠道充值成功率_底稿'!$F:$F,'渠道充值成功率_底稿'!$A:$A,$A57,'渠道充值成功率_底稿'!$B:$B,G$1) -> 42 | H57: =SUMIFS('渠道充值成功率_底稿'!$F:$F,'渠道充值成功率_底稿'!$A:$A,$A57,'渠道充值成功率_底稿'!$B:$B,H$1) -> 0 | I57: =SUMIFS('渠道充值成功率_底稿'!$F:$F,'渠道充值成功率_底稿'!$A:$A,$A57,'渠道充值成功率_底稿'!$B:$B,I$1) -> 0 | J57: =SUMIFS('渠道充值成功率_底稿'!$F:$F,'渠道充值成功率_底稿'!$A:$A,$A57,'渠道充值成功率_底稿'!$B:$B,J$1) -> 0 | K57: =SUMIFS('渠道充值成功率_底稿'!$F:$F,'渠道充值成功率_底稿'!$A:$A,$A57,'渠道充值成功率_底稿'!$B:$B,K$1) -> 0 | L57: =SUMIFS('渠道充值成功率_底稿'!$F:$F,'渠道充值成功率_底稿'!$A:$A,$A57,'渠道充值成功率_底稿'!$B:$B,L$1) -> 0
A58: =B56 -> 46091 | C58: 笔数成功率 | D58: =IFERROR(ROUND(D57/D56,6),"0") -> 0.778711 | E58: =IFERROR(ROUND(E57/E56,6),"0") -> 0.916667 | F58: =IFERROR(ROUND(F57/F56,6),"0") -> 0.578947 | G58: =IFERROR(ROUND(G57/G56,6),"0") -> 0.724138 | H58: =IFERROR(ROUND(H57/H56,6),"0") -> 0 | I58: =IFERROR(ROUND(I57/I56,6),"0") -> 0 | J58: =IFERROR(ROUND(J57/J56,6),"0") -> 0 | K58: =IFERROR(ROUND(K57/K56,6),"0") -> 0 | L58: =IFERROR(ROUND(L57/L56,6),"0") -> 0
A59: =B56 -> 46091 | C59: 申请金额 | D59: =SUMIFS('渠道充值成功率_底稿'!$D:$D,'渠道充值成功率_底稿'!$A:$A,$A60,'渠道充值成功率_底稿'!$B:$B,D$1) -> 59453 | E59: =SUMIFS('渠道充值成功率_底稿'!$D:$D,'渠道充值成功率_底稿'!$A:$A,$A59,'渠道充值成功率_底稿'!$B:$B,E$1) -> 4106 | F59: =SUMIFS('渠道充值成功率_底稿'!$D:$D,'渠道充值成功率_底稿'!$A:$A,$A59,'渠道充值成功率_底稿'!$B:$B,F$1) -> 2150 | G59: =SUMIFS('渠道充值成功率_底稿'!$D:$D,'渠道充值成功率_底稿'!$A:$A,$A59,'渠道充值成功率_底稿'!$B:$B,G$1) -> 6569 | H59: =SUMIFS('渠道充值成功率_底稿'!$D:$D,'渠道充值成功率_底稿'!$A:$A,$A59,'渠道充值成功率_底稿'!$B:$B,H$1) -> 0 | I59: =SUMIFS('渠道充值成功率_底稿'!$D:$D,'渠道充值成功率_底稿'!$A:$A,$A59,'渠道充值成功率_底稿'!$B:$B,I$1) -> 0 | J59: =SUMIFS('渠道充值成功率_底稿'!$D:$D,'渠道充值成功率_底稿'!$A:$A,$A59,'渠道充值成功率_底稿'!$B:$B,J$1) -> 0 | K59: =SUMIFS('渠道充值成功率_底稿'!$D:$D,'渠道充值成功率_底稿'!$A:$A,$A59,'渠道充值成功率_底稿'!$B:$B,K$1) -> 0 | L59: =SUMIFS('渠道充值成功率_底稿'!$D:$D,'渠道充值成功率_底稿'!$A:$A,$A59,'渠道充值成功率_底稿'!$B:$B,L$1) -> 0
A60: =B56 -> 46091 | C60: 到账金额 | D60: =SUMIFS('渠道充值成功率_底稿'!$G:$G,'渠道充值成功率_底稿'!$A:$A,$A61,'渠道充值成功率_底稿'!$B:$B,D$1) -> 43783 | E60: =SUMIFS('渠道充值成功率_底稿'!$G:$G,'渠道充值成功率_底稿'!$A:$A,$A60,'渠道充值成功率_底稿'!$B:$B,E$1) -> 4003 | F60: =SUMIFS('渠道充值成功率_底稿'!$G:$G,'渠道充值成功率_底稿'!$A:$A,$A60,'渠道充值成功率_底稿'!$B:$B,F$1) -> 1250 | G60: =SUMIFS('渠道充值成功率_底稿'!$G:$G,'渠道充值成功率_底稿'!$A:$A,$A60,'渠道充值成功率_底稿'!$B:$B,G$1) -> 4709 | H60: =SUMIFS('渠道充值成功率_底稿'!$G:$G,'渠道充值成功率_底稿'!$A:$A,$A60,'渠道充值成功率_底稿'!$B:$B,H$1) -> 0 | I60: =SUMIFS('渠道充值成功率_底稿'!$G:$G,'渠道充值成功率_底稿'!$A:$A,$A60,'渠道充值成功率_底稿'!$B:$B,I$1) -> 0 | J60: =SUMIFS('渠道充值成功率_底稿'!$G:$G,'渠道充值成功率_底稿'!$A:$A,$A60,'渠道充值成功率_底稿'!$B:$B,J$1) -> 0 | K60: =SUMIFS('渠道充值成功率_底稿'!$G:$G,'渠道充值成功率_底稿'!$A:$A,$A60,'渠道充值成功率_底稿'!$B:$B,K$1) -> 0 | L60: =SUMIFS('渠道充值成功率_底稿'!$G:$G,'渠道充值成功率_底稿'!$A:$A,$A60,'渠道充值成功率_底稿'!$B:$B,L$1) -> 0
A61: =B56 -> 46091 | C61: 金额成功率 | D61: =IFERROR(ROUND(D60/D59,6),"0") -> 0.73643 | E61: =IFERROR(ROUND(E60/E59,6),"0") -> 0.974915 | F61: =IFERROR(ROUND(F60/F59,6),"0") -> 0.581395 | G61: =IFERROR(ROUND(G60/G59,6),"0") -> 0.716852 | H61: =IFERROR(ROUND(H60/H59,6),"0") -> 0 | I61: =IFERROR(ROUND(I60/I59,6),"0") -> 0 | J61: =IFERROR(ROUND(J60/J59,6),"0") -> 0 | K61: =IFERROR(ROUND(K60/K59,6),"0") -> 0 | L61: =IFERROR(ROUND(L60/L59,6),"0") -> 0
A62: =B62 -> 46092 | B62: =B56+1 -> 46092 | C62: 申请笔数 | D62: =SUMIFS('渠道充值成功率_底稿'!$C:$C,'渠道充值成功率_底稿'!$A:$A,$A62,'渠道充值成功率_底稿'!$B:$B,D$1) -> 479 | E62: =SUMIFS('渠道充值成功率_底稿'!$C:$C,'渠道充值成功率_底稿'!$A:$A,$A62,'渠道充值成功率_底稿'!$B:$B,E$1) -> 18 | F62: =SUMIFS('渠道充值成功率_底稿'!$C:$C,'渠道充值成功率_底稿'!$A:$A,$A62,'渠道充值成功率_底稿'!$B:$B,F$1) -> 26 | G62: =SUMIFS('渠道充值成功率_底稿'!$C:$C,'渠道充值成功率_底稿'!$A:$A,$A62,'渠道充值成功率_底稿'!$B:$B,G$1) -> 70 | H62: =SUMIFS('渠道充值成功率_底稿'!$C:$C,'渠道充值成功率_底稿'!$A:$A,$A62,'渠道充值成功率_底稿'!$B:$B,H$1) -> 0 | I62: =SUMIFS('渠道充值成功率_底稿'!$C:$C,'渠道充值成功率_底稿'!$A:$A,$A62,'渠道充值成功率_底稿'!$B:$B,I$1) -> 0 | J62: =SUMIFS('渠道充值成功率_底稿'!$C:$C,'渠道充值成功率_底稿'!$A:$A,$A62,'渠道充值成功率_底稿'!$B:$B,J$1) -> 0 | K62: =SUMIFS('渠道充值成功率_底稿'!$C:$C,'渠道充值成功率_底稿'!$A:$A,$A62,'渠道充值成功率_底稿'!$B:$B,K$1) -> 5 | L62: =SUMIFS('渠道充值成功率_底稿'!$C:$C,'渠道充值成功率_底稿'!$A:$A,$A62,'渠道充值成功率_底稿'!$B:$B,L$1) -> 0
A63: =B62 -> 46092 | C63: 到账笔数 | D63: =SUMIFS('渠道充值成功率_底稿'!$F:$F,'渠道充值成功率_底稿'!$A:$A,$A63,'渠道充值成功率_底稿'!$B:$B,D$1) -> 331 | E63: =SUMIFS('渠道充值成功率_底稿'!$F:$F,'渠道充值成功率_底稿'!$A:$A,$A63,'渠道充值成功率_底稿'!$B:$B,E$1) -> 12 | F63: =SUMIFS('渠道充值成功率_底稿'!$F:$F,'渠道充值成功率_底稿'!$A:$A,$A63,'渠道充值成功率_底稿'!$B:$B,F$1) -> 11 | G63: =SUMIFS('渠道充值成功率_底稿'!$F:$F,'渠道充值成功率_底稿'!$A:$A,$A63,'渠道充值成功率_底稿'!$B:$B,G$1) -> 49 | H63: =SUMIFS('渠道充值成功率_底稿'!$F:$F,'渠道充值成功率_底稿'!$A:$A,$A63,'渠道充值成功率_底稿'!$B:$B,H$1) -> 0 | I63: =SUMIFS('渠道充值成功率_底稿'!$F:$F,'渠道充值成功率_底稿'!$A:$A,$A63,'渠道充值成功率_底稿'!$B:$B,I$1) -> 0 | J63: =SUMIFS('渠道充值成功率_底稿'!$F:$F,'渠道充值成功率_底稿'!$A:$A,$A63,'渠道充值成功率_底稿'!$B:$B,J$1) -> 0 | K63: =SUMIFS('渠道充值成功率_底稿'!$F:$F,'渠道充值成功率_底稿'!$A:$A,$A63,'渠道充值成功率_底稿'!$B:$B,K$1) -> 5 | L63: =SUMIFS('渠道充值成功率_底稿'!$F:$F,'渠道充值成功率_底稿'!$A:$A,$A63,'渠道充值成功率_底稿'!$B:$B,L$1) -> 0
A64: =B62 -> 46092 | C64: 笔数成功率 | D64: =IFERROR(ROUND(D63/D62,6),"0") -> 0.691023 | E64: =IFERROR(ROUND(E63/E62,6),"0") -> 0.666667 | F64: =IFERROR(ROUND(F63/F62,6),"0") -> 0.423077 | G64: =IFERROR(ROUND(G63/G62,6),"0") -> 0.7 | H64: =IFERROR(ROUND(H63/H62,6),"0") -> 0 | I64: =IFERROR(ROUND(I63/I62,6),"0") -> 0 | J64: =IFERROR(ROUND(J63/J62,6),"0") -> 0 | K64: =IFERROR(ROUND(K63/K62,6),"0") -> 1 | L64: =IFERROR(ROUND(L63/L62,6),"0") -> 0
A65: =B62 -> 46092 | C65: 申请金额 | D65: =SUMIFS('渠道充值成功率_底稿'!$D:$D,'渠道充值成功率_底稿'!$A:$A,$A66,'渠道充值成功率_底稿'!$B:$B,D$1) -> 63978 | E65: =SUMIFS('渠道充值成功率_底稿'!$D:$D,'渠道充值成功率_底稿'!$A:$A,$A65,'渠道充值成功率_底稿'!$B:$B,E$1) -> 4270 | F65: =SUMIFS('渠道充值成功率_底稿'!$D:$D,'渠道充值成功率_底稿'!$A:$A,$A65,'渠道充值成功率_底稿'!$B:$B,F$1) -> 3306 | G65: =SUMIFS('渠道充值成功率_底稿'!$D:$D,'渠道充值成功率_底稿'!$A:$A,$A65,'渠道充值成功率_底稿'!$B:$B,G$1) -> 10363 | H65: =SUMIFS('渠道充值成功率_底稿'!$D:$D,'渠道充值成功率_底稿'!$A:$A,$A65,'渠道充值成功率_底稿'!$B:$B,H$1) -> 0 | I65: =SUMIFS('渠道充值成功率_底稿'!$D:$D,'渠道充值成功率_底稿'!$A:$A,$A65,'渠道充值成功率_底稿'!$B:$B,I$1) -> 0 | J65: =SUMIFS('渠道充值成功率_底稿'!$D:$D,'渠道充值成功率_底稿'!$A:$A,$A65,'渠道充值成功率_底稿'!$B:$B,J$1) -> 0 | K65: =SUMIFS('渠道充值成功率_底稿'!$D:$D,'渠道充值成功率_底稿'!$A:$A,$A65,'渠道充值成功率_底稿'!$B:$B,K$1) -> 600 | L65: =SUMIFS('渠道充值成功率_底稿'!$D:$D,'渠道充值成功率_底稿'!$A:$A,$A65,'渠道充值成功率_底稿'!$B:$B,L$1) -> 0
A66: =B62 -> 46092 | C66: 到账金额 | D66: =SUMIFS('渠道充值成功率_底稿'!$G:$G,'渠道充值成功率_底稿'!$A:$A,$A67,'渠道充值成功率_底稿'!$B:$B,D$1) -> 43743 | E66: =SUMIFS('渠道充值成功率_底稿'!$G:$G,'渠道充值成功率_底稿'!$A:$A,$A66,'渠道充值成功率_底稿'!$B:$B,E$1) -> 2770 | F66: =SUMIFS('渠道充值成功率_底稿'!$G:$G,'渠道充值成功率_底稿'!$A:$A,$A66,'渠道充值成功率_底稿'!$B:$B,F$1) -> 1151 | G66: =SUMIFS('渠道充值成功率_底稿'!$G:$G,'渠道充值成功率_底稿'!$A:$A,$A66,'渠道充值成功率_底稿'!$B:$B,G$1) -> 5004 | H66: =SUMIFS('渠道充值成功率_底稿'!$G:$G,'渠道充值成功率_底稿'!$A:$A,$A66,'渠道充值成功率_底稿'!$B:$B,H$1) -> 0 | I66: =SUMIFS('渠道充值成功率_底稿'!$G:$G,'渠道充值成功率_底稿'!$A:$A,$A66,'渠道充值成功率_底稿'!$B:$B,I$1) -> 0 | J66: =SUMIFS('渠道充值成功率_底稿'!$G:$G,'渠道充值成功率_底稿'!$A:$A,$A66,'渠道充值成功率_底稿'!$B:$B,J$1) -> 0 | K66: =SUMIFS('渠道充值成功率_底稿'!$G:$G,'渠道充值成功率_底稿'!$A:$A,$A66,'渠道充值成功率_底稿'!$B:$B,K$1) -> 600 | L66: =SUMIFS('渠道充值成功率_底稿'!$G:$G,'渠道充值成功率_底稿'!$A:$A,$A66,'渠道充值成功率_底稿'!$B:$B,L$1) -> 0
A67: =B62 -> 46092 | C67: 金额成功率 | D67: =IFERROR(ROUND(D66/D65,6),"0") -> 0.683719 | E67: =IFERROR(ROUND(E66/E65,6),"0") -> 0.648712 | F67: =IFERROR(ROUND(F66/F65,6),"0") -> 0.348155 | G67: =IFERROR(ROUND(G66/G65,6),"0") -> 0.482872 | H67: =IFERROR(ROUND(H66/H65,6),"0") -> 0 | I67: =IFERROR(ROUND(I66/I65,6),"0") -> 0 | J67: =IFERROR(ROUND(J66/J65,6),"0") -> 0 | K67: =IFERROR(ROUND(K66/K65,6),"0") -> 1 | L67: =IFERROR(ROUND(L66/L65,6),"0") -> 0
A68: =B68 -> 46093 | B68: =B62+1 -> 46093 | C68: 申请笔数 | D68: =SUMIFS('渠道充值成功率_底稿'!$C:$C,'渠道充值成功率_底稿'!$A:$A,$A68,'渠道充值成功率_底稿'!$B:$B,D$1) -> 0 | E68: =SUMIFS('渠道充值成功率_底稿'!$C:$C,'渠道充值成功率_底稿'!$A:$A,$A68,'渠道充值成功率_底稿'!$B:$B,E$1) -> 0 | F68: =SUMIFS('渠道充值成功率_底稿'!$C:$C,'渠道充值成功率_底稿'!$A:$A,$A68,'渠道充值成功率_底稿'!$B:$B,F$1) -> 0 | G68: =SUMIFS('渠道充值成功率_底稿'!$C:$C,'渠道充值成功率_底稿'!$A:$A,$A68,'渠道充值成功率_底稿'!$B:$B,G$1) -> 0 | H68: =SUMIFS('渠道充值成功率_底稿'!$C:$C,'渠道充值成功率_底稿'!$A:$A,$A68,'渠道充值成功率_底稿'!$B:$B,H$1) -> 0 | I68: =SUMIFS('渠道充值成功率_底稿'!$C:$C,'渠道充值成功率_底稿'!$A:$A,$A68,'渠道充值成功率_底稿'!$B:$B,I$1) -> 0 | J68: =SUMIFS('渠道充值成功率_底稿'!$C:$C,'渠道充值成功率_底稿'!$A:$A,$A68,'渠道充值成功率_底稿'!$B:$B,J$1) -> 0 | K68: =SUMIFS('渠道充值成功率_底稿'!$C:$C,'渠道充值成功率_底稿'!$A:$A,$A68,'渠道充值成功率_底稿'!$B:$B,K$1) -> 0 | L68: =SUMIFS('渠道充值成功率_底稿'!$C:$C,'渠道充值成功率_底稿'!$A:$A,$A68,'渠道充值成功率_底稿'!$B:$B,L$1) -> 0
A69: =B68 -> 46093 | C69: 到账笔数 | D69: =SUMIFS('渠道充值成功率_底稿'!$F:$F,'渠道充值成功率_底稿'!$A:$A,$A69,'渠道充值成功率_底稿'!$B:$B,D$1) -> 0 | E69: =SUMIFS('渠道充值成功率_底稿'!$F:$F,'渠道充值成功率_底稿'!$A:$A,$A69,'渠道充值成功率_底稿'!$B:$B,E$1) -> 0 | F69: =SUMIFS('渠道充值成功率_底稿'!$F:$F,'渠道充值成功率_底稿'!$A:$A,$A69,'渠道充值成功率_底稿'!$B:$B,F$1) -> 0 | G69: =SUMIFS('渠道充值成功率_底稿'!$F:$F,'渠道充值成功率_底稿'!$A:$A,$A69,'渠道充值成功率_底稿'!$B:$B,G$1) -> 0 | H69: =SUMIFS('渠道充值成功率_底稿'!$F:$F,'渠道充值成功率_底稿'!$A:$A,$A69,'渠道充值成功率_底稿'!$B:$B,H$1) -> 0 | I69: =SUMIFS('渠道充值成功率_底稿'!$F:$F,'渠道充值成功率_底稿'!$A:$A,$A69,'渠道充值成功率_底稿'!$B:$B,I$1) -> 0 | J69: =SUMIFS('渠道充值成功率_底稿'!$F:$F,'渠道充值成功率_底稿'!$A:$A,$A69,'渠道充值成功率_底稿'!$B:$B,J$1) -> 0 | K69: =SUMIFS('渠道充值成功率_底稿'!$F:$F,'渠道充值成功率_底稿'!$A:$A,$A69,'渠道充值成功率_底稿'!$B:$B,K$1) -> 0 | L69: =SUMIFS('渠道充值成功率_底稿'!$F:$F,'渠道充值成功率_底稿'!$A:$A,$A69,'渠道充值成功率_底稿'!$B:$B,L$1) -> 0
A70: =B68 -> 46093 | C70: 笔数成功率 | D70: =IFERROR(ROUND(D69/D68,6),"0") -> 0 | E70: =IFERROR(ROUND(E69/E68,6),"0") -> 0 | F70: =IFERROR(ROUND(F69/F68,6),"0") -> 0 | G70: =IFERROR(ROUND(G69/G68,6),"0") -> 0 | H70: =IFERROR(ROUND(H69/H68,6),"0") -> 0 | I70: =IFERROR(ROUND(I69/I68,6),"0") -> 0 | J70: =IFERROR(ROUND(J69/J68,6),"0") -> 0 | K70: =IFERROR(ROUND(K69/K68,6),"0") -> 0 | L70: =IFERROR(ROUND(L69/L68,6),"0") -> 0
A71: =B68 -> 46093 | C71: 申请金额 | D71: =SUMIFS('渠道充值成功率_底稿'!$D:$D,'渠道充值成功率_底稿'!$A:$A,$A72,'渠道充值成功率_底稿'!$B:$B,D$1) -> 0 | E71: =SUMIFS('渠道充值成功率_底稿'!$D:$D,'渠道充值成功率_底稿'!$A:$A,$A71,'渠道充值成功率_底稿'!$B:$B,E$1) -> 0 | F71: =SUMIFS('渠道充值成功率_底稿'!$D:$D,'渠道充值成功率_底稿'!$A:$A,$A71,'渠道充值成功率_底稿'!$B:$B,F$1) -> 0 | G71: =SUMIFS('渠道充值成功率_底稿'!$D:$D,'渠道充值成功率_底稿'!$A:$A,$A71,'渠道充值成功率_底稿'!$B:$B,G$1) -> 0 | H71: =SUMIFS('渠道充值成功率_底稿'!$D:$D,'渠道充值成功率_底稿'!$A:$A,$A71,'渠道充值成功率_底稿'!$B:$B,H$1) -> 0 | I71: =SUMIFS('渠道充值成功率_底稿'!$D:$D,'渠道充值成功率_底稿'!$A:$A,$A71,'渠道充值成功率_底稿'!$B:$B,I$1) -> 0 | J71: =SUMIFS('渠道充值成功率_底稿'!$D:$D,'渠道充值成功率_底稿'!$A:$A,$A71,'渠道充值成功率_底稿'!$B:$B,J$1) -> 0 | K71: =SUMIFS('渠道充值成功率_底稿'!$D:$D,'渠道充值成功率_底稿'!$A:$A,$A71,'渠道充值成功率_底稿'!$B:$B,K$1) -> 0 | L71: =SUMIFS('渠道充值成功率_底稿'!$D:$D,'渠道充值成功率_底稿'!$A:$A,$A71,'渠道充值成功率_底稿'!$B:$B,L$1) -> 0
A72: =B68 -> 46093 | C72: 到账金额 | D72: =SUMIFS('渠道充值成功率_底稿'!$G:$G,'渠道充值成功率_底稿'!$A:$A,$A73,'渠道充值成功率_底稿'!$B:$B,D$1) -> 0 | E72: =SUMIFS('渠道充值成功率_底稿'!$G:$G,'渠道充值成功率_底稿'!$A:$A,$A72,'渠道充值成功率_底稿'!$B:$B,E$1) -> 0 | F72: =SUMIFS('渠道充值成功率_底稿'!$G:$G,'渠道充值成功率_底稿'!$A:$A,$A72,'渠道充值成功率_底稿'!$B:$B,F$1) -> 0 | G72: =SUMIFS('渠道充值成功率_底稿'!$G:$G,'渠道充值成功率_底稿'!$A:$A,$A72,'渠道充值成功率_底稿'!$B:$B,G$1) -> 0 | H72: =SUMIFS('渠道充值成功率_底稿'!$G:$G,'渠道充值成功率_底稿'!$A:$A,$A72,'渠道充值成功率_底稿'!$B:$B,H$1) -> 0 | I72: =SUMIFS('渠道充值成功率_底稿'!$G:$G,'渠道充值成功率_底稿'!$A:$A,$A72,'渠道充值成功率_底稿'!$B:$B,I$1) -> 0 | J72: =SUMIFS('渠道充值成功率_底稿'!$G:$G,'渠道充值成功率_底稿'!$A:$A,$A72,'渠道充值成功率_底稿'!$B:$B,J$1) -> 0 | K72: =SUMIFS('渠道充值成功率_底稿'!$G:$G,'渠道充值成功率_底稿'!$A:$A,$A72,'渠道充值成功率_底稿'!$B:$B,K$1) -> 0 | L72: =SUMIFS('渠道充值成功率_底稿'!$G:$G,'渠道充值成功率_底稿'!$A:$A,$A72,'渠道充值成功率_底稿'!$B:$B,L$1) -> 0
A73: =B68 -> 46093 | C73: 金额成功率 | D73: =IFERROR(ROUND(D72/D71,6),"0") -> 0 | E73: =IFERROR(ROUND(E72/E71,6),"0") -> 0 | F73: =IFERROR(ROUND(F72/F71,6),"0") -> 0 | G73: =IFERROR(ROUND(G72/G71,6),"0") -> 0 | H73: =IFERROR(ROUND(H72/H71,6),"0") -> 0 | I73: =IFERROR(ROUND(I72/I71,6),"0") -> 0 | J73: =IFERROR(ROUND(J72/J71,6),"0") -> 0 | K73: =IFERROR(ROUND(K72/K71,6),"0") -> 0 | L73: =IFERROR(ROUND(L72/L71,6),"0") -> 0
A74: =B74 -> 46094 | B74: =B68+1 -> 46094 | C74: 申请笔数 | D74: =SUMIFS('渠道充值成功率_底稿'!$C:$C,'渠道充值成功率_底稿'!$A:$A,$A74,'渠道充值成功率_底稿'!$B:$B,D$1) -> 0 | E74: =SUMIFS('渠道充值成功率_底稿'!$C:$C,'渠道充值成功率_底稿'!$A:$A,$A74,'渠道充值成功率_底稿'!$B:$B,E$1) -> 0 | F74: =SUMIFS('渠道充值成功率_底稿'!$C:$C,'渠道充值成功率_底稿'!$A:$A,$A74,'渠道充值成功率_底稿'!$B:$B,F$1) -> 0 | G74: =SUMIFS('渠道充值成功率_底稿'!$C:$C,'渠道充值成功率_底稿'!$A:$A,$A74,'渠道充值成功率_底稿'!$B:$B,G$1) -> 0 | H74: =SUMIFS('渠道充值成功率_底稿'!$C:$C,'渠道充值成功率_底稿'!$A:$A,$A74,'渠道充值成功率_底稿'!$B:$B,H$1) -> 0 | I74: =SUMIFS('渠道充值成功率_底稿'!$C:$C,'渠道充值成功率_底稿'!$A:$A,$A74,'渠道充值成功率_底稿'!$B:$B,I$1) -> 0 | J74: =SUMIFS('渠道充值成功率_底稿'!$C:$C,'渠道充值成功率_底稿'!$A:$A,$A74,'渠道充值成功率_底稿'!$B:$B,J$1) -> 0 | K74: =SUMIFS('渠道充值成功率_底稿'!$C:$C,'渠道充值成功率_底稿'!$A:$A,$A74,'渠道充值成功率_底稿'!$B:$B,K$1) -> 0 | L74: =SUMIFS('渠道充值成功率_底稿'!$C:$C,'渠道充值成功率_底稿'!$A:$A,$A74,'渠道充值成功率_底稿'!$B:$B,L$1) -> 0
A75: =B74 -> 46094 | C75: 到账笔数 | D75: =SUMIFS('渠道充值成功率_底稿'!$F:$F,'渠道充值成功率_底稿'!$A:$A,$A75,'渠道充值成功率_底稿'!$B:$B,D$1) -> 0 | E75: =SUMIFS('渠道充值成功率_底稿'!$F:$F,'渠道充值成功率_底稿'!$A:$A,$A75,'渠道充值成功率_底稿'!$B:$B,E$1) -> 0 | F75: =SUMIFS('渠道充值成功率_底稿'!$F:$F,'渠道充值成功率_底稿'!$A:$A,$A75,'渠道充值成功率_底稿'!$B:$B,F$1) -> 0 | G75: =SUMIFS('渠道充值成功率_底稿'!$F:$F,'渠道充值成功率_底稿'!$A:$A,$A75,'渠道充值成功率_底稿'!$B:$B,G$1) -> 0 | H75: =SUMIFS('渠道充值成功率_底稿'!$F:$F,'渠道充值成功率_底稿'!$A:$A,$A75,'渠道充值成功率_底稿'!$B:$B,H$1) -> 0 | I75: =SUMIFS('渠道充值成功率_底稿'!$F:$F,'渠道充值成功率_底稿'!$A:$A,$A75,'渠道充值成功率_底稿'!$B:$B,I$1) -> 0 | J75: =SUMIFS('渠道充值成功率_底稿'!$F:$F,'渠道充值成功率_底稿'!$A:$A,$A75,'渠道充值成功率_底稿'!$B:$B,J$1) -> 0 | K75: =SUMIFS('渠道充值成功率_底稿'!$F:$F,'渠道充值成功率_底稿'!$A:$A,$A75,'渠道充值成功率_底稿'!$B:$B,K$1) -> 0 | L75: =SUMIFS('渠道充值成功率_底稿'!$F:$F,'渠道充值成功率_底稿'!$A:$A,$A75,'渠道充值成功率_底稿'!$B:$B,L$1) -> 0
A76: =B74 -> 46094 | C76: 笔数成功率 | D76: =IFERROR(ROUND(D75/D74,6),"0") -> 0 | E76: =IFERROR(ROUND(E75/E74,6),"0") -> 0 | F76: =IFERROR(ROUND(F75/F74,6),"0") -> 0 | G76: =IFERROR(ROUND(G75/G74,6),"0") -> 0 | H76: =IFERROR(ROUND(H75/H74,6),"0") -> 0 | I76: =IFERROR(ROUND(I75/I74,6),"0") -> 0 | J76: =IFERROR(ROUND(J75/J74,6),"0") -> 0 | K76: =IFERROR(ROUND(K75/K74,6),"0") -> 0 | L76: =IFERROR(ROUND(L75/L74,6),"0") -> 0
A77: =B74 -> 46094 | C77: 申请金额 | D77: =SUMIFS('渠道充值成功率_底稿'!$D:$D,'渠道充值成功率_底稿'!$A:$A,$A78,'渠道充值成功率_底稿'!$B:$B,D$1) -> 0 | E77: =SUMIFS('渠道充值成功率_底稿'!$D:$D,'渠道充值成功率_底稿'!$A:$A,$A77,'渠道充值成功率_底稿'!$B:$B,E$1) -> 0 | F77: =SUMIFS('渠道充值成功率_底稿'!$D:$D,'渠道充值成功率_底稿'!$A:$A,$A77,'渠道充值成功率_底稿'!$B:$B,F$1) -> 0 | G77: =SUMIFS('渠道充值成功率_底稿'!$D:$D,'渠道充值成功率_底稿'!$A:$A,$A77,'渠道充值成功率_底稿'!$B:$B,G$1) -> 0 | H77: =SUMIFS('渠道充值成功率_底稿'!$D:$D,'渠道充值成功率_底稿'!$A:$A,$A77,'渠道充值成功率_底稿'!$B:$B,H$1) -> 0 | I77: =SUMIFS('渠道充值成功率_底稿'!$D:$D,'渠道充值成功率_底稿'!$A:$A,$A77,'渠道充值成功率_底稿'!$B:$B,I$1) -> 0 | J77: =SUMIFS('渠道充值成功率_底稿'!$D:$D,'渠道充值成功率_底稿'!$A:$A,$A77,'渠道充值成功率_底稿'!$B:$B,J$1) -> 0 | K77: =SUMIFS('渠道充值成功率_底稿'!$D:$D,'渠道充值成功率_底稿'!$A:$A,$A77,'渠道充值成功率_底稿'!$B:$B,K$1) -> 0 | L77: =SUMIFS('渠道充值成功率_底稿'!$D:$D,'渠道充值成功率_底稿'!$A:$A,$A77,'渠道充值成功率_底稿'!$B:$B,L$1) -> 0
A78: =B74 -> 46094 | C78: 到账金额 | D78: =SUMIFS('渠道充值成功率_底稿'!$G:$G,'渠道充值成功率_底稿'!$A:$A,$A79,'渠道充值成功率_底稿'!$B:$B,D$1) -> 0 | E78: =SUMIFS('渠道充值成功率_底稿'!$G:$G,'渠道充值成功率_底稿'!$A:$A,$A78,'渠道充值成功率_底稿'!$B:$B,E$1) -> 0 | F78: =SUMIFS('渠道充值成功率_底稿'!$G:$G,'渠道充值成功率_底稿'!$A:$A,$A78,'渠道充值成功率_底稿'!$B:$B,F$1) -> 0 | G78: =SUMIFS('渠道充值成功率_底稿'!$G:$G,'渠道充值成功率_底稿'!$A:$A,$A78,'渠道充值成功率_底稿'!$B:$B,G$1) -> 0 | H78: =SUMIFS('渠道充值成功率_底稿'!$G:$G,'渠道充值成功率_底稿'!$A:$A,$A78,'渠道充值成功率_底稿'!$B:$B,H$1) -> 0 | I78: =SUMIFS('渠道充值成功率_底稿'!$G:$G,'渠道充值成功率_底稿'!$A:$A,$A78,'渠道充值成功率_底稿'!$B:$B,I$1) -> 0 | J78: =SUMIFS('渠道充值成功率_底稿'!$G:$G,'渠道充值成功率_底稿'!$A:$A,$A78,'渠道充值成功率_底稿'!$B:$B,J$1) -> 0 | K78: =SUMIFS('渠道充值成功率_底稿'!$G:$G,'渠道充值成功率_底稿'!$A:$A,$A78,'渠道充值成功率_底稿'!$B:$B,K$1) -> 0 | L78: =SUMIFS('渠道充值成功率_底稿'!$G:$G,'渠道充值成功率_底稿'!$A:$A,$A78,'渠道充值成功率_底稿'!$B:$B,L$1) -> 0
A79: =B74 -> 46094 | C79: 金额成功率 | D79: =IFERROR(ROUND(D78/D77,6),"0") -> 0 | E79: =IFERROR(ROUND(E78/E77,6),"0") -> 0 | F79: =IFERROR(ROUND(F78/F77,6),"0") -> 0 | G79: =IFERROR(ROUND(G78/G77,6),"0") -> 0 | H79: =IFERROR(ROUND(H78/H77,6),"0") -> 0 | I79: =IFERROR(ROUND(I78/I77,6),"0") -> 0 | J79: =IFERROR(ROUND(J78/J77,6),"0") -> 0 | K79: =IFERROR(ROUND(K78/K77,6),"0") -> 0 | L79: =IFERROR(ROUND(L78/L77,6),"0") -> 0
A80: =B80 -> 46095 | B80: =B74+1 -> 46095 | C80: 申请笔数 | D80: =SUMIFS('渠道充值成功率_底稿'!$C:$C,'渠道充值成功率_底稿'!$A:$A,$A80,'渠道充值成功率_底稿'!$B:$B,D$1) -> 0 | E80: =SUMIFS('渠道充值成功率_底稿'!$C:$C,'渠道充值成功率_底稿'!$A:$A,$A80,'渠道充值成功率_底稿'!$B:$B,E$1) -> 0 | F80: =SUMIFS('渠道充值成功率_底稿'!$C:$C,'渠道充值成功率_底稿'!$A:$A,$A80,'渠道充值成功率_底稿'!$B:$B,F$1) -> 0 | G80: =SUMIFS('渠道充值成功率_底稿'!$C:$C,'渠道充值成功率_底稿'!$A:$A,$A80,'渠道充值成功率_底稿'!$B:$B,G$1) -> 0 | H80: =SUMIFS('渠道充值成功率_底稿'!$C:$C,'渠道充值成功率_底稿'!$A:$A,$A80,'渠道充值成功率_底稿'!$B:$B,H$1) -> 0 | I80: =SUMIFS('渠道充值成功率_底稿'!$C:$C,'渠道充值成功率_底稿'!$A:$A,$A80,'渠道充值成功率_底稿'!$B:$B,I$1) -> 0 | J80: =SUMIFS('渠道充值成功率_底稿'!$C:$C,'渠道充值成功率_底稿'!$A:$A,$A80,'渠道充值成功率_底稿'!$B:$B,J$1) -> 0 | K80: =SUMIFS('渠道充值成功率_底稿'!$C:$C,'渠道充值成功率_底稿'!$A:$A,$A80,'渠道充值成功率_底稿'!$B:$B,K$1) -> 0 | L80: =SUMIFS('渠道充值成功率_底稿'!$C:$C,'渠道充值成功率_底稿'!$A:$A,$A80,'渠道充值成功率_底稿'!$B:$B,L$1) -> 0
A81: =B80 -> 46095 | C81: 到账笔数 | D81: =SUMIFS('渠道充值成功率_底稿'!$F:$F,'渠道充值成功率_底稿'!$A:$A,$A81,'渠道充值成功率_底稿'!$B:$B,D$1) -> 0 | E81: =SUMIFS('渠道充值成功率_底稿'!$F:$F,'渠道充值成功率_底稿'!$A:$A,$A81,'渠道充值成功率_底稿'!$B:$B,E$1) -> 0 | F81: =SUMIFS('渠道充值成功率_底稿'!$F:$F,'渠道充值成功率_底稿'!$A:$A,$A81,'渠道充值成功率_底稿'!$B:$B,F$1) -> 0 | G81: =SUMIFS('渠道充值成功率_底稿'!$F:$F,'渠道充值成功率_底稿'!$A:$A,$A81,'渠道充值成功率_底稿'!$B:$B,G$1) -> 0 | H81: =SUMIFS('渠道充值成功率_底稿'!$F:$F,'渠道充值成功率_底稿'!$A:$A,$A81,'渠道充值成功率_底稿'!$B:$B,H$1) -> 0 | I81: =SUMIFS('渠道充值成功率_底稿'!$F:$F,'渠道充值成功率_底稿'!$A:$A,$A81,'渠道充值成功率_底稿'!$B:$B,I$1) -> 0 | J81: =SUMIFS('渠道充值成功率_底稿'!$F:$F,'渠道充值成功率_底稿'!$A:$A,$A81,'渠道充值成功率_底稿'!$B:$B,J$1) -> 0 | K81: =SUMIFS('渠道充值成功率_底稿'!$F:$F,'渠道充值成功率_底稿'!$A:$A,$A81,'渠道充值成功率_底稿'!$B:$B,K$1) -> 0 | L81: =SUMIFS('渠道充值成功率_底稿'!$F:$F,'渠道充值成功率_底稿'!$A:$A,$A81,'渠道充值成功率_底稿'!$B:$B,L$1) -> 0
A82: =B80 -> 46095 | C82: 笔数成功率 | D82: =IFERROR(ROUND(D81/D80,6),"0") -> 0 | E82: =IFERROR(ROUND(E81/E80,6),"0") -> 0 | F82: =IFERROR(ROUND(F81/F80,6),"0") -> 0 | G82: =IFERROR(ROUND(G81/G80,6),"0") -> 0 | H82: =IFERROR(ROUND(H81/H80,6),"0") -> 0 | I82: =IFERROR(ROUND(I81/I80,6),"0") -> 0 | J82: =IFERROR(ROUND(J81/J80,6),"0") -> 0 | K82: =IFERROR(ROUND(K81/K80,6),"0") -> 0 | L82: =IFERROR(ROUND(L81/L80,6),"0") -> 0
A83: =B80 -> 46095 | C83: 申请金额 | D83: =SUMIFS('渠道充值成功率_底稿'!$D:$D,'渠道充值成功率_底稿'!$A:$A,$A84,'渠道充值成功率_底稿'!$B:$B,D$1) -> 0 | E83: =SUMIFS('渠道充值成功率_底稿'!$D:$D,'渠道充值成功率_底稿'!$A:$A,$A83,'渠道充值成功率_底稿'!$B:$B,E$1) -> 0 | F83: =SUMIFS('渠道充值成功率_底稿'!$D:$D,'渠道充值成功率_底稿'!$A:$A,$A83,'渠道充值成功率_底稿'!$B:$B,F$1) -> 0 | G83: =SUMIFS('渠道充值成功率_底稿'!$D:$D,'渠道充值成功率_底稿'!$A:$A,$A83,'渠道充值成功率_底稿'!$B:$B,G$1) -> 0 | H83: =SUMIFS('渠道充值成功率_底稿'!$D:$D,'渠道充值成功率_底稿'!$A:$A,$A83,'渠道充值成功率_底稿'!$B:$B,H$1) -> 0 | I83: =SUMIFS('渠道充值成功率_底稿'!$D:$D,'渠道充值成功率_底稿'!$A:$A,$A83,'渠道充值成功率_底稿'!$B:$B,I$1) -> 0 | J83: =SUMIFS('渠道充值成功率_底稿'!$D:$D,'渠道充值成功率_底稿'!$A:$A,$A83,'渠道充值成功率_底稿'!$B:$B,J$1) -> 0 | K83: =SUMIFS('渠道充值成功率_底稿'!$D:$D,'渠道充值成功率_底稿'!$A:$A,$A83,'渠道充值成功率_底稿'!$B:$B,K$1) -> 0 | L83: =SUMIFS('渠道充值成功率_底稿'!$D:$D,'渠道充值成功率_底稿'!$A:$A,$A83,'渠道充值成功率_底稿'!$B:$B,L$1) -> 0
A84: =B80 -> 46095 | C84: 到账金额 | D84: =SUMIFS('渠道充值成功率_底稿'!$G:$G,'渠道充值成功率_底稿'!$A:$A,$A85,'渠道充值成功率_底稿'!$B:$B,D$1) -> 0 | E84: =SUMIFS('渠道充值成功率_底稿'!$G:$G,'渠道充值成功率_底稿'!$A:$A,$A84,'渠道充值成功率_底稿'!$B:$B,E$1) -> 0 | F84: =SUMIFS('渠道充值成功率_底稿'!$G:$G,'渠道充值成功率_底稿'!$A:$A,$A84,'渠道充值成功率_底稿'!$B:$B,F$1) -> 0 | G84: =SUMIFS('渠道充值成功率_底稿'!$G:$G,'渠道充值成功率_底稿'!$A:$A,$A84,'渠道充值成功率_底稿'!$B:$B,G$1) -> 0 | H84: =SUMIFS('渠道充值成功率_底稿'!$G:$G,'渠道充值成功率_底稿'!$A:$A,$A84,'渠道充值成功率_底稿'!$B:$B,H$1) -> 0 | I84: =SUMIFS('渠道充值成功率_底稿'!$G:$G,'渠道充值成功率_底稿'!$A:$A,$A84,'渠道充值成功率_底稿'!$B:$B,I$1) -> 0 | J84: =SUMIFS('渠道充值成功率_底稿'!$G:$G,'渠道充值成功率_底稿'!$A:$A,$A84,'渠道充值成功率_底稿'!$B:$B,J$1) -> 0 | K84: =SUMIFS('渠道充值成功率_底稿'!$G:$G,'渠道充值成功率_底稿'!$A:$A,$A84,'渠道充值成功率_底稿'!$B:$B,K$1) -> 0 | L84: =SUMIFS('渠道充值成功率_底稿'!$G:$G,'渠道充值成功率_底稿'!$A:$A,$A84,'渠道充值成功率_底稿'!$B:$B,L$1) -> 0
A85: =B80 -> 46095 | C85: 金额成功率 | D85: =IFERROR(ROUND(D84/D83,6),"0") -> 0 | E85: =IFERROR(ROUND(E84/E83,6),"0") -> 0 | F85: =IFERROR(ROUND(F84/F83,6),"0") -> 0 | G85: =IFERROR(ROUND(G84/G83,6),"0") -> 0 | H85: =IFERROR(ROUND(H84/H83,6),"0") -> 0 | I85: =IFERROR(ROUND(I84/I83,6),"0") -> 0 | J85: =IFERROR(ROUND(J84/J83,6),"0") -> 0 | K85: =IFERROR(ROUND(K84/K83,6),"0") -> 0 | L85: =IFERROR(ROUND(L84/L83,6),"0") -> 0
A86: =B86 -> 46096 | B86: =B80+1 -> 46096 | C86: 申请笔数 | D86: =SUMIFS('渠道充值成功率_底稿'!$C:$C,'渠道充值成功率_底稿'!$A:$A,$A86,'渠道充值成功率_底稿'!$B:$B,D$1) -> 0 | E86: =SUMIFS('渠道充值成功率_底稿'!$C:$C,'渠道充值成功率_底稿'!$A:$A,$A86,'渠道充值成功率_底稿'!$B:$B,E$1) -> 0 | F86: =SUMIFS('渠道充值成功率_底稿'!$C:$C,'渠道充值成功率_底稿'!$A:$A,$A86,'渠道充值成功率_底稿'!$B:$B,F$1) -> 0 | G86: =SUMIFS('渠道充值成功率_底稿'!$C:$C,'渠道充值成功率_底稿'!$A:$A,$A86,'渠道充值成功率_底稿'!$B:$B,G$1) -> 0 | H86: =SUMIFS('渠道充值成功率_底稿'!$C:$C,'渠道充值成功率_底稿'!$A:$A,$A86,'渠道充值成功率_底稿'!$B:$B,H$1) -> 0 | I86: =SUMIFS('渠道充值成功率_底稿'!$C:$C,'渠道充值成功率_底稿'!$A:$A,$A86,'渠道充值成功率_底稿'!$B:$B,I$1) -> 0 | J86: =SUMIFS('渠道充值成功率_底稿'!$C:$C,'渠道充值成功率_底稿'!$A:$A,$A86,'渠道充值成功率_底稿'!$B:$B,J$1) -> 0 | K86: =SUMIFS('渠道充值成功率_底稿'!$C:$C,'渠道充值成功率_底稿'!$A:$A,$A86,'渠道充值成功率_底稿'!$B:$B,K$1) -> 0 | L86: =SUMIFS('渠道充值成功率_底稿'!$C:$C,'渠道充值成功率_底稿'!$A:$A,$A86,'渠道充值成功率_底稿'!$B:$B,L$1) -> 0
A87: =B86 -> 46096 | C87: 到账笔数 | D87: =SUMIFS('渠道充值成功率_底稿'!$F:$F,'渠道充值成功率_底稿'!$A:$A,$A87,'渠道充值成功率_底稿'!$B:$B,D$1) -> 0 | E87: =SUMIFS('渠道充值成功率_底稿'!$F:$F,'渠道充值成功率_底稿'!$A:$A,$A87,'渠道充值成功率_底稿'!$B:$B,E$1) -> 0 | F87: =SUMIFS('渠道充值成功率_底稿'!$F:$F,'渠道充值成功率_底稿'!$A:$A,$A87,'渠道充值成功率_底稿'!$B:$B,F$1) -> 0 | G87: =SUMIFS('渠道充值成功率_底稿'!$F:$F,'渠道充值成功率_底稿'!$A:$A,$A87,'渠道充值成功率_底稿'!$B:$B,G$1) -> 0 | H87: =SUMIFS('渠道充值成功率_底稿'!$F:$F,'渠道充值成功率_底稿'!$A:$A,$A87,'渠道充值成功率_底稿'!$B:$B,H$1) -> 0 | I87: =SUMIFS('渠道充值成功率_底稿'!$F:$F,'渠道充值成功率_底稿'!$A:$A,$A87,'渠道充值成功率_底稿'!$B:$B,I$1) -> 0 | J87: =SUMIFS('渠道充值成功率_底稿'!$F:$F,'渠道充值成功率_底稿'!$A:$A,$A87,'渠道充值成功率_底稿'!$B:$B,J$1) -> 0 | K87: =SUMIFS('渠道充值成功率_底稿'!$F:$F,'渠道充值成功率_底稿'!$A:$A,$A87,'渠道充值成功率_底稿'!$B:$B,K$1) -> 0 | L87: =SUMIFS('渠道充值成功率_底稿'!$F:$F,'渠道充值成功率_底稿'!$A:$A,$A87,'渠道充值成功率_底稿'!$B:$B,L$1) -> 0
A88: =B86 -> 46096 | C88: 笔数成功率 | D88: =IFERROR(ROUND(D87/D86,6),"0") -> 0 | E88: =IFERROR(ROUND(E87/E86,6),"0") -> 0 | F88: =IFERROR(ROUND(F87/F86,6),"0") -> 0 | G88: =IFERROR(ROUND(G87/G86,6),"0") -> 0 | H88: =IFERROR(ROUND(H87/H86,6),"0") -> 0 | I88: =IFERROR(ROUND(I87/I86,6),"0") -> 0 | J88: =IFERROR(ROUND(J87/J86,6),"0") -> 0 | K88: =IFERROR(ROUND(K87/K86,6),"0") -> 0 | L88: =IFERROR(ROUND(L87/L86,6),"0") -> 0
A89: =B86 -> 46096 | C89: 申请金额 | D89: =SUMIFS('渠道充值成功率_底稿'!$D:$D,'渠道充值成功率_底稿'!$A:$A,$A90,'渠道充值成功率_底稿'!$B:$B,D$1) -> 0 | E89: =SUMIFS('渠道充值成功率_底稿'!$D:$D,'渠道充值成功率_底稿'!$A:$A,$A89,'渠道充值成功率_底稿'!$B:$B,E$1) -> 0 | F89: =SUMIFS('渠道充值成功率_底稿'!$D:$D,'渠道充值成功率_底稿'!$A:$A,$A89,'渠道充值成功率_底稿'!$B:$B,F$1) -> 0 | G89: =SUMIFS('渠道充值成功率_底稿'!$D:$D,'渠道充值成功率_底稿'!$A:$A,$A89,'渠道充值成功率_底稿'!$B:$B,G$1) -> 0 | H89: =SUMIFS('渠道充值成功率_底稿'!$D:$D,'渠道充值成功率_底稿'!$A:$A,$A89,'渠道充值成功率_底稿'!$B:$B,H$1) -> 0 | I89: =SUMIFS('渠道充值成功率_底稿'!$D:$D,'渠道充值成功率_底稿'!$A:$A,$A89,'渠道充值成功率_底稿'!$B:$B,I$1) -> 0 | J89: =SUMIFS('渠道充值成功率_底稿'!$D:$D,'渠道充值成功率_底稿'!$A:$A,$A89,'渠道充值成功率_底稿'!$B:$B,J$1) -> 0 | K89: =SUMIFS('渠道充值成功率_底稿'!$D:$D,'渠道充值成功率_底稿'!$A:$A,$A89,'渠道充值成功率_底稿'!$B:$B,K$1) -> 0 | L89: =SUMIFS('渠道充值成功率_底稿'!$D:$D,'渠道充值成功率_底稿'!$A:$A,$A89,'渠道充值成功率_底稿'!$B:$B,L$1) -> 0
A90: =B86 -> 46096 | C90: 到账金额 | D90: =SUMIFS('渠道充值成功率_底稿'!$G:$G,'渠道充值成功率_底稿'!$A:$A,$A91,'渠道充值成功率_底稿'!$B:$B,D$1) -> 0 | E90: =SUMIFS('渠道充值成功率_底稿'!$G:$G,'渠道充值成功率_底稿'!$A:$A,$A90,'渠道充值成功率_底稿'!$B:$B,E$1) -> 0 | F90: =SUMIFS('渠道充值成功率_底稿'!$G:$G,'渠道充值成功率_底稿'!$A:$A,$A90,'渠道充值成功率_底稿'!$B:$B,F$1) -> 0 | G90: =SUMIFS('渠道充值成功率_底稿'!$G:$G,'渠道充值成功率_底稿'!$A:$A,$A90,'渠道充值成功率_底稿'!$B:$B,G$1) -> 0 | H90: =SUMIFS('渠道充值成功率_底稿'!$G:$G,'渠道充值成功率_底稿'!$A:$A,$A90,'渠道充值成功率_底稿'!$B:$B,H$1) -> 0 | I90: =SUMIFS('渠道充值成功率_底稿'!$G:$G,'渠道充值成功率_底稿'!$A:$A,$A90,'渠道充值成功率_底稿'!$B:$B,I$1) -> 0 | J90: =SUMIFS('渠道充值成功率_底稿'!$G:$G,'渠道充值成功率_底稿'!$A:$A,$A90,'渠道充值成功率_底稿'!$B:$B,J$1) -> 0 | K90: =SUMIFS('渠道充值成功率_底稿'!$G:$G,'渠道充值成功率_底稿'!$A:$A,$A90,'渠道充值成功率_底稿'!$B:$B,K$1) -> 0 | L90: =SUMIFS('渠道充值成功率_底稿'!$G:$G,'渠道充值成功率_底稿'!$A:$A,$A90,'渠道充值成功率_底稿'!$B:$B,L$1) -> 0
A91: =B86 -> 46096 | C91: 金额成功率 | D91: =IFERROR(ROUND(D90/D89,6),"0") -> 0 | E91: =IFERROR(ROUND(E90/E89,6),"0") -> 0 | F91: =IFERROR(ROUND(F90/F89,6),"0") -> 0 | G91: =IFERROR(ROUND(G90/G89,6),"0") -> 0 | H91: =IFERROR(ROUND(H90/H89,6),"0") -> 0 | I91: =IFERROR(ROUND(I90/I89,6),"0") -> 0 | J91: =IFERROR(ROUND(J90/J89,6),"0") -> 0 | K91: =IFERROR(ROUND(K90/K89,6),"0") -> 0 | L91: =IFERROR(ROUND(L90/L89,6),"0") -> 0
A92: =B92 -> 46097 | B92: =B86+1 -> 46097 | C92: 申请笔数 | D92: =SUMIFS('渠道充值成功率_底稿'!$C:$C,'渠道充值成功率_底稿'!$A:$A,$A92,'渠道充值成功率_底稿'!$B:$B,D$1) -> 0 | E92: =SUMIFS('渠道充值成功率_底稿'!$C:$C,'渠道充值成功率_底稿'!$A:$A,$A92,'渠道充值成功率_底稿'!$B:$B,E$1) -> 0 | F92: =SUMIFS('渠道充值成功率_底稿'!$C:$C,'渠道充值成功率_底稿'!$A:$A,$A92,'渠道充值成功率_底稿'!$B:$B,F$1) -> 0 | G92: =SUMIFS('渠道充值成功率_底稿'!$C:$C,'渠道充值成功率_底稿'!$A:$A,$A92,'渠道充值成功率_底稿'!$B:$B,G$1) -> 0 | H92: =SUMIFS('渠道充值成功率_底稿'!$C:$C,'渠道充值成功率_底稿'!$A:$A,$A92,'渠道充值成功率_底稿'!$B:$B,H$1) -> 0 | I92: =SUMIFS('渠道充值成功率_底稿'!$C:$C,'渠道充值成功率_底稿'!$A:$A,$A92,'渠道充值成功率_底稿'!$B:$B,I$1) -> 0 | J92: =SUMIFS('渠道充值成功率_底稿'!$C:$C,'渠道充值成功率_底稿'!$A:$A,$A92,'渠道充值成功率_底稿'!$B:$B,J$1) -> 0 | K92: =SUMIFS('渠道充值成功率_底稿'!$C:$C,'渠道充值成功率_底稿'!$A:$A,$A92,'渠道充值成功率_底稿'!$B:$B,K$1) -> 0 | L92: =SUMIFS('渠道充值成功率_底稿'!$C:$C,'渠道充值成功率_底稿'!$A:$A,$A92,'渠道充值成功率_底稿'!$B:$B,L$1) -> 0
A93: =B92 -> 46097 | C93: 到账笔数 | D93: =SUMIFS('渠道充值成功率_底稿'!$F:$F,'渠道充值成功率_底稿'!$A:$A,$A93,'渠道充值成功率_底稿'!$B:$B,D$1) -> 0 | E93: =SUMIFS('渠道充值成功率_底稿'!$F:$F,'渠道充值成功率_底稿'!$A:$A,$A93,'渠道充值成功率_底稿'!$B:$B,E$1) -> 0 | F93: =SUMIFS('渠道充值成功率_底稿'!$F:$F,'渠道充值成功率_底稿'!$A:$A,$A93,'渠道充值成功率_底稿'!$B:$B,F$1) -> 0 | G93: =SUMIFS('渠道充值成功率_底稿'!$F:$F,'渠道充值成功率_底稿'!$A:$A,$A93,'渠道充值成功率_底稿'!$B:$B,G$1) -> 0 | H93: =SUMIFS('渠道充值成功率_底稿'!$F:$F,'渠道充值成功率_底稿'!$A:$A,$A93,'渠道充值成功率_底稿'!$B:$B,H$1) -> 0 | I93: =SUMIFS('渠道充值成功率_底稿'!$F:$F,'渠道充值成功率_底稿'!$A:$A,$A93,'渠道充值成功率_底稿'!$B:$B,I$1) -> 0 | J93: =SUMIFS('渠道充值成功率_底稿'!$F:$F,'渠道充值成功率_底稿'!$A:$A,$A93,'渠道充值成功率_底稿'!$B:$B,J$1) -> 0 | K93: =SUMIFS('渠道充值成功率_底稿'!$F:$F,'渠道充值成功率_底稿'!$A:$A,$A93,'渠道充值成功率_底稿'!$B:$B,K$1) -> 0 | L93: =SUMIFS('渠道充值成功率_底稿'!$F:$F,'渠道充值成功率_底稿'!$A:$A,$A93,'渠道充值成功率_底稿'!$B:$B,L$1) -> 0
A94: =B92 -> 46097 | C94: 笔数成功率 | D94: =IFERROR(ROUND(D93/D92,6),"0") -> 0 | E94: =IFERROR(ROUND(E93/E92,6),"0") -> 0 | F94: =IFERROR(ROUND(F93/F92,6),"0") -> 0 | G94: =IFERROR(ROUND(G93/G92,6),"0") -> 0 | H94: =IFERROR(ROUND(H93/H92,6),"0") -> 0 | I94: =IFERROR(ROUND(I93/I92,6),"0") -> 0 | J94: =IFERROR(ROUND(J93/J92,6),"0") -> 0 | K94: =IFERROR(ROUND(K93/K92,6),"0") -> 0 | L94: =IFERROR(ROUND(L93/L92,6),"0") -> 0
A95: =B92 -> 46097 | C95: 申请金额 | D95: =SUMIFS('渠道充值成功率_底稿'!$D:$D,'渠道充值成功率_底稿'!$A:$A,$A96,'渠道充值成功率_底稿'!$B:$B,D$1) -> 0 | E95: =SUMIFS('渠道充值成功率_底稿'!$D:$D,'渠道充值成功率_底稿'!$A:$A,$A95,'渠道充值成功率_底稿'!$B:$B,E$1) -> 0 | F95: =SUMIFS('渠道充值成功率_底稿'!$D:$D,'渠道充值成功率_底稿'!$A:$A,$A95,'渠道充值成功率_底稿'!$B:$B,F$1) -> 0 | G95: =SUMIFS('渠道充值成功率_底稿'!$D:$D,'渠道充值成功率_底稿'!$A:$A,$A95,'渠道充值成功率_底稿'!$B:$B,G$1) -> 0 | H95: =SUMIFS('渠道充值成功率_底稿'!$D:$D,'渠道充值成功率_底稿'!$A:$A,$A95,'渠道充值成功率_底稿'!$B:$B,H$1) -> 0 | I95: =SUMIFS('渠道充值成功率_底稿'!$D:$D,'渠道充值成功率_底稿'!$A:$A,$A95,'渠道充值成功率_底稿'!$B:$B,I$1) -> 0 | J95: =SUMIFS('渠道充值成功率_底稿'!$D:$D,'渠道充值成功率_底稿'!$A:$A,$A95,'渠道充值成功率_底稿'!$B:$B,J$1) -> 0 | K95: =SUMIFS('渠道充值成功率_底稿'!$D:$D,'渠道充值成功率_底稿'!$A:$A,$A95,'渠道充值成功率_底稿'!$B:$B,K$1) -> 0 | L95: =SUMIFS('渠道充值成功率_底稿'!$D:$D,'渠道充值成功率_底稿'!$A:$A,$A95,'渠道充值成功率_底稿'!$B:$B,L$1) -> 0
A96: =B92 -> 46097 | C96: 到账金额 | D96: =SUMIFS('渠道充值成功率_底稿'!$G:$G,'渠道充值成功率_底稿'!$A:$A,$A97,'渠道充值成功率_底稿'!$B:$B,D$1) -> 0 | E96: =SUMIFS('渠道充值成功率_底稿'!$G:$G,'渠道充值成功率_底稿'!$A:$A,$A96,'渠道充值成功率_底稿'!$B:$B,E$1) -> 0 | F96: =SUMIFS('渠道充值成功率_底稿'!$G:$G,'渠道充值成功率_底稿'!$A:$A,$A96,'渠道充值成功率_底稿'!$B:$B,F$1) -> 0 | G96: =SUMIFS('渠道充值成功率_底稿'!$G:$G,'渠道充值成功率_底稿'!$A:$A,$A96,'渠道充值成功率_底稿'!$B:$B,G$1) -> 0 | H96: =SUMIFS('渠道充值成功率_底稿'!$G:$G,'渠道充值成功率_底稿'!$A:$A,$A96,'渠道充值成功率_底稿'!$B:$B,H$1) -> 0 | I96: =SUMIFS('渠道充值成功率_底稿'!$G:$G,'渠道充值成功率_底稿'!$A:$A,$A96,'渠道充值成功率_底稿'!$B:$B,I$1) -> 0 | J96: =SUMIFS('渠道充值成功率_底稿'!$G:$G,'渠道充值成功率_底稿'!$A:$A,$A96,'渠道充值成功率_底稿'!$B:$B,J$1) -> 0 | K96: =SUMIFS('渠道充值成功率_底稿'!$G:$G,'渠道充值成功率_底稿'!$A:$A,$A96,'渠道充值成功率_底稿'!$B:$B,K$1) -> 0 | L96: =SUMIFS('渠道充值成功率_底稿'!$G:$G,'渠道充值成功率_底稿'!$A:$A,$A96,'渠道充值成功率_底稿'!$B:$B,L$1) -> 0
A97: =B92 -> 46097 | C97: 金额成功率 | D97: =IFERROR(ROUND(D96/D95,6),"0") -> 0 | E97: =IFERROR(ROUND(E96/E95,6),"0") -> 0 | F97: =IFERROR(ROUND(F96/F95,6),"0") -> 0 | G97: =IFERROR(ROUND(G96/G95,6),"0") -> 0 | H97: =IFERROR(ROUND(H96/H95,6),"0") -> 0 | I97: =IFERROR(ROUND(I96/I95,6),"0") -> 0 | J97: =IFERROR(ROUND(J96/J95,6),"0") -> 0 | K97: =IFERROR(ROUND(K96/K95,6),"0") -> 0 | L97: =IFERROR(ROUND(L96/L95,6),"0") -> 0
A98: =B98 -> 46098 | B98: =B92+1 -> 46098 | C98: 申请笔数 | D98: =SUMIFS('渠道充值成功率_底稿'!$C:$C,'渠道充值成功率_底稿'!$A:$A,$A98,'渠道充值成功率_底稿'!$B:$B,D$1) -> 0 | E98: =SUMIFS('渠道充值成功率_底稿'!$C:$C,'渠道充值成功率_底稿'!$A:$A,$A98,'渠道充值成功率_底稿'!$B:$B,E$1) -> 0 | F98: =SUMIFS('渠道充值成功率_底稿'!$C:$C,'渠道充值成功率_底稿'!$A:$A,$A98,'渠道充值成功率_底稿'!$B:$B,F$1) -> 0 | G98: =SUMIFS('渠道充值成功率_底稿'!$C:$C,'渠道充值成功率_底稿'!$A:$A,$A98,'渠道充值成功率_底稿'!$B:$B,G$1) -> 0 | H98: =SUMIFS('渠道充值成功率_底稿'!$C:$C,'渠道充值成功率_底稿'!$A:$A,$A98,'渠道充值成功率_底稿'!$B:$B,H$1) -> 0 | I98: =SUMIFS('渠道充值成功率_底稿'!$C:$C,'渠道充值成功率_底稿'!$A:$A,$A98,'渠道充值成功率_底稿'!$B:$B,I$1) -> 0 | J98: =SUMIFS('渠道充值成功率_底稿'!$C:$C,'渠道充值成功率_底稿'!$A:$A,$A98,'渠道充值成功率_底稿'!$B:$B,J$1) -> 0 | K98: =SUMIFS('渠道充值成功率_底稿'!$C:$C,'渠道充值成功率_底稿'!$A:$A,$A98,'渠道充值成功率_底稿'!$B:$B,K$1) -> 0 | L98: =SUMIFS('渠道充值成功率_底稿'!$C:$C,'渠道充值成功率_底稿'!$A:$A,$A98,'渠道充值成功率_底稿'!$B:$B,L$1) -> 0
A99: =B98 -> 46098 | C99: 到账笔数 | D99: =SUMIFS('渠道充值成功率_底稿'!$F:$F,'渠道充值成功率_底稿'!$A:$A,$A99,'渠道充值成功率_底稿'!$B:$B,D$1) -> 0 | E99: =SUMIFS('渠道充值成功率_底稿'!$F:$F,'渠道充值成功率_底稿'!$A:$A,$A99,'渠道充值成功率_底稿'!$B:$B,E$1) -> 0 | F99: =SUMIFS('渠道充值成功率_底稿'!$F:$F,'渠道充值成功率_底稿'!$A:$A,$A99,'渠道充值成功率_底稿'!$B:$B,F$1) -> 0 | G99: =SUMIFS('渠道充值成功率_底稿'!$F:$F,'渠道充值成功率_底稿'!$A:$A,$A99,'渠道充值成功率_底稿'!$B:$B,G$1) -> 0 | H99: =SUMIFS('渠道充值成功率_底稿'!$F:$F,'渠道充值成功率_底稿'!$A:$A,$A99,'渠道充值成功率_底稿'!$B:$B,H$1) -> 0 | I99: =SUMIFS('渠道充值成功率_底稿'!$F:$F,'渠道充值成功率_底稿'!$A:$A,$A99,'渠道充值成功率_底稿'!$B:$B,I$1) -> 0 | J99: =SUMIFS('渠道充值成功率_底稿'!$F:$F,'渠道充值成功率_底稿'!$A:$A,$A99,'渠道充值成功率_底稿'!$B:$B,J$1) -> 0 | K99: =SUMIFS('渠道充值成功率_底稿'!$F:$F,'渠道充值成功率_底稿'!$A:$A,$A99,'渠道充值成功率_底稿'!$B:$B,K$1) -> 0 | L99: =SUMIFS('渠道充值成功率_底稿'!$F:$F,'渠道充值成功率_底稿'!$A:$A,$A99,'渠道充值成功率_底稿'!$B:$B,L$1) -> 0
A100: =B98 -> 46098 | C100: 笔数成功率 | D100: =IFERROR(ROUND(D99/D98,6),"0") -> 0 | E100: =IFERROR(ROUND(E99/E98,6),"0") -> 0 | F100: =IFERROR(ROUND(F99/F98,6),"0") -> 0 | G100: =IFERROR(ROUND(G99/G98,6),"0") -> 0 | H100: =IFERROR(ROUND(H99/H98,6),"0") -> 0 | I100: =IFERROR(ROUND(I99/I98,6),"0") -> 0 | J100: =IFERROR(ROUND(J99/J98,6),"0") -> 0 | K100: =IFERROR(ROUND(K99/K98,6),"0") -> 0 | L100: =IFERROR(ROUND(L99/L98,6),"0") -> 0
...

Sheet 渠道充值成功率_底稿
B1: jiliarena
A2: 时间 | B2: 充值方式 | C2: 申请笔数 | D2: 申请金额 | E2: 申请人数 | F2: 到账笔数 | G2: 到账金额 | H2: 到账人数 | I2: 首存人数 | J2: 首存金额 | K2: 成功率 (%) | L2: 到账金额占比 (%) | M2: 平均到账时间
A3: 46082 | B3: GOTYME | C3: 6 | D3: 900 | E3: 5 | F3: 4 | G3: 700 | H3: 4 | I3: 3 | J3: 500 | K3: 66.66 % | L3: 0.37 % | M3: 0.0046064815
A4: 46082 | B4: QRPH | C4: 32 | D4: 5860 | E4: 19 | F4: 24 | G4: 4610 | H4: 17 | I4: 11 | J4: 2050 | K4: 75.00 % | L4: 2.46 % | M4: 0.00081018519
A5: 46082 | B5: GCash | C5: 1458 | D5: 201674 | E5: 854 | F5: 1065 | G5: 162179 | H5: 786 | I5: 530 | J5: 75007 | K5: 73.04 % | L5: 86.75 % | M5: 0.00071759259
A6: 46082 | B6: GCashQR | C6: 61 | D6: 8630 | E6: 46 | F6: 41 | G6: 5980 | H6: 32 | I6: 21 | J6: 3000 | K6: 67.21 % | L6: 3.19 % | M6: 0.00075231481
A7: 46082 | B7: Maya | C7: 146 | D7: 18592 | E7: 120 | F7: 117 | G7: 13472 | H7: 104 | I7: 60 | J7: 6970 | K7: 80.13 % | L7: 7.20 % | M7: 0.000625
A9: 46083 | B9: GOTYME | C9: 14 | D9: 3110 | E9: 4 | F9: 13 | G9: 2910 | H9: 3 | I9: 1 | J9: 200 | K9: 92.85 % | L9: 3.21 % | M9: 0.000625
A10: 46083 | B10: QRPH | C10: 14 | D10: 2325 | E10: 6 | F10: 13 | G10: 2225 | H10: 5 | I10: 0 | J10: 0 | K10: 92.85 % | L10: 2.45 % | M10: 0.00045138889
A11: 46083 | B11: GCash | C11: 611 | D11: 97556 | E11: 382 | F11: 492 | G11: 76391 | H11: 359 | I11: 119 | J11: 17236 | K11: 80.52 % | L11: 84.45 % | M11: 0.00074074074
A12: 46083 | B12: GCashQR | C12: 30 | D12: 4167 | E12: 24 | F12: 24 | G12: 3467 | H12: 19 | I12: 8 | J12: 1235 | K12: 80.00 % | L12: 3.83 % | M12: 0.00056712963
A13: 46083 | B13: Maya | C13: 81 | D13: 9777 | E13: 54 | F13: 57 | G13: 5458 | H13: 46 | I13: 12 | J13: 1024 | K13: 70.37 % | L13: 6.03 % | M13: 0.000625
A15: 46084 | B15: GOTYME | C15: 11 | D15: 2100 | E15: 4 | F15: 6 | G15: 1200 | H15: 2 | I15: 0 | J15: 0 | K15: 54.54 % | L15: 1.37 % | M15: 0.00060185185
A16: 46084 | B16: QRPH | C16: 22 | D16: 3250 | E16: 5 | F16: 21 | G16: 3050 | H16: 4 | I16: 0 | J16: 0 | K16: 95.45 % | L16: 3.49 % | M16: 0.00054398148
... A59: 46091 | B59: Maya | C59: 58 | D59: 6569 | E59: 35 | F59: 42 | G59: 4709 | H59: 31 | I59: 7 | J59: 550 | K59: 72.41 % | L59: 8.76 % | M59: 0.00069444444
A61: 46092 | B61: GOTYME | C61: 5 | D61: 600 | E61: 2 | F61: 5 | G61: 600 | H61: 2 | I61: 1 | J61: 100 | K61: 100 | L61: 1.12 | M61: 0.0017939815
A62: 46092 | B62: QRPH | C62: 18 | D62: 4270 | E62: 8 | F62: 12 | G62: 2770 | H62: 7 | I62: 3 | J62: 300 | K62: 66.66 | L62: 5.2 | M62: 0.00056712963
A63: 46092 | B63: GCash | C63: 479 | D63: 63978 | E63: 301 | F63: 331 | G63: 43743 | H63: 268 | I63: 93 | J63: 11375 | K63: 69.1 | L63: 82.11 | M63: 0.00087962963
A64: 46092 | B64: GCashQR | C64: 26 | D64: 3306 | E64: 20 | F64: 11 | G64: 1151 | H64: 11 | I64: 3 | J64: 300 | K64: 42.3 | L64: 2.16 | M64: 0.0014351852
A65: 46092 | B65: Maya | C65: 70 | D65: 10363 | E65: 51 | F65: 49 | G65: 5004 | H65: 43 | I65: 19 | J65: 2035 | K65: 70 | L65: 9.39 | M65: 0.00065972222

Sheet jiliarena
A1: jiliarena | W1: 净输/投注 | Z1: 净赢/中奖 | BW1: 8月 | BX1: 手续费费率 | BY1: 0.0241 | BZ1: 0.002
B2: 报表管理-平台损益总表 | C2: 报表管理-平台损益总表 | D2: 报表管理-平台损益总表 | E2: 报表管理-留存用户分析 | F2: 报表管理-平台损益总表 | G2: 报表管理-平台损益-充值 | H2: 报表管理-平台损益总表 | J2: 报表管理-平台损益总表 | L2: 报表管理-平台损益总表 | M2: 报表管理-平台损益总表 | W2: 报表管理-游戏玩家分析 | X2: 报表管理-游戏玩家分析 | Y2: 报表管理-游戏玩家分析 | Z2: 报表管理-游戏玩家分析 | AT2: GAME_REBATE | AU2: APP_DOWNLOAD | AV2: DEPOSIT | AW2: LOGIN | AX2: UPGRADE_BONUS | AY2: MANUAL | BA2: PROMO_CODE | BB2: 邀请返佣 | BC2: LOGIN_TASK | BD2: DEPOSIT_BET_BONUS | BE2: SAVIOR | BF2: MISSION | BG2: RANK_SALARY | BH2: SECOND_DEPOSIT | BI2: THIRD_DEPOSIT | BJ2: FIRST_DEPOSIT | BY2: 报表管理-平台损益-手续费 | BZ2: 报表管理-平台损益-手续费 | CF2: 报表管理-平台损益-平台毛利 | CG2: 报表管理-平台损益-平台毛利 | CH2: 报表管理-平台损益-平台毛利
B3: 注册人数 | C3: 首充人数 | D3: 登录人数 | E3: 报表管理-留存用户分析 | F3: 存款人数 | G3: 存款次数 | H3: 提款人数 | I3: 出款笔数 | J3: 投注人数 | K3: 总首存 | L3: 日充值 | M3: 提款金额 | N3: 公式 | O3: 公式 | P3: 公式 | Q3: 公式 | R3: 公式 | S3: 公式 | T3: 公式 | U3: 公式 | V3: 公式 | W3: 投注 | X3: 有效投注 | Y3: 公司输赢 | Z3: 派彩 | AA3: 公式 | AB3: 棋牌输额 | AC3: 棋牌赢额 | AD3: 公式 | AE3: 电子投注 | AF3: 电子中奖 | AG3: 公式 | AH3: 真人投注 | AI3: 真人中奖 | AJ3: 公式 | AK3: 捕鱼投注 | AL3: 捕鱼中奖 | AM3: 公式 | AN3: 体育投注 | AO3: 体育中奖 | AP3: 公式 | AQ3: 盘口彩票投注 | AR3: 盘口彩票中奖 | AS3: 公式 | AT3: 玩家返水 | AU3: APP下载 | AV3: 笔笔存送 | AW3: 签到奖励 | AX3: 升级奖励 | AY3: 手动红利 | AZ3: 红利扣除 | BA3: 优惠码 | BB3: 邀请返佣 | BC3: 登录任务 | BD3: 存款达标奖励 | BE3: 关怀援助金 | BF3: 任务排行榜 | BG3: VIP俸禄 | BH3: 二次存送 | BI3: 三次存送 | BJ3: 首存 | BK3: 新手任务奖励 | BL3: 注册奖励 | BM3: 四次存送 | BN3: 五次存送 | BQ3: 总优惠 | BR3: 返点 | BS3: 代理贡献层级 | BT3: 公式 | BW3: 公式 | BY3: 渠道手续费 | BZ3: 玩家提现手续费 | CA3: 公式 | CB3: 公式 | CD3: 代理佣金（周） | CE3: 代理佣金（月 | CF3: 开分 | CG3: 洗分 | CH3: 结算余额
A4: 时间 Date | B4: 平台新注册人数 Total New Users | C4: 总首充人数 first depositor / no of first time depositors | D4: 总登录人数 Login Head Count | E4: 续存人数 Number of survivors | F4: 总存款人数 no of total depositors | G4: 总存款次数 deposit times / total deposit counts | H4: 总取款人数 no of total withdrawer | I4: 总取款次数 withdrawal times / total withdrawal counts | J4: 总投注人数 no of bettors / No of bet | K4: 首存金额 First deposit amount | L4: 总存款额度 total deposit amount | M4: 总取款额度 total withdrawal amount | N4: 平台转化率 Conversion rate | O4: 人均首存金额 | P4: 首存比例存款 First deposit ratio total deposit | Q4: 人均次数 Per capita times | R4: 人均入款 Per capita deposit | S4: 單次人均入款 | T4: 續存/首存 比 | U4: 人均提款 Withdrawal per capita | V4: 存提差 Deposit/withdrawal difference | W4: 投注 Betting | X4: 有效投注额 Valid bet | Y4: 公司输赢 Win or lose | Z4: 派彩 Payouts | AA4: 杀率 kill rate | AB4: 棋牌投注 PVP Bet | AC4: 棋牌赢额 PVP Win | AD4: 棋牌杀率 PVP kill rate | AE4: 電子投注 RNG Bet | AF4: 電子中獎 RNG Win | AG4: 電子杀率 RNG kill rate | AH4: 真人投注 LIVE Bet | AI4: 真人中獎 LIVE Win | AJ4: 真人杀率 LIVE kill rate | AK4: 捕魚投注 FISH Bet | AL4: 捕魚中獎 FISH Win | AM4: 捕魚杀率 FISH kill rate | AN4: 體育投注 SPORTS Bet | AO4: 體育中獎 SPORTS Win | AP4: 體育杀率 SPORTS kill rate | AQ4: 盘口彩票投注 ELOTT Bet | AR4: 盘口彩票中獎 ELOTT Win | AS4: 盘口彩票 ELOTT kill rate | AT4: 玩家返水 | AU4: APP下载 | AV4: 笔笔存送 | AW4: 签到奖励 | AX4: 升级奖励 | AY4: 手动红利 | AZ4: 红利扣除 | BA4: 优惠码 | BB4: 邀请返佣 | BC4: 登录任务 | BD4: 存款达标奖励 | BE4: 关怀援助金 | BF4: 任务排行榜 | BG4: VIP俸禄 | BH4: 二次存送 | BI4: 三次存送 | BJ4: 首存 | BK4: 新手任务奖励 | BL4: 注册奖励 | BM4: 四次存送 | BN4: 五次存送 | BP4: 其他奖励 Other Bonus | BQ4: 总优惠 （Z+...+AH） Total Bonus | BR4: 返点 Rebates | BS4: 邀请返佣 Referral rebates | BT4: 优惠占比投注 Preferential ratio bet | BU4: 优惠占比充值 Bonus rebates | BV4: 优惠占比游戏亏损 Preferential astio loss | BW4: 公司净利 company net profit | BX4: 優惠/ 淨利 | BY4: 存款手续费 Deposit fees | BZ4: 提款手续费 Withdrawal fees | CA4: 支付手续费 service fees (Payment Channel Fee) | CB4: 预估平台费9% Estimate platform fee | CC4: 支付費用/淨利 | CD4: 代理佣金（周） Affiliate Commission (Weekly) | CE4: 代理佣金（月） Affiliate Commission (Monthly) | CF4: 開分 Credit Adjustment | CG4: 洗分 Debit Adjustment | CH4: 平台余额 Platform balance | CI4: 平台毛利 3 GP3 | CJ4: 月份 | CK4: 日期
A5: 46076 | B5: 623 | C5: 161 | D5: 3493 | E5: 33 | F5: 419 | G5: 578 | H5: 94 | I5: 132 | J5: 2358 | K5: 21559 | L5: 75103 | M5: 67348 | N5: 0.2584 | O5: 134 | P5: 0.2871 | Q5: 1.4 | R5: 179 | S5: 130 | T5: 1 | U5: 716 | V5: 7755 | W5: 799540.59 | X5: 751956.38 | Y5: 23986.09 | Z5: 775554.5 | AA5: 0.03 | AB5: 0 | AC5: 0 | AD5: #DIV/0! | AE5: 767010.59 | AF5: 740575.58 | AG5: 0.0345 | AH5: 3935 | AI5: 4190 | AJ5: -0.0648 | AK5: 27093.9 | AL5: 28727.6 | AM5: -0.0603 | AN5: 1495.1 | AO5: 981.32 | AP5: 0.3436 | AQ5: 6 | AR5: 1080 | AS5: -179 | AT5: 5406.93 | AU5: 0 | AV5: 3121.1 | AW5: 4366 | AX5: 427 | AY5: 0 | AZ5: 0 | BA5: 0 | BB5: 457.68 | BC5: 246 | BD5: 0 | BE5: 0 | BF5: 405 | BG5: 0 | BH5: 0 | BI5: 0 | BJ5: 3777 | BK5: 0 | BL5: 0 | BM5: 0 | BN5: 0 | BO5: 0 | BP5: 0 | BQ5: 18206.71 | BR5: 5406.93 | BS5: 457.68 | BT5: 0.0242 | BU5: 0.2424 | BV5: 0.7591 | BW5: 5779 | BX5: 3.1503 | BY5: 1810 | BZ5: 135 | CA5: 1945 | CB5: 2159 | CC5: 0.3365 | CD5: 0 | CF5: 0 | CG5: 0 | CH5: 88711.73 | CI5: 1676 | CJ5: 2 | CK5: 23
A6: 46077 | B6: 707 | C6: 199 | D6: 3785 | E6: 39 | F6: 498 | G6: 699 | H6: 95 | I6: 125 | J6: 2686 | K6: 29064 | L6: 120843 | M6: 59351 | N6: 0.2815 | O6: 146 | P6: 0.2405 | Q6: 1.4 | R6: 243 | S6: 173 | T6: 1.2 | U6: 625 | V6: 61492 | W6: 1175025.7 | X6: 1108281.9 | Y6: 63427.47 | Z6: 1111598.2 | AA6: 0.054 | AB6: 1 | AC6: 0 | AD6: 1 | AE6: 1086922.3 | AF6: 1029615.4 | AG6: 0.0527 | AH6: 14221.23 | AI6: 10874.82 | AJ6: 0.2353 | AK6: 71861.15 | AL6: 69691.8 | AM6: 0.0302 | AN6: 2018 | AO6: 1416.17 | AP6: 0.2982 | AQ6: 2 | AR6: 0 | AS6: 1 | AT6: 2417.95 | AU6: 0 | AV6: 3828.77 | AW6: 4504 | AX6: 457 | AY6: 0 | AZ6: 0 | BA6: 0 | BB6: 471.85 | BC6: 348 | BD6: 0 | BE6: 0 | BF6: 497 | BG6: 0 | BH6: 0 | BI6: 0 | BJ6: 3603 | BK6: 0 | BL6: 0 | BM6: 0 | BN6: 0 | BO6: 0 | BP6: 0 | BQ6: 16127.57 | BR6: 2417.95 | BS6: 471.85 | BT6: 0.0146 | BU6: 0.1335 | BV6: 0.2543 | BW6: 47300 | BX6: 0.341 | BY6: 2912 | BZ6: 119 | CA6: 3031 | CB6: 5708 | CC6: 0.0641 | CD6: 0 | CF6: 0 | CG6: 0 | CH6: 93016.97 | CI6: 38561 | CJ6: 2 | CK6: 24
A7: 46078 | B7: 826 | C7: 213 | D7: 3611 | E7: 36 | F7: 481 | G7: 657 | H7: 97 | I7: 121 | J7: 2548 | K7: 27687 | L7: 92719 | M7: 75437 | N7: 0.2579 | O7: 130 | P7: 0.2986 | Q7: 1.4 | R7: 193 | S7: 141 | T7: 1.1 | U7: 778 | V7: 17282 | W7: 873983.42 | X7: 822652.93 | Y7: 17252.13 | Z7: 856731.3 | AA7: 0.0197 | AB7: 0 | AC7: 0 | AD7: #DIV/0! | AE7: 840574.91 | AF7: 823468.46 | AG7: 0.0204 | AH7: 15722.08 | AI7: 15147.22 | AJ7: 0.0366 | AK7: 17582.43 | AL7: 18115.62 | AM7: -0.0303 | AN7: 100 | AO7: 0 | AP7: 1 | AQ7: 4 | AR7: 0 | AS7: 1 | AT7: 3906.86 | AU7: 0 | AV7: 2830.51 | AW7: 4518 | AX7: 580 | AY7: 0 | AZ7: 0 | BA7: 0 | BB7: 271.96 | BC7: 318 | BD7: 0 | BE7: 0 | BF7: 291 | BG7: 0 | BH7: 0 | BI7: 0 | BJ7: 4701 | BK7: 0 | BL7: 0 | BM7: 0 | BN7: 0 | BO7: 0 | BP7: 0 | BQ7: 17417.33 | BR7: 3906.86 | BS7: 271.96 | BT7: 0.0212 | BU7: 0.1879 | BV7: 1.0096 | BW7: -165 | BX7: -105.4286 | BY7: 2235 | BZ7: 151 | CA7: 2385 | CB7: 1553 | CC7: -14.439 | CD7: 0 | CF7: 0 | CG7: 0 | CH7: 96459.38 | CI7: -4104 | CJ7: 2 | CK7: 25
A8: 46079 | B8: 594 | C8: 172 | D8: 3223 | E8: 52 | F8: 437 | G8: 634 | H8: 108 | I8: 146 | J8: 2304 | K8: 23238 | L8: 96473 | M8: 89750 | N8: 0.2896 | O8: 135 | P8: 0.2409 | Q8: 1.5 | R8: 221 | S8: 152 | T8: 1.1 | U8: 831 | V8: 6723 | W8: 853298.63 | X8: 804306.43 | Y8: 13146.22 | Z8: 840152.41 | AA8: 0.0154 | AB8: 60 | AC8: 0 | AD8: 1 | AE8: 821477.24 | AF8: 808905.75 | AG8: 0.0153 | AH8: 18235.59 | AI8: 19190 | AJ8: -0.0523 | AK8: 13524.8 | AL8: 12056.66 | AM8: 0.1086 | AN8: 0 | AO8: 0 | AP8: #DIV/0! | AQ8: 1 | AR8: 0 | AS8: 1 | AT8: 3076.5 | AU8: 0 | AV8: 3710.2 | AW8: 3784 | AX8: 528 | AY8: 0 | AZ8: 0 | BA8: 0 | BB8: 104.46 | BC8: 346 | BD8: 0 | BE8: 0 | BF8: 424 | BG8: 0 | BH8: 0 | BI8: 0 | BJ8: 4112.5 | BK8: 0 | BL8: 0 | BM8: 0 | BN8: 0 | BO8: 0 | BP8: 0 | BQ8: 16085.66 | BR8: 3076.5 | BS8: 104.46 | BT8: 0.02 | BU8: 0.1667 | BV8: 1.2236 | BW8: -2939 | BX8: -5.4724 | BY8: 2325 | BZ8: 180 | CA8: 2504 | CB8: 1183 | CC8: -0.852 | CD8: 0 | CF8: 0 | CG8: 0 | CH8: 94316.75 | CI8: -6627 | CJ8: 2 | CK8: 26
A9: 46080 | B9: 268 | C9: 89 | D9: 2890 | E9: 16 | F9: 352 | G9: 519 | H9: 92 | I9: 519 | J9: 2122 | K9: 12300 | L9: 94962 | M9: 93643 | N9: 0.3321 | O9: 138 | P9: 0.1295 | Q9: 1.5 | R9: 270 | S9: 183 | T9: 1.3 | U9: 1018 | V9: 1319 | W9: 742129.38 | X9: 692850.77 | Y9: 11032.04 | Z9: 731097.35 | AA9: 0.0149 | AB9: 0 | AC9: 0 | AD9: #DIV/0! | AE9: 734752.98 | AF9: 724516.45 | AG9: 0.0139 | AH9: 2734.5 | AI9: 1846.5 | AJ9: 0.3247 | AK9: 4639.9 | AL9: 4734.4 | AM9: -0.0204 | AN9: 0 | AO9: 0 | AP9: #DIV/0! | AQ9: 2 | AR9: 0 | AS9: 1 | AT9: 2605.21 | AU9: 0 | AV9: 2664.5 | AW9: 3699 | AX9: 340 | AY9: 0 | AZ9: 0 | BA9: 0 | BB9: 208.11 | BC9: 249 | BD9: 0 | BE9: 0 | BF9: 6 | BG9: 0 | BH9: 0 | BI9: 0 | BJ9: 2075 | BK9: 0 | BL9: 0 | BM9: 0 | BN9: 0 | BO9: 0 | BP9: 0 | BQ9: 11846.82 | BR9: 2605.21 | BS9: 208.11 | BT9: 0.0171 | BU9: 0.1248 | BV9: 1.0739 | BW9: -815 | BX9: -14.5398 | BY9: 2289 | BZ9: 187 | CA9: 2476 | CB9: 993 | CC9: -3.0387 | CD9: 0 | CF9: 0 | CG9: 0 | CH9: 96202.4 | CI9: -4284 | CJ9: 2 | CK9: 27
A10: 46081 | B10: 717 | C10: 231 | D10: 3515 | E10: 91 | F10: 515 | G10: 679 | H10: 98 | I10: 120 | J10: 2404 | K10: 30310 | L10: 103745 | M10: 68336 | N10: 0.3222 | O10: 131 | P10: 0.2922 | Q10: 1.3 | R10: 201 | S10: 153 | T10: 1.2 | U10: 697 | V10: 35409 | W10: 913539.63 | X10: 851449.64 | Y10: 27029.51 | Z10: 886510.11 | AA10: 0.0296 | AB10: 1 | AC10: 0 | AD10: 1 | AE10: 893340.12 | AF10: 864325.06 | AG10: 0.0325 | AH10: 7245.31 | AI10: 8340 | AJ10: -0.1511 | AK10: 12950.2 | AL10: 13845.05 | AM10: -0.0691 | AN10: 0 | AO10: 0 | AP10: #DIV/0! | AQ10: 3 | AR10: 0 | AS10: 1 | AT10: 2251.1 | AU10: 0 | AV10: 2762.09 | AW10: 4033 | AX10: 395 | AY10: 0 | AZ10: 0 | BA10: 0 | BB10: 61.05 | BC10: 299 | BD10: 0 | BE10: 0 | BF10: 0 | BG10: 0 | BH10: 0 | BI10: 0 | BJ10: 5353.5 | BK10: 0 | BL10: 0 | BM10: 0 | BN10: 0 | BO10: 0 | BP10: 0 | BQ10: 15154.74 | BR10: 2251.1 | BS10: 61.05 | BT10: 0.0178 | BU10: 0.1461 | BV10: 0.5607 | BW10: 11875 | BX10: 1.2762 | BY10: 2500 | BZ10: 137 | CA10: 2637 | CB10: 2433 | CC10: 0.2221 | CD10: 0 | CF10: 0 | CG10: 0 | CH10: 113632.87 | CI10: 6805 | CJ10: 2 | CK10: 28
A11: 46082 | B11: {=INDEX('jiliarena_日报_底稿'!$A$3:$N$34,MATCH($A11,'jiliarena_日报_底稿'!$A$3:$A$34,0),MATCH(B$3,'jiliarena_日报_底稿'!$A$3:$N$3,0))} -> 1098 | C11: {=INDEX('jiliarena_日报_底稿'!$A$3:$N$34,MATCH($A11,'jiliarena_日报_底稿'!$A$3:$A$34,0),MATCH(C$3,'jiliarena_日报_底稿'!$A$3:$N$3,0))} -> 625 | D11: {=INDEX('jiliarena_日报_底稿'!$A$3:$N$34,MATCH($A11,'jiliarena_日报_底稿'!$A$3:$A$34,0),MATCH(D$3,'jiliarena_日报_底稿'!$A$3:$N$3,0))} -> 4268 | E11: 178 | F11: {=INDEX('jiliarena_日报_底稿'!$A$3:$N$34,MATCH($A11,'jiliarena_日报_底稿'!$A$3:$A$34,0),MATCH(F$3,'jiliarena_日报_底稿'!$A$3:$N$3,0))} -> 928 | G11: =SUMIFS('渠道充值成功率_底稿'!$F:$F,'渠道充值成功率_底稿'!$A:$A,A11) -> 1251 | H11: {=INDEX('jiliarena_日报_底稿'!$A$3:$N$34,MATCH($A11,'jiliarena_日报_底稿'!$A$3:$A$34,0),MATCH(H$3,'jiliarena_日报_底稿'!$A$3:$N$3,0))} -> 189 | I11: 247 | J11: {=INDEX('jiliarena_日报_底稿'!$A$3:$N$34,MATCH($A11,'jiliarena_日报_底稿'!$A$3:$A$34,0),MATCH(J$3,'jiliarena_日报_底稿'!$A$3:$N$3,0))} -> 3186 | K11: =SUMIFS('渠道充值成功率_底稿'!$J:$J,'渠道充值成功率_底稿'!$A:$A,$A11) -> 87527 | L11: {=INDEX('jiliarena_日报_底稿'!$A$3:$N$34,MATCH($A11,'jiliarena_日报_底稿'!$A$3:$A$34,0),MATCH(L$3,'jiliarena_日报_底稿'!$A$3:$N$3,0))} -> 186941 | M11: {=INDEX('jiliarena_日报_底稿'!$P$2:$DS$34,MATCH($A11,'jiliarena_日报_底稿'!$P$2:$P$34,0),MATCH($M$3,'jiliarena_日报_底稿'!$P$3:$DS$3,0))} -> 131003 | N11: =IF(C11="","",ROUND(C11/B11,4)) -> 0.5692 | O11: =IF(K11="","",ROUND(K11/C11,0)) -> 140 | P11: =IF(L11="","",ROUND(K11/L11,6)) -> 0.468207 | Q11: =IF(G11="","",ROUND(G11/F11,1)) -> 1.3 | R11: =IF(L11="","",ROUND(L11/F11,0)) -> 201 | S11: =IF(L11="","",ROUND(L11/G11,0)) -> 149 | T11: =IF(S11="","",ROUND(S11/O11,1)) -> 1.1 | U11: =IF(M11="","",ROUND(M11/H11,0)) -> 693 | V11: =IF(M11="","",L11-M11) -> 55938 | W11: =AB11+AE11+AH11+AK11+AN11+AQ11 -> 1794608.7 | X11: {=index('jiliarena_日报_底稿'!$P$2:$DS$34,match($A11,'jiliarena_日报_底稿'!$P$2:$P$34,0),match("电子有效投注",'jiliarena_日报_底稿'!$P$3:$DS$3,0))+index('jiliarena_日报_底稿'!$P$2:$DS$34,match($A11,'jiliarena_日报_底稿'!$P$2:$P$34,0),match("真人有效投注",'jiliarena_日报_底稿'!$P$3:$DS$3,0))+index('jiliarena_日报_底稿'!$P$2:$DS$34,match($A11,'jiliarena_日报_底稿'!$P$2:$P$34,0),match("彩票有效投注",'jiliarena_日报_底稿'!$P$3:$DS$3,0))+index('jiliarena_日报_底稿'!$P$2:$DS$34,match($A11,'jiliarena_日报_底稿'!$P$2:$P$34,0),match("棋牌有效投注",'jiliarena_日报_底稿'!$P$3:$DS$3,0))+index('jiliarena_日报_底稿'!$P$2:$DS$34,match($A11,'jiliarena_日报_底稿'!$P$2:$P$34,0),match("捕鱼有效投注",'jiliarena_日报_底稿'!$P$3:$DS$3,0))+index('jiliarena_日报_底稿'!$P$2:$DS$34,match($A11,'jiliarena_日报_底稿'!$P$2:$P$34,0),match("体育有效投注",'jiliarena_日报_底稿'!$P$3:$DS$3,0))+index('jiliarena_日报_底稿'!$P$2:$DS$34,match($A11,'jiliarena_日报_底稿'!$P$2:$P$34,0),match("盘口彩票有效投注",'jiliarena_日报_底稿'!$P$3:$DS$3,0))} -> 1674018.2 | Y11: =AB11+AE11+AH11+AK11+AN11+AQ11-AR11-AO11-AL11-AI11-AF11-AC11 -> 81864.325 | Z11: =AC11+AF11+AI11+AL11+AO11+AR11 -> 1712744.4 | AA11: =IFERROR(ROUND(1-(Z11/W11),6),"") -> 0.045617 | AB11: {=INDEX('jiliarena_日报_底稿'!$P$2:$DS$34,MATCH($A11,'jiliarena_日报_底稿'!$P$2:$P$34,0),MATCH(AB$3,'jiliarena_日报_底稿'!$P$3:$DS$3,0))} -> 450 | AC11: {=INDEX('jiliarena_日报_底稿'!$P$2:$DS$34,MATCH($A11,'jiliarena_日报_底稿'!$P$2:$P$34,0),MATCH(AC$3,'jiliarena_日报_底稿'!$P$3:$DS$3,0))} -> 386.15 | AD11: =IF(AC11="","",ROUND((1-(AC11/AB11)),6)) -> 0.141889 | AE11: {=INDEX('jiliarena_日报_底稿'!$P$2:$DS$34,MATCH($A11,'jiliarena_日报_底稿'!$P$2:$P$34,0),MATCH(AE$3,'jiliarena_日报_底稿'!$P$3:$DS$3,0))} -> 1772693 | AF11: {=INDEX('jiliarena_日报_底稿'!$P$2:$DS$34,MATCH($A11,'jiliarena_日报_底稿'!$P$2:$P$34,0),MATCH(AF$3,'jiliarena_日报_底稿'!$P$3:$DS$3,0))} -> 1694500.6 | AG11: =IF(AF11="","",ROUND((1-(AF11/AE11)),6)) -> 0.044109 | AH11: {=INDEX('jiliarena_日报_底稿'!$P$2:$DS$34,MATCH($A11,'jiliarena_日报_底稿'!$P$2:$P$34,0),MATCH(AH$3,'jiliarena_日报_底稿'!$P$3:$DS$3,0))} -> 8456.8 | AI11: {=INDEX('jiliarena_日报_底稿'!$P$2:$DS$34,MATCH($A11,'jiliarena_日报_底稿'!$P$2:$P$34,0),MATCH(AI$3,'jiliarena_日报_底稿'!$P$3:$DS$3,0))} -> 5555 | AJ11: =IF(AI11="","",ROUND((1-(AI11/AH11)),6)) -> 0.343132 | AK11: {=INDEX('jiliarena_日报_底稿'!$P$2:$DS$34,MATCH($A11,'jiliarena_日报_底稿'!$P$2:$P$34,0),MATCH(AK$3,'jiliarena_日报_底稿'!$P$3:$DS$3,0))} -> 13004.9 | AL11: {=INDEX('jiliarena_日报_底稿'!$P$2:$DS$34,MATCH($A11,'jiliarena_日报_底稿'!$P$2:$P$34,0),MATCH(AL$3,'jiliarena_日报_底稿'!$P$3:$DS$3,0))} -> 12302.7 | AM11: =IF(AL11="","",ROUND((1-(AL11/AK11)),6)) -> 0.053995 | AN11: {=INDEX('jiliarena_日报_底稿'!$P$2:$DS$34,MATCH($A11,'jiliarena_日报_底稿'!$P$2:$P$34,0),MATCH(AN$3,'jiliarena_日报_底稿'!$P$3:$DS$3,0))} -> 0 | AO11: {=INDEX('jiliarena_日报_底稿'!$P$2:$DS$34,MATCH($A11,'jiliarena_日报_底稿'!$P$2:$P$34,0),MATCH(AO$3,'jiliarena_日报_底稿'!$P$3:$DS$3,0))} -> 0 | AP11: =IF(AO11="","",ROUND((1-(AO11/AN11)),6)) -> #DIV/0! | AQ11: {=INDEX('jiliarena_日报_底稿'!$P$2:$DS$34,MATCH($A11,'jiliarena_日报_底稿'!$P$2:$P$34,0),MATCH(AQ$3,'jiliarena_日报_底稿'!$P$3:$DS$3,0))} -> 4 | AR11: {=INDEX('jiliarena_日报_底稿'!$P$2:$DS$34,MATCH($A11,'jiliarena_日报_底稿'!$P$2:$P$34,0),MATCH(AR$3,'jiliarena_日报_底稿'!$P$3:$DS$3,0))} -> 0 | AS11: =IF(AR11="","",ROUND((1-(AR11/AQ11)),6)) -> 1 | AT11: =SUMIFS('jiliarena_活动分析数据_底稿'!$K:$K,'jiliarena_活动分析数据_底稿'!$B:$B,$A11,'jiliarena_活动分析数据_底稿'!$L:$L,AT$3) -> 2895.46 | AU11: =SUMIFS('jiliarena_活动分析数据_底稿'!$K:$K,'jiliarena_活动分析数据_底稿'!$B:$B,$A11,'jiliarena_活动分析数据_底稿'!$L:$L,AU$3) -> 0 | AV11: =SUMIFS('jiliarena_活动分析数据_底稿'!$K:$K,'jiliarena_活动分析数据_底稿'!$B:$B,$A11,'jiliarena_活动分析数据_底稿'!$L:$L,AV$3) -> 734.22 | AW11: =SUMIFS('jiliarena_活动分析数据_底稿'!$K:$K,'jiliarena_活动分析数据_底稿'!$B:$B,$A11,'jiliarena_活动分析数据_底稿'!$L:$L,AW$3) -> 4988 | AX11: =SUMIFS('jiliarena_活动分析数据_底稿'!$K:$K,'jiliarena_活动分析数据_底稿'!$B:$B,$A11,'jiliarena_活动分析数据_底稿'!$L:$L,AX$3) -> 572 | AY11: =SUMIFS('jiliarena_活动分析数据_底稿'!$K:$K,'jiliarena_活动分析数据_底稿'!$B:$B,$A11,'jiliarena_活动分析数据_底稿'!$L:$L,AY$3) -> 0 | AZ11: =SUMIFS('jiliarena_活动分析数据_底稿'!$K:$K,'jiliarena_活动分析数据_底稿'!$B:$B,$A11,'jiliarena_活动分析数据_底稿'!$L:$L,AZ$3) -> 0 | BA11: =SUMIFS('jiliarena_活动分析数据_底稿'!$K:$K,'jiliarena_活动分析数据_底稿'!$B:$B,$A11,'jiliarena_活动分析数据_底稿'!$L:$L,BA$3) -> 0 | ... BP11: =SUMIFS('jiliarena_活动分析数据_底稿'!$K:$K,'jiliarena_活动分析数据_底稿'!$B:$B,$A11,'jiliarena_活动分析数据_底稿'!$L:$L,BP$3) -> 0 | BQ11: =SUM(AT11:BP11) -> 32032.43 | BR11: =AT11 -> 2895.46 | BS11: =BB11 -> 381.75 | BT11: =iferror(IF(BQ11="","",ROUND(BQ11/X11,6)),"") -> 0.019135 | BU11: =iferror(BQ11/L11,"") -> 0.17135048 | BV11: =iferror(BQ11/Y11,"") -> 0.3912868 | BW11: =IF(BQ11="","",Y11-BQ11) -> 49831.895 | BX11: =iferror(BQ11/BW11,"") -> 0.64280979 | BY11: =L11*$BY$1 -> 4505.2781 | BZ11: =M11*$BZ$1 -> 262.006 | CA11: =BY11+BZ11 -> 4767.2841 | CB11: =IF(Y11="","",ROUND(Y11*9%,0)) -> 7368 | CC11: =iferror(CA11/BW11,"") -> 0.095667325 | CD11: {=index('jiliarena_日报_底稿'!$P$3:$DS$34,match(A11,'jiliarena_日报_底稿'!$P$3:$P$34,0),match("综合性分红",'jiliarena_日报_底稿'!$P$3:$DS$3,0))} -> 0 | CF11: {=INDEX('jiliarena_日报_底稿'!$P$2:$DS$34,MATCH($A11,'jiliarena_日报_底稿'!$P$2:$P$34,0),MATCH(CF$3,'jiliarena_日报_底稿'!$P$3:$DS$3,0))} -> 0 | CG11: {=-INDEX('jiliarena_日报_底稿'!$P$2:$DS$34,MATCH($A11,'jiliarena_日报_底稿'!$P$2:$P$34,0),MATCH(CG$3,'jiliarena_日报_底稿'!$P$3:$DS$3,0))} -> 0 | CH11: {=INDEX('jiliarena_日报_底稿'!$P$2:$DS$34,MATCH($A11,'jiliarena_日报_底稿'!$P$2:$P$34,0),MATCH(CH$3,'jiliarena_日报_底稿'!$P$3:$DS$3,0))} -> 119399.8 | CI11: =IF(CA11="","",BW11-CA11-CD11-CB11) -> 37696.611 | CJ11: =IFERROR(month(A11),"") -> 3 | CK11: =IFERROR(DAY(A11),"") -> 1
A12: SUB total | B12: =SUM(B5:B11) -> 4833 | C12: =SUM(C5:C11) -> 1690 | D12: =SUM(D5:D11) -> 24785 | E12: =SUM(E5:E11) -> 445 | F12: =SUM(F5:F11) -> 3630 | G12: =SUM(G5:G11) -> 5017 | H12: =SUM(H5:H11) -> 773 | I12: =SUM(I5:I11) -> 1410 | ... M12: =SUM(M5:M11) -> 584868 | N12: =IF(C12="","",ROUND(C12/B12,4)) -> 0.3497 | O12: =IF(K12="","",ROUND(K12/C12,0)) -> 137 | P12: =IF(L12="","",ROUND(K12/L12,6)) -> 0.300583 | Q12: =IF(G12="","",ROUND(G12/F12,1)) -> 1.4 | R12: =IF(L12="","",ROUND(L12/F12,0)) -> 212 | S12: =IF(L12="","",ROUND(L12/G12,0)) -> 154 | T12: =IF(S12="","",ROUND(S12/O12,1)) -> 1.1 | U12: =IF(M12="","",ROUND(M12/H12,0)) -> 757 | V12: =IF(M12="","",L12-M12) -> 185918 | W12: =SUM(W5:W11) -> 7152126.1 | X12: =SUM(X5:X11) -> 6705516.3 | Y12: =SUM(Y5:Y11) -> 237737.79 | Z12: =SUM(Z5:Z11) -> 6914388.3 | AA12: =IFERROR(ROUND(1-(Z12/W12),6),"") -> 0.03324 | AB12: =SUM(AB5:AB11) -> 512 | AC12: =SUM(AC5:AC11) -> 386.15 | AD12: =IF(AC12="","",ROUND((1-(AC12/AB12)),6)) -> 0.245801 | AE12: =SUM(AE5:AE11) -> 6916771.2 | AF12: =SUM(AF5:AF11) -> 6685907.3 | AG12: =IF(AF12="","",ROUND((1-(AF12/AE12)),6)) -> 0.033377 | AH12: =SUM(AH5:AH11) -> 70550.51 | AI12: =SUM(AI5:AI11) -> 65143.54 | AJ12: =IF(AI12="","",ROUND((1-(AI12/AH12)),6)) -> 0.07664 | AK12: =SUM(AK5:AK11) -> 160657.28 | AL12: =SUM(AL5:AL11) -> 159473.83 | AM12: =IF(AL12="","",ROUND((1-(AL12/AK12)),6)) -> 0.007366 | AN12: =SUM(AN5:AN11) -> 3613.1 | AO12: =SUM(AO5:AO11) -> 2397.49 | AP12: =IF(AO12="","",ROUND((1-(AO12/AN12)),6)) -> 0.336445 | AQ12: =SUM(AQ5:AQ11) -> 22 | AR12: =SUM(AR5:AR11) -> 1080 | AS12: =IF(AR12="","",ROUND((1-(AR12/AQ12)),6)) -> -48.090909 | AT12: =SUM(AT5:AT11) -> 22560.01 | AU12: =SUM(AU5:AU11) -> 0 | AV12: =SUM(AV5:AV11) -> 19651.39 | AW12: =SUM(AW5:AW11) -> 29892 | AX12: =SUM(AX5:AX11) -> 3299 | AY12: =SUM(AY5:AY11) -> 0 | AZ12: =SUM(AZ5:AZ11) -> 0 | BA12: =SUM(BA5:BA11) -> 0 | ... BS12: =SUM(BS5:BS11) -> 1956.86 | BT12: =iferror(IF(BQ12="","",ROUND(BQ12/X12,6)),"") -> 0.01892 | BU12: =iferror(BQ12/L12,"") -> 0.16459985 | BV12: =iferror(BQ12/Y12,"") -> 0.53366048 | BW12: =IF(BQ12="","",Y12-BQ12) -> 110866.52 | BX12: =iferror(BQ12/BW12,"") -> 1.1443604 | BY12: =L12*$BY$1 -> 18575.943 | BZ12: =M12*$BZ$1 -> 1169.736 | CA12: =BY12+BZ12 -> 19745.679 | CB12: =IF(Y12="","",ROUND(Y12*9%,0)) -> 21396 | CC12: =iferror(CA12/BW12,"") -> 0.17810316 | CD12: =SUM(CD5:CD11) -> 0 | CE12: =SUM(CE5:CE11) -> 0 | CF12: =SUM(CF5:CF11) -> 0 | CG12: =SUM(CG5:CG11) -> 0 | CH12: =SUM(CH5:CH11) -> 701739.9 | CI12: =IF(CA12="","",BW12-CA12-CD12-CB12) -> 69724.846 | CJ12: =IFERROR(month(A12),"") | CK12: =IFERROR(DAY(A12),"")
A13: =A11+1 -> 46083 | B13: {=INDEX('jiliarena_日报_底稿'!$A$3:$N$34,MATCH($A13,'jiliarena_日报_底稿'!$A$3:$A$34,0),MATCH(B$3,'jiliarena_日报_底稿'!$A$3:$N$3,0))} -> 197 | C13: {=INDEX('jiliarena_日报_底稿'!$A$3:$N$34,MATCH($A13,'jiliarena_日报_底稿'!$A$3:$A$34,0),MATCH(C$3,'jiliarena_日报_底稿'!$A$3:$N$3,0))} -> 140 | D13: {=INDEX('jiliarena_日报_底稿'!$A$3:$N$34,MATCH($A13,'jiliarena_日报_底稿'!$A$3:$A$34,0),MATCH(D$3,'jiliarena_日报_底稿'!$A$3:$N$3,0))} -> 3109 | E13: 23 | F13: {=INDEX('jiliarena_日报_底稿'!$A$3:$N$34,MATCH($A13,'jiliarena_日报_底稿'!$A$3:$A$34,0),MATCH(F$3,'jiliarena_日报_底稿'!$A$3:$N$3,0))} -> 423 | G13: =SUMIFS('渠道充值成功率_底稿'!$F:$F,'渠道充值成功率_底稿'!$A:$A,A13) -> 599 | H13: {=INDEX('jiliarena_日报_底稿'!$A$3:$N$34,MATCH($A13,'jiliarena_日报_底稿'!$A$3:$A$34,0),MATCH(H$3,'jiliarena_日报_底稿'!$A$3:$N$3,0))} -> 96 | I13: 121 | J13: {=INDEX('jiliarena_日报_底稿'!$A$3:$N$34,MATCH($A13,'jiliarena_日报_底稿'!$A$3:$A$34,0),MATCH(J$3,'jiliarena_日报_底稿'!$A$3:$N$3,0))} -> 2227 | K13: =SUMIFS('渠道充值成功率_底稿'!$J:$J,'渠道充值成功率_底稿'!$A:$A,$A13) -> 19695 | L13: {=INDEX('jiliarena_日报_底稿'!$A$3:$N$34,MATCH($A13,'jiliarena_日报_底稿'!$A$3:$A$34,0),MATCH(L$3,'jiliarena_日报_底稿'!$A$3:$N$3,0))} -> 90451 | M13: {=INDEX('jiliarena_日报_底稿'!$P$2:$DS$34,MATCH($A13,'jiliarena_日报_底稿'!$P$2:$P$34,0),MATCH($M$3,'jiliarena_日报_底稿'!$P$3:$DS$3,0))} -> 66903 | N13: =IF(C13="","",ROUND(C13/B13,4)) -> 0.7107 | O13: =IF(K13="","",ROUND(K13/C13,0)) -> 141 | P13: =IF(L13="","",ROUND(K13/L13,6)) -> 0.217742 | Q13: =IF(G13="","",ROUND(G13/F13,1)) -> 1.4 | R13: =IF(L13="","",ROUND(L13/F13,0)) -> 214 | S13: =IF(L13="","",ROUND(L13/G13,0)) -> 151 | T13: =IF(S13="","",ROUND(S13/O13,1)) -> 1.1 | U13: =IF(M13="","",ROUND(M13/H13,0)) -> 697 | V13: =IF(M13="","",L13-M13) -> 23548 | W13: =AB13+AE13+AH13+AK13+AN13+AQ13 -> 889864.08 | X13: {=index('jiliarena_日报_底稿'!$P$2:$DS$34,match($A13,'jiliarena_日报_底稿'!$P$2:$P$34,0),match("电子有效投注",'jiliarena_日报_底稿'!$P$3:$DS$3,0))+index('jiliarena_日报_底稿'!$P$2:$DS$34,match($A13,'jiliarena_日报_底稿'!$P$2:$P$34,0),match("真人有效投注",'jiliarena_日报_底稿'!$P$3:$DS$3,0))+index('jiliarena_日报_底稿'!$P$2:$DS$34,match($A13,'jiliarena_日报_底稿'!$P$2:$P$34,0),match("彩票有效投注",'jiliarena_日报_底稿'!$P$3:$DS$3,0))+index('jiliarena_日报_底稿'!$P$2:$DS$34,match($A13,'jiliarena_日报_底稿'!$P$2:$P$34,0),match("棋牌有效投注",'jiliarena_日报_底稿'!$P$3:$DS$3,0))+index('jiliarena_日报_底稿'!$P$2:$DS$34,match($A13,'jiliarena_日报_底稿'!$P$2:$P$34,0),match("捕鱼有效投注",'jiliarena_日报_底稿'!$P$3:$DS$3,0))+index('jiliarena_日报_底稿'!$P$2:$DS$34,match($A13,'jiliarena_日报_底稿'!$P$2:$P$34,0),match("体育有效投注",'jiliarena_日报_底稿'!$P$3:$DS$3,0))+index('jiliarena_日报_底稿'!$P$2:$DS$34,match($A13,'jiliarena_日报_底稿'!$P$2:$P$34,0),match("盘口彩票有效投注",'jiliarena_日报_底稿'!$P$3:$DS$3,0))} -> 830058.92 | Y13: =AB13+AE13+AH13+AK13+AN13+AQ13-AR13-AO13-AL13-AI13-AF13-AC13 -> 26535.125 | Z13: =AC13+AF13+AI13+AL13+AO13+AR13 -> 863328.95 | AA13: =IFERROR(ROUND(1-(Z13/W13),6),"") -> 0.029819 | AB13: {=INDEX('jiliarena_日报_底稿'!$P$2:$DS$34,MATCH($A13,'jiliarena_日报_底稿'!$P$2:$P$34,0),MATCH(AB$3,'jiliarena_日报_底稿'!$P$3:$DS$3,0))} -> 0 | AC13: {=INDEX('jiliarena_日报_底稿'!$P$2:$DS$34,MATCH($A13,'jiliarena_日报_底稿'!$P$2:$P$34,0),MATCH(AC$3,'jiliarena_日报_底稿'!$P$3:$DS$3,0))} -> 0 | AD13: =IF(AC13="","",ROUND((1-(AC13/AB13)),6)) -> #DIV/0! | AE13: {=INDEX('jiliarena_日报_底稿'!$P$2:$DS$34,MATCH($A13,'jiliarena_日报_底稿'!$P$2:$P$34,0),MATCH(AE$3,'jiliarena_日报_底稿'!$P$3:$DS$3,0))} -> 853219.28 | AF13: {=INDEX('jiliarena_日报_底稿'!$P$2:$DS$34,MATCH($A13,'jiliarena_日报_底稿'!$P$2:$P$34,0),MATCH(AF$3,'jiliarena_日报_底稿'!$P$3:$DS$3,0))} -> 821850.07 | AG13: =IF(AF13="","",ROUND((1-(AF13/AE13)),6)) -> 0.036766 | AH13: {=INDEX('jiliarena_日报_底稿'!$P$2:$DS$34,MATCH($A13,'jiliarena_日报_底稿'!$P$2:$P$34,0),MATCH(AH$3,'jiliarena_日报_底稿'!$P$3:$DS$3,0))} -> 931.05 | AI13: {=INDEX('jiliarena_日报_底稿'!$P$2:$DS$34,MATCH($A13,'jiliarena_日报_底稿'!$P$2:$P$34,0),MATCH(AI$3,'jiliarena_日报_底稿'!$P$3:$DS$3,0))} -> 717.6 | AJ13: =IF(AI13="","",ROUND((1-(AI13/AH13)),6)) -> 0.229257 | AK13: {=INDEX('jiliarena_日报_底稿'!$P$2:$DS$34,MATCH($A13,'jiliarena_日报_底稿'!$P$2:$P$34,0),MATCH(AK$3,'jiliarena_日报_底稿'!$P$3:$DS$3,0))} -> 35624.75 | AL13: {=INDEX('jiliarena_日报_底稿'!$P$2:$DS$34,MATCH($A13,'jiliarena_日报_底稿'!$P$2:$P$34,0),MATCH(AL$3,'jiliarena_日报_底稿'!$P$3:$DS$3,0))} -> 40761.28 | AM13: =IF(AL13="","",ROUND((1-(AL13/AK13)),6)) -> -0.144184 | AN13: {=INDEX('jiliarena_日报_底稿'!$P$2:$DS$34,MATCH($A13,'jiliarena_日报_底稿'!$P$2:$P$34,0),MATCH(AN$3,'jiliarena_日报_底稿'!$P$3:$DS$3,0))} -> 85 | AO13: {=INDEX('jiliarena_日报_底稿'!$P$2:$DS$34,MATCH($A13,'jiliarena_日报_底稿'!$P$2:$P$34,0),MATCH(AO$3,'jiliarena_日报_底稿'!$P$3:$DS$3,0))} -> 0 | AP13: =IF(AO13="","",ROUND((1-(AO13/AN13)),6)) -> 1 | AQ13: {=INDEX('jiliarena_日报_底稿'!$P$2:$DS$34,MATCH($A13,'jiliarena_日报_底稿'!$P$2:$P$34,0),MATCH(AQ$3,'jiliarena_日报_底稿'!$P$3:$DS$3,0))} -> 4 | AR13: {=INDEX('jiliarena_日报_底稿'!$P$2:$DS$34,MATCH($A13,'jiliarena_日报_底稿'!$P$2:$P$34,0),MATCH(AR$3,'jiliarena_日报_底稿'!$P$3:$DS$3,0))} -> 0 | AS13: =IF(AR13="","",ROUND((1-(AR13/AQ13)),6)) -> 1 | AT13: =SUMIFS('jiliarena_活动分析数据_底稿'!$K:$K,'jiliarena_活动分析数据_底稿'!$B:$B,$A13,'jiliarena_活动分析数据_底稿'!$L:$L,AT$3) -> 4082.18 | AU13: =SUMIFS('jiliarena_活动分析数据_底稿'!$K:$K,'jiliarena_活动分析数据_底稿'!$B:$B,$A13,'jiliarena_活动分析数据_底稿'!$L:$L,AU$3) -> 0 | AV13: =SUMIFS('jiliarena_活动分析数据_底稿'!$K:$K,'jiliarena_活动分析数据_底稿'!$B:$B,$A13,'jiliarena_活动分析数据_底稿'!$L:$L,AV$3) -> 523.26 | AW13: =SUMIFS('jiliarena_活动分析数据_底稿'!$K:$K,'jiliarena_活动分析数据_底稿'!$B:$B,$A13,'jiliarena_活动分析数据_底稿'!$L:$L,AW$3) -> 4192 | AX13: =SUMIFS('jiliarena_活动分析数据_底稿'!$K:$K,'jiliarena_活动分析数据_底稿'!$B:$B,$A13,'jiliarena_活动分析数据_底稿'!$L:$L,AX$3) -> 276 | AY13: =SUMIFS('jiliarena_活动分析数据_底稿'!$K:$K,'jiliarena_活动分析数据_底稿'!$B:$B,$A13,'jiliarena_活动分析数据_底稿'!$L:$L,AY$3) -> 0 | AZ13: =SUMIFS('jiliarena_活动分析数据_底稿'!$K:$K,'jiliarena_活动分析数据_底稿'!$B:$B,$A13,'jiliarena_活动分析数据_底稿'!$L:$L,AZ$3) -> 0 | BA13: =SUMIFS('jiliarena_活动分析数据_底稿'!$K:$K,'jiliarena_活动分析数据_底稿'!$B:$B,$A13,'jiliarena_活动分析数据_底稿'!$L:$L,BA$3) -> 0 | ... BP13: =SUMIFS('jiliarena_活动分析数据_底稿'!$K:$K,'jiliarena_活动分析数据_底稿'!$B:$B,$A13,'jiliarena_活动分析数据_底稿'!$L:$L,BP$3) -> 0 | BQ13: =SUM(AT13:BP13) -> 13886.28 | BR13: =AT13 -> 4082.18 | BS13: =BB13 -> 178.84 | BT13: =iferror(IF(BQ13="","",ROUND(BQ13/X13,6)),"") -> 0.016729 | BU13: =iferror(BQ13/L13,"") -> 0.15352268 | BV13: =iferror(BQ13/Y13,"") -> 0.52331692 | BW13: =IF(BQ13="","",Y13-BQ13) -> 12648.845 | BX13: =iferror(BQ13/BW13,"") -> 1.0978299 | BY13: =L13*$BY$1 -> 2179.8691 | BZ13: =M13*$BZ$1 -> 133.806 | CA13: =BY13+BZ13 -> 2313.6751 | CB13: =IF(Y13="","",ROUND(Y13*9%,0)) -> 2388 | CC13: =iferror(CA13/BW13,"") -> 0.18291592 | CD13: {=index('jiliarena_日报_底稿'!$P$3:$DS$34,match(A13,'jiliarena_日报_底稿'!$P$3:$P$34,0),match("综合性分红",'jiliarena_日报_底稿'!$P$3:$DS$3,0))} -> 0 | CF13: {=INDEX('jiliarena_日报_底稿'!$P$2:$DS$34,MATCH($A13,'jiliarena_日报_底稿'!$P$2:$P$34,0),MATCH(CF$3,'jiliarena_日报_底稿'!$P$3:$DS$3,0))} -> 0 | CG13: {=-INDEX('jiliarena_日报_底稿'!$P$2:$DS$34,MATCH($A13,'jiliarena_日报_底稿'!$P$2:$P$34,0),MATCH(CG$3,'jiliarena_日报_底稿'!$P$3:$DS$3,0))} -> 0 | CH13: {=INDEX('jiliarena_日报_底稿'!$P$2:$DS$34,MATCH($A13,'jiliarena_日报_底稿'!$P$2:$P$34,0),MATCH(CH$3,'jiliarena_日报_底稿'!$P$3:$DS$3,0))} -> 120153.84 | CI13: =IF(CA13="","",BW13-CA13-CD13-CB13) -> 7947.1699 | CJ13: =IFERROR(month(A13),"") -> 3 | CK13: =IFERROR(DAY(A13),"") -> 2
A14: =A13+1 -> 46084 | B14: {=INDEX('jiliarena_日报_底稿'!$A$3:$N$34,MATCH($A14,'jiliarena_日报_底稿'!$A$3:$A$34,0),MATCH(B$3,'jiliarena_日报_底稿'!$A$3:$N$3,0))} -> 164 | C14: {=INDEX('jiliarena_日报_底稿'!$A$3:$N$34,MATCH($A14,'jiliarena_日报_底稿'!$A$3:$A$34,0),MATCH(C$3,'jiliarena_日报_底稿'!$A$3:$N$3,0))} -> 106 | D14: {=INDEX('jiliarena_日报_底稿'!$A$3:$N$34,MATCH($A14,'jiliarena_日报_底稿'!$A$3:$A$34,0),MATCH(D$3,'jiliarena_日报_底稿'!$A$3:$N$3,0))} -> 3134 | E14: 15 | F14: {=INDEX('jiliarena_日报_底稿'!$A$3:$N$34,MATCH($A14,'jiliarena_日报_底稿'!$A$3:$A$34,0),MATCH(F$3,'jiliarena_日报_底稿'!$A$3:$N$3,0))} -> 363 | G14: =SUMIFS('渠道充值成功率_底稿'!$F:$F,'渠道充值成功率_底稿'!$A:$A,A14) -> 528 | H14: {=INDEX('jiliarena_日报_底稿'!$A$3:$N$34,MATCH($A14,'jiliarena_日报_底稿'!$A$3:$A$34,0),MATCH(H$3,'jiliarena_日报_底稿'!$A$3:$N$3,0))} -> 69 | I14: 87 | J14: {=INDEX('jiliarena_日报_底稿'!$A$3:$N$34,MATCH($A14,'jiliarena_日报_底稿'!$A$3:$A$34,0),MATCH(J$3,'jiliarena_日报_底稿'!$A$3:$N$3,0))} -> 2295 | K14: =SUMIFS('渠道充值成功率_底稿'!$J:$J,'渠道充值成功率_底稿'!$A:$A,$A14) -> 15685 | L14: {=INDEX('jiliarena_日报_底稿'!$A$3:$N$34,MATCH($A14,'jiliarena_日报_底稿'!$A$3:$A$34,0),MATCH(L$3,'jiliarena_日报_底稿'!$A$3:$N$3,0))} -> 87308 | M14: {=INDEX('jiliarena_日报_底稿'!$P$2:$DS$34,MATCH($A14,'jiliarena_日报_底稿'!$P$2:$P$34,0),MATCH($M$3,'jiliarena_日报_底稿'!$P$3:$DS$3,0))} -> 50169 | N14: =IF(C14="","",ROUND(C14/B14,4)) -> 0.6463 | O14: =IF(K14="","",ROUND(K14/C14,0)) -> 148 | P14: =IF(L14="","",ROUND(K14/L14,6)) -> 0.179651 | Q14: =IF(G14="","",ROUND(G14/F14,1)) -> 1.5 | R14: =IF(L14="","",ROUND(L14/F14,0)) -> 241 | S14: =IF(L14="","",ROUND(L14/G14,0)) -> 165 | T14: =IF(S14="","",ROUND(S14/O14,1)) -> 1.1 | U14: =IF(M14="","",ROUND(M14/H14,0)) -> 727 | V14: =IF(M14="","",L14-M14) -> 37139 | W14: =AB14+AE14+AH14+AK14+AN14+AQ14 -> 676425.27 | X14: {=index('jiliarena_日报_底稿'!$P$2:$DS$34,match($A14,'jiliarena_日报_底稿'!$P$2:$P$34,0),match("电子有效投注",'jiliarena_日报_底稿'!$P$3:$DS$3,0))+index('jiliarena_日报_底稿'!$P$2:$DS$34,match($A14,'jiliarena_日报_底稿'!$P$2:$P$34,0),match("真人有效投注",'jiliarena_日报_底稿'!$P$3:$DS$3,0))+index('jiliarena_日报_底稿'!$P$2:$DS$34,match($A14,'jiliarena_日报_底稿'!$P$2:$P$34,0),match("彩票有效投注",'jiliarena_日报_底稿'!$P$3:$DS$3,0))+index('jiliarena_日报_底稿'!$P$2:$DS$34,match($A14,'jiliarena_日报_底稿'!$P$2:$P$34,0),match("棋牌有效投注",'jiliarena_日报_底稿'!$P$3:$DS$3,0))+index('jiliarena_日报_底稿'!$P$2:$DS$34,match($A14,'jiliarena_日报_底稿'!$P$2:$P$34,0),match("捕鱼有效投注",'jiliarena_日报_底稿'!$P$3:$DS$3,0))+index('jiliarena_日报_底稿'!$P$2:$DS$34,match($A14,'jiliarena_日报_底稿'!$P$2:$P$34,0),match("体育有效投注",'jiliarena_日报_底稿'!$P$3:$DS$3,0))+index('jiliarena_日报_底稿'!$P$2:$DS$34,match($A14,'jiliarena_日报_底稿'!$P$2:$P$34,0),match("盘口彩票有效投注",'jiliarena_日报_底稿'!$P$3:$DS$3,0))} -> 634117.71 | Y14: =AB14+AE14+AH14+AK14+AN14+AQ14-AR14-AO14-AL14-AI14-AF14-AC14 -> 47971.765 | Z14: =AC14+AF14+AI14+AL14+AO14+AR14 -> 628453.51 | AA14: =IFERROR(ROUND(1-(Z14/W14),6),"") -> 0.07092 | AB14: {=INDEX('jiliarena_日报_底稿'!$P$2:$DS$34,MATCH($A14,'jiliarena_日报_底稿'!$P$2:$P$34,0),MATCH(AB$3,'jiliarena_日报_底稿'!$P$3:$DS$3,0))} -> 24 | AC14: {=INDEX('jiliarena_日报_底稿'!$P$2:$DS$34,MATCH($A14,'jiliarena_日报_底稿'!$P$2:$P$34,0),MATCH(AC$3,'jiliarena_日报_底稿'!$P$3:$DS$3,0))} -> 4 | AD14: =IF(AC14="","",ROUND((1-(AC14/AB14)),6)) -> 0.833333 | AE14: {=INDEX('jiliarena_日报_底稿'!$P$2:$DS$34,MATCH($A14,'jiliarena_日报_底稿'!$P$2:$P$34,0),MATCH(AE$3,'jiliarena_日报_底稿'!$P$3:$DS$3,0))} -> 669470.47 | AF14: {=INDEX('jiliarena_日报_底稿'!$P$2:$DS$34,MATCH($A14,'jiliarena_日报_底稿'!$P$2:$P$34,0),MATCH(AF$3,'jiliarena_日报_底稿'!$P$3:$DS$3,0))} -> 622926.2 | AG14: =IF(AF14="","",ROUND((1-(AF14/AE14)),6)) -> 0.069524 | AH14: {=INDEX('jiliarena_日报_底稿'!$P$2:$DS$34,MATCH($A14,'jiliarena_日报_底稿'!$P$2:$P$34,0),MATCH(AH$3,'jiliarena_日报_底稿'!$P$3:$DS$3,0))} -> 2632.5 | AI14: {=INDEX('jiliarena_日报_底稿'!$P$2:$DS$34,MATCH($A14,'jiliarena_日报_底稿'!$P$2:$P$34,0),MATCH(AI$3,'jiliarena_日报_底稿'!$P$3:$DS$3,0))} -> 1491.5 | AJ14: =IF(AI14="","",ROUND((1-(AI14/AH14)),6)) -> 0.433428 | AK14: {=INDEX('jiliarena_日报_底稿'!$P$2:$DS$34,MATCH($A14,'jiliarena_日报_底稿'!$P$2:$P$34,0),MATCH(AK$3,'jiliarena_日报_底稿'!$P$3:$DS$3,0))} -> 4092.3 | AL14: {=INDEX('jiliarena_日报_底稿'!$P$2:$DS$34,MATCH($A14,'jiliarena_日报_底稿'!$P$2:$P$34,0),MATCH(AL$3,'jiliarena_日报_底稿'!$P$3:$DS$3,0))} -> 4003.8 | AM14: =IF(AL14="","",ROUND((1-(AL14/AK14)),6)) -> 0.021626 | AN14: {=INDEX('jiliarena_日报_底稿'!$P$2:$DS$34,MATCH($A14,'jiliarena_日报_底稿'!$P$2:$P$34,0),MATCH(AN$3,'jiliarena_日报_底稿'!$P$3:$DS$3,0))} -> 203 | AO14: {=INDEX('jiliarena_日报_底稿'!$P$2:$DS$34,MATCH($A14,'jiliarena_日报_底稿'!$P$2:$P$34,0),MATCH(AO$3,'jiliarena_日报_底稿'!$P$3:$DS$3,0))} -> 28 | AP14: =IF(AO14="","",ROUND((1-(AO14/AN14)),6)) -> 0.862069 | AQ14: {=INDEX('jiliarena_日报_底稿'!$P$2:$DS$34,MATCH($A14,'jiliarena_日报_底稿'!$P$2:$P$34,0),MATCH(AQ$3,'jiliarena_日报_底稿'!$P$3:$DS$3,0))} -> 3 | AR14: {=INDEX('jiliarena_日报_底稿'!$P$2:$DS$34,MATCH($A14,'jiliarena_日报_底稿'!$P$2:$P$34,0),MATCH(AR$3,'jiliarena_日报_底稿'!$P$3:$DS$3,0))} -> 0 | AS14: =IF(AR14="","",ROUND((1-(AR14/AQ14)),6)) -> 1 | AT14: =SUMIFS('jiliarena_活动分析数据_底稿'!$K:$K,'jiliarena_活动分析数据_底稿'!$B:$B,$A14,'jiliarena_活动分析数据_底稿'!$L:$L,AT$3) -> 2947.54 | AU14: =SUMIFS('jiliarena_活动分析数据_底稿'!$K:$K,'jiliarena_活动分析数据_底稿'!$B:$B,$A14,'jiliarena_活动分析数据_底稿'!$L:$L,AU$3) -> 0 | AV14: =SUMIFS('jiliarena_活动分析数据_底稿'!$K:$K,'jiliarena_活动分析数据_底稿'!$B:$B,$A14,'jiliarena_活动分析数据_底稿'!$L:$L,AV$3) -> 499.89 | AW14: =SUMIFS('jiliarena_活动分析数据_底稿'!$K:$K,'jiliarena_活动分析数据_底稿'!$B:$B,$A14,'jiliarena_活动分析数据_底稿'!$L:$L,AW$3) -> 4078 | AX14: =SUMIFS('jiliarena_活动分析数据_底稿'!$K:$K,'jiliarena_活动分析数据_底稿'!$B:$B,$A14,'jiliarena_活动分析数据_底稿'!$L:$L,AX$3) -> 426 | AY14: =SUMIFS('jiliarena_活动分析数据_底稿'!$K:$K,'jiliarena_活动分析数据_底稿'!$B:$B,$A14,'jiliarena_活动分析数据_底稿'!$L:$L,AY$3) -> 0 | AZ14: =SUMIFS('jiliarena_活动分析数据_底稿'!$K:$K,'jiliarena_活动分析数据_底稿'!$B:$B,$A14,'jiliarena_活动分析数据_底稿'!$L:$L,AZ$3) -> 0 | BA14: =SUMIFS('jiliarena_活动分析数据_底稿'!$K:$K,'jiliarena_活动分析数据_底稿'!$B:$B,$A14,'jiliarena_活动分析数据_底稿'!$L:$L,BA$3) -> 0 | ... BP14: =SUMIFS('jiliarena_活动分析数据_底稿'!$K:$K,'jiliarena_活动分析数据_底稿'!$B:$B,$A14,'jiliarena_活动分析数据_底稿'!$L:$L,BP$3) -> 0 | BQ14: =SUM(AT14:BP14) -> 11476.32 | BR14: =AT14 -> 2947.54 | BS14: =BB14 -> 251.89 | BT14: =iferror(IF(BQ14="","",ROUND(BQ14/X14,6)),"") -> 0.018098 | BU14: =iferror(BQ14/L14,"") -> 0.13144637 | BV14: =iferror(BQ14/Y14,"") -> 0.23923072 | BW14: =IF(BQ14="","",Y14-BQ14) -> 36495.445 | BX14: =iferror(BQ14/BW14,"") -> 0.31445897 | BY14: =L14*$BY$1 -> 2104.1228 | BZ14: =M14*$BZ$1 -> 100.338 | CA14: =BY14+BZ14 -> 2204.4608 | CB14: =IF(Y14="","",ROUND(Y14*9%,0)) -> 4317 | CC14: =iferror(CA14/BW14,"") -> 0.060403724 | CD14: {=index('jiliarena_日报_底稿'!$P$3:$DS$34,match(A14,'jiliarena_日报_底稿'!$P$3:$P$34,0),match("综合性分红",'jiliarena_日报_底稿'!$P$3:$DS$3,0))} -> 0 | CF14: {=INDEX('jiliarena_日报_底稿'!$P$2:$DS$34,MATCH($A14,'jiliarena_日报_底稿'!$P$2:$P$34,0),MATCH(CF$3,'jiliarena_日报_底稿'!$P$3:$DS$3,0))} -> 0 | CG14: {=-INDEX('jiliarena_日报_底稿'!$P$2:$DS$34,MATCH($A14,'jiliarena_日报_底稿'!$P$2:$P$34,0),MATCH(CG$3,'jiliarena_日报_底稿'!$P$3:$DS$3,0))} -> 0 | CH14: {=INDEX('jiliarena_日报_底稿'!$P$2:$DS$34,MATCH($A14,'jiliarena_日报_底稿'!$P$2:$P$34,0),MATCH(CH$3,'jiliarena_日报_底稿'!$P$3:$DS$3,0))} -> 120268.59 | CI14: =IF(CA14="","",BW14-CA14-CD14-CB14) -> 29973.984 | CJ14: =IFERROR(month(A14),"") -> 3 | CK14: =IFERROR(DAY(A14),"") -> 3
A15: =A14+1 -> 46085 | B15: {=INDEX('jiliarena_日报_底稿'!$A$3:$N$34,MATCH($A15,'jiliarena_日报_底稿'!$A$3:$A$34,0),MATCH(B$3,'jiliarena_日报_底稿'!$A$3:$N$3,0))} -> 147 | C15: {=INDEX('jiliarena_日报_底稿'!$A$3:$N$34,MATCH($A15,'jiliarena_日报_底稿'!$A$3:$A$34,0),MATCH(C$3,'jiliarena_日报_底稿'!$A$3:$N$3,0))} -> 102 | D15: {=INDEX('jiliarena_日报_底稿'!$A$3:$N$34,MATCH($A15,'jiliarena_日报_底稿'!$A$3:$A$34,0),MATCH(D$3,'jiliarena_日报_底稿'!$A$3:$N$3,0))} -> 2976 | E15: 20 | F15: {=INDEX('jiliarena_日报_底稿'!$A$3:$N$34,MATCH($A15,'jiliarena_日报_底稿'!$A$3:$A$34,0),MATCH(F$3,'jiliarena_日报_底稿'!$A$3:$N$3,0))} -> 349 | G15: =SUMIFS('渠道充值成功率_底稿'!$F:$F,'渠道充值成功率_底稿'!$A:$A,A15) -> 504 | H15: {=INDEX('jiliarena_日报_底稿'!$A$3:$N$34,MATCH($A15,'jiliarena_日报_底稿'!$A$3:$A$34,0),MATCH(H$3,'jiliarena_日报_底稿'!$A$3:$N$3,0))} -> 99 | I15: 130 | J15: {=INDEX('jiliarena_日报_底稿'!$A$3:$N$34,MATCH($A15,'jiliarena_日报_底稿'!$A$3:$A$34,0),MATCH(J$3,'jiliarena_日报_底稿'!$A$3:$N$3,0))} -> 2117 | K15: =SUMIFS('渠道充值成功率_底稿'!$J:$J,'渠道充值成功率_底稿'!$A:$A,$A15) -> 16194 | L15: {=INDEX('jiliarena_日报_底稿'!$A$3:$N$34,MATCH($A15,'jiliarena_日报_底稿'!$A$3:$A$34,0),MATCH(L$3,'jiliarena_日报_底稿'!$A$3:$N$3,0))} -> 83228 | M15: {=INDEX('jiliarena_日报_底稿'!$P$2:$DS$34,MATCH($A15,'jiliarena_日报_底稿'!$P$2:$P$34,0),MATCH($M$3,'jiliarena_日报_底稿'!$P$3:$DS$3,0))} -> 70478 | N15: =IF(C15="","",ROUND(C15/B15,4)) -> 0.6939 | O15: =IF(K15="","",ROUND(K15/C15,0)) -> 159 | P15: =IF(L15="","",ROUND(K15/L15,6)) -> 0.194574 | Q15: =IF(G15="","",ROUND(G15/F15,1)) -> 1.4 | R15: =IF(L15="","",ROUND(L15/F15,0)) -> 238 | S15: =IF(L15="","",ROUND(L15/G15,0)) -> 165 | T15: =IF(S15="","",ROUND(S15/O15,1)) -> 1 | U15: =IF(M15="","",ROUND(M15/H15,0)) -> 712 | V15: =IF(M15="","",L15-M15) -> 12750 | W15: =AB15+AE15+AH15+AK15+AN15+AQ15 -> 795270.57 | X15: {=index('jiliarena_日报_底稿'!$P$2:$DS$34,match($A15,'jiliarena_日报_底稿'!$P$2:$P$34,0),match("电子有效投注",'jiliarena_日报_底稿'!$P$3:$DS$3,0))+index('jiliarena_日报_底稿'!$P$2:$DS$34,match($A15,'jiliarena_日报_底稿'!$P$2:$P$34,0),match("真人有效投注",'jiliarena_日报_底稿'!$P$3:$DS$3,0))+index('jiliarena_日报_底稿'!$P$2:$DS$34,match($A15,'jiliarena_日报_底稿'!$P$2:$P$34,0),match("彩票有效投注",'jiliarena_日报_底稿'!$P$3:$DS$3,0))+index('jiliarena_日报_底稿'!$P$2:$DS$34,match($A15,'jiliarena_日报_底稿'!$P$2:$P$34,0),match("棋牌有效投注",'jiliarena_日报_底稿'!$P$3:$DS$3,0))+index('jiliarena_日报_底稿'!$P$2:$DS$34,match($A15,'jiliarena_日报_底稿'!$P$2:$P$34,0),match("捕鱼有效投注",'jiliarena_日报_底稿'!$P$3:$DS$3,0))+index('jiliarena_日报_底稿'!$P$2:$DS$34,match($A15,'jiliarena_日报_底稿'!$P$2:$P$34,0),match("体育有效投注",'jiliarena_日报_底稿'!$P$3:$DS$3,0))+index('jiliarena_日报_底稿'!$P$2:$DS$34,match($A15,'jiliarena_日报_底稿'!$P$2:$P$34,0),match("盘口彩票有效投注",'jiliarena_日报_底稿'!$P$3:$DS$3,0))} -> 738708.54 | Y15: =AB15+AE15+AH15+AK15+AN15+AQ15-AR15-AO15-AL15-AI15-AF15-AC15 -> -5634.265 | Z15: =AC15+AF15+AI15+AL15+AO15+AR15 -> 800904.83 | AA15: =IFERROR(ROUND(1-(Z15/W15),6),"") -> -0.007085 | AB15: {=INDEX('jiliarena_日报_底稿'!$P$2:$DS$34,MATCH($A15,'jiliarena_日报_底稿'!$P$2:$P$34,0),MATCH(AB$3,'jiliarena_日报_底稿'!$P$3:$DS$3,0))} -> 0 | AC15: {=INDEX('jiliarena_日报_底稿'!$P$2:$DS$34,MATCH($A15,'jiliarena_日报_底稿'!$P$2:$P$34,0),MATCH(AC$3,'jiliarena_日报_底稿'!$P$3:$DS$3,0))} -> 0 | AD15: =IF(AC15="","",ROUND((1-(AC15/AB15)),6)) -> #DIV/0! | AE15: {=INDEX('jiliarena_日报_底稿'!$P$2:$DS$34,MATCH($A15,'jiliarena_日报_底稿'!$P$2:$P$34,0),MATCH(AE$3,'jiliarena_日报_底稿'!$P$3:$DS$3,0))} -> 754228.52 | AF15: {=INDEX('jiliarena_日报_底稿'!$P$2:$DS$34,MATCH($A15,'jiliarena_日报_底稿'!$P$2:$P$34,0),MATCH(AF$3,'jiliarena_日报_底稿'!$P$3:$DS$3,0))} -> 755109.36 | AG15: =IF(AF15="","",ROUND((1-(AF15/AE15)),6)) -> -0.001168 | AH15: {=INDEX('jiliarena_日报_底稿'!$P$2:$DS$34,MATCH($A15,'jiliarena_日报_底稿'!$P$2:$P$34,0),MATCH(AH$3,'jiliarena_日报_底稿'!$P$3:$DS$3,0))} -> 8291 | AI15: {=INDEX('jiliarena_日报_底稿'!$P$2:$DS$34,MATCH($A15,'jiliarena_日报_底稿'!$P$2:$P$34,0),MATCH(AI$3,'jiliarena_日报_底稿'!$P$3:$DS$3,0))} -> 11903.3 | AJ15: =IF(AI15="","",ROUND((1-(AI15/AH15)),6)) -> -0.435689 | AK15: {=INDEX('jiliarena_日报_底稿'!$P$2:$DS$34,MATCH($A15,'jiliarena_日报_底稿'!$P$2:$P$34,0),MATCH(AK$3,'jiliarena_日报_底稿'!$P$3:$DS$3,0))} -> 32039.05 | AL15: {=INDEX('jiliarena_日报_底稿'!$P$2:$DS$34,MATCH($A15,'jiliarena_日报_底稿'!$P$2:$P$34,0),MATCH(AL$3,'jiliarena_日报_底稿'!$P$3:$DS$3,0))} -> 33323.62 | AM15: =IF(AL15="","",ROUND((1-(AL15/AK15)),6)) -> -0.040094 | AN15: {=INDEX('jiliarena_日报_底稿'!$P$2:$DS$34,MATCH($A15,'jiliarena_日报_底稿'!$P$2:$P$34,0),MATCH(AN$3,'jiliarena_日报_底稿'!$P$3:$DS$3,0))} -> 707 | AO15: {=INDEX('jiliarena_日报_底稿'!$P$2:$DS$34,MATCH($A15,'jiliarena_日报_底稿'!$P$2:$P$34,0),MATCH(AO$3,'jiliarena_日报_底稿'!$P$3:$DS$3,0))} -> 568.55 | AP15: =IF(AO15="","",ROUND((1-(AO15/AN15)),6)) -> 0.195827 | AQ15: {=INDEX('jiliarena_日报_底稿'!$P$2:$DS$34,MATCH($A15,'jiliarena_日报_底稿'!$P$2:$P$34,0),MATCH(AQ$3,'jiliarena_日报_底稿'!$P$3:$DS$3,0))} -> 5 | AR15: {=INDEX('jiliarena_日报_底稿'!$P$2:$DS$34,MATCH($A15,'jiliarena_日报_底稿'!$P$2:$P$34,0),MATCH(AR$3,'jiliarena_日报_底稿'!$P$3:$DS$3,0))} -> 0 | AS15: =IF(AR15="","",ROUND((1-(AR15/AQ15)),6)) -> 1 | AT15: =SUMIFS('jiliarena_活动分析数据_底稿'!$K:$K,'jiliarena_活动分析数据_底稿'!$B:$B,$A15,'jiliarena_活动分析数据_底稿'!$L:$L,AT$3) -> 1945.7 | AU15: =SUMIFS('jiliarena_活动分析数据_底稿'!$K:$K,'jiliarena_活动分析数据_底稿'!$B:$B,$A15,'jiliarena_活动分析数据_底稿'!$L:$L,AU$3) -> 0 | AV15: =SUMIFS('jiliarena_活动分析数据_底稿'!$K:$K,'jiliarena_活动分析数据_底稿'!$B:$B,$A15,'jiliarena_活动分析数据_底稿'!$L:$L,AV$3) -> 636.6 | AW15: =SUMIFS('jiliarena_活动分析数据_底稿'!$K:$K,'jiliarena_活动分析数据_底稿'!$B:$B,$A15,'jiliarena_活动分析数据_底稿'!$L:$L,AW$3) -> 4123 | AX15: =SUMIFS('jiliarena_活动分析数据_底稿'!$K:$K,'jiliarena_活动分析数据_底稿'!$B:$B,$A15,'jiliarena_活动分析数据_底稿'!$L:$L,AX$3) -> 312 | AY15: =SUMIFS('jiliarena_活动分析数据_底稿'!$K:$K,'jiliarena_活动分析数据_底稿'!$B:$B,$A15,'jiliarena_活动分析数据_底稿'!$L:$L,AY$3) -> 0 | AZ15: =SUMIFS('jiliarena_活动分析数据_底稿'!$K:$K,'jiliarena_活动分析数据_底稿'!$B:$B,$A15,'jiliarena_活动分析数据_底稿'!$L:$L,AZ$3) -> 0 | BA15: =SUMIFS('jiliarena_活动分析数据_底稿'!$K:$K,'jiliarena_活动分析数据_底稿'!$B:$B,$A15,'jiliarena_活动分析数据_底稿'!$L:$L,BA$3) -> 0 | ... BP15: =SUMIFS('jiliarena_活动分析数据_底稿'!$K:$K,'jiliarena_活动分析数据_底稿'!$B:$B,$A15,'jiliarena_活动分析数据_底稿'!$L:$L,BP$3) -> 0 | BQ15: =SUM(AT15:BP15) -> 11588.64 | BR15: =AT15 -> 1945.7 | BS15: =BB15 -> 431.34 | BT15: =iferror(IF(BQ15="","",ROUND(BQ15/X15,6)),"") -> 0.015688 | BU15: =iferror(BQ15/L15,"") -> 0.13923968 | BV15: =iferror(BQ15/Y15,"") -> -2.0568149 | BW15: =IF(BQ15="","",Y15-BQ15) -> -17222.905 | BX15: =iferror(BQ15/BW15,"") -> -0.6728621 | BY15: =L15*$BY$1 -> 2005.7948 | BZ15: =M15*$BZ$1 -> 140.956 | CA15: =BY15+BZ15 -> 2146.7508 | CB15: =IF(Y15="","",ROUND(Y15*9%,0)) -> -507 | CC15: =iferror(CA15/BW15,"") -> -0.1246451 | CD15: {=index('jiliarena_日报_底稿'!$P$3:$DS$34,match(A15,'jiliarena_日报_底稿'!$P$3:$P$34,0),match("综合性分红",'jiliarena_日报_底稿'!$P$3:$DS$3,0))} -> 0 | CF15: {=INDEX('jiliarena_日报_底稿'!$P$2:$DS$34,MATCH($A15,'jiliarena_日报_底稿'!$P$2:$P$34,0),MATCH(CF$3,'jiliarena_日报_底稿'!$P$3:$DS$3,0))} -> 0 | CG15: {=-INDEX('jiliarena_日报_底稿'!$P$2:$DS$34,MATCH($A15,'jiliarena_日报_底稿'!$P$2:$P$34,0),MATCH(CG$3,'jiliarena_日报_底稿'!$P$3:$DS$3,0))} -> 0 | CH15: {=INDEX('jiliarena_日报_底稿'!$P$2:$DS$34,MATCH($A15,'jiliarena_日报_底稿'!$P$2:$P$34,0),MATCH(CH$3,'jiliarena_日报_底稿'!$P$3:$DS$3,0))} -> 125526.74 | CI15: =IF(CA15="","",BW15-CA15-CD15-CB15) -> -18862.656 | CJ15: =IFERROR(month(A15),"") -> 3 | CK15: =IFERROR(DAY(A15),"") -> 4
A16: =A15+1 -> 46086 | B16: {=INDEX('jiliarena_日报_底稿'!$A$3:$N$34,MATCH($A16,'jiliarena_日报_底稿'!$A$3:$A$34,0),MATCH(B$3,'jiliarena_日报_底稿'!$A$3:$N$3,0))} -> 330 | C16: {=INDEX('jiliarena_日报_底稿'!$A$3:$N$34,MATCH($A16,'jiliarena_日报_底稿'!$A$3:$A$34,0),MATCH(C$3,'jiliarena_日报_底稿'!$A$3:$N$3,0))} -> 171 | D16: {=INDEX('jiliarena_日报_底稿'!$A$3:$N$34,MATCH($A16,'jiliarena_日报_底稿'!$A$3:$A$34,0),MATCH(D$3,'jiliarena_日报_底稿'!$A$3:$N$3,0))} -> 3996 | E16: 24 | F16: {=INDEX('jiliarena_日报_底稿'!$A$3:$N$34,MATCH($A16,'jiliarena_日报_底稿'!$A$3:$A$34,0),MATCH(F$3,'jiliarena_日报_底稿'!$A$3:$N$3,0))} -> 453 | G16: =SUMIFS('渠道充值成功率_底稿'!$F:$F,'渠道充值成功率_底稿'!$A:$A,A16) -> 629 | H16: {=INDEX('jiliarena_日报_底稿'!$A$3:$N$34,MATCH($A16,'jiliarena_日报_底稿'!$A$3:$A$34,0),MATCH(H$3,'jiliarena_日报_底稿'!$A$3:$N$3,0))} -> 103 | I16: 130 | J16: {=INDEX('jiliarena_日报_底稿'!$A$3:$N$34,MATCH($A16,'jiliarena_日报_底稿'!$A$3:$A$34,0),MATCH(J$3,'jiliarena_日报_底稿'!$A$3:$N$3,0))} -> 2755 | K16: =SUMIFS('渠道充值成功率_底稿'!$J:$J,'渠道充值成功率_底稿'!$A:$A,$A16) -> 26905 | L16: {=INDEX('jiliarena_日报_底稿'!$A$3:$N$34,MATCH($A16,'jiliarena_日报_底稿'!$A$3:$A$34,0),MATCH(L$3,'jiliarena_日报_底稿'!$A$3:$N$3,0))} -> 122698 | M16: {=INDEX('jiliarena_日报_底稿'!$P$2:$DS$34,MATCH($A16,'jiliarena_日报_底稿'!$P$2:$P$34,0),MATCH($M$3,'jiliarena_日报_底稿'!$P$3:$DS$3,0))} -> 91721 | N16: =IF(C16="","",ROUND(C16/B16,4)) -> 0.5182 | O16: =IF(K16="","",ROUND(K16/C16,0)) -> 157 | P16: =IF(L16="","",ROUND(K16/L16,6)) -> 0.219278 | Q16: =IF(G16="","",ROUND(G16/F16,1)) -> 1.4 | R16: =IF(L16="","",ROUND(L16/F16,0)) -> 271 | S16: =IF(L16="","",ROUND(L16/G16,0)) -> 195 | T16: =IF(S16="","",ROUND(S16/O16,1)) -> 1.2 | U16: =IF(M16="","",ROUND(M16/H16,0)) -> 890 | V16: =IF(M16="","",L16-M16) -> 30977 | W16: =AB16+AE16+AH16+AK16+AN16+AQ16 -> 1053886 | X16: {=index('jiliarena_日报_底稿'!$P$2:$DS$34,match($A16,'jiliarena_日报_底稿'!$P$2:$P$34,0),match("电子有效投注",'jiliarena_日报_底稿'!$P$3:$DS$3,0))+index('jiliarena_日报_底稿'!$P$2:$DS$34,match($A16,'jiliarena_日报_底稿'!$P$2:$P$34,0),match("真人有效投注",'jiliarena_日报_底稿'!$P$3:$DS$3,0))+index('jiliarena_日报_底稿'!$P$2:$DS$34,match($A16,'jiliarena_日报_底稿'!$P$2:$P$34,0),match("彩票有效投注",'jiliarena_日报_底稿'!$P$3:$DS$3,0))+index('jiliarena_日报_底稿'!$P$2:$DS$34,match($A16,'jiliarena_日报_底稿'!$P$2:$P$34,0),match("棋牌有效投注",'jiliarena_日报_底稿'!$P$3:$DS$3,0))+index('jiliarena_日报_底稿'!$P$2:$DS$34,match($A16,'jiliarena_日报_底稿'!$P$2:$P$34,0),match("捕鱼有效投注",'jiliarena_日报_底稿'!$P$3:$DS$3,0))+index('jiliarena_日报_底稿'!$P$2:$DS$34,match($A16,'jiliarena_日报_底稿'!$P$2:$P$34,0),match("体育有效投注",'jiliarena_日报_底稿'!$P$3:$DS$3,0))+index('jiliarena_日报_底稿'!$P$2:$DS$34,match($A16,'jiliarena_日报_底稿'!$P$2:$P$34,0),match("盘口彩票有效投注",'jiliarena_日报_底稿'!$P$3:$DS$3,0))} -> 985532.4 | Y16: =AB16+AE16+AH16+AK16+AN16+AQ16-AR16-AO16-AL16-AI16-AF16-AC16 -> 37589.305 | Z16: =AC16+AF16+AI16+AL16+AO16+AR16 -> 1016296.7 | AA16: =IFERROR(ROUND(1-(Z16/W16),6),"") -> 0.035667 | AB16: {=INDEX('jiliarena_日报_底稿'!$P$2:$DS$34,MATCH($A16,'jiliarena_日报_底稿'!$P$2:$P$34,0),MATCH(AB$3,'jiliarena_日报_底稿'!$P$3:$DS$3,0))} -> 1 | AC16: {=INDEX('jiliarena_日报_底稿'!$P$2:$DS$34,MATCH($A16,'jiliarena_日报_底稿'!$P$2:$P$34,0),MATCH(AC$3,'jiliarena_日报_底稿'!$P$3:$DS$3,0))} -> 0 | AD16: =IF(AC16="","",ROUND((1-(AC16/AB16)),6)) -> 1 | AE16: {=INDEX('jiliarena_日报_底稿'!$P$2:$DS$34,MATCH($A16,'jiliarena_日报_底稿'!$P$2:$P$34,0),MATCH(AE$3,'jiliarena_日报_底稿'!$P$3:$DS$3,0))} -> 1043759.1 | AF16: {=INDEX('jiliarena_日报_底稿'!$P$2:$DS$34,MATCH($A16,'jiliarena_日报_底稿'!$P$2:$P$34,0),MATCH(AF$3,'jiliarena_日报_底稿'!$P$3:$DS$3,0))} -> 1007563.5 | AG16: =IF(AF16="","",ROUND((1-(AF16/AE16)),6)) -> 0.034678 | AH16: {=INDEX('jiliarena_日报_底稿'!$P$2:$DS$34,MATCH($A16,'jiliarena_日报_底稿'!$P$2:$P$34,0),MATCH(AH$3,'jiliarena_日报_底稿'!$P$3:$DS$3,0))} -> 1378 | AI16: {=INDEX('jiliarena_日报_底稿'!$P$2:$DS$34,MATCH($A16,'jiliarena_日报_底稿'!$P$2:$P$34,0),MATCH(AI$3,'jiliarena_日报_底稿'!$P$3:$DS$3,0))} -> 847.05 | AJ16: =IF(AI16="","",ROUND((1-(AI16/AH16)),6)) -> 0.385305 | AK16: {=INDEX('jiliarena_日报_底稿'!$P$2:$DS$34,MATCH($A16,'jiliarena_日报_底稿'!$P$2:$P$34,0),MATCH(AK$3,'jiliarena_日报_底稿'!$P$3:$DS$3,0))} -> 8110.9 | AL16: {=INDEX('jiliarena_日报_底稿'!$P$2:$DS$34,MATCH($A16,'jiliarena_日报_底稿'!$P$2:$P$34,0),MATCH(AL$3,'jiliarena_日报_底稿'!$P$3:$DS$3,0))} -> 7307.44 | AM16: =IF(AL16="","",ROUND((1-(AL16/AK16)),6)) -> 0.099059 | AN16: {=INDEX('jiliarena_日报_底稿'!$P$2:$DS$34,MATCH($A16,'jiliarena_日报_底稿'!$P$2:$P$34,0),MATCH(AN$3,'jiliarena_日报_底稿'!$P$3:$DS$3,0))} -> 633 | AO16: {=INDEX('jiliarena_日报_底稿'!$P$2:$DS$34,MATCH($A16,'jiliarena_日报_底稿'!$P$2:$P$34,0),MATCH(AO$3,'jiliarena_日报_底稿'!$P$3:$DS$3,0))} -> 578.72 | AP16: =IF(AO16="","",ROUND((1-(AO16/AN16)),6)) -> 0.08575 | AQ16: {=INDEX('jiliarena_日报_底稿'!$P$2:$DS$34,MATCH($A16,'jiliarena_日报_底稿'!$P$2:$P$34,0),MATCH(AQ$3,'jiliarena_日报_底稿'!$P$3:$DS$3,0))} -> 4 | AR16: {=INDEX('jiliarena_日报_底稿'!$P$2:$DS$34,MATCH($A16,'jiliarena_日报_底稿'!$P$2:$P$34,0),MATCH(AR$3,'jiliarena_日报_底稿'!$P$3:$DS$3,0))} -> 0 | AS16: =IF(AR16="","",ROUND((1-(AR16/AQ16)),6)) -> 1 | AT16: =SUMIFS('jiliarena_活动分析数据_底稿'!$K:$K,'jiliarena_活动分析数据_底稿'!$B:$B,$A16,'jiliarena_活动分析数据_底稿'!$L:$L,AT$3) -> 1722.23 | AU16: =SUMIFS('jiliarena_活动分析数据_底稿'!$K:$K,'jiliarena_活动分析数据_底稿'!$B:$B,$A16,'jiliarena_活动分析数据_底稿'!$L:$L,AU$3) -> 0 | AV16: =SUMIFS('jiliarena_活动分析数据_底稿'!$K:$K,'jiliarena_活动分析数据_底稿'!$B:$B,$A16,'jiliarena_活动分析数据_底稿'!$L:$L,AV$3) -> 732.41 | AW16: =SUMIFS('jiliarena_活动分析数据_底稿'!$K:$K,'jiliarena_活动分析数据_底稿'!$B:$B,$A16,'jiliarena_活动分析数据_底稿'!$L:$L,AW$3) -> 4733 | AX16: =SUMIFS('jiliarena_活动分析数据_底稿'!$K:$K,'jiliarena_活动分析数据_底稿'!$B:$B,$A16,'jiliarena_活动分析数据_底稿'!$L:$L,AX$3) -> 305 | AY16: =SUMIFS('jiliarena_活动分析数据_底稿'!$K:$K,'jiliarena_活动分析数据_底稿'!$B:$B,$A16,'jiliarena_活动分析数据_底稿'!$L:$L,AY$3) -> 0 | AZ16: =SUMIFS('jiliarena_活动分析数据_底稿'!$K:$K,'jiliarena_活动分析数据_底稿'!$B:$B,$A16,'jiliarena_活动分析数据_底稿'!$L:$L,AZ$3) -> 0 | BA16: =SUMIFS('jiliarena_活动分析数据_底稿'!$K:$K,'jiliarena_活动分析数据_底稿'!$B:$B,$A16,'jiliarena_活动分析数据_底稿'!$L:$L,BA$3) -> 0 | ... BP16: =SUMIFS('jiliarena_活动分析数据_底稿'!$K:$K,'jiliarena_活动分析数据_底稿'!$B:$B,$A16,'jiliarena_活动分析数据_底稿'!$L:$L,BP$3) -> 0 | BQ16: =SUM(AT16:BP16) -> 13185.91 | BR16: =AT16 -> 1722.23 | BS16: =BB16 -> 317.77 | BT16: =iferror(IF(BQ16="","",ROUND(BQ16/X16,6)),"") -> 0.013379 | BU16: =iferror(BQ16/L16,"") -> 0.10746638 | BV16: =iferror(BQ16/Y16,"") -> 0.35078887 | BW16: =IF(BQ16="","",Y16-BQ16) -> 24403.395 | BX16: =iferror(BQ16/BW16,"") -> 0.54033097 | BY16: =L16*$BY$1 -> 2957.0218 | BZ16: =M16*$BZ$1 -> 183.442 | CA16: =BY16+BZ16 -> 3140.4638 | CB16: =IF(Y16="","",ROUND(Y16*9%,0)) -> 3383 | CC16: =iferror(CA16/BW16,"") -> 0.12868963 | CD16: {=index('jiliarena_日报_底稿'!$P$3:$DS$34,match(A16,'jiliarena_日报_底稿'!$P$3:$P$34,0),match("综合性分红",'jiliarena_日报_底稿'!$P$3:$DS$3,0))} -> 0 | CF16: {=INDEX('jiliarena_日报_底稿'!$P$2:$DS$34,MATCH($A16,'jiliarena_日报_底稿'!$P$2:$P$34,0),MATCH(CF$3,'jiliarena_日报_底稿'!$P$3:$DS$3,0))} -> 0 | CG16: {=-INDEX('jiliarena_日报_底稿'!$P$2:$DS$34,MATCH($A16,'jiliarena_日报_底稿'!$P$2:$P$34,0),MATCH(CG$3,'jiliarena_日报_底稿'!$P$3:$DS$3,0))} -> 0 | CH16: {=INDEX('jiliarena_日报_底稿'!$P$2:$DS$34,MATCH($A16,'jiliarena_日报_底稿'!$P$2:$P$34,0),MATCH(CH$3,'jiliarena_日报_底稿'!$P$3:$DS$3,0))} -> 141233.32 | CI16: =IF(CA16="","",BW16-CA16-CD16-CB16) -> 17879.931 | CJ16: =IFERROR(month(A16),"") -> 3 | CK16: =IFERROR(DAY(A16),"") -> 5
A17: =A16+1 -> 46087 | B17: {=INDEX('jiliarena_日报_底稿'!$A$3:$N$34,MATCH($A17,'jiliarena_日报_底稿'!$A$3:$A$34,0),MATCH(B$3,'jiliarena_日报_底稿'!$A$3:$N$3,0))} -> 231 | C17: {=INDEX('jiliarena_日报_底稿'!$A$3:$N$34,MATCH($A17,'jiliarena_日报_底稿'!$A$3:$A$34,0),MATCH(C$3,'jiliarena_日报_底稿'!$A$3:$N$3,0))} -> 133 | D17: {=INDEX('jiliarena_日报_底稿'!$A$3:$N$34,MATCH($A17,'jiliarena_日报_底稿'!$A$3:$A$34,0),MATCH(D$3,'jiliarena_日报_底稿'!$A$3:$N$3,0))} -> 3924 | E17: 17 | F17: {=INDEX('jiliarena_日报_底稿'!$A$3:$N$34,MATCH($A17,'jiliarena_日报_底稿'!$A$3:$A$34,0),MATCH(F$3,'jiliarena_日报_底稿'!$A$3:$N$3,0))} -> 399 | G17: =SUMIFS('渠道充值成功率_底稿'!$F:$F,'渠道充值成功率_底稿'!$A:$A,A17) -> 531 | H17: {=INDEX('jiliarena_日报_底稿'!$A$3:$N$34,MATCH($A17,'jiliarena_日报_底稿'!$A$3:$A$34,0),MATCH(H$3,'jiliarena_日报_底稿'!$A$3:$N$3,0))} -> 89 | I17: 106 | J17: {=INDEX('jiliarena_日报_底稿'!$A$3:$N$34,MATCH($A17,'jiliarena_日报_底稿'!$A$3:$A$34,0),MATCH(J$3,'jiliarena_日报_底稿'!$A$3:$N$3,0))} -> 2777 | K17: =SUMIFS('渠道充值成功率_底稿'!$J:$J,'渠道充值成功率_底稿'!$A:$A,$A17) -> 21176 | L17: {=INDEX('jiliarena_日报_底稿'!$A$3:$N$34,MATCH($A17,'jiliarena_日报_底稿'!$A$3:$A$34,0),MATCH(L$3,'jiliarena_日报_底稿'!$A$3:$N$3,0))} -> 82445 | M17: {=INDEX('jiliarena_日报_底稿'!$P$2:$DS$34,MATCH($A17,'jiliarena_日报_底稿'!$P$2:$P$34,0),MATCH($M$3,'jiliarena_日报_底稿'!$P$3:$DS$3,0))} -> 76326 | N17: =IF(C17="","",ROUND(C17/B17,4)) -> 0.5758 | O17: =IF(K17="","",ROUND(K17/C17,0)) -> 159 | P17: =IF(L17="","",ROUND(K17/L17,6)) -> 0.25685 | Q17: =IF(G17="","",ROUND(G17/F17,1)) -> 1.3 | R17: =IF(L17="","",ROUND(L17/F17,0)) -> 207 | S17: =IF(L17="","",ROUND(L17/G17,0)) -> 155 | T17: =IF(S17="","",ROUND(S17/O17,1)) -> 1 | U17: =IF(M17="","",ROUND(M17/H17,0)) -> 858 | V17: =IF(M17="","",L17-M17) -> 6119 | W17: =AB17+AE17+AH17+AK17+AN17+AQ17 -> 714338.85 | X17: {=index('jiliarena_日报_底稿'!$P$2:$DS$34,match($A17,'jiliarena_日报_底稿'!$P$2:$P$34,0),match("电子有效投注",'jiliarena_日报_底稿'!$P$3:$DS$3,0))+index('jiliarena_日报_底稿'!$P$2:$DS$34,match($A17,'jiliarena_日报_底稿'!$P$2:$P$34,0),match("真人有效投注",'jiliarena_日报_底稿'!$P$3:$DS$3,0))+index('jiliarena_日报_底稿'!$P$2:$DS$34,match($A17,'jiliarena_日报_底稿'!$P$2:$P$34,0),match("彩票有效投注",'jiliarena_日报_底稿'!$P$3:$DS$3,0))+index('jiliarena_日报_底稿'!$P$2:$DS$34,match($A17,'jiliarena_日报_底稿'!$P$2:$P$34,0),match("棋牌有效投注",'jiliarena_日报_底稿'!$P$3:$DS$3,0))+index('jiliarena_日报_底稿'!$P$2:$DS$34,match($A17,'jiliarena_日报_底稿'!$P$2:$P$34,0),match("捕鱼有效投注",'jiliarena_日报_底稿'!$P$3:$DS$3,0))+index('jiliarena_日报_底稿'!$P$2:$DS$34,match($A17,'jiliarena_日报_底稿'!$P$2:$P$34,0),match("体育有效投注",'jiliarena_日报_底稿'!$P$3:$DS$3,0))+index('jiliarena_日报_底稿'!$P$2:$DS$34,match($A17,'jiliarena_日报_底稿'!$P$2:$P$34,0),match("盘口彩票有效投注",'jiliarena_日报_底稿'!$P$3:$DS$3,0))} -> 677047.53 | Y17: =AB17+AE17+AH17+AK17+AN17+AQ17-AR17-AO17-AL17-AI17-AF17-AC17 -> 47690.245 | Z17: =AC17+AF17+AI17+AL17+AO17+AR17 -> 666648.6 | AA17: =IFERROR(ROUND(1-(Z17/W17),6),"") -> 0.066761 | AB17: {=INDEX('jiliarena_日报_底稿'!$P$2:$DS$34,MATCH($A17,'jiliarena_日报_底稿'!$P$2:$P$34,0),MATCH(AB$3,'jiliarena_日报_底稿'!$P$3:$DS$3,0))} -> 0 | AC17: {=INDEX('jiliarena_日报_底稿'!$P$2:$DS$34,MATCH($A17,'jiliarena_日报_底稿'!$P$2:$P$34,0),MATCH(AC$3,'jiliarena_日报_底稿'!$P$3:$DS$3,0))} -> 0 | AD17: =IF(AC17="","",ROUND((1-(AC17/AB17)),6)) -> #DIV/0! | AE17: {=INDEX('jiliarena_日报_底稿'!$P$2:$DS$34,MATCH($A17,'jiliarena_日报_底稿'!$P$2:$P$34,0),MATCH(AE$3,'jiliarena_日报_底稿'!$P$3:$DS$3,0))} -> 698787.03 | AF17: {=INDEX('jiliarena_日报_底稿'!$P$2:$DS$34,MATCH($A17,'jiliarena_日报_底稿'!$P$2:$P$34,0),MATCH(AF$3,'jiliarena_日报_底稿'!$P$3:$DS$3,0))} -> 654158.46 | AG17: =IF(AF17="","",ROUND((1-(AF17/AE17)),6)) -> 0.063866 | AH17: {=INDEX('jiliarena_日报_底稿'!$P$2:$DS$34,MATCH($A17,'jiliarena_日报_底稿'!$P$2:$P$34,0),MATCH(AH$3,'jiliarena_日报_底稿'!$P$3:$DS$3,0))} -> 4507.42 | AI17: {=INDEX('jiliarena_日报_底稿'!$P$2:$DS$34,MATCH($A17,'jiliarena_日报_底稿'!$P$2:$P$34,0),MATCH(AI$3,'jiliarena_日报_底稿'!$P$3:$DS$3,0))} -> 3196.82 | AJ17: =IF(AI17="","",ROUND((1-(AI17/AH17)),6)) -> 0.290765 | AK17: {=INDEX('jiliarena_日报_底稿'!$P$2:$DS$34,MATCH($A17,'jiliarena_日报_底稿'!$P$2:$P$34,0),MATCH(AK$3,'jiliarena_日报_底稿'!$P$3:$DS$3,0))} -> 10892.4 | AL17: {=INDEX('jiliarena_日报_底稿'!$P$2:$DS$34,MATCH($A17,'jiliarena_日报_底稿'!$P$2:$P$34,0),MATCH(AL$3,'jiliarena_日报_底稿'!$P$3:$DS$3,0))} -> 9241.32 | AM17: =IF(AL17="","",ROUND((1-(AL17/AK17)),6)) -> 0.151581 | AN17: {=INDEX('jiliarena_日报_底稿'!$P$2:$DS$34,MATCH($A17,'jiliarena_日报_底稿'!$P$2:$P$34,0),MATCH(AN$3,'jiliarena_日报_底稿'!$P$3:$DS$3,0))} -> 150 | AO17: {=INDEX('jiliarena_日报_底稿'!$P$2:$DS$34,MATCH($A17,'jiliarena_日报_底稿'!$P$2:$P$34,0),MATCH(AO$3,'jiliarena_日报_底稿'!$P$3:$DS$3,0))} -> 52 | AP17: =IF(AO17="","",ROUND((1-(AO17/AN17)),6)) -> 0.653333 | AQ17: {=INDEX('jiliarena_日报_底稿'!$P$2:$DS$34,MATCH($A17,'jiliarena_日报_底稿'!$P$2:$P$34,0),MATCH(AQ$3,'jiliarena_日报_底稿'!$P$3:$DS$3,0))} -> 2 | AR17: {=INDEX('jiliarena_日报_底稿'!$P$2:$DS$34,MATCH($A17,'jiliarena_日报_底稿'!$P$2:$P$34,0),MATCH(AR$3,'jiliarena_日报_底稿'!$P$3:$DS$3,0))} -> 0 | AS17: =IF(AR17="","",ROUND((1-(AR17/AQ17)),6)) -> 1 | AT17: =SUMIFS('jiliarena_活动分析数据_底稿'!$K:$K,'jiliarena_活动分析数据_底稿'!$B:$B,$A17,'jiliarena_活动分析数据_底稿'!$L:$L,AT$3) -> 3686.1 | AU17: =SUMIFS('jiliarena_活动分析数据_底稿'!$K:$K,'jiliarena_活动分析数据_底稿'!$B:$B,$A17,'jiliarena_活动分析数据_底稿'!$L:$L,AU$3) -> 0 | AV17: =SUMIFS('jiliarena_活动分析数据_底稿'!$K:$K,'jiliarena_活动分析数据_底稿'!$B:$B,$A17,'jiliarena_活动分析数据_底稿'!$L:$L,AV$3) -> 767.05 | AW17: =SUMIFS('jiliarena_活动分析数据_底稿'!$K:$K,'jiliarena_活动分析数据_底稿'!$B:$B,$A17,'jiliarena_活动分析数据_底稿'!$L:$L,AW$3) -> 4946 | AX17: =SUMIFS('jiliarena_活动分析数据_底稿'!$K:$K,'jiliarena_活动分析数据_底稿'!$B:$B,$A17,'jiliarena_活动分析数据_底稿'!$L:$L,AX$3) -> 439 | AY17: =SUMIFS('jiliarena_活动分析数据_底稿'!$K:$K,'jiliarena_活动分析数据_底稿'!$B:$B,$A17,'jiliarena_活动分析数据_底稿'!$L:$L,AY$3) -> 0 | AZ17: =SUMIFS('jiliarena_活动分析数据_底稿'!$K:$K,'jiliarena_活动分析数据_底稿'!$B:$B,$A17,'jiliarena_活动分析数据_底稿'!$L:$L,AZ$3) -> 0 | BA17: =SUMIFS('jiliarena_活动分析数据_底稿'!$K:$K,'jiliarena_活动分析数据_底稿'!$B:$B,$A17,'jiliarena_活动分析数据_底稿'!$L:$L,BA$3) -> 0 | ... BP17: =SUMIFS('jiliarena_活动分析数据_底稿'!$K:$K,'jiliarena_活动分析数据_底稿'!$B:$B,$A17,'jiliarena_活动分析数据_底稿'!$L:$L,BP$3) -> 0 | BQ17: =SUM(AT17:BP17) -> 15579.54 | BR17: =AT17 -> 3686.1 | BS17: =BB17 -> 402.89 | BT17: =iferror(IF(BQ17="","",ROUND(BQ17/X17,6)),"") -> 0.023011 | BU17: =iferror(BQ17/L17,"") -> 0.18896889 | BV17: =iferror(BQ17/Y17,"") -> 0.3266819 | BW17: =IF(BQ17="","",Y17-BQ17) -> 32110.705 | BX17: =iferror(BQ17/BW17,"") -> 0.48518212 | BY17: =L17*$BY$1 -> 1986.9245 | BZ17: =M17*$BZ$1 -> 152.652 | CA17: =BY17+BZ17 -> 2139.5765 | CB17: =IF(Y17="","",ROUND(Y17*9%,0)) -> 4292 | CC17: =iferror(CA17/BW17,"") -> 0.066631253 | CD17: {=index('jiliarena_日报_底稿'!$P$3:$DS$34,match(A17,'jiliarena_日报_底稿'!$P$3:$P$34,0),match("综合性分红",'jiliarena_日报_底稿'!$P$3:$DS$3,0))} -> 0 | CF17: {=INDEX('jiliarena_日报_底稿'!$P$2:$DS$34,MATCH($A17,'jiliarena_日报_底稿'!$P$2:$P$34,0),MATCH(CF$3,'jiliarena_日报_底稿'!$P$3:$DS$3,0))} -> 0 | CG17: {=-INDEX('jiliarena_日报_底稿'!$P$2:$DS$34,MATCH($A17,'jiliarena_日报_底稿'!$P$2:$P$34,0),MATCH(CG$3,'jiliarena_日报_底稿'!$P$3:$DS$3,0))} -> 0 | CH17: {=INDEX('jiliarena_日报_底稿'!$P$2:$DS$34,MATCH($A17,'jiliarena_日报_底稿'!$P$2:$P$34,0),MATCH(CH$3,'jiliarena_日报_底稿'!$P$3:$DS$3,0))} -> 136799.24 | CI17: =IF(CA17="","",BW17-CA17-CD17-CB17) -> 25679.128 | CJ17: =IFERROR(month(A17),"") -> 3 | CK17: =IFERROR(DAY(A17),"") -> 6
A18: =A17+1 -> 46088 | B18: {=INDEX('jiliarena_日报_底稿'!$A$3:$N$34,MATCH($A18,'jiliarena_日报_底稿'!$A$3:$A$34,0),MATCH(B$3,'jiliarena_日报_底稿'!$A$3:$N$3,0))} -> 104 | C18: {=INDEX('jiliarena_日报_底稿'!$A$3:$N$34,MATCH($A18,'jiliarena_日报_底稿'!$A$3:$A$34,0),MATCH(C$3,'jiliarena_日报_底稿'!$A$3:$N$3,0))} -> 75 | D18: {=INDEX('jiliarena_日报_底稿'!$A$3:$N$34,MATCH($A18,'jiliarena_日报_底稿'!$A$3:$A$34,0),MATCH(D$3,'jiliarena_日报_底稿'!$A$3:$N$3,0))} -> 2978 | E18: 11 | F18: {=INDEX('jiliarena_日报_底稿'!$A$3:$N$34,MATCH($A18,'jiliarena_日报_底稿'!$A$3:$A$34,0),MATCH(F$3,'jiliarena_日报_底稿'!$A$3:$N$3,0))} -> 311 | G18: =SUMIFS('渠道充值成功率_底稿'!$F:$F,'渠道充值成功率_底稿'!$A:$A,A18) -> 460 | H18: {=INDEX('jiliarena_日报_底稿'!$A$3:$N$34,MATCH($A18,'jiliarena_日报_底稿'!$A$3:$A$34,0),MATCH(H$3,'jiliarena_日报_底稿'!$A$3:$N$3,0))} -> 72 | I18: 96 | J18: {=INDEX('jiliarena_日报_底稿'!$A$3:$N$34,MATCH($A18,'jiliarena_日报_底稿'!$A$3:$A$34,0),MATCH(J$3,'jiliarena_日报_底稿'!$A$3:$N$3,0))} -> 2099 | K18: =SUMIFS('渠道充值成功率_底稿'!$J:$J,'渠道充值成功率_底稿'!$A:$A,$A18) -> 9596 | L18: {=INDEX('jiliarena_日报_底稿'!$A$3:$N$34,MATCH($A18,'jiliarena_日报_底稿'!$A$3:$A$34,0),MATCH(L$3,'jiliarena_日报_底稿'!$A$3:$N$3,0))} -> 78253 | M18: {=INDEX('jiliarena_日报_底稿'!$P$2:$DS$34,MATCH($A18,'jiliarena_日报_底稿'!$P$2:$P$34,0),MATCH($M$3,'jiliarena_日报_底稿'!$P$3:$DS$3,0))} -> 55531 | N18: =IF(C18="","",ROUND(C18/B18,4)) -> 0.7212 | O18: =IF(K18="","",ROUND(K18/C18,0)) -> 128 | P18: =IF(L18="","",ROUND(K18/L18,6)) -> 0.122628 | Q18: =IF(G18="","",ROUND(G18/F18,1)) -> 1.5 | R18: =IF(L18="","",ROUND(L18/F18,0)) -> 252 | S18: =IF(L18="","",ROUND(L18/G18,0)) -> 170 | T18: =IF(S18="","",ROUND(S18/O18,1)) -> 1.3 | U18: =IF(M18="","",ROUND(M18/H18,0)) -> 771 | V18: =IF(M18="","",L18-M18) -> 22722 | W18: =AB18+AE18+AH18+AK18+AN18+AQ18 -> 596338.88 | X18: {=index('jiliarena_日报_底稿'!$P$2:$DS$34,match($A18,'jiliarena_日报_底稿'!$P$2:$P$34,0),match("电子有效投注",'jiliarena_日报_底稿'!$P$3:$DS$3,0))+index('jiliarena_日报_底稿'!$P$2:$DS$34,match($A18,'jiliarena_日报_底稿'!$P$2:$P$34,0),match("真人有效投注",'jiliarena_日报_底稿'!$P$3:$DS$3,0))+index('jiliarena_日报_底稿'!$P$2:$DS$34,match($A18,'jiliarena_日报_底稿'!$P$2:$P$34,0),match("彩票有效投注",'jiliarena_日报_底稿'!$P$3:$DS$3,0))+index('jiliarena_日报_底稿'!$P$2:$DS$34,match($A18,'jiliarena_日报_底稿'!$P$2:$P$34,0),match("棋牌有效投注",'jiliarena_日报_底稿'!$P$3:$DS$3,0))+index('jiliarena_日报_底稿'!$P$2:$DS$34,match($A18,'jiliarena_日报_底稿'!$P$2:$P$34,0),match("捕鱼有效投注",'jiliarena_日报_底稿'!$P$3:$DS$3,0))+index('jiliarena_日报_底稿'!$P$2:$DS$34,match($A18,'jiliarena_日报_底稿'!$P$2:$P$34,0),match("体育有效投注",'jiliarena_日报_底稿'!$P$3:$DS$3,0))+index('jiliarena_日报_底稿'!$P$2:$DS$34,match($A18,'jiliarena_日报_底稿'!$P$2:$P$34,0),match("盘口彩票有效投注",'jiliarena_日报_底稿'!$P$3:$DS$3,0))} -> 566030.4 | Y18: =AB18+AE18+AH18+AK18+AN18+AQ18-AR18-AO18-AL18-AI18-AF18-AC18 -> 16566.735 | Z18: =AC18+AF18+AI18+AL18+AO18+AR18 -> 579772.15 | AA18: =IFERROR(ROUND(1-(Z18/W18),6),"") -> 0.027781 | AB18: {=INDEX('jiliarena_日报_底稿'!$P$2:$DS$34,MATCH($A18,'jiliarena_日报_底稿'!$P$2:$P$34,0),MATCH(AB$3,'jiliarena_日报_底稿'!$P$3:$DS$3,0))} -> 1 | AC18: {=INDEX('jiliarena_日报_底稿'!$P$2:$DS$34,MATCH($A18,'jiliarena_日报_底稿'!$P$2:$P$34,0),MATCH(AC$3,'jiliarena_日报_底稿'!$P$3:$DS$3,0))} -> 0 | AD18: =IF(AC18="","",ROUND((1-(AC18/AB18)),6)) -> 1 | AE18: {=INDEX('jiliarena_日报_底稿'!$P$2:$DS$34,MATCH($A18,'jiliarena_日报_底稿'!$P$2:$P$34,0),MATCH(AE$3,'jiliarena_日报_底稿'!$P$3:$DS$3,0))} -> 586052.88 | AF18: {=INDEX('jiliarena_日报_底稿'!$P$2:$DS$34,MATCH($A18,'jiliarena_日报_底稿'!$P$2:$P$34,0),MATCH(AF$3,'jiliarena_日报_底稿'!$P$3:$DS$3,0))} -> 571806.77 | AG18: =IF(AF18="","",ROUND((1-(AF18/AE18)),6)) -> 0.024309 | AH18: {=INDEX('jiliarena_日报_底稿'!$P$2:$DS$34,MATCH($A18,'jiliarena_日报_底稿'!$P$2:$P$34,0),MATCH(AH$3,'jiliarena_日报_底稿'!$P$3:$DS$3,0))} -> 6927.45 | AI18: {=INDEX('jiliarena_日报_底稿'!$P$2:$DS$34,MATCH($A18,'jiliarena_日报_底稿'!$P$2:$P$34,0),MATCH(AI$3,'jiliarena_日报_底稿'!$P$3:$DS$3,0))} -> 5238.3 | AJ18: =IF(AI18="","",ROUND((1-(AI18/AH18)),6)) -> 0.243834 | AK18: {=INDEX('jiliarena_日报_底稿'!$P$2:$DS$34,MATCH($A18,'jiliarena_日报_底稿'!$P$2:$P$34,0),MATCH(AK$3,'jiliarena_日报_底稿'!$P$3:$DS$3,0))} -> 3056.55 | AL18: {=INDEX('jiliarena_日报_底稿'!$P$2:$DS$34,MATCH($A18,'jiliarena_日报_底稿'!$P$2:$P$34,0),MATCH(AL$3,'jiliarena_日报_底稿'!$P$3:$DS$3,0))} -> 2586.08 | AM18: =IF(AL18="","",ROUND((1-(AL18/AK18)),6)) -> 0.153922 | AN18: {=INDEX('jiliarena_日报_底稿'!$P$2:$DS$34,MATCH($A18,'jiliarena_日报_底稿'!$P$2:$P$34,0),MATCH(AN$3,'jiliarena_日报_底稿'!$P$3:$DS$3,0))} -> 300 | AO18: {=INDEX('jiliarena_日报_底稿'!$P$2:$DS$34,MATCH($A18,'jiliarena_日报_底稿'!$P$2:$P$34,0),MATCH(AO$3,'jiliarena_日报_底稿'!$P$3:$DS$3,0))} -> 141 | AP18: =IF(AO18="","",ROUND((1-(AO18/AN18)),6)) -> 0.53 | AQ18: {=INDEX('jiliarena_日报_底稿'!$P$2:$DS$34,MATCH($A18,'jiliarena_日报_底稿'!$P$2:$P$34,0),MATCH(AQ$3,'jiliarena_日报_底稿'!$P$3:$DS$3,0))} -> 1 | AR18: {=INDEX('jiliarena_日报_底稿'!$P$2:$DS$34,MATCH($A18,'jiliarena_日报_底稿'!$P$2:$P$34,0),MATCH(AR$3,'jiliarena_日报_底稿'!$P$3:$DS$3,0))} -> 0 | AS18: =IF(AR18="","",ROUND((1-(AR18/AQ18)),6)) -> 1 | AT18: =SUMIFS('jiliarena_活动分析数据_底稿'!$K:$K,'jiliarena_活动分析数据_底稿'!$B:$B,$A18,'jiliarena_活动分析数据_底稿'!$L:$L,AT$3) -> 1784.98 | AU18: =SUMIFS('jiliarena_活动分析数据_底稿'!$K:$K,'jiliarena_活动分析数据_底稿'!$B:$B,$A18,'jiliarena_活动分析数据_底稿'!$L:$L,AU$3) -> 0 | AV18: =SUMIFS('jiliarena_活动分析数据_底稿'!$K:$K,'jiliarena_活动分析数据_底稿'!$B:$B,$A18,'jiliarena_活动分析数据_底稿'!$L:$L,AV$3) -> 777.03 | AW18: =SUMIFS('jiliarena_活动分析数据_底稿'!$K:$K,'jiliarena_活动分析数据_底稿'!$B:$B,$A18,'jiliarena_活动分析数据_底稿'!$L:$L,AW$3) -> 4108 | AX18: =SUMIFS('jiliarena_活动分析数据_底稿'!$K:$K,'jiliarena_活动分析数据_底稿'!$B:$B,$A18,'jiliarena_活动分析数据_底稿'!$L:$L,AX$3) -> 282 | AY18: =SUMIFS('jiliarena_活动分析数据_底稿'!$K:$K,'jiliarena_活动分析数据_底稿'!$B:$B,$A18,'jiliarena_活动分析数据_底稿'!$L:$L,AY$3) -> 0 | AZ18: =SUMIFS('jiliarena_活动分析数据_底稿'!$K:$K,'jiliarena_活动分析数据_底稿'!$B:$B,$A18,'jiliarena_活动分析数据_底稿'!$L:$L,AZ$3) -> 0 | BA18: =SUMIFS('jiliarena_活动分析数据_底稿'!$K:$K,'jiliarena_活动分析数据_底稿'!$B:$B,$A18,'jiliarena_活动分析数据_底稿'!$L:$L,BA$3) -> 0 | ... BP18: =SUMIFS('jiliarena_活动分析数据_底稿'!$K:$K,'jiliarena_活动分析数据_底稿'!$B:$B,$A18,'jiliarena_活动分析数据_底稿'!$L:$L,BP$3) -> 0 | BQ18: =SUM(AT18:BP18) -> 9888.47 | BR18: =AT18 -> 1784.98 | BS18: =BB18 -> 119.46 | BT18: =iferror(IF(BQ18="","",ROUND(BQ18/X18,6)),"") -> 0.01747 | BU18: =iferror(BQ18/L18,"") -> 0.12636538 | BV18: =iferror(BQ18/Y18,"") -> 0.59688708 | BW18: =IF(BQ18="","",Y18-BQ18) -> 6678.265 | BX18: =iferror(BQ18/BW18,"") -> 1.4806945 | BY18: =L18*$BY$1 -> 1885.8973 | BZ18: =M18*$BZ$1 -> 111.062 | CA18: =BY18+BZ18 -> 1996.9593 | CB18: =IF(Y18="","",ROUND(Y18*9%,0)) -> 1491 | CC18: =iferror(CA18/BW18,"") -> 0.29902367 | CD18: {=index('jiliarena_日报_底稿'!$P$3:$DS$34,match(A18,'jiliarena_日报_底稿'!$P$3:$P$34,0),match("综合性分红",'jiliarena_日报_底稿'!$P$3:$DS$3,0))} -> 0 | CF18: {=INDEX('jiliarena_日报_底稿'!$P$2:$DS$34,MATCH($A18,'jiliarena_日报_底稿'!$P$2:$P$34,0),MATCH(CF$3,'jiliarena_日报_底稿'!$P$3:$DS$3,0))} -> 0 | CG18: {=-INDEX('jiliarena_日报_底稿'!$P$2:$DS$34,MATCH($A18,'jiliarena_日报_底稿'!$P$2:$P$34,0),MATCH(CG$3,'jiliarena_日报_底稿'!$P$3:$DS$3,0))} -> 0 | CH18: {=INDEX('jiliarena_日报_底稿'!$P$2:$DS$34,MATCH($A18,'jiliarena_日报_底稿'!$P$2:$P$34,0),MATCH(CH$3,'jiliarena_日报_底稿'!$P$3:$DS$3,0))} -> 136707.03 | CI18: =IF(CA18="","",BW18-CA18-CD18-CB18) -> 3190.3057 | CJ18: =IFERROR(month(A18),"") -> 3 | CK18: =IFERROR(DAY(A18),"") -> 7
A19: =A18+1 -> 46089 | B19: {=INDEX('jiliarena_日报_底稿'!$A$3:$N$34,MATCH($A19,'jiliarena_日报_底稿'!$A$3:$A$34,0),MATCH(B$3,'jiliarena_日报_底稿'!$A$3:$N$3,0))} -> 128 | C19: {=INDEX('jiliarena_日报_底稿'!$A$3:$N$34,MATCH($A19,'jiliarena_日报_底稿'!$A$3:$A$34,0),MATCH(C$3,'jiliarena_日报_底稿'!$A$3:$N$3,0))} -> 70 | D19: {=INDEX('jiliarena_日报_底稿'!$A$3:$N$34,MATCH($A19,'jiliarena_日报_底稿'!$A$3:$A$34,0),MATCH(D$3,'jiliarena_日报_底稿'!$A$3:$N$3,0))} -> 2944 | E19: 9 | F19: {=INDEX('jiliarena_日报_底稿'!$A$3:$N$34,MATCH($A19,'jiliarena_日报_底稿'!$A$3:$A$34,0),MATCH(F$3,'jiliarena_日报_底稿'!$A$3:$N$3,0))} -> 293 | G19: =SUMIFS('渠道充值成功率_底稿'!$F:$F,'渠道充值成功率_底稿'!$A:$A,A19) -> 452 | H19: {=INDEX('jiliarena_日报_底稿'!$A$3:$N$34,MATCH($A19,'jiliarena_日报_底稿'!$A$3:$A$34,0),MATCH(H$3,'jiliarena_日报_底稿'!$A$3:$N$3,0))} -> 63 | I19: 79 | J19: {=INDEX('jiliarena_日报_底稿'!$A$3:$N$34,MATCH($A19,'jiliarena_日报_底稿'!$A$3:$A$34,0),MATCH(J$3,'jiliarena_日报_底稿'!$A$3:$N$3,0))} -> 2192 | K19: =SUMIFS('渠道充值成功率_底稿'!$J:$J,'渠道充值成功率_底稿'!$A:$A,$A19) -> 7718 | L19: {=INDEX('jiliarena_日报_底稿'!$A$3:$N$34,MATCH($A19,'jiliarena_日报_底稿'!$A$3:$A$34,0),MATCH(L$3,'jiliarena_日报_底稿'!$A$3:$N$3,0))} -> 74194 | M19: {=INDEX('jiliarena_日报_底稿'!$P$2:$DS$34,MATCH($A19,'jiliarena_日报_底稿'!$P$2:$P$34,0),MATCH($M$3,'jiliarena_日报_底稿'!$P$3:$DS$3,0))} -> 63261 | N19: =IF(C19="","",ROUND(C19/B19,4)) -> 0.5469 | O19: =IF(K19="","",ROUND(K19/C19,0)) -> 110 | P19: =IF(L19="","",ROUND(K19/L19,6)) -> 0.104025 | Q19: =IF(G19="","",ROUND(G19/F19,1)) -> 1.5 | R19: =IF(L19="","",ROUND(L19/F19,0)) -> 253 | S19: =IF(L19="","",ROUND(L19/G19,0)) -> 164 | T19: =IF(S19="","",ROUND(S19/O19,1)) -> 1.5 | U19: =IF(M19="","",ROUND(M19/H19,0)) -> 1004 | V19: =IF(M19="","",L19-M19) -> 10933 | W19: =AB19+AE19+AH19+AK19+AN19+AQ19 -> 600686.94 | X19: {=index('jiliarena_日报_底稿'!$P$2:$DS$34,match($A19,'jiliarena_日报_底稿'!$P$2:$P$34,0),match("电子有效投注",'jiliarena_日报_底稿'!$P$3:$DS$3,0))+index('jiliarena_日报_底稿'!$P$2:$DS$34,match($A19,'jiliarena_日报_底稿'!$P$2:$P$34,0),match("真人有效投注",'jiliarena_日报_底稿'!$P$3:$DS$3,0))+index('jiliarena_日报_底稿'!$P$2:$DS$34,match($A19,'jiliarena_日报_底稿'!$P$2:$P$34,0),match("彩票有效投注",'jiliarena_日报_底稿'!$P$3:$DS$3,0))+index('jiliarena_日报_底稿'!$P$2:$DS$34,match($A19,'jiliarena_日报_底稿'!$P$2:$P$34,0),match("棋牌有效投注",'jiliarena_日报_底稿'!$P$3:$DS$3,0))+index('jiliarena_日报_底稿'!$P$2:$DS$34,match($A19,'jiliarena_日报_底稿'!$P$2:$P$34,0),match("捕鱼有效投注",'jiliarena_日报_底稿'!$P$3:$DS$3,0))+index('jiliarena_日报_底稿'!$P$2:$DS$34,match($A19,'jiliarena_日报_底稿'!$P$2:$P$34,0),match("体育有效投注",'jiliarena_日报_底稿'!$P$3:$DS$3,0))+index('jiliarena_日报_底稿'!$P$2:$DS$34,match($A19,'jiliarena_日报_底稿'!$P$2:$P$34,0),match("盘口彩票有效投注",'jiliarena_日报_底稿'!$P$3:$DS$3,0))} -> 565918.89 | Y19: =AB19+AE19+AH19+AK19+AN19+AQ19-AR19-AO19-AL19-AI19-AF19-AC19 -> 19024.71 | Z19: =AC19+AF19+AI19+AL19+AO19+AR19 -> 581662.23 | AA19: =IFERROR(ROUND(1-(Z19/W19),6),"") -> 0.031672 | AB19: {=INDEX('jiliarena_日报_底稿'!$P$2:$DS$34,MATCH($A19,'jiliarena_日报_底稿'!$P$2:$P$34,0),MATCH(AB$3,'jiliarena_日报_底稿'!$P$3:$DS$3,0))} -> 0 | AC19: {=INDEX('jiliarena_日报_底稿'!$P$2:$DS$34,MATCH($A19,'jiliarena_日报_底稿'!$P$2:$P$34,0),MATCH(AC$3,'jiliarena_日报_底稿'!$P$3:$DS$3,0))} -> 0 | AD19: =IF(AC19="","",ROUND((1-(AC19/AB19)),6)) -> #DIV/0! | AE19: {=INDEX('jiliarena_日报_底稿'!$P$2:$DS$34,MATCH($A19,'jiliarena_日报_底稿'!$P$2:$P$34,0),MATCH(AE$3,'jiliarena_日报_底稿'!$P$3:$DS$3,0))} -> 597649.12 | AF19: {=INDEX('jiliarena_日报_底稿'!$P$2:$DS$34,MATCH($A19,'jiliarena_日报_底稿'!$P$2:$P$34,0),MATCH(AF$3,'jiliarena_日报_底稿'!$P$3:$DS$3,0))} -> 578135.45 | AG19: =IF(AF19="","",ROUND((1-(AF19/AE19)),6)) -> 0.032651 | AH19: {=INDEX('jiliarena_日报_底稿'!$P$2:$DS$34,MATCH($A19,'jiliarena_日报_底稿'!$P$2:$P$34,0),MATCH(AH$3,'jiliarena_日报_底稿'!$P$3:$DS$3,0))} -> 840.72 | AI19: {=INDEX('jiliarena_日报_底稿'!$P$2:$DS$34,MATCH($A19,'jiliarena_日报_底稿'!$P$2:$P$34,0),MATCH(AI$3,'jiliarena_日报_底稿'!$P$3:$DS$3,0))} -> 330 | AJ19: =IF(AI19="","",ROUND((1-(AI19/AH19)),6)) -> 0.607479 | AK19: {=INDEX('jiliarena_日报_底稿'!$P$2:$DS$34,MATCH($A19,'jiliarena_日报_底稿'!$P$2:$P$34,0),MATCH(AK$3,'jiliarena_日报_底稿'!$P$3:$DS$3,0))} -> 2196.1 | AL19: {=INDEX('jiliarena_日报_底稿'!$P$2:$DS$34,MATCH($A19,'jiliarena_日报_底稿'!$P$2:$P$34,0),MATCH(AL$3,'jiliarena_日报_底稿'!$P$3:$DS$3,0))} -> 3196.78 | AM19: =IF(AL19="","",ROUND((1-(AL19/AK19)),6)) -> -0.455662 | AN19: {=INDEX('jiliarena_日报_底稿'!$P$2:$DS$34,MATCH($A19,'jiliarena_日报_底稿'!$P$2:$P$34,0),MATCH(AN$3,'jiliarena_日报_底稿'!$P$3:$DS$3,0))} -> 0 | AO19: {=INDEX('jiliarena_日报_底稿'!$P$2:$DS$34,MATCH($A19,'jiliarena_日报_底稿'!$P$2:$P$34,0),MATCH(AO$3,'jiliarena_日报_底稿'!$P$3:$DS$3,0))} -> 0 | AP19: =IF(AO19="","",ROUND((1-(AO19/AN19)),6)) -> #DIV/0! | AQ19: {=INDEX('jiliarena_日报_底稿'!$P$2:$DS$34,MATCH($A19,'jiliarena_日报_底稿'!$P$2:$P$34,0),MATCH(AQ$3,'jiliarena_日报_底稿'!$P$3:$DS$3,0))} -> 1 | AR19: {=INDEX('jiliarena_日报_底稿'!$P$2:$DS$34,MATCH($A19,'jiliarena_日报_底稿'!$P$2:$P$34,0),MATCH(AR$3,'jiliarena_日报_底稿'!$P$3:$DS$3,0))} -> 0 | AS19: =IF(AR19="","",ROUND((1-(AR19/AQ19)),6)) -> 1 | AT19: =SUMIFS('jiliarena_活动分析数据_底稿'!$K:$K,'jiliarena_活动分析数据_底稿'!$B:$B,$A19,'jiliarena_活动分析数据_底稿'!$L:$L,AT$3) -> 1759.84 | AU19: =SUMIFS('jiliarena_活动分析数据_底稿'!$K:$K,'jiliarena_活动分析数据_底稿'!$B:$B,$A19,'jiliarena_活动分析数据_底稿'!$L:$L,AU$3) -> 0 | AV19: =SUMIFS('jiliarena_活动分析数据_底稿'!$K:$K,'jiliarena_活动分析数据_底稿'!$B:$B,$A19,'jiliarena_活动分析数据_底稿'!$L:$L,AV$3) -> 374.44 | AW19: =SUMIFS('jiliarena_活动分析数据_底稿'!$K:$K,'jiliarena_活动分析数据_底稿'!$B:$B,$A19,'jiliarena_活动分析数据_底稿'!$L:$L,AW$3) -> 4149 | AX19: =SUMIFS('jiliarena_活动分析数据_底稿'!$K:$K,'jiliarena_活动分析数据_底稿'!$B:$B,$A19,'jiliarena_活动分析数据_底稿'!$L:$L,AX$3) -> 224 | AY19: =SUMIFS('jiliarena_活动分析数据_底稿'!$K:$K,'jiliarena_活动分析数据_底稿'!$B:$B,$A19,'jiliarena_活动分析数据_底稿'!$L:$L,AY$3) -> 0 | AZ19: =SUMIFS('jiliarena_活动分析数据_底稿'!$K:$K,'jiliarena_活动分析数据_底稿'!$B:$B,$A19,'jiliarena_活动分析数据_底稿'!$L:$L,AZ$3) -> 0 | BA19: =SUMIFS('jiliarena_活动分析数据_底稿'!$K:$K,'jiliarena_活动分析数据_底稿'!$B:$B,$A19,'jiliarena_活动分析数据_底稿'!$L:$L,BA$3) -> 0 | ... BP19: =SUMIFS('jiliarena_活动分析数据_底稿'!$K:$K,'jiliarena_活动分析数据_底稿'!$B:$B,$A19,'jiliarena_活动分析数据_底稿'!$L:$L,BP$3) -> 0 | BQ19: =SUM(AT19:BP19) -> 9542 | BR19: =AT19 -> 1759.84 | BS19: =BB19 -> 223.22 | BT19: =iferror(IF(BQ19="","",ROUND(BQ19/X19,6)),"") -> 0.016861 | BU19: =iferror(BQ19/L19,"") -> 0.12860878 | BV19: =iferror(BQ19/Y19,"") -> 0.50155824 | BW19: =IF(BQ19="","",Y19-BQ19) -> 9482.71 | BX19: =iferror(BQ19/BW19,"") -> 1.0062524 | BY19: =L19*$BY$1 -> 1788.0754 | BZ19: =M19*$BZ$1 -> 126.522 | CA19: =BY19+BZ19 -> 1914.5974 | CB19: =IF(Y19="","",ROUND(Y19*9%,0)) -> 1712 | CC19: =iferror(CA19/BW19,"") -> 0.20190403 | CD19: {=index('jiliarena_日报_底稿'!$P$3:$DS$34,match(A19,'jiliarena_日报_底稿'!$P$3:$P$34,0),match("综合性分红",'jiliarena_日报_底稿'!$P$3:$DS$3,0))} -> 0 | CF19: {=INDEX('jiliarena_日报_底稿'!$P$2:$DS$34,MATCH($A19,'jiliarena_日报_底稿'!$P$2:$P$34,0),MATCH(CF$3,'jiliarena_日报_底稿'!$P$3:$DS$3,0))} -> 0 | CG19: {=-INDEX('jiliarena_日报_底稿'!$P$2:$DS$34,MATCH($A19,'jiliarena_日报_底稿'!$P$2:$P$34,0),MATCH(CG$3,'jiliarena_日报_底稿'!$P$3:$DS$3,0))} -> 0 | CH19: {=INDEX('jiliarena_日报_底稿'!$P$2:$DS$34,MATCH($A19,'jiliarena_日报_底稿'!$P$2:$P$34,0),MATCH(CH$3,'jiliarena_日报_底稿'!$P$3:$DS$3,0))} -> 141243.58 | CI19: =IF(CA19="","",BW19-CA19-CD19-CB19) -> 5856.1126 | CJ19: =IFERROR(month(A19),"") -> 3 | CK19: =IFERROR(DAY(A19),"") -> 8
A20: SUB total | B20: =SUM(B13:B19) -> 1301 | C20: =SUM(C13:C19) -> 797 | D20: =SUM(D13:D19) -> 23061 | E20: =SUM(E13:E19) -> 119 | F20: =SUM(F13:F19) -> 2591 | G20: =SUM(G13:G19) -> 3703 | H20: =SUM(H13:H19) -> 591 | I20: =SUM(I13:I19) -> 749 | ... M20: =SUM(M13:M19) -> 474389 | N20: =IF(C20="","",ROUND(C20/B20,4)) -> 0.6126 | O20: =IF(K20="","",ROUND(K20/C20,0)) -> 147 | P20: =IF(L20="","",ROUND(K20/L20,6)) -> 0.189094 | Q20: =IF(G20="","",ROUND(G20/F20,1)) -> 1.4 | R20: =IF(L20="","",ROUND(L20/F20,0)) -> 239 | S20: =IF(L20="","",ROUND(L20/G20,0)) -> 167 | T20: =IF(S20="","",ROUND(S20/O20,1)) -> 1.1 | U20: =IF(M20="","",ROUND(M20/H20,0)) -> 803 | V20: =IF(M20="","",L20-M20) -> 144188 | W20: =SUM(W13:W19) -> 5326810.6 | X20: =SUM(X13:X19) -> 4997414.4 | Y20: =SUM(Y13:Y19) -> 189743.62 | Z20: =SUM(Z13:Z19) -> 5137067 | AA20: =IFERROR(ROUND(1-(Z20/W20),6),"") -> 0.03562 | AB20: =SUM(AB13:AB19) -> 26 | AC20: =SUM(AC13:AC19) -> 4 | AD20: =IF(AC20="","",ROUND((1-(AC20/AB20)),6)) -> 0.846154 | AE20: =SUM(AE13:AE19) -> 5203166.4 | AF20: =SUM(AF13:AF19) -> 5011549.8 | AG20: =IF(AF20="","",ROUND((1-(AF20/AE20)),6)) -> 0.036827 | AH20: =SUM(AH13:AH19) -> 25508.14 | AI20: =SUM(AI13:AI19) -> 23724.57 | AJ20: =IF(AI20="","",ROUND((1-(AI20/AH20)),6)) -> 0.069922 | AK20: =SUM(AK13:AK19) -> 96012.05 | AL20: =SUM(AL13:AL19) -> 100420.32 | AM20: =IF(AL20="","",ROUND((1-(AL20/AK20)),6)) -> -0.045914 | AN20: =SUM(AN13:AN19) -> 2078 | AO20: =SUM(AO13:AO19) -> 1368.27 | AP20: =IF(AO20="","",ROUND((1-(AO20/AN20)),6)) -> 0.341545 | AQ20: =SUM(AQ13:AQ19) -> 20 | AR20: =SUM(AR13:AR19) -> 0 | AS20: =IF(AR20="","",ROUND((1-(AR20/AQ20)),6)) -> 1 | AT20: =SUM(AT13:AT19) -> 17928.57 | AU20: =SUM(AU13:AU19) -> 0 | AV20: =SUM(AV13:AV19) -> 4310.68 | AW20: =SUM(AW13:AW19) -> 30329 | AX20: =SUM(AX13:AX19) -> 2264 | AY20: =SUM(AY13:AY19) -> 0 | AZ20: =SUM(AZ13:AZ19) -> 0 | BA20: =SUM(BA13:BA19) -> 0 | ... BS20: =SUM(BS13:BS19) -> 1925.41 | BT20: =iferror(IF(BQ20="","",ROUND(BQ20/X20,6)),"") -> 0.017038 | BU20: =iferror(BQ20/L20,"") -> 0.13765006 | BV20: =iferror(BQ20/Y20,"") -> 0.44874847 | BW20: =IF(BQ20="","",Y20-BQ20) -> 104596.46 | BX20: =iferror(BQ20/BW20,"") -> 0.81405394 | BY20: =L20*$BY$1 -> 14907.706 | BZ20: =M20*$BZ$1 -> 948.778 | CA20: =BY20+BZ20 -> 15856.484 | CB20: =IF(Y20="","",ROUND(Y20*9%,0)) -> 17077 | CC20: =iferror(CA20/BW20,"") -> 0.15159675 | CD20: =SUM(CD13:CD19) -> 0 | CE20: =SUM(CE13:CE19) -> 0 | CF20: =SUM(CF13:CF19) -> 0 | CG20: =SUM(CG13:CG19) -> 0 | CH20: =SUM(CH13:CH19) -> 921932.35 | CI20: =IF(CA20="","",BW20-CA20-CD20-CB20) -> 71662.976 | CJ20: =IFERROR(month(A20),"") | CK20: =IFERROR(DAY(A20),"")
A21: =A19+1 -> 46090 | B21: {=INDEX('jiliarena_日报_底稿'!$A$3:$N$34,MATCH($A21,'jiliarena_日报_底稿'!$A$3:$A$34,0),MATCH(B$3,'jiliarena_日报_底稿'!$A$3:$N$3,0))} -> 115 | C21: {=INDEX('jiliarena_日报_底稿'!$A$3:$N$34,MATCH($A21,'jiliarena_日报_底稿'!$A$3:$A$34,0),MATCH(C$3,'jiliarena_日报_底稿'!$A$3:$N$3,0))} -> 53 | D21: {=INDEX('jiliarena_日报_底稿'!$A$3:$N$34,MATCH($A21,'jiliarena_日报_底稿'!$A$3:$A$34,0),MATCH(D$3,'jiliarena_日报_底稿'!$A$3:$N$3,0))} -> 2668 | E21: 8 | F21: {=INDEX('jiliarena_日报_底稿'!$A$3:$N$34,MATCH($A21,'jiliarena_日报_底稿'!$A$3:$A$34,0),MATCH(F$3,'jiliarena_日报_底稿'!$A$3:$N$3,0))} -> 203 | G21: =SUMIFS('渠道充值成功率_底稿'!$F:$F,'渠道充值成功率_底稿'!$A:$A,A21) -> 301 | H21: {=INDEX('jiliarena_日报_底稿'!$A$3:$N$34,MATCH($A21,'jiliarena_日报_底稿'!$A$3:$A$34,0),MATCH(H$3,'jiliarena_日报_底稿'!$A$3:$N$3,0))} -> 59 | I21: 77 | J21: {=INDEX('jiliarena_日报_底稿'!$A$3:$N$34,MATCH($A21,'jiliarena_日报_底稿'!$A$3:$A$34,0),MATCH(J$3,'jiliarena_日报_底稿'!$A$3:$N$3,0))} -> 1866 | K21: =SUMIFS('渠道充值成功率_底稿'!$J:$J,'渠道充值成功率_底稿'!$A:$A,$A21) -> 6845 | L21: {=INDEX('jiliarena_日报_底稿'!$A$3:$N$34,MATCH($A21,'jiliarena_日报_底稿'!$A$3:$A$34,0),MATCH(L$3,'jiliarena_日报_底稿'!$A$3:$N$3,0))} -> 43525 | M21: {=INDEX('jiliarena_日报_底稿'!$P$2:$DS$34,MATCH($A21,'jiliarena_日报_底稿'!$P$2:$P$34,0),MATCH($M$3,'jiliarena_日报_底稿'!$P$3:$DS$3,0))} -> 42820 | N21: =IF(C21="","",ROUND(C21/B21,4)) -> 0.4609 | O21: =IF(K21="","",ROUND(K21/C21,0)) -> 129 | P21: =IF(L21="","",ROUND(K21/L21,6)) -> 0.157266 | Q21: =IF(G21="","",ROUND(G21/F21,1)) -> 1.5 | R21: =IF(L21="","",ROUND(L21/F21,0)) -> 214 | S21: =IF(L21="","",ROUND(L21/G21,0)) -> 145 | T21: =IF(S21="","",ROUND(S21/O21,1)) -> 1.1 | U21: =IF(M21="","",ROUND(M21/H21,0)) -> 726 | V21: =IF(M21="","",L21-M21) -> 705 | W21: =AB21+AE21+AH21+AK21+AN21+AQ21 -> 360673.28 | X21: {=index('jiliarena_日报_底稿'!$P$2:$DS$34,match($A21,'jiliarena_日报_底稿'!$P$2:$P$34,0),match("电子有效投注",'jiliarena_日报_底稿'!$P$3:$DS$3,0))+index('jiliarena_日报_底稿'!$P$2:$DS$34,match($A21,'jiliarena_日报_底稿'!$P$2:$P$34,0),match("真人有效投注",'jiliarena_日报_底稿'!$P$3:$DS$3,0))+index('jiliarena_日报_底稿'!$P$2:$DS$34,match($A21,'jiliarena_日报_底稿'!$P$2:$P$34,0),match("彩票有效投注",'jiliarena_日报_底稿'!$P$3:$DS$3,0))+index('jiliarena_日报_底稿'!$P$2:$DS$34,match($A21,'jiliarena_日报_底稿'!$P$2:$P$34,0),match("棋牌有效投注",'jiliarena_日报_底稿'!$P$3:$DS$3,0))+index('jiliarena_日报_底稿'!$P$2:$DS$34,match($A21,'jiliarena_日报_底稿'!$P$2:$P$34,0),match("捕鱼有效投注",'jiliarena_日报_底稿'!$P$3:$DS$3,0))+index('jiliarena_日报_底稿'!$P$2:$DS$34,match($A21,'jiliarena_日报_底稿'!$P$2:$P$34,0),match("体育有效投注",'jiliarena_日报_底稿'!$P$3:$DS$3,0))+index('jiliarena_日报_底稿'!$P$2:$DS$34,match($A21,'jiliarena_日报_底稿'!$P$2:$P$34,0),match("盘口彩票有效投注",'jiliarena_日报_底稿'!$P$3:$DS$3,0))} -> 337673 | Y21: =AB21+AE21+AH21+AK21+AN21+AQ21-AR21-AO21-AL21-AI21-AF21-AC21 -> 15777.649 | Z21: =AC21+AF21+AI21+AL21+AO21+AR21 -> 344895.63 | AA21: =IFERROR(ROUND(1-(Z21/W21),6),"") -> 0.043745 | AB21: {=INDEX('jiliarena_日报_底稿'!$P$2:$DS$34,MATCH($A21,'jiliarena_日报_底稿'!$P$2:$P$34,0),MATCH(AB$3,'jiliarena_日报_底稿'!$P$3:$DS$3,0))} -> 0 | AC21: {=INDEX('jiliarena_日报_底稿'!$P$2:$DS$34,MATCH($A21,'jiliarena_日报_底稿'!$P$2:$P$34,0),MATCH(AC$3,'jiliarena_日报_底稿'!$P$3:$DS$3,0))} -> 0 | AD21: =IF(AC21="","",ROUND((1-(AC21/AB21)),6)) -> #DIV/0! | AE21: {=INDEX('jiliarena_日报_底稿'!$P$2:$DS$34,MATCH($A21,'jiliarena_日报_底稿'!$P$2:$P$34,0),MATCH(AE$3,'jiliarena_日报_底稿'!$P$3:$DS$3,0))} -> 357631.53 | AF21: {=INDEX('jiliarena_日报_底稿'!$P$2:$DS$34,MATCH($A21,'jiliarena_日报_底稿'!$P$2:$P$34,0),MATCH(AF$3,'jiliarena_日报_底稿'!$P$3:$DS$3,0))} -> 342343.69 | AG21: =IF(AF21="","",ROUND((1-(AF21/AE21)),6)) -> 0.042747 | AH21: {=INDEX('jiliarena_日报_底稿'!$P$2:$DS$34,MATCH($A21,'jiliarena_日报_底稿'!$P$2:$P$34,0),MATCH(AH$3,'jiliarena_日报_底稿'!$P$3:$DS$3,0))} -> 1085 | AI21: {=INDEX('jiliarena_日报_底稿'!$P$2:$DS$34,MATCH($A21,'jiliarena_日报_底稿'!$P$2:$P$34,0),MATCH(AI$3,'jiliarena_日报_底稿'!$P$3:$DS$3,0))} -> 937.5 | AJ21: =IF(AI21="","",ROUND((1-(AI21/AH21)),6)) -> 0.135945 | AK21: {=INDEX('jiliarena_日报_底稿'!$P$2:$DS$34,MATCH($A21,'jiliarena_日报_底稿'!$P$2:$P$34,0),MATCH(AK$3,'jiliarena_日报_底稿'!$P$3:$DS$3,0))} -> 1953.75 | AL21: {=INDEX('jiliarena_日报_底稿'!$P$2:$DS$34,MATCH($A21,'jiliarena_日报_底稿'!$P$2:$P$34,0),MATCH(AL$3,'jiliarena_日报_底稿'!$P$3:$DS$3,0))} -> 1614.44 | AM21: =IF(AL21="","",ROUND((1-(AL21/AK21)),6)) -> 0.173671 | AN21: {=INDEX('jiliarena_日报_底稿'!$P$2:$DS$34,MATCH($A21,'jiliarena_日报_底稿'!$P$2:$P$34,0),MATCH(AN$3,'jiliarena_日报_底稿'!$P$3:$DS$3,0))} -> 0 | AO21: {=INDEX('jiliarena_日报_底稿'!$P$2:$DS$34,MATCH($A21,'jiliarena_日报_底稿'!$P$2:$P$34,0),MATCH(AO$3,'jiliarena_日报_底稿'!$P$3:$DS$3,0))} -> 0 | AP21: =IF(AO21="","",ROUND((1-(AO21/AN21)),6)) -> #DIV/0! | AQ21: {=INDEX('jiliarena_日报_底稿'!$P$2:$DS$34,MATCH($A21,'jiliarena_日报_底稿'!$P$2:$P$34,0),MATCH(AQ$3,'jiliarena_日报_底稿'!$P$3:$DS$3,0))} -> 3 | AR21: {=INDEX('jiliarena_日报_底稿'!$P$2:$DS$34,MATCH($A21,'jiliarena_日报_底稿'!$P$2:$P$34,0),MATCH(AR$3,'jiliarena_日报_底稿'!$P$3:$DS$3,0))} -> 0 | AS21: =IF(AR21="","",ROUND((1-(AR21/AQ21)),6)) -> 1 | AT21: =SUMIFS('jiliarena_活动分析数据_底稿'!$K:$K,'jiliarena_活动分析数据_底稿'!$B:$B,$A21,'jiliarena_活动分析数据_底稿'!$L:$L,AT$3) -> 2055.56 | AU21: =SUMIFS('jiliarena_活动分析数据_底稿'!$K:$K,'jiliarena_活动分析数据_底稿'!$B:$B,$A21,'jiliarena_活动分析数据_底稿'!$L:$L,AU$3) -> 0 | AV21: =SUMIFS('jiliarena_活动分析数据_底稿'!$K:$K,'jiliarena_活动分析数据_底稿'!$B:$B,$A21,'jiliarena_活动分析数据_底稿'!$L:$L,AV$3) -> 394.34 | AW21: =SUMIFS('jiliarena_活动分析数据_底稿'!$K:$K,'jiliarena_活动分析数据_底稿'!$B:$B,$A21,'jiliarena_活动分析数据_底稿'!$L:$L,AW$3) -> 3706 | AX21: =SUMIFS('jiliarena_活动分析数据_底稿'!$K:$K,'jiliarena_活动分析数据_底稿'!$B:$B,$A21,'jiliarena_活动分析数据_底稿'!$L:$L,AX$3) -> 170 | AY21: =SUMIFS('jiliarena_活动分析数据_底稿'!$K:$K,'jiliarena_活动分析数据_底稿'!$B:$B,$A21,'jiliarena_活动分析数据_底稿'!$L:$L,AY$3) -> 0 | AZ21: =SUMIFS('jiliarena_活动分析数据_底稿'!$K:$K,'jiliarena_活动分析数据_底稿'!$B:$B,$A21,'jiliarena_活动分析数据_底稿'!$L:$L,AZ$3) -> 0 | BA21: =SUMIFS('jiliarena_活动分析数据_底稿'!$K:$K,'jiliarena_活动分析数据_底稿'!$B:$B,$A21,'jiliarena_活动分析数据_底稿'!$L:$L,BA$3) -> 0 | ... BP21: =SUMIFS('jiliarena_活动分析数据_底稿'!$K:$K,'jiliarena_活动分析数据_底稿'!$B:$B,$A21,'jiliarena_活动分析数据_底稿'!$L:$L,BP$3) -> 0 | BQ21: =SUM(AT21:BP21) -> 8507.33 | BR21: =AT21 -> 2055.56 | BS21: =BB21 -> 255.43 | BT21: =iferror(IF(BQ21="","",ROUND(BQ21/X21,6)),"") -> 0.025194 | BU21: =iferror(BQ21/L21,"") -> 0.19545847 | BV21: =iferror(BQ21/Y21,"") -> 0.53920137 | BW21: =IF(BQ21="","",Y21-BQ21) -> 7270.319 | BX21: =iferror(BQ21/BW21,"") -> 1.1701454 | BY21: =L21*$BY$1 -> 1048.9525 | BZ21: =M21*$BZ$1 -> 85.64 | CA21: =BY21+BZ21 -> 1134.5925 | CB21: =IF(Y21="","",ROUND(Y21*9%,0)) -> 1420 | CC21: =iferror(CA21/BW21,"") -> 0.15605815 | CD21: {=index('jiliarena_日报_底稿'!$P$3:$DS$34,match(A21,'jiliarena_日报_底稿'!$P$3:$P$34,0),match("综合性分红",'jiliarena_日报_底稿'!$P$3:$DS$3,0))} -> 0 | CF21: {=INDEX('jiliarena_日报_底稿'!$P$2:$DS$34,MATCH($A21,'jiliarena_日报_底稿'!$P$2:$P$34,0),MATCH(CF$3,'jiliarena_日报_底稿'!$P$3:$DS$3,0))} -> 0 | CG21: {=-INDEX('jiliarena_日报_底稿'!$P$2:$DS$34,MATCH($A21,'jiliarena_日报_底稿'!$P$2:$P$34,0),MATCH(CG$3,'jiliarena_日报_底稿'!$P$3:$DS$3,0))} -> 0 | CH21: {=INDEX('jiliarena_日报_底稿'!$P$2:$DS$34,MATCH($A21,'jiliarena_日报_底稿'!$P$2:$P$34,0),MATCH(CH$3,'jiliarena_日报_底稿'!$P$3:$DS$3,0))} -> 140364.91 | CI21: =IF(CA21="","",BW21-CA21-CD21-CB21) -> 4715.7265 | CJ21: =IFERROR(month(A21),"") -> 3 | CK21: =IFERROR(DAY(A21),"") -> 9
A22: =A21+1 -> 46091 | B22: {=INDEX('jiliarena_日报_底稿'!$A$3:$N$34,MATCH($A22,'jiliarena_日报_底稿'!$A$3:$A$34,0),MATCH(B$3,'jiliarena_日报_底稿'!$A$3:$N$3,0))} -> 104 | C22: {=INDEX('jiliarena_日报_底稿'!$A$3:$N$34,MATCH($A22,'jiliarena_日报_底稿'!$A$3:$A$34,0),MATCH(C$3,'jiliarena_日报_底稿'!$A$3:$N$3,0))} -> 66 | D22: {=INDEX('jiliarena_日报_底稿'!$A$3:$N$34,MATCH($A22,'jiliarena_日报_底稿'!$A$3:$A$34,0),MATCH(D$3,'jiliarena_日报_底稿'!$A$3:$N$3,0))} -> 2516 | E22: 14 | F22: {=INDEX('jiliarena_日报_底稿'!$A$3:$N$34,MATCH($A22,'jiliarena_日报_底稿'!$A$3:$A$34,0),MATCH(F$3,'jiliarena_日报_底稿'!$A$3:$N$3,0))} -> 231 | G22: =SUMIFS('渠道充值成功率_底稿'!$F:$F,'渠道充值成功率_底稿'!$A:$A,A22) -> 342 | H22: {=INDEX('jiliarena_日报_底稿'!$A$3:$N$34,MATCH($A22,'jiliarena_日报_底稿'!$A$3:$A$34,0),MATCH(H$3,'jiliarena_日报_底稿'!$A$3:$N$3,0))} -> 67 | I22: 78 | J22: {=INDEX('jiliarena_日报_底稿'!$A$3:$N$34,MATCH($A22,'jiliarena_日报_底稿'!$A$3:$A$34,0),MATCH(J$3,'jiliarena_日报_底稿'!$A$3:$N$3,0))} -> 1963 | K22: =SUMIFS('渠道充值成功率_底稿'!$J:$J,'渠道充值成功率_底稿'!$A:$A,$A22) -> 7738 | L22: {=INDEX('jiliarena_日报_底稿'!$A$3:$N$34,MATCH($A22,'jiliarena_日报_底稿'!$A$3:$A$34,0),MATCH(L$3,'jiliarena_日报_底稿'!$A$3:$N$3,0))} -> 53745 | M22: {=INDEX('jiliarena_日报_底稿'!$P$2:$DS$34,MATCH($A22,'jiliarena_日报_底稿'!$P$2:$P$34,0),MATCH($M$3,'jiliarena_日报_底稿'!$P$3:$DS$3,0))} -> 45929 | N22: =IF(C22="","",ROUND(C22/B22,4)) -> 0.6346 | O22: =IF(K22="","",ROUND(K22/C22,0)) -> 117 | P22: =IF(L22="","",ROUND(K22/L22,6)) -> 0.143976 | Q22: =IF(G22="","",ROUND(G22/F22,1)) -> 1.5 | R22: =IF(L22="","",ROUND(L22/F22,0)) -> 233 | S22: =IF(L22="","",ROUND(L22/G22,0)) -> 157 | T22: =IF(S22="","",ROUND(S22/O22,1)) -> 1.3 | U22: =IF(M22="","",ROUND(M22/H22,0)) -> 686 | V22: =IF(M22="","",L22-M22) -> 7816 | W22: =AB22+AE22+AH22+AK22+AN22+AQ22 -> 523584.82 | X22: {=index('jiliarena_日报_底稿'!$P$2:$DS$34,match($A22,'jiliarena_日报_底稿'!$P$2:$P$34,0),match("电子有效投注",'jiliarena_日报_底稿'!$P$3:$DS$3,0))+index('jiliarena_日报_底稿'!$P$2:$DS$34,match($A22,'jiliarena_日报_底稿'!$P$2:$P$34,0),match("真人有效投注",'jiliarena_日报_底稿'!$P$3:$DS$3,0))+index('jiliarena_日报_底稿'!$P$2:$DS$34,match($A22,'jiliarena_日报_底稿'!$P$2:$P$34,0),match("彩票有效投注",'jiliarena_日报_底稿'!$P$3:$DS$3,0))+index('jiliarena_日报_底稿'!$P$2:$DS$34,match($A22,'jiliarena_日报_底稿'!$P$2:$P$34,0),match("棋牌有效投注",'jiliarena_日报_底稿'!$P$3:$DS$3,0))+index('jiliarena_日报_底稿'!$P$2:$DS$34,match($A22,'jiliarena_日报_底稿'!$P$2:$P$34,0),match("捕鱼有效投注",'jiliarena_日报_底稿'!$P$3:$DS$3,0))+index('jiliarena_日报_底稿'!$P$2:$DS$34,match($A22,'jiliarena_日报_底稿'!$P$2:$P$34,0),match("体育有效投注",'jiliarena_日报_底稿'!$P$3:$DS$3,0))+index('jiliarena_日报_底稿'!$P$2:$DS$34,match($A22,'jiliarena_日报_底稿'!$P$2:$P$34,0),match("盘口彩票有效投注",'jiliarena_日报_底稿'!$P$3:$DS$3,0))} -> 486699.45 | Y22: =AB22+AE22+AH22+AK22+AN22+AQ22-AR22-AO22-AL22-AI22-AF22-AC22 -> 19212.095 | Z22: =AC22+AF22+AI22+AL22+AO22+AR22 -> 504372.72 | AA22: =IFERROR(ROUND(1-(Z22/W22),6),"") -> 0.036693 | AB22: {=INDEX('jiliarena_日报_底稿'!$P$2:$DS$34,MATCH($A22,'jiliarena_日报_底稿'!$P$2:$P$34,0),MATCH(AB$3,'jiliarena_日报_底稿'!$P$3:$DS$3,0))} -> 0 | AC22: {=INDEX('jiliarena_日报_底稿'!$P$2:$DS$34,MATCH($A22,'jiliarena_日报_底稿'!$P$2:$P$34,0),MATCH(AC$3,'jiliarena_日报_底稿'!$P$3:$DS$3,0))} -> 0 | AD22: =IF(AC22="","",ROUND((1-(AC22/AB22)),6)) -> #DIV/0! | AE22: {=INDEX('jiliarena_日报_底稿'!$P$2:$DS$34,MATCH($A22,'jiliarena_日报_底稿'!$P$2:$P$34,0),MATCH(AE$3,'jiliarena_日报_底稿'!$P$3:$DS$3,0))} -> 512460.42 | AF22: {=INDEX('jiliarena_日报_底稿'!$P$2:$DS$34,MATCH($A22,'jiliarena_日报_底稿'!$P$2:$P$34,0),MATCH(AF$3,'jiliarena_日报_底稿'!$P$3:$DS$3,0))} -> 492843.33 | AG22: =IF(AF22="","",ROUND((1-(AF22/AE22)),6)) -> 0.03828 | AH22: {=INDEX('jiliarena_日报_底稿'!$P$2:$DS$34,MATCH($A22,'jiliarena_日报_底稿'!$P$2:$P$34,0),MATCH(AH$3,'jiliarena_日报_底稿'!$P$3:$DS$3,0))} -> 2660 | AI22: {=INDEX('jiliarena_日报_底稿'!$P$2:$DS$34,MATCH($A22,'jiliarena_日报_底稿'!$P$2:$P$34,0),MATCH(AI$3,'jiliarena_日报_底稿'!$P$3:$DS$3,0))} -> 3065 | AJ22: =IF(AI22="","",ROUND((1-(AI22/AH22)),6)) -> -0.152256 | AK22: {=INDEX('jiliarena_日报_底稿'!$P$2:$DS$34,MATCH($A22,'jiliarena_日报_底稿'!$P$2:$P$34,0),MATCH(AK$3,'jiliarena_日报_底稿'!$P$3:$DS$3,0))} -> 8461.4 | AL22: {=INDEX('jiliarena_日报_底稿'!$P$2:$DS$34,MATCH($A22,'jiliarena_日报_底稿'!$P$2:$P$34,0),MATCH(AL$3,'jiliarena_日报_底稿'!$P$3:$DS$3,0))} -> 8464.4 | AM22: =IF(AL22="","",ROUND((1-(AL22/AK22)),6)) -> -0.000355 | AN22: {=INDEX('jiliarena_日报_底稿'!$P$2:$DS$34,MATCH($A22,'jiliarena_日报_底稿'!$P$2:$P$34,0),MATCH(AN$3,'jiliarena_日报_底稿'!$P$3:$DS$3,0))} -> 0 | AO22: {=INDEX('jiliarena_日报_底稿'!$P$2:$DS$34,MATCH($A22,'jiliarena_日报_底稿'!$P$2:$P$34,0),MATCH(AO$3,'jiliarena_日报_底稿'!$P$3:$DS$3,0))} -> 0 | AP22: =IF(AO22="","",ROUND((1-(AO22/AN22)),6)) -> #DIV/0! | AQ22: {=INDEX('jiliarena_日报_底稿'!$P$2:$DS$34,MATCH($A22,'jiliarena_日报_底稿'!$P$2:$P$34,0),MATCH(AQ$3,'jiliarena_日报_底稿'!$P$3:$DS$3,0))} -> 3 | AR22: {=INDEX('jiliarena_日报_底稿'!$P$2:$DS$34,MATCH($A22,'jiliarena_日报_底稿'!$P$2:$P$34,0),MATCH(AR$3,'jiliarena_日报_底稿'!$P$3:$DS$3,0))} -> 0 | AS22: =IF(AR22="","",ROUND((1-(AR22/AQ22)),6)) -> 1 | AT22: =SUMIFS('jiliarena_活动分析数据_底稿'!$K:$K,'jiliarena_活动分析数据_底稿'!$B:$B,$A22,'jiliarena_活动分析数据_底稿'!$L:$L,AT$3) -> 872.27 | AU22: =SUMIFS('jiliarena_活动分析数据_底稿'!$K:$K,'jiliarena_活动分析数据_底稿'!$B:$B,$A22,'jiliarena_活动分析数据_底稿'!$L:$L,AU$3) -> 0 | AV22: =SUMIFS('jiliarena_活动分析数据_底稿'!$K:$K,'jiliarena_活动分析数据_底稿'!$B:$B,$A22,'jiliarena_活动分析数据_底稿'!$L:$L,AV$3) -> 354.46 | AW22: =SUMIFS('jiliarena_活动分析数据_底稿'!$K:$K,'jiliarena_活动分析数据_底稿'!$B:$B,$A22,'jiliarena_活动分析数据_底稿'!$L:$L,AW$3) -> 3624 | AX22: =SUMIFS('jiliarena_活动分析数据_底稿'!$K:$K,'jiliarena_活动分析数据_底稿'!$B:$B,$A22,'jiliarena_活动分析数据_底稿'!$L:$L,AX$3) -> 186 | AY22: =SUMIFS('jiliarena_活动分析数据_底稿'!$K:$K,'jiliarena_活动分析数据_底稿'!$B:$B,$A22,'jiliarena_活动分析数据_底稿'!$L:$L,AY$3) -> 0 | AZ22: =SUMIFS('jiliarena_活动分析数据_底稿'!$K:$K,'jiliarena_活动分析数据_底稿'!$B:$B,$A22,'jiliarena_活动分析数据_底稿'!$L:$L,AZ$3) -> 0 | BA22: =SUMIFS('jiliarena_活动分析数据_底稿'!$K:$K,'jiliarena_活动分析数据_底稿'!$B:$B,$A22,'jiliarena_活动分析数据_底稿'!$L:$L,BA$3) -> 0 | ... BP22: =SUMIFS('jiliarena_活动分析数据_底稿'!$K:$K,'jiliarena_活动分析数据_底稿'!$B:$B,$A22,'jiliarena_活动分析数据_底稿'!$L:$L,BP$3) -> 0 | BQ22: =SUM(AT22:BP22) -> 7476.27 | BR22: =AT22 -> 872.27 | BS22: =BB22 -> 341.04 | BT22: =iferror(IF(BQ22="","",ROUND(BQ22/X22,6)),"") -> 0.015361 | BU22: =iferror(BQ22/L22,"") -> 0.13910634 | BV22: =iferror(BQ22/Y22,"") -> 0.38914392 | BW22: =IF(BQ22="","",Y22-BQ22) -> 11735.825 | BX22: =iferror(BQ22/BW22,"") -> 0.63704682 | BY22: =L22*$BY$1 -> 1295.2545 | BZ22: =M22*$BZ$1 -> 91.858 | CA22: =BY22+BZ22 -> 1387.1125 | CB22: =IF(Y22="","",ROUND(Y22*9%,0)) -> 1729 | CC22: =iferror(CA22/BW22,"") -> 0.11819472 | CD22: {=index('jiliarena_日报_底稿'!$P$3:$DS$34,match(A22,'jiliarena_日报_底稿'!$P$3:$P$34,0),match("综合性分红",'jiliarena_日报_底稿'!$P$3:$DS$3,0))} -> 0 | CF22: {=INDEX('jiliarena_日报_底稿'!$P$2:$DS$34,MATCH($A22,'jiliarena_日报_底稿'!$P$2:$P$34,0),MATCH(CF$3,'jiliarena_日报_底稿'!$P$3:$DS$3,0))} -> 0 | CG22: {=-INDEX('jiliarena_日报_底稿'!$P$2:$DS$34,MATCH($A22,'jiliarena_日报_底稿'!$P$2:$P$34,0),MATCH(CG$3,'jiliarena_日报_底稿'!$P$3:$DS$3,0))} -> 0 | CH22: {=INDEX('jiliarena_日报_底稿'!$P$2:$DS$34,MATCH($A22,'jiliarena_日报_底稿'!$P$2:$P$34,0),MATCH(CH$3,'jiliarena_日报_底稿'!$P$3:$DS$3,0))} -> 139051.88 | CI22: =IF(CA22="","",BW22-CA22-CD22-CB22) -> 8619.7125 | CJ22: =IFERROR(month(A22),"") -> 3 | CK22: =IFERROR(DAY(A22),"") -> 10
A23: =A22+1 -> 46092 | B23: {=INDEX('jiliarena_日报_底稿'!$A$3:$N$34,MATCH($A23,'jiliarena_日报_底稿'!$A$3:$A$34,0),MATCH(B$3,'jiliarena_日报_底稿'!$A$3:$N$3,0))} -> 281 | C23: {=INDEX('jiliarena_日报_底稿'!$A$3:$N$34,MATCH($A23,'jiliarena_日报_底稿'!$A$3:$A$34,0),MATCH(C$3,'jiliarena_日报_底稿'!$A$3:$N$3,0))} -> 119 | D23: {=INDEX('jiliarena_日报_底稿'!$A$3:$N$34,MATCH($A23,'jiliarena_日报_底稿'!$A$3:$A$34,0),MATCH(D$3,'jiliarena_日报_底稿'!$A$3:$N$3,0))} -> 6025 | E23: 6 | F23: {=INDEX('jiliarena_日报_底稿'!$A$3:$N$34,MATCH($A23,'jiliarena_日报_底稿'!$A$3:$A$34,0),MATCH(F$3,'jiliarena_日报_底稿'!$A$3:$N$3,0))} -> 327 | G23: =SUMIFS('渠道充值成功率_底稿'!$F:$F,'渠道充值成功率_底稿'!$A:$A,A23) -> 408 | H23: {=INDEX('jiliarena_日报_底稿'!$A$3:$N$34,MATCH($A23,'jiliarena_日报_底稿'!$A$3:$A$34,0),MATCH(H$3,'jiliarena_日报_底稿'!$A$3:$N$3,0))} -> 107 | I23: 124 | J23: {=INDEX('jiliarena_日报_底稿'!$A$3:$N$34,MATCH($A23,'jiliarena_日报_底稿'!$A$3:$A$34,0),MATCH(J$3,'jiliarena_日报_底稿'!$A$3:$N$3,0))} -> 4665 | K23: =SUMIFS('渠道充值成功率_底稿'!$J:$J,'渠道充值成功率_底稿'!$A:$A,$A23) -> 14110 | L23: {=INDEX('jiliarena_日报_底稿'!$A$3:$N$34,MATCH($A23,'jiliarena_日报_底稿'!$A$3:$A$34,0),MATCH(L$3,'jiliarena_日报_底稿'!$A$3:$N$3,0))} -> 53268 | M23: {=INDEX('jiliarena_日报_底稿'!$P$2:$DS$34,MATCH($A23,'jiliarena_日报_底稿'!$P$2:$P$34,0),MATCH($M$3,'jiliarena_日报_底稿'!$P$3:$DS$3,0))} -> 51771 | N23: =IF(C23="","",ROUND(C23/B23,4)) -> 0.4235 | O23: =IF(K23="","",ROUND(K23/C23,0)) -> 119 | P23: =IF(L23="","",ROUND(K23/L23,6)) -> 0.264887 | Q23: =IF(G23="","",ROUND(G23/F23,1)) -> 1.2 | R23: =IF(L23="","",ROUND(L23/F23,0)) -> 163 | S23: =IF(L23="","",ROUND(L23/G23,0)) -> 131 | T23: =IF(S23="","",ROUND(S23/O23,1)) -> 1.1 | U23: =IF(M23="","",ROUND(M23/H23,0)) -> 484 | V23: =IF(M23="","",L23-M23) -> 1497 | W23: =AB23+AE23+AH23+AK23+AN23+AQ23 -> 775594.38 | X23: {=index('jiliarena_日报_底稿'!$P$2:$DS$34,match($A23,'jiliarena_日报_底稿'!$P$2:$P$34,0),match("电子有效投注",'jiliarena_日报_底稿'!$P$3:$DS$3,0))+index('jiliarena_日报_底稿'!$P$2:$DS$34,match($A23,'jiliarena_日报_底稿'!$P$2:$P$34,0),match("真人有效投注",'jiliarena_日报_底稿'!$P$3:$DS$3,0))+index('jiliarena_日报_底稿'!$P$2:$DS$34,match($A23,'jiliarena_日报_底稿'!$P$2:$P$34,0),match("彩票有效投注",'jiliarena_日报_底稿'!$P$3:$DS$3,0))+index('jiliarena_日报_底稿'!$P$2:$DS$34,match($A23,'jiliarena_日报_底稿'!$P$2:$P$34,0),match("棋牌有效投注",'jiliarena_日报_底稿'!$P$3:$DS$3,0))+index('jiliarena_日报_底稿'!$P$2:$DS$34,match($A23,'jiliarena_日报_底稿'!$P$2:$P$34,0),match("捕鱼有效投注",'jiliarena_日报_底稿'!$P$3:$DS$3,0))+index('jiliarena_日报_底稿'!$P$2:$DS$34,match($A23,'jiliarena_日报_底稿'!$P$2:$P$34,0),match("体育有效投注",'jiliarena_日报_底稿'!$P$3:$DS$3,0))+index('jiliarena_日报_底稿'!$P$2:$DS$34,match($A23,'jiliarena_日报_底稿'!$P$2:$P$34,0),match("盘口彩票有效投注",'jiliarena_日报_底稿'!$P$3:$DS$3,0))} -> 705311.59 | Y23: =AB23+AE23+AH23+AK23+AN23+AQ23-AR23-AO23-AL23-AI23-AF23-AC23 -> 25692.14 | Z23: =AC23+AF23+AI23+AL23+AO23+AR23 -> 749902.24 | AA23: =IFERROR(ROUND(1-(Z23/W23),6),"") -> 0.033126 | AB23: {=INDEX('jiliarena_日报_底稿'!$P$2:$DS$34,MATCH($A23,'jiliarena_日报_底稿'!$P$2:$P$34,0),MATCH(AB$3,'jiliarena_日报_底稿'!$P$3:$DS$3,0))} -> 0 | AC23: {=INDEX('jiliarena_日报_底稿'!$P$2:$DS$34,MATCH($A23,'jiliarena_日报_底稿'!$P$2:$P$34,0),MATCH(AC$3,'jiliarena_日报_底稿'!$P$3:$DS$3,0))} -> 0 | AD23: =IF(AC23="","",ROUND((1-(AC23/AB23)),6)) -> #DIV/0! | AE23: {=INDEX('jiliarena_日报_底稿'!$P$2:$DS$34,MATCH($A23,'jiliarena_日报_底稿'!$P$2:$P$34,0),MATCH(AE$3,'jiliarena_日报_底稿'!$P$3:$DS$3,0))} -> 770071.48 | AF23: {=INDEX('jiliarena_日报_底稿'!$P$2:$DS$34,MATCH($A23,'jiliarena_日报_底稿'!$P$2:$P$34,0),MATCH(AF$3,'jiliarena_日报_底稿'!$P$3:$DS$3,0))} -> 743488.78 | AG23: =IF(AF23="","",ROUND((1-(AF23/AE23)),6)) -> 0.03452 | AH23: {=INDEX('jiliarena_日报_底稿'!$P$2:$DS$34,MATCH($A23,'jiliarena_日报_底稿'!$P$2:$P$34,0),MATCH(AH$3,'jiliarena_日报_底稿'!$P$3:$DS$3,0))} -> 4791.5 | AI23: {=INDEX('jiliarena_日报_底稿'!$P$2:$DS$34,MATCH($A23,'jiliarena_日报_底稿'!$P$2:$P$34,0),MATCH(AI$3,'jiliarena_日报_底稿'!$P$3:$DS$3,0))} -> 5894 | AJ23: =IF(AI23="","",ROUND((1-(AI23/AH23)),6)) -> -0.230095 | AK23: {=INDEX('jiliarena_日报_底稿'!$P$2:$DS$34,MATCH($A23,'jiliarena_日报_底稿'!$P$2:$P$34,0),MATCH(AK$3,'jiliarena_日报_底稿'!$P$3:$DS$3,0))} -> 705.4 | AL23: {=INDEX('jiliarena_日报_底稿'!$P$2:$DS$34,MATCH($A23,'jiliarena_日报_底稿'!$P$2:$P$34,0),MATCH(AL$3,'jiliarena_日报_底稿'!$P$3:$DS$3,0))} -> 519.46 | AM23: =IF(AL23="","",ROUND((1-(AL23/AK23)),6)) -> 0.263595 | AN23: {=INDEX('jiliarena_日报_底稿'!$P$2:$DS$34,MATCH($A23,'jiliarena_日报_底稿'!$P$2:$P$34,0),MATCH(AN$3,'jiliarena_日报_底稿'!$P$3:$DS$3,0))} -> 0 | AO23: {=INDEX('jiliarena_日报_底稿'!$P$2:$DS$34,MATCH($A23,'jiliarena_日报_底稿'!$P$2:$P$34,0),MATCH(AO$3,'jiliarena_日报_底稿'!$P$3:$DS$3,0))} -> 0 | AP23: =IF(AO23="","",ROUND((1-(AO23/AN23)),6)) -> #DIV/0! | AQ23: {=INDEX('jiliarena_日报_底稿'!$P$2:$DS$34,MATCH($A23,'jiliarena_日报_底稿'!$P$2:$P$34,0),MATCH(AQ$3,'jiliarena_日报_底稿'!$P$3:$DS$3,0))} -> 26 | AR23: {=INDEX('jiliarena_日报_底稿'!$P$2:$DS$34,MATCH($A23,'jiliarena_日报_底稿'!$P$2:$P$34,0),MATCH(AR$3,'jiliarena_日报_底稿'!$P$3:$DS$3,0))} -> 0 | AS23: =IF(AR23="","",ROUND((1-(AR23/AQ23)),6)) -> 1 | AT23: =SUMIFS('jiliarena_活动分析数据_底稿'!$K:$K,'jiliarena_活动分析数据_底稿'!$B:$B,$A23,'jiliarena_活动分析数据_底稿'!$L:$L,AT$3) -> 1556.69 | AU23: =SUMIFS('jiliarena_活动分析数据_底稿'!$K:$K,'jiliarena_活动分析数据_底稿'!$B:$B,$A23,'jiliarena_活动分析数据_底稿'!$L:$L,AU$3) -> 0 | AV23: =SUMIFS('jiliarena_活动分析数据_底稿'!$K:$K,'jiliarena_活动分析数据_底稿'!$B:$B,$A23,'jiliarena_活动分析数据_底稿'!$L:$L,AV$3) -> 352.88 | AW23: =SUMIFS('jiliarena_活动分析数据_底稿'!$K:$K,'jiliarena_活动分析数据_底稿'!$B:$B,$A23,'jiliarena_活动分析数据_底稿'!$L:$L,AW$3) -> 6015 | AX23: =SUMIFS('jiliarena_活动分析数据_底稿'!$K:$K,'jiliarena_活动分析数据_底稿'!$B:$B,$A23,'jiliarena_活动分析数据_底稿'!$L:$L,AX$3) -> 327 | AY23: =SUMIFS('jiliarena_活动分析数据_底稿'!$K:$K,'jiliarena_活动分析数据_底稿'!$B:$B,$A23,'jiliarena_活动分析数据_底稿'!$L:$L,AY$3) -> 0 | AZ23: =SUMIFS('jiliarena_活动分析数据_底稿'!$K:$K,'jiliarena_活动分析数据_底稿'!$B:$B,$A23,'jiliarena_活动分析数据_底稿'!$L:$L,AZ$3) -> 0 | BA23: =SUMIFS('jiliarena_活动分析数据_底稿'!$K:$K,'jiliarena_活动分析数据_底稿'!$B:$B,$A23,'jiliarena_活动分析数据_底稿'!$L:$L,BA$3) -> 0 | ... BP23: =SUMIFS('jiliarena_活动分析数据_底稿'!$K:$K,'jiliarena_活动分析数据_底稿'!$B:$B,$A23,'jiliarena_活动分析数据_底稿'!$L:$L,BP$3) -> 0 | BQ23: =SUM(AT23:BP23) -> 12252.97 | BR23: =AT23 -> 1556.69 | BS23: =BB23 -> 242.4 | BT23: =iferror(IF(BQ23="","",ROUND(BQ23/X23,6)),"") -> 0.017372 | BU23: =iferror(BQ23/L23,"") -> 0.23002497 | BV23: =iferror(BQ23/Y23,"") -> 0.47691512 | BW23: =IF(BQ23="","",Y23-BQ23) -> 13439.17 | BX23: =iferror(BQ23/BW23,"") -> 0.91173562 | BY23: =L23*$BY$1 -> 1283.7588 | BZ23: =M23*$BZ$1 -> 103.542 | CA23: =BY23+BZ23 -> 1387.3008 | CB23: =IF(Y23="","",ROUND(Y23*9%,0)) -> 2312 | CC23: =iferror(CA23/BW23,"") -> 0.10322816 | CD23: {=index('jiliarena_日报_底稿'!$P$3:$DS$34,match(A23,'jiliarena_日报_底稿'!$P$3:$P$34,0),match("综合性分红",'jiliarena_日报_底稿'!$P$3:$DS$3,0))} -> 0 | CF23: {=INDEX('jiliarena_日报_底稿'!$P$2:$DS$34,MATCH($A23,'jiliarena_日报_底稿'!$P$2:$P$34,0),MATCH(CF$3,'jiliarena_日报_底稿'!$P$3:$DS$3,0))} -> 0 | CG23: {=-INDEX('jiliarena_日报_底稿'!$P$2:$DS$34,MATCH($A23,'jiliarena_日报_底稿'!$P$2:$P$34,0),MATCH(CG$3,'jiliarena_日报_底稿'!$P$3:$DS$3,0))} -> 0 | CH23: {=INDEX('jiliarena_日报_底稿'!$P$2:$DS$34,MATCH($A23,'jiliarena_日报_底稿'!$P$2:$P$34,0),MATCH(CH$3,'jiliarena_日报_底稿'!$P$3:$DS$3,0))} -> 143518.5 | CI23: =IF(CA23="","",BW23-CA23-CD23-CB23) -> 9739.8692 | CJ23: =IFERROR(month(A23),"") -> 3 | CK23: =IFERROR(DAY(A23),"") -> 11
A24: =A23+1 -> 46093 | B24: {=INDEX('jiliarena_日报_底稿'!$A$3:$N$34,MATCH($A24,'jiliarena_日报_底稿'!$A$3:$A$34,0),MATCH(B$3,'jiliarena_日报_底稿'!$A$3:$N$3,0))} | C24: {=INDEX('jiliarena_日报_底稿'!$A$3:$N$34,MATCH($A24,'jiliarena_日报_底稿'!$A$3:$A$34,0),MATCH(C$3,'jiliarena_日报_底稿'!$A$3:$N$3,0))} | D24: {=INDEX('jiliarena_日报_底稿'!$A$3:$N$34,MATCH($A24,'jiliarena_日报_底稿'!$A$3:$A$34,0),MATCH(D$3,'jiliarena_日报_底稿'!$A$3:$N$3,0))} | F24: {=INDEX('jiliarena_日报_底稿'!$A$3:$N$34,MATCH($A24,'jiliarena_日报_底稿'!$A$3:$A$34,0),MATCH(F$3,'jiliarena_日报_底稿'!$A$3:$N$3,0))} | G24: =SUMIFS('渠道充值成功率_底稿'!$F:$F,'渠道充值成功率_底稿'!$A:$A,A24) -> 0 | H24: {=INDEX('jiliarena_日报_底稿'!$A$3:$N$34,MATCH($A24,'jiliarena_日报_底稿'!$A$3:$A$34,0),MATCH(H$3,'jiliarena_日报_底稿'!$A$3:$N$3,0))} | J24: {=INDEX('jiliarena_日报_底稿'!$A$3:$N$34,MATCH($A24,'jiliarena_日报_底稿'!$A$3:$A$34,0),MATCH(J$3,'jiliarena_日报_底稿'!$A$3:$N$3,0))} | K24: =SUMIFS('渠道充值成功率_底稿'!$J:$J,'渠道充值成功率_底稿'!$A:$A,$A24) -> 0 | L24: {=INDEX('jiliarena_日报_底稿'!$A$3:$N$34,MATCH($A24,'jiliarena_日报_底稿'!$A$3:$A$34,0),MATCH(L$3,'jiliarena_日报_底稿'!$A$3:$N$3,0))} | M24: {=INDEX('jiliarena_日报_底稿'!$P$2:$DS$34,MATCH($A24,'jiliarena_日报_底稿'!$P$2:$P$34,0),MATCH($M$3,'jiliarena_日报_底稿'!$P$3:$DS$3,0))} | N24: =IF(C24="","",ROUND(C24/B24,4)) | O24: =IF(K24="","",ROUND(K24/C24,0)) -> #DIV/0! | P24: =IF(L24="","",ROUND(K24/L24,6)) | Q24: =IF(G24="","",ROUND(G24/F24,1)) -> #DIV/0! | R24: =IF(L24="","",ROUND(L24/F24,0)) | S24: =IF(L24="","",ROUND(L24/G24,0)) | T24: =IF(S24="","",ROUND(S24/O24,1)) | U24: =IF(M24="","",ROUND(M24/H24,0)) | V24: =IF(M24="","",L24-M24) | W24: =AB24+AE24+AH24+AK24+AN24+AQ24 -> 0 | X24: {=index('jiliarena_日报_底稿'!$P$2:$DS$34,match($A24,'jiliarena_日报_底稿'!$P$2:$P$34,0),match("电子有效投注",'jiliarena_日报_底稿'!$P$3:$DS$3,0))+index('jiliarena_日报_底稿'!$P$2:$DS$34,match($A24,'jiliarena_日报_底稿'!$P$2:$P$34,0),match("真人有效投注",'jiliarena_日报_底稿'!$P$3:$DS$3,0))+index('jiliarena_日报_底稿'!$P$2:$DS$34,match($A24,'jiliarena_日报_底稿'!$P$2:$P$34,0),match("彩票有效投注",'jiliarena_日报_底稿'!$P$3:$DS$3,0))+index('jiliarena_日报_底稿'!$P$2:$DS$34,match($A24,'jiliarena_日报_底稿'!$P$2:$P$34,0),match("棋牌有效投注",'jiliarena_日报_底稿'!$P$3:$DS$3,0))+index('jiliarena_日报_底稿'!$P$2:$DS$34,match($A24,'jiliarena_日报_底稿'!$P$2:$P$34,0),match("捕鱼有效投注",'jiliarena_日报_底稿'!$P$3:$DS$3,0))+index('jiliarena_日报_底稿'!$P$2:$DS$34,match($A24,'jiliarena_日报_底稿'!$P$2:$P$34,0),match("体育有效投注",'jiliarena_日报_底稿'!$P$3:$DS$3,0))+index('jiliarena_日报_底稿'!$P$2:$DS$34,match($A24,'jiliarena_日报_底稿'!$P$2:$P$34,0),match("盘口彩票有效投注",'jiliarena_日报_底稿'!$P$3:$DS$3,0))} -> 0 | Y24: =AB24+AE24+AH24+AK24+AN24+AQ24-AR24-AO24-AL24-AI24-AF24-AC24 -> 0 | Z24: =AC24+AF24+AI24+AL24+AO24+AR24 -> 0 | AA24: =IFERROR(ROUND(1-(Z24/W24),6),"") | AB24: {=INDEX('jiliarena_日报_底稿'!$P$2:$DS$34,MATCH($A24,'jiliarena_日报_底稿'!$P$2:$P$34,0),MATCH(AB$3,'jiliarena_日报_底稿'!$P$3:$DS$3,0))} | AC24: {=INDEX('jiliarena_日报_底稿'!$P$2:$DS$34,MATCH($A24,'jiliarena_日报_底稿'!$P$2:$P$34,0),MATCH(AC$3,'jiliarena_日报_底稿'!$P$3:$DS$3,0))} | AD24: =IF(AC24="","",ROUND((1-(AC24/AB24)),6)) | AE24: {=INDEX('jiliarena_日报_底稿'!$P$2:$DS$34,MATCH($A24,'jiliarena_日报_底稿'!$P$2:$P$34,0),MATCH(AE$3,'jiliarena_日报_底稿'!$P$3:$DS$3,0))} | AF24: {=INDEX('jiliarena_日报_底稿'!$P$2:$DS$34,MATCH($A24,'jiliarena_日报_底稿'!$P$2:$P$34,0),MATCH(AF$3,'jiliarena_日报_底稿'!$P$3:$DS$3,0))} | AG24: =IF(AF24="","",ROUND((1-(AF24/AE24)),6)) | AH24: {=INDEX('jiliarena_日报_底稿'!$P$2:$DS$34,MATCH($A24,'jiliarena_日报_底稿'!$P$2:$P$34,0),MATCH(AH$3,'jiliarena_日报_底稿'!$P$3:$DS$3,0))} | AI24: {=INDEX('jiliarena_日报_底稿'!$P$2:$DS$34,MATCH($A24,'jiliarena_日报_底稿'!$P$2:$P$34,0),MATCH(AI$3,'jiliarena_日报_底稿'!$P$3:$DS$3,0))} | AJ24: =IF(AI24="","",ROUND((1-(AI24/AH24)),6)) | AK24: {=INDEX('jiliarena_日报_底稿'!$P$2:$DS$34,MATCH($A24,'jiliarena_日报_底稿'!$P$2:$P$34,0),MATCH(AK$3,'jiliarena_日报_底稿'!$P$3:$DS$3,0))} | AL24: {=INDEX('jiliarena_日报_底稿'!$P$2:$DS$34,MATCH($A24,'jiliarena_日报_底稿'!$P$2:$P$34,0),MATCH(AL$3,'jiliarena_日报_底稿'!$P$3:$DS$3,0))} | AM24: =IF(AL24="","",ROUND((1-(AL24/AK24)),6)) | AN24: {=INDEX('jiliarena_日报_底稿'!$P$2:$DS$34,MATCH($A24,'jiliarena_日报_底稿'!$P$2:$P$34,0),MATCH(AN$3,'jiliarena_日报_底稿'!$P$3:$DS$3,0))} | AO24: {=INDEX('jiliarena_日报_底稿'!$P$2:$DS$34,MATCH($A24,'jiliarena_日报_底稿'!$P$2:$P$34,0),MATCH(AO$3,'jiliarena_日报_底稿'!$P$3:$DS$3,0))} | AP24: =IF(AO24="","",ROUND((1-(AO24/AN24)),6)) | AQ24: {=INDEX('jiliarena_日报_底稿'!$P$2:$DS$34,MATCH($A24,'jiliarena_日报_底稿'!$P$2:$P$34,0),MATCH(AQ$3,'jiliarena_日报_底稿'!$P$3:$DS$3,0))} | AR24: {=INDEX('jiliarena_日报_底稿'!$P$2:$DS$34,MATCH($A24,'jiliarena_日报_底稿'!$P$2:$P$34,0),MATCH(AR$3,'jiliarena_日报_底稿'!$P$3:$DS$3,0))} | AS24: =IF(AR24="","",ROUND((1-(AR24/AQ24)),6)) | AT24: =SUMIFS('jiliarena_活动分析数据_底稿'!$K:$K,'jiliarena_活动分析数据_底稿'!$B:$B,$A24,'jiliarena_活动分析数据_底稿'!$L:$L,AT$3) -> 0 | AU24: =SUMIFS('jiliarena_活动分析数据_底稿'!$K:$K,'jiliarena_活动分析数据_底稿'!$B:$B,$A24,'jiliarena_活动分析数据_底稿'!$L:$L,AU$3) -> 0 | AV24: =SUMIFS('jiliarena_活动分析数据_底稿'!$K:$K,'jiliarena_活动分析数据_底稿'!$B:$B,$A24,'jiliarena_活动分析数据_底稿'!$L:$L,AV$3) -> 0 | AW24: =SUMIFS('jiliarena_活动分析数据_底稿'!$K:$K,'jiliarena_活动分析数据_底稿'!$B:$B,$A24,'jiliarena_活动分析数据_底稿'!$L:$L,AW$3) -> 0 | AX24: =SUMIFS('jiliarena_活动分析数据_底稿'!$K:$K,'jiliarena_活动分析数据_底稿'!$B:$B,$A24,'jiliarena_活动分析数据_底稿'!$L:$L,AX$3) -> 0 | AY24: =SUMIFS('jiliarena_活动分析数据_底稿'!$K:$K,'jiliarena_活动分析数据_底稿'!$B:$B,$A24,'jiliarena_活动分析数据_底稿'!$L:$L,AY$3) -> 0 | AZ24: =SUMIFS('jiliarena_活动分析数据_底稿'!$K:$K,'jiliarena_活动分析数据_底稿'!$B:$B,$A24,'jiliarena_活动分析数据_底稿'!$L:$L,AZ$3) -> 0 | BA24: =SUMIFS('jiliarena_活动分析数据_底稿'!$K:$K,'jiliarena_活动分析数据_底稿'!$B:$B,$A24,'jiliarena_活动分析数据_底稿'!$L:$L,BA$3) -> 0 | ... BP24: =SUMIFS('jiliarena_活动分析数据_底稿'!$K:$K,'jiliarena_活动分析数据_底稿'!$B:$B,$A24,'jiliarena_活动分析数据_底稿'!$L:$L,BP$3) -> 0 | BQ24: =SUM(AT24:BP24) -> 0 | BR24: =AT24 -> 0 | BS24: =BB24 -> 0 | BT24: =iferror(IF(BQ24="","",ROUND(BQ24/X24,6)),"") | BU24: =iferror(BQ24/L24,"") | BV24: =iferror(BQ24/Y24,"") | BW24: =IF(BQ24="","",Y24-BQ24) -> 0 | BX24: =iferror(BQ24/BW24,"") | BY24: =L24*$BY$1 -> 0 | BZ24: =M24*$BZ$1 -> 0 | CA24: =BY24+BZ24 -> 0 | CB24: =IF(Y24="","",ROUND(Y24*9%,0)) -> 0 | CC24: =iferror(CA24/BW24,"") | CD24: {=index('jiliarena_日报_底稿'!$P$3:$DS$34,match(A24,'jiliarena_日报_底稿'!$P$3:$P$34,0),match("综合性分红",'jiliarena_日报_底稿'!$P$3:$DS$3,0))} | CF24: {=INDEX('jiliarena_日报_底稿'!$P$2:$DS$34,MATCH($A24,'jiliarena_日报_底稿'!$P$2:$P$34,0),MATCH(CF$3,'jiliarena_日报_底稿'!$P$3:$DS$3,0))} | CG24: {=-INDEX('jiliarena_日报_底稿'!$P$2:$DS$34,MATCH($A24,'jiliarena_日报_底稿'!$P$2:$P$34,0),MATCH(CG$3,'jiliarena_日报_底稿'!$P$3:$DS$3,0))} -> 0 | CH24: {=INDEX('jiliarena_日报_底稿'!$P$2:$DS$34,MATCH($A24,'jiliarena_日报_底稿'!$P$2:$P$34,0),MATCH(CH$3,'jiliarena_日报_底稿'!$P$3:$DS$3,0))} | CI24: =IF(CA24="","",BW24-CA24-CD24-CB24) -> 0 | CJ24: =IFERROR(month(A24),"") -> 3 | CK24: =IFERROR(DAY(A24),"") -> 12
A25: =A24+1 -> 46094 | B25: {=INDEX('jiliarena_日报_底稿'!$A$3:$N$34,MATCH($A25,'jiliarena_日报_底稿'!$A$3:$A$34,0),MATCH(B$3,'jiliarena_日报_底稿'!$A$3:$N$3,0))} | C25: {=INDEX('jiliarena_日报_底稿'!$A$3:$N$34,MATCH($A25,'jiliarena_日报_底稿'!$A$3:$A$34,0),MATCH(C$3,'jiliarena_日报_底稿'!$A$3:$N$3,0))} | D25: {=INDEX('jiliarena_日报_底稿'!$A$3:$N$34,MATCH($A25,'jiliarena_日报_底稿'!$A$3:$A$34,0),MATCH(D$3,'jiliarena_日报_底稿'!$A$3:$N$3,0))} | F25: {=INDEX('jiliarena_日报_底稿'!$A$3:$N$34,MATCH($A25,'jiliarena_日报_底稿'!$A$3:$A$34,0),MATCH(F$3,'jiliarena_日报_底稿'!$A$3:$N$3,0))} | G25: =SUMIFS('渠道充值成功率_底稿'!$F:$F,'渠道充值成功率_底稿'!$A:$A,A25) -> 0 | H25: {=INDEX('jiliarena_日报_底稿'!$A$3:$N$34,MATCH($A25,'jiliarena_日报_底稿'!$A$3:$A$34,0),MATCH(H$3,'jiliarena_日报_底稿'!$A$3:$N$3,0))} | J25: {=INDEX('jiliarena_日报_底稿'!$A$3:$N$34,MATCH($A25,'jiliarena_日报_底稿'!$A$3:$A$34,0),MATCH(J$3,'jiliarena_日报_底稿'!$A$3:$N$3,0))} | K25: =SUMIFS('渠道充值成功率_底稿'!$J:$J,'渠道充值成功率_底稿'!$A:$A,$A25) -> 0 | L25: {=INDEX('jiliarena_日报_底稿'!$A$3:$N$34,MATCH($A25,'jiliarena_日报_底稿'!$A$3:$A$34,0),MATCH(L$3,'jiliarena_日报_底稿'!$A$3:$N$3,0))} | M25: {=INDEX('jiliarena_日报_底稿'!$P$2:$DS$34,MATCH($A25,'jiliarena_日报_底稿'!$P$2:$P$34,0),MATCH($M$3,'jiliarena_日报_底稿'!$P$3:$DS$3,0))} | N25: =IF(C25="","",ROUND(C25/B25,4)) | O25: =IF(K25="","",ROUND(K25/C25,0)) -> #DIV/0! | P25: =IF(L25="","",ROUND(K25/L25,6)) | Q25: =IF(G25="","",ROUND(G25/F25,1)) -> #DIV/0! | R25: =IF(L25="","",ROUND(L25/F25,0)) | S25: =IF(L25="","",ROUND(L25/G25,0)) | T25: =IF(S25="","",ROUND(S25/O25,1)) | U25: =IF(M25="","",ROUND(M25/H25,0)) | V25: =IF(M25="","",L25-M25) | W25: =AB25+AE25+AH25+AK25+AN25+AQ25 -> 0 | X25: {=index('jiliarena_日报_底稿'!$P$2:$DS$34,match($A25,'jiliarena_日报_底稿'!$P$2:$P$34,0),match("电子有效投注",'jiliarena_日报_底稿'!$P$3:$DS$3,0))+index('jiliarena_日报_底稿'!$P$2:$DS$34,match($A25,'jiliarena_日报_底稿'!$P$2:$P$34,0),match("真人有效投注",'jiliarena_日报_底稿'!$P$3:$DS$3,0))+index('jiliarena_日报_底稿'!$P$2:$DS$34,match($A25,'jiliarena_日报_底稿'!$P$2:$P$34,0),match("彩票有效投注",'jiliarena_日报_底稿'!$P$3:$DS$3,0))+index('jiliarena_日报_底稿'!$P$2:$DS$34,match($A25,'jiliarena_日报_底稿'!$P$2:$P$34,0),match("棋牌有效投注",'jiliarena_日报_底稿'!$P$3:$DS$3,0))+index('jiliarena_日报_底稿'!$P$2:$DS$34,match($A25,'jiliarena_日报_底稿'!$P$2:$P$34,0),match("捕鱼有效投注",'jiliarena_日报_底稿'!$P$3:$DS$3,0))+index('jiliarena_日报_底稿'!$P$2:$DS$34,match($A25,'jiliarena_日报_底稿'!$P$2:$P$34,0),match("体育有效投注",'jiliarena_日报_底稿'!$P$3:$DS$3,0))+index('jiliarena_日报_底稿'!$P$2:$DS$34,match($A25,'jiliarena_日报_底稿'!$P$2:$P$34,0),match("盘口彩票有效投注",'jiliarena_日报_底稿'!$P$3:$DS$3,0))} -> 0 | Y25: =AB25+AE25+AH25+AK25+AN25+AQ25-AR25-AO25-AL25-AI25-AF25-AC25 -> 0 | Z25: =AC25+AF25+AI25+AL25+AO25+AR25 -> 0 | AA25: =IFERROR(ROUND(1-(Z25/W25),6),"") | AB25: {=INDEX('jiliarena_日报_底稿'!$P$2:$DS$34,MATCH($A25,'jiliarena_日报_底稿'!$P$2:$P$34,0),MATCH(AB$3,'jiliarena_日报_底稿'!$P$3:$DS$3,0))} | AC25: {=INDEX('jiliarena_日报_底稿'!$P$2:$DS$34,MATCH($A25,'jiliarena_日报_底稿'!$P$2:$P$34,0),MATCH(AC$3,'jiliarena_日报_底稿'!$P$3:$DS$3,0))} | AD25: =IF(AC25="","",ROUND((1-(AC25/AB25)),6)) | AE25: {=INDEX('jiliarena_日报_底稿'!$P$2:$DS$34,MATCH($A25,'jiliarena_日报_底稿'!$P$2:$P$34,0),MATCH(AE$3,'jiliarena_日报_底稿'!$P$3:$DS$3,0))} | AF25: {=INDEX('jiliarena_日报_底稿'!$P$2:$DS$34,MATCH($A25,'jiliarena_日报_底稿'!$P$2:$P$34,0),MATCH(AF$3,'jiliarena_日报_底稿'!$P$3:$DS$3,0))} | AG25: =IF(AF25="","",ROUND((1-(AF25/AE25)),6)) | AH25: {=INDEX('jiliarena_日报_底稿'!$P$2:$DS$34,MATCH($A25,'jiliarena_日报_底稿'!$P$2:$P$34,0),MATCH(AH$3,'jiliarena_日报_底稿'!$P$3:$DS$3,0))} | AI25: {=INDEX('jiliarena_日报_底稿'!$P$2:$DS$34,MATCH($A25,'jiliarena_日报_底稿'!$P$2:$P$34,0),MATCH(AI$3,'jiliarena_日报_底稿'!$P$3:$DS$3,0))} | AJ25: =IF(AI25="","",ROUND((1-(AI25/AH25)),6)) | AK25: {=INDEX('jiliarena_日报_底稿'!$P$2:$DS$34,MATCH($A25,'jiliarena_日报_底稿'!$P$2:$P$34,0),MATCH(AK$3,'jiliarena_日报_底稿'!$P$3:$DS$3,0))} | AL25: {=INDEX('jiliarena_日报_底稿'!$P$2:$DS$34,MATCH($A25,'jiliarena_日报_底稿'!$P$2:$P$34,0),MATCH(AL$3,'jiliarena_日报_底稿'!$P$3:$DS$3,0))} | AM25: =IF(AL25="","",ROUND((1-(AL25/AK25)),6)) | AN25: {=INDEX('jiliarena_日报_底稿'!$P$2:$DS$34,MATCH($A25,'jiliarena_日报_底稿'!$P$2:$P$34,0),MATCH(AN$3,'jiliarena_日报_底稿'!$P$3:$DS$3,0))} | AO25: {=INDEX('jiliarena_日报_底稿'!$P$2:$DS$34,MATCH($A25,'jiliarena_日报_底稿'!$P$2:$P$34,0),MATCH(AO$3,'jiliarena_日报_底稿'!$P$3:$DS$3,0))} | AP25: =IF(AO25="","",ROUND((1-(AO25/AN25)),6)) | AQ25: {=INDEX('jiliarena_日报_底稿'!$P$2:$DS$34,MATCH($A25,'jiliarena_日报_底稿'!$P$2:$P$34,0),MATCH(AQ$3,'jiliarena_日报_底稿'!$P$3:$DS$3,0))} | AR25: {=INDEX('jiliarena_日报_底稿'!$P$2:$DS$34,MATCH($A25,'jiliarena_日报_底稿'!$P$2:$P$34,0),MATCH(AR$3,'jiliarena_日报_底稿'!$P$3:$DS$3,0))} | AS25: =IF(AR25="","",ROUND((1-(AR25/AQ25)),6)) | AT25: =SUMIFS('jiliarena_活动分析数据_底稿'!$K:$K,'jiliarena_活动分析数据_底稿'!$B:$B,$A25,'jiliarena_活动分析数据_底稿'!$L:$L,AT$3) -> 0 | AU25: =SUMIFS('jiliarena_活动分析数据_底稿'!$K:$K,'jiliarena_活动分析数据_底稿'!$B:$B,$A25,'jiliarena_活动分析数据_底稿'!$L:$L,AU$3) -> 0 | AV25: =SUMIFS('jiliarena_活动分析数据_底稿'!$K:$K,'jiliarena_活动分析数据_底稿'!$B:$B,$A25,'jiliarena_活动分析数据_底稿'!$L:$L,AV$3) -> 0 | AW25: =SUMIFS('jiliarena_活动分析数据_底稿'!$K:$K,'jiliarena_活动分析数据_底稿'!$B:$B,$A25,'jiliarena_活动分析数据_底稿'!$L:$L,AW$3) -> 0 | AX25: =SUMIFS('jiliarena_活动分析数据_底稿'!$K:$K,'jiliarena_活动分析数据_底稿'!$B:$B,$A25,'jiliarena_活动分析数据_底稿'!$L:$L,AX$3) -> 0 | AY25: =SUMIFS('jiliarena_活动分析数据_底稿'!$K:$K,'jiliarena_活动分析数据_底稿'!$B:$B,$A25,'jiliarena_活动分析数据_底稿'!$L:$L,AY$3) -> 0 | AZ25: =SUMIFS('jiliarena_活动分析数据_底稿'!$K:$K,'jiliarena_活动分析数据_底稿'!$B:$B,$A25,'jiliarena_活动分析数据_底稿'!$L:$L,AZ$3) -> 0 | BA25: =SUMIFS('jiliarena_活动分析数据_底稿'!$K:$K,'jiliarena_活动分析数据_底稿'!$B:$B,$A25,'jiliarena_活动分析数据_底稿'!$L:$L,BA$3) -> 0 | ... BP25: =SUMIFS('jiliarena_活动分析数据_底稿'!$K:$K,'jiliarena_活动分析数据_底稿'!$B:$B,$A25,'jiliarena_活动分析数据_底稿'!$L:$L,BP$3) -> 0 | BQ25: =SUM(AT25:BP25) -> 0 | BR25: =AT25 -> 0 | BS25: =BB25 -> 0 | BT25: =iferror(IF(BQ25="","",ROUND(BQ25/X25,6)),"") | BU25: =iferror(BQ25/L25,"") | BV25: =iferror(BQ25/Y25,"") | BW25: =IF(BQ25="","",Y25-BQ25) -> 0 | BX25: =iferror(BQ25/BW25,"") | BY25: =L25*$BY$1 -> 0 | BZ25: =M25*$BZ$1 -> 0 | CA25: =BY25+BZ25 -> 0 | CB25: =IF(Y25="","",ROUND(Y25*9%,0)) -> 0 | CC25: =iferror(CA25/BW25,"") | CD25: {=index('jiliarena_日报_底稿'!$P$3:$DS$34,match(A25,'jiliarena_日报_底稿'!$P$3:$P$34,0),match("综合性分红",'jiliarena_日报_底稿'!$P$3:$DS$3,0))} | CF25: {=INDEX('jiliarena_日报_底稿'!$P$2:$DS$34,MATCH($A25,'jiliarena_日报_底稿'!$P$2:$P$34,0),MATCH(CF$3,'jiliarena_日报_底稿'!$P$3:$DS$3,0))} | CG25: {=-INDEX('jiliarena_日报_底稿'!$P$2:$DS$34,MATCH($A25,'jiliarena_日报_底稿'!$P$2:$P$34,0),MATCH(CG$3,'jiliarena_日报_底稿'!$P$3:$DS$3,0))} -> 0 | CH25: {=INDEX('jiliarena_日报_底稿'!$P$2:$DS$34,MATCH($A25,'jiliarena_日报_底稿'!$P$2:$P$34,0),MATCH(CH$3,'jiliarena_日报_底稿'!$P$3:$DS$3,0))} | CI25: =IF(CA25="","",BW25-CA25-CD25-CB25) -> 0 | CJ25: =IFERROR(month(A25),"") -> 3 | CK25: =IFERROR(DAY(A25),"") -> 13
A26: =A25+1 -> 46095 | B26: {=INDEX('jiliarena_日报_底稿'!$A$3:$N$34,MATCH($A26,'jiliarena_日报_底稿'!$A$3:$A$34,0),MATCH(B$3,'jiliarena_日报_底稿'!$A$3:$N$3,0))} | C26: {=INDEX('jiliarena_日报_底稿'!$A$3:$N$34,MATCH($A26,'jiliarena_日报_底稿'!$A$3:$A$34,0),MATCH(C$3,'jiliarena_日报_底稿'!$A$3:$N$3,0))} | D26: {=INDEX('jiliarena_日报_底稿'!$A$3:$N$34,MATCH($A26,'jiliarena_日报_底稿'!$A$3:$A$34,0),MATCH(D$3,'jiliarena_日报_底稿'!$A$3:$N$3,0))} | F26: {=INDEX('jiliarena_日报_底稿'!$A$3:$N$34,MATCH($A26,'jiliarena_日报_底稿'!$A$3:$A$34,0),MATCH(F$3,'jiliarena_日报_底稿'!$A$3:$N$3,0))} | G26: =SUMIFS('渠道充值成功率_底稿'!$F:$F,'渠道充值成功率_底稿'!$A:$A,A26) -> 0 | H26: {=INDEX('jiliarena_日报_底稿'!$A$3:$N$34,MATCH($A26,'jiliarena_日报_底稿'!$A$3:$A$34,0),MATCH(H$3,'jiliarena_日报_底稿'!$A$3:$N$3,0))} | J26: {=INDEX('jiliarena_日报_底稿'!$A$3:$N$34,MATCH($A26,'jiliarena_日报_底稿'!$A$3:$A$34,0),MATCH(J$3,'jiliarena_日报_底稿'!$A$3:$N$3,0))} | K26: =SUMIFS('渠道充值成功率_底稿'!$J:$J,'渠道充值成功率_底稿'!$A:$A,$A26) -> 0 | L26: {=INDEX('jiliarena_日报_底稿'!$A$3:$N$34,MATCH($A26,'jiliarena_日报_底稿'!$A$3:$A$34,0),MATCH(L$3,'jiliarena_日报_底稿'!$A$3:$N$3,0))} | M26: {=INDEX('jiliarena_日报_底稿'!$P$2:$DS$34,MATCH($A26,'jiliarena_日报_底稿'!$P$2:$P$34,0),MATCH($M$3,'jiliarena_日报_底稿'!$P$3:$DS$3,0))} | N26: =IF(C26="","",ROUND(C26/B26,4)) | O26: =IF(K26="","",ROUND(K26/C26,0)) -> #DIV/0! | P26: =IF(L26="","",ROUND(K26/L26,6)) | Q26: =IF(G26="","",ROUND(G26/F26,1)) -> #DIV/0! | R26: =IF(L26="","",ROUND(L26/F26,0)) | S26: =IF(L26="","",ROUND(L26/G26,0)) | T26: =IF(S26="","",ROUND(S26/O26,1)) | U26: =IF(M26="","",ROUND(M26/H26,0)) | V26: =IF(M26="","",L26-M26) | W26: =AB26+AE26+AH26+AK26+AN26+AQ26 -> 0 | X26: {=index('jiliarena_日报_底稿'!$P$2:$DS$34,match($A26,'jiliarena_日报_底稿'!$P$2:$P$34,0),match("电子有效投注",'jiliarena_日报_底稿'!$P$3:$DS$3,0))+index('jiliarena_日报_底稿'!$P$2:$DS$34,match($A26,'jiliarena_日报_底稿'!$P$2:$P$34,0),match("真人有效投注",'jiliarena_日报_底稿'!$P$3:$DS$3,0))+index('jiliarena_日报_底稿'!$P$2:$DS$34,match($A26,'jiliarena_日报_底稿'!$P$2:$P$34,0),match("彩票有效投注",'jiliarena_日报_底稿'!$P$3:$DS$3,0))+index('jiliarena_日报_底稿'!$P$2:$DS$34,match($A26,'jiliarena_日报_底稿'!$P$2:$P$34,0),match("棋牌有效投注",'jiliarena_日报_底稿'!$P$3:$DS$3,0))+index('jiliarena_日报_底稿'!$P$2:$DS$34,match($A26,'jiliarena_日报_底稿'!$P$2:$P$34,0),match("捕鱼有效投注",'jiliarena_日报_底稿'!$P$3:$DS$3,0))+index('jiliarena_日报_底稿'!$P$2:$DS$34,match($A26,'jiliarena_日报_底稿'!$P$2:$P$34,0),match("体育有效投注",'jiliarena_日报_底稿'!$P$3:$DS$3,0))+index('jiliarena_日报_底稿'!$P$2:$DS$34,match($A26,'jiliarena_日报_底稿'!$P$2:$P$34,0),match("盘口彩票有效投注",'jiliarena_日报_底稿'!$P$3:$DS$3,0))} -> 0 | Y26: =AB26+AE26+AH26+AK26+AN26+AQ26-AR26-AO26-AL26-AI26-AF26-AC26 -> 0 | Z26: =AC26+AF26+AI26+AL26+AO26+AR26 -> 0 | AA26: =IFERROR(ROUND(1-(Z26/W26),6),"") | AB26: {=INDEX('jiliarena_日报_底稿'!$P$2:$DS$34,MATCH($A26,'jiliarena_日报_底稿'!$P$2:$P$34,0),MATCH(AB$3,'jiliarena_日报_底稿'!$P$3:$DS$3,0))} | AC26: {=INDEX('jiliarena_日报_底稿'!$P$2:$DS$34,MATCH($A26,'jiliarena_日报_底稿'!$P$2:$P$34,0),MATCH(AC$3,'jiliarena_日报_底稿'!$P$3:$DS$3,0))} | AD26: =IF(AC26="","",ROUND((1-(AC26/AB26)),6)) | AE26: {=INDEX('jiliarena_日报_底稿'!$P$2:$DS$34,MATCH($A26,'jiliarena_日报_底稿'!$P$2:$P$34,0),MATCH(AE$3,'jiliarena_日报_底稿'!$P$3:$DS$3,0))} | AF26: {=INDEX('jiliarena_日报_底稿'!$P$2:$DS$34,MATCH($A26,'jiliarena_日报_底稿'!$P$2:$P$34,0),MATCH(AF$3,'jiliarena_日报_底稿'!$P$3:$DS$3,0))} | AG26: =IF(AF26="","",ROUND((1-(AF26/AE26)),6)) | AH26: {=INDEX('jiliarena_日报_底稿'!$P$2:$DS$34,MATCH($A26,'jiliarena_日报_底稿'!$P$2:$P$34,0),MATCH(AH$3,'jiliarena_日报_底稿'!$P$3:$DS$3,0))} | AI26: {=INDEX('jiliarena_日报_底稿'!$P$2:$DS$34,MATCH($A26,'jiliarena_日报_底稿'!$P$2:$P$34,0),MATCH(AI$3,'jiliarena_日报_底稿'!$P$3:$DS$3,0))} | AJ26: =IF(AI26="","",ROUND((1-(AI26/AH26)),6)) | AK26: {=INDEX('jiliarena_日报_底稿'!$P$2:$DS$34,MATCH($A26,'jiliarena_日报_底稿'!$P$2:$P$34,0),MATCH(AK$3,'jiliarena_日报_底稿'!$P$3:$DS$3,0))} | AL26: {=INDEX('jiliarena_日报_底稿'!$P$2:$DS$34,MATCH($A26,'jiliarena_日报_底稿'!$P$2:$P$34,0),MATCH(AL$3,'jiliarena_日报_底稿'!$P$3:$DS$3,0))} | AM26: =IF(AL26="","",ROUND((1-(AL26/AK26)),6)) | AN26: {=INDEX('jiliarena_日报_底稿'!$P$2:$DS$34,MATCH($A26,'jiliarena_日报_底稿'!$P$2:$P$34,0),MATCH(AN$3,'jiliarena_日报_底稿'!$P$3:$DS$3,0))} | AO26: {=INDEX('jiliarena_日报_底稿'!$P$2:$DS$34,MATCH($A26,'jiliarena_日报_底稿'!$P$2:$P$34,0),MATCH(AO$3,'jiliarena_日报_底稿'!$P$3:$DS$3,0))} | AP26: =IF(AO26="","",ROUND((1-(AO26/AN26)),6)) | AQ26: {=INDEX('jiliarena_日报_底稿'!$P$2:$DS$34,MATCH($A26,'jiliarena_日报_底稿'!$P$2:$P$34,0),MATCH(AQ$3,'jiliarena_日报_底稿'!$P$3:$DS$3,0))} | AR26: {=INDEX('jiliarena_日报_底稿'!$P$2:$DS$34,MATCH($A26,'jiliarena_日报_底稿'!$P$2:$P$34,0),MATCH(AR$3,'jiliarena_日报_底稿'!$P$3:$DS$3,0))} | AS26: =IF(AR26="","",ROUND((1-(AR26/AQ26)),6)) | AT26: =SUMIFS('jiliarena_活动分析数据_底稿'!$K:$K,'jiliarena_活动分析数据_底稿'!$B:$B,$A26,'jiliarena_活动分析数据_底稿'!$L:$L,AT$3) -> 0 | AU26: =SUMIFS('jiliarena_活动分析数据_底稿'!$K:$K,'jiliarena_活动分析数据_底稿'!$B:$B,$A26,'jiliarena_活动分析数据_底稿'!$L:$L,AU$3) -> 0 | AV26: =SUMIFS('jiliarena_活动分析数据_底稿'!$K:$K,'jiliarena_活动分析数据_底稿'!$B:$B,$A26,'jiliarena_活动分析数据_底稿'!$L:$L,AV$3) -> 0 | AW26: =SUMIFS('jiliarena_活动分析数据_底稿'!$K:$K,'jiliarena_活动分析数据_底稿'!$B:$B,$A26,'jiliarena_活动分析数据_底稿'!$L:$L,AW$3) -> 0 | AX26: =SUMIFS('jiliarena_活动分析数据_底稿'!$K:$K,'jiliarena_活动分析数据_底稿'!$B:$B,$A26,'jiliarena_活动分析数据_底稿'!$L:$L,AX$3) -> 0 | AY26: =SUMIFS('jiliarena_活动分析数据_底稿'!$K:$K,'jiliarena_活动分析数据_底稿'!$B:$B,$A26,'jiliarena_活动分析数据_底稿'!$L:$L,AY$3) -> 0 | AZ26: =SUMIFS('jiliarena_活动分析数据_底稿'!$K:$K,'jiliarena_活动分析数据_底稿'!$B:$B,$A26,'jiliarena_活动分析数据_底稿'!$L:$L,AZ$3) -> 0 | BA26: =SUMIFS('jiliarena_活动分析数据_底稿'!$K:$K,'jiliarena_活动分析数据_底稿'!$B:$B,$A26,'jiliarena_活动分析数据_底稿'!$L:$L,BA$3) -> 0 | ... BP26: =SUMIFS('jiliarena_活动分析数据_底稿'!$K:$K,'jiliarena_活动分析数据_底稿'!$B:$B,$A26,'jiliarena_活动分析数据_底稿'!$L:$L,BP$3) -> 0 | BQ26: =SUM(AT26:BP26) -> 0 | BR26: =AT26 -> 0 | BS26: =BB26 -> 0 | BT26: =iferror(IF(BQ26="","",ROUND(BQ26/X26,6)),"") | BU26: =iferror(BQ26/L26,"") | BV26: =iferror(BQ26/Y26,"") | BW26: =IF(BQ26="","",Y26-BQ26) -> 0 | BX26: =iferror(BQ26/BW26,"") | BY26: =L26*$BY$1 -> 0 | BZ26: =M26*$BZ$1 -> 0 | CA26: =BY26+BZ26 -> 0 | CB26: =IF(Y26="","",ROUND(Y26*9%,0)) -> 0 | CC26: =iferror(CA26/BW26,"") | CD26: {=index('jiliarena_日报_底稿'!$P$3:$DS$34,match(A26,'jiliarena_日报_底稿'!$P$3:$P$34,0),match("综合性分红",'jiliarena_日报_底稿'!$P$3:$DS$3,0))} | CF26: {=INDEX('jiliarena_日报_底稿'!$P$2:$DS$34,MATCH($A26,'jiliarena_日报_底稿'!$P$2:$P$34,0),MATCH(CF$3,'jiliarena_日报_底稿'!$P$3:$DS$3,0))} | CG26: {=-INDEX('jiliarena_日报_底稿'!$P$2:$DS$34,MATCH($A26,'jiliarena_日报_底稿'!$P$2:$P$34,0),MATCH(CG$3,'jiliarena_日报_底稿'!$P$3:$DS$3,0))} -> 0 | CH26: {=INDEX('jiliarena_日报_底稿'!$P$2:$DS$34,MATCH($A26,'jiliarena_日报_底稿'!$P$2:$P$34,0),MATCH(CH$3,'jiliarena_日报_底稿'!$P$3:$DS$3,0))} | CI26: =IF(CA26="","",BW26-CA26-CD26-CB26) -> 0 | CJ26: =IFERROR(month(A26),"") -> 3 | CK26: =IFERROR(DAY(A26),"") -> 14
A27: =A26+1 -> 46096 | B27: {=INDEX('jiliarena_日报_底稿'!$A$3:$N$34,MATCH($A27,'jiliarena_日报_底稿'!$A$3:$A$34,0),MATCH(B$3,'jiliarena_日报_底稿'!$A$3:$N$3,0))} | C27: {=INDEX('jiliarena_日报_底稿'!$A$3:$N$34,MATCH($A27,'jiliarena_日报_底稿'!$A$3:$A$34,0),MATCH(C$3,'jiliarena_日报_底稿'!$A$3:$N$3,0))} | D27: {=INDEX('jiliarena_日报_底稿'!$A$3:$N$34,MATCH($A27,'jiliarena_日报_底稿'!$A$3:$A$34,0),MATCH(D$3,'jiliarena_日报_底稿'!$A$3:$N$3,0))} | F27: {=INDEX('jiliarena_日报_底稿'!$A$3:$N$34,MATCH($A27,'jiliarena_日报_底稿'!$A$3:$A$34,0),MATCH(F$3,'jiliarena_日报_底稿'!$A$3:$N$3,0))} | G27: =SUMIFS('渠道充值成功率_底稿'!$F:$F,'渠道充值成功率_底稿'!$A:$A,A27) -> 0 | H27: {=INDEX('jiliarena_日报_底稿'!$A$3:$N$34,MATCH($A27,'jiliarena_日报_底稿'!$A$3:$A$34,0),MATCH(H$3,'jiliarena_日报_底稿'!$A$3:$N$3,0))} | J27: {=INDEX('jiliarena_日报_底稿'!$A$3:$N$34,MATCH($A27,'jiliarena_日报_底稿'!$A$3:$A$34,0),MATCH(J$3,'jiliarena_日报_底稿'!$A$3:$N$3,0))} | K27: =SUMIFS('渠道充值成功率_底稿'!$J:$J,'渠道充值成功率_底稿'!$A:$A,$A27) -> 0 | L27: {=INDEX('jiliarena_日报_底稿'!$A$3:$N$34,MATCH($A27,'jiliarena_日报_底稿'!$A$3:$A$34,0),MATCH(L$3,'jiliarena_日报_底稿'!$A$3:$N$3,0))} | M27: {=INDEX('jiliarena_日报_底稿'!$P$2:$DS$34,MATCH($A27,'jiliarena_日报_底稿'!$P$2:$P$34,0),MATCH($M$3,'jiliarena_日报_底稿'!$P$3:$DS$3,0))} | N27: =IF(C27="","",ROUND(C27/B27,4)) | O27: =IF(K27="","",ROUND(K27/C27,0)) -> #DIV/0! | P27: =IF(L27="","",ROUND(K27/L27,6)) | Q27: =IF(G27="","",ROUND(G27/F27,1)) -> #DIV/0! | R27: =IF(L27="","",ROUND(L27/F27,0)) | S27: =IF(L27="","",ROUND(L27/G27,0)) | T27: =IF(S27="","",ROUND(S27/O27,1)) | U27: =IF(M27="","",ROUND(M27/H27,0)) | V27: =IF(M27="","",L27-M27) | W27: =AB27+AE27+AH27+AK27+AN27+AQ27 -> 0 | X27: {=index('jiliarena_日报_底稿'!$P$2:$DS$34,match($A27,'jiliarena_日报_底稿'!$P$2:$P$34,0),match("电子有效投注",'jiliarena_日报_底稿'!$P$3:$DS$3,0))+index('jiliarena_日报_底稿'!$P$2:$DS$34,match($A27,'jiliarena_日报_底稿'!$P$2:$P$34,0),match("真人有效投注",'jiliarena_日报_底稿'!$P$3:$DS$3,0))+index('jiliarena_日报_底稿'!$P$2:$DS$34,match($A27,'jiliarena_日报_底稿'!$P$2:$P$34,0),match("彩票有效投注",'jiliarena_日报_底稿'!$P$3:$DS$3,0))+index('jiliarena_日报_底稿'!$P$2:$DS$34,match($A27,'jiliarena_日报_底稿'!$P$2:$P$34,0),match("棋牌有效投注",'jiliarena_日报_底稿'!$P$3:$DS$3,0))+index('jiliarena_日报_底稿'!$P$2:$DS$34,match($A27,'jiliarena_日报_底稿'!$P$2:$P$34,0),match("捕鱼有效投注",'jiliarena_日报_底稿'!$P$3:$DS$3,0))+index('jiliarena_日报_底稿'!$P$2:$DS$34,match($A27,'jiliarena_日报_底稿'!$P$2:$P$34,0),match("体育有效投注",'jiliarena_日报_底稿'!$P$3:$DS$3,0))+index('jiliarena_日报_底稿'!$P$2:$DS$34,match($A27,'jiliarena_日报_底稿'!$P$2:$P$34,0),match("盘口彩票有效投注",'jiliarena_日报_底稿'!$P$3:$DS$3,0))} -> 0 | Y27: =AB27+AE27+AH27+AK27+AN27+AQ27-AR27-AO27-AL27-AI27-AF27-AC27 -> 0 | Z27: =AC27+AF27+AI27+AL27+AO27+AR27 -> 0 | AA27: =IFERROR(ROUND(1-(Z27/W27),6),"") | AB27: {=INDEX('jiliarena_日报_底稿'!$P$2:$DS$34,MATCH($A27,'jiliarena_日报_底稿'!$P$2:$P$34,0),MATCH(AB$3,'jiliarena_日报_底稿'!$P$3:$DS$3,0))} | AC27: {=INDEX('jiliarena_日报_底稿'!$P$2:$DS$34,MATCH($A27,'jiliarena_日报_底稿'!$P$2:$P$34,0),MATCH(AC$3,'jiliarena_日报_底稿'!$P$3:$DS$3,0))} | AD27: =IF(AC27="","",ROUND((1-(AC27/AB27)),6)) | AE27: {=INDEX('jiliarena_日报_底稿'!$P$2:$DS$34,MATCH($A27,'jiliarena_日报_底稿'!$P$2:$P$34,0),MATCH(AE$3,'jiliarena_日报_底稿'!$P$3:$DS$3,0))} | AF27: {=INDEX('jiliarena_日报_底稿'!$P$2:$DS$34,MATCH($A27,'jiliarena_日报_底稿'!$P$2:$P$34,0),MATCH(AF$3,'jiliarena_日报_底稿'!$P$3:$DS$3,0))} | AG27: =IF(AF27="","",ROUND((1-(AF27/AE27)),6)) | AH27: {=INDEX('jiliarena_日报_底稿'!$P$2:$DS$34,MATCH($A27,'jiliarena_日报_底稿'!$P$2:$P$34,0),MATCH(AH$3,'jiliarena_日报_底稿'!$P$3:$DS$3,0))} | AI27: {=INDEX('jiliarena_日报_底稿'!$P$2:$DS$34,MATCH($A27,'jiliarena_日报_底稿'!$P$2:$P$34,0),MATCH(AI$3,'jiliarena_日报_底稿'!$P$3:$DS$3,0))} | AJ27: =IF(AI27="","",ROUND((1-(AI27/AH27)),6)) | AK27: {=INDEX('jiliarena_日报_底稿'!$P$2:$DS$34,MATCH($A27,'jiliarena_日报_底稿'!$P$2:$P$34,0),MATCH(AK$3,'jiliarena_日报_底稿'!$P$3:$DS$3,0))} | AL27: {=INDEX('jiliarena_日报_底稿'!$P$2:$DS$34,MATCH($A27,'jiliarena_日报_底稿'!$P$2:$P$34,0),MATCH(AL$3,'jiliarena_日报_底稿'!$P$3:$DS$3,0))} | AM27: =IF(AL27="","",ROUND((1-(AL27/AK27)),6)) | AN27: {=INDEX('jiliarena_日报_底稿'!$P$2:$DS$34,MATCH($A27,'jiliarena_日报_底稿'!$P$2:$P$34,0),MATCH(AN$3,'jiliarena_日报_底稿'!$P$3:$DS$3,0))} | AO27: {=INDEX('jiliarena_日报_底稿'!$P$2:$DS$34,MATCH($A27,'jiliarena_日报_底稿'!$P$2:$P$34,0),MATCH(AO$3,'jiliarena_日报_底稿'!$P$3:$DS$3,0))} | AP27: =IF(AO27="","",ROUND((1-(AO27/AN27)),6)) | AQ27: {=INDEX('jiliarena_日报_底稿'!$P$2:$DS$34,MATCH($A27,'jiliarena_日报_底稿'!$P$2:$P$34,0),MATCH(AQ$3,'jiliarena_日报_底稿'!$P$3:$DS$3,0))} | AR27: {=INDEX('jiliarena_日报_底稿'!$P$2:$DS$34,MATCH($A27,'jiliarena_日报_底稿'!$P$2:$P$34,0),MATCH(AR$3,'jiliarena_日报_底稿'!$P$3:$DS$3,0))} | AS27: =IF(AR27="","",ROUND((1-(AR27/AQ27)),6)) | AT27: =SUMIFS('jiliarena_活动分析数据_底稿'!$K:$K,'jiliarena_活动分析数据_底稿'!$B:$B,$A27,'jiliarena_活动分析数据_底稿'!$L:$L,AT$3) -> 0 | AU27: =SUMIFS('jiliarena_活动分析数据_底稿'!$K:$K,'jiliarena_活动分析数据_底稿'!$B:$B,$A27,'jiliarena_活动分析数据_底稿'!$L:$L,AU$3) -> 0 | AV27: =SUMIFS('jiliarena_活动分析数据_底稿'!$K:$K,'jiliarena_活动分析数据_底稿'!$B:$B,$A27,'jiliarena_活动分析数据_底稿'!$L:$L,AV$3) -> 0 | AW27: =SUMIFS('jiliarena_活动分析数据_底稿'!$K:$K,'jiliarena_活动分析数据_底稿'!$B:$B,$A27,'jiliarena_活动分析数据_底稿'!$L:$L,AW$3) -> 0 | AX27: =SUMIFS('jiliarena_活动分析数据_底稿'!$K:$K,'jiliarena_活动分析数据_底稿'!$B:$B,$A27,'jiliarena_活动分析数据_底稿'!$L:$L,AX$3) -> 0 | AY27: =SUMIFS('jiliarena_活动分析数据_底稿'!$K:$K,'jiliarena_活动分析数据_底稿'!$B:$B,$A27,'jiliarena_活动分析数据_底稿'!$L:$L,AY$3) -> 0 | AZ27: =SUMIFS('jiliarena_活动分析数据_底稿'!$K:$K,'jiliarena_活动分析数据_底稿'!$B:$B,$A27,'jiliarena_活动分析数据_底稿'!$L:$L,AZ$3) -> 0 | BA27: =SUMIFS('jiliarena_活动分析数据_底稿'!$K:$K,'jiliarena_活动分析数据_底稿'!$B:$B,$A27,'jiliarena_活动分析数据_底稿'!$L:$L,BA$3) -> 0 | ... BP27: =SUMIFS('jiliarena_活动分析数据_底稿'!$K:$K,'jiliarena_活动分析数据_底稿'!$B:$B,$A27,'jiliarena_活动分析数据_底稿'!$L:$L,BP$3) -> 0 | BQ27: =SUM(AT27:BP27) -> 0 | BR27: =AT27 -> 0 | BS27: =BB27 -> 0 | BT27: =iferror(IF(BQ27="","",ROUND(BQ27/X27,6)),"") | BU27: =iferror(BQ27/L27,"") | BV27: =iferror(BQ27/Y27,"") | BW27: =IF(BQ27="","",Y27-BQ27) -> 0 | BX27: =iferror(BQ27/BW27,"") | BY27: =L27*$BY$1 -> 0 | BZ27: =M27*$BZ$1 -> 0 | CA27: =BY27+BZ27 -> 0 | CB27: =IF(Y27="","",ROUND(Y27*9%,0)) -> 0 | CC27: =iferror(CA27/BW27,"") | CD27: {=index('jiliarena_日报_底稿'!$P$3:$DS$34,match(A27,'jiliarena_日报_底稿'!$P$3:$P$34,0),match("综合性分红",'jiliarena_日报_底稿'!$P$3:$DS$3,0))} | CF27: {=INDEX('jiliarena_日报_底稿'!$P$2:$DS$34,MATCH($A27,'jiliarena_日报_底稿'!$P$2:$P$34,0),MATCH(CF$3,'jiliarena_日报_底稿'!$P$3:$DS$3,0))} | CG27: {=-INDEX('jiliarena_日报_底稿'!$P$2:$DS$34,MATCH($A27,'jiliarena_日报_底稿'!$P$2:$P$34,0),MATCH(CG$3,'jiliarena_日报_底稿'!$P$3:$DS$3,0))} -> 0 | CH27: {=INDEX('jiliarena_日报_底稿'!$P$2:$DS$34,MATCH($A27,'jiliarena_日报_底稿'!$P$2:$P$34,0),MATCH(CH$3,'jiliarena_日报_底稿'!$P$3:$DS$3,0))} | CI27: =IF(CA27="","",BW27-CA27-CD27-CB27) -> 0 | CJ27: =IFERROR(month(A27),"") -> 3 | CK27: =IFERROR(DAY(A27),"") -> 15
A28: SUB total | B28: =SUM(B21:B27) -> 500 | C28: =SUM(C21:C27) -> 238 | D28: =SUM(D21:D27) -> 11209 | E28: =SUM(E21:E27) -> 28 | F28: =SUM(F21:F27) -> 761 | G28: =SUM(G21:G27) -> 1051 | H28: =SUM(H21:H27) -> 233 | I28: =SUM(I21:I27) -> 279 | ... M28: =SUM(M21:M27) -> 140520 | N28: =IF(C28="","",ROUND(C28/B28,4)) -> 0.476 | O28: =IF(K28="","",ROUND(K28/C28,0)) -> 121 | P28: =IF(L28="","",ROUND(K28/L28,6)) -> 0.190603 | Q28: =IF(G28="","",ROUND(G28/F28,1)) -> 1.4 | R28: =IF(L28="","",ROUND(L28/F28,0)) -> 198 | S28: =IF(L28="","",ROUND(L28/G28,0)) -> 143 | T28: =IF(S28="","",ROUND(S28/O28,1)) -> 1.2 | U28: =IF(M28="","",ROUND(M28/H28,0)) -> 603 | V28: =IF(M28="","",L28-M28) -> 10018 | W28: =SUM(W21:W27) -> 1659852.5 | X28: =SUM(X21:X27) -> 1529684 | Y28: =SUM(Y21:Y27) -> 60681.884 | Z28: =SUM(Z21:Z27) -> 1599170.6 | AA28: =IFERROR(ROUND(1-(Z28/W28),6),"") -> 0.036559 | AB28: =SUM(AB21:AB27) -> 0 | AC28: =SUM(AC21:AC27) -> 0 | AD28: =IF(AC28="","",ROUND((1-(AC28/AB28)),6)) -> #DIV/0! | AE28: =SUM(AE21:AE27) -> 1640163.4 | AF28: =SUM(AF21:AF27) -> 1578675.8 | AG28: =IF(AF28="","",ROUND((1-(AF28/AE28)),6)) -> 0.037489 | AH28: =SUM(AH21:AH27) -> 8536.5 | AI28: =SUM(AI21:AI27) -> 9896.5 | AJ28: =IF(AI28="","",ROUND((1-(AI28/AH28)),6)) -> -0.159316 | AK28: =SUM(AK21:AK27) -> 11120.55 | AL28: =SUM(AL21:AL27) -> 10598.3 | AM28: =IF(AL28="","",ROUND((1-(AL28/AK28)),6)) -> 0.046963 | AN28: =SUM(AN21:AN27) -> 0 | AO28: =SUM(AO21:AO27) -> 0 | AP28: =IF(AO28="","",ROUND((1-(AO28/AN28)),6)) -> #DIV/0! | AQ28: =SUM(AQ21:AQ27) -> 32 | AR28: =SUM(AR21:AR27) -> 0 | AS28: =IF(AR28="","",ROUND((1-(AR28/AQ28)),6)) -> 1 | AT28: =SUM(AT21:AT27) -> 4484.52 | AU28: =SUM(AU21:AU27) -> 0 | AV28: =SUM(AV21:AV27) -> 1101.68 | AW28: =SUM(AW21:AW27) -> 13345 | AX28: =SUM(AX21:AX27) -> 683 | AY28: =SUM(AY21:AY27) -> 0 | AZ28: =SUM(AZ21:AZ27) -> 0 | BA28: =SUM(BA21:BA27) -> 0 | ... BS28: =SUM(BS21:BS27) -> 838.87 | BT28: =iferror(IF(BQ28="","",ROUND(BQ28/X28,6)),"") -> 0.018459 | BU28: =iferror(BQ28/L28,"") -> 0.18757105 | BV28: =iferror(BQ28/Y28,"") -> 0.46532125 | BW28: =IF(BQ28="","",Y28-BQ28) -> 32445.314 | BX28: =iferror(BQ28/BW28,"") -> 0.87028191 | BY28: =L28*$BY$1 -> 3627.9658 | BZ28: =M28*$BZ$1 -> 281.04 | CA28: =BY28+BZ28 -> 3909.0058 | CB28: =IF(Y28="","",ROUND(Y28*9%,0)) -> 5461 | CC28: =iferror(CA28/BW28,"") -> 0.12047983 | CD28: =SUM(CD21:CD27) -> 0 | CE28: =SUM(CE21:CE27) -> 0 | CF28: =SUM(CF21:CF27) -> 0 | CG28: =SUM(CG21:CG27) -> 0 | CH28: =SUM(CH21:CH27) -> 422935.3 | CI28: =IF(CA28="","",BW28-CA28-CD28-CB28) -> 23075.308 | CJ28: =IFERROR(month(A28),"") | CK28: =IFERROR(DAY(A28),"")
