Workbook

Sheet 渠道充值成功率-统整
B1: Date | C1: jiliarena | D1: GCash | E1: QRPH | F1: GCashQR | G1: Maya | H1: GRABPAY | I1: Online Banking | J1: USDT | K1: GOTYME | L1: GCASHPAY
A2: =B2 -> 46054 | B2: 46054 | C2: 申请笔数 | D2: =SUMIFS('渠道充值成功率_底稿'!$C:$C,'渠道充值成功率_底稿'!$A:$A,$A2,'渠道充值成功率_底稿'!$B:$B,D$1) -> 0 | E2: =SUMIFS('渠道充值成功率_底稿'!$C:$C,'渠道充值成功率_底稿'!$A:$A,$A2,'渠道充值成功率_底稿'!$B:$B,E$1) -> 0 | F2: =SUMIFS('渠道充值成功率_底稿'!$C:$C,'渠道充值成功率_底稿'!$A:$A,$A2,'渠道充值成功率_底稿'!$B:$B,F$1) -> 0 | G2: =SUMIFS('渠道充值成功率_底稿'!$C:$C,'渠道充值成功率_底稿'!$A:$A,$A2,'渠道充值成功率_底稿'!$B:$B,G$1) -> 0 | H2: =SUMIFS('渠道充值成功率_底稿'!$C:$C,'渠道充值成功率_底稿'!$A:$A,$A2,'渠道充值成功率_底稿'!$B:$B,H$1) -> 0 | I2: =SUMIFS('渠道充值成功率_底稿'!$C:$C,'渠道充值成功率_底稿'!$A:$A,$A2,'渠道充值成功率_底稿'!$B:$B,I$1) -> 0 | J2: =SUMIFS('渠道充值成功率_底稿'!$C:$C,'渠道充值成功率_底稿'!$A:$A,$A2,'渠道充值成功率_底稿'!$B:$B,J$1) -> 0 | K2: =SUMIFS('渠道充值成功率_底稿'!$C:$C,'渠道充值成功率_底稿'!$A:$A,$A2,'渠道充值成功率_底稿'!$B:$B,K$1) -> 0 | L2: =SUMIFS('渠道充值成功率_底稿'!$C:$C,'渠道充值成功率_底稿'!$A:$A,$A2,'渠道充值成功率_底稿'!$B:$B,L$1) -> 0
A3: =B2 -> 46054 | C3: 到账笔数 | D3: =SUMIFS('渠道充值成功率_底稿'!$F:$F,'渠道充值成功率_底稿'!$A:$A,$A3,'渠道充值成功率_底稿'!$B:$B,D$1) -> 0 | E3: =SUMIFS('渠道充值成功率_底稿'!$F:$F,'渠道充值成功率_底稿'!$A:$A,$A3,'渠道充值成功率_底稿'!$B:$B,E$1) -> 0 | F3: =SUMIFS('渠道充值成功率_底稿'!$F:$F,'渠道充值成功率_底稿'!$A:$A,$A3,'渠道充值成功率_底稿'!$B:$B,F$1) -> 0 | G3: =SUMIFS('渠道充值成功率_底稿'!$F:$F,'渠道充值成功率_底稿'!$A:$A,$A3,'渠道充值成功率_底稿'!$B:$B,G$1) -> 0 | H3: =SUMIFS('渠道充值成功率_底稿'!$F:$F,'渠道充值成功率_底稿'!$A:$A,$A3,'渠道充值成功率_底稿'!$B:$B,H$1) -> 0 | I3: =SUMIFS('渠道充值成功率_底稿'!$F:$F,'渠道充值成功率_底稿'!$A:$A,$A3,'渠道充值成功率_底稿'!$B:$B,I$1) -> 0 | J3: =SUMIFS('渠道充值成功率_底稿'!$F:$F,'渠道充值成功率_底稿'!$A:$A,$A3,'渠道充值成功率_底稿'!$B:$B,J$1) -> 0 | K3: =SUMIFS('渠道充值成功率_底稿'!$F:$F,'渠道充值成功率_底稿'!$A:$A,$A3,'渠道充值成功率_底稿'!$B:$B,K$1) -> 0 | L3: =SUMIFS('渠道充值成功率_底稿'!$F:$F,'渠道充值成功率_底稿'!$A:$A,$A3,'渠道充值成功率_底稿'!$B:$B,L$1) -> 0
A4: =B2 -> 46054 | C4: 笔数成功率 | D4: =IFERROR(ROUND(D3/D2,6),"0") -> 0 | E4: =IFERROR(ROUND(E3/E2,6),"0") -> 0 | F4: =IFERROR(ROUND(F3/F2,6),"0") -> 0 | G4: =IFERROR(ROUND(G3/G2,6),"0") -> 0 | H4: =IFERROR(ROUND(H3/H2,6),"0") -> 0 | I4: =IFERROR(ROUND(I3/I2,6),"0") -> 0 | J4: =IFERROR(ROUND(J3/J2,6),"0") -> 0 | K4: =IFERROR(ROUND(K3/K2,6),"0") -> 0 | L4: =IFERROR(ROUND(L3/L2,6),"0") -> 0
A5: =B2 -> 46054 | C5: 申请金额 | D5: =SUMIFS('渠道充值成功率_底稿'!$D:$D,'渠道充值成功率_底稿'!$A:$A,$A6,'渠道充值成功率_底稿'!$B:$B,D$1) -> 0 | E5: =SUMIFS('渠道充值成功率_底稿'!$D:$D,'渠道充值成功率_底稿'!$A:$A,$A5,'渠道充值成功率_底稿'!$B:$B,E$1) -> 0 | F5: =SUMIFS('渠道充值成功率_底稿'!$D:$D,'渠道充值成功率_底稿'!$A:$A,$A5,'渠道充值成功率_底稿'!$B:$B,F$1) -> 0 | G5: =SUMIFS('渠道充值成功率_底稿'!$D:$D,'渠道充值成功率_底稿'!$A:$A,$A5,'渠道充值成功率_底稿'!$B:$B,G$1) -> 0 | H5: =SUMIFS('渠道充值成功率_底稿'!$D:$D,'渠道充值成功率_底稿'!$A:$A,$A5,'渠道充值成功率_底稿'!$B:$B,H$1) -> 0 | I5: =SUMIFS('渠道充值成功率_底稿'!$D:$D,'渠道充值成功率_底稿'!$A:$A,$A5,'渠道充值成功率_底稿'!$B:$B,I$1) -> 0 | J5: =SUMIFS('渠道充值成功率_底稿'!$D:$D,'渠道充值成功率_底稿'!$A:$A,$A5,'渠道充值成功率_底稿'!$B:$B,J$1) -> 0 | K5: =SUMIFS('渠道充值成功率_底稿'!$D:$D,'渠道充值成功率_底稿'!$A:$A,$A5,'渠道充值成功率_底稿'!$B:$B,K$1) -> 0 | L5: =SUMIFS('渠道充值成功率_底稿'!$D:$D,'渠道充值成功率_底稿'!$A:$A,$A5,'渠道充值成功率_底稿'!$B:$B,L$1) -> 0
A6: =B2 -> 46054 | C6: 到账金额 | D6: =SUMIFS('渠道充值成功率_底稿'!$G:$G,'渠道充值成功率_底稿'!$A:$A,$A7,'渠道充值成功率_底稿'!$B:$B,D$1) -> 0 | E6: =SUMIFS('渠道充值成功率_底稿'!$G:$G,'渠道充值成功率_底稿'!$A:$A,$A6,'渠道充值成功率_底稿'!$B:$B,E$1) -> 0 | F6: =SUMIFS('渠道充值成功率_底稿'!$G:$G,'渠道充值成功率_底稿'!$A:$A,$A6,'渠道充值成功率_底稿'!$B:$B,F$1) -> 0 | G6: =SUMIFS('渠道充值成功率_底稿'!$G:$G,'渠道充值成功率_底稿'!$A:$A,$A6,'渠道充值成功率_底稿'!$B:$B,G$1) -> 0 | H6: =SUMIFS('渠道充值成功率_底稿'!$G:$G,'渠道充值成功率_底稿'!$A:$A,$A6,'渠道充值成功率_底稿'!$B:$B,H$1) -> 0 | I6: =SUMIFS('渠道充值成功率_底稿'!$G:$G,'渠道充值成功率_底稿'!$A:$A,$A6,'渠道充值成功率_底稿'!$B:$B,I$1) -> 0 | J6: =SUMIFS('渠道充值成功率_底稿'!$G:$G,'渠道充值成功率_底稿'!$A:$A,$A6,'渠道充值成功率_底稿'!$B:$B,J$1) -> 0 | K6: =SUMIFS('渠道充值成功率_底稿'!$G:$G,'渠道充值成功率_底稿'!$A:$A,$A6,'渠道充值成功率_底稿'!$B:$B,K$1) -> 0 | L6: =SUMIFS('渠道充值成功率_底稿'!$G:$G,'渠道充值成功率_底稿'!$A:$A,$A6,'渠道充值成功率_底稿'!$B:$B,L$1) -> 0
A7: =B2 -> 46054 | C7: 金额成功率 | D7: =IFERROR(ROUND(D6/D5,6),"0") -> 0 | E7: =IFERROR(ROUND(E6/E5,6),"0") -> 0 | F7: =IFERROR(ROUND(F6/F5,6),"0") -> 0 | G7: =IFERROR(ROUND(G6/G5,6),"0") -> 0 | H7: =IFERROR(ROUND(H6/H5,6),"0") -> 0 | I7: =IFERROR(ROUND(I6/I5,6),"0") -> 0 | J7: =IFERROR(ROUND(J6/J5,6),"0") -> 0 | K7: =IFERROR(ROUND(K6/K5,6),"0") -> 0 | L7: =IFERROR(ROUND(L6/L5,6),"0") -> 0
A8: =B8 -> 46055 | B8: =B2+1 -> 46055 | C8: 申请笔数 | D8: =SUMIFS('渠道充值成功率_底稿'!$C:$C,'渠道充值成功率_底稿'!$A:$A,$A8,'渠道充值成功率_底稿'!$B:$B,D$1) -> 0 | E8: =SUMIFS('渠道充值成功率_底稿'!$C:$C,'渠道充值成功率_底稿'!$A:$A,$A8,'渠道充值成功率_底稿'!$B:$B,E$1) -> 0 | F8: =SUMIFS('渠道充值成功率_底稿'!$C:$C,'渠道充值成功率_底稿'!$A:$A,$A8,'渠道充值成功率_底稿'!$B:$B,F$1) -> 0 | G8: =SUMIFS('渠道充值成功率_底稿'!$C:$C,'渠道充值成功率_底稿'!$A:$A,$A8,'渠道充值成功率_底稿'!$B:$B,G$1) -> 0 | H8: =SUMIFS('渠道充值成功率_底稿'!$C:$C,'渠道充值成功率_底稿'!$A:$A,$A8,'渠道充值成功率_底稿'!$B:$B,H$1) -> 0 | I8: =SUMIFS('渠道充值成功率_底稿'!$C:$C,'渠道充值成功率_底稿'!$A:$A,$A8,'渠道充值成功率_底稿'!$B:$B,I$1) -> 0 | J8: =SUMIFS('渠道充值成功率_底稿'!$C:$C,'渠道充值成功率_底稿'!$A:$A,$A8,'渠道充值成功率_底稿'!$B:$B,J$1) -> 0 | K8: =SUMIFS('渠道充值成功率_底稿'!$C:$C,'渠道充值成功率_底稿'!$A:$A,$A8,'渠道充值成功率_底稿'!$B:$B,K$1) -> 0 | L8: =SUMIFS('渠道充值成功率_底稿'!$C:$C,'渠道充值成功率_底稿'!$A:$A,$A8,'渠道充值成功率_底稿'!$B:$B,L$1) -> 0
A9: =B8 -> 46055 | C9: 到账笔数 | D9: =SUMIFS('渠道充值成功率_底稿'!$F:$F,'渠道充值成功率_底稿'!$A:$A,$A9,'渠道充值成功率_底稿'!$B:$B,D$1) -> 0 | E9: =SUMIFS('渠道充值成功率_底稿'!$F:$F,'渠道充值成功率_底稿'!$A:$A,$A9,'渠道充值成功率_底稿'!$B:$B,E$1) -> 0 | F9: =SUMIFS('渠道充值成功率_底稿'!$F:$F,'渠道充值成功率_底稿'!$A:$A,$A9,'渠道充值成功率_底稿'!$B:$B,F$1) -> 0 | G9: =SUMIFS('渠道充值成功率_底稿'!$F:$F,'渠道充值成功率_底稿'!$A:$A,$A9,'渠道充值成功率_底稿'!$B:$B,G$1) -> 0 | H9: =SUMIFS('渠道充值成功率_底稿'!$F:$F,'渠道充值成功率_底稿'!$A:$A,$A9,'渠道充值成功率_底稿'!$B:$B,H$1) -> 0 | I9: =SUMIFS('渠道充值成功率_底稿'!$F:$F,'渠道充值成功率_底稿'!$A:$A,$A9,'渠道充值成功率_底稿'!$B:$B,I$1) -> 0 | J9: =SUMIFS('渠道充值成功率_底稿'!$F:$F,'渠道充值成功率_底稿'!$A:$A,$A9,'渠道充值成功率_底稿'!$B:$B,J$1) -> 0 | K9: =SUMIFS('渠道充值成功率_底稿'!$F:$F,'渠道充值成功率_底稿'!$A:$A,$A9,'渠道充值成功率_底稿'!$B:$B,K$1) -> 0 | L9: =SUMIFS('渠道充值成功率_底稿'!$F:$F,'渠道充值成功率_底稿'!$A:$A,$A9,'渠道充值成功率_底稿'!$B:$B,L$1) -> 0
A10: =B8 -> 46055 | C10: 笔数成功率 | D10: =IFERROR(ROUND(D9/D8,6),"0") -> 0 | E10: =IFERROR(ROUND(E9/E8,6),"0") -> 0 | F10: =IFERROR(ROUND(F9/F8,6),"0") -> 0 | G10: =IFERROR(ROUND(G9/G8,6),"0") -> 0 | H10: =IFERROR(ROUND(H9/H8,6),"0") -> 0 | I10: =IFERROR(ROUND(I9/I8,6),"0") -> 0 | J10: =IFERROR(ROUND(J9/J8,6),"0") -> 0 | K10: =IFERROR(ROUND(K9/K8,6),"0") -> 0 | L10: =IFERROR(ROUND(L9/L8,6),"0") -> 0
A11: =B8 -> 46055 | C11: 申请金额 | D11: =SUMIFS('渠道充值成功率_底稿'!$D:$D,'渠道充值成功率_底稿'!$A:$A,$A12,'渠道充值成功率_底稿'!$B:$B,D$1) -> 0 | E11: =SUMIFS('渠道充值成功率_底稿'!$D:$D,'渠道充值成功率_底稿'!$A:$A,$A11,'渠道充值成功率_底稿'!$B:$B,E$1) -> 0 | F11: =SUMIFS('渠道充值成功率_底稿'!$D:$D,'渠道充值成功率_底稿'!$A:$A,$A11,'渠道充值成功率_底稿'!$B:$B,F$1) -> 0 | G11: =SUMIFS('渠道充值成功率_底稿'!$D:$D,'渠道充值成功率_底稿'!$A:$A,$A11,'渠道充值成功率_底稿'!$B:$B,G$1) -> 0 | H11: =SUMIFS('渠道充值成功率_底稿'!$D:$D,'渠道充值成功率_底稿'!$A:$A,$A11,'渠道充值成功率_底稿'!$B:$B,H$1) -> 0 | I11: =SUMIFS('渠道充值成功率_底稿'!$D:$D,'渠道充值成功率_底稿'!$A:$A,$A11,'渠道充值成功率_底稿'!$B:$B,I$1) -> 0 | J11: =SUMIFS('渠道充值成功率_底稿'!$D:$D,'渠道充值成功率_底稿'!$A:$A,$A11,'渠道充值成功率_底稿'!$B:$B,J$1) -> 0 | K11: =SUMIFS('渠道充值成功率_底稿'!$D:$D,'渠道充值成功率_底稿'!$A:$A,$A11,'渠道充值成功率_底稿'!$B:$B,K$1) -> 0 | L11: =SUMIFS('渠道充值成功率_底稿'!$D:$D,'渠道充值成功率_底稿'!$A:$A,$A11,'渠道充值成功率_底稿'!$B:$B,L$1) -> 0
A12: =B8 -> 46055 | C12: 到账金额 | D12: =SUMIFS('渠道充值成功率_底稿'!$G:$G,'渠道充值成功率_底稿'!$A:$A,$A13,'渠道充值成功率_底稿'!$B:$B,D$1) -> 0 | E12: =SUMIFS('渠道充值成功率_底稿'!$G:$G,'渠道充值成功率_底稿'!$A:$A,$A12,'渠道充值成功率_底稿'!$B:$B,E$1) -> 0 | F12: =SUMIFS('渠道充值成功率_底稿'!$G:$G,'渠道充值成功率_底稿'!$A:$A,$A12,'渠道充值成功率_底稿'!$B:$B,F$1) -> 0 | G12: =SUMIFS('渠道充值成功率_底稿'!$G:$G,'渠道充值成功率_底稿'!$A:$A,$A12,'渠道充值成功率_底稿'!$B:$B,G$1) -> 0 | H12: =SUMIFS('渠道充值成功率_底稿'!$G:$G,'渠道充值成功率_底稿'!$A:$A,$A12,'渠道充值成功率_底稿'!$B:$B,H$1) -> 0 | I12: =SUMIFS('渠道充值成功率_底稿'!$G:$G,'渠道充值成功率_底稿'!$A:$A,$A12,'渠道充值成功率_底稿'!$B:$B,I$1) -> 0 | J12: =SUMIFS('渠道充值成功率_底稿'!$G:$G,'渠道充值成功率_底稿'!$A:$A,$A12,'渠道充值成功率_底稿'!$B:$B,J$1) -> 0 | K12: =SUMIFS('渠道充值成功率_底稿'!$G:$G,'渠道充值成功率_底稿'!$A:$A,$A12,'渠道充值成功率_底稿'!$B:$B,K$1) -> 0 | L12: =SUMIFS('渠道充值成功率_底稿'!$G:$G,'渠道充值成功率_底稿'!$A:$A,$A12,'渠道充值成功率_底稿'!$B:$B,L$1) -> 0
A13: =B8 -> 46055 | C13: 金额成功率 | D13: =IFERROR(ROUND(D12/D11,6),"0") -> 0 | E13: =IFERROR(ROUND(E12/E11,6),"0") -> 0 | F13: =IFERROR(ROUND(F12/F11,6),"0") -> 0 | G13: =IFERROR(ROUND(G12/G11,6),"0") -> 0 | H13: =IFERROR(ROUND(H12/H11,6),"0") -> 0 | I13: =IFERROR(ROUND(I12/I11,6),"0") -> 0 | J13: =IFERROR(ROUND(J12/J11,6),"0") -> 0 | K13: =IFERROR(ROUND(K12/K11,6),"0") -> 0 | L13: =IFERROR(ROUND(L12/L11,6),"0") -> 0
A14: =B14 -> 46056 | B14: =B8+1 -> 46056 | C14: 申请笔数 | D14: =SUMIFS('渠道充值成功率_底稿'!$C:$C,'渠道充值成功率_底稿'!$A:$A,$A14,'渠道充值成功率_底稿'!$B:$B,D$1) -> 0 | E14: =SUMIFS('渠道充值成功率_底稿'!$C:$C,'渠道充值成功率_底稿'!$A:$A,$A14,'渠道充值成功率_底稿'!$B:$B,E$1) -> 0 | F14: =SUMIFS('渠道充值成功率_底稿'!$C:$C,'渠道充值成功率_底稿'!$A:$A,$A14,'渠道充值成功率_底稿'!$B:$B,F$1) -> 0 | G14: =SUMIFS('渠道充值成功率_底稿'!$C:$C,'渠道充值成功率_底稿'!$A:$A,$A14,'渠道充值成功率_底稿'!$B:$B,G$1) -> 0 | H14: =SUMIFS('渠道充值成功率_底稿'!$C:$C,'渠道充值成功率_底稿'!$A:$A,$A14,'渠道充值成功率_底稿'!$B:$B,H$1) -> 0 | I14: =SUMIFS('渠道充值成功率_底稿'!$C:$C,'渠道充值成功率_底稿'!$A:$A,$A14,'渠道充值成功率_底稿'!$B:$B,I$1) -> 0 | J14: =SUMIFS('渠道充值成功率_底稿'!$C:$C,'渠道充值成功率_底稿'!$A:$A,$A14,'渠道充值成功率_底稿'!$B:$B,J$1) -> 0 | K14: =SUMIFS('渠道充值成功率_底稿'!$C:$C,'渠道充值成功率_底稿'!$A:$A,$A14,'渠道充值成功率_底稿'!$B:$B,K$1) -> 0 | L14: =SUMIFS('渠道充值成功率_底稿'!$C:$C,'渠道充值成功率_底稿'!$A:$A,$A14,'渠道充值成功率_底稿'!$B:$B,L$1) -> 0
A15: =B14 -> 46056 | C15: 到账笔数 | D15: =SUMIFS('渠道充值成功率_底稿'!$F:$F,'渠道充值成功率_底稿'!$A:$A,$A15,'渠道充值成功率_底稿'!$B:$B,D$1) -> 0 | E15: =SUMIFS('渠道充值成功率_底稿'!$F:$F,'渠道充值成功率_底稿'!$A:$A,$A15,'渠道充值成功率_底稿'!$B:$B,E$1) -> 0 | F15: =SUMIFS('渠道充值成功率_底稿'!$F:$F,'渠道充值成功率_底稿'!$A:$A,$A15,'渠道充值成功率_底稿'!$B:$B,F$1) -> 0 | G15: =SUMIFS('渠道充值成功率_底稿'!$F:$F,'渠道充值成功率_底稿'!$A:$A,$A15,'渠道充值成功率_底稿'!$B:$B,G$1) -> 0 | H15: =SUMIFS('渠道充值成功率_底稿'!$F:$F,'渠道充值成功率_底稿'!$A:$A,$A15,'渠道充值成功率_底稿'!$B:$B,H$1) -> 0 | I15: =SUMIFS('渠道充值成功率_底稿'!$F:$F,'渠道充值成功率_底稿'!$A:$A,$A15,'渠道充值成功率_底稿'!$B:$B,I$1) -> 0 | J15: =SUMIFS('渠道充值成功率_底稿'!$F:$F,'渠道充值成功率_底稿'!$A:$A,$A15,'渠道充值成功率_底稿'!$B:$B,J$1) -> 0 | K15: =SUMIFS('渠道充值成功率_底稿'!$F:$F,'渠道充值成功率_底稿'!$A:$A,$A15,'渠道充值成功率_底稿'!$B:$B,K$1) -> 0 | L15: =SUMIFS('渠道充值成功率_底稿'!$F:$F,'渠道充值成功率_底稿'!$A:$A,$A15,'渠道充值成功率_底稿'!$B:$B,L$1) -> 0
A16: =B14 -> 46056 | C16: 笔数成功率 | D16: =IFERROR(ROUND(D15/D14,6),"0") -> 0 | E16: =IFERROR(ROUND(E15/E14,6),"0") -> 0 | F16: =IFERROR(ROUND(F15/F14,6),"0") -> 0 | G16: =IFERROR(ROUND(G15/G14,6),"0") -> 0 | H16: =IFERROR(ROUND(H15/H14,6),"0") -> 0 | I16: =IFERROR(ROUND(I15/I14,6),"0") -> 0 | J16: =IFERROR(ROUND(J15/J14,6),"0") -> 0 | K16: =IFERROR(ROUND(K15/K14,6),"0") -> 0 | L16: =IFERROR(ROUND(L15/L14,6),"0") -> 0
A17: =B14 -> 46056 | C17: 申请金额 | D17: =SUMIFS('渠道充值成功率_底稿'!$D:$D,'渠道充值成功率_底稿'!$A:$A,$A18,'渠道充值成功率_底稿'!$B:$B,D$1) -> 0 | E17: =SUMIFS('渠道充值成功率_底稿'!$D:$D,'渠道充值成功率_底稿'!$A:$A,$A17,'渠道充值成功率_底稿'!$B:$B,E$1) -> 0 | F17: =SUMIFS('渠道充值成功率_底稿'!$D:$D,'渠道充值成功率_底稿'!$A:$A,$A17,'渠道充值成功率_底稿'!$B:$B,F$1) -> 0 | G17: =SUMIFS('渠道充值成功率_底稿'!$D:$D,'渠道充值成功率_底稿'!$A:$A,$A17,'渠道充值成功率_底稿'!$B:$B,G$1) -> 0 | H17: =SUMIFS('渠道充值成功率_底稿'!$D:$D,'渠道充值成功率_底稿'!$A:$A,$A17,'渠道充值成功率_底稿'!$B:$B,H$1) -> 0 | I17: =SUMIFS('渠道充值成功率_底稿'!$D:$D,'渠道充值成功率_底稿'!$A:$A,$A17,'渠道充值成功率_底稿'!$B:$B,I$1) -> 0 | J17: =SUMIFS('渠道充值成功率_底稿'!$D:$D,'渠道充值成功率_底稿'!$A:$A,$A17,'渠道充值成功率_底稿'!$B:$B,J$1) -> 0 | K17: =SUMIFS('渠道充值成功率_底稿'!$D:$D,'渠道充值成功率_底稿'!$A:$A,$A17,'渠道充值成功率_底稿'!$B:$B,K$1) -> 0 | L17: =SUMIFS('渠道充值成功率_底稿'!$D:$D,'渠道充值成功率_底稿'!$A:$A,$A17,'渠道充值成功率_底稿'!$B:$B,L$1) -> 0
A18: =B14 -> 46056 | C18: 到账金额 | D18: =SUMIFS('渠道充值成功率_底稿'!$G:$G,'渠道充值成功率_底稿'!$A:$A,$A19,'渠道充值成功率_底稿'!$B:$B,D$1) -> 0 | E18: =SUMIFS('渠道充值成功率_底稿'!$G:$G,'渠道充值成功率_底稿'!$A:$A,$A18,'渠道充值成功率_底稿'!$B:$B,E$1) -> 0 | F18: =SUMIFS('渠道充值成功率_底稿'!$G:$G,'渠道充值成功率_底稿'!$A:$A,$A18,'渠道充值成功率_底稿'!$B:$B,F$1) -> 0 | G18: =SUMIFS('渠道充值成功率_底稿'!$G:$G,'渠道充值成功率_底稿'!$A:$A,$A18,'渠道充值成功率_底稿'!$B:$B,G$1) -> 0 | H18: =SUMIFS('渠道充值成功率_底稿'!$G:$G,'渠道充值成功率_底稿'!$A:$A,$A18,'渠道充值成功率_底稿'!$B:$B,H$1) -> 0 | I18: =SUMIFS('渠道充值成功率_底稿'!$G:$G,'渠道充值成功率_底稿'!$A:$A,$A18,'渠道充值成功率_底稿'!$B:$B,I$1) -> 0 | J18: =SUMIFS('渠道充值成功率_底稿'!$G:$G,'渠道充值成功率_底稿'!$A:$A,$A18,'渠道充值成功率_底稿'!$B:$B,J$1) -> 0 | K18: =SUMIFS('渠道充值成功率_底稿'!$G:$G,'渠道充值成功率_底稿'!$A:$A,$A18,'渠道充值成功率_底稿'!$B:$B,K$1) -> 0 | L18: =SUMIFS('渠道充值成功率_底稿'!$G:$G,'渠道充值成功率_底稿'!$A:$A,$A18,'渠道充值成功率_底稿'!$B:$B,L$1) -> 0
A19: =B14 -> 46056 | C19: 金额成功率 | D19: =IFERROR(ROUND(D18/D17,6),"0") -> 0 | E19: =IFERROR(ROUND(E18/E17,6),"0") -> 0 | F19: =IFERROR(ROUND(F18/F17,6),"0") -> 0 | G19: =IFERROR(ROUND(G18/G17,6),"0") -> 0 | H19: =IFERROR(ROUND(H18/H17,6),"0") -> 0 | I19: =IFERROR(ROUND(I18/I17,6),"0") -> 0 | J19: =IFERROR(ROUND(J18/J17,6),"0") -> 0 | K19: =IFERROR(ROUND(K18/K17,6),"0") -> 0 | L19: =IFERROR(ROUND(L18/L17,6),"0") -> 0
A20: =B20 -> 46057 | B20: =B14+1 -> 46057 | C20: 申请笔数 | D20: =SUMIFS('渠道充值成功率_底稿'!$C:$C,'渠道充值成功率_底稿'!$A:$A,$A20,'渠道充值成功率_底稿'!$B:$B,D$1) -> 0 | E20: =SUMIFS('渠道充值成功率_底稿'!$C:$C,'渠道充值成功率_底稿'!$A:$A,$A20,'渠道充值成功率_底稿'!$B:$B,E$1) -> 0 | F20: =SUMIFS('渠道充值成功率_底稿'!$C:$C,'渠道充值成功率_底稿'!$A:$A,$A20,'渠道充值成功率_底稿'!$B:$B,F$1) -> 0 | G20: =SUMIFS('渠道充值成功率_底稿'!$C:$C,'渠道充值成功率_底稿'!$A:$A,$A20,'渠道充值成功率_底稿'!$B:$B,G$1) -> 0 | H20: =SUMIFS('渠道充值成功率_底稿'!$C:$C,'渠道充值成功率_底稿'!$A:$A,$A20,'渠道充值成功率_底稿'!$B:$B,H$1) -> 0 | I20: =SUMIFS('渠道充值成功率_底稿'!$C:$C,'渠道充值成功率_底稿'!$A:$A,$A20,'渠道充值成功率_底稿'!$B:$B,I$1) -> 0 | J20: =SUMIFS('渠道充值成功率_底稿'!$C:$C,'渠道充值成功率_底稿'!$A:$A,$A20,'渠道充值成功率_底稿'!$B:$B,J$1) -> 0 | K20: =SUMIFS('渠道充值成功率_底稿'!$C:$C,'渠道充值成功率_底稿'!$A:$A,$A20,'渠道充值成功率_底稿'!$B:$B,K$1) -> 0 | L20: =SUMIFS('渠道充值成功率_底稿'!$C:$C,'渠道充值成功率_底稿'!$A:$A,$A20,'渠道充值成功率_底稿'!$B:$B,L$1) -> 0
A21: =B20 -> 46057 | C21: 到账笔数 | D21: =SUMIFS('渠道充值成功率_底稿'!$F:$F,'渠道充值成功率_底稿'!$A:$A,$A21,'渠道充值成功率_底稿'!$B:$B,D$1) -> 0 | E21: =SUMIFS('渠道充值成功率_底稿'!$F:$F,'渠道充值成功率_底稿'!$A:$A,$A21,'渠道充值成功率_底稿'!$B:$B,E$1) -> 0 | F21: =SUMIFS('渠道充值成功率_底稿'!$F:$F,'渠道充值成功率_底稿'!$A:$A,$A21,'渠道充值成功率_底稿'!$B:$B,F$1) -> 0 | G21: =SUMIFS('渠道充值成功率_底稿'!$F:$F,'渠道充值成功率_底稿'!$A:$A,$A21,'渠道充值成功率_底稿'!$B:$B,G$1) -> 0 | H21: =SUMIFS('渠道充值成功率_底稿'!$F:$F,'渠道充值成功率_底稿'!$A:$A,$A21,'渠道充值成功率_底稿'!$B:$B,H$1) -> 0 | I21: =SUMIFS('渠道充值成功率_底稿'!$F:$F,'渠道充值成功率_底稿'!$A:$A,$A21,'渠道充值成功率_底稿'!$B:$B,I$1) -> 0 | J21: =SUMIFS('渠道充值成功率_底稿'!$F:$F,'渠道充值成功率_底稿'!$A:$A,$A21,'渠道充值成功率_底稿'!$B:$B,J$1) -> 0 | K21: =SUMIFS('渠道充值成功率_底稿'!$F:$F,'渠道充值成功率_底稿'!$A:$A,$A21,'渠道充值成功率_底稿'!$B:$B,K$1) -> 0 | L21: =SUMIFS('渠道充值成功率_底稿'!$F:$F,'渠道充值成功率_底稿'!$A:$A,$A21,'渠道充值成功率_底稿'!$B:$B,L$1) -> 0
A22: =B20 -> 46057 | C22: 笔数成功率 | D22: =IFERROR(ROUND(D21/D20,6),"0") -> 0 | E22: =IFERROR(ROUND(E21/E20,6),"0") -> 0 | F22: =IFERROR(ROUND(F21/F20,6),"0") -> 0 | G22: =IFERROR(ROUND(G21/G20,6),"0") -> 0 | H22: =IFERROR(ROUND(H21/H20,6),"0") -> 0 | I22: =IFERROR(ROUND(I21/I20,6),"0") -> 0 | J22: =IFERROR(ROUND(J21/J20,6),"0") -> 0 | K22: =IFERROR(ROUND(K21/K20,6),"0") -> 0 | L22: =IFERROR(ROUND(L21/L20,6),"0") -> 0
A23: =B20 -> 46057 | C23: 申请金额 | D23: =SUMIFS('渠道充值成功率_底稿'!$D:$D,'渠道充值成功率_底稿'!$A:$A,$A24,'渠道充值成功率_底稿'!$B:$B,D$1) -> 0 | E23: =SUMIFS('渠道充值成功率_底稿'!$D:$D,'渠道充值成功率_底稿'!$A:$A,$A23,'渠道充值成功率_底稿'!$B:$B,E$1) -> 0 | F23: =SUMIFS('渠道充值成功率_底稿'!$D:$D,'渠道充值成功率_底稿'!$A:$A,$A23,'渠道充值成功率_底稿'!$B:$B,F$1) -> 0 | G23: =SUMIFS('渠道充值成功率_底稿'!$D:$D,'渠道充值成功率_底稿'!$A:$A,$A23,'渠道充值成功率_底稿'!$B:$B,G$1) -> 0 | H23: =SUMIFS('渠道充值成功率_底稿'!$D:$D,'渠道充值成功率_底稿'!$A:$A,$A23,'渠道充值成功率_底稿'!$B:$B,H$1) -> 0 | I23: =SUMIFS('渠道充值成功率_底稿'!$D:$D,'渠道充值成功率_底稿'!$A:$A,$A23,'渠道充值成功率_底稿'!$B:$B,I$1) -> 0 | J23: =SUMIFS('渠道充值成功率_底稿'!$D:$D,'渠道充值成功率_底稿'!$A:$A,$A23,'渠道充值成功率_底稿'!$B:$B,J$1) -> 0 | K23: =SUMIFS('渠道充值成功率_底稿'!$D:$D,'渠道充值成功率_底稿'!$A:$A,$A23,'渠道充值成功率_底稿'!$B:$B,K$1) -> 0 | L23: =SUMIFS('渠道充值成功率_底稿'!$D:$D,'渠道充值成功率_底稿'!$A:$A,$A23,'渠道充值成功率_底稿'!$B:$B,L$1) -> 0
A24: =B20 -> 46057 | C24: 到账金额 | D24: =SUMIFS('渠道充值成功率_底稿'!$G:$G,'渠道充值成功率_底稿'!$A:$A,$A25,'渠道充值成功率_底稿'!$B:$B,D$1) -> 0 | E24: =SUMIFS('渠道充值成功率_底稿'!$G:$G,'渠道充值成功率_底稿'!$A:$A,$A24,'渠道充值成功率_底稿'!$B:$B,E$1) -> 0 | F24: =SUMIFS('渠道充值成功率_底稿'!$G:$G,'渠道充值成功率_底稿'!$A:$A,$A24,'渠道充值成功率_底稿'!$B:$B,F$1) -> 0 | G24: =SUMIFS('渠道充值成功率_底稿'!$G:$G,'渠道充值成功率_底稿'!$A:$A,$A24,'渠道充值成功率_底稿'!$B:$B,G$1) -> 0 | H24: =SUMIFS('渠道充值成功率_底稿'!$G:$G,'渠道充值成功率_底稿'!$A:$A,$A24,'渠道充值成功率_底稿'!$B:$B,H$1) -> 0 | I24: =SUMIFS('渠道充值成功率_底稿'!$G:$G,'渠道充值成功率_底稿'!$A:$A,$A24,'渠道充值成功率_底稿'!$B:$B,I$1) -> 0 | J24: =SUMIFS('渠道充值成功率_底稿'!$G:$G,'渠道充值成功率_底稿'!$A:$A,$A24,'渠道充值成功率_底稿'!$B:$B,J$1) -> 0 | K24: =SUMIFS('渠道充值成功率_底稿'!$G:$G,'渠道充值成功率_底稿'!$A:$A,$A24,'渠道充值成功率_底稿'!$B:$B,K$1) -> 0 | L24: =SUMIFS('渠道充值成功率_底稿'!$G:$G,'渠道充值成功率_底稿'!$A:$A,$A24,'渠道充值成功率_底稿'!$B:$B,L$1) -> 0
A25: =B20 -> 46057 | C25: 金额成功率 | D25: =IFERROR(ROUND(D24/D23,6),"0") -> 0 | E25: =IFERROR(ROUND(E24/E23,6),"0") -> 0 | F25: =IFERROR(ROUND(F24/F23,6),"0") -> 0 | G25: =IFERROR(ROUND(G24/G23,6),"0") -> 0 | H25: =IFERROR(ROUND(H24/H23,6),"0") -> 0 | I25: =IFERROR(ROUND(I24/I23,6),"0") -> 0 | J25: =IFERROR(ROUND(J24/J23,6),"0") -> 0 | K25: =IFERROR(ROUND(K24/K23,6),"0") -> 0 | L25: =IFERROR(ROUND(L24/L23,6),"0") -> 0
A26: =B26 -> 46058 | B26: =B20+1 -> 46058 | C26: 申请笔数 | D26: =SUMIFS('渠道充值成功率_底稿'!$C:$C,'渠道充值成功率_底稿'!$A:$A,$A26,'渠道充值成功率_底稿'!$B:$B,D$1) -> 0 | E26: =SUMIFS('渠道充值成功率_底稿'!$C:$C,'渠道充值成功率_底稿'!$A:$A,$A26,'渠道充值成功率_底稿'!$B:$B,E$1) -> 0 | F26: =SUMIFS('渠道充值成功率_底稿'!$C:$C,'渠道充值成功率_底稿'!$A:$A,$A26,'渠道充值成功率_底稿'!$B:$B,F$1) -> 0 | G26: =SUMIFS('渠道充值成功率_底稿'!$C:$C,'渠道充值成功率_底稿'!$A:$A,$A26,'渠道充值成功率_底稿'!$B:$B,G$1) -> 0 | H26: =SUMIFS('渠道充值成功率_底稿'!$C:$C,'渠道充值成功率_底稿'!$A:$A,$A26,'渠道充值成功率_底稿'!$B:$B,H$1) -> 0 | I26: =SUMIFS('渠道充值成功率_底稿'!$C:$C,'渠道充值成功率_底稿'!$A:$A,$A26,'渠道充值成功率_底稿'!$B:$B,I$1) -> 0 | J26: =SUMIFS('渠道充值成功率_底稿'!$C:$C,'渠道充值成功率_底稿'!$A:$A,$A26,'渠道充值成功率_底稿'!$B:$B,J$1) -> 0 | K26: =SUMIFS('渠道充值成功率_底稿'!$C:$C,'渠道充值成功率_底稿'!$A:$A,$A26,'渠道充值成功率_底稿'!$B:$B,K$1) -> 0 | L26: =SUMIFS('渠道充值成功率_底稿'!$C:$C,'渠道充值成功率_底稿'!$A:$A,$A26,'渠道充值成功率_底稿'!$B:$B,L$1) -> 0
A27: =B26 -> 46058 | C27: 到账笔数 | D27: =SUMIFS('渠道充值成功率_底稿'!$F:$F,'渠道充值成功率_底稿'!$A:$A,$A27,'渠道充值成功率_底稿'!$B:$B,D$1) -> 0 | E27: =SUMIFS('渠道充值成功率_底稿'!$F:$F,'渠道充值成功率_底稿'!$A:$A,$A27,'渠道充值成功率_底稿'!$B:$B,E$1) -> 0 | F27: =SUMIFS('渠道充值成功率_底稿'!$F:$F,'渠道充值成功率_底稿'!$A:$A,$A27,'渠道充值成功率_底稿'!$B:$B,F$1) -> 0 | G27: =SUMIFS('渠道充值成功率_底稿'!$F:$F,'渠道充值成功率_底稿'!$A:$A,$A27,'渠道充值成功率_底稿'!$B:$B,G$1) -> 0 | H27: =SUMIFS('渠道充值成功率_底稿'!$F:$F,'渠道充值成功率_底稿'!$A:$A,$A27,'渠道充值成功率_底稿'!$B:$B,H$1) -> 0 | I27: =SUMIFS('渠道充值成功率_底稿'!$F:$F,'渠道充值成功率_底稿'!$A:$A,$A27,'渠道充值成功率_底稿'!$B:$B,I$1) -> 0 | J27: =SUMIFS('渠道充值成功率_底稿'!$F:$F,'渠道充值成功率_底稿'!$A:$A,$A27,'渠道充值成功率_底稿'!$B:$B,J$1) -> 0 | K27: =SUMIFS('渠道充值成功率_底稿'!$F:$F,'渠道充值成功率_底稿'!$A:$A,$A27,'渠道充值成功率_底稿'!$B:$B,K$1) -> 0 | L27: =SUMIFS('渠道充值成功率_底稿'!$F:$F,'渠道充值成功率_底稿'!$A:$A,$A27,'渠道充值成功率_底稿'!$B:$B,L$1) -> 0
A28: =B26 -> 46058 | C28: 笔数成功率 | D28: =IFERROR(ROUND(D27/D26,6),"0") -> 0 | E28: =IFERROR(ROUND(E27/E26,6),"0") -> 0 | F28: =IFERROR(ROUND(F27/F26,6),"0") -> 0 | G28: =IFERROR(ROUND(G27/G26,6),"0") -> 0 | H28: =IFERROR(ROUND(H27/H26,6),"0") -> 0 | I28: =IFERROR(ROUND(I27/I26,6),"0") -> 0 | J28: =IFERROR(ROUND(J27/J26,6),"0") -> 0 | K28: =IFERROR(ROUND(K27/K26,6),"0") -> 0 | L28: =IFERROR(ROUND(L27/L26,6),"0") -> 0
A29: =B26 -> 46058 | C29: 申请金额 | D29: =SUMIFS('渠道充值成功率_底稿'!$D:$D,'渠道充值成功率_底稿'!$A:$A,$A30,'渠道充值成功率_底稿'!$B:$B,D$1) -> 0 | E29: =SUMIFS('渠道充值成功率_底稿'!$D:$D,'渠道充值成功率_底稿'!$A:$A,$A29,'渠道充值成功率_底稿'!$B:$B,E$1) -> 0 | F29: =SUMIFS('渠道充值成功率_底稿'!$D:$D,'渠道充值成功率_底稿'!$A:$A,$A29,'渠道充值成功率_底稿'!$B:$B,F$1) -> 0 | G29: =SUMIFS('渠道充值成功率_底稿'!$D:$D,'渠道充值成功率_底稿'!$A:$A,$A29,'渠道充值成功率_底稿'!$B:$B,G$1) -> 0 | H29: =SUMIFS('渠道充值成功率_底稿'!$D:$D,'渠道充值成功率_底稿'!$A:$A,$A29,'渠道充值成功率_底稿'!$B:$B,H$1) -> 0 | I29: =SUMIFS('渠道充值成功率_底稿'!$D:$D,'渠道充值成功率_底稿'!$A:$A,$A29,'渠道充值成功率_底稿'!$B:$B,I$1) -> 0 | J29: =SUMIFS('渠道充值成功率_底稿'!$D:$D,'渠道充值成功率_底稿'!$A:$A,$A29,'渠道充值成功率_底稿'!$B:$B,J$1) -> 0 | K29: =SUMIFS('渠道充值成功率_底稿'!$D:$D,'渠道充值成功率_底稿'!$A:$A,$A29,'渠道充值成功率_底稿'!$B:$B,K$1) -> 0 | L29: =SUMIFS('渠道充值成功率_底稿'!$D:$D,'渠道充值成功率_底稿'!$A:$A,$A29,'渠道充值成功率_底稿'!$B:$B,L$1) -> 0
A30: =B26 -> 46058 | C30: 到账金额 | D30: =SUMIFS('渠道充值成功率_底稿'!$G:$G,'渠道充值成功率_底稿'!$A:$A,$A31,'渠道充值成功率_底稿'!$B:$B,D$1) -> 0 | E30: =SUMIFS('渠道充值成功率_底稿'!$G:$G,'渠道充值成功率_底稿'!$A:$A,$A30,'渠道充值成功率_底稿'!$B:$B,E$1) -> 0 | F30: =SUMIFS('渠道充值成功率_底稿'!$G:$G,'渠道充值成功率_底稿'!$A:$A,$A30,'渠道充值成功率_底稿'!$B:$B,F$1) -> 0 | G30: =SUMIFS('渠道充值成功率_底稿'!$G:$G,'渠道充值成功率_底稿'!$A:$A,$A30,'渠道充值成功率_底稿'!$B:$B,G$1) -> 0 | H30: =SUMIFS('渠道充值成功率_底稿'!$G:$G,'渠道充值成功率_底稿'!$A:$A,$A30,'渠道充值成功率_底稿'!$B:$B,H$1) -> 0 | I30: =SUMIFS('渠道充值成功率_底稿'!$G:$G,'渠道充值成功率_底稿'!$A:$A,$A30,'渠道充值成功率_底稿'!$B:$B,I$1) -> 0 | J30: =SUMIFS('渠道充值成功率_底稿'!$G:$G,'渠道充值成功率_底稿'!$A:$A,$A30,'渠道充值成功率_底稿'!$B:$B,J$1) -> 0 | K30: =SUMIFS('渠道充值成功率_底稿'!$G:$G,'渠道充值成功率_底稿'!$A:$A,$A30,'渠道充值成功率_底稿'!$B:$B,K$1) -> 0 | L30: =SUMIFS('渠道充值成功率_底稿'!$G:$G,'渠道充值成功率_底稿'!$A:$A,$A30,'渠道充值成功率_底稿'!$B:$B,L$1) -> 0
A31: =B26 -> 46058 | C31: 金额成功率 | D31: =IFERROR(ROUND(D30/D29,6),"0") -> 0 | E31: =IFERROR(ROUND(E30/E29,6),"0") -> 0 | F31: =IFERROR(ROUND(F30/F29,6),"0") -> 0 | G31: =IFERROR(ROUND(G30/G29,6),"0") -> 0 | H31: =IFERROR(ROUND(H30/H29,6),"0") -> 0 | I31: =IFERROR(ROUND(I30/I29,6),"0") -> 0 | J31: =IFERROR(ROUND(J30/J29,6),"0") -> 0 | K31: =IFERROR(ROUND(K30/K29,6),"0") -> 0 | L31: =IFERROR(ROUND(L30/L29,6),"0") -> 0
A32: =B32 -> 46059 | B32: =B26+1 -> 46059 | C32: 申请笔数 | D32: =SUMIFS('渠道充值成功率_底稿'!$C:$C,'渠道充值成功率_底稿'!$A:$A,$A32,'渠道充值成功率_底稿'!$B:$B,D$1) -> 0 | E32: =SUMIFS('渠道充值成功率_底稿'!$C:$C,'渠道充值成功率_底稿'!$A:$A,$A32,'渠道充值成功率_底稿'!$B:$B,E$1) -> 0 | F32: =SUMIFS('渠道充值成功率_底稿'!$C:$C,'渠道充值成功率_底稿'!$A:$A,$A32,'渠道充值成功率_底稿'!$B:$B,F$1) -> 0 | G32: =SUMIFS('渠道充值成功率_底稿'!$C:$C,'渠道充值成功率_底稿'!$A:$A,$A32,'渠道充值成功率_底稿'!$B:$B,G$1) -> 0 | H32: =SUMIFS('渠道充值成功率_底稿'!$C:$C,'渠道充值成功率_底稿'!$A:$A,$A32,'渠道充值成功率_底稿'!$B:$B,H$1) -> 0 | I32: =SUMIFS('渠道充值成功率_底稿'!$C:$C,'渠道充值成功率_底稿'!$A:$A,$A32,'渠道充值成功率_底稿'!$B:$B,I$1) -> 0 | J32: =SUMIFS('渠道充值成功率_底稿'!$C:$C,'渠道充值成功率_底稿'!$A:$A,$A32,'渠道充值成功率_底稿'!$B:$B,J$1) -> 0 | K32: =SUMIFS('渠道充值成功率_底稿'!$C:$C,'渠道充值成功率_底稿'!$A:$A,$A32,'渠道充值成功率_底稿'!$B:$B,K$1) -> 0 | L32: =SUMIFS('渠道充值成功率_底稿'!$C:$C,'渠道充值成功率_底稿'!$A:$A,$A32,'渠道充值成功率_底稿'!$B:$B,L$1) -> 0
A33: =B32 -> 46059 | C33: 到账笔数 | D33: =SUMIFS('渠道充值成功率_底稿'!$F:$F,'渠道充值成功率_底稿'!$A:$A,$A33,'渠道充值成功率_底稿'!$B:$B,D$1) -> 0 | E33: =SUMIFS('渠道充值成功率_底稿'!$F:$F,'渠道充值成功率_底稿'!$A:$A,$A33,'渠道充值成功率_底稿'!$B:$B,E$1) -> 0 | F33: =SUMIFS('渠道充值成功率_底稿'!$F:$F,'渠道充值成功率_底稿'!$A:$A,$A33,'渠道充值成功率_底稿'!$B:$B,F$1) -> 0 | G33: =SUMIFS('渠道充值成功率_底稿'!$F:$F,'渠道充值成功率_底稿'!$A:$A,$A33,'渠道充值成功率_底稿'!$B:$B,G$1) -> 0 | H33: =SUMIFS('渠道充值成功率_底稿'!$F:$F,'渠道充值成功率_底稿'!$A:$A,$A33,'渠道充值成功率_底稿'!$B:$B,H$1) -> 0 | I33: =SUMIFS('渠道充值成功率_底稿'!$F:$F,'渠道充值成功率_底稿'!$A:$A,$A33,'渠道充值成功率_底稿'!$B:$B,I$1) -> 0 | J33: =SUMIFS('渠道充值成功率_底稿'!$F:$F,'渠道充值成功率_底稿'!$A:$A,$A33,'渠道充值成功率_底稿'!$B:$B,J$1) -> 0 | K33: =SUMIFS('渠道充值成功率_底稿'!$F:$F,'渠道充值成功率_底稿'!$A:$A,$A33,'渠道充值成功率_底稿'!$B:$B,K$1) -> 0 | L33: =SUMIFS('渠道充值成功率_底稿'!$F:$F,'渠道充值成功率_底稿'!$A:$A,$A33,'渠道充值成功率_底稿'!$B:$B,L$1) -> 0
A34: =B32 -> 46059 | C34: 笔数成功率 | D34: =IFERROR(ROUND(D33/D32,6),"0") -> 0 | E34: =IFERROR(ROUND(E33/E32,6),"0") -> 0 | F34: =IFERROR(ROUND(F33/F32,6),"0") -> 0 | G34: =IFERROR(ROUND(G33/G32,6),"0") -> 0 | H34: =IFERROR(ROUND(H33/H32,6),"0") -> 0 | I34: =IFERROR(ROUND(I33/I32,6),"0") -> 0 | J34: =IFERROR(ROUND(J33/J32,6),"0") -> 0 | K34: =IFERROR(ROUND(K33/K32,6),"0") -> 0 | L34: =IFERROR(ROUND(L33/L32,6),"0") -> 0
A35: =B32 -> 46059 | C35: 申请金额 | D35: =SUMIFS('渠道充值成功率_底稿'!$D:$D,'渠道充值成功率_底稿'!$A:$A,$A36,'渠道充值成功率_底稿'!$B:$B,D$1) -> 0 | E35: =SUMIFS('渠道充值成功率_底稿'!$D:$D,'渠道充值成功率_底稿'!$A:$A,$A35,'渠道充值成功率_底稿'!$B:$B,E$1) -> 0 | F35: =SUMIFS('渠道充值成功率_底稿'!$D:$D,'渠道充值成功率_底稿'!$A:$A,$A35,'渠道充值成功率_底稿'!$B:$B,F$1) -> 0 | G35: =SUMIFS('渠道充值成功率_底稿'!$D:$D,'渠道充值成功率_底稿'!$A:$A,$A35,'渠道充值成功率_底稿'!$B:$B,G$1) -> 0 | H35: =SUMIFS('渠道充值成功率_底稿'!$D:$D,'渠道充值成功率_底稿'!$A:$A,$A35,'渠道充值成功率_底稿'!$B:$B,H$1) -> 0 | I35: =SUMIFS('渠道充值成功率_底稿'!$D:$D,'渠道充值成功率_底稿'!$A:$A,$A35,'渠道充值成功率_底稿'!$B:$B,I$1) -> 0 | J35: =SUMIFS('渠道充值成功率_底稿'!$D:$D,'渠道充值成功率_底稿'!$A:$A,$A35,'渠道充值成功率_底稿'!$B:$B,J$1) -> 0 | K35: =SUMIFS('渠道充值成功率_底稿'!$D:$D,'渠道充值成功率_底稿'!$A:$A,$A35,'渠道充值成功率_底稿'!$B:$B,K$1) -> 0 | L35: =SUMIFS('渠道充值成功率_底稿'!$D:$D,'渠道充值成功率_底稿'!$A:$A,$A35,'渠道充值成功率_底稿'!$B:$B,L$1) -> 0
A36: =B32 -> 46059 | C36: 到账金额 | D36: =SUMIFS('渠道充值成功率_底稿'!$G:$G,'渠道充值成功率_底稿'!$A:$A,$A37,'渠道充值成功率_底稿'!$B:$B,D$1) -> 0 | E36: =SUMIFS('渠道充值成功率_底稿'!$G:$G,'渠道充值成功率_底稿'!$A:$A,$A36,'渠道充值成功率_底稿'!$B:$B,E$1) -> 0 | F36: =SUMIFS('渠道充值成功率_底稿'!$G:$G,'渠道充值成功率_底稿'!$A:$A,$A36,'渠道充值成功率_底稿'!$B:$B,F$1) -> 0 | G36: =SUMIFS('渠道充值成功率_底稿'!$G:$G,'渠道充值成功率_底稿'!$A:$A,$A36,'渠道充值成功率_底稿'!$B:$B,G$1) -> 0 | H36: =SUMIFS('渠道充值成功率_底稿'!$G:$G,'渠道充值成功率_底稿'!$A:$A,$A36,'渠道充值成功率_底稿'!$B:$B,H$1) -> 0 | I36: =SUMIFS('渠道充值成功率_底稿'!$G:$G,'渠道充值成功率_底稿'!$A:$A,$A36,'渠道充值成功率_底稿'!$B:$B,I$1) -> 0 | J36: =SUMIFS('渠道充值成功率_底稿'!$G:$G,'渠道充值成功率_底稿'!$A:$A,$A36,'渠道充值成功率_底稿'!$B:$B,J$1) -> 0 | K36: =SUMIFS('渠道充值成功率_底稿'!$G:$G,'渠道充值成功率_底稿'!$A:$A,$A36,'渠道充值成功率_底稿'!$B:$B,K$1) -> 0 | L36: =SUMIFS('渠道充值成功率_底稿'!$G:$G,'渠道充值成功率_底稿'!$A:$A,$A36,'渠道充值成功率_底稿'!$B:$B,L$1) -> 0
A37: =B32 -> 46059 | C37: 金额成功率 | D37: =IFERROR(ROUND(D36/D35,6),"0") -> 0 | E37: =IFERROR(ROUND(E36/E35,6),"0") -> 0 | F37: =IFERROR(ROUND(F36/F35,6),"0") -> 0 | G37: =IFERROR(ROUND(G36/G35,6),"0") -> 0 | H37: =IFERROR(ROUND(H36/H35,6),"0") -> 0 | I37: =IFERROR(ROUND(I36/I35,6),"0") -> 0 | J37: =IFERROR(ROUND(J36/J35,6),"0") -> 0 | K37: =IFERROR(ROUND(K36/K35,6),"0") -> 0 | L37: =IFERROR(ROUND(L36/L35,6),"0") -> 0
A38: =B38 -> 46060 | B38: =B32+1 -> 46060 | C38: 申请笔数 | D38: =SUMIFS('渠道充值成功率_底稿'!$C:$C,'渠道充值成功率_底稿'!$A:$A,$A38,'渠道充值成功率_底稿'!$B:$B,D$1) -> 0 | E38: =SUMIFS('渠道充值成功率_底稿'!$C:$C,'渠道充值成功率_底稿'!$A:$A,$A38,'渠道充值成功率_底稿'!$B:$B,E$1) -> 0 | F38: =SUMIFS('渠道充值成功率_底稿'!$C:$C,'渠道充值成功率_底稿'!$A:$A,$A38,'渠道充值成功率_底稿'!$B:$B,F$1) -> 0 | G38: =SUMIFS('渠道充值成功率_底稿'!$C:$C,'渠道充值成功率_底稿'!$A:$A,$A38,'渠道充值成功率_底稿'!$B:$B,G$1) -> 0 | H38: =SUMIFS('渠道充值成功率_底稿'!$C:$C,'渠道充值成功率_底稿'!$A:$A,$A38,'渠道充值成功率_底稿'!$B:$B,H$1) -> 0 | I38: =SUMIFS('渠道充值成功率_底稿'!$C:$C,'渠道充值成功率_底稿'!$A:$A,$A38,'渠道充值成功率_底稿'!$B:$B,I$1) -> 0 | J38: =SUMIFS('渠道充值成功率_底稿'!$C:$C,'渠道充值成功率_底稿'!$A:$A,$A38,'渠道充值成功率_底稿'!$B:$B,J$1) -> 0 | K38: =SUMIFS('渠道充值成功率_底稿'!$C:$C,'渠道充值成功率_底稿'!$A:$A,$A38,'渠道充值成功率_底稿'!$B:$B,K$1) -> 0 | L38: =SUMIFS('渠道充值成功率_底稿'!$C:$C,'渠道充值成功率_底稿'!$A:$A,$A38,'渠道充值成功率_底稿'!$B:$B,L$1) -> 0
A39: =B38 -> 46060 | C39: 到账笔数 | D39: =SUMIFS('渠道充值成功率_底稿'!$F:$F,'渠道充值成功率_底稿'!$A:$A,$A39,'渠道充值成功率_底稿'!$B:$B,D$1) -> 0 | E39: =SUMIFS('渠道充值成功率_底稿'!$F:$F,'渠道充值成功率_底稿'!$A:$A,$A39,'渠道充值成功率_底稿'!$B:$B,E$1) -> 0 | F39: =SUMIFS('渠道充值成功率_底稿'!$F:$F,'渠道充值成功率_底稿'!$A:$A,$A39,'渠道充值成功率_底稿'!$B:$B,F$1) -> 0 | G39: =SUMIFS('渠道充值成功率_底稿'!$F:$F,'渠道充值成功率_底稿'!$A:$A,$A39,'渠道充值成功率_底稿'!$B:$B,G$1) -> 0 | H39: =SUMIFS('渠道充值成功率_底稿'!$F:$F,'渠道充值成功率_底稿'!$A:$A,$A39,'渠道充值成功率_底稿'!$B:$B,H$1) -> 0 | I39: =SUMIFS('渠道充值成功率_底稿'!$F:$F,'渠道充值成功率_底稿'!$A:$A,$A39,'渠道充值成功率_底稿'!$B:$B,I$1) -> 0 | J39: =SUMIFS('渠道充值成功率_底稿'!$F:$F,'渠道充值成功率_底稿'!$A:$A,$A39,'渠道充值成功率_底稿'!$B:$B,J$1) -> 0 | K39: =SUMIFS('渠道充值成功率_底稿'!$F:$F,'渠道充值成功率_底稿'!$A:$A,$A39,'渠道充值成功率_底稿'!$B:$B,K$1) -> 0 | L39: =SUMIFS('渠道充值成功率_底稿'!$F:$F,'渠道充值成功率_底稿'!$A:$A,$A39,'渠道充值成功率_底稿'!$B:$B,L$1) -> 0
A40: =B38 -> 46060 | C40: 笔数成功率 | D40: =IFERROR(ROUND(D39/D38,6),"0") -> 0 | E40: =IFERROR(ROUND(E39/E38,6),"0") -> 0 | F40: =IFERROR(ROUND(F39/F38,6),"0") -> 0 | G40: =IFERROR(ROUND(G39/G38,6),"0") -> 0 | H40: =IFERROR(ROUND(H39/H38,6),"0") -> 0 | I40: =IFERROR(ROUND(I39/I38,6),"0") -> 0 | J40: =IFERROR(ROUND(J39/J38,6),"0") -> 0 | K40: =IFERROR(ROUND(K39/K38,6),"0") -> 0 | L40: =IFERROR(ROUND(L39/L38,6),"0") -> 0
A41: =B38 -> 46060 | C41: 申请金额 | D41: =SUMIFS('渠道充值成功率_底稿'!$D:$D,'渠道充值成功率_底稿'!$A:$A,$A42,'渠道充值成功率_底稿'!$B:$B,D$1) -> 0 | E41: =SUMIFS('渠道充值成功率_底稿'!$D:$D,'渠道充值成功率_底稿'!$A:$A,$A41,'渠道充值成功率_底稿'!$B:$B,E$1) -> 0 | F41: =SUMIFS('渠道充值成功率_底稿'!$D:$D,'渠道充值成功率_底稿'!$A:$A,$A41,'渠道充值成功率_底稿'!$B:$B,F$1) -> 0 | G41: =SUMIFS('渠道充值成功率_底稿'!$D:$D,'渠道充值成功率_底稿'!$A:$A,$A41,'渠道充值成功率_底稿'!$B:$B,G$1) -> 0 | H41: =SUMIFS('渠道充值成功率_底稿'!$D:$D,'渠道充值成功率_底稿'!$A:$A,$A41,'渠道充值成功率_底稿'!$B:$B,H$1) -> 0 | I41: =SUMIFS('渠道充值成功率_底稿'!$D:$D,'渠道充值成功率_底稿'!$A:$A,$A41,'渠道充值成功率_底稿'!$B:$B,I$1) -> 0 | J41: =SUMIFS('渠道充值成功率_底稿'!$D:$D,'渠道充值成功率_底稿'!$A:$A,$A41,'渠道充值成功率_底稿'!$B:$B,J$1) -> 0 | K41: =SUMIFS('渠道充值成功率_底稿'!$D:$D,'渠道充值成功率_底稿'!$A:$A,$A41,'渠道充值成功率_底稿'!$B:$B,K$1) -> 0 | L41: =SUMIFS('渠道充值成功率_底稿'!$D:$D,'渠道充值成功率_底稿'!$A:$A,$A41,'渠道充值成功率_底稿'!$B:$B,L$1) -> 0
A42: =B38 -> 46060 | C42: 到账金额 | D42: =SUMIFS('渠道充值成功率_底稿'!$G:$G,'渠道充值成功率_底稿'!$A:$A,$A43,'渠道充值成功率_底稿'!$B:$B,D$1) -> 0 | E42: =SUMIFS('渠道充值成功率_底稿'!$G:$G,'渠道充值成功率_底稿'!$A:$A,$A42,'渠道充值成功率_底稿'!$B:$B,E$1) -> 0 | F42: =SUMIFS('渠道充值成功率_底稿'!$G:$G,'渠道充值成功率_底稿'!$A:$A,$A42,'渠道充值成功率_底稿'!$B:$B,F$1) -> 0 | G42: =SUMIFS('渠道充值成功率_底稿'!$G:$G,'渠道充值成功率_底稿'!$A:$A,$A42,'渠道充值成功率_底稿'!$B:$B,G$1) -> 0 | H42: =SUMIFS('渠道充值成功率_底稿'!$G:$G,'渠道充值成功率_底稿'!$A:$A,$A42,'渠道充值成功率_底稿'!$B:$B,H$1) -> 0 | I42: =SUMIFS('渠道充值成功率_底稿'!$G:$G,'渠道充值成功率_底稿'!$A:$A,$A42,'渠道充值成功率_底稿'!$B:$B,I$1) -> 0 | J42: =SUMIFS('渠道充值成功率_底稿'!$G:$G,'渠道充值成功率_底稿'!$A:$A,$A42,'渠道充值成功率_底稿'!$B:$B,J$1) -> 0 | K42: =SUMIFS('渠道充值成功率_底稿'!$G:$G,'渠道充值成功率_底稿'!$A:$A,$A42,'渠道充值成功率_底稿'!$B:$B,K$1) -> 0 | L42: =SUMIFS('渠道充值成功率_底稿'!$G:$G,'渠道充值成功率_底稿'!$A:$A,$A42,'渠道充值成功率_底稿'!$B:$B,L$1) -> 0
A43: =B38 -> 46060 | C43: 金额成功率 | D43: =IFERROR(ROUND(D42/D41,6),"0") -> 0 | E43: =IFERROR(ROUND(E42/E41,6),"0") -> 0 | F43: =IFERROR(ROUND(F42/F41,6),"0") -> 0 | G43: =IFERROR(ROUND(G42/G41,6),"0") -> 0 | H43: =IFERROR(ROUND(H42/H41,6),"0") -> 0 | I43: =IFERROR(ROUND(I42/I41,6),"0") -> 0 | J43: =IFERROR(ROUND(J42/J41,6),"0") -> 0 | K43: =IFERROR(ROUND(K42/K41,6),"0") -> 0 | L43: =IFERROR(ROUND(L42/L41,6),"0") -> 0
A44: =B44 -> 46061 | B44: =B38+1 -> 46061 | C44: 申请笔数 | D44: =SUMIFS('渠道充值成功率_底稿'!$C:$C,'渠道充值成功率_底稿'!$A:$A,$A44,'渠道充值成功率_底稿'!$B:$B,D$1) -> 0 | E44: =SUMIFS('渠道充值成功率_底稿'!$C:$C,'渠道充值成功率_底稿'!$A:$A,$A44,'渠道充值成功率_底稿'!$B:$B,E$1) -> 0 | F44: =SUMIFS('渠道充值成功率_底稿'!$C:$C,'渠道充值成功率_底稿'!$A:$A,$A44,'渠道充值成功率_底稿'!$B:$B,F$1) -> 0 | G44: =SUMIFS('渠道充值成功率_底稿'!$C:$C,'渠道充值成功率_底稿'!$A:$A,$A44,'渠道充值成功率_底稿'!$B:$B,G$1) -> 0 | H44: =SUMIFS('渠道充值成功率_底稿'!$C:$C,'渠道充值成功率_底稿'!$A:$A,$A44,'渠道充值成功率_底稿'!$B:$B,H$1) -> 0 | I44: =SUMIFS('渠道充值成功率_底稿'!$C:$C,'渠道充值成功率_底稿'!$A:$A,$A44,'渠道充值成功率_底稿'!$B:$B,I$1) -> 0 | J44: =SUMIFS('渠道充值成功率_底稿'!$C:$C,'渠道充值成功率_底稿'!$A:$A,$A44,'渠道充值成功率_底稿'!$B:$B,J$1) -> 0 | K44: =SUMIFS('渠道充值成功率_底稿'!$C:$C,'渠道充值成功率_底稿'!$A:$A,$A44,'渠道充值成功率_底稿'!$B:$B,K$1) -> 0 | L44: =SUMIFS('渠道充值成功率_底稿'!$C:$C,'渠道充值成功率_底稿'!$A:$A,$A44,'渠道充值成功率_底稿'!$B:$B,L$1) -> 0
A45: =B44 -> 46061 | C45: 到账笔数 | D45: =SUMIFS('渠道充值成功率_底稿'!$F:$F,'渠道充值成功率_底稿'!$A:$A,$A45,'渠道充值成功率_底稿'!$B:$B,D$1) -> 0 | E45: =SUMIFS('渠道充值成功率_底稿'!$F:$F,'渠道充值成功率_底稿'!$A:$A,$A45,'渠道充值成功率_底稿'!$B:$B,E$1) -> 0 | F45: =SUMIFS('渠道充值成功率_底稿'!$F:$F,'渠道充值成功率_底稿'!$A:$A,$A45,'渠道充值成功率_底稿'!$B:$B,F$1) -> 0 | G45: =SUMIFS('渠道充值成功率_底稿'!$F:$F,'渠道充值成功率_底稿'!$A:$A,$A45,'渠道充值成功率_底稿'!$B:$B,G$1) -> 0 | H45: =SUMIFS('渠道充值成功率_底稿'!$F:$F,'渠道充值成功率_底稿'!$A:$A,$A45,'渠道充值成功率_底稿'!$B:$B,H$1) -> 0 | I45: =SUMIFS('渠道充值成功率_底稿'!$F:$F,'渠道充值成功率_底稿'!$A:$A,$A45,'渠道充值成功率_底稿'!$B:$B,I$1) -> 0 | J45: =SUMIFS('渠道充值成功率_底稿'!$F:$F,'渠道充值成功率_底稿'!$A:$A,$A45,'渠道充值成功率_底稿'!$B:$B,J$1) -> 0 | K45: =SUMIFS('渠道充值成功率_底稿'!$F:$F,'渠道充值成功率_底稿'!$A:$A,$A45,'渠道充值成功率_底稿'!$B:$B,K$1) -> 0 | L45: =SUMIFS('渠道充值成功率_底稿'!$F:$F,'渠道充值成功率_底稿'!$A:$A,$A45,'渠道充值成功率_底稿'!$B:$B,L$1) -> 0
A46: =B44 -> 46061 | C46: 笔数成功率 | D46: =IFERROR(ROUND(D45/D44,6),"0") -> 0 | E46: =IFERROR(ROUND(E45/E44,6),"0") -> 0 | F46: =IFERROR(ROUND(F45/F44,6),"0") -> 0 | G46: =IFERROR(ROUND(G45/G44,6),"0") -> 0 | H46: =IFERROR(ROUND(H45/H44,6),"0") -> 0 | I46: =IFERROR(ROUND(I45/I44,6),"0") -> 0 | J46: =IFERROR(ROUND(J45/J44,6),"0") -> 0 | K46: =IFERROR(ROUND(K45/K44,6),"0") -> 0 | L46: =IFERROR(ROUND(L45/L44,6),"0") -> 0
A47: =B44 -> 46061 | C47: 申请金额 | D47: =SUMIFS('渠道充值成功率_底稿'!$D:$D,'渠道充值成功率_底稿'!$A:$A,$A48,'渠道充值成功率_底稿'!$B:$B,D$1) -> 0 | E47: =SUMIFS('渠道充值成功率_底稿'!$D:$D,'渠道充值成功率_底稿'!$A:$A,$A47,'渠道充值成功率_底稿'!$B:$B,E$1) -> 0 | F47: =SUMIFS('渠道充值成功率_底稿'!$D:$D,'渠道充值成功率_底稿'!$A:$A,$A47,'渠道充值成功率_底稿'!$B:$B,F$1) -> 0 | G47: =SUMIFS('渠道充值成功率_底稿'!$D:$D,'渠道充值成功率_底稿'!$A:$A,$A47,'渠道充值成功率_底稿'!$B:$B,G$1) -> 0 | H47: =SUMIFS('渠道充值成功率_底稿'!$D:$D,'渠道充值成功率_底稿'!$A:$A,$A47,'渠道充值成功率_底稿'!$B:$B,H$1) -> 0 | I47: =SUMIFS('渠道充值成功率_底稿'!$D:$D,'渠道充值成功率_底稿'!$A:$A,$A47,'渠道充值成功率_底稿'!$B:$B,I$1) -> 0 | J47: =SUMIFS('渠道充值成功率_底稿'!$D:$D,'渠道充值成功率_底稿'!$A:$A,$A47,'渠道充值成功率_底稿'!$B:$B,J$1) -> 0 | K47: =SUMIFS('渠道充值成功率_底稿'!$D:$D,'渠道充值成功率_底稿'!$A:$A,$A47,'渠道充值成功率_底稿'!$B:$B,K$1) -> 0 | L47: =SUMIFS('渠道充值成功率_底稿'!$D:$D,'渠道充值成功率_底稿'!$A:$A,$A47,'渠道充值成功率_底稿'!$B:$B,L$1) -> 0
A48: =B44 -> 46061 | C48: 到账金额 | D48: =SUMIFS('渠道充值成功率_底稿'!$G:$G,'渠道充值成功率_底稿'!$A:$A,$A49,'渠道充值成功率_底稿'!$B:$B,D$1) -> 0 | E48: =SUMIFS('渠道充值成功率_底稿'!$G:$G,'渠道充值成功率_底稿'!$A:$A,$A48,'渠道充值成功率_底稿'!$B:$B,E$1) -> 0 | F48: =SUMIFS('渠道充值成功率_底稿'!$G:$G,'渠道充值成功率_底稿'!$A:$A,$A48,'渠道充值成功率_底稿'!$B:$B,F$1) -> 0 | G48: =SUMIFS('渠道充值成功率_底稿'!$G:$G,'渠道充值成功率_底稿'!$A:$A,$A48,'渠道充值成功率_底稿'!$B:$B,G$1) -> 0 | H48: =SUMIFS('渠道充值成功率_底稿'!$G:$G,'渠道充值成功率_底稿'!$A:$A,$A48,'渠道充值成功率_底稿'!$B:$B,H$1) -> 0 | I48: =SUMIFS('渠道充值成功率_底稿'!$G:$G,'渠道充值成功率_底稿'!$A:$A,$A48,'渠道充值成功率_底稿'!$B:$B,I$1) -> 0 | J48: =SUMIFS('渠道充值成功率_底稿'!$G:$G,'渠道充值成功率_底稿'!$A:$A,$A48,'渠道充值成功率_底稿'!$B:$B,J$1) -> 0 | K48: =SUMIFS('渠道充值成功率_底稿'!$G:$G,'渠道充值成功率_底稿'!$A:$A,$A48,'渠道充值成功率_底稿'!$B:$B,K$1) -> 0 | L48: =SUMIFS('渠道充值成功率_底稿'!$G:$G,'渠道充值成功率_底稿'!$A:$A,$A48,'渠道充值成功率_底稿'!$B:$B,L$1) -> 0
A49: =B44 -> 46061 | C49: 金额成功率 | D49: =IFERROR(ROUND(D48/D47,6),"0") -> 0 | E49: =IFERROR(ROUND(E48/E47,6),"0") -> 0 | F49: =IFERROR(ROUND(F48/F47,6),"0") -> 0 | G49: =IFERROR(ROUND(G48/G47,6),"0") -> 0 | H49: =IFERROR(ROUND(H48/H47,6),"0") -> 0 | I49: =IFERROR(ROUND(I48/I47,6),"0") -> 0 | J49: =IFERROR(ROUND(J48/J47,6),"0") -> 0 | K49: =IFERROR(ROUND(K48/K47,6),"0") -> 0 | L49: =IFERROR(ROUND(L48/L47,6),"0") -> 0
A50: =B50 -> 46062 | B50: =B44+1 -> 46062 | C50: 申请笔数 | D50: =SUMIFS('渠道充值成功率_底稿'!$C:$C,'渠道充值成功率_底稿'!$A:$A,$A50,'渠道充值成功率_底稿'!$B:$B,D$1) -> 0 | E50: =SUMIFS('渠道充值成功率_底稿'!$C:$C,'渠道充值成功率_底稿'!$A:$A,$A50,'渠道充值成功率_底稿'!$B:$B,E$1) -> 0 | F50: =SUMIFS('渠道充值成功率_底稿'!$C:$C,'渠道充值成功率_底稿'!$A:$A,$A50,'渠道充值成功率_底稿'!$B:$B,F$1) -> 0 | G50: =SUMIFS('渠道充值成功率_底稿'!$C:$C,'渠道充值成功率_底稿'!$A:$A,$A50,'渠道充值成功率_底稿'!$B:$B,G$1) -> 0 | H50: =SUMIFS('渠道充值成功率_底稿'!$C:$C,'渠道充值成功率_底稿'!$A:$A,$A50,'渠道充值成功率_底稿'!$B:$B,H$1) -> 0 | I50: =SUMIFS('渠道充值成功率_底稿'!$C:$C,'渠道充值成功率_底稿'!$A:$A,$A50,'渠道充值成功率_底稿'!$B:$B,I$1) -> 0 | J50: =SUMIFS('渠道充值成功率_底稿'!$C:$C,'渠道充值成功率_底稿'!$A:$A,$A50,'渠道充值成功率_底稿'!$B:$B,J$1) -> 0 | K50: =SUMIFS('渠道充值成功率_底稿'!$C:$C,'渠道充值成功率_底稿'!$A:$A,$A50,'渠道充值成功率_底稿'!$B:$B,K$1) -> 0 | L50: =SUMIFS('渠道充值成功率_底稿'!$C:$C,'渠道充值成功率_底稿'!$A:$A,$A50,'渠道充值成功率_底稿'!$B:$B,L$1) -> 0
A51: =B50 -> 46062 | C51: 到账笔数 | D51: =SUMIFS('渠道充值成功率_底稿'!$F:$F,'渠道充值成功率_底稿'!$A:$A,$A51,'渠道充值成功率_底稿'!$B:$B,D$1) -> 0 | E51: =SUMIFS('渠道充值成功率_底稿'!$F:$F,'渠道充值成功率_底稿'!$A:$A,$A51,'渠道充值成功率_底稿'!$B:$B,E$1) -> 0 | F51: =SUMIFS('渠道充值成功率_底稿'!$F:$F,'渠道充值成功率_底稿'!$A:$A,$A51,'渠道充值成功率_底稿'!$B:$B,F$1) -> 0 | G51: =SUMIFS('渠道充值成功率_底稿'!$F:$F,'渠道充值成功率_底稿'!$A:$A,$A51,'渠道充值成功率_底稿'!$B:$B,G$1) -> 0 | H51: =SUMIFS('渠道充值成功率_底稿'!$F:$F,'渠道充值成功率_底稿'!$A:$A,$A51,'渠道充值成功率_底稿'!$B:$B,H$1) -> 0 | I51: =SUMIFS('渠道充值成功率_底稿'!$F:$F,'渠道充值成功率_底稿'!$A:$A,$A51,'渠道充值成功率_底稿'!$B:$B,I$1) -> 0 | J51: =SUMIFS('渠道充值成功率_底稿'!$F:$F,'渠道充值成功率_底稿'!$A:$A,$A51,'渠道充值成功率_底稿'!$B:$B,J$1) -> 0 | K51: =SUMIFS('渠道充值成功率_底稿'!$F:$F,'渠道充值成功率_底稿'!$A:$A,$A51,'渠道充值成功率_底稿'!$B:$B,K$1) -> 0 | L51: =SUMIFS('渠道充值成功率_底稿'!$F:$F,'渠道充值成功率_底稿'!$A:$A,$A51,'渠道充值成功率_底稿'!$B:$B,L$1) -> 0
A52: =B50 -> 46062 | C52: 笔数成功率 | D52: =IFERROR(ROUND(D51/D50,6),"0") -> 0 | E52: =IFERROR(ROUND(E51/E50,6),"0") -> 0 | F52: =IFERROR(ROUND(F51/F50,6),"0") -> 0 | G52: =IFERROR(ROUND(G51/G50,6),"0") -> 0 | H52: =IFERROR(ROUND(H51/H50,6),"0") -> 0 | I52: =IFERROR(ROUND(I51/I50,6),"0") -> 0 | J52: =IFERROR(ROUND(J51/J50,6),"0") -> 0 | K52: =IFERROR(ROUND(K51/K50,6),"0") -> 0 | L52: =IFERROR(ROUND(L51/L50,6),"0") -> 0
A53: =B50 -> 46062 | C53: 申请金额 | D53: =SUMIFS('渠道充值成功率_底稿'!$D:$D,'渠道充值成功率_底稿'!$A:$A,$A54,'渠道充值成功率_底稿'!$B:$B,D$1) -> 0 | E53: =SUMIFS('渠道充值成功率_底稿'!$D:$D,'渠道充值成功率_底稿'!$A:$A,$A53,'渠道充值成功率_底稿'!$B:$B,E$1) -> 0 | F53: =SUMIFS('渠道充值成功率_底稿'!$D:$D,'渠道充值成功率_底稿'!$A:$A,$A53,'渠道充值成功率_底稿'!$B:$B,F$1) -> 0 | G53: =SUMIFS('渠道充值成功率_底稿'!$D:$D,'渠道充值成功率_底稿'!$A:$A,$A53,'渠道充值成功率_底稿'!$B:$B,G$1) -> 0 | H53: =SUMIFS('渠道充值成功率_底稿'!$D:$D,'渠道充值成功率_底稿'!$A:$A,$A53,'渠道充值成功率_底稿'!$B:$B,H$1) -> 0 | I53: =SUMIFS('渠道充值成功率_底稿'!$D:$D,'渠道充值成功率_底稿'!$A:$A,$A53,'渠道充值成功率_底稿'!$B:$B,I$1) -> 0 | J53: =SUMIFS('渠道充值成功率_底稿'!$D:$D,'渠道充值成功率_底稿'!$A:$A,$A53,'渠道充值成功率_底稿'!$B:$B,J$1) -> 0 | K53: =SUMIFS('渠道充值成功率_底稿'!$D:$D,'渠道充值成功率_底稿'!$A:$A,$A53,'渠道充值成功率_底稿'!$B:$B,K$1) -> 0 | L53: =SUMIFS('渠道充值成功率_底稿'!$D:$D,'渠道充值成功率_底稿'!$A:$A,$A53,'渠道充值成功率_底稿'!$B:$B,L$1) -> 0
A54: =B50 -> 46062 | C54: 到账金额 | D54: =SUMIFS('渠道充值成功率_底稿'!$G:$G,'渠道充值成功率_底稿'!$A:$A,$A55,'渠道充值成功率_底稿'!$B:$B,D$1) -> 0 | E54: =SUMIFS('渠道充值成功率_底稿'!$G:$G,'渠道充值成功率_底稿'!$A:$A,$A54,'渠道充值成功率_底稿'!$B:$B,E$1) -> 0 | F54: =SUMIFS('渠道充值成功率_底稿'!$G:$G,'渠道充值成功率_底稿'!$A:$A,$A54,'渠道充值成功率_底稿'!$B:$B,F$1) -> 0 | G54: =SUMIFS('渠道充值成功率_底稿'!$G:$G,'渠道充值成功率_底稿'!$A:$A,$A54,'渠道充值成功率_底稿'!$B:$B,G$1) -> 0 | H54: =SUMIFS('渠道充值成功率_底稿'!$G:$G,'渠道充值成功率_底稿'!$A:$A,$A54,'渠道充值成功率_底稿'!$B:$B,H$1) -> 0 | I54: =SUMIFS('渠道充值成功率_底稿'!$G:$G,'渠道充值成功率_底稿'!$A:$A,$A54,'渠道充值成功率_底稿'!$B:$B,I$1) -> 0 | J54: =SUMIFS('渠道充值成功率_底稿'!$G:$G,'渠道充值成功率_底稿'!$A:$A,$A54,'渠道充值成功率_底稿'!$B:$B,J$1) -> 0 | K54: =SUMIFS('渠道充值成功率_底稿'!$G:$G,'渠道充值成功率_底稿'!$A:$A,$A54,'渠道充值成功率_底稿'!$B:$B,K$1) -> 0 | L54: =SUMIFS('渠道充值成功率_底稿'!$G:$G,'渠道充值成功率_底稿'!$A:$A,$A54,'渠道充值成功率_底稿'!$B:$B,L$1) -> 0
A55: =B50 -> 46062 | C55: 金额成功率 | D55: =IFERROR(ROUND(D54/D53,6),"0") -> 0 | E55: =IFERROR(ROUND(E54/E53,6),"0") -> 0 | F55: =IFERROR(ROUND(F54/F53,6),"0") -> 0 | G55: =IFERROR(ROUND(G54/G53,6),"0") -> 0 | H55: =IFERROR(ROUND(H54/H53,6),"0") -> 0 | I55: =IFERROR(ROUND(I54/I53,6),"0") -> 0 | J55: =IFERROR(ROUND(J54/J53,6),"0") -> 0 | K55: =IFERROR(ROUND(K54/K53,6),"0") -> 0 | L55: =IFERROR(ROUND(L54/L53,6),"0") -> 0
A56: =B56 -> 46063 | B56: =B50+1 -> 46063 | C56: 申请笔数 | D56: =SUMIFS('渠道充值成功率_底稿'!$C:$C,'渠道充值成功率_底稿'!$A:$A,$A56,'渠道充值成功率_底稿'!$B:$B,D$1) -> 0 | E56: =SUMIFS('渠道充值成功率_底稿'!$C:$C,'渠道充值成功率_底稿'!$A:$A,$A56,'渠道充值成功率_底稿'!$B:$B,E$1) -> 0 | F56: =SUMIFS('渠道充值成功率_底稿'!$C:$C,'渠道充值成功率_底稿'!$A:$A,$A56,'渠道充值成功率_底稿'!$B:$B,F$1) -> 0 | G56: =SUMIFS('渠道充值成功率_底稿'!$C:$C,'渠道充值成功率_底稿'!$A:$A,$A56,'渠道充值成功率_底稿'!$B:$B,G$1) -> 0 | H56: =SUMIFS('渠道充值成功率_底稿'!$C:$C,'渠道充值成功率_底稿'!$A:$A,$A56,'渠道充值成功率_底稿'!$B:$B,H$1) -> 0 | I56: =SUMIFS('渠道充值成功率_底稿'!$C:$C,'渠道充值成功率_底稿'!$A:$A,$A56,'渠道充值成功率_底稿'!$B:$B,I$1) -> 0 | J56: =SUMIFS('渠道充值成功率_底稿'!$C:$C,'渠道充值成功率_底稿'!$A:$A,$A56,'渠道充值成功率_底稿'!$B:$B,J$1) -> 0 | K56: =SUMIFS('渠道充值成功率_底稿'!$C:$C,'渠道充值成功率_底稿'!$A:$A,$A56,'渠道充值成功率_底稿'!$B:$B,K$1) -> 0 | L56: =SUMIFS('渠道充值成功率_底稿'!$C:$C,'渠道充值成功率_底稿'!$A:$A,$A56,'渠道充值成功率_底稿'!$B:$B,L$1) -> 0
A57: =B56 -> 46063 | C57: 到账笔数 | D57: =SUMIFS('渠道充值成功率_底稿'!$F:$F,'渠道充值成功率_底稿'!$A:$A,$A57,'渠道充值成功率_底稿'!$B:$B,D$1) -> 0 | E57: =SUMIFS('渠道充值成功率_底稿'!$F:$F,'渠道充值成功率_底稿'!$A:$A,$A57,'渠道充值成功率_底稿'!$B:$B,E$1) -> 0 | F57: =SUMIFS('渠道充值成功率_底稿'!$F:$F,'渠道充值成功率_底稿'!$A:$A,$A57,'渠道充值成功率_底稿'!$B:$B,F$1) -> 0 | G57: =SUMIFS('渠道充值成功率_底稿'!$F:$F,'渠道充值成功率_底稿'!$A:$A,$A57,'渠道充值成功率_底稿'!$B:$B,G$1) -> 0 | H57: =SUMIFS('渠道充值成功率_底稿'!$F:$F,'渠道充值成功率_底稿'!$A:$A,$A57,'渠道充值成功率_底稿'!$B:$B,H$1) -> 0 | I57: =SUMIFS('渠道充值成功率_底稿'!$F:$F,'渠道充值成功率_底稿'!$A:$A,$A57,'渠道充值成功率_底稿'!$B:$B,I$1) -> 0 | J57: =SUMIFS('渠道充值成功率_底稿'!$F:$F,'渠道充值成功率_底稿'!$A:$A,$A57,'渠道充值成功率_底稿'!$B:$B,J$1) -> 0 | K57: =SUMIFS('渠道充值成功率_底稿'!$F:$F,'渠道充值成功率_底稿'!$A:$A,$A57,'渠道充值成功率_底稿'!$B:$B,K$1) -> 0 | L57: =SUMIFS('渠道充值成功率_底稿'!$F:$F,'渠道充值成功率_底稿'!$A:$A,$A57,'渠道充值成功率_底稿'!$B:$B,L$1) -> 0
A58: =B56 -> 46063 | C58: 笔数成功率 | D58: =IFERROR(ROUND(D57/D56,6),"0") -> 0 | E58: =IFERROR(ROUND(E57/E56,6),"0") -> 0 | F58: =IFERROR(ROUND(F57/F56,6),"0") -> 0 | G58: =IFERROR(ROUND(G57/G56,6),"0") -> 0 | H58: =IFERROR(ROUND(H57/H56,6),"0") -> 0 | I58: =IFERROR(ROUND(I57/I56,6),"0") -> 0 | J58: =IFERROR(ROUND(J57/J56,6),"0") -> 0 | K58: =IFERROR(ROUND(K57/K56,6),"0") -> 0 | L58: =IFERROR(ROUND(L57/L56,6),"0") -> 0
A59: =B56 -> 46063 | C59: 申请金额 | D59: =SUMIFS('渠道充值成功率_底稿'!$D:$D,'渠道充值成功率_底稿'!$A:$A,$A60,'渠道充值成功率_底稿'!$B:$B,D$1) -> 0 | E59: =SUMIFS('渠道充值成功率_底稿'!$D:$D,'渠道充值成功率_底稿'!$A:$A,$A59,'渠道充值成功率_底稿'!$B:$B,E$1) -> 0 | F59: =SUMIFS('渠道充值成功率_底稿'!$D:$D,'渠道充值成功率_底稿'!$A:$A,$A59,'渠道充值成功率_底稿'!$B:$B,F$1) -> 0 | G59: =SUMIFS('渠道充值成功率_底稿'!$D:$D,'渠道充值成功率_底稿'!$A:$A,$A59,'渠道充值成功率_底稿'!$B:$B,G$1) -> 0 | H59: =SUMIFS('渠道充值成功率_底稿'!$D:$D,'渠道充值成功率_底稿'!$A:$A,$A59,'渠道充值成功率_底稿'!$B:$B,H$1) -> 0 | I59: =SUMIFS('渠道充值成功率_底稿'!$D:$D,'渠道充值成功率_底稿'!$A:$A,$A59,'渠道充值成功率_底稿'!$B:$B,I$1) -> 0 | J59: =SUMIFS('渠道充值成功率_底稿'!$D:$D,'渠道充值成功率_底稿'!$A:$A,$A59,'渠道充值成功率_底稿'!$B:$B,J$1) -> 0 | K59: =SUMIFS('渠道充值成功率_底稿'!$D:$D,'渠道充值成功率_底稿'!$A:$A,$A59,'渠道充值成功率_底稿'!$B:$B,K$1) -> 0 | L59: =SUMIFS('渠道充值成功率_底稿'!$D:$D,'渠道充值成功率_底稿'!$A:$A,$A59,'渠道充值成功率_底稿'!$B:$B,L$1) -> 0
A60: =B56 -> 46063 | C60: 到账金额 | D60: =SUMIFS('渠道充值成功率_底稿'!$G:$G,'渠道充值成功率_底稿'!$A:$A,$A61,'渠道充值成功率_底稿'!$B:$B,D$1) -> 0 | E60: =SUMIFS('渠道充值成功率_底稿'!$G:$G,'渠道充值成功率_底稿'!$A:$A,$A60,'渠道充值成功率_底稿'!$B:$B,E$1) -> 0 | F60: =SUMIFS('渠道充值成功率_底稿'!$G:$G,'渠道充值成功率_底稿'!$A:$A,$A60,'渠道充值成功率_底稿'!$B:$B,F$1) -> 0 | G60: =SUMIFS('渠道充值成功率_底稿'!$G:$G,'渠道充值成功率_底稿'!$A:$A,$A60,'渠道充值成功率_底稿'!$B:$B,G$1) -> 0 | H60: =SUMIFS('渠道充值成功率_底稿'!$G:$G,'渠道充值成功率_底稿'!$A:$A,$A60,'渠道充值成功率_底稿'!$B:$B,H$1) -> 0 | I60: =SUMIFS('渠道充值成功率_底稿'!$G:$G,'渠道充值成功率_底稿'!$A:$A,$A60,'渠道充值成功率_底稿'!$B:$B,I$1) -> 0 | J60: =SUMIFS('渠道充值成功率_底稿'!$G:$G,'渠道充值成功率_底稿'!$A:$A,$A60,'渠道充值成功率_底稿'!$B:$B,J$1) -> 0 | K60: =SUMIFS('渠道充值成功率_底稿'!$G:$G,'渠道充值成功率_底稿'!$A:$A,$A60,'渠道充值成功率_底稿'!$B:$B,K$1) -> 0 | L60: =SUMIFS('渠道充值成功率_底稿'!$G:$G,'渠道充值成功率_底稿'!$A:$A,$A60,'渠道充值成功率_底稿'!$B:$B,L$1) -> 0
A61: =B56 -> 46063 | C61: 金额成功率 | D61: =IFERROR(ROUND(D60/D59,6),"0") -> 0 | E61: =IFERROR(ROUND(E60/E59,6),"0") -> 0 | F61: =IFERROR(ROUND(F60/F59,6),"0") -> 0 | G61: =IFERROR(ROUND(G60/G59,6),"0") -> 0 | H61: =IFERROR(ROUND(H60/H59,6),"0") -> 0 | I61: =IFERROR(ROUND(I60/I59,6),"0") -> 0 | J61: =IFERROR(ROUND(J60/J59,6),"0") -> 0 | K61: =IFERROR(ROUND(K60/K59,6),"0") -> 0 | L61: =IFERROR(ROUND(L60/L59,6),"0") -> 0
A62: =B62 -> 46064 | B62: =B56+1 -> 46064 | C62: 申请笔数 | D62: =SUMIFS('渠道充值成功率_底稿'!$C:$C,'渠道充值成功率_底稿'!$A:$A,$A62,'渠道充值成功率_底稿'!$B:$B,D$1) -> 336 | E62: =SUMIFS('渠道充值成功率_底稿'!$C:$C,'渠道充值成功率_底稿'!$A:$A,$A62,'渠道充值成功率_底稿'!$B:$B,E$1) -> 15 | F62: =SUMIFS('渠道充值成功率_底稿'!$C:$C,'渠道充值成功率_底稿'!$A:$A,$A62,'渠道充值成功率_底稿'!$B:$B,F$1) -> 7 | G62: =SUMIFS('渠道充值成功率_底稿'!$C:$C,'渠道充值成功率_底稿'!$A:$A,$A62,'渠道充值成功率_底稿'!$B:$B,G$1) -> 57 | H62: =SUMIFS('渠道充值成功率_底稿'!$C:$C,'渠道充值成功率_底稿'!$A:$A,$A62,'渠道充值成功率_底稿'!$B:$B,H$1) -> 0 | I62: =SUMIFS('渠道充值成功率_底稿'!$C:$C,'渠道充值成功率_底稿'!$A:$A,$A62,'渠道充值成功率_底稿'!$B:$B,I$1) -> 0 | J62: =SUMIFS('渠道充值成功率_底稿'!$C:$C,'渠道充值成功率_底稿'!$A:$A,$A62,'渠道充值成功率_底稿'!$B:$B,J$1) -> 0 | K62: =SUMIFS('渠道充值成功率_底稿'!$C:$C,'渠道充值成功率_底稿'!$A:$A,$A62,'渠道充值成功率_底稿'!$B:$B,K$1) -> 2 | L62: =SUMIFS('渠道充值成功率_底稿'!$C:$C,'渠道充值成功率_底稿'!$A:$A,$A62,'渠道充值成功率_底稿'!$B:$B,L$1) -> 0
A63: =B62 -> 46064 | C63: 到账笔数 | D63: =SUMIFS('渠道充值成功率_底稿'!$F:$F,'渠道充值成功率_底稿'!$A:$A,$A63,'渠道充值成功率_底稿'!$B:$B,D$1) -> 264 | E63: =SUMIFS('渠道充值成功率_底稿'!$F:$F,'渠道充值成功率_底稿'!$A:$A,$A63,'渠道充值成功率_底稿'!$B:$B,E$1) -> 14 | F63: =SUMIFS('渠道充值成功率_底稿'!$F:$F,'渠道充值成功率_底稿'!$A:$A,$A63,'渠道充值成功率_底稿'!$B:$B,F$1) -> 6 | G63: =SUMIFS('渠道充值成功率_底稿'!$F:$F,'渠道充值成功率_底稿'!$A:$A,$A63,'渠道充值成功率_底稿'!$B:$B,G$1) -> 45 | H63: =SUMIFS('渠道充值成功率_底稿'!$F:$F,'渠道充值成功率_底稿'!$A:$A,$A63,'渠道充值成功率_底稿'!$B:$B,H$1) -> 0 | I63: =SUMIFS('渠道充值成功率_底稿'!$F:$F,'渠道充值成功率_底稿'!$A:$A,$A63,'渠道充值成功率_底稿'!$B:$B,I$1) -> 0 | J63: =SUMIFS('渠道充值成功率_底稿'!$F:$F,'渠道充值成功率_底稿'!$A:$A,$A63,'渠道充值成功率_底稿'!$B:$B,J$1) -> 0 | K63: =SUMIFS('渠道充值成功率_底稿'!$F:$F,'渠道充值成功率_底稿'!$A:$A,$A63,'渠道充值成功率_底稿'!$B:$B,K$1) -> 2 | L63: =SUMIFS('渠道充值成功率_底稿'!$F:$F,'渠道充值成功率_底稿'!$A:$A,$A63,'渠道充值成功率_底稿'!$B:$B,L$1) -> 0
A64: =B62 -> 46064 | C64: 笔数成功率 | D64: =IFERROR(ROUND(D63/D62,6),"0") -> 0.785714 | E64: =IFERROR(ROUND(E63/E62,6),"0") -> 0.933333 | F64: =IFERROR(ROUND(F63/F62,6),"0") -> 0.857143 | G64: =IFERROR(ROUND(G63/G62,6),"0") -> 0.789474 | H64: =IFERROR(ROUND(H63/H62,6),"0") -> 0 | I64: =IFERROR(ROUND(I63/I62,6),"0") -> 0 | J64: =IFERROR(ROUND(J63/J62,6),"0") -> 0 | K64: =IFERROR(ROUND(K63/K62,6),"0") -> 1 | L64: =IFERROR(ROUND(L63/L62,6),"0") -> 0
A65: =B62 -> 46064 | C65: 申请金额 | D65: =SUMIFS('渠道充值成功率_底稿'!$D:$D,'渠道充值成功率_底稿'!$A:$A,$A66,'渠道充值成功率_底稿'!$B:$B,D$1) -> 45098 | E65: =SUMIFS('渠道充值成功率_底稿'!$D:$D,'渠道充值成功率_底稿'!$A:$A,$A65,'渠道充值成功率_底稿'!$B:$B,E$1) -> 9270 | F65: =SUMIFS('渠道充值成功率_底稿'!$D:$D,'渠道充值成功率_底稿'!$A:$A,$A65,'渠道充值成功率_底稿'!$B:$B,F$1) -> 700 | G65: =SUMIFS('渠道充值成功率_底稿'!$D:$D,'渠道充值成功率_底稿'!$A:$A,$A65,'渠道充值成功率_底稿'!$B:$B,G$1) -> 6415 | H65: =SUMIFS('渠道充值成功率_底稿'!$D:$D,'渠道充值成功率_底稿'!$A:$A,$A65,'渠道充值成功率_底稿'!$B:$B,H$1) -> 0 | I65: =SUMIFS('渠道充值成功率_底稿'!$D:$D,'渠道充值成功率_底稿'!$A:$A,$A65,'渠道充值成功率_底稿'!$B:$B,I$1) -> 0 | J65: =SUMIFS('渠道充值成功率_底稿'!$D:$D,'渠道充值成功率_底稿'!$A:$A,$A65,'渠道充值成功率_底稿'!$B:$B,J$1) -> 0 | K65: =SUMIFS('渠道充值成功率_底稿'!$D:$D,'渠道充值成功率_底稿'!$A:$A,$A65,'渠道充值成功率_底稿'!$B:$B,K$1) -> 400 | L65: =SUMIFS('渠道充值成功率_底稿'!$D:$D,'渠道充值成功率_底稿'!$A:$A,$A65,'渠道充值成功率_底稿'!$B:$B,L$1) -> 0
A66: =B62 -> 46064 | C66: 到账金额 | D66: =SUMIFS('渠道充值成功率_底稿'!$G:$G,'渠道充值成功率_底稿'!$A:$A,$A67,'渠道充值成功率_底稿'!$B:$B,D$1) -> 34978 | E66: =SUMIFS('渠道充值成功率_底稿'!$G:$G,'渠道充值成功率_底稿'!$A:$A,$A66,'渠道充值成功率_底稿'!$B:$B,E$1) -> 9070 | F66: =SUMIFS('渠道充值成功率_底稿'!$G:$G,'渠道充值成功率_底稿'!$A:$A,$A66,'渠道充值成功率_底稿'!$B:$B,F$1) -> 600 | G66: =SUMIFS('渠道充值成功率_底稿'!$G:$G,'渠道充值成功率_底稿'!$A:$A,$A66,'渠道充值成功率_底稿'!$B:$B,G$1) -> 5665 | H66: =SUMIFS('渠道充值成功率_底稿'!$G:$G,'渠道充值成功率_底稿'!$A:$A,$A66,'渠道充值成功率_底稿'!$B:$B,H$1) -> 0 | I66: =SUMIFS('渠道充值成功率_底稿'!$G:$G,'渠道充值成功率_底稿'!$A:$A,$A66,'渠道充值成功率_底稿'!$B:$B,I$1) -> 0 | J66: =SUMIFS('渠道充值成功率_底稿'!$G:$G,'渠道充值成功率_底稿'!$A:$A,$A66,'渠道充值成功率_底稿'!$B:$B,J$1) -> 0 | K66: =SUMIFS('渠道充值成功率_底稿'!$G:$G,'渠道充值成功率_底稿'!$A:$A,$A66,'渠道充值成功率_底稿'!$B:$B,K$1) -> 400 | L66: =SUMIFS('渠道充值成功率_底稿'!$G:$G,'渠道充值成功率_底稿'!$A:$A,$A66,'渠道充值成功率_底稿'!$B:$B,L$1) -> 0
A67: =B62 -> 46064 | C67: 金额成功率 | D67: =IFERROR(ROUND(D66/D65,6),"0") -> 0.7756 | E67: =IFERROR(ROUND(E66/E65,6),"0") -> 0.978425 | F67: =IFERROR(ROUND(F66/F65,6),"0") -> 0.857143 | G67: =IFERROR(ROUND(G66/G65,6),"0") -> 0.883087 | H67: =IFERROR(ROUND(H66/H65,6),"0") -> 0 | I67: =IFERROR(ROUND(I66/I65,6),"0") -> 0 | J67: =IFERROR(ROUND(J66/J65,6),"0") -> 0 | K67: =IFERROR(ROUND(K66/K65,6),"0") -> 1 | L67: =IFERROR(ROUND(L66/L65,6),"0") -> 0
A68: =B68 -> 46065 | B68: =B62+1 -> 46065 | C68: 申请笔数 | D68: =SUMIFS('渠道充值成功率_底稿'!$C:$C,'渠道充值成功率_底稿'!$A:$A,$A68,'渠道充值成功率_底稿'!$B:$B,D$1) -> 3522 | E68: =SUMIFS('渠道充值成功率_底稿'!$C:$C,'渠道充值成功率_底稿'!$A:$A,$A68,'渠道充值成功率_底稿'!$B:$B,E$1) -> 176 | F68: =SUMIFS('渠道充值成功率_底稿'!$C:$C,'渠道充值成功率_底稿'!$A:$A,$A68,'渠道充值成功率_底稿'!$B:$B,F$1) -> 238 | G68: =SUMIFS('渠道充值成功率_底稿'!$C:$C,'渠道充值成功率_底稿'!$A:$A,$A68,'渠道充值成功率_底稿'!$B:$B,G$1) -> 609 | H68: =SUMIFS('渠道充值成功率_底稿'!$C:$C,'渠道充值成功率_底稿'!$A:$A,$A68,'渠道充值成功率_底稿'!$B:$B,H$1) -> 0 | I68: =SUMIFS('渠道充值成功率_底稿'!$C:$C,'渠道充值成功率_底稿'!$A:$A,$A68,'渠道充值成功率_底稿'!$B:$B,I$1) -> 0 | J68: =SUMIFS('渠道充值成功率_底稿'!$C:$C,'渠道充值成功率_底稿'!$A:$A,$A68,'渠道充值成功率_底稿'!$B:$B,J$1) -> 0 | K68: =SUMIFS('渠道充值成功率_底稿'!$C:$C,'渠道充值成功率_底稿'!$A:$A,$A68,'渠道充值成功率_底稿'!$B:$B,K$1) -> 17 | L68: =SUMIFS('渠道充值成功率_底稿'!$C:$C,'渠道充值成功率_底稿'!$A:$A,$A68,'渠道充值成功率_底稿'!$B:$B,L$1) -> 0
A69: =B68 -> 46065 | C69: 到账笔数 | D69: =SUMIFS('渠道充值成功率_底稿'!$F:$F,'渠道充值成功率_底稿'!$A:$A,$A69,'渠道充值成功率_底稿'!$B:$B,D$1) -> 2658 | E69: =SUMIFS('渠道充值成功率_底稿'!$F:$F,'渠道充值成功率_底稿'!$A:$A,$A69,'渠道充值成功率_底稿'!$B:$B,E$1) -> 151 | F69: =SUMIFS('渠道充值成功率_底稿'!$F:$F,'渠道充值成功率_底稿'!$A:$A,$A69,'渠道充值成功率_底稿'!$B:$B,F$1) -> 132 | G69: =SUMIFS('渠道充值成功率_底稿'!$F:$F,'渠道充值成功率_底稿'!$A:$A,$A69,'渠道充值成功率_底稿'!$B:$B,G$1) -> 487 | H69: =SUMIFS('渠道充值成功率_底稿'!$F:$F,'渠道充值成功率_底稿'!$A:$A,$A69,'渠道充值成功率_底稿'!$B:$B,H$1) -> 0 | I69: =SUMIFS('渠道充值成功率_底稿'!$F:$F,'渠道充值成功率_底稿'!$A:$A,$A69,'渠道充值成功率_底稿'!$B:$B,I$1) -> 0 | J69: =SUMIFS('渠道充值成功率_底稿'!$F:$F,'渠道充值成功率_底稿'!$A:$A,$A69,'渠道充值成功率_底稿'!$B:$B,J$1) -> 0 | K69: =SUMIFS('渠道充值成功率_底稿'!$F:$F,'渠道充值成功率_底稿'!$A:$A,$A69,'渠道充值成功率_底稿'!$B:$B,K$1) -> 16 | L69: =SUMIFS('渠道充值成功率_底稿'!$F:$F,'渠道充值成功率_底稿'!$A:$A,$A69,'渠道充值成功率_底稿'!$B:$B,L$1) -> 0
A70: =B68 -> 46065 | C70: 笔数成功率 | D70: =IFERROR(ROUND(D69/D68,6),"0") -> 0.754685 | E70: =IFERROR(ROUND(E69/E68,6),"0") -> 0.857955 | F70: =IFERROR(ROUND(F69/F68,6),"0") -> 0.554622 | G70: =IFERROR(ROUND(G69/G68,6),"0") -> 0.799672 | H70: =IFERROR(ROUND(H69/H68,6),"0") -> 0 | I70: =IFERROR(ROUND(I69/I68,6),"0") -> 0 | J70: =IFERROR(ROUND(J69/J68,6),"0") -> 0 | K70: =IFERROR(ROUND(K69/K68,6),"0") -> 0.941176 | L70: =IFERROR(ROUND(L69/L68,6),"0") -> 0
A71: =B68 -> 46065 | C71: 申请金额 | D71: =SUMIFS('渠道充值成功率_底稿'!$D:$D,'渠道充值成功率_底稿'!$A:$A,$A72,'渠道充值成功率_底稿'!$B:$B,D$1) -> 594748 | E71: =SUMIFS('渠道充值成功率_底稿'!$D:$D,'渠道充值成功率_底稿'!$A:$A,$A71,'渠道充值成功率_底稿'!$B:$B,E$1) -> 41417 | F71: =SUMIFS('渠道充值成功率_底稿'!$D:$D,'渠道充值成功率_底稿'!$A:$A,$A71,'渠道充值成功率_底稿'!$B:$B,F$1) -> 45503 | G71: =SUMIFS('渠道充值成功率_底稿'!$D:$D,'渠道充值成功率_底稿'!$A:$A,$A71,'渠道充值成功率_底稿'!$B:$B,G$1) -> 114956 | H71: =SUMIFS('渠道充值成功率_底稿'!$D:$D,'渠道充值成功率_底稿'!$A:$A,$A71,'渠道充值成功率_底稿'!$B:$B,H$1) -> 0 | I71: =SUMIFS('渠道充值成功率_底稿'!$D:$D,'渠道充值成功率_底稿'!$A:$A,$A71,'渠道充值成功率_底稿'!$B:$B,I$1) -> 0 | J71: =SUMIFS('渠道充值成功率_底稿'!$D:$D,'渠道充值成功率_底稿'!$A:$A,$A71,'渠道充值成功率_底稿'!$B:$B,J$1) -> 0 | K71: =SUMIFS('渠道充值成功率_底稿'!$D:$D,'渠道充值成功率_底稿'!$A:$A,$A71,'渠道充值成功率_底稿'!$B:$B,K$1) -> 3970 | L71: =SUMIFS('渠道充值成功率_底稿'!$D:$D,'渠道充值成功率_底稿'!$A:$A,$A71,'渠道充值成功率_底稿'!$B:$B,L$1) -> 0
A72: =B68 -> 46065 | C72: 到账金额 | D72: =SUMIFS('渠道充值成功率_底稿'!$G:$G,'渠道充值成功率_底稿'!$A:$A,$A73,'渠道充值成功率_底稿'!$B:$B,D$1) -> 393917 | E72: =SUMIFS('渠道充值成功率_底稿'!$G:$G,'渠道充值成功率_底稿'!$A:$A,$A72,'渠道充值成功率_底稿'!$B:$B,E$1) -> 35097 | F72: =SUMIFS('渠道充值成功率_底稿'!$G:$G,'渠道充值成功率_底稿'!$A:$A,$A72,'渠道充值成功率_底稿'!$B:$B,F$1) -> 26162 | G72: =SUMIFS('渠道充值成功率_底稿'!$G:$G,'渠道充值成功率_底稿'!$A:$A,$A72,'渠道充值成功率_底稿'!$B:$B,G$1) -> 89690 | H72: =SUMIFS('渠道充值成功率_底稿'!$G:$G,'渠道充值成功率_底稿'!$A:$A,$A72,'渠道充值成功率_底稿'!$B:$B,H$1) -> 0 | I72: =SUMIFS('渠道充值成功率_底稿'!$G:$G,'渠道充值成功率_底稿'!$A:$A,$A72,'渠道充值成功率_底稿'!$B:$B,I$1) -> 0 | J72: =SUMIFS('渠道充值成功率_底稿'!$G:$G,'渠道充值成功率_底稿'!$A:$A,$A72,'渠道充值成功率_底稿'!$B:$B,J$1) -> 0 | K72: =SUMIFS('渠道充值成功率_底稿'!$G:$G,'渠道充值成功率_底稿'!$A:$A,$A72,'渠道充值成功率_底稿'!$B:$B,K$1) -> 3870 | L72: =SUMIFS('渠道充值成功率_底稿'!$G:$G,'渠道充值成功率_底稿'!$A:$A,$A72,'渠道充值成功率_底稿'!$B:$B,L$1) -> 0
A73: =B68 -> 46065 | C73: 金额成功率 | D73: =IFERROR(ROUND(D72/D71,6),"0") -> 0.662326 | E73: =IFERROR(ROUND(E72/E71,6),"0") -> 0.847406 | F73: =IFERROR(ROUND(F72/F71,6),"0") -> 0.574951 | G73: =IFERROR(ROUND(G72/G71,6),"0") -> 0.780212 | H73: =IFERROR(ROUND(H72/H71,6),"0") -> 0 | I73: =IFERROR(ROUND(I72/I71,6),"0") -> 0 | J73: =IFERROR(ROUND(J72/J71,6),"0") -> 0 | K73: =IFERROR(ROUND(K72/K71,6),"0") -> 0.974811 | L73: =IFERROR(ROUND(L72/L71,6),"0") -> 0
A74: =B74 -> 46066 | B74: =B68+1 -> 46066 | C74: 申请笔数 | D74: =SUMIFS('渠道充值成功率_底稿'!$C:$C,'渠道充值成功率_底稿'!$A:$A,$A74,'渠道充值成功率_底稿'!$B:$B,D$1) -> 3138 | E74: =SUMIFS('渠道充值成功率_底稿'!$C:$C,'渠道充值成功率_底稿'!$A:$A,$A74,'渠道充值成功率_底稿'!$B:$B,E$1) -> 145 | F74: =SUMIFS('渠道充值成功率_底稿'!$C:$C,'渠道充值成功率_底稿'!$A:$A,$A74,'渠道充值成功率_底稿'!$B:$B,F$1) -> 221 | G74: =SUMIFS('渠道充值成功率_底稿'!$C:$C,'渠道充值成功率_底稿'!$A:$A,$A74,'渠道充值成功率_底稿'!$B:$B,G$1) -> 574 | H74: =SUMIFS('渠道充值成功率_底稿'!$C:$C,'渠道充值成功率_底稿'!$A:$A,$A74,'渠道充值成功率_底稿'!$B:$B,H$1) -> 0 | I74: =SUMIFS('渠道充值成功率_底稿'!$C:$C,'渠道充值成功率_底稿'!$A:$A,$A74,'渠道充值成功率_底稿'!$B:$B,I$1) -> 0 | J74: =SUMIFS('渠道充值成功率_底稿'!$C:$C,'渠道充值成功率_底稿'!$A:$A,$A74,'渠道充值成功率_底稿'!$B:$B,J$1) -> 0 | K74: =SUMIFS('渠道充值成功率_底稿'!$C:$C,'渠道充值成功率_底稿'!$A:$A,$A74,'渠道充值成功率_底稿'!$B:$B,K$1) -> 76 | L74: =SUMIFS('渠道充值成功率_底稿'!$C:$C,'渠道充值成功率_底稿'!$A:$A,$A74,'渠道充值成功率_底稿'!$B:$B,L$1) -> 0
A75: =B74 -> 46066 | C75: 到账笔数 | D75: =SUMIFS('渠道充值成功率_底稿'!$F:$F,'渠道充值成功率_底稿'!$A:$A,$A75,'渠道充值成功率_底稿'!$B:$B,D$1) -> 2662 | E75: =SUMIFS('渠道充值成功率_底稿'!$F:$F,'渠道充值成功率_底稿'!$A:$A,$A75,'渠道充值成功率_底稿'!$B:$B,E$1) -> 123 | F75: =SUMIFS('渠道充值成功率_底稿'!$F:$F,'渠道充值成功率_底稿'!$A:$A,$A75,'渠道充值成功率_底稿'!$B:$B,F$1) -> 155 | G75: =SUMIFS('渠道充值成功率_底稿'!$F:$F,'渠道充值成功率_底稿'!$A:$A,$A75,'渠道充值成功率_底稿'!$B:$B,G$1) -> 471 | H75: =SUMIFS('渠道充值成功率_底稿'!$F:$F,'渠道充值成功率_底稿'!$A:$A,$A75,'渠道充值成功率_底稿'!$B:$B,H$1) -> 0 | I75: =SUMIFS('渠道充值成功率_底稿'!$F:$F,'渠道充值成功率_底稿'!$A:$A,$A75,'渠道充值成功率_底稿'!$B:$B,I$1) -> 0 | J75: =SUMIFS('渠道充值成功率_底稿'!$F:$F,'渠道充值成功率_底稿'!$A:$A,$A75,'渠道充值成功率_底稿'!$B:$B,J$1) -> 0 | K75: =SUMIFS('渠道充值成功率_底稿'!$F:$F,'渠道充值成功率_底稿'!$A:$A,$A75,'渠道充值成功率_底稿'!$B:$B,K$1) -> 59 | L75: =SUMIFS('渠道充值成功率_底稿'!$F:$F,'渠道充值成功率_底稿'!$A:$A,$A75,'渠道充值成功率_底稿'!$B:$B,L$1) -> 0
A76: =B74 -> 46066 | C76: 笔数成功率 | D76: =IFERROR(ROUND(D75/D74,6),"0") -> 0.848311 | E76: =IFERROR(ROUND(E75/E74,6),"0") -> 0.848276 | F76: =IFERROR(ROUND(F75/F74,6),"0") -> 0.701357 | G76: =IFERROR(ROUND(G75/G74,6),"0") -> 0.820557 | H76: =IFERROR(ROUND(H75/H74,6),"0") -> 0 | I76: =IFERROR(ROUND(I75/I74,6),"0") -> 0 | J76: =IFERROR(ROUND(J75/J74,6),"0") -> 0 | K76: =IFERROR(ROUND(K75/K74,6),"0") -> 0.776316 | L76: =IFERROR(ROUND(L75/L74,6),"0") -> 0
A77: =B74 -> 46066 | C77: 申请金额 | D77: =SUMIFS('渠道充值成功率_底稿'!$D:$D,'渠道充值成功率_底稿'!$A:$A,$A78,'渠道充值成功率_底稿'!$B:$B,D$1) -> 480873 | E77: =SUMIFS('渠道充值成功率_底稿'!$D:$D,'渠道充值成功率_底稿'!$A:$A,$A77,'渠道充值成功率_底稿'!$B:$B,E$1) -> 33078 | F77: =SUMIFS('渠道充值成功率_底稿'!$D:$D,'渠道充值成功率_底稿'!$A:$A,$A77,'渠道充值成功率_底稿'!$B:$B,F$1) -> 45857 | G77: =SUMIFS('渠道充值成功率_底稿'!$D:$D,'渠道充值成功率_底稿'!$A:$A,$A77,'渠道充值成功率_底稿'!$B:$B,G$1) -> 101172 | H77: =SUMIFS('渠道充值成功率_底稿'!$D:$D,'渠道充值成功率_底稿'!$A:$A,$A77,'渠道充值成功率_底稿'!$B:$B,H$1) -> 0 | I77: =SUMIFS('渠道充值成功率_底稿'!$D:$D,'渠道充值成功率_底稿'!$A:$A,$A77,'渠道充值成功率_底稿'!$B:$B,I$1) -> 0 | J77: =SUMIFS('渠道充值成功率_底稿'!$D:$D,'渠道充值成功率_底稿'!$A:$A,$A77,'渠道充值成功率_底稿'!$B:$B,J$1) -> 0 | K77: =SUMIFS('渠道充值成功率_底稿'!$D:$D,'渠道充值成功率_底稿'!$A:$A,$A77,'渠道充值成功率_底稿'!$B:$B,K$1) -> 23630 | L77: =SUMIFS('渠道充值成功率_底稿'!$D:$D,'渠道充值成功率_底稿'!$A:$A,$A77,'渠道充值成功率_底稿'!$B:$B,L$1) -> 0
A78: =B74 -> 46066 | C78: 到账金额 | D78: =SUMIFS('渠道充值成功率_底稿'!$G:$G,'渠道充值成功率_底稿'!$A:$A,$A79,'渠道充值成功率_底稿'!$B:$B,D$1) -> 388877 | E78: =SUMIFS('渠道充值成功率_底稿'!$G:$G,'渠道充值成功率_底稿'!$A:$A,$A78,'渠道充值成功率_底稿'!$B:$B,E$1) -> 28478 | F78: =SUMIFS('渠道充值成功率_底稿'!$G:$G,'渠道充值成功率_底稿'!$A:$A,$A78,'渠道充值成功率_底稿'!$B:$B,F$1) -> 30188 | G78: =SUMIFS('渠道充值成功率_底稿'!$G:$G,'渠道充值成功率_底稿'!$A:$A,$A78,'渠道充值成功率_底稿'!$B:$B,G$1) -> 83453 | H78: =SUMIFS('渠道充值成功率_底稿'!$G:$G,'渠道充值成功率_底稿'!$A:$A,$A78,'渠道充值成功率_底稿'!$B:$B,H$1) -> 0 | I78: =SUMIFS('渠道充值成功率_底稿'!$G:$G,'渠道充值成功率_底稿'!$A:$A,$A78,'渠道充值成功率_底稿'!$B:$B,I$1) -> 0 | J78: =SUMIFS('渠道充值成功率_底稿'!$G:$G,'渠道充值成功率_底稿'!$A:$A,$A78,'渠道充值成功率_底稿'!$B:$B,J$1) -> 0 | K78: =SUMIFS('渠道充值成功率_底稿'!$G:$G,'渠道充值成功率_底稿'!$A:$A,$A78,'渠道充值成功率_底稿'!$B:$B,K$1) -> 18270 | L78: =SUMIFS('渠道充值成功率_底稿'!$G:$G,'渠道充值成功率_底稿'!$A:$A,$A78,'渠道充值成功率_底稿'!$B:$B,L$1) -> 0
A79: =B74 -> 46066 | C79: 金额成功率 | D79: =IFERROR(ROUND(D78/D77,6),"0") -> 0.80869 | E79: =IFERROR(ROUND(E78/E77,6),"0") -> 0.860935 | F79: =IFERROR(ROUND(F78/F77,6),"0") -> 0.658307 | G79: =IFERROR(ROUND(G78/G77,6),"0") -> 0.824863 | H79: =IFERROR(ROUND(H78/H77,6),"0") -> 0 | I79: =IFERROR(ROUND(I78/I77,6),"0") -> 0 | J79: =IFERROR(ROUND(J78/J77,6),"0") -> 0 | K79: =IFERROR(ROUND(K78/K77,6),"0") -> 0.77317 | L79: =IFERROR(ROUND(L78/L77,6),"0") -> 0
A80: =B80 -> 46067 | B80: =B74+1 -> 46067 | C80: 申请笔数 | D80: =SUMIFS('渠道充值成功率_底稿'!$C:$C,'渠道充值成功率_底稿'!$A:$A,$A80,'渠道充值成功率_底稿'!$B:$B,D$1) -> 2086 | E80: =SUMIFS('渠道充值成功率_底稿'!$C:$C,'渠道充值成功率_底稿'!$A:$A,$A80,'渠道充值成功率_底稿'!$B:$B,E$1) -> 104 | F80: =SUMIFS('渠道充值成功率_底稿'!$C:$C,'渠道充值成功率_底稿'!$A:$A,$A80,'渠道充值成功率_底稿'!$B:$B,F$1) -> 101 | G80: =SUMIFS('渠道充值成功率_底稿'!$C:$C,'渠道充值成功率_底稿'!$A:$A,$A80,'渠道充值成功率_底稿'!$B:$B,G$1) -> 349 | H80: =SUMIFS('渠道充值成功率_底稿'!$C:$C,'渠道充值成功率_底稿'!$A:$A,$A80,'渠道充值成功率_底稿'!$B:$B,H$1) -> 0 | I80: =SUMIFS('渠道充值成功率_底稿'!$C:$C,'渠道充值成功率_底稿'!$A:$A,$A80,'渠道充值成功率_底稿'!$B:$B,I$1) -> 0 | J80: =SUMIFS('渠道充值成功率_底稿'!$C:$C,'渠道充值成功率_底稿'!$A:$A,$A80,'渠道充值成功率_底稿'!$B:$B,J$1) -> 0 | K80: =SUMIFS('渠道充值成功率_底稿'!$C:$C,'渠道充值成功率_底稿'!$A:$A,$A80,'渠道充值成功率_底稿'!$B:$B,K$1) -> 64 | L80: =SUMIFS('渠道充值成功率_底稿'!$C:$C,'渠道充值成功率_底稿'!$A:$A,$A80,'渠道充值成功率_底稿'!$B:$B,L$1) -> 0
A81: =B80 -> 46067 | C81: 到账笔数 | D81: =SUMIFS('渠道充值成功率_底稿'!$F:$F,'渠道充值成功率_底稿'!$A:$A,$A81,'渠道充值成功率_底稿'!$B:$B,D$1) -> 1749 | E81: =SUMIFS('渠道充值成功率_底稿'!$F:$F,'渠道充值成功率_底稿'!$A:$A,$A81,'渠道充值成功率_底稿'!$B:$B,E$1) -> 93 | F81: =SUMIFS('渠道充值成功率_底稿'!$F:$F,'渠道充值成功率_底稿'!$A:$A,$A81,'渠道充值成功率_底稿'!$B:$B,F$1) -> 71 | G81: =SUMIFS('渠道充值成功率_底稿'!$F:$F,'渠道充值成功率_底稿'!$A:$A,$A81,'渠道充值成功率_底稿'!$B:$B,G$1) -> 297 | H81: =SUMIFS('渠道充值成功率_底稿'!$F:$F,'渠道充值成功率_底稿'!$A:$A,$A81,'渠道充值成功率_底稿'!$B:$B,H$1) -> 0 | I81: =SUMIFS('渠道充值成功率_底稿'!$F:$F,'渠道充值成功率_底稿'!$A:$A,$A81,'渠道充值成功率_底稿'!$B:$B,I$1) -> 0 | J81: =SUMIFS('渠道充值成功率_底稿'!$F:$F,'渠道充值成功率_底稿'!$A:$A,$A81,'渠道充值成功率_底稿'!$B:$B,J$1) -> 0 | K81: =SUMIFS('渠道充值成功率_底稿'!$F:$F,'渠道充值成功率_底稿'!$A:$A,$A81,'渠道充值成功率_底稿'!$B:$B,K$1) -> 62 | L81: =SUMIFS('渠道充值成功率_底稿'!$F:$F,'渠道充值成功率_底稿'!$A:$A,$A81,'渠道充值成功率_底稿'!$B:$B,L$1) -> 0
A82: =B80 -> 46067 | C82: 笔数成功率 | D82: =IFERROR(ROUND(D81/D80,6),"0") -> 0.838447 | E82: =IFERROR(ROUND(E81/E80,6),"0") -> 0.894231 | F82: =IFERROR(ROUND(F81/F80,6),"0") -> 0.70297 | G82: =IFERROR(ROUND(G81/G80,6),"0") -> 0.851003 | H82: =IFERROR(ROUND(H81/H80,6),"0") -> 0 | I82: =IFERROR(ROUND(I81/I80,6),"0") -> 0 | J82: =IFERROR(ROUND(J81/J80,6),"0") -> 0 | K82: =IFERROR(ROUND(K81/K80,6),"0") -> 0.96875 | L82: =IFERROR(ROUND(L81/L80,6),"0") -> 0
A83: =B80 -> 46067 | C83: 申请金额 | D83: =SUMIFS('渠道充值成功率_底稿'!$D:$D,'渠道充值成功率_底稿'!$A:$A,$A84,'渠道充值成功率_底稿'!$B:$B,D$1) -> 341824 | E83: =SUMIFS('渠道充值成功率_底稿'!$D:$D,'渠道充值成功率_底稿'!$A:$A,$A83,'渠道充值成功率_底稿'!$B:$B,E$1) -> 47720 | F83: =SUMIFS('渠道充值成功率_底稿'!$D:$D,'渠道充值成功率_底稿'!$A:$A,$A83,'渠道充值成功率_底稿'!$B:$B,F$1) -> 22175 | G83: =SUMIFS('渠道充值成功率_底稿'!$D:$D,'渠道充值成功率_底稿'!$A:$A,$A83,'渠道充值成功率_底稿'!$B:$B,G$1) -> 88258 | H83: =SUMIFS('渠道充值成功率_底稿'!$D:$D,'渠道充值成功率_底稿'!$A:$A,$A83,'渠道充值成功率_底稿'!$B:$B,H$1) -> 0 | I83: =SUMIFS('渠道充值成功率_底稿'!$D:$D,'渠道充值成功率_底稿'!$A:$A,$A83,'渠道充值成功率_底稿'!$B:$B,I$1) -> 0 | J83: =SUMIFS('渠道充值成功率_底稿'!$D:$D,'渠道充值成功率_底稿'!$A:$A,$A83,'渠道充值成功率_底稿'!$B:$B,J$1) -> 0 | K83: =SUMIFS('渠道充值成功率_底稿'!$D:$D,'渠道充值成功率_底稿'!$A:$A,$A83,'渠道充值成功率_底稿'!$B:$B,K$1) -> 21990 | L83: =SUMIFS('渠道充值成功率_底稿'!$D:$D,'渠道充值成功率_底稿'!$A:$A,$A83,'渠道充值成功率_底稿'!$B:$B,L$1) -> 0
A84: =B80 -> 46067 | C84: 到账金额 | D84: =SUMIFS('渠道充值成功率_底稿'!$G:$G,'渠道充值成功率_底稿'!$A:$A,$A85,'渠道充值成功率_底稿'!$B:$B,D$1) -> 283234 | E84: =SUMIFS('渠道充值成功率_底稿'!$G:$G,'渠道充值成功率_底稿'!$A:$A,$A84,'渠道充值成功率_底稿'!$B:$B,E$1) -> 44710 | F84: =SUMIFS('渠道充值成功率_底稿'!$G:$G,'渠道充值成功率_底稿'!$A:$A,$A84,'渠道充值成功率_底稿'!$B:$B,F$1) -> 12977 | G84: =SUMIFS('渠道充值成功率_底稿'!$G:$G,'渠道充值成功率_底稿'!$A:$A,$A84,'渠道充值成功率_底稿'!$B:$B,G$1) -> 79670 | H84: =SUMIFS('渠道充值成功率_底稿'!$G:$G,'渠道充值成功率_底稿'!$A:$A,$A84,'渠道充值成功率_底稿'!$B:$B,H$1) -> 0 | I84: =SUMIFS('渠道充值成功率_底稿'!$G:$G,'渠道充值成功率_底稿'!$A:$A,$A84,'渠道充值成功率_底稿'!$B:$B,I$1) -> 0 | J84: =SUMIFS('渠道充值成功率_底稿'!$G:$G,'渠道充值成功率_底稿'!$A:$A,$A84,'渠道充值成功率_底稿'!$B:$B,J$1) -> 0 | K84: =SUMIFS('渠道充值成功率_底稿'!$G:$G,'渠道充值成功率_底稿'!$A:$A,$A84,'渠道充值成功率_底稿'!$B:$B,K$1) -> 21390 | L84: =SUMIFS('渠道充值成功率_底稿'!$G:$G,'渠道充值成功率_底稿'!$A:$A,$A84,'渠道充值成功率_底稿'!$B:$B,L$1) -> 0
A85: =B80 -> 46067 | C85: 金额成功率 | D85: =IFERROR(ROUND(D84/D83,6),"0") -> 0.828596 | E85: =IFERROR(ROUND(E84/E83,6),"0") -> 0.936924 | F85: =IFERROR(ROUND(F84/F83,6),"0") -> 0.585209 | G85: =IFERROR(ROUND(G84/G83,6),"0") -> 0.902694 | H85: =IFERROR(ROUND(H84/H83,6),"0") -> 0 | I85: =IFERROR(ROUND(I84/I83,6),"0") -> 0 | J85: =IFERROR(ROUND(J84/J83,6),"0") -> 0 | K85: =IFERROR(ROUND(K84/K83,6),"0") -> 0.972715 | L85: =IFERROR(ROUND(L84/L83,6),"0") -> 0
A86: =B86 -> 46068 | B86: =B80+1 -> 46068 | C86: 申请笔数 | D86: =SUMIFS('渠道充值成功率_底稿'!$C:$C,'渠道充值成功率_底稿'!$A:$A,$A86,'渠道充值成功率_底稿'!$B:$B,D$1) -> 1356 | E86: =SUMIFS('渠道充值成功率_底稿'!$C:$C,'渠道充值成功率_底稿'!$A:$A,$A86,'渠道充值成功率_底稿'!$B:$B,E$1) -> 33 | F86: =SUMIFS('渠道充值成功率_底稿'!$C:$C,'渠道充值成功率_底稿'!$A:$A,$A86,'渠道充值成功率_底稿'!$B:$B,F$1) -> 124 | G86: =SUMIFS('渠道充值成功率_底稿'!$C:$C,'渠道充值成功率_底稿'!$A:$A,$A86,'渠道充值成功率_底稿'!$B:$B,G$1) -> 177 | H86: =SUMIFS('渠道充值成功率_底稿'!$C:$C,'渠道充值成功率_底稿'!$A:$A,$A86,'渠道充值成功率_底稿'!$B:$B,H$1) -> 0 | I86: =SUMIFS('渠道充值成功率_底稿'!$C:$C,'渠道充值成功率_底稿'!$A:$A,$A86,'渠道充值成功率_底稿'!$B:$B,I$1) -> 0 | J86: =SUMIFS('渠道充值成功率_底稿'!$C:$C,'渠道充值成功率_底稿'!$A:$A,$A86,'渠道充值成功率_底稿'!$B:$B,J$1) -> 0 | K86: =SUMIFS('渠道充值成功率_底稿'!$C:$C,'渠道充值成功率_底稿'!$A:$A,$A86,'渠道充值成功率_底稿'!$B:$B,K$1) -> 8 | L86: =SUMIFS('渠道充值成功率_底稿'!$C:$C,'渠道充值成功率_底稿'!$A:$A,$A86,'渠道充值成功率_底稿'!$B:$B,L$1) -> 0
A87: =B86 -> 46068 | C87: 到账笔数 | D87: =SUMIFS('渠道充值成功率_底稿'!$F:$F,'渠道充值成功率_底稿'!$A:$A,$A87,'渠道充值成功率_底稿'!$B:$B,D$1) -> 1073 | E87: =SUMIFS('渠道充值成功率_底稿'!$F:$F,'渠道充值成功率_底稿'!$A:$A,$A87,'渠道充值成功率_底稿'!$B:$B,E$1) -> 22 | F87: =SUMIFS('渠道充值成功率_底稿'!$F:$F,'渠道充值成功率_底稿'!$A:$A,$A87,'渠道充值成功率_底稿'!$B:$B,F$1) -> 59 | G87: =SUMIFS('渠道充值成功率_底稿'!$F:$F,'渠道充值成功率_底稿'!$A:$A,$A87,'渠道充值成功率_底稿'!$B:$B,G$1) -> 150 | H87: =SUMIFS('渠道充值成功率_底稿'!$F:$F,'渠道充值成功率_底稿'!$A:$A,$A87,'渠道充值成功率_底稿'!$B:$B,H$1) -> 0 | I87: =SUMIFS('渠道充值成功率_底稿'!$F:$F,'渠道充值成功率_底稿'!$A:$A,$A87,'渠道充值成功率_底稿'!$B:$B,I$1) -> 0 | J87: =SUMIFS('渠道充值成功率_底稿'!$F:$F,'渠道充值成功率_底稿'!$A:$A,$A87,'渠道充值成功率_底稿'!$B:$B,J$1) -> 0 | K87: =SUMIFS('渠道充值成功率_底稿'!$F:$F,'渠道充值成功率_底稿'!$A:$A,$A87,'渠道充值成功率_底稿'!$B:$B,K$1) -> 6 | L87: =SUMIFS('渠道充值成功率_底稿'!$F:$F,'渠道充值成功率_底稿'!$A:$A,$A87,'渠道充值成功率_底稿'!$B:$B,L$1) -> 0
A88: =B86 -> 46068 | C88: 笔数成功率 | D88: =IFERROR(ROUND(D87/D86,6),"0") -> 0.791298 | E88: =IFERROR(ROUND(E87/E86,6),"0") -> 0.666667 | F88: =IFERROR(ROUND(F87/F86,6),"0") -> 0.475806 | G88: =IFERROR(ROUND(G87/G86,6),"0") -> 0.847458 | H88: =IFERROR(ROUND(H87/H86,6),"0") -> 0 | I88: =IFERROR(ROUND(I87/I86,6),"0") -> 0 | J88: =IFERROR(ROUND(J87/J86,6),"0") -> 0 | K88: =IFERROR(ROUND(K87/K86,6),"0") -> 0.75 | L88: =IFERROR(ROUND(L87/L86,6),"0") -> 0
A89: =B86 -> 46068 | C89: 申请金额 | D89: =SUMIFS('渠道充值成功率_底稿'!$D:$D,'渠道充值成功率_底稿'!$A:$A,$A90,'渠道充值成功率_底稿'!$B:$B,D$1) -> 190005 | E89: =SUMIFS('渠道充值成功率_底稿'!$D:$D,'渠道充值成功率_底稿'!$A:$A,$A89,'渠道充值成功率_底稿'!$B:$B,E$1) -> 4520 | F89: =SUMIFS('渠道充值成功率_底稿'!$D:$D,'渠道充值成功率_底稿'!$A:$A,$A89,'渠道充值成功率_底稿'!$B:$B,F$1) -> 21716 | G89: =SUMIFS('渠道充值成功率_底稿'!$D:$D,'渠道充值成功率_底稿'!$A:$A,$A89,'渠道充值成功率_底稿'!$B:$B,G$1) -> 21445 | H89: =SUMIFS('渠道充值成功率_底稿'!$D:$D,'渠道充值成功率_底稿'!$A:$A,$A89,'渠道充值成功率_底稿'!$B:$B,H$1) -> 0 | I89: =SUMIFS('渠道充值成功率_底稿'!$D:$D,'渠道充值成功率_底稿'!$A:$A,$A89,'渠道充值成功率_底稿'!$B:$B,I$1) -> 0 | J89: =SUMIFS('渠道充值成功率_底稿'!$D:$D,'渠道充值成功率_底稿'!$A:$A,$A89,'渠道充值成功率_底稿'!$B:$B,J$1) -> 0 | K89: =SUMIFS('渠道充值成功率_底稿'!$D:$D,'渠道充值成功率_底稿'!$A:$A,$A89,'渠道充值成功率_底稿'!$B:$B,K$1) -> 2980 | L89: =SUMIFS('渠道充值成功率_底稿'!$D:$D,'渠道充值成功率_底稿'!$A:$A,$A89,'渠道充值成功率_底稿'!$B:$B,L$1) -> 0
A90: =B86 -> 46068 | C90: 到账金额 | D90: =SUMIFS('渠道充值成功率_底稿'!$G:$G,'渠道充值成功率_底稿'!$A:$A,$A91,'渠道充值成功率_底稿'!$B:$B,D$1) -> 153442 | E90: =SUMIFS('渠道充值成功率_底稿'!$G:$G,'渠道充值成功率_底稿'!$A:$A,$A90,'渠道充值成功率_底稿'!$B:$B,E$1) -> 3120 | F90: =SUMIFS('渠道充值成功率_底稿'!$G:$G,'渠道充值成功率_底稿'!$A:$A,$A90,'渠道充值成功率_底稿'!$B:$B,F$1) -> 10656 | G90: =SUMIFS('渠道充值成功率_底稿'!$G:$G,'渠道充值成功率_底稿'!$A:$A,$A90,'渠道充值成功率_底稿'!$B:$B,G$1) -> 17255 | H90: =SUMIFS('渠道充值成功率_底稿'!$G:$G,'渠道充值成功率_底稿'!$A:$A,$A90,'渠道充值成功率_底稿'!$B:$B,H$1) -> 0 | I90: =SUMIFS('渠道充值成功率_底稿'!$G:$G,'渠道充值成功率_底稿'!$A:$A,$A90,'渠道充值成功率_底稿'!$B:$B,I$1) -> 0 | J90: =SUMIFS('渠道充值成功率_底稿'!$G:$G,'渠道充值成功率_底稿'!$A:$A,$A90,'渠道充值成功率_底稿'!$B:$B,J$1) -> 0 | K90: =SUMIFS('渠道充值成功率_底稿'!$G:$G,'渠道充值成功率_底稿'!$A:$A,$A90,'渠道充值成功率_底稿'!$B:$B,K$1) -> 2480 | L90: =SUMIFS('渠道充值成功率_底稿'!$G:$G,'渠道充值成功率_底稿'!$A:$A,$A90,'渠道充值成功率_底稿'!$B:$B,L$1) -> 0
A91: =B86 -> 46068 | C91: 金额成功率 | D91: =IFERROR(ROUND(D90/D89,6),"0") -> 0.807568 | E91: =IFERROR(ROUND(E90/E89,6),"0") -> 0.690265 | F91: =IFERROR(ROUND(F90/F89,6),"0") -> 0.490698 | G91: =IFERROR(ROUND(G90/G89,6),"0") -> 0.804616 | H91: =IFERROR(ROUND(H90/H89,6),"0") -> 0 | I91: =IFERROR(ROUND(I90/I89,6),"0") -> 0 | J91: =IFERROR(ROUND(J90/J89,6),"0") -> 0 | K91: =IFERROR(ROUND(K90/K89,6),"0") -> 0.832215 | L91: =IFERROR(ROUND(L90/L89,6),"0") -> 0
A92: =B92 -> 46069 | B92: =B86+1 -> 46069 | C92: 申请笔数 | D92: =SUMIFS('渠道充值成功率_底稿'!$C:$C,'渠道充值成功率_底稿'!$A:$A,$A92,'渠道充值成功率_底稿'!$B:$B,D$1) -> 1232 | E92: =SUMIFS('渠道充值成功率_底稿'!$C:$C,'渠道充值成功率_底稿'!$A:$A,$A92,'渠道充值成功率_底稿'!$B:$B,E$1) -> 63 | F92: =SUMIFS('渠道充值成功率_底稿'!$C:$C,'渠道充值成功率_底稿'!$A:$A,$A92,'渠道充值成功率_底稿'!$B:$B,F$1) -> 76 | G92: =SUMIFS('渠道充值成功率_底稿'!$C:$C,'渠道充值成功率_底稿'!$A:$A,$A92,'渠道充值成功率_底稿'!$B:$B,G$1) -> 162 | H92: =SUMIFS('渠道充值成功率_底稿'!$C:$C,'渠道充值成功率_底稿'!$A:$A,$A92,'渠道充值成功率_底稿'!$B:$B,H$1) -> 0 | I92: =SUMIFS('渠道充值成功率_底稿'!$C:$C,'渠道充值成功率_底稿'!$A:$A,$A92,'渠道充值成功率_底稿'!$B:$B,I$1) -> 0 | J92: =SUMIFS('渠道充值成功率_底稿'!$C:$C,'渠道充值成功率_底稿'!$A:$A,$A92,'渠道充值成功率_底稿'!$B:$B,J$1) -> 0 | K92: =SUMIFS('渠道充值成功率_底稿'!$C:$C,'渠道充值成功率_底稿'!$A:$A,$A92,'渠道充值成功率_底稿'!$B:$B,K$1) -> 6 | L92: =SUMIFS('渠道充值成功率_底稿'!$C:$C,'渠道充值成功率_底稿'!$A:$A,$A92,'渠道充值成功率_底稿'!$B:$B,L$1) -> 0
A93: =B92 -> 46069 | C93: 到账笔数 | D93: =SUMIFS('渠道充值成功率_底稿'!$F:$F,'渠道充值成功率_底稿'!$A:$A,$A93,'渠道充值成功率_底稿'!$B:$B,D$1) -> 907 | E93: =SUMIFS('渠道充值成功率_底稿'!$F:$F,'渠道充值成功率_底稿'!$A:$A,$A93,'渠道充值成功率_底稿'!$B:$B,E$1) -> 24 | F93: =SUMIFS('渠道充值成功率_底稿'!$F:$F,'渠道充值成功率_底稿'!$A:$A,$A93,'渠道充值成功率_底稿'!$B:$B,F$1) -> 38 | G93: =SUMIFS('渠道充值成功率_底稿'!$F:$F,'渠道充值成功率_底稿'!$A:$A,$A93,'渠道充值成功率_底稿'!$B:$B,G$1) -> 121 | H93: =SUMIFS('渠道充值成功率_底稿'!$F:$F,'渠道充值成功率_底稿'!$A:$A,$A93,'渠道充值成功率_底稿'!$B:$B,H$1) -> 0 | I93: =SUMIFS('渠道充值成功率_底稿'!$F:$F,'渠道充值成功率_底稿'!$A:$A,$A93,'渠道充值成功率_底稿'!$B:$B,I$1) -> 0 | J93: =SUMIFS('渠道充值成功率_底稿'!$F:$F,'渠道充值成功率_底稿'!$A:$A,$A93,'渠道充值成功率_底稿'!$B:$B,J$1) -> 0 | K93: =SUMIFS('渠道充值成功率_底稿'!$F:$F,'渠道充值成功率_底稿'!$A:$A,$A93,'渠道充值成功率_底稿'!$B:$B,K$1) -> 4 | L93: =SUMIFS('渠道充值成功率_底稿'!$F:$F,'渠道充值成功率_底稿'!$A:$A,$A93,'渠道充值成功率_底稿'!$B:$B,L$1) -> 0
A94: =B92 -> 46069 | C94: 笔数成功率 | D94: =IFERROR(ROUND(D93/D92,6),"0") -> 0.736201 | E94: =IFERROR(ROUND(E93/E92,6),"0") -> 0.380952 | F94: =IFERROR(ROUND(F93/F92,6),"0") -> 0.5 | G94: =IFERROR(ROUND(G93/G92,6),"0") -> 0.746914 | H94: =IFERROR(ROUND(H93/H92,6),"0") -> 0 | I94: =IFERROR(ROUND(I93/I92,6),"0") -> 0 | J94: =IFERROR(ROUND(J93/J92,6),"0") -> 0 | K94: =IFERROR(ROUND(K93/K92,6),"0") -> 0.666667 | L94: =IFERROR(ROUND(L93/L92,6),"0") -> 0
A95: =B92 -> 46069 | C95: 申请金额 | D95: =SUMIFS('渠道充值成功率_底稿'!$D:$D,'渠道充值成功率_底稿'!$A:$A,$A96,'渠道充值成功率_底稿'!$B:$B,D$1) -> 190784 | E95: =SUMIFS('渠道充值成功率_底稿'!$D:$D,'渠道充值成功率_底稿'!$A:$A,$A95,'渠道充值成功率_底稿'!$B:$B,E$1) -> 11471 | F95: =SUMIFS('渠道充值成功率_底稿'!$D:$D,'渠道充值成功率_底稿'!$A:$A,$A95,'渠道充值成功率_底稿'!$B:$B,F$1) -> 10714 | G95: =SUMIFS('渠道充值成功率_底稿'!$D:$D,'渠道充值成功率_底稿'!$A:$A,$A95,'渠道充值成功率_底稿'!$B:$B,G$1) -> 19899 | H95: =SUMIFS('渠道充值成功率_底稿'!$D:$D,'渠道充值成功率_底稿'!$A:$A,$A95,'渠道充值成功率_底稿'!$B:$B,H$1) -> 0 | I95: =SUMIFS('渠道充值成功率_底稿'!$D:$D,'渠道充值成功率_底稿'!$A:$A,$A95,'渠道充值成功率_底稿'!$B:$B,I$1) -> 0 | J95: =SUMIFS('渠道充值成功率_底稿'!$D:$D,'渠道充值成功率_底稿'!$A:$A,$A95,'渠道充值成功率_底稿'!$B:$B,J$1) -> 0 | K95: =SUMIFS('渠道充值成功率_底稿'!$D:$D,'渠道充值成功率_底稿'!$A:$A,$A95,'渠道充值成功率_底稿'!$B:$B,K$1) -> 1000 | L95: =SUMIFS('渠道充值成功率_底稿'!$D:$D,'渠道充值成功率_底稿'!$A:$A,$A95,'渠道充值成功率_底稿'!$B:$B,L$1) -> 0
A96: =B92 -> 46069 | C96: 到账金额 | D96: =SUMIFS('渠道充值成功率_底稿'!$G:$G,'渠道充值成功率_底稿'!$A:$A,$A97,'渠道充值成功率_底稿'!$B:$B,D$1) -> 137585 | E96: =SUMIFS('渠道充值成功率_底稿'!$G:$G,'渠道充值成功率_底稿'!$A:$A,$A96,'渠道充值成功率_底稿'!$B:$B,E$1) -> 3026 | F96: =SUMIFS('渠道充值成功率_底稿'!$G:$G,'渠道充值成功率_底稿'!$A:$A,$A96,'渠道充值成功率_底稿'!$B:$B,F$1) -> 5000 | G96: =SUMIFS('渠道充值成功率_底稿'!$G:$G,'渠道充值成功率_底稿'!$A:$A,$A96,'渠道充值成功率_底稿'!$B:$B,G$1) -> 15053 | H96: =SUMIFS('渠道充值成功率_底稿'!$G:$G,'渠道充值成功率_底稿'!$A:$A,$A96,'渠道充值成功率_底稿'!$B:$B,H$1) -> 0 | I96: =SUMIFS('渠道充值成功率_底稿'!$G:$G,'渠道充值成功率_底稿'!$A:$A,$A96,'渠道充值成功率_底稿'!$B:$B,I$1) -> 0 | J96: =SUMIFS('渠道充值成功率_底稿'!$G:$G,'渠道充值成功率_底稿'!$A:$A,$A96,'渠道充值成功率_底稿'!$B:$B,J$1) -> 0 | K96: =SUMIFS('渠道充值成功率_底稿'!$G:$G,'渠道充值成功率_底稿'!$A:$A,$A96,'渠道充值成功率_底稿'!$B:$B,K$1) -> 800 | L96: =SUMIFS('渠道充值成功率_底稿'!$G:$G,'渠道充值成功率_底稿'!$A:$A,$A96,'渠道充值成功率_底稿'!$B:$B,L$1) -> 0
A97: =B92 -> 46069 | C97: 金额成功率 | D97: =IFERROR(ROUND(D96/D95,6),"0") -> 0.721156 | E97: =IFERROR(ROUND(E96/E95,6),"0") -> 0.263796 | F97: =IFERROR(ROUND(F96/F95,6),"0") -> 0.466679 | G97: =IFERROR(ROUND(G96/G95,6),"0") -> 0.75647 | H97: =IFERROR(ROUND(H96/H95,6),"0") -> 0 | I97: =IFERROR(ROUND(I96/I95,6),"0") -> 0 | J97: =IFERROR(ROUND(J96/J95,6),"0") -> 0 | K97: =IFERROR(ROUND(K96/K95,6),"0") -> 0.8 | L97: =IFERROR(ROUND(L96/L95,6),"0") -> 0
A98: =B98 -> 46070 | B98: =B92+1 -> 46070 | C98: 申请笔数 | D98: =SUMIFS('渠道充值成功率_底稿'!$C:$C,'渠道充值成功率_底稿'!$A:$A,$A98,'渠道充值成功率_底稿'!$B:$B,D$1) -> 1081 | E98: =SUMIFS('渠道充值成功率_底稿'!$C:$C,'渠道充值成功率_底稿'!$A:$A,$A98,'渠道充值成功率_底稿'!$B:$B,E$1) -> 30 | F98: =SUMIFS('渠道充值成功率_底稿'!$C:$C,'渠道充值成功率_底稿'!$A:$A,$A98,'渠道充值成功率_底稿'!$B:$B,F$1) -> 53 | G98: =SUMIFS('渠道充值成功率_底稿'!$C:$C,'渠道充值成功率_底稿'!$A:$A,$A98,'渠道充值成功率_底稿'!$B:$B,G$1) -> 138 | H98: =SUMIFS('渠道充值成功率_底稿'!$C:$C,'渠道充值成功率_底稿'!$A:$A,$A98,'渠道充值成功率_底稿'!$B:$B,H$1) -> 0 | I98: =SUMIFS('渠道充值成功率_底稿'!$C:$C,'渠道充值成功率_底稿'!$A:$A,$A98,'渠道充值成功率_底稿'!$B:$B,I$1) -> 0 | J98: =SUMIFS('渠道充值成功率_底稿'!$C:$C,'渠道充值成功率_底稿'!$A:$A,$A98,'渠道充值成功率_底稿'!$B:$B,J$1) -> 0 | K98: =SUMIFS('渠道充值成功率_底稿'!$C:$C,'渠道充值成功率_底稿'!$A:$A,$A98,'渠道充值成功率_底稿'!$B:$B,K$1) -> 22 | L98: =SUMIFS('渠道充值成功率_底稿'!$C:$C,'渠道充值成功率_底稿'!$A:$A,$A98,'渠道充值成功率_底稿'!$B:$B,L$1) -> 0
A99: =B98 -> 46070 | C99: 到账笔数 | D99: =SUMIFS('渠道充值成功率_底稿'!$F:$F,'渠道充值成功率_底稿'!$A:$A,$A99,'渠道充值成功率_底稿'!$B:$B,D$1) -> 859 | E99: =SUMIFS('渠道充值成功率_底稿'!$F:$F,'渠道充值成功率_底稿'!$A:$A,$A99,'渠道充值成功率_底稿'!$B:$B,E$1) -> 28 | F99: =SUMIFS('渠道充值成功率_底稿'!$F:$F,'渠道充值成功率_底稿'!$A:$A,$A99,'渠道充值成功率_底稿'!$B:$B,F$1) -> 33 | G99: =SUMIFS('渠道充值成功率_底稿'!$F:$F,'渠道充值成功率_底稿'!$A:$A,$A99,'渠道充值成功率_底稿'!$B:$B,G$1) -> 112 | H99: =SUMIFS('渠道充值成功率_底稿'!$F:$F,'渠道充值成功率_底稿'!$A:$A,$A99,'渠道充值成功率_底稿'!$B:$B,H$1) -> 0 | I99: =SUMIFS('渠道充值成功率_底稿'!$F:$F,'渠道充值成功率_底稿'!$A:$A,$A99,'渠道充值成功率_底稿'!$B:$B,I$1) -> 0 | J99: =SUMIFS('渠道充值成功率_底稿'!$F:$F,'渠道充值成功率_底稿'!$A:$A,$A99,'渠道充值成功率_底稿'!$B:$B,J$1) -> 0 | K99: =SUMIFS('渠道充值成功率_底稿'!$F:$F,'渠道充值成功率_底稿'!$A:$A,$A99,'渠道充值成功率_底稿'!$B:$B,K$1) -> 20 | L99: =SUMIFS('渠道充值成功率_底稿'!$F:$F,'渠道充值成功率_底稿'!$A:$A,$A99,'渠道充值成功率_底稿'!$B:$B,L$1) -> 0
A100: =B98 -> 46070 | C100: 笔数成功率 | D100: =IFERROR(ROUND(D99/D98,6),"0") -> 0.794635 | E100: =IFERROR(ROUND(E99/E98,6),"0") -> 0.933333 | F100: =IFERROR(ROUND(F99/F98,6),"0") -> 0.622642 | G100: =IFERROR(ROUND(G99/G98,6),"0") -> 0.811594 | H100: =IFERROR(ROUND(H99/H98,6),"0") -> 0 | I100: =IFERROR(ROUND(I99/I98,6),"0") -> 0 | J100: =IFERROR(ROUND(J99/J98,6),"0") -> 0 | K100: =IFERROR(ROUND(K99/K98,6),"0") -> 0.909091 | L100: =IFERROR(ROUND(L99/L98,6),"0") -> 0
...

Sheet 渠道充值成功率_底稿
B1: jiliarena
A2: 时间 | B2: 充值方式 | C2: 申请笔数 | D2: 申请金额 | E2: 申请人数 | F2: 到账笔数 | G2: 到账金额 | H2: 到账人数 | I2: 首存人数 | J2: 首存金额 | K2: 成功率 (%) | L2: 到账金额占比 (%) | M2: 平均到账时间
A3: 46064 | B3: GOTYME | C3: 2 | D3: 400 | E3: 2 | F3: 2 | G3: 400 | H3: 2 | I3: 2 | J3: 400 | K3: 100.00 % | L3: 0.78 % | M3: 0.00085648148
A4: 46064 | B4: QRPH | C4: 15 | D4: 9270 | E4: 11 | F4: 14 | G4: 9070 | H4: 10 | I4: 10 | J4: 2270 | K4: 93.33 % | L4: 17.88 % | M4: 0.00061342593
A5: 46064 | B5: GCash | C5: 336 | D5: 45098 | E5: 261 | F5: 264 | G5: 34978 | H5: 234 | I5: 233 | J5: 30238 | K5: 78.57 % | L5: 68.97 % | M5: 0.00099537037
A6: 46064 | B6: GCashQR | C6: 7 | D6: 700 | E6: 6 | F6: 6 | G6: 600 | H6: 6 | I6: 6 | J6: 600 | K6: 85.71 % | L6: 1.18 % | M6: 0.00068287037
A7: 46064 | B7: Maya | C7: 57 | D7: 6415 | E7: 46 | F7: 45 | G7: 5665 | H7: 43 | I7: 43 | J7: 5415 | K7: 78.94 % | L7: 11.17 % | M7: 0.00060185185
A9: 46065 | B9: GOTYME | C9: 17 | D9: 3970 | E9: 12 | F9: 16 | G9: 3870 | H9: 12 | I9: 12 | J9: 3270 | K9: 94.11 % | L9: 0.70 % | M9: 0.00072916667
A10: 46065 | B10: QRPH | C10: 176 | D10: 41417 | E10: 145 | F10: 151 | G10: 35097 | H10: 139 | I10: 125 | J10: 28610 | K10: 85.79 % | L10: 6.39 % | M10: 0.00074074074
A11: 46065 | B11: GCash | C11: 3522 | D11: 594748 | E11: 2253 | F11: 2658 | G11: 393917 | H11: 2124 | I11: 2026 | J11: 297423 | K11: 75.46 % | L11: 71.78 % | M11: 0.00087962963
A12: 46065 | B12: GCashQR | C12: 238 | D12: 45503 | E12: 170 | F12: 132 | G12: 26162 | H12: 122 | I12: 107 | J12: 21600 | K12: 55.46 % | L12: 4.76 % | M12: 0.00070601852
A13: 46065 | B13: Maya | C13: 609 | D13: 114956 | E13: 427 | F13: 487 | G13: 89690 | H13: 402 | I13: 359 | J13: 60636 | K13: 79.96 % | L13: 16.34 % | M13: 0.0006712963
A15: 46066 | B15: GOTYME | C15: 76 | D15: 23630 | E15: 62 | F15: 59 | G15: 18270 | H15: 56 | I15: 54 | J15: 16470 | K15: 77.63 | L15: 3.32 | M15: 0.00070601852
A16: 46066 | B16: QRPH | C16: 145 | D16: 33078 | E16: 115 | F16: 123 | G16: 28478 | H16: 106 | I16: 82 | J16: 18755 | K16: 84.82 | L16: 5.18 | M16: 0.00072916667
A17: 46066 | B17: GCash | C17: 3138 | D17: 480873 | E17: 2198 | F17: 2662 | G17: 388877 | H17: 2102 | I17: 1668 | J17: 245396 | K17: 84.83 | L17: 70.79 | M17: 0.00092592593
A18: 46066 | B18: GCashQR | C18: 221 | D18: 45857 | E18: 163 | F18: 155 | G18: 30188 | H18: 140 | I18: 103 | J18: 21798 | K18: 70.13 | L18: 5.49 | M18: 0.0010185185
A19: 46066 | B19: Maya | C19: 574 | D19: 101172 | E19: 427 | F19: 471 | G19: 83453 | H19: 408 | I19: 337 | J19: 65947 | K19: 82.05 | L19: 15.19 | M19: 0.00065972222
A21: 46067 | B21: GCash | C21: 2086 | D21: 341824 | E21: 1415 | F21: 1749 | G21: 283234 | H21: 1328 | I21: 859 | J21: 136474 | K21: 83.84 % | L21: 64.08 % | M21: 0.00086805556
A22: 46067 | B22: QRPH | C22: 104 | D22: 47720 | E22: 84 | F22: 93 | G22: 44710 | H22: 80 | I22: 59 | J22: 15099 | K22: 89.42 % | L22: 10.11 % | M22: 0.00072916667
A23: 46067 | B23: GOTYME | C23: 64 | D23: 21990 | E23: 60 | F23: 62 | G23: 21390 | H23: 60 | I23: 57 | J23: 20640 | K23: 96.87 % | L23: 4.83 % | M23: 0.00063657407
A24: 46067 | B24: GCashQR | C24: 101 | D24: 22175 | E24: 74 | F24: 71 | G24: 12977 | H24: 61 | I24: 39 | J24: 6280 | K24: 70.29 % | L24: 2.93 % | M24: 0.00081018519
A25: 46067 | B25: Maya | C25: 349 | D25: 88258 | E25: 263 | F25: 297 | G25: 79670 | H25: 249 | I25: 165 | J25: 28343 | K25: 85.10 % | L25: 18.02 % | M25: 0.00070601852
A27: 46068 | B27: GCash | C27: 1356 | D27: 190005 | E27: 848 | F27: 1073 | G27: 153442 | H27: 775 | I27: 414 | J27: 56094 | K27: 79.12 % | L27: 82.07 % | M27: 0.00086805556
A28: 46068 | B28: GOTYME | C28: 8 | D28: 2980 | E28: 6 | F28: 6 | G28: 2480 | H28: 5 | I28: 4 | J28: 2280 | K28: 75.00 % | L28: 1.32 % | M28: 0.00065972222
A29: 46068 | B29: QRPH | C29: 33 | D29: 4520 | E29: 20 | F29: 22 | G29: 3120 | H29: 14 | I29: 3 | J29: 300 | K29: 66.66 % | L29: 1.66 % | M29: 0.00075231481
A30: 46068 | B30: Maya | C30: 177 | D30: 21445 | E30: 121 | F30: 150 | G30: 17255 | H30: 109 | I30: 51 | J30: 5420 | K30: 84.74 % | L30: 9.22 % | M30: 0.00065972222
A31: 46068 | B31: GCashQR | C31: 124 | D31: 21716 | E31: 58 | F31: 59 | G31: 10656 | H31: 36 | I31: 18 | J31: 2735 | K31: 47.58 % | L31: 5.69 % | M31: 0.00085648148
A33: 46069 | B33: GCash | C33: 1232 | D33: 190784 | E33: 756 | F33: 907 | G33: 137585 | H33: 688 | I33: 339 | J33: 49268 | K33: 73.62 % | L33: 85.21 % | M33: 0.0009837963
A34: 46069 | B34: QRPH | C34: 63 | D34: 11471 | E34: 19 | F34: 24 | G34: 3026 | H34: 17 | I34: 8 | J34: 900 | K34: 38.09 % | L34: 1.87 % | M34: 0.00074074074
... A37: 46069 | B37: GCashQR | C37: 76 | D37: 10714 | E37: 52 | F37: 38 | G37: 5000 | H37: 30 | I37: 16 | J37: 2300 | K37: 50.00 % | L37: 3.09 % | M37: 0.00072916667
A39: 46070 | B39: GOTYME | C39: 22 | D39: 5800 | E39: 21 | F39: 20 | G39: 5600 | H39: 20 | I39: 20 | J39: 5600 | K39: 90.9 | L39: 3.38 | M39: 0.000625
A40: 46070 | B40: QRPH | C40: 30 | D40: 6485 | E40: 21 | F40: 28 | G40: 6185 | H40: 21 | I40: 5 | J40: 1355 | K40: 93.33 | L40: 3.73 | M40: 0.00056712963
A41: 46070 | B41: GCash | C41: 1081 | D41: 166483 | E41: 708 | F41: 859 | G41: 136348 | H41: 640 | I41: 306 | J41: 44430 | K41: 79.46 | L41: 82.3 | M41: 0.00078703704
A42: 46070 | B42: GCashQR | C42: 53 | D42: 7970 | E42: 43 | F42: 33 | G42: 5050 | H42: 30 | I42: 11 | J42: 1650 | K42: 62.26 | L42: 3.04 | M42: 0.00077546296
A43: 46070 | B43: Maya | C43: 138 | D43: 15328 | E43: 105 | F43: 112 | G43: 12483 | H43: 91 | I43: 36 | J43: 4696 | K43: 81.15 | L43: 7.53 | M43: 0.00068287037
A45: 46071 | B45: GOTYME | C45: 58 | D45: 30880 | E45: 28 | F45: 34 | G45: 10280 | H45: 26 | I45: 24 | J45: 9280 | K45: 58.62 % | L45: 7.84 % | M45: 0.00082175926
A46: 46071 | B46: QRPH | C46: 50 | D46: 9007 | E46: 26 | F46: 46 | G46: 8387 | H46: 25 | I46: 13 | J46: 2317 | K46: 92.00 % | L46: 6.39 % | M46: 0.00064814815
A47: 46071 | B47: GCash | C47: 888 | D47: 122582 | E47: 571 | F47: 699 | G47: 94531 | H47: 529 | I47: 209 | J47: 26798 | K47: 78.71 % | L47: 72.11 % | M47: 0.00076388889
A48: 46071 | B48: GCashQR | C48: 50 | D48: 12006 | E48: 35 | F48: 29 | G48: 6828 | H48: 22 | I48: 9 | J48: 1430 | K48: 58.00 % | L48: 5.20 % | M48: 0.0005787037
A49: 46071 | B49: Maya | C49: 140 | D49: 15164 | E49: 101 | F49: 102 | G49: 11062 | H49: 86 | I49: 36 | J49: 3239 | K49: 72.85 % | L49: 8.43 % | M49: 0.00064814815
A51: 46072 | B51: GOTYME | C51: 19 | D51: 5180 | E51: 15 | F51: 15 | G51: 4780 | H51: 14 | I51: 12 | J51: 4480 | K51: 78.94 % | L51: 3.26 % | M51: 0.00083333333
A52: 46072 | B52: QRPH | C52: 30 | D52: 6175 | E52: 24 | F52: 23 | G52: 5170 | H52: 20 | I52: 10 | J52: 3100 | K52: 76.66 % | L52: 3.52 % | M52: 0.0006712963
A53: 46072 | B53: GCash | C53: 1002 | D53: 148648 | E53: 611 | F53: 766 | G53: 117392 | H53: 555 | I53: 278 | J53: 38137 | K53: 76.44 % | L53: 80.11 % | M53: 0.00085648148
A54: 46072 | B54: GCashQR | C54: 67 | D54: 15380 | E54: 40 | F54: 34 | G54: 6660 | H54: 26 | I54: 12 | J54: 1930 | K54: 50.74 % | L54: 4.54 % | M54: 0.00053240741
A55: 46072 | B55: Maya | C55: 146 | D55: 17389 | E55: 83 | F55: 100 | G55: 12519 | H55: 69 | I55: 32 | J55: 3361 | K55: 68.49 % | L55: 8.54 % | M55: 0.00068287037
A57: 46073 | B57: GOTYME | C57: 2 | D57: 200 | E57: 2 | F57: 2 | G57: 200 | H57: 2 | I57: 2 | J57: 200 | K57: 100.00 % | L57: 0.14 % | M57: 0.0008912037
A58: 46073 | B58: QRPH | C58: 46 | D58: 10820 | E58: 26 | F58: 38 | G58: 9120 | H58: 24 | I58: 14 | J58: 3400 | K58: 82.60 % | L58: 6.54 % | M58: 0.00068287037
... A108: 46081 | B108: Maya | C108: 125 | D108: 15376 | E108: 85 | F108: 97 | G108: 11476 | H108: 74 | I108: 33 | J108: 4515 | K108: 77.60 % | L108: 11.06 % | M108: 0.0006712963

Sheet jiliarena-每日报告
A2: 日期： | B2: 46065 | C2: =B2-1 -> 46064
B4: Date | C4: jiliarena | D4: GCash | E4: QRPH | F4: GCashQR | G4: Maya | H4: GRABPAY | I4: Online Banking | J4: USDT | K4: GOTYME | L4: GCASHPAY | M4: 加总 | N4: 差额
B5: =B2 -> 46065 | C5: 申请笔数 | D5: =SUMIFS('渠道充值成功率_底稿'!$C:$C,'渠道充值成功率_底稿'!$A:$A,$B$5,'渠道充值成功率_底稿'!$B:$B,D$4) -> 3522 | E5: =SUMIFS('渠道充值成功率_底稿'!$C:$C,'渠道充值成功率_底稿'!$A:$A,$B$5,'渠道充值成功率_底稿'!$B:$B,E$4) -> 176 | F5: =SUMIFS('渠道充值成功率_底稿'!$C:$C,'渠道充值成功率_底稿'!$A:$A,$B$5,'渠道充值成功率_底稿'!$B:$B,F$4) -> 238 | G5: =SUMIFS('渠道充值成功率_底稿'!$C:$C,'渠道充值成功率_底稿'!$A:$A,$B$5,'渠道充值成功率_底稿'!$B:$B,G$4) -> 609 | H5: =SUMIFS('渠道充值成功率_底稿'!$C:$C,'渠道充值成功率_底稿'!$A:$A,$B$5,'渠道充值成功率_底稿'!$B:$B,H$4) -> 0 | I5: =SUMIFS('渠道充值成功率_底稿'!$C:$C,'渠道充值成功率_底稿'!$A:$A,$B$5,'渠道充值成功率_底稿'!$B:$B,I$4) -> 0 | J5: =SUMIFS('渠道充值成功率_底稿'!$C:$C,'渠道充值成功率_底稿'!$A:$A,$B$5,'渠道充值成功率_底稿'!$B:$B,J$4) -> 0 | K5: =SUMIFS('渠道充值成功率_底稿'!$C:$C,'渠道充值成功率_底稿'!$A:$A,$B$5,'渠道充值成功率_底稿'!$B:$B,K$4) -> 17 | L5: =SUMIFS('渠道充值成功率_底稿'!$C:$C,'渠道充值成功率_底稿'!$A:$A,$B$5,'渠道充值成功率_底稿'!$B:$B,L$4) -> 0 | M5: =SUM(D5:L5) -> 4562 | N5: =M5-M13 -> 4145
C6: 到账笔数 | D6: =SUMIFS('渠道充值成功率_底稿'!$F:$F,'渠道充值成功率_底稿'!$A:$A,$B5,'渠道充值成功率_底稿'!$B:$B,D$4) -> 2658 | E6: =SUMIFS('渠道充值成功率_底稿'!$F:$F,'渠道充值成功率_底稿'!$A:$A,$B5,'渠道充值成功率_底稿'!$B:$B,E$4) -> 151 | F6: =SUMIFS('渠道充值成功率_底稿'!$F:$F,'渠道充值成功率_底稿'!$A:$A,$B5,'渠道充值成功率_底稿'!$B:$B,F$4) -> 132 | G6: =SUMIFS('渠道充值成功率_底稿'!$F:$F,'渠道充值成功率_底稿'!$A:$A,$B5,'渠道充值成功率_底稿'!$B:$B,G$4) -> 487 | H6: =SUMIFS('渠道充值成功率_底稿'!$F:$F,'渠道充值成功率_底稿'!$A:$A,$B5,'渠道充值成功率_底稿'!$B:$B,H$4) -> 0 | I6: =SUMIFS('渠道充值成功率_底稿'!$F:$F,'渠道充值成功率_底稿'!$A:$A,$B5,'渠道充值成功率_底稿'!$B:$B,I$4) -> 0 | J6: =SUMIFS('渠道充值成功率_底稿'!$F:$F,'渠道充值成功率_底稿'!$A:$A,$B5,'渠道充值成功率_底稿'!$B:$B,J$4) -> 0 | K6: =SUMIFS('渠道充值成功率_底稿'!$F:$F,'渠道充值成功率_底稿'!$A:$A,$B5,'渠道充值成功率_底稿'!$B:$B,K$4) -> 16 | L6: =SUMIFS('渠道充值成功率_底稿'!$F:$F,'渠道充值成功率_底稿'!$A:$A,$B5,'渠道充值成功率_底稿'!$B:$B,L$4) -> 0 | M6: =SUM(D6:L6) -> 3444 | N6: =M6-M14 -> 3113
C7: 笔数成功率 | D7: =IFERROR(ROUND(D6/D5,6),"0") -> 0.754685 | E7: =IFERROR(ROUND(E6/E5,6),"0") -> 0.857955 | F7: =IFERROR(ROUND(F6/F5,6),"0") -> 0.554622 | G7: =IFERROR(ROUND(G6/G5,6),"0") -> 0.799672 | H7: =IFERROR(ROUND(H6/H5,6),"0") -> 0 | I7: =IFERROR(ROUND(I6/I5,6),"0") -> 0 | J7: =IFERROR(ROUND(J6/J5,6),"0") -> 0 | K7: =IFERROR(ROUND(K6/K5,6),"0") -> 0.941176 | L7: =IFERROR(ROUND(L6/L5,6),"0") -> 0 | M7: =M6/M5 -> 0.75493205 | N7: =M7-M15 -> -0.038832941
C8: 申请金额 | D8: =SUMIFS('渠道充值成功率_底稿'!$D:$D,'渠道充值成功率_底稿'!$A:$A,$B$2,'渠道充值成功率_底稿'!$B:$B,D$4) -> 594748 | E8: =SUMIFS('渠道充值成功率_底稿'!$D:$D,'渠道充值成功率_底稿'!$A:$A,$B$2,'渠道充值成功率_底稿'!$B:$B,E$4) -> 41417 | F8: =SUMIFS('渠道充值成功率_底稿'!$D:$D,'渠道充值成功率_底稿'!$A:$A,$B$2,'渠道充值成功率_底稿'!$B:$B,F$4) -> 45503 | G8: =SUMIFS('渠道充值成功率_底稿'!$D:$D,'渠道充值成功率_底稿'!$A:$A,$B$2,'渠道充值成功率_底稿'!$B:$B,G$4) -> 114956 | H8: =SUMIFS('渠道充值成功率_底稿'!$D:$D,'渠道充值成功率_底稿'!$A:$A,$B$2,'渠道充值成功率_底稿'!$B:$B,H$4) -> 0 | I8: =SUMIFS('渠道充值成功率_底稿'!$D:$D,'渠道充值成功率_底稿'!$A:$A,$B$2,'渠道充值成功率_底稿'!$B:$B,I$4) -> 0 | J8: =SUMIFS('渠道充值成功率_底稿'!$D:$D,'渠道充值成功率_底稿'!$A:$A,$B$2,'渠道充值成功率_底稿'!$B:$B,J$4) -> 0 | K8: =SUMIFS('渠道充值成功率_底稿'!$D:$D,'渠道充值成功率_底稿'!$A:$A,$B$2,'渠道充值成功率_底稿'!$B:$B,K$4) -> 3970 | L8: =SUMIFS('渠道充值成功率_底稿'!$D:$D,'渠道充值成功率_底稿'!$A:$A,$B$2,'渠道充值成功率_底稿'!$B:$B,L$4) -> 0 | M8: =SUM(D8:L8) -> 800594 | N8: =M8-M16 -> 738711
C9: 到账金额 | D9: =SUMIFS('渠道充值成功率_底稿'!$G:$G,'渠道充值成功率_底稿'!$A:$A,$B$2,'渠道充值成功率_底稿'!$B:$B,D$4) -> 393917 | E9: =SUMIFS('渠道充值成功率_底稿'!$G:$G,'渠道充值成功率_底稿'!$A:$A,$B$2,'渠道充值成功率_底稿'!$B:$B,E$4) -> 35097 | F9: =SUMIFS('渠道充值成功率_底稿'!$G:$G,'渠道充值成功率_底稿'!$A:$A,$B$2,'渠道充值成功率_底稿'!$B:$B,F$4) -> 26162 | G9: =SUMIFS('渠道充值成功率_底稿'!$G:$G,'渠道充值成功率_底稿'!$A:$A,$B$2,'渠道充值成功率_底稿'!$B:$B,G$4) -> 89690 | H9: =SUMIFS('渠道充值成功率_底稿'!$G:$G,'渠道充值成功率_底稿'!$A:$A,$B$2,'渠道充值成功率_底稿'!$B:$B,H$4) -> 0 | I9: =SUMIFS('渠道充值成功率_底稿'!$G:$G,'渠道充值成功率_底稿'!$A:$A,$B$2,'渠道充值成功率_底稿'!$B:$B,I$4) -> 0 | J9: =SUMIFS('渠道充值成功率_底稿'!$G:$G,'渠道充值成功率_底稿'!$A:$A,$B$2,'渠道充值成功率_底稿'!$B:$B,J$4) -> 0 | K9: =SUMIFS('渠道充值成功率_底稿'!$G:$G,'渠道充值成功率_底稿'!$A:$A,$B$2,'渠道充值成功率_底稿'!$B:$B,K$4) -> 3870 | L9: =SUMIFS('渠道充值成功率_底稿'!$G:$G,'渠道充值成功率_底稿'!$A:$A,$B$2,'渠道充值成功率_底稿'!$B:$B,L$4) -> 0 | M9: =SUM(D9:L9) -> 548736 | N9: =M9-M17 -> 498023
C10: 金额成功率 | D10: =IFERROR(ROUND(D9/D8,6),"0") -> 0.662326 | E10: =IFERROR(ROUND(E9/E8,6),"0") -> 0.847406 | F10: =IFERROR(ROUND(F9/F8,6),"0") -> 0.574951 | G10: =IFERROR(ROUND(G9/G8,6),"0") -> 0.780212 | H10: =IFERROR(ROUND(H9/H8,6),"0") -> 0 | I10: =IFERROR(ROUND(I9/I8,6),"0") -> 0 | J10: =IFERROR(ROUND(J9/J8,6),"0") -> 0 | K10: =IFERROR(ROUND(K9/K8,6),"0") -> 0.974811 | L10: =IFERROR(ROUND(L9/L8,6),"0") -> 0 | M10: =M9/M8 -> 0.68541108 | N10: =M10-M18 -> -0.134087
B12: Date | C12: jiliarena | D12: GCash | E12: QRPH | F12: GCashQR | G12: Maya | H12: GRABPAY | I12: Online Banking | J12: USDT | K12: GOTYME | L12: GCASHPAY | M12: 加总
B13: =B2-1 -> 46064 | C13: 申请笔数 | D13: =SUMIFS('渠道充值成功率_底稿'!$C:$C,'渠道充值成功率_底稿'!$A:$A,$B$13,'渠道充值成功率_底稿'!$B:$B,D$4) -> 336 | E13: =SUMIFS('渠道充值成功率_底稿'!$C:$C,'渠道充值成功率_底稿'!$A:$A,$B$13,'渠道充值成功率_底稿'!$B:$B,E$4) -> 15 | F13: =SUMIFS('渠道充值成功率_底稿'!$C:$C,'渠道充值成功率_底稿'!$A:$A,$B$13,'渠道充值成功率_底稿'!$B:$B,F$4) -> 7 | G13: =SUMIFS('渠道充值成功率_底稿'!$C:$C,'渠道充值成功率_底稿'!$A:$A,$B$13,'渠道充值成功率_底稿'!$B:$B,G$4) -> 57 | H13: =SUMIFS('渠道充值成功率_底稿'!$C:$C,'渠道充值成功率_底稿'!$A:$A,$B$13,'渠道充值成功率_底稿'!$B:$B,H$4) -> 0 | I13: =SUMIFS('渠道充值成功率_底稿'!$C:$C,'渠道充值成功率_底稿'!$A:$A,$B$13,'渠道充值成功率_底稿'!$B:$B,I$4) -> 0 | J13: =SUMIFS('渠道充值成功率_底稿'!$C:$C,'渠道充值成功率_底稿'!$A:$A,$B$13,'渠道充值成功率_底稿'!$B:$B,J$4) -> 0 | K13: =SUMIFS('渠道充值成功率_底稿'!$C:$C,'渠道充值成功率_底稿'!$A:$A,$B$13,'渠道充值成功率_底稿'!$B:$B,K$4) -> 2 | L13: =SUMIFS('渠道充值成功率_底稿'!$C:$C,'渠道充值成功率_底稿'!$A:$A,$B$13,'渠道充值成功率_底稿'!$B:$B,L$4) -> 0 | M13: =SUM(D13:L13) -> 417
C14: 到账笔数 | D14: =SUMIFS('渠道充值成功率_底稿'!$F:$F,'渠道充值成功率_底稿'!$A:$A,$B13,'渠道充值成功率_底稿'!$B:$B,D$4) -> 264 | E14: =SUMIFS('渠道充值成功率_底稿'!$F:$F,'渠道充值成功率_底稿'!$A:$A,$B13,'渠道充值成功率_底稿'!$B:$B,E$4) -> 14 | F14: =SUMIFS('渠道充值成功率_底稿'!$F:$F,'渠道充值成功率_底稿'!$A:$A,$B13,'渠道充值成功率_底稿'!$B:$B,F$4) -> 6 | G14: =SUMIFS('渠道充值成功率_底稿'!$F:$F,'渠道充值成功率_底稿'!$A:$A,$B13,'渠道充值成功率_底稿'!$B:$B,G$4) -> 45 | H14: =SUMIFS('渠道充值成功率_底稿'!$F:$F,'渠道充值成功率_底稿'!$A:$A,$B13,'渠道充值成功率_底稿'!$B:$B,H$4) -> 0 | I14: =SUMIFS('渠道充值成功率_底稿'!$F:$F,'渠道充值成功率_底稿'!$A:$A,$B13,'渠道充值成功率_底稿'!$B:$B,I$4) -> 0 | J14: =SUMIFS('渠道充值成功率_底稿'!$F:$F,'渠道充值成功率_底稿'!$A:$A,$B13,'渠道充值成功率_底稿'!$B:$B,J$4) -> 0 | K14: =SUMIFS('渠道充值成功率_底稿'!$F:$F,'渠道充值成功率_底稿'!$A:$A,$B13,'渠道充值成功率_底稿'!$B:$B,K$4) -> 2 | L14: =SUMIFS('渠道充值成功率_底稿'!$F:$F,'渠道充值成功率_底稿'!$A:$A,$B13,'渠道充值成功率_底稿'!$B:$B,L$4) -> 0 | M14: =SUM(D14:L14) -> 331
C15: 笔数成功率 | D15: =IFERROR(ROUND(D14/D13,6),"0") -> 0.785714 | E15: =IFERROR(ROUND(E14/E13,6),"0") -> 0.933333 | F15: =IFERROR(ROUND(F14/F13,6),"0") -> 0.857143 | G15: =IFERROR(ROUND(G14/G13,6),"0") -> 0.789474 | H15: =IFERROR(ROUND(H14/H13,6),"0") -> 0 | I15: =IFERROR(ROUND(I14/I13,6),"0") -> 0 | J15: =IFERROR(ROUND(J14/J13,6),"0") -> 0 | K15: =IFERROR(ROUND(K14/K13,6),"0") -> 1 | L15: =IFERROR(ROUND(L14/L13,6),"0") -> 0 | M15: =M14/M13 -> 0.79376499
C16: 申请金额 | D16: =SUMIFS('渠道充值成功率_底稿'!$D:$D,'渠道充值成功率_底稿'!$A:$A,$B$13,'渠道充值成功率_底稿'!$B:$B,D$4) -> 45098 | E16: =SUMIFS('渠道充值成功率_底稿'!$D:$D,'渠道充值成功率_底稿'!$A:$A,$B$13,'渠道充值成功率_底稿'!$B:$B,E$4) -> 9270 | F16: =SUMIFS('渠道充值成功率_底稿'!$D:$D,'渠道充值成功率_底稿'!$A:$A,$B$13,'渠道充值成功率_底稿'!$B:$B,F$4) -> 700 | G16: =SUMIFS('渠道充值成功率_底稿'!$D:$D,'渠道充值成功率_底稿'!$A:$A,$B$13,'渠道充值成功率_底稿'!$B:$B,G$4) -> 6415 | H16: =SUMIFS('渠道充值成功率_底稿'!$D:$D,'渠道充值成功率_底稿'!$A:$A,$B$13,'渠道充值成功率_底稿'!$B:$B,H$4) -> 0 | I16: =SUMIFS('渠道充值成功率_底稿'!$D:$D,'渠道充值成功率_底稿'!$A:$A,$B$13,'渠道充值成功率_底稿'!$B:$B,I$4) -> 0 | J16: =SUMIFS('渠道充值成功率_底稿'!$D:$D,'渠道充值成功率_底稿'!$A:$A,$B$13,'渠道充值成功率_底稿'!$B:$B,J$4) -> 0 | K16: =SUMIFS('渠道充值成功率_底稿'!$D:$D,'渠道充值成功率_底稿'!$A:$A,$B$13,'渠道充值成功率_底稿'!$B:$B,K$4) -> 400 | L16: =SUMIFS('渠道充值成功率_底稿'!$D:$D,'渠道充值成功率_底稿'!$A:$A,$B$13,'渠道充值成功率_底稿'!$B:$B,L$4) -> 0 | M16: =SUM(D16:L16) -> 61883
C17: 到账金额 | D17: =SUMIFS('渠道充值成功率_底稿'!$G:$G,'渠道充值成功率_底稿'!$A:$A,$B$13,'渠道充值成功率_底稿'!$B:$B,D$4) -> 34978 | E17: =SUMIFS('渠道充值成功率_底稿'!$G:$G,'渠道充值成功率_底稿'!$A:$A,$B$13,'渠道充值成功率_底稿'!$B:$B,E$4) -> 9070 | F17: =SUMIFS('渠道充值成功率_底稿'!$G:$G,'渠道充值成功率_底稿'!$A:$A,$B$13,'渠道充值成功率_底稿'!$B:$B,F$4) -> 600 | G17: =SUMIFS('渠道充值成功率_底稿'!$G:$G,'渠道充值成功率_底稿'!$A:$A,$B$13,'渠道充值成功率_底稿'!$B:$B,G$4) -> 5665 | H17: =SUMIFS('渠道充值成功率_底稿'!$G:$G,'渠道充值成功率_底稿'!$A:$A,$B$13,'渠道充值成功率_底稿'!$B:$B,H$4) -> 0 | I17: =SUMIFS('渠道充值成功率_底稿'!$G:$G,'渠道充值成功率_底稿'!$A:$A,$B$13,'渠道充值成功率_底稿'!$B:$B,I$4) -> 0 | J17: =SUMIFS('渠道充值成功率_底稿'!$G:$G,'渠道充值成功率_底稿'!$A:$A,$B$13,'渠道充值成功率_底稿'!$B:$B,J$4) -> 0 | K17: =SUMIFS('渠道充值成功率_底稿'!$G:$G,'渠道充值成功率_底稿'!$A:$A,$B$13,'渠道充值成功率_底稿'!$B:$B,K$4) -> 400 | L17: =SUMIFS('渠道充值成功率_底稿'!$G:$G,'渠道充值成功率_底稿'!$A:$A,$B$13,'渠道充值成功率_底稿'!$B:$B,L$4) -> 0 | M17: =SUM(D17:L17) -> 50713
C18: 金额成功率 | D18: =IFERROR(ROUND(D17/D16,6),"0") -> 0.7756 | E18: =IFERROR(ROUND(E17/E16,6),"0") -> 0.978425 | F18: =IFERROR(ROUND(F17/F16,6),"0") -> 0.857143 | G18: =IFERROR(ROUND(G17/G16,6),"0") -> 0.883087 | H18: =IFERROR(ROUND(H17/H16,6),"0") -> 0 | I18: =IFERROR(ROUND(I17/I16,6),"0") -> 0 | J18: =IFERROR(ROUND(J17/J16,6),"0") -> 0 | K18: =IFERROR(ROUND(K17/K16,6),"0") -> 1 | L18: =IFERROR(ROUND(L17/L16,6),"0") -> 0 | M18: =M17/M16 -> 0.81949809
B22: =MONTH(B2)&"/"&DAY(B2) &" WP充值分析" -> 2/12 WP充值分析
B24: ="总充值申请笔数："&TEXT($M$5,"0,000") -> 总充值申请笔数：4,562
B25: ="总充值到帐笔数："&TEXT($M$6,"0,000") -> 总充值到帐笔数：3,444
B26: ="总笔数成功率："&TEXT($M$6/$M$5,"0.00%") -> 总笔数成功率：75.49%
B27: ="总充值申请金额："&TEXT($M$8,"0,000") -> 总充值申请金额：800,594
B28: ="总充值到帐金额："&TEXT($M$9,"0,000") -> 总充值到帐金额：548,736
B29: ="总笔数成功率："&TEXT($M$9/$M$8,"0.00%") -> 总笔数成功率：68.54%
B30: ="总充值申请人数："&text(sumifs('渠道充值成功率_底稿'!$E:$E,'渠道充值成功率_底稿'!$A:$A,$B$2),"0,000") -> 总充值申请人数：3,007
B31: ="总充值到帐人数："&text(sumifs('渠道充值成功率_底稿'!$H:$H,'渠道充值成功率_底稿'!$A:$A,$B$2),"0,000") -> 总充值到帐人数：2,799
B34: ="对比前日充值申请笔数"&IF(M6-M14>0,"增长："&TEXT(M5-M13,"000"),"减少："&TEXT(M5-M13,"000")) -> 对比前日充值申请笔数增长：4145
B35: ="对比前日充值到帐笔数"&IF(M6-M14>0,"增长："&TEXT(M6-M14,"000"),"减少："&TEXT(M6-M14,"000")) -> 对比前日充值到帐笔数增长：3113
B36: ="对比前日充值申请金额"&IF(M9-M17>0,"增长："&TEXT(M8-M16,"0,000"),"减少："&TEXT(M8-M16,"0,000")) -> 对比前日充值申请金额增长：738,711
B37: ="对比前日充值到帐金额"&IF(M9-M17>0,"增长："&TEXT(M9-M17,"0,000"),"减少："&TEXT(M9-M17,"0,000")) -> 对比前日充值到帐金额增长：498,023
B38: ="对比前日充值金额成功率"&IF(((M9/M8)-(M17/M16))>0,"增长："&TEXT(((M9/M8)-(M17/M16)),"0.00%"),"减少："&TEXT(((M9/M8)-(M17/M16)),"0.00%")) -> 对比前日充值金额成功率减少：-13.41%
B39: ="对比前日充值申请人数"&text(if(sumifs('渠道充值成功率_底稿'!$E:$E,'渠道充值成功率_底稿'!$A:$A,$B$2)-sumifs('渠道充值成功率_底稿'!$E:$E,'渠道充值成功率_底稿'!$A:$A,($B$2-1))>0,"增加："&sumifs('渠道充值成功率_底稿'!$E:$E,'渠道充值成功率_底稿'!$A:$A,$B$2)-sumifs('渠道充值成功率_底稿'!$E:$E,'渠道充值成功率_底稿'!$A:$A,($B$2-1)),"减少："&sumifs('渠道充值成功率_底稿'!$E:$E,'渠道充值成功率_底稿'!$A:$A,$B$2)-sumifs('渠道充值成功率_底稿'!$E:$E,'渠道充值成功率_底稿'!$A:$A,($B$2-1))),"0,000") -> 对比前日充值申请人数增加：2681
B40: ="对比前日充值到帐人数"&text(if(sumifs('渠道充值成功率_底稿'!$H:$H,'渠道充值成功率_底稿'!$A:$A,$B$2)-sumifs('渠道充值成功率_底稿'!$H:$H,'渠道充值成功率_底稿'!$A:$A,($B$2-1))>0,"增加："&sumifs('渠道充值成功率_底稿'!$H:$H,'渠道充值成功率_底稿'!$A:$A,$B$2)-sumifs('渠道充值成功率_底稿'!$H:$H,'渠道充值成功率_底稿'!$A:$A,($B$2-1)),"减少："&sumifs('渠道充值成功率_底稿'!$H:$H,'渠道充值成功率_底稿'!$A:$A,$B$2)-sumifs('渠道充值成功率_底稿'!$H:$H,'渠道充值成功率_底稿'!$A:$A,($B$2-1))),"0,000") -> 对比前日充值到帐人数增加：2504
B42: {="主要充值金额渠道："&index($C$4:$L$10,1,match(max($C$9:$L$9),C9:L9,0))} -> 主要充值金额渠道：GCash | G42: {=index($C$4:$L$10,1,match(max($C$9:$L$9),C9:L9,0))} -> GCash
B43: ="充值金额："&text(max($C$9:$L9),"0,000") -> 充值金额：393,917
B44: {="充值笔数："&text(index($C$4:$L$10,3,match(G42,$C$4:$L$4,0)),"0,000")} -> 充值笔数：2,658
B45: {="成功率："&text(index($C$4:$L$10,7,match(G42,$C$4:$L$4,0)),"0.00%")} -> 成功率：66.23%
B46: {="充值成功率最低渠道："&index($C$4:$L$10,1,match(MIN($C$9:$L$9),C9:L9,0))} -> 充值成功率最低渠道：GRABPAY | G46: {=index($C$4:$L$10,1,match(MIN($C$9:$L$9),C9:L9,0))} -> GRABPAY
B47: ="充值金额："&text(MIN($C$9:$L9),"0,000") -> 充值金额：0,000
B48: {="充值笔数："&text(index($C$4:$L$10,3,match(G46,$C$4:$L$4,0)),"0,000")} -> 充值笔数：0,000
B49: {="成功率："&text(index($C$4:$L$10,7,match(G46,$C$4:$L$4,0)),"0.00%")} -> 成功率：0.00%
A82: =MONTH(B2)&"月"&DAY(B2) &"日"&" jiliarena 活动红利分析" -> 2月12日 jiliarena 活动红利分析
A83: 序号 | B83: 活动名称 | C83: 活动类型 | D83: 笔数 | E83: 人数 | F83: 充值金額 | G83: 总充值占比 | H83: 活动金额 | I83: 活动占比 | J83: 活动/投注 % | K83: 活动/充值 % | L83: 活动/亏损 % | N83: 活动细项 | O83: 活动金额 | P83: 笔数 | Q83: 人数
A84: 1 | B84: 玩家返水 | C84: 返水 | D84: =SUM(D85:D90) -> 108 | E84: =SUM(E85:E90) -> 108 | F84: =IF(SUM(F85:F90)=0,"",SUM(F85:F90)) | G84: {=if(F84="","",(F84/index(jiliarena!$A$4:$M$39,match($B$2,jiliarena!$A$4:$A$39,0),match("总存款额度 total deposit amount",jiliarena!$A$4:$M$4,0))))} | H84: =SUM(H85:H90) -> 245.67 | I84: =SUM(I85:I90) -> 0.00041490692 | J84: =SUM(J85:J90) -> 3.0420458e-05 | K84: =SUM(K85:K90) -> 0.00044770163 | L84: =SUM(L85:L90) -> 0.00095188569 | N84: RNG Rebate | O84: =sumifs($H$83:$H$126,$B$83:$B$126,N84) -> 239.87 | P84: =sumifs($D$83:$D$126,$B$83:$B$126,$N84) -> 107 | Q84: =sumifs($E$83:$E$126,$B$83:$B$126,$N84) -> 107
B85: RNG Rebate | C85: 返水 | D85: =SUMIFS('jiliarena_活动分析数据_底稿'!$F:$F,'jiliarena_活动分析数据_底稿'!$C:$C,B85,'jiliarena_活动分析数据_底稿'!$B:$B,$B$2) -> 107 | E85: =SUMIFS('jiliarena_活动分析数据_底稿'!$G:$G,'jiliarena_活动分析数据_底稿'!$B:$B,$B$2,'jiliarena_活动分析数据_底稿'!$C:$C,B85) -> 107 | F85: =if(sumifs('jiliarena_活动分析数据_底稿'!$V:$V,'jiliarena_活动分析数据_底稿'!$T:$T,$B$2,'jiliarena_活动分析数据_底稿'!$U:$U,B85)=0,"",sumifs('jiliarena_活动分析数据_底稿'!$V:$V,'jiliarena_活动分析数据_底稿'!$T:$T,$B$2,'jiliarena_活动分析数据_底稿'!$U:$U,B85)) | G85: {=if(F85="","",(F85/index(jiliarena!$A$4:$M$39,match($B$2,jiliarena!$A$4:$A$39,0),match("总存款额度 total deposit amount",jiliarena!$A$4:$M$4,0))))} | H85: =sumifs('jiliarena_活动分析数据_底稿'!$K:$K,'jiliarena_活动分析数据_底稿'!$B:$B,$B$2,'jiliarena_活动分析数据_底稿'!$C:$C,B85) -> 239.87 | I85: {=H85/INDEX(jiliarena!$A$4:$BQ$39,MATCH($B$2,jiliarena!$A$4:$A$39,0),MATCH("总优惠 （Z+...+AH） Total Bonus",jiliarena!$4:$4,0))} -> 0.00040511143 | J85: {=$H85/index(jiliarena!$A$4:$Z$39,match($B$2,jiliarena!$A$4:$A$39,0),match("有效投注额 Valid bet",jiliarena!$A$4:$Z$4,0))} -> 2.9702264e-05 | K85: {=$H85/index(jiliarena!$A$4:$Z$39,match($B$2,jiliarena!$A$4:$A$39,0),match("总存款额度 total deposit amount",jiliarena!$A$4:$Z$4,0))} -> 0.00043713188 | L85: {=$H85/index(jiliarena!$A$4:$Z$39,match($B$2,jiliarena!$A$4:$A$39,0),match("公司输赢 Win or lose",jiliarena!$A$4:$Z$4,0))} -> 0.00092941271 | N85: LIVE Rebate | O85: =sumifs($H$83:$H$126,$B$83:$B$126,N85) -> 5.8 | P85: =sumifs($D$83:$D$126,$B$83:$B$126,$N85) -> 1 | Q85: =sumifs($E$83:$E$126,$B$83:$B$126,$N85) -> 1
B86: LIVE Rebate | D86: =SUMIFS('jiliarena_活动分析数据_底稿'!$F:$F,'jiliarena_活动分析数据_底稿'!$C:$C,B86,'jiliarena_活动分析数据_底稿'!$B:$B,$B$2) -> 1 | E86: =SUMIFS('jiliarena_活动分析数据_底稿'!$G:$G,'jiliarena_活动分析数据_底稿'!$B:$B,$B$2,'jiliarena_活动分析数据_底稿'!$C:$C,B86) -> 1 | F86: =if(sumifs('jiliarena_活动分析数据_底稿'!$V:$V,'jiliarena_活动分析数据_底稿'!$T:$T,$B$2,'jiliarena_活动分析数据_底稿'!$U:$U,B86)=0,"",sumifs('jiliarena_活动分析数据_底稿'!$V:$V,'jiliarena_活动分析数据_底稿'!$T:$T,$B$2,'jiliarena_活动分析数据_底稿'!$U:$U,B86)) | G86: {=if(F86="","",(F86/index(jiliarena!$A$4:$M$39,match($B$2,jiliarena!$A$4:$A$39,0),match("总存款额度 total deposit amount",jiliarena!$A$4:$M$4,0))))} | H86: =sumifs('jiliarena_活动分析数据_底稿'!$K:$K,'jiliarena_活动分析数据_底稿'!$B:$B,$B$2,'jiliarena_活动分析数据_底稿'!$C:$C,B86) -> 5.8 | I86: {=H86/INDEX(jiliarena!$A$4:$BQ$39,MATCH($B$2,jiliarena!$A$4:$A$39,0),MATCH("总优惠 （Z+...+AH） Total Bonus",jiliarena!$4:$4,0))} -> 9.7954987e-06 | J86: {=$H86/index(jiliarena!$A$4:$Z$39,match($B$2,jiliarena!$A$4:$A$39,0),match("有效投注额 Valid bet",jiliarena!$A$4:$Z$4,0))} -> 7.1819373e-07 | K86: {=$H86/index(jiliarena!$A$4:$Z$39,match($B$2,jiliarena!$A$4:$A$39,0),match("总存款额度 total deposit amount",jiliarena!$A$4:$Z$4,0))} -> 1.0569746e-05 | L86: {=$H86/index(jiliarena!$A$4:$Z$39,match($B$2,jiliarena!$A$4:$A$39,0),match("公司输赢 Win or lose",jiliarena!$A$4:$Z$4,0))} -> 2.247298e-05 | N86: PVP Rebate | O86: =sumifs($H$83:$H$126,$B$83:$B$126,N86) -> 0 | P86: =sumifs($D$83:$D$126,$B$83:$B$126,$N86) -> 0 | Q86: =sumifs($E$83:$E$126,$B$83:$B$126,$N86) -> 0
B87: PVP Rebate | D87: =SUMIFS('jiliarena_活动分析数据_底稿'!$F:$F,'jiliarena_活动分析数据_底稿'!$C:$C,B87,'jiliarena_活动分析数据_底稿'!$B:$B,$B$2) -> 0 | E87: =SUMIFS('jiliarena_活动分析数据_底稿'!$G:$G,'jiliarena_活动分析数据_底稿'!$B:$B,$B$2,'jiliarena_活动分析数据_底稿'!$C:$C,B87) -> 0 | F87: =if(sumifs('jiliarena_活动分析数据_底稿'!$V:$V,'jiliarena_活动分析数据_底稿'!$T:$T,$B$2,'jiliarena_活动分析数据_底稿'!$U:$U,B87)=0,"",sumifs('jiliarena_活动分析数据_底稿'!$V:$V,'jiliarena_活动分析数据_底稿'!$T:$T,$B$2,'jiliarena_活动分析数据_底稿'!$U:$U,B87)) | G87: {=if(F87="","",(F87/index(jiliarena!$A$4:$M$39,match($B$2,jiliarena!$A$4:$A$39,0),match("总存款额度 total deposit amount",jiliarena!$A$4:$M$4,0))))} | H87: =sumifs('jiliarena_活动分析数据_底稿'!$K:$K,'jiliarena_活动分析数据_底稿'!$B:$B,$B$2,'jiliarena_活动分析数据_底稿'!$C:$C,B87) -> 0 | I87: {=H87/INDEX(jiliarena!$A$4:$BQ$39,MATCH($B$2,jiliarena!$A$4:$A$39,0),MATCH("总优惠 （Z+...+AH） Total Bonus",jiliarena!$4:$4,0))} -> 0 | J87: {=$H87/index(jiliarena!$A$4:$Z$39,match($B$2,jiliarena!$A$4:$A$39,0),match("有效投注额 Valid bet",jiliarena!$A$4:$Z$4,0))} -> 0 | K87: {=$H87/index(jiliarena!$A$4:$Z$39,match($B$2,jiliarena!$A$4:$A$39,0),match("总存款额度 total deposit amount",jiliarena!$A$4:$Z$4,0))} -> 0 | L87: {=$H87/index(jiliarena!$A$4:$Z$39,match($B$2,jiliarena!$A$4:$A$39,0),match("公司输赢 Win or lose",jiliarena!$A$4:$Z$4,0))} -> 0 | N87: FISH Rebate | O87: =sumifs($H$83:$H$126,$B$83:$B$126,N87) -> 0 | P87: =sumifs($D$83:$D$126,$B$83:$B$126,$N87) -> 0 | Q87: =sumifs($E$83:$E$126,$B$83:$B$126,$N87) -> 0
B88: FISH Rebate | D88: =SUMIFS('jiliarena_活动分析数据_底稿'!$F:$F,'jiliarena_活动分析数据_底稿'!$C:$C,B88,'jiliarena_活动分析数据_底稿'!$B:$B,$B$2) -> 0 | E88: =SUMIFS('jiliarena_活动分析数据_底稿'!$G:$G,'jiliarena_活动分析数据_底稿'!$B:$B,$B$2,'jiliarena_活动分析数据_底稿'!$C:$C,B88) -> 0 | F88: =if(sumifs('jiliarena_活动分析数据_底稿'!$V:$V,'jiliarena_活动分析数据_底稿'!$T:$T,$B$2,'jiliarena_活动分析数据_底稿'!$U:$U,B88)=0,"",sumifs('jiliarena_活动分析数据_底稿'!$V:$V,'jiliarena_活动分析数据_底稿'!$T:$T,$B$2,'jiliarena_活动分析数据_底稿'!$U:$U,B88)) | G88: {=if(F88="","",(F88/index(jiliarena!$A$4:$M$39,match($B$2,jiliarena!$A$4:$A$39,0),match("总存款额度 total deposit amount",jiliarena!$A$4:$M$4,0))))} | H88: =sumifs('jiliarena_活动分析数据_底稿'!$K:$K,'jiliarena_活动分析数据_底稿'!$B:$B,$B$2,'jiliarena_活动分析数据_底稿'!$C:$C,B88) -> 0 | I88: {=H88/INDEX(jiliarena!$A$4:$BQ$39,MATCH($B$2,jiliarena!$A$4:$A$39,0),MATCH("总优惠 （Z+...+AH） Total Bonus",jiliarena!$4:$4,0))} -> 0 | J88: {=$H88/index(jiliarena!$A$4:$Z$39,match($B$2,jiliarena!$A$4:$A$39,0),match("有效投注额 Valid bet",jiliarena!$A$4:$Z$4,0))} -> 0 | K88: {=$H88/index(jiliarena!$A$4:$Z$39,match($B$2,jiliarena!$A$4:$A$39,0),match("总存款额度 total deposit amount",jiliarena!$A$4:$Z$4,0))} -> 0 | L88: {=$H88/index(jiliarena!$A$4:$Z$39,match($B$2,jiliarena!$A$4:$A$39,0),match("公司输赢 Win or lose",jiliarena!$A$4:$Z$4,0))} -> 0 | N88: E-LOTTO Rebate | O88: =sumifs($H$83:$H$126,$B$83:$B$126,N88) -> 0 | P88: =sumifs($D$83:$D$126,$B$83:$B$126,$N88) -> 0 | Q88: =sumifs($E$83:$E$126,$B$83:$B$126,$N88) -> 0
B89: E-LOTTO Rebate | D89: =SUMIFS('jiliarena_活动分析数据_底稿'!$F:$F,'jiliarena_活动分析数据_底稿'!$C:$C,B89,'jiliarena_活动分析数据_底稿'!$B:$B,$B$2) -> 0 | E89: =SUMIFS('jiliarena_活动分析数据_底稿'!$G:$G,'jiliarena_活动分析数据_底稿'!$B:$B,$B$2,'jiliarena_活动分析数据_底稿'!$C:$C,B89) -> 0 | F89: =if(sumifs('jiliarena_活动分析数据_底稿'!$V:$V,'jiliarena_活动分析数据_底稿'!$T:$T,$B$2,'jiliarena_活动分析数据_底稿'!$U:$U,B89)=0,"",sumifs('jiliarena_活动分析数据_底稿'!$V:$V,'jiliarena_活动分析数据_底稿'!$T:$T,$B$2,'jiliarena_活动分析数据_底稿'!$U:$U,B89)) | G89: {=if(F89="","",(F89/index(jiliarena!$A$4:$M$39,match($B$2,jiliarena!$A$4:$A$39,0),match("总存款额度 total deposit amount",jiliarena!$A$4:$M$4,0))))} | H89: =sumifs('jiliarena_活动分析数据_底稿'!$K:$K,'jiliarena_活动分析数据_底稿'!$B:$B,$B$2,'jiliarena_活动分析数据_底稿'!$C:$C,B89) -> 0 | I89: {=H89/INDEX(jiliarena!$A$4:$BQ$39,MATCH($B$2,jiliarena!$A$4:$A$39,0),MATCH("总优惠 （Z+...+AH） Total Bonus",jiliarena!$4:$4,0))} -> 0 | J89: {=$H89/index(jiliarena!$A$4:$Z$39,match($B$2,jiliarena!$A$4:$A$39,0),match("有效投注额 Valid bet",jiliarena!$A$4:$Z$4,0))} -> 0 | K89: {=$H89/index(jiliarena!$A$4:$Z$39,match($B$2,jiliarena!$A$4:$A$39,0),match("总存款额度 total deposit amount",jiliarena!$A$4:$Z$4,0))} -> 0 | L89: {=$H89/index(jiliarena!$A$4:$Z$39,match($B$2,jiliarena!$A$4:$A$39,0),match("公司输赢 Win or lose",jiliarena!$A$4:$Z$4,0))} -> 0 | N89: SPORTS Rebate | O89: =sumifs($H$83:$H$126,$B$83:$B$126,N89) -> 0 | P89: =sumifs($D$83:$D$126,$B$83:$B$126,$N89) -> 0 | Q89: =sumifs($E$83:$E$126,$B$83:$B$126,$N89) -> 0
B90: SPORTS Rebate | D90: =SUMIFS('jiliarena_活动分析数据_底稿'!$F:$F,'jiliarena_活动分析数据_底稿'!$C:$C,B90,'jiliarena_活动分析数据_底稿'!$B:$B,$B$2) -> 0 | E90: =SUMIFS('jiliarena_活动分析数据_底稿'!$G:$G,'jiliarena_活动分析数据_底稿'!$B:$B,$B$2,'jiliarena_活动分析数据_底稿'!$C:$C,B90) -> 0 | F90: =if(sumifs('jiliarena_活动分析数据_底稿'!$V:$V,'jiliarena_活动分析数据_底稿'!$T:$T,$B$2,'jiliarena_活动分析数据_底稿'!$U:$U,B90)=0,"",sumifs('jiliarena_活动分析数据_底稿'!$V:$V,'jiliarena_活动分析数据_底稿'!$T:$T,$B$2,'jiliarena_活动分析数据_底稿'!$U:$U,B90)) | G90: {=if(F90="","",(F90/index(jiliarena!$A$4:$M$39,match($B$2,jiliarena!$A$4:$A$39,0),match("总存款额度 total deposit amount",jiliarena!$A$4:$M$4,0))))} | H90: =sumifs('jiliarena_活动分析数据_底稿'!$K:$K,'jiliarena_活动分析数据_底稿'!$B:$B,$B$2,'jiliarena_活动分析数据_底稿'!$C:$C,B90) -> 0 | I90: {=H90/INDEX(jiliarena!$A$4:$BQ$39,MATCH($B$2,jiliarena!$A$4:$A$39,0),MATCH("总优惠 （Z+...+AH） Total Bonus",jiliarena!$4:$4,0))} -> 0 | J90: {=$H90/index(jiliarena!$A$4:$Z$39,match($B$2,jiliarena!$A$4:$A$39,0),match("有效投注额 Valid bet",jiliarena!$A$4:$Z$4,0))} -> 0 | K90: {=$H90/index(jiliarena!$A$4:$Z$39,match($B$2,jiliarena!$A$4:$A$39,0),match("总存款额度 total deposit amount",jiliarena!$A$4:$Z$4,0))} -> 0 | L90: {=$H90/index(jiliarena!$A$4:$Z$39,match($B$2,jiliarena!$A$4:$A$39,0),match("公司输赢 Win or lose",jiliarena!$A$4:$Z$4,0))} -> 0 | N90: 3% DEPOSIT BONUS | O90: =sumifs($H$83:$H$126,$B$83:$B$126,N90) -> 0 | P90: =sumifs($D$83:$D$126,$B$83:$B$126,$N90) -> 0 | Q90: =sumifs($E$83:$E$126,$B$83:$B$126,$N90) -> 0
A91: 2 | D91: =SUMIFS('jiliarena_活动分析数据_底稿'!$F:$F,'jiliarena_活动分析数据_底稿'!$C:$C,B91,'jiliarena_活动分析数据_底稿'!$B:$B,$B$2) -> 0 | E91: =SUMIFS('jiliarena_活动分析数据_底稿'!$G:$G,'jiliarena_活动分析数据_底稿'!$B:$B,$B$2,'jiliarena_活动分析数据_底稿'!$C:$C,B91) -> 0 | F91: =if(sumifs('jiliarena_活动分析数据_底稿'!$V:$V,'jiliarena_活动分析数据_底稿'!$T:$T,$B$2,'jiliarena_活动分析数据_底稿'!$U:$U,B91)=0,"",sumifs('jiliarena_活动分析数据_底稿'!$V:$V,'jiliarena_活动分析数据_底稿'!$T:$T,$B$2,'jiliarena_活动分析数据_底稿'!$U:$U,B91)) | G91: {=if(F91="","",(F91/index(jiliarena!$A$4:$M$39,match($B$2,jiliarena!$A$4:$A$39,0),match("总存款额度 total deposit amount",jiliarena!$A$4:$M$4,0))))} | H91: =sumifs('jiliarena_活动分析数据_底稿'!$K:$K,'jiliarena_活动分析数据_底稿'!$B:$B,$B$2,'jiliarena_活动分析数据_底稿'!$C:$C,B91) -> 0 | I91: {=H91/INDEX(jiliarena!$A$4:$BQ$39,MATCH($B$2,jiliarena!$A$4:$A$39,0),MATCH("总优惠 （Z+...+AH） Total Bonus",jiliarena!$4:$4,0))} -> 0 | J91: {=$H91/index(jiliarena!$A$4:$Z$39,match($B$2,jiliarena!$A$4:$A$39,0),match("有效投注额 Valid bet",jiliarena!$A$4:$Z$4,0))} -> 0 | K91: {=$H91/index(jiliarena!$A$4:$Z$39,match($B$2,jiliarena!$A$4:$A$39,0),match("总存款额度 total deposit amount",jiliarena!$A$4:$Z$4,0))} -> 0 | L91: {=$H91/index(jiliarena!$A$4:$Z$39,match($B$2,jiliarena!$A$4:$A$39,0),match("公司输赢 Win or lose",jiliarena!$A$4:$Z$4,0))} -> 0 | N91: 6% DEPOSIT BONUS | O91: =sumifs($H$83:$H$126,$B$83:$B$126,N91) -> 0 | P91: =sumifs($D$83:$D$126,$B$83:$B$126,$N91) -> 0 | Q91: =sumifs($E$83:$E$126,$B$83:$B$126,$N91) -> 0
A92: 3 | B92: 笔笔存送 | C92: 笔笔存送 | D92: =SUM(D93:D104) -> 0 | E92: =SUM(E93:E104) -> 0 | F92: =IF(SUM(F93:F104)=0,"",SUM(F93:F104)) | G92: =SUM(G93:G104) -> 0 | H92: =SUM(H93:H104) -> 0 | I92: =SUM(I93:I104) -> 0 | J92: =SUM(J93:J104) -> 0 | K92: =SUM(K93:K104) -> 0 | L92: =SUM(L93:L104) -> 0 | N92: 4% DEPOSIT BONUS | O92: =sumifs($H$83:$H$126,$B$83:$B$126,N92) -> 0 | P92: =sumifs($D$83:$D$126,$B$83:$B$126,$N92) -> 0 | Q92: =sumifs($E$83:$E$126,$B$83:$B$126,$N92) -> 0
B93: 3% DEPOSIT BONUS | C93: 存款奖金 | D93: =SUMIFS('jiliarena_活动分析数据_底稿'!$F:$F,'jiliarena_活动分析数据_底稿'!$C:$C,B93,'jiliarena_活动分析数据_底稿'!$B:$B,$B$2) -> 0 | E93: =SUMIFS('jiliarena_活动分析数据_底稿'!$G:$G,'jiliarena_活动分析数据_底稿'!$B:$B,$B$2,'jiliarena_活动分析数据_底稿'!$C:$C,B93) -> 0 | F93: =if(sumifs('jiliarena_活动分析数据_底稿'!$V:$V,'jiliarena_活动分析数据_底稿'!$T:$T,$B$2,'jiliarena_活动分析数据_底稿'!$U:$U,B93)=0,"",sumifs('jiliarena_活动分析数据_底稿'!$V:$V,'jiliarena_活动分析数据_底稿'!$T:$T,$B$2,'jiliarena_活动分析数据_底稿'!$U:$U,B93)) | G93: {=if(F93="","",(F93/index(jiliarena!$A$4:$M$39,match($B$2,jiliarena!$A$4:$A$39,0),match("总存款额度 total deposit amount",jiliarena!$A$4:$M$4,0))))} | H93: =sumifs('jiliarena_活动分析数据_底稿'!$K:$K,'jiliarena_活动分析数据_底稿'!$B:$B,$B$2,'jiliarena_活动分析数据_底稿'!$C:$C,B93) -> 0 | I93: {=H93/INDEX(jiliarena!$A$4:$BQ$39,MATCH($B$2,jiliarena!$A$4:$A$39,0),MATCH("总优惠 （Z+...+AH） Total Bonus",jiliarena!$4:$4,0))} -> 0 | J93: {=$H93/index(jiliarena!$A$4:$Z$39,match($B$2,jiliarena!$A$4:$A$39,0),match("有效投注额 Valid bet",jiliarena!$A$4:$Z$4,0))} -> 0 | K93: {=$H93/index(jiliarena!$A$4:$Z$39,match($B$2,jiliarena!$A$4:$A$39,0),match("总存款额度 total deposit amount",jiliarena!$A$4:$Z$4,0))} -> 0 | L93: {=$H93/index(jiliarena!$A$4:$Z$39,match($B$2,jiliarena!$A$4:$A$39,0),match("公司输赢 Win or lose",jiliarena!$A$4:$Z$4,0))} -> 0 | N93: GOTYME 5% DEPOSIT BONUS | O93: =sumifs($H$83:$H$126,$B$83:$B$126,N93) -> 0 | P93: =sumifs($D$83:$D$126,$B$83:$B$126,$N93) -> 0 | Q93: =sumifs($E$83:$E$126,$B$83:$B$126,$N93) -> 0
B94: 6% DEPOSIT BONUS | C94: 存款奖金 | D94: =SUMIFS('jiliarena_活动分析数据_底稿'!$F:$F,'jiliarena_活动分析数据_底稿'!$C:$C,B94,'jiliarena_活动分析数据_底稿'!$B:$B,$B$2) -> 0 | E94: =SUMIFS('jiliarena_活动分析数据_底稿'!$G:$G,'jiliarena_活动分析数据_底稿'!$B:$B,$B$2,'jiliarena_活动分析数据_底稿'!$C:$C,B94) -> 0 | F94: =if(sumifs('jiliarena_活动分析数据_底稿'!$V:$V,'jiliarena_活动分析数据_底稿'!$T:$T,$B$2,'jiliarena_活动分析数据_底稿'!$U:$U,B94)=0,"",sumifs('jiliarena_活动分析数据_底稿'!$V:$V,'jiliarena_活动分析数据_底稿'!$T:$T,$B$2,'jiliarena_活动分析数据_底稿'!$U:$U,B94)) | G94: {=if(F94="","",(F94/index(jiliarena!$A$4:$M$39,match($B$2,jiliarena!$A$4:$A$39,0),match("总存款额度 total deposit amount",jiliarena!$A$4:$M$4,0))))} | H94: =sumifs('jiliarena_活动分析数据_底稿'!$K:$K,'jiliarena_活动分析数据_底稿'!$B:$B,$B$2,'jiliarena_活动分析数据_底稿'!$C:$C,B94) -> 0 | I94: {=H94/INDEX(jiliarena!$A$4:$BQ$39,MATCH($B$2,jiliarena!$A$4:$A$39,0),MATCH("总优惠 （Z+...+AH） Total Bonus",jiliarena!$4:$4,0))} -> 0 | J94: {=$H94/index(jiliarena!$A$4:$Z$39,match($B$2,jiliarena!$A$4:$A$39,0),match("有效投注额 Valid bet",jiliarena!$A$4:$Z$4,0))} -> 0 | K94: {=$H94/index(jiliarena!$A$4:$Z$39,match($B$2,jiliarena!$A$4:$A$39,0),match("总存款额度 total deposit amount",jiliarena!$A$4:$Z$4,0))} -> 0 | L94: {=$H94/index(jiliarena!$A$4:$Z$39,match($B$2,jiliarena!$A$4:$A$39,0),match("公司输赢 Win or lose",jiliarena!$A$4:$Z$4,0))} -> 0 | N94: Daily Deposit 1000 Get 50 | O94: =sumifs($H$83:$H$126,$B$83:$B$126,N94) -> 0 | P94: =sumifs($D$83:$D$126,$B$83:$B$126,$N94) -> 0 | Q94: =sumifs($E$83:$E$126,$B$83:$B$126,$N94) -> 0
B95: 4% DEPOSIT BONUS | C95: 存款奖金 | D95: =SUMIFS('jiliarena_活动分析数据_底稿'!$F:$F,'jiliarena_活动分析数据_底稿'!$C:$C,B95,'jiliarena_活动分析数据_底稿'!$B:$B,$B$2) -> 0 | E95: =SUMIFS('jiliarena_活动分析数据_底稿'!$G:$G,'jiliarena_活动分析数据_底稿'!$B:$B,$B$2,'jiliarena_活动分析数据_底稿'!$C:$C,B95) -> 0 | F95: =if(sumifs('jiliarena_活动分析数据_底稿'!$V:$V,'jiliarena_活动分析数据_底稿'!$T:$T,$B$2,'jiliarena_活动分析数据_底稿'!$U:$U,B95)=0,"",sumifs('jiliarena_活动分析数据_底稿'!$V:$V,'jiliarena_活动分析数据_底稿'!$T:$T,$B$2,'jiliarena_活动分析数据_底稿'!$U:$U,B95)) | G95: {=if(F95="","",(F95/index(jiliarena!$A$4:$M$39,match($B$2,jiliarena!$A$4:$A$39,0),match("总存款额度 total deposit amount",jiliarena!$A$4:$M$4,0))))} | H95: =sumifs('jiliarena_活动分析数据_底稿'!$K:$K,'jiliarena_活动分析数据_底稿'!$B:$B,$B$2,'jiliarena_活动分析数据_底稿'!$C:$C,B95) -> 0 | I95: {=H95/INDEX(jiliarena!$A$4:$BQ$39,MATCH($B$2,jiliarena!$A$4:$A$39,0),MATCH("总优惠 （Z+...+AH） Total Bonus",jiliarena!$4:$4,0))} -> 0 | J95: {=$H95/index(jiliarena!$A$4:$Z$39,match($B$2,jiliarena!$A$4:$A$39,0),match("有效投注额 Valid bet",jiliarena!$A$4:$Z$4,0))} -> 0 | K95: {=$H95/index(jiliarena!$A$4:$Z$39,match($B$2,jiliarena!$A$4:$A$39,0),match("总存款额度 total deposit amount",jiliarena!$A$4:$Z$4,0))} -> 0 | L95: {=$H95/index(jiliarena!$A$4:$Z$39,match($B$2,jiliarena!$A$4:$A$39,0),match("公司输赢 Win or lose",jiliarena!$A$4:$Z$4,0))} -> 0 | N95: Daily Deposit 10000 Get 800 | O95: =sumifs($H$83:$H$126,$B$83:$B$126,N95) -> 0 | P95: =sumifs($D$83:$D$126,$B$83:$B$126,$N95) -> 0 | Q95: =sumifs($E$83:$E$126,$B$83:$B$126,$N95) -> 0
B96: GOTYME 5% DEPOSIT BONUS | C96: 存款奖金 | D96: =SUMIFS('jiliarena_活动分析数据_底稿'!$F:$F,'jiliarena_活动分析数据_底稿'!$C:$C,B96,'jiliarena_活动分析数据_底稿'!$B:$B,$B$2) -> 0 | E96: =SUMIFS('jiliarena_活动分析数据_底稿'!$G:$G,'jiliarena_活动分析数据_底稿'!$B:$B,$B$2,'jiliarena_活动分析数据_底稿'!$C:$C,B96) -> 0 | F96: =if(sumifs('jiliarena_活动分析数据_底稿'!$V:$V,'jiliarena_活动分析数据_底稿'!$T:$T,$B$2,'jiliarena_活动分析数据_底稿'!$U:$U,B96)=0,"",sumifs('jiliarena_活动分析数据_底稿'!$V:$V,'jiliarena_活动分析数据_底稿'!$T:$T,$B$2,'jiliarena_活动分析数据_底稿'!$U:$U,B96)) | G96: {=if(F96="","",(F96/index(jiliarena!$A$4:$M$39,match($B$2,jiliarena!$A$4:$A$39,0),match("总存款额度 total deposit amount",jiliarena!$A$4:$M$4,0))))} | H96: =sumifs('jiliarena_活动分析数据_底稿'!$K:$K,'jiliarena_活动分析数据_底稿'!$B:$B,$B$2,'jiliarena_活动分析数据_底稿'!$C:$C,B96) -> 0 | I96: {=H96/INDEX(jiliarena!$A$4:$BQ$39,MATCH($B$2,jiliarena!$A$4:$A$39,0),MATCH("总优惠 （Z+...+AH） Total Bonus",jiliarena!$4:$4,0))} -> 0 | J96: {=$H96/index(jiliarena!$A$4:$Z$39,match($B$2,jiliarena!$A$4:$A$39,0),match("有效投注额 Valid bet",jiliarena!$A$4:$Z$4,0))} -> 0 | K96: {=$H96/index(jiliarena!$A$4:$Z$39,match($B$2,jiliarena!$A$4:$A$39,0),match("总存款额度 total deposit amount",jiliarena!$A$4:$Z$4,0))} -> 0 | L96: {=$H96/index(jiliarena!$A$4:$Z$39,match($B$2,jiliarena!$A$4:$A$39,0),match("公司输赢 Win or lose",jiliarena!$A$4:$Z$4,0))} -> 0 | N96: Daily Deposit 3000 Get 150 | O96: =sumifs($H$83:$H$126,$B$83:$B$126,N96) -> 0 | P96: =sumifs($D$83:$D$126,$B$83:$B$126,$N96) -> 0 | Q96: =sumifs($E$83:$E$126,$B$83:$B$126,$N96) -> 0
B97: Daily Deposit 1000 Get 50 | C97: 每日存款返利 | D97: =SUMIFS('jiliarena_活动分析数据_底稿'!$F:$F,'jiliarena_活动分析数据_底稿'!$C:$C,B97,'jiliarena_活动分析数据_底稿'!$B:$B,$B$2) -> 0 | E97: =SUMIFS('jiliarena_活动分析数据_底稿'!$G:$G,'jiliarena_活动分析数据_底稿'!$B:$B,$B$2,'jiliarena_活动分析数据_底稿'!$C:$C,B97) -> 0 | F97: =if(sumifs('jiliarena_活动分析数据_底稿'!$V:$V,'jiliarena_活动分析数据_底稿'!$T:$T,$B$2,'jiliarena_活动分析数据_底稿'!$U:$U,B97)=0,"",sumifs('jiliarena_活动分析数据_底稿'!$V:$V,'jiliarena_活动分析数据_底稿'!$T:$T,$B$2,'jiliarena_活动分析数据_底稿'!$U:$U,B97)) | G97: {=if(F97="","",(F97/index(jiliarena!$A$4:$M$39,match($B$2,jiliarena!$A$4:$A$39,0),match("总存款额度 total deposit amount",jiliarena!$A$4:$M$4,0))))} | H97: =sumifs('jiliarena_活动分析数据_底稿'!$K:$K,'jiliarena_活动分析数据_底稿'!$B:$B,$B$2,'jiliarena_活动分析数据_底稿'!$C:$C,B97) -> 0 | I97: {=H97/INDEX(jiliarena!$A$4:$BQ$39,MATCH($B$2,jiliarena!$A$4:$A$39,0),MATCH("总优惠 （Z+...+AH） Total Bonus",jiliarena!$4:$4,0))} -> 0 | J97: {=$H97/index(jiliarena!$A$4:$Z$39,match($B$2,jiliarena!$A$4:$A$39,0),match("有效投注额 Valid bet",jiliarena!$A$4:$Z$4,0))} -> 0 | K97: {=$H97/index(jiliarena!$A$4:$Z$39,match($B$2,jiliarena!$A$4:$A$39,0),match("总存款额度 total deposit amount",jiliarena!$A$4:$Z$4,0))} -> 0 | L97: {=$H97/index(jiliarena!$A$4:$Z$39,match($B$2,jiliarena!$A$4:$A$39,0),match("公司输赢 Win or lose",jiliarena!$A$4:$Z$4,0))} -> 0 | N97: Daily Deposit 500 Get 20 | O97: =sumifs($H$83:$H$126,$B$83:$B$126,N97) -> 0 | P97: =sumifs($D$83:$D$126,$B$83:$B$126,$N97) -> 0 | Q97: =sumifs($E$83:$E$126,$B$83:$B$126,$N97) -> 0
B98: Daily Deposit 10000 Get 800 | C98: 每日存款返利 | D98: =SUMIFS('jiliarena_活动分析数据_底稿'!$F:$F,'jiliarena_活动分析数据_底稿'!$C:$C,B98,'jiliarena_活动分析数据_底稿'!$B:$B,$B$2) -> 0 | E98: =SUMIFS('jiliarena_活动分析数据_底稿'!$G:$G,'jiliarena_活动分析数据_底稿'!$B:$B,$B$2,'jiliarena_活动分析数据_底稿'!$C:$C,B98) -> 0 | F98: =if(sumifs('jiliarena_活动分析数据_底稿'!$V:$V,'jiliarena_活动分析数据_底稿'!$T:$T,$B$2,'jiliarena_活动分析数据_底稿'!$U:$U,B98)=0,"",sumifs('jiliarena_活动分析数据_底稿'!$V:$V,'jiliarena_活动分析数据_底稿'!$T:$T,$B$2,'jiliarena_活动分析数据_底稿'!$U:$U,B98)) | G98: {=if(F98="","",(F98/index(jiliarena!$A$4:$M$39,match($B$2,jiliarena!$A$4:$A$39,0),match("总存款额度 total deposit amount",jiliarena!$A$4:$M$4,0))))} | H98: =sumifs('jiliarena_活动分析数据_底稿'!$K:$K,'jiliarena_活动分析数据_底稿'!$B:$B,$B$2,'jiliarena_活动分析数据_底稿'!$C:$C,B98) -> 0 | I98: {=H98/INDEX(jiliarena!$A$4:$BQ$39,MATCH($B$2,jiliarena!$A$4:$A$39,0),MATCH("总优惠 （Z+...+AH） Total Bonus",jiliarena!$4:$4,0))} -> 0 | J98: {=$H98/index(jiliarena!$A$4:$Z$39,match($B$2,jiliarena!$A$4:$A$39,0),match("有效投注额 Valid bet",jiliarena!$A$4:$Z$4,0))} -> 0 | K98: {=$H98/index(jiliarena!$A$4:$Z$39,match($B$2,jiliarena!$A$4:$A$39,0),match("总存款额度 total deposit amount",jiliarena!$A$4:$Z$4,0))} -> 0 | L98: {=$H98/index(jiliarena!$A$4:$Z$39,match($B$2,jiliarena!$A$4:$A$39,0),match("公司输赢 Win or lose",jiliarena!$A$4:$Z$4,0))} -> 0 | N98: Daily Deposit 5000 Get 300 | O98: =sumifs($H$83:$H$126,$B$83:$B$126,N98) -> 0 | P98: =sumifs($D$83:$D$126,$B$83:$B$126,$N98) -> 0 | Q98: =sumifs($E$83:$E$126,$B$83:$B$126,$N98) -> 0
B99: Daily Deposit 3000 Get 150 | C99: 每日存款返利 | D99: =SUMIFS('jiliarena_活动分析数据_底稿'!$F:$F,'jiliarena_活动分析数据_底稿'!$C:$C,B99,'jiliarena_活动分析数据_底稿'!$B:$B,$B$2) -> 0 | E99: =SUMIFS('jiliarena_活动分析数据_底稿'!$G:$G,'jiliarena_活动分析数据_底稿'!$B:$B,$B$2,'jiliarena_活动分析数据_底稿'!$C:$C,B99) -> 0 | F99: =if(sumifs('jiliarena_活动分析数据_底稿'!$V:$V,'jiliarena_活动分析数据_底稿'!$T:$T,$B$2,'jiliarena_活动分析数据_底稿'!$U:$U,B99)=0,"",sumifs('jiliarena_活动分析数据_底稿'!$V:$V,'jiliarena_活动分析数据_底稿'!$T:$T,$B$2,'jiliarena_活动分析数据_底稿'!$U:$U,B99)) | G99: {=if(F99="","",(F99/index(jiliarena!$A$4:$M$39,match($B$2,jiliarena!$A$4:$A$39,0),match("总存款额度 total deposit amount",jiliarena!$A$4:$M$4,0))))} | H99: =sumifs('jiliarena_活动分析数据_底稿'!$K:$K,'jiliarena_活动分析数据_底稿'!$B:$B,$B$2,'jiliarena_活动分析数据_底稿'!$C:$C,B99) -> 0 | I99: {=H99/INDEX(jiliarena!$A$4:$BQ$39,MATCH($B$2,jiliarena!$A$4:$A$39,0),MATCH("总优惠 （Z+...+AH） Total Bonus",jiliarena!$4:$4,0))} -> 0 | J99: {=$H99/index(jiliarena!$A$4:$Z$39,match($B$2,jiliarena!$A$4:$A$39,0),match("有效投注额 Valid bet",jiliarena!$A$4:$Z$4,0))} -> 0 | K99: {=$H99/index(jiliarena!$A$4:$Z$39,match($B$2,jiliarena!$A$4:$A$39,0),match("总存款额度 total deposit amount",jiliarena!$A$4:$Z$4,0))} -> 0 | L99: {=$H99/index(jiliarena!$A$4:$Z$39,match($B$2,jiliarena!$A$4:$A$39,0),match("公司输赢 Win or lose",jiliarena!$A$4:$Z$4,0))} -> 0 | N99: 10% JL&PG SLOT Bonus | O99: =sumifs($H$83:$H$126,$B$83:$B$126,N99) -> 0 | P99: =sumifs($D$83:$D$126,$B$83:$B$126,$N99) -> 0 | Q99: =sumifs($E$83:$E$126,$B$83:$B$126,$N99) -> 0
B100: Daily Deposit 500 Get 20 | C100: 每日存款返利 | D100: =SUMIFS('jiliarena_活动分析数据_底稿'!$F:$F,'jiliarena_活动分析数据_底稿'!$C:$C,B100,'jiliarena_活动分析数据_底稿'!$B:$B,$B$2) -> 0 | E100: =SUMIFS('jiliarena_活动分析数据_底稿'!$G:$G,'jiliarena_活动分析数据_底稿'!$B:$B,$B$2,'jiliarena_活动分析数据_底稿'!$C:$C,B100) -> 0 | F100: =if(sumifs('jiliarena_活动分析数据_底稿'!$V:$V,'jiliarena_活动分析数据_底稿'!$T:$T,$B$2,'jiliarena_活动分析数据_底稿'!$U:$U,B100)=0,"",sumifs('jiliarena_活动分析数据_底稿'!$V:$V,'jiliarena_活动分析数据_底稿'!$T:$T,$B$2,'jiliarena_活动分析数据_底稿'!$U:$U,B100)) | G100: {=if(F100="","",(F100/index(jiliarena!$A$4:$M$39,match($B$2,jiliarena!$A$4:$A$39,0),match("总存款额度 total deposit amount",jiliarena!$A$4:$M$4,0))))} | H100: =sumifs('jiliarena_活动分析数据_底稿'!$K:$K,'jiliarena_活动分析数据_底稿'!$B:$B,$B$2,'jiliarena_活动分析数据_底稿'!$C:$C,B100) -> 0 | I100: {=H100/INDEX(jiliarena!$A$4:$BQ$39,MATCH($B$2,jiliarena!$A$4:$A$39,0),MATCH("总优惠 （Z+...+AH） Total Bonus",jiliarena!$4:$4,0))} -> 0 | J100: {=$H100/index(jiliarena!$A$4:$Z$39,match($B$2,jiliarena!$A$4:$A$39,0),match("有效投注额 Valid bet",jiliarena!$A$4:$Z$4,0))} -> 0 | K100: {=$H100/index(jiliarena!$A$4:$Z$39,match($B$2,jiliarena!$A$4:$A$39,0),match("总存款额度 total deposit amount",jiliarena!$A$4:$Z$4,0))} -> 0 | L100: {=$H100/index(jiliarena!$A$4:$Z$39,match($B$2,jiliarena!$A$4:$A$39,0),match("公司输赢 Win or lose",jiliarena!$A$4:$Z$4,0))} -> 0 | N100: 50% SATURDAY&SUNDAY DEPOSIT BONUS 2/7-2/8 | O100: =sumifs($H$83:$H$126,$B$83:$B$126,N100) -> 0 | P100: =sumifs($D$83:$D$126,$B$83:$B$126,$N100) -> 0 | Q100: =sumifs($E$83:$E$126,$B$83:$B$126,$N100) -> 0
B101: Daily Deposit 5000 Get 300 | C101: 每日存款返利 | D101: =SUMIFS('jiliarena_活动分析数据_底稿'!$F:$F,'jiliarena_活动分析数据_底稿'!$C:$C,B101,'jiliarena_活动分析数据_底稿'!$B:$B,$B$2) -> 0 | E101: =SUMIFS('jiliarena_活动分析数据_底稿'!$G:$G,'jiliarena_活动分析数据_底稿'!$B:$B,$B$2,'jiliarena_活动分析数据_底稿'!$C:$C,B101) -> 0 | F101: =if(sumifs('jiliarena_活动分析数据_底稿'!$V:$V,'jiliarena_活动分析数据_底稿'!$T:$T,$B$2,'jiliarena_活动分析数据_底稿'!$U:$U,B101)=0,"",sumifs('jiliarena_活动分析数据_底稿'!$V:$V,'jiliarena_活动分析数据_底稿'!$T:$T,$B$2,'jiliarena_活动分析数据_底稿'!$U:$U,B101)) | G101: {=if(F101="","",(F101/index(jiliarena!$A$4:$M$39,match($B$2,jiliarena!$A$4:$A$39,0),match("总存款额度 total deposit amount",jiliarena!$A$4:$M$4,0))))} | H101: =sumifs('jiliarena_活动分析数据_底稿'!$K:$K,'jiliarena_活动分析数据_底稿'!$B:$B,$B$2,'jiliarena_活动分析数据_底稿'!$C:$C,B101) -> 0 | I101: {=H101/INDEX(jiliarena!$A$4:$BQ$39,MATCH($B$2,jiliarena!$A$4:$A$39,0),MATCH("总优惠 （Z+...+AH） Total Bonus",jiliarena!$4:$4,0))} -> 0 | J101: {=$H101/index(jiliarena!$A$4:$Z$39,match($B$2,jiliarena!$A$4:$A$39,0),match("有效投注额 Valid bet",jiliarena!$A$4:$Z$4,0))} -> 0 | K101: {=$H101/index(jiliarena!$A$4:$Z$39,match($B$2,jiliarena!$A$4:$A$39,0),match("总存款额度 total deposit amount",jiliarena!$A$4:$Z$4,0))} -> 0 | L101: {=$H101/index(jiliarena!$A$4:$Z$39,match($B$2,jiliarena!$A$4:$A$39,0),match("公司输赢 Win or lose",jiliarena!$A$4:$Z$4,0))} -> 0 | N101: 签到奖励 | O101: =sumifs($H$83:$H$126,$B$83:$B$126,N101) -> 8052 | P101: =sumifs($D$83:$D$126,$B$83:$B$126,$N101) -> 7460 | Q101: =sumifs($E$83:$E$126,$B$83:$B$126,$N101) -> 7460
B102: 10% JL&PG SLOT Bonus | C102: 老虎机奖金 | D102: =SUMIFS('jiliarena_活动分析数据_底稿'!$F:$F,'jiliarena_活动分析数据_底稿'!$C:$C,B102,'jiliarena_活动分析数据_底稿'!$B:$B,$B$2) -> 0 | E102: =SUMIFS('jiliarena_活动分析数据_底稿'!$G:$G,'jiliarena_活动分析数据_底稿'!$B:$B,$B$2,'jiliarena_活动分析数据_底稿'!$C:$C,B102) -> 0 | F102: =if(sumifs('jiliarena_活动分析数据_底稿'!$V:$V,'jiliarena_活动分析数据_底稿'!$T:$T,$B$2,'jiliarena_活动分析数据_底稿'!$U:$U,B102)=0,"",sumifs('jiliarena_活动分析数据_底稿'!$V:$V,'jiliarena_活动分析数据_底稿'!$T:$T,$B$2,'jiliarena_活动分析数据_底稿'!$U:$U,B102)) | G102: {=if(F102="","",(F102/index(jiliarena!$A$4:$M$39,match($B$2,jiliarena!$A$4:$A$39,0),match("总存款额度 total deposit amount",jiliarena!$A$4:$M$4,0))))} | H102: =sumifs('jiliarena_活动分析数据_底稿'!$K:$K,'jiliarena_活动分析数据_底稿'!$B:$B,$B$2,'jiliarena_活动分析数据_底稿'!$C:$C,B102) -> 0 | I102: {=H102/INDEX(jiliarena!$A$4:$BQ$39,MATCH($B$2,jiliarena!$A$4:$A$39,0),MATCH("总优惠 （Z+...+AH） Total Bonus",jiliarena!$4:$4,0))} -> 0 | J102: {=$H102/index(jiliarena!$A$4:$Z$39,match($B$2,jiliarena!$A$4:$A$39,0),match("有效投注额 Valid bet",jiliarena!$A$4:$Z$4,0))} -> 0 | K102: {=$H102/index(jiliarena!$A$4:$Z$39,match($B$2,jiliarena!$A$4:$A$39,0),match("总存款额度 total deposit amount",jiliarena!$A$4:$Z$4,0))} -> 0 | L102: {=$H102/index(jiliarena!$A$4:$Z$39,match($B$2,jiliarena!$A$4:$A$39,0),match("公司输赢 Win or lose",jiliarena!$A$4:$Z$4,0))} -> 0 | N102: 升级奖励 | O102: =sumifs($H$83:$H$126,$B$83:$B$126,N102) -> 902 | P102: =sumifs($D$83:$D$126,$B$83:$B$126,$N102) -> 630 | Q102: =sumifs($E$83:$E$126,$B$83:$B$126,$N102) -> 501
D103: =SUMIFS('jiliarena_活动分析数据_底稿'!$F:$F,'jiliarena_活动分析数据_底稿'!$C:$C,B103,'jiliarena_活动分析数据_底稿'!$B:$B,$B$2) -> 0 | E103: =SUMIFS('jiliarena_活动分析数据_底稿'!$G:$G,'jiliarena_活动分析数据_底稿'!$B:$B,$B$2,'jiliarena_活动分析数据_底稿'!$C:$C,B103) -> 0 | F103: =if(sumifs('jiliarena_活动分析数据_底稿'!$V:$V,'jiliarena_活动分析数据_底稿'!$T:$T,$B$2,'jiliarena_活动分析数据_底稿'!$U:$U,B103)=0,"",sumifs('jiliarena_活动分析数据_底稿'!$V:$V,'jiliarena_活动分析数据_底稿'!$T:$T,$B$2,'jiliarena_活动分析数据_底稿'!$U:$U,B103)) | G103: {=if(F103="","",(F103/index(jiliarena!$A$4:$M$39,match($B$2,jiliarena!$A$4:$A$39,0),match("总存款额度 total deposit amount",jiliarena!$A$4:$M$4,0))))} | H103: =sumifs('jiliarena_活动分析数据_底稿'!$K:$K,'jiliarena_活动分析数据_底稿'!$B:$B,$B$2,'jiliarena_活动分析数据_底稿'!$C:$C,B103) -> 0 | I103: {=H103/INDEX(jiliarena!$A$4:$BQ$39,MATCH($B$2,jiliarena!$A$4:$A$39,0),MATCH("总优惠 （Z+...+AH） Total Bonus",jiliarena!$4:$4,0))} -> 0 | J103: {=$H103/index(jiliarena!$A$4:$Z$39,match($B$2,jiliarena!$A$4:$A$39,0),match("有效投注额 Valid bet",jiliarena!$A$4:$Z$4,0))} -> 0 | K103: {=$H103/index(jiliarena!$A$4:$Z$39,match($B$2,jiliarena!$A$4:$A$39,0),match("总存款额度 total deposit amount",jiliarena!$A$4:$Z$4,0))} -> 0 | L103: {=$H103/index(jiliarena!$A$4:$Z$39,match($B$2,jiliarena!$A$4:$A$39,0),match("公司输赢 Win or lose",jiliarena!$A$4:$Z$4,0))} -> 0 | N103: TG Lucky Balance Bonus | O103: =sumifs($H$83:$H$126,$B$83:$B$126,N103) -> 0 | P103: =sumifs($D$83:$D$126,$B$83:$B$126,$N103) -> 0 | Q103: =sumifs($E$83:$E$126,$B$83:$B$126,$N103) -> 0
D104: =SUMIFS('jiliarena_活动分析数据_底稿'!$F:$F,'jiliarena_活动分析数据_底稿'!$C:$C,B104,'jiliarena_活动分析数据_底稿'!$B:$B,$B$2) -> 0 | E104: =SUMIFS('jiliarena_活动分析数据_底稿'!$G:$G,'jiliarena_活动分析数据_底稿'!$B:$B,$B$2,'jiliarena_活动分析数据_底稿'!$C:$C,B104) -> 0 | F104: =if(sumifs('jiliarena_活动分析数据_底稿'!$V:$V,'jiliarena_活动分析数据_底稿'!$T:$T,$B$2,'jiliarena_活动分析数据_底稿'!$U:$U,B104)=0,"",sumifs('jiliarena_活动分析数据_底稿'!$V:$V,'jiliarena_活动分析数据_底稿'!$T:$T,$B$2,'jiliarena_活动分析数据_底稿'!$U:$U,B104)) | G104: {=if(F104="","",(F104/index(jiliarena!$A$4:$M$39,match($B$2,jiliarena!$A$4:$A$39,0),match("总存款额度 total deposit amount",jiliarena!$A$4:$M$4,0))))} | H104: =sumifs('jiliarena_活动分析数据_底稿'!$K:$K,'jiliarena_活动分析数据_底稿'!$B:$B,$B$2,'jiliarena_活动分析数据_底稿'!$C:$C,B104) -> 0 | I104: {=H104/INDEX(jiliarena!$A$4:$BQ$39,MATCH($B$2,jiliarena!$A$4:$A$39,0),MATCH("总优惠 （Z+...+AH） Total Bonus",jiliarena!$4:$4,0))} -> 0 | J104: {=$H104/index(jiliarena!$A$4:$Z$39,match($B$2,jiliarena!$A$4:$A$39,0),match("有效投注额 Valid bet",jiliarena!$A$4:$Z$4,0))} -> 0 | K104: {=$H104/index(jiliarena!$A$4:$Z$39,match($B$2,jiliarena!$A$4:$A$39,0),match("总存款额度 total deposit amount",jiliarena!$A$4:$Z$4,0))} -> 0 | L104: {=$H104/index(jiliarena!$A$4:$Z$39,match($B$2,jiliarena!$A$4:$A$39,0),match("公司输赢 Win or lose",jiliarena!$A$4:$Z$4,0))} -> 0 | N104: TG Daily Top-Up Leaderboard | O104: =sumifs($H$83:$H$126,$B$83:$B$126,N104) -> 0 | P104: =sumifs($D$83:$D$126,$B$83:$B$126,$N104) -> 0 | Q104: =sumifs($E$83:$E$126,$B$83:$B$126,$N104) -> 0
A105: 4 | B105: 签到奖励 | D105: =SUMIFS('jiliarena_活动分析数据_底稿'!$F:$F,'jiliarena_活动分析数据_底稿'!$C:$C,B105,'jiliarena_活动分析数据_底稿'!$B:$B,$B$2) -> 7460 | E105: =SUMIFS('jiliarena_活动分析数据_底稿'!$G:$G,'jiliarena_活动分析数据_底稿'!$B:$B,$B$2,'jiliarena_活动分析数据_底稿'!$C:$C,B105) -> 7460 | F105: =if(sumifs('jiliarena_活动分析数据_底稿'!$V:$V,'jiliarena_活动分析数据_底稿'!$T:$T,$B$2,'jiliarena_活动分析数据_底稿'!$U:$U,B105)=0,"",sumifs('jiliarena_活动分析数据_底稿'!$V:$V,'jiliarena_活动分析数据_底稿'!$T:$T,$B$2,'jiliarena_活动分析数据_底稿'!$U:$U,B105)) | G105: {=if(F105="","",(F105/index(jiliarena!$A$4:$M$39,match($B$2,jiliarena!$A$4:$A$39,0),match("总存款额度 total deposit amount",jiliarena!$A$4:$M$4,0))))} | H105: =sumifs('jiliarena_活动分析数据_底稿'!$K:$K,'jiliarena_活动分析数据_底稿'!$B:$B,$B$2,'jiliarena_活动分析数据_底稿'!$C:$C,B105) -> 8052 | I105: {=H105/INDEX(jiliarena!$A$4:$BQ$39,MATCH($B$2,jiliarena!$A$4:$A$39,0),MATCH("总优惠 （Z+...+AH） Total Bonus",jiliarena!$4:$4,0))} -> 0.013598854 | J105: {=$H105/index(jiliarena!$A$4:$Z$39,match($B$2,jiliarena!$A$4:$A$39,0),match("有效投注额 Valid bet",jiliarena!$A$4:$Z$4,0))} -> 0.00099705102 | K105: {=$H105/index(jiliarena!$A$4:$Z$39,match($B$2,jiliarena!$A$4:$A$39,0),match("总存款额度 total deposit amount",jiliarena!$A$4:$Z$4,0))} -> 0.014673723 | L105: {=$H105/index(jiliarena!$A$4:$Z$39,match($B$2,jiliarena!$A$4:$A$39,0),match("公司输赢 Win or lose",jiliarena!$A$4:$Z$4,0))} -> 0.031198696 | N105: TG rewards ranking | O105: =sumifs($H$83:$H$126,$B$83:$B$126,N105) -> 0 | P105: =sumifs($D$83:$D$126,$B$83:$B$126,$N105) -> 0 | Q105: =sumifs($E$83:$E$126,$B$83:$B$126,$N105) -> 0
A106: 5 | B106: 升级奖励 | D106: =SUMIFS('jiliarena_活动分析数据_底稿'!$F:$F,'jiliarena_活动分析数据_底稿'!$C:$C,B106,'jiliarena_活动分析数据_底稿'!$B:$B,$B$2) -> 630 | E106: =SUMIFS('jiliarena_活动分析数据_底稿'!$G:$G,'jiliarena_活动分析数据_底稿'!$B:$B,$B$2,'jiliarena_活动分析数据_底稿'!$C:$C,B106) -> 501 | F106: =if(sumifs('jiliarena_活动分析数据_底稿'!$V:$V,'jiliarena_活动分析数据_底稿'!$T:$T,$B$2,'jiliarena_活动分析数据_底稿'!$U:$U,B106)=0,"",sumifs('jiliarena_活动分析数据_底稿'!$V:$V,'jiliarena_活动分析数据_底稿'!$T:$T,$B$2,'jiliarena_活动分析数据_底稿'!$U:$U,B106)) | G106: {=if(F106="","",(F106/index(jiliarena!$A$4:$M$39,match($B$2,jiliarena!$A$4:$A$39,0),match("总存款额度 total deposit amount",jiliarena!$A$4:$M$4,0))))} | H106: =sumifs('jiliarena_活动分析数据_底稿'!$K:$K,'jiliarena_活动分析数据_底稿'!$B:$B,$B$2,'jiliarena_活动分析数据_底稿'!$C:$C,B106) -> 902 | I106: {=H106/INDEX(jiliarena!$A$4:$BQ$39,MATCH($B$2,jiliarena!$A$4:$A$39,0),MATCH("总优惠 （Z+...+AH） Total Bonus",jiliarena!$4:$4,0))} -> 0.0015233689 | J106: {=$H106/index(jiliarena!$A$4:$Z$39,match($B$2,jiliarena!$A$4:$A$39,0),match("投注 Betting",jiliarena!$A$4:$Z$4,0))} -> 0.00010333673 | K106: {=$H106/index(jiliarena!$A$4:$Z$39,match($B$2,jiliarena!$A$4:$A$39,0),match("总存款额度 total deposit amount",jiliarena!$A$4:$Z$4,0))} -> 0.0016437777 | L106: {=$H106/index(jiliarena!$A$4:$Z$39,match($B$2,jiliarena!$A$4:$A$39,0),match("公司输赢 Win or lose",jiliarena!$A$4:$Z$4,0))} -> 0.0034949358 | N106: TG Share Withdrawal screenshots | O106: =sumifs($H$83:$H$126,$B$83:$B$126,N106) -> 0 | P106: =sumifs($D$83:$D$126,$B$83:$B$126,$N106) -> 0 | Q106: =sumifs($E$83:$E$126,$B$83:$B$126,$N106) -> 0
A107: 6 | B107: 手动红利 | D107: =SUM(D108:D115) -> 0 | E107: =SUM(E108:E115) -> 0 | F107: =IF(SUM(F109:F115)=0,"",SUM(F109:F115)) | G107: =if(F107="","", SUM(G109:G115)) | H107: =SUM(H108:H115) -> 0 | I107: =SUM(I108:I115) -> 0 | J107: =SUM(J108:J115) -> 0 | K107: =SUM(K108:K115) -> 0 | L107: =SUM(L108:L115) -> 0 | O107: =sumifs($H$83:$H$126,$B$83:$B$126,N107) -> 0 | P107: =sumifs($D$83:$D$126,$B$83:$B$126,$N107) -> 0 | Q107: =sumifs($E$83:$E$126,$B$83:$B$126,$N107) -> 0
B108: TG Lucky Balance Bonus | C108: TG幸运余额奖励 | D108: =SUMIFS('jiliarena_活动分析数据_底稿'!$F:$F,'jiliarena_活动分析数据_底稿'!$C:$C,B108,'jiliarena_活动分析数据_底稿'!$B:$B,$B$2) -> 0 | E108: =SUMIFS('jiliarena_活动分析数据_底稿'!$G:$G,'jiliarena_活动分析数据_底稿'!$B:$B,$B$2,'jiliarena_活动分析数据_底稿'!$C:$C,B108) -> 0 | F108: =if(sumifs('jiliarena_活动分析数据_底稿'!$V:$V,'jiliarena_活动分析数据_底稿'!$T:$T,$B$2,'jiliarena_活动分析数据_底稿'!$U:$U,B108)=0,"",sumifs('jiliarena_活动分析数据_底稿'!$V:$V,'jiliarena_活动分析数据_底稿'!$T:$T,$B$2,'jiliarena_活动分析数据_底稿'!$U:$U,B108)) | G108: {=if(F108="","",(F108/index(jiliarena!$A$4:$M$39,match($B$2,jiliarena!$A$4:$A$39,0),match("总存款额度 total deposit amount",jiliarena!$A$4:$M$4,0))))} | H108: =sumifs('jiliarena_活动分析数据_底稿'!$K:$K,'jiliarena_活动分析数据_底稿'!$B:$B,$B$2,'jiliarena_活动分析数据_底稿'!$C:$C,B108) -> 0 | I108: {=H108/INDEX(jiliarena!$A$4:$BQ$39,MATCH($B$2,jiliarena!$A$4:$A$39,0),MATCH("总优惠 （Z+...+AH） Total Bonus",jiliarena!$4:$4,0))} -> 0 | J108: {=$H108/index(jiliarena!$A$4:$Z$39,match($B$2,jiliarena!$A$4:$A$39,0),match("有效投注额 Valid bet",jiliarena!$A$4:$Z$4,0))} -> 0 | K108: {=$H108/index(jiliarena!$A$4:$Z$39,match($B$2,jiliarena!$A$4:$A$39,0),match("总存款额度 total deposit amount",jiliarena!$A$4:$Z$4,0))} -> 0 | L108: {=$H108/index(jiliarena!$A$4:$Z$39,match($B$2,jiliarena!$A$4:$A$39,0),match("公司输赢 Win or lose",jiliarena!$A$4:$Z$4,0))} -> 0 | O108: =sumifs($H$83:$H$126,$B$83:$B$126,N108) -> 0 | P108: =sumifs($D$83:$D$126,$B$83:$B$126,$N108) -> 0 | Q108: =sumifs($E$83:$E$126,$B$83:$B$126,$N108) -> 0
B109: TG Daily Top-Up Leaderboard | C109: TG每日储值排行榜 | D109: =SUMIFS('jiliarena_活动分析数据_底稿'!$F:$F,'jiliarena_活动分析数据_底稿'!$C:$C,B109,'jiliarena_活动分析数据_底稿'!$B:$B,$B$2) -> 0 | E109: =SUMIFS('jiliarena_活动分析数据_底稿'!$G:$G,'jiliarena_活动分析数据_底稿'!$B:$B,$B$2,'jiliarena_活动分析数据_底稿'!$C:$C,B109) -> 0 | F109: =if(sumifs('jiliarena_活动分析数据_底稿'!$V:$V,'jiliarena_活动分析数据_底稿'!$T:$T,$B$2,'jiliarena_活动分析数据_底稿'!$U:$U,B109)=0,"",sumifs('jiliarena_活动分析数据_底稿'!$V:$V,'jiliarena_活动分析数据_底稿'!$T:$T,$B$2,'jiliarena_活动分析数据_底稿'!$U:$U,B109)) | G109: {=if(F109="","",(F109/index(jiliarena!$A$4:$M$39,match($B$2,jiliarena!$A$4:$A$39,0),match("总存款额度 total deposit amount",jiliarena!$A$4:$M$4,0))))} | H109: =sumifs('jiliarena_活动分析数据_底稿'!$K:$K,'jiliarena_活动分析数据_底稿'!$B:$B,$B$2,'jiliarena_活动分析数据_底稿'!$C:$C,B109) -> 0 | I109: {=H109/INDEX(jiliarena!$A$4:$BQ$39,MATCH($B$2,jiliarena!$A$4:$A$39,0),MATCH("总优惠 （Z+...+AH） Total Bonus",jiliarena!$4:$4,0))} -> 0 | J109: {=$H109/index(jiliarena!$A$4:$Z$39,match($B$2,jiliarena!$A$4:$A$39,0),match("有效投注额 Valid bet",jiliarena!$A$4:$Z$4,0))} -> 0 | K109: {=$H109/index(jiliarena!$A$4:$Z$39,match($B$2,jiliarena!$A$4:$A$39,0),match("总存款额度 total deposit amount",jiliarena!$A$4:$Z$4,0))} -> 0 | L109: {=$H109/index(jiliarena!$A$4:$Z$39,match($B$2,jiliarena!$A$4:$A$39,0),match("公司输赢 Win or lose",jiliarena!$A$4:$Z$4,0))} -> 0 | O109: =sumifs($H$83:$H$126,$B$83:$B$126,N109) -> 0 | P109: =sumifs($D$83:$D$126,$B$83:$B$126,$N109) -> 0 | Q109: =sumifs($E$83:$E$126,$B$83:$B$126,$N109) -> 0
B110: TG rewards ranking | C110: TG奖励排名 | D110: =SUMIFS('jiliarena_活动分析数据_底稿'!$F:$F,'jiliarena_活动分析数据_底稿'!$C:$C,B110,'jiliarena_活动分析数据_底稿'!$B:$B,$B$2) -> 0 | E110: =SUMIFS('jiliarena_活动分析数据_底稿'!$G:$G,'jiliarena_活动分析数据_底稿'!$B:$B,$B$2,'jiliarena_活动分析数据_底稿'!$C:$C,B110) -> 0 | F110: =if(sumifs('jiliarena_活动分析数据_底稿'!$V:$V,'jiliarena_活动分析数据_底稿'!$T:$T,$B$2,'jiliarena_活动分析数据_底稿'!$U:$U,B110)=0,"",sumifs('jiliarena_活动分析数据_底稿'!$V:$V,'jiliarena_活动分析数据_底稿'!$T:$T,$B$2,'jiliarena_活动分析数据_底稿'!$U:$U,B110)) | G110: {=if(F110="","",(F110/index(jiliarena!$A$4:$M$39,match($B$2,jiliarena!$A$4:$A$39,0),match("总存款额度 total deposit amount",jiliarena!$A$4:$M$4,0))))} | H110: =sumifs('jiliarena_活动分析数据_底稿'!$K:$K,'jiliarena_活动分析数据_底稿'!$B:$B,$B$2,'jiliarena_活动分析数据_底稿'!$C:$C,B110) -> 0 | I110: {=H110/INDEX(jiliarena!$A$4:$BQ$39,MATCH($B$2,jiliarena!$A$4:$A$39,0),MATCH("总优惠 （Z+...+AH） Total Bonus",jiliarena!$4:$4,0))} -> 0 | J110: {=$H110/index(jiliarena!$A$4:$Z$39,match($B$2,jiliarena!$A$4:$A$39,0),match("有效投注额 Valid bet",jiliarena!$A$4:$Z$4,0))} -> 0 | K110: {=$H110/index(jiliarena!$A$4:$Z$39,match($B$2,jiliarena!$A$4:$A$39,0),match("总存款额度 total deposit amount",jiliarena!$A$4:$Z$4,0))} -> 0 | L110: {=$H110/index(jiliarena!$A$4:$Z$39,match($B$2,jiliarena!$A$4:$A$39,0),match("公司输赢 Win or lose",jiliarena!$A$4:$Z$4,0))} -> 0 | O110: =sumifs($H$83:$H$126,$B$83:$B$126,N110) -> 0 | P110: =sumifs($D$83:$D$126,$B$83:$B$126,$N110) -> 0 | Q110: =sumifs($E$83:$E$126,$B$83:$B$126,$N110) -> 0
B111: TG Share Withdrawal screenshots | C111: TG提现截图 | D111: =SUMIFS('jiliarena_活动分析数据_底稿'!$F:$F,'jiliarena_活动分析数据_底稿'!$C:$C,B111,'jiliarena_活动分析数据_底稿'!$B:$B,$B$2) -> 0 | E111: =SUMIFS('jiliarena_活动分析数据_底稿'!$G:$G,'jiliarena_活动分析数据_底稿'!$B:$B,$B$2,'jiliarena_活动分析数据_底稿'!$C:$C,B111) -> 0 | F111: =if(sumifs('jiliarena_活动分析数据_底稿'!$V:$V,'jiliarena_活动分析数据_底稿'!$T:$T,$B$2,'jiliarena_活动分析数据_底稿'!$U:$U,B111)=0,"",sumifs('jiliarena_活动分析数据_底稿'!$V:$V,'jiliarena_活动分析数据_底稿'!$T:$T,$B$2,'jiliarena_活动分析数据_底稿'!$U:$U,B111)) | G111: {=if(F111="","",(F111/index(jiliarena!$A$4:$M$39,match($B$2,jiliarena!$A$4:$A$39,0),match("总存款额度 total deposit amount",jiliarena!$A$4:$M$4,0))))} | H111: =sumifs('jiliarena_活动分析数据_底稿'!$K:$K,'jiliarena_活动分析数据_底稿'!$B:$B,$B$2,'jiliarena_活动分析数据_底稿'!$C:$C,B111) -> 0 | I111: {=H111/INDEX(jiliarena!$A$4:$BQ$39,MATCH($B$2,jiliarena!$A$4:$A$39,0),MATCH("总优惠 （Z+...+AH） Total Bonus",jiliarena!$4:$4,0))} -> 0 | J111: {=$H111/index(jiliarena!$A$4:$Z$39,match($B$2,jiliarena!$A$4:$A$39,0),match("有效投注额 Valid bet",jiliarena!$A$4:$Z$4,0))} -> 0 | K111: {=$H111/index(jiliarena!$A$4:$Z$39,match($B$2,jiliarena!$A$4:$A$39,0),match("总存款额度 total deposit amount",jiliarena!$A$4:$Z$4,0))} -> 0 | L111: {=$H111/index(jiliarena!$A$4:$Z$39,match($B$2,jiliarena!$A$4:$A$39,0),match("公司输赢 Win or lose",jiliarena!$A$4:$Z$4,0))} -> 0 | O111: =sumifs($H$83:$H$126,$B$83:$B$126,N111) -> 0 | P111: =sumifs($D$83:$D$126,$B$83:$B$126,$N111) -> 0 | Q111: =sumifs($E$83:$E$126,$B$83:$B$126,$N111) -> 0
D112: =SUMIFS('jiliarena_活动分析数据_底稿'!$F:$F,'jiliarena_活动分析数据_底稿'!$C:$C,B112,'jiliarena_活动分析数据_底稿'!$B:$B,$B$2) -> 0 | E112: =SUMIFS('jiliarena_活动分析数据_底稿'!$G:$G,'jiliarena_活动分析数据_底稿'!$B:$B,$B$2,'jiliarena_活动分析数据_底稿'!$C:$C,B112) -> 0 | F112: =if(sumifs('jiliarena_活动分析数据_底稿'!$V:$V,'jiliarena_活动分析数据_底稿'!$T:$T,$B$2,'jiliarena_活动分析数据_底稿'!$U:$U,B112)=0,"",sumifs('jiliarena_活动分析数据_底稿'!$V:$V,'jiliarena_活动分析数据_底稿'!$T:$T,$B$2,'jiliarena_活动分析数据_底稿'!$U:$U,B112)) | G112: {=if(F112="","",(F112/index(jiliarena!$A$4:$M$39,match($B$2,jiliarena!$A$4:$A$39,0),match("总存款额度 total deposit amount",jiliarena!$A$4:$M$4,0))))} | H112: =sumifs('jiliarena_活动分析数据_底稿'!$K:$K,'jiliarena_活动分析数据_底稿'!$B:$B,$B$2,'jiliarena_活动分析数据_底稿'!$C:$C,B112) -> 0 | I112: {=H112/INDEX(jiliarena!$A$4:$BQ$39,MATCH($B$2,jiliarena!$A$4:$A$39,0),MATCH("总优惠 （Z+...+AH） Total Bonus",jiliarena!$4:$4,0))} -> 0 | J112: {=$H112/index(jiliarena!$A$4:$Z$39,match($B$2,jiliarena!$A$4:$A$39,0),match("有效投注额 Valid bet",jiliarena!$A$4:$Z$4,0))} -> 0 | K112: {=$H112/index(jiliarena!$A$4:$Z$39,match($B$2,jiliarena!$A$4:$A$39,0),match("总存款额度 total deposit amount",jiliarena!$A$4:$Z$4,0))} -> 0 | L112: {=$H112/index(jiliarena!$A$4:$Z$39,match($B$2,jiliarena!$A$4:$A$39,0),match("公司输赢 Win or lose",jiliarena!$A$4:$Z$4,0))} -> 0 | N112: NEW MEMBER 1ST DEPOSIT BONUS | O112: =sumifs($H$83:$H$126,$B$83:$B$126,N112) -> 0 | P112: =sumifs($D$83:$D$126,$B$83:$B$126,$N112) -> 0 | Q112: =sumifs($E$83:$E$126,$B$83:$B$126,$N112) -> 0
F113: =if(sumifs('jiliarena_活动分析数据_底稿'!$V:$V,'jiliarena_活动分析数据_底稿'!$T:$T,$B$2,'jiliarena_活动分析数据_底稿'!$U:$U,B113)=0,"",sumifs('jiliarena_活动分析数据_底稿'!$V:$V,'jiliarena_活动分析数据_底稿'!$T:$T,$B$2,'jiliarena_活动分析数据_底稿'!$U:$U,B113)) | G113: {=if(F113="","",(F113/index(jiliarena!$A$4:$M$39,match($B$2,jiliarena!$A$4:$A$39,0),match("总存款额度 total deposit amount",jiliarena!$A$4:$M$4,0))))} | H113: =sumifs('jiliarena_活动分析数据_底稿'!$K:$K,'jiliarena_活动分析数据_底稿'!$B:$B,$B$2,'jiliarena_活动分析数据_底稿'!$C:$C,B113) -> 0 | I113: {=H113/INDEX(jiliarena!$A$4:$BQ$39,MATCH($B$2,jiliarena!$A$4:$A$39,0),MATCH("总优惠 （Z+...+AH） Total Bonus",jiliarena!$4:$4,0))} -> 0 | J113: {=$H113/index(jiliarena!$A$4:$Z$39,match($B$2,jiliarena!$A$4:$A$39,0),match("有效投注额 Valid bet",jiliarena!$A$4:$Z$4,0))} -> 0 | K113: {=$H113/index(jiliarena!$A$4:$Z$39,match($B$2,jiliarena!$A$4:$A$39,0),match("总存款额度 total deposit amount",jiliarena!$A$4:$Z$4,0))} -> 0 | L113: {=$H113/index(jiliarena!$A$4:$Z$39,match($B$2,jiliarena!$A$4:$A$39,0),match("公司输赢 Win or lose",jiliarena!$A$4:$Z$4,0))} -> 0 | N113: NEW MEMBER 2ND DEPOSIT BONUS | O113: =sumifs($H$83:$H$126,$B$83:$B$126,N113) -> 0 | P113: =sumifs($D$83:$D$126,$B$83:$B$126,$N113) -> 0 | Q113: =sumifs($E$83:$E$126,$B$83:$B$126,$N113) -> 0
F114: =if(sumifs('jiliarena_活动分析数据_底稿'!$V:$V,'jiliarena_活动分析数据_底稿'!$T:$T,$B$2,'jiliarena_活动分析数据_底稿'!$U:$U,B114)=0,"",sumifs('jiliarena_活动分析数据_底稿'!$V:$V,'jiliarena_活动分析数据_底稿'!$T:$T,$B$2,'jiliarena_活动分析数据_底稿'!$U:$U,B114)) | G114: {=if(F114="","",(F114/index(jiliarena!$A$4:$M$39,match($B$2,jiliarena!$A$4:$A$39,0),match("总存款额度 total deposit amount",jiliarena!$A$4:$M$4,0))))} | H114: =sumifs('jiliarena_活动分析数据_底稿'!$K:$K,'jiliarena_活动分析数据_底稿'!$B:$B,$B$2,'jiliarena_活动分析数据_底稿'!$C:$C,B114) -> 0 | I114: {=H114/INDEX(jiliarena!$A$4:$BQ$39,MATCH($B$2,jiliarena!$A$4:$A$39,0),MATCH("总优惠 （Z+...+AH） Total Bonus",jiliarena!$4:$4,0))} -> 0 | J114: {=$H114/index(jiliarena!$A$4:$Z$39,match($B$2,jiliarena!$A$4:$A$39,0),match("有效投注额 Valid bet",jiliarena!$A$4:$Z$4,0))} -> 0 | K114: {=$H114/index(jiliarena!$A$4:$Z$39,match($B$2,jiliarena!$A$4:$A$39,0),match("总存款额度 total deposit amount",jiliarena!$A$4:$Z$4,0))} -> 0 | L114: {=$H114/index(jiliarena!$A$4:$Z$39,match($B$2,jiliarena!$A$4:$A$39,0),match("公司输赢 Win or lose",jiliarena!$A$4:$Z$4,0))} -> 0 | N114: NEW MEMBER 3RD DEPOSIT BONUS | O114: =sumifs($H$83:$H$126,$B$83:$B$126,N114) -> 0 | P114: =sumifs($D$83:$D$126,$B$83:$B$126,$N114) -> 0 | Q114: =sumifs($E$83:$E$126,$B$83:$B$126,$N114) -> 0
F115: =if(sumifs('jiliarena_活动分析数据_底稿'!$V:$V,'jiliarena_活动分析数据_底稿'!$T:$T,$B$2,'jiliarena_活动分析数据_底稿'!$U:$U,B115)=0,"",sumifs('jiliarena_活动分析数据_底稿'!$V:$V,'jiliarena_活动分析数据_底稿'!$T:$T,$B$2,'jiliarena_活动分析数据_底稿'!$U:$U,B115)) | G115: {=if(F115="","",(F115/index(jiliarena!$A$4:$M$39,match($B$2,jiliarena!$A$4:$A$39,0),match("总存款额度 total deposit amount",jiliarena!$A$4:$M$4,0))))} | H115: =sumifs('jiliarena_活动分析数据_底稿'!$K:$K,'jiliarena_活动分析数据_底稿'!$B:$B,$B$2,'jiliarena_活动分析数据_底稿'!$C:$C,B115) -> 0 | I115: {=H115/INDEX(jiliarena!$A$4:$BQ$39,MATCH($B$2,jiliarena!$A$4:$A$39,0),MATCH("总优惠 （Z+...+AH） Total Bonus",jiliarena!$4:$4,0))} -> 0 | J115: {=$H115/index(jiliarena!$A$4:$Z$39,match($B$2,jiliarena!$A$4:$A$39,0),match("有效投注额 Valid bet",jiliarena!$A$4:$Z$4,0))} -> 0 | K115: {=$H115/index(jiliarena!$A$4:$Z$39,match($B$2,jiliarena!$A$4:$A$39,0),match("总存款额度 total deposit amount",jiliarena!$A$4:$Z$4,0))} -> 0 | L115: {=$H115/index(jiliarena!$A$4:$Z$39,match($B$2,jiliarena!$A$4:$A$39,0),match("公司输赢 Win or lose",jiliarena!$A$4:$Z$4,0))} -> 0 | N115: 优惠码 | O115: =sumifs($H$83:$H$126,$B$83:$B$126,N115) -> 0 | P115: =sumifs($D$83:$D$126,$B$83:$B$126,$N115) -> 0 | Q115: =sumifs($E$83:$E$126,$B$83:$B$126,$N115) -> 0
A116: 7 | B116: NEW MEMBER 1ST DEPOSIT BONUS | C116: 首存 | D116: =SUMIFS('jiliarena_活动分析数据_底稿'!$F:$F,'jiliarena_活动分析数据_底稿'!$C:$C,B116,'jiliarena_活动分析数据_底稿'!$B:$B,$B$2) -> 0 | E116: =SUMIFS('jiliarena_活动分析数据_底稿'!$G:$G,'jiliarena_活动分析数据_底稿'!$B:$B,$B$2,'jiliarena_活动分析数据_底稿'!$C:$C,B116) -> 0 | F116: =if(sumifs('jiliarena_活动分析数据_底稿'!$V:$V,'jiliarena_活动分析数据_底稿'!$T:$T,$B$2,'jiliarena_活动分析数据_底稿'!$U:$U,B116)=0,"",sumifs('jiliarena_活动分析数据_底稿'!$V:$V,'jiliarena_活动分析数据_底稿'!$T:$T,$B$2,'jiliarena_活动分析数据_底稿'!$U:$U,B116)) | G116: {=if(F116="","",(F116/index(jiliarena!$A$4:$M$39,match($B$2,jiliarena!$A$4:$A$39,0),match("总存款额度 total deposit amount",jiliarena!$A$4:$M$4,0))))} | H116: =sumifs('jiliarena_活动分析数据_底稿'!$K:$K,'jiliarena_活动分析数据_底稿'!$B:$B,$B$2,'jiliarena_活动分析数据_底稿'!$C:$C,B116) -> 0 | I116: {=H116/INDEX(jiliarena!$A$4:$BQ$39,MATCH($B$2,jiliarena!$A$4:$A$39,0),MATCH("总优惠 （Z+...+AH） Total Bonus",jiliarena!$4:$4,0))} -> 0 | J116: {=$H116/index(jiliarena!$A$4:$Z$39,match($B$2,jiliarena!$A$4:$A$39,0),match("有效投注额 Valid bet",jiliarena!$A$4:$Z$4,0))} -> 0 | K116: {=$H116/index(jiliarena!$A$4:$Z$39,match($B$2,jiliarena!$A$4:$A$39,0),match("总存款额度 total deposit amount",jiliarena!$A$4:$Z$4,0))} -> 0 | L116: {=$H116/index(jiliarena!$A$4:$Z$39,match($B$2,jiliarena!$A$4:$A$39,0),match("公司输赢 Win or lose",jiliarena!$A$4:$Z$4,0))} -> 0 | N116: 任务排行榜 | O116: =sumifs($H$83:$H$126,$B$83:$B$126,N116) -> 0 | P116: =sumifs($D$83:$D$126,$B$83:$B$126,$N116) -> 0 | Q116: =sumifs($E$83:$E$126,$B$83:$B$126,$N116) -> 0
A117: 8 | B117: NEW MEMBER 2ND DEPOSIT BONUS | C117: 二次存送 | D117: =SUMIFS('jiliarena_活动分析数据_底稿'!$F:$F,'jiliarena_活动分析数据_底稿'!$C:$C,B117,'jiliarena_活动分析数据_底稿'!$B:$B,$B$2) -> 0 | E117: =SUMIFS('jiliarena_活动分析数据_底稿'!$G:$G,'jiliarena_活动分析数据_底稿'!$B:$B,$B$2,'jiliarena_活动分析数据_底稿'!$C:$C,B117) -> 0 | F117: =if(sumifs('jiliarena_活动分析数据_底稿'!$V:$V,'jiliarena_活动分析数据_底稿'!$T:$T,$B$2,'jiliarena_活动分析数据_底稿'!$U:$U,B117)=0,"",sumifs('jiliarena_活动分析数据_底稿'!$V:$V,'jiliarena_活动分析数据_底稿'!$T:$T,$B$2,'jiliarena_活动分析数据_底稿'!$U:$U,B117)) | G117: {=if(F117="","",(F117/index(jiliarena!$A$4:$M$39,match($B$2,jiliarena!$A$4:$A$39,0),match("总存款额度 total deposit amount",jiliarena!$A$4:$M$4,0))))} | H117: =sumifs('jiliarena_活动分析数据_底稿'!$K:$K,'jiliarena_活动分析数据_底稿'!$B:$B,$B$2,'jiliarena_活动分析数据_底稿'!$C:$C,B117) -> 0 | I117: {=H117/INDEX(jiliarena!$A$4:$BQ$39,MATCH($B$2,jiliarena!$A$4:$A$39,0),MATCH("总优惠 （Z+...+AH） Total Bonus",jiliarena!$4:$4,0))} -> 0 | J117: 0.00028434132 | K117: {=$H117/index(jiliarena!$A$4:$Z$39,match($B$2,jiliarena!$A$4:$A$39,0),match("总存款额度 total deposit amount",jiliarena!$A$4:$Z$4,0))} -> 0 | L117: {=$H117/index(jiliarena!$A$4:$Z$39,match($B$2,jiliarena!$A$4:$A$39,0),match("公司输赢 Win or lose",jiliarena!$A$4:$Z$4,0))} -> 0 | N117: 登录任务 | O117: =sumifs($H$83:$H$126,$B$83:$B$126,N117) -> 2161 | P117: =sumifs($D$83:$D$126,$B$83:$B$126,$N117) -> 0 | Q117: =sumifs($E$83:$E$126,$B$83:$B$126,$N117) -> 1442
A118: 9 | B118: NEW MEMBER 3RD DEPOSIT BONUS | C118: 三次存送 | D118: =SUMIFS('jiliarena_活动分析数据_底稿'!$F:$F,'jiliarena_活动分析数据_底稿'!$C:$C,B118,'jiliarena_活动分析数据_底稿'!$B:$B,$B$2) -> 0 | E118: =SUMIFS('jiliarena_活动分析数据_底稿'!$G:$G,'jiliarena_活动分析数据_底稿'!$B:$B,$B$2,'jiliarena_活动分析数据_底稿'!$C:$C,B118) -> 0 | F118: =if(sumifs('jiliarena_活动分析数据_底稿'!$V:$V,'jiliarena_活动分析数据_底稿'!$T:$T,$B$2,'jiliarena_活动分析数据_底稿'!$U:$U,B118)=0,"",sumifs('jiliarena_活动分析数据_底稿'!$V:$V,'jiliarena_活动分析数据_底稿'!$T:$T,$B$2,'jiliarena_活动分析数据_底稿'!$U:$U,B118)) | G118: {=if(F118="","",(F118/index(jiliarena!$A$4:$M$39,match($B$2,jiliarena!$A$4:$A$39,0),match("总存款额度 total deposit amount",jiliarena!$A$4:$M$4,0))))} | H118: =sumifs('jiliarena_活动分析数据_底稿'!$K:$K,'jiliarena_活动分析数据_底稿'!$B:$B,$B$2,'jiliarena_活动分析数据_底稿'!$C:$C,B118) -> 0 | I118: {=H118/INDEX(jiliarena!$A$4:$BQ$39,MATCH($B$2,jiliarena!$A$4:$A$39,0),MATCH("总优惠 （Z+...+AH） Total Bonus",jiliarena!$4:$4,0))} -> 0 | J118: 5.6690179e-05 | K118: {=$H118/index(jiliarena!$A$4:$Z$39,match($B$2,jiliarena!$A$4:$A$39,0),match("总存款额度 total deposit amount",jiliarena!$A$4:$Z$4,0))} -> 0 | L118: {=$H118/index(jiliarena!$A$4:$Z$39,match($B$2,jiliarena!$A$4:$A$39,0),match("公司输赢 Win or lose",jiliarena!$A$4:$Z$4,0))} -> 0 | N118: 邀请返佣 | O118: =sumifs($H$83:$H$126,$B$83:$B$126,N118) -> 14630.65 | P118: =sumifs($D$83:$D$126,$B$83:$B$126,$N118) -> 1013 | Q118: =sumifs($E$83:$E$126,$B$83:$B$126,$N118) -> 569
A119: 10 | B119: 优惠码 | C119: 优惠码 | D119: =SUMIFS('jiliarena_活动分析数据_底稿'!$F:$F,'jiliarena_活动分析数据_底稿'!$C:$C,B119,'jiliarena_活动分析数据_底稿'!$B:$B,$B$2) -> 0 | E119: =SUMIFS('jiliarena_活动分析数据_底稿'!$G:$G,'jiliarena_活动分析数据_底稿'!$B:$B,$B$2,'jiliarena_活动分析数据_底稿'!$C:$C,B119) -> 0 | F119: =if(sumifs('jiliarena_活动分析数据_底稿'!$V:$V,'jiliarena_活动分析数据_底稿'!$T:$T,$B$2,'jiliarena_活动分析数据_底稿'!$U:$U,B119)=0,"",sumifs('jiliarena_活动分析数据_底稿'!$V:$V,'jiliarena_活动分析数据_底稿'!$T:$T,$B$2,'jiliarena_活动分析数据_底稿'!$U:$U,B119)) | G119: {=if(F119="","",(F119/index(jiliarena!$A$4:$M$39,match($B$2,jiliarena!$A$4:$A$39,0),match("总存款额度 total deposit amount",jiliarena!$A$4:$M$4,0))))} | H119: =sumifs('jiliarena_活动分析数据_底稿'!$K:$K,'jiliarena_活动分析数据_底稿'!$B:$B,$B$2,'jiliarena_活动分析数据_底稿'!$C:$C,B119) -> 0 | I119: {=H119/INDEX(jiliarena!$A$4:$BQ$39,MATCH($B$2,jiliarena!$A$4:$A$39,0),MATCH("总优惠 （Z+...+AH） Total Bonus",jiliarena!$4:$4,0))} -> 0 | J119: 8.9119839e-09 | K119: {=$H119/index(jiliarena!$A$4:$Z$39,match($B$2,jiliarena!$A$4:$A$39,0),match("总存款额度 total deposit amount",jiliarena!$A$4:$Z$4,0))} -> 0 | L119: {=$H119/index(jiliarena!$A$4:$Z$39,match($B$2,jiliarena!$A$4:$A$39,0),match("公司输赢 Win or lose",jiliarena!$A$4:$Z$4,0))} -> 0 | N119: 存款达标奖励 | O119: =sumifs($H$83:$H$126,$B$83:$B$126,N119) -> 0 | P119: =sumifs($D$83:$D$126,$B$83:$B$126,$N119) -> 0 | Q119: =sumifs($E$83:$E$126,$B$83:$B$126,$N119) -> 0
A120: 11 | B120: 任务排行榜 | C120: 任务排行榜 | D120: =SUMIFS('jiliarena_活动分析数据_底稿'!$F:$F,'jiliarena_活动分析数据_底稿'!$C:$C,B120,'jiliarena_活动分析数据_底稿'!$B:$B,$B$2) -> 0 | E120: =SUMIFS('jiliarena_活动分析数据_底稿'!$G:$G,'jiliarena_活动分析数据_底稿'!$B:$B,$B$2,'jiliarena_活动分析数据_底稿'!$C:$C,B120) -> 0 | F120: =if(sumifs('jiliarena_活动分析数据_底稿'!$V:$V,'jiliarena_活动分析数据_底稿'!$T:$T,$B$2,'jiliarena_活动分析数据_底稿'!$U:$U,B120)=0,"",sumifs('jiliarena_活动分析数据_底稿'!$V:$V,'jiliarena_活动分析数据_底稿'!$T:$T,$B$2,'jiliarena_活动分析数据_底稿'!$U:$U,B120)) | G120: {=if(F120="","",(F120/index(jiliarena!$A$4:$M$39,match($B$2,jiliarena!$A$4:$A$39,0),match("总存款额度 total deposit amount",jiliarena!$A$4:$M$4,0))))} | H120: =sumifs('jiliarena_活动分析数据_底稿'!$K:$K,'jiliarena_活动分析数据_底稿'!$B:$B,$B$2,'jiliarena_活动分析数据_底稿'!$C:$C,B120) -> 0 | I120: {=H120/INDEX(jiliarena!$A$4:$BQ$39,MATCH($B$2,jiliarena!$A$4:$A$39,0),MATCH("总优惠 （Z+...+AH） Total Bonus",jiliarena!$4:$4,0))} -> 0 | J120: 8.9119839e-09 | K120: {=$H120/index(jiliarena!$A$4:$Z$39,match($B$2,jiliarena!$A$4:$A$39,0),match("总存款额度 total deposit amount",jiliarena!$A$4:$Z$4,0))} -> 0 | L120: {=$H120/index(jiliarena!$A$4:$Z$39,match($B$2,jiliarena!$A$4:$A$39,0),match("公司输赢 Win or lose",jiliarena!$A$4:$Z$4,0))} -> 0 | N120: 3% DAILY CASHBACK | O120: =sumifs($H$83:$H$126,$B$83:$B$126,N120) -> 0 | P120: =sumifs($D$83:$D$126,$B$83:$B$126,$N120) -> 0 | Q120: =sumifs($E$83:$E$126,$B$83:$B$126,$N120) -> 0
A121: 11 | B121: 登录任务 | C121: 登录任务 | D121: =SUMIFS('jiliarena_活动分析数据_底稿'!$F:$F,'jiliarena_活动分析数据_底稿'!$C:$C,B121,'jiliarena_活动分析数据_底稿'!$B:$B,$B$2) -> 0 | E121: =SUMIFS('jiliarena_活动分析数据_底稿'!$G:$G,'jiliarena_活动分析数据_底稿'!$B:$B,$B$2,'jiliarena_活动分析数据_底稿'!$C:$C,B121) -> 1442 | F121: =if(sumifs('jiliarena_活动分析数据_底稿'!$V:$V,'jiliarena_活动分析数据_底稿'!$T:$T,$B$2,'jiliarena_活动分析数据_底稿'!$U:$U,B121)=0,"",sumifs('jiliarena_活动分析数据_底稿'!$V:$V,'jiliarena_活动分析数据_底稿'!$T:$T,$B$2,'jiliarena_活动分析数据_底稿'!$U:$U,B121)) | G121: {=if(F121="","",(F121/index(jiliarena!$A$4:$M$39,match($B$2,jiliarena!$A$4:$A$39,0),match("总存款额度 total deposit amount",jiliarena!$A$4:$M$4,0))))} | H121: =sumifs('jiliarena_活动分析数据_底稿'!$K:$K,'jiliarena_活动分析数据_底稿'!$B:$B,$B$2,'jiliarena_活动分析数据_底稿'!$C:$C,B121) -> 2161 | I121: {=H121/INDEX(jiliarena!$A$4:$BQ$39,MATCH($B$2,jiliarena!$A$4:$A$39,0),MATCH("总优惠 （Z+...+AH） Total Bonus",jiliarena!$4:$4,0))} -> 0.0036496677 | J121: 8.9119839e-09 | K121: {=$H121/index(jiliarena!$A$4:$Z$39,match($B$2,jiliarena!$A$4:$A$39,0),match("总存款额度 total deposit amount",jiliarena!$A$4:$Z$4,0))} -> 0.0039381415 | L121: {=$H121/index(jiliarena!$A$4:$Z$39,match($B$2,jiliarena!$A$4:$A$39,0),match("公司输赢 Win or lose",jiliarena!$A$4:$Z$4,0))} -> 0.0083731224 | N121: 新手任务奖励 | O121: =sumifs($H$83:$H$126,$B$83:$B$126,N121) -> 0 | P121: =sumifs($D$83:$D$126,$B$83:$B$126,$N121) -> 0 | Q121: =sumifs($E$83:$E$126,$B$83:$B$126,$N121) -> 0
A122: 12 | B122: 邀请返佣 | C122: 推薦好友 | D122: =SUMIFS('jiliarena_活动分析数据_底稿'!$F:$F,'jiliarena_活动分析数据_底稿'!$C:$C,B122,'jiliarena_活动分析数据_底稿'!$B:$B,$B$2) -> 1013 | E122: =SUMIFS('jiliarena_活动分析数据_底稿'!$G:$G,'jiliarena_活动分析数据_底稿'!$B:$B,$B$2,'jiliarena_活动分析数据_底稿'!$C:$C,B122) -> 569 | F122: =if(sumifs('jiliarena_活动分析数据_底稿'!$V:$V,'jiliarena_活动分析数据_底稿'!$T:$T,$B$2,'jiliarena_活动分析数据_底稿'!$U:$U,B122)=0,"",sumifs('jiliarena_活动分析数据_底稿'!$V:$V,'jiliarena_活动分析数据_底稿'!$T:$T,$B$2,'jiliarena_活动分析数据_底稿'!$U:$U,B122)) | G122: {=if(F122="","",(F122/index(jiliarena!$A$4:$M$39,match($B$2,jiliarena!$A$4:$A$39,0),match("总存款额度 total deposit amount",jiliarena!$A$4:$M$4,0))))} | H122: =sumifs('jiliarena_活动分析数据_底稿'!$K:$K,'jiliarena_活动分析数据_底稿'!$B:$B,$B$2,'jiliarena_活动分析数据_底稿'!$C:$C,B122) -> 14630.65 | I122: {=H122/INDEX(jiliarena!$A$4:$BQ$39,MATCH($B$2,jiliarena!$A$4:$A$39,0),MATCH("总优惠 （Z+...+AH） Total Bonus",jiliarena!$4:$4,0))} -> 0.024709399 | J122: 0.00033365089 | K122: {=$H122/index(jiliarena!$A$4:$Z$39,match($B$2,jiliarena!$A$4:$A$39,0),match("总存款额度 total deposit amount",jiliarena!$A$4:$Z$4,0))} -> 0.026662457 | L122: {=$H122/index(jiliarena!$A$4:$Z$39,match($B$2,jiliarena!$A$4:$A$39,0),match("公司输赢 Win or lose",jiliarena!$A$4:$Z$4,0))} -> 0.056688673 | O122: =sumifs($H$83:$H$126,$B$83:$B$126,N122) -> 0 | P122: =sumifs($D$83:$D$126,$B$83:$B$126,$N122) -> 0 | Q122: =sumifs($E$83:$E$126,$B$83:$B$126,$N122) -> 0
A123: 13 | B123: 存款达标奖励 | C123: 存款達標 | D123: =SUMIFS('jiliarena_活动分析数据_底稿'!$F:$F,'jiliarena_活动分析数据_底稿'!$C:$C,B123,'jiliarena_活动分析数据_底稿'!$B:$B,$B$2) -> 0 | E123: =SUMIFS('jiliarena_活动分析数据_底稿'!$G:$G,'jiliarena_活动分析数据_底稿'!$B:$B,$B$2,'jiliarena_活动分析数据_底稿'!$C:$C,B123) -> 0 | F123: =if(sumifs('jiliarena_活动分析数据_底稿'!$V:$V,'jiliarena_活动分析数据_底稿'!$T:$T,$B$2,'jiliarena_活动分析数据_底稿'!$U:$U,B123)=0,"",sumifs('jiliarena_活动分析数据_底稿'!$V:$V,'jiliarena_活动分析数据_底稿'!$T:$T,$B$2,'jiliarena_活动分析数据_底稿'!$U:$U,B123)) | G123: {=if(F123="","",(F123/index(jiliarena!$A$4:$M$39,match($B$2,jiliarena!$A$4:$A$39,0),match("总存款额度 total deposit amount",jiliarena!$A$4:$M$4,0))))} | H123: =sumifs('jiliarena_活动分析数据_底稿'!$K:$K,'jiliarena_活动分析数据_底稿'!$B:$B,$B$2,'jiliarena_活动分析数据_底稿'!$C:$C,B123) -> 0 | I123: {=H123/INDEX(jiliarena!$A$4:$BQ$39,MATCH($B$2,jiliarena!$A$4:$A$39,0),MATCH("总优惠 （Z+...+AH） Total Bonus",jiliarena!$4:$4,0))} -> 0 | J123: 0.00033365089 | K123: {=$H123/index(jiliarena!$A$4:$Z$39,match($B$2,jiliarena!$A$4:$A$39,0),match("总存款额度 total deposit amount",jiliarena!$A$4:$Z$4,0))} -> 0 | L123: {=$H123/index(jiliarena!$A$4:$Z$39,match($B$2,jiliarena!$A$4:$A$39,0),match("公司输赢 Win or lose",jiliarena!$A$4:$Z$4,0))} -> 0 | O123: =sumifs($H$83:$H$126,$B$83:$B$126,N123) -> 0 | P123: =sumifs($D$83:$D$126,$B$83:$B$126,$N123) -> 0 | Q123: =sumifs($E$83:$E$126,$B$83:$B$126,$N123) -> 0
A124: 14 | B124: 3% DAILY CASHBACK | C124: 关怀援助金 | D124: =SUMIFS('jiliarena_活动分析数据_底稿'!$F:$F,'jiliarena_活动分析数据_底稿'!$E:$E,C124,'jiliarena_活动分析数据_底稿'!$B:$B,$B$2) -> 0 | E124: =SUMIFS('jiliarena_活动分析数据_底稿'!$G:$G,'jiliarena_活动分析数据_底稿'!$B:$B,$B$2,'jiliarena_活动分析数据_底稿'!$E:$E,C124) -> 0 | F124: =if(sumifs('jiliarena_活动分析数据_底稿'!$V:$V,'jiliarena_活动分析数据_底稿'!$T:$T,$B$2,'jiliarena_活动分析数据_底稿'!$U:$U,B124)=0,"",sumifs('jiliarena_活动分析数据_底稿'!$V:$V,'jiliarena_活动分析数据_底稿'!$T:$T,$B$2,'jiliarena_活动分析数据_底稿'!$U:$U,B124)) | G124: {=if(F124="","",(F124/index(jiliarena!$A$4:$M$39,match($B$2,jiliarena!$A$4:$A$39,0),match("总存款额度 total deposit amount",jiliarena!$A$4:$M$4,0))))} | H124: =sumifs('jiliarena_活动分析数据_底稿'!$K:$K,'jiliarena_活动分析数据_底稿'!$B:$B,$B$2,'jiliarena_活动分析数据_底稿'!$E:$E,C124) -> 0 | I124: {=H124/INDEX(jiliarena!$A$4:$BQ$39,MATCH($B$2,jiliarena!$A$4:$A$39,0),MATCH("总优惠 （Z+...+AH） Total Bonus",jiliarena!$4:$4,0))} -> 0 | J124: 0.0010583072 | K124: {=$H124/index(jiliarena!$A$4:$Z$39,match($B$2,jiliarena!$A$4:$A$39,0),match("总存款额度 total deposit amount",jiliarena!$A$4:$Z$4,0))} -> 0 | L124: {=$H124/index(jiliarena!$A$4:$Z$39,match($B$2,jiliarena!$A$4:$A$39,0),match("公司输赢 Win or lose",jiliarena!$A$4:$Z$4,0))} -> 0 | O124: =sumifs($H$83:$H$126,$B$83:$B$126,N124) -> 0 | P124: =sumifs($D$83:$D$126,$B$83:$B$126,$N124) -> 0 | Q124: =sumifs($E$83:$E$126,$B$83:$B$126,$N124) -> 0
A125: 18 | B125: 新手任务奖励 | C125: 新手任务奖励 | D125: =SUMIFS('jiliarena_活动分析数据_底稿'!$F:$F,'jiliarena_活动分析数据_底稿'!$C:$C,B125,'jiliarena_活动分析数据_底稿'!$B:$B,$B$2) -> 0 | E125: =SUMIFS('jiliarena_活动分析数据_底稿'!$G:$G,'jiliarena_活动分析数据_底稿'!$B:$B,$B$2,'jiliarena_活动分析数据_底稿'!$C:$C,B125) -> 0 | F125: =if(sumifs('jiliarena_活动分析数据_底稿'!$V:$V,'jiliarena_活动分析数据_底稿'!$T:$T,$B$2,'jiliarena_活动分析数据_底稿'!$U:$U,B125)=0,"",sumifs('jiliarena_活动分析数据_底稿'!$V:$V,'jiliarena_活动分析数据_底稿'!$T:$T,$B$2,'jiliarena_活动分析数据_底稿'!$U:$U,B125)) | G125: {=if(F125="","",(F125/index(jiliarena!$A$4:$M$39,match($B$2,jiliarena!$A$4:$A$39,0),match("总存款额度 total deposit amount",jiliarena!$A$4:$M$4,0))))} | H125: =sumifs('jiliarena_活动分析数据_底稿'!$K:$K,'jiliarena_活动分析数据_底稿'!$B:$B,$B$2,'jiliarena_活动分析数据_底稿'!$C:$C,B125) -> 0 | I125: {=H125/INDEX(jiliarena!$A$4:$BQ$39,MATCH($B$2,jiliarena!$A$4:$A$39,0),MATCH("总优惠 （Z+...+AH） Total Bonus",jiliarena!$4:$4,0))} -> 0 | J125: 0.00020974377 | K125: {=$H125/index(jiliarena!$A$4:$Z$39,match($B$2,jiliarena!$A$4:$A$39,0),match("总存款额度 total deposit amount",jiliarena!$A$4:$Z$4,0))} -> 0 | L125: {=$H125/index(jiliarena!$A$4:$Z$39,match($B$2,jiliarena!$A$4:$A$39,0),match("公司输赢 Win or lose",jiliarena!$A$4:$Z$4,0))} -> 0 | N125: 加总 | O125: =SUM(O84:O124) -> 25991.32 | P125: =SUM(P84:P124) -> 9211 | Q125: =SUM(Q84:Q124) -> 10080
A126: 总计 | D126: =SUM(D84,D92,D105:D107,D116:D125) -> 9211 | E126: =SUM(E84,E92,E105:E107,E116:E125,E91) -> 10080 | F126: =SUM(F84,F92,F105:F107,F116:F125) -> 0 | G126: {=if(F126="","",(F126/index(jiliarena!$A$4:$M$39,match($B$2,jiliarena!$A$4:$A$39,0),match("总存款额度 total deposit amount",jiliarena!$A$4:$M$4,0))))} -> 0 | H126: =SUM(H84,H92,H105:H107,H116:H125,H91) -> 25991.32 | I126: =SUM(I84,I92,I105:I107,I116:I125) -> 0.043896197 | J126: =SUM(J84,J92,J105:J107,J116:J125) -> 0.0034072192 | K126: =SUM(K84,K92,K105:K107,K116:K125) -> 0.047365801 | L126: =SUM(L84,L92,L105:L107,L116:L125) -> 0.10070731 | O126: =O125-H127 -> -566117.38 | P126: =P125-D126 -> 0 | Q126: =Q125-E126 -> 0
H127: {=index(jiliarena!$A$4:$BQ$39,match($B$2,jiliarena!$A$4:$A$39,0),match("总优惠 （Z+...+AH） Total Bonus",jiliarena!$A$4:$BQ$4,0))} -> 592108.7
B128: =MONTH(B2)&"/"&DAY(B2) &" WP活动分析" -> 2/12 WP活动分析 | H128: =H126-H127 -> -566117.38
B130: 活动金额前三名：
B131: ="活动名称： "&C131&" 发放金额：" &TEXT(D131,"0,000")&" 领取人数 ："&text(E131,"0,000")&" 领取笔数："&text(F131,"0,000") -> 活动名称： 邀请返佣 发放金额：14,631 领取人数 ：0,569 领取笔数：1,013 | C131: {=index($N$83:$N$124, match(large(O83:O124,1),O83:O124,0),1)} -> 邀请返佣 | D131: =index($N$83:$Q$124,match(C131,$N$83:$N$124,0),2) -> 14630.65 | E131: =index($N$83:$Q$124,match(C131,$N$83:$N$124,0),4) -> 569 | F131: =index($N$83:$Q$124,match(C131,$N$83:$N$124,0),3) -> 1013
B132: ="活动名称： "&C132&" 发放金额：" &TEXT(D132,"0,000")&" 领取人数 ："&text(E132,"0,000")&" 领取笔数："&text(F132,"0,000") -> 活动名称： 签到奖励 发放金额：8,052 领取人数 ：7,460 领取笔数：7,460 | C132: {=index($N$83:$N$124, match(large(O83:O124,2),O83:O124,0),1)} -> 签到奖励 | D132: =index($N$83:$Q$124,match(C132,$N$83:$N$124,0),2) -> 8052 | E132: =index($N$83:$Q$124,match(C132,$N$83:$N$124,0),4) -> 7460 | F132: =index($N$83:$Q$124,match(C132,$N$83:$N$124,0),3) -> 7460
B133: ="活动名称： "&C133&" 发放金额：" &TEXT(D133,"0,000")&" 领取人数 ："&text(E133,"0,000")&" 领取笔数："&text(F133,"0,000") -> 活动名称： 登录任务 发放金额：2,161 领取人数 ：1,442 领取笔数：0,000 | C133: {=index($N$83:$N$124, match(large(O83:O124,3),O83:O124,0),1)} -> 登录任务 | D133: =index($N$83:$Q$124,match(C133,$N$83:$N$124,0),2) -> 2161 | E133: =index($N$83:$Q$124,match(C133,$N$83:$N$124,0),4) -> 1442 | F133: =index($N$83:$Q$124,match(C133,$N$83:$N$124,0),3) -> 0
B135: 活动人数前三名：
B136: ="活动名称： "&C136&" 发放金额：" &TEXT(D136,"0,000")&" 领取人数 ："&text(E136,"0,000")&" 领取笔数："&text(F136,"0,000") -> 活动名称： 签到奖励 发放金额：8,052 领取人数 ：7,460 领取笔数：7,460 | C136: {=index($N$83:$N$122, match(large($Q$83:$Q$122,1),$Q$83:$Q$122,0),1)} -> 签到奖励 | D136: =index($N$83:$Q$124,match(C136,$N$83:$N$124,0),2) -> 8052 | E136: =index($N$83:$Q$124,match(C136,$N$83:$N$124,0),4) -> 7460 | F136: =index($N$83:$Q$124,match(C136,$N$83:$N$124,0),3) -> 7460
B137: ="活动名称： "&C137&" 发放金额：" &TEXT(D137,"0,000")&" 领取人数 ："&text(E137,"0,000")&" 领取笔数："&text(F137,"0,000") -> 活动名称： 登录任务 发放金额：2,161 领取人数 ：1,442 领取笔数：0,000 | C137: {=index($N$83:$N$122, match(large($Q$83:$Q$122,2),$Q$83:$Q$122,0),1)} -> 登录任务 | D137: =index($N$83:$Q$124,match(C137,$N$83:$N$124,0),2) -> 2161 | E137: =index($N$83:$Q$124,match(C137,$N$83:$N$124,0),4) -> 1442 | F137: =index($N$83:$Q$124,match(C137,$N$83:$N$124,0),3) -> 0
B138: ="活动名称： "&C138&" 发放金额：" &TEXT(D138,"0,000")&" 领取人数 ："&text(E138,"0,000")&" 领取笔数："&text(F138,"0,000") -> 活动名称： 邀请返佣 发放金额：14,631 领取人数 ：0,569 领取笔数：1,013 | C138: {=index($N$83:$N$122, match(large($Q$83:$Q$122,3),$Q$83:$Q$122,0),1)} -> 邀请返佣 | D138: =index($N$83:$Q$124,match(C138,$N$83:$N$124,0),2) -> 14630.65 | E138: =index($N$83:$Q$124,match(C138,$N$83:$N$124,0),4) -> 569 | F138: =index($N$83:$Q$124,match(C138,$N$83:$N$124,0),3) -> 1013
B140: 活动笔数前三名：
B141: ="活动名称： "&C141&" 发放金额：" &TEXT(D141,"0,000")&" 领取人数 ："&text(E141,"0,000")&" 领取笔数："&text(F141,"0,000") -> 活动名称： 签到奖励 发放金额：8,052 领取人数 ：7,460 领取笔数：7,460 | C141: {=index($N$83:$N$122, match(large($P$83:$P$122,1),$P$83:$P$122,0),1)} -> 签到奖励 | D141: =index($N$83:$Q$124,match(C141,$N$83:$N$124,0),2) -> 8052 | E141: =index($N$83:$Q$124,match(C141,$N$83:$N$124,0),4) -> 7460 | F141: =index($N$83:$Q$124,match(C141,$N$83:$N$124,0),3) -> 7460
B142: ="活动名称： "&C142&" 发放金额：" &TEXT(D142,"0,000")&" 领取人数 ："&text(E142,"0,000")&" 领取笔数："&text(F142,"0,000") -> 活动名称： 邀请返佣 发放金额：14,631 领取人数 ：0,569 领取笔数：1,013 | C142: {=index($N$83:$N$122, match(large($P$83:$P$122,2),$P$83:$P$122,0),1)} -> 邀请返佣 | D142: =index($N$83:$Q$124,match(C142,$N$83:$N$124,0),2) -> 14630.65 | E142: =index($N$83:$Q$124,match(C142,$N$83:$N$124,0),4) -> 569 | F142: =index($N$83:$Q$124,match(C142,$N$83:$N$124,0),3) -> 1013
B143: ="活动名称： "&C143&" 发放金额：" &TEXT(D143,"0,000")&" 领取人数 ："&text(E143,"0,000")&" 领取笔数："&text(F143,"0,000") -> 活动名称： 升级奖励 发放金额：0,902 领取人数 ：0,501 领取笔数：0,630 | C143: {=index($N$83:$N$122, match(large($P$83:$P$122,3),$P$83:$P$122,0),1)} -> 升级奖励 | D143: =index($N$83:$Q$124,match(C143,$N$83:$N$124,0),2) -> 902 | E143: =index($N$83:$Q$124,match(C143,$N$83:$N$124,0),4) -> 501 | F143: =index($N$83:$Q$124,match(C143,$N$83:$N$124,0),3) -> 630
B147: 异常手动写
A211: 日期 | B211: winp001 | C211: eli168 | D211: wpluseli168 | E211: mkttestgame | F211: winningxtt | G211: blackmarket | H211: jasonbathan | I211: seo168 | J211: zzz168 | K211: bewin2023 | L211: ahb566 | M211: wilson168 | N211: daitou168 | O211: fbbot001 | P211: finixio | Q211: gaussie168 | R211: ryan168 | S211: pablosgroll | T211: casper888 | U211: game168 | V211: win1888 | W211: tcgtest00 | X211: wpdxag01 | Y211: wpopdwh1 | Z211: tgbomb168 | AA211: wpads002 | AB211: seowp001 | AC211: wpads001 | AD211: wpmetads001 | AE211: lstreaming1 | AK211: 加总
...

Sheet jiliarena_日报_底稿
B1: WP
A2: 报表管理-活跃用户分析 | P2: 报表管理-平台损益
A3: 日期 | B3: 总账号 | C3: 登录人数 | D3: 投注人数 | E3: 存款人数 | F3: 提款人数 | G3: 注册人数 | H3: 首投人数 | I3: 首充人数 | J3: 首提人数 | K3: 彩金领取人数 | L3: 充提差 | M3: 日充值 | N3: ARPU | P3: 日期 | Q3: 平台毛利 | R3: 充值 | S3: 提款金额 | T3: 充值人数 | U3: 提现人数 | V3: 充提差 | W3: 玩家充值手续费 | X3: 玩家提款手续费 | Y3: 渠道手续费 | Z3: 手续费 | AA3: 电子投注 | AB3: 电子有效投注 | AC3: 电子中奖 | AD3: 电子红利 | AE3: 电子返水 | AF3: 电子邀请返佣 | AG3: 电子代理返点 | AH3: 电子代理日工资 | AI3: 电子代理佣金 | AJ3: 电子代理分红 | AK3: 电子盈亏 | AL3: 真人投注 | AM3: 真人有效投注 | AN3: 真人中奖 | AO3: 真人红利 | AP3: 真人返水 | AQ3: 真人邀请返佣 | AR3: 真人代理返点 | AS3: 真人代理日工资 | AT3: 真人代理佣金 | AU3: 真人代理分红 | AV3: 真人盈亏 | AW3: 彩票投注 | AX3: 彩票有效投注 | AY3: 彩票中奖 | AZ3: 彩票红利 | BA3: 彩票返水 | BB3: 彩票邀请返佣 | BC3: 彩票代理返点 | BD3: 平台佣金 | BE3: 彩票代理日工资 | BF3: 彩票代理佣金 | BG3: 彩票代理分红 | BH3: 彩票盈亏 | BI3: 棋牌输额 | BJ3: 棋牌有效投注 | BK3: 棋牌赢额 | BL3: 棋牌红利 | BM3: 棋牌返水 | BN3: 棋牌邀请返佣 | BO3: 棋牌代理返点 | BP3: 棋牌代理日工资 | BQ3: 棋牌代理佣金 | BR3: 棋牌代理分红 | BS3: 棋牌盈亏 | BT3: 捕鱼投注 | BU3: 捕鱼有效投注 | BV3: 捕鱼中奖 | BW3: 捕鱼红利 | BX3: 捕鱼玩家返水 | BY3: 捕鱼邀请返佣 | BZ3: 捕鱼代理返点 | CA3: 捕鱼代理日工资 | CB3: 捕鱼代理佣金 | CC3: 捕鱼代理分红 | CD3: 捕鱼盈亏 | CE3: 体育投注 | CF3: 体育有效投注 | CG3: 体育中奖 | CH3: 体育红利 | CI3: 体育玩家返水 | CJ3: 体育邀请返佣 | CK3: 体育代理返点 | CL3: 体育代理日工资 | CM3: 体育代理佣金 | CN3: 体育代理分红 | CO3: 体育盈亏 | CP3: 盘口彩票投注 | CQ3: 盘口彩票有效投注 | CR3: 盘口彩票中奖 | CS3: 盘口彩票红利 | CT3: 盘口彩票玩家返水 | CU3: 盘口彩邀请返佣 | CV3: 盘口彩票代理返点 | CW3: 平台佣金 | CX3: 盘口彩票代理日工资 | CY3: 盘口彩票代理佣金 | CZ3: 盘口彩票代理分红 | DA3: 盘口彩票盈亏 | DB3: 开分 | DC3: 洗分 | DD3: 中心钱包红利 | DE3: 综合性分红 | DF3: 综合佣金 | DG3: 综合日工资 | DH3: 直播送礼 | DI3: 邀请奖励 | DJ3: 成就奖励 | DK3: 充值返佣 | DL3: 手续费返还 | DM3: 其他 | DN3: 中心开始馀额 | DO3: 中心开始浮动余额 | DP3: 开始余额 | DQ3: 中心结算馀额 | DR3: 中心结算浮动余额 | DS3: 结算余额
A4: =A5+1 -> 46081 | B4: 45101 | C4: 3515 | D4: 2404 | E4: 515 | F4: 98 | G4: 717 | H4: 438 | I4: 231 | J4: 44 | K4: 2936 | L4: 35409 | M4: 103745 | N4: 201.44 | P4: =P5+1 -> 46081 | Q4: 10242.68 | R4: 103745 | S4: 68336 | T4: 515 | U4: 98 | V4: 35409 | W4: 0 | X4: 0 | Y4: 1632.09 | Z4: -1632.09 | AA4: 893340.12 | AB4: 831495.63 | AC4: 864325.06 | AD4: 7942.1 | AE4: 2245.66 | AF4: 26.8151 | AG4: 0 | AH4: 0 | AI4: 0 | AJ4: 0 | AK4: 18800.485 | AL4: 7245.31 | AM4: 7020.31 | AN4: 8340 | AO4: 0 | AP4: 5.45 | AQ4: 0.175 | AR4: 0 | AS4: 0 | AT4: 0 | AU4: 0 | AV4: -1100.315 | AW4: 0 | AX4: 0 | AY4: 0 | AZ4: 0 | BA4: 0 | BB4: 0 | BC4: 0 | BD4: 0 | BE4: 0 | BF4: 0 | BG4: 0 | BH4: 0 | BI4: 1 | BJ4: 0.5 | BK4: 0 | BL4: 0 | BM4: 0 | BN4: 0 | BO4: 0 | BP4: 0 | BQ4: 0 | BR4: 0 | BS4: 1 | BT4: 12950.2 | BU4: 12930.2 | BV4: 13845.05 | BW4: 0 | BX4: 0 | BY4: 0 | BZ4: 0 | CA4: 0 | CB4: 0 | CC4: 0 | CD4: -894.85 | CE4: 0 | CF4: 0 | CG4: 0 | CH4: 0 | CI4: 0 | CJ4: 0 | CK4: 0 | CL4: 0 | CM4: 0 | CN4: 0 | CO4: 0 | CP4: 3 | CQ4: 3 | CR4: 0 | CS4: 0 | CT4: 0 | CU4: 0 | CV4: 0 | CW4: 0 | CX4: 0 | CY4: 0 | CZ4: 0 | DA4: 3 | DB4: 0 | DC4: 0 | DD4: 4900.49 | DE4: 0 | DF4: 0 | DG4: 0 | DH4: 30 | DI4: 0 | DJ4: 4.06 | DK4: 0 | DL4: 0 | DM4: -4934.55 | DN4: 96202.404 | DO4: 448009.19 | DP4: 96202.404 | DQ4: 113632.87 | DR4: 460446.19 | DS4: 113632.87
A5: =A6+1 -> 46080 | B5: 44226 | C5: 2890 | D5: 2122 | E5: 352 | F5: 92 | G5: 268 | H5: 203 | I5: 89 | J5: 40 | K5: 2466 | L5: 1319 | M5: 94962 | N5: 269.77 | P5: =P6+1 -> 46080 | Q5: -2378.5037 | R5: 94962 | S5: 93643 | T5: 352 | U5: 92 | V5: 1319 | W5: 0 | X5: 0 | Y5: 1563.72 | Z5: -1563.72 | AA5: 734752.98 | AB5: 685755.37 | AC5: 724516.44 | AD5: 4628.2 | AE5: 2559.04 | AF5: 38.0387 | AG5: 0 | AH5: 0 | AI5: 0 | AJ5: 0 | AK5: 3011.2563 | AL5: 2734.5 | AM5: 2453.5 | AN5: 1846.5 | AO5: 0 | AP5: 46 | AQ5: 0 | AR5: 0 | AS5: 0 | AT5: 0 | AU5: 0 | AV5: 842 | AW5: 0 | AX5: 0 | AY5: 0 | AZ5: 0 | BA5: 0 | BB5: 0 | BC5: 0 | BD5: 0 | BE5: 0 | BF5: 0 | BG5: 0 | BH5: 0 | BI5: 0 | BJ5: 0 | BK5: 0 | BL5: 0 | BM5: 0.17 | BN5: 0 | BO5: 0 | BP5: 0 | BQ5: 0 | BR5: 0 | BS5: -0.17 | BT5: 4639.9 | BU5: 4639.9 | BV5: 4734.4 | BW5: 0 | BX5: 0 | BY5: 0 | BZ5: 0 | CA5: 0 | CB5: 0 | CC5: 0 | CD5: -94.5 | CE5: 0 | CF5: 0 | CG5: 0 | CH5: 0 | CI5: 0 | CJ5: 0 | CK5: 0 | CL5: 0 | CM5: 0 | CN5: 0 | CO5: 0 | CP5: 2 | CQ5: 2 | CR5: 0 | CS5: 0 | CT5: 0 | CU5: 0 | CV5: 0 | CW5: 0 | CX5: 0 | CY5: 0 | CZ5: 0 | DA5: 2 | DB5: 0 | DC5: 0 | DD5: 4405.3 | DE5: 0 | DF5: 0 | DG5: 0 | DH5: 150 | DI5: 15 | DJ5: 5.07 | DK5: 0 | DL5: 0 | DM5: -4575.37 | DN5: 94316.745 | DO5: 459403.19 | DP5: 94316.745 | DQ5: 96202.404 | DR5: 448009.19 | DS5: 96202.404
A6: =A7+1 -> 46079 | B6: 43919 | C6: 3223 | D6: 2304 | E6: 437 | F6: 108 | G6: 594 | H6: 388 | I6: 172 | J6: 58 | K6: 2635 | L6: 6723 | M6: 96473 | N6: 220.76 | P6: =P7+1 -> 46079 | Q6: -4441.5865 | R6: 96473 | S6: 89750 | T6: 437 | U6: 108 | V6: 6723 | W6: 0 | X6: 0 | Y6: 1502.14 | Z6: -1502.14 | AA6: 821477.24 | AB6: 773582.83 | AC6: 808905.75 | AD6: 8075.7 | AE6: 3055.64 | AF6: 39.4043 | AG6: 0 | AH6: 0 | AI6: 0 | AJ6: 0 | AK6: 1400.7435 | AL6: 18235.59 | AM6: 17330.59 | AN6: 19190 | AO6: 0 | AP6: 20.86 | AQ6: 0 | AR6: 0 | AS6: 0 | AT6: 0 | AU6: 0 | AV6: -975.27 | AW6: 0 | AX6: 0 | AY6: 0 | AZ6: 0 | BA6: 0 | BB6: 0 | BC6: 0 | BD6: 0 | BE6: 0 | BF6: 0 | BG6: 0 | BH6: 0 | BI6: 60 | BJ6: 60 | BK6: 0 | BL6: 0 | BM6: 0 | BN6: 0 | BO6: 0 | BP6: 0 | BQ6: 0 | BR6: 0 | BS6: 60 | BT6: 13524.8 | BU6: 13332 | BV6: 12056.66 | BW6: 0 | BX6: 0 | BY6: 0 | BZ6: 0 | CA6: 0 | CB6: 0 | CC6: 0 | CD6: 1468.14 | CE6: 0 | CF6: 0 | CG6: 0 | CH6: 0 | CI6: 0 | CJ6: 0 | CK6: 0 | CL6: 0 | CM6: 0 | CN6: 0 | CO6: 0 | CP6: 1 | CQ6: 1 | CR6: 0 | CS6: 0 | CT6: 0 | CU6: 0 | CV6: 0 | CW6: 0 | CX6: 0 | CY6: 0 | CZ6: 0 | DA6: 1 | DB6: 0 | DC6: 0 | DD6: 4829 | DE6: 0 | DF6: 0 | DG6: 0 | DH6: 60 | DI6: 0 | DJ6: 5.06 | DK6: 0 | DL6: 0 | DM6: -4894.06 | DN6: 96459.381 | DO6: 442980.49 | DP6: 96459.381 | DQ6: 94316.745 | DR6: 459403.19 | DS6: 94316.745
A7: =A8+1 -> 46078 | B7: 43332 | C7: 3611 | D7: 2548 | E7: 481 | F7: 97 | G7: 826 | H7: 488 | I7: 213 | J7: 53 | K7: 2869 | L7: 17282 | M7: 92719 | N7: 192.76 | P7: =P8+1 -> 46078 | Q7: -1655.4399 | R7: 92719 | S7: 75437 | T7: 481 | U7: 97 | V7: 17282 | W7: 0 | X7: 0 | Y7: 1490.23 | Z7: -1490.23 | AA7: 840574.91 | AB7: 789677.61 | AC7: 823468.45 | AD7: 7556.2 | AE7: 3869.24 | AF7: 40.7879 | AG7: 0 | AH7: 0 | AI7: 0 | AJ7: 0 | AK7: 5640.2271 | AL7: 15722.08 | AM7: 15443.58 | AN7: 15147.22 | AO7: 0 | AP7: 37.62 | AQ7: 0 | AR7: 0 | AS7: 0 | AT7: 0 | AU7: 0 | AV7: 537.24 | AW7: 0 | AX7: 0 | AY7: 0 | AZ7: 0 | BA7: 0 | BB7: 0 | BC7: 0 | BD7: 0 | BE7: 0 | BF7: 0 | BG7: 0 | BH7: 0 | BI7: 0 | BJ7: 0 | BK7: 0 | BL7: 0 | BM7: 0 | BN7: 0 | BO7: 0 | BP7: 0 | BQ7: 0 | BR7: 0 | BS7: 0 | BT7: 17582.43 | BU7: 17427.73 | BV7: 18115.62 | BW7: 0 | BX7: 0 | BY7: 0 | BZ7: 0 | CA7: 0 | CB7: 0 | CC7: 0 | CD7: -533.19 | CE7: 100 | CF7: 100 | CG7: 0 | CH7: 0 | CI7: 0 | CJ7: 0 | CK7: 0 | CL7: 0 | CM7: 0 | CN7: 0 | CO7: 100 | CP7: 4 | CQ7: 4 | CR7: 0 | CS7: 0 | CT7: 0 | CU7: 0 | CV7: 0 | CW7: 0 | CX7: 0 | CY7: 0 | CZ7: 0 | DA7: 4 | DB7: 0 | DC7: 0 | DD7: 5682.31 | DE7: 0 | DF7: 0 | DG7: 0 | DH7: 210 | DI7: 15 | DJ7: 6.177 | DK7: 0 | DL7: 0 | DM7: -5913.487 | DN7: 93016.966 | DO7: 488797.49 | DP7: 93016.966 | DQ7: 96459.381 | DR7: 442980.49 | DS7: 96459.381
A8: =A9+1 -> 46077 | B8: 42520 | C8: 3785 | D8: 2686 | E8: 498 | F8: 95 | G8: 707 | H8: 455 | I8: 199 | J8: 50 | K8: 3090 | L8: 61492 | M8: 120843 | N8: 242.65 | P8: =P9+1 -> 46077 | Q8: 45355.231 | R8: 120843 | S8: 59351 | T8: 498 | U8: 95 | V8: 61492 | W8: 0 | X8: 0 | Y8: 1945.67 | Z8: -1945.67 | AA8: 1086922.3 | AB8: 1020854.9 | AC8: 1029615.4 | AD8: 7578.4 | AE8: 2413.28 | AF8: 50.5814 | AG8: 0 | AH8: 0 | AI8: 0 | AJ8: 0 | AK8: 47264.624 | AL8: 14221.23 | AM8: 13642.73 | AN8: 10874.82 | AO8: 0 | AP8: 4.67 | AQ8: 0 | AR8: 0 | AS8: 0 | AT8: 0 | AU8: 0 | AV8: 3341.74 | AW8: 0 | AX8: 0 | AY8: 0 | AZ8: 0 | BA8: 0 | BB8: 0 | BC8: 0 | BD8: 0 | BE8: 0 | BF8: 0 | BG8: 0 | BH8: 0 | BI8: 1 | BJ8: 0.5 | BK8: 0 | BL8: 0 | BM8: 0 | BN8: 0 | BO8: 0 | BP8: 0 | BQ8: 0 | BR8: 0 | BS8: 1 | BT8: 71861.15 | BU8: 71783.85 | BV8: 69691.8 | BW8: 0 | BX8: 0 | BY8: 0 | BZ8: 0 | CA8: 0 | CB8: 0 | CC8: 0 | CD8: 2169.35 | CE8: 2018 | CF8: 1998 | CG8: 1416.17 | CH8: 0 | CI8: 0 | CJ8: 0 | CK8: 0 | CL8: 0 | CM8: 0 | CN8: 0 | CO8: 601.83 | CP8: 2 | CQ8: 2 | CR8: 0 | CS8: 0 | CT8: 0 | CU8: 0 | CV8: 0 | CW8: 0 | CX8: 0 | CY8: 0 | CZ8: 0 | DA8: 2 | DB8: 0 | DC8: 0 | DD8: 5658.37 | DE8: 0 | DF8: 0 | DG8: 0 | DH8: 360 | DI8: 55 | DJ8: 6.273 | DK8: 0 | DL8: 0 | DM8: -6079.643 | DN8: 88711.731 | DO8: 488188.25 | DP8: 88711.731 | DQ8: 93016.966 | DR8: 488797.49 | DS8: 93016.966
A9: =A10+1 -> 46076 | B9: 41903 | C9: 3493 | D9: 2358 | E9: 419 | F9: 94 | G9: 623 | H9: 373 | I9: 161 | J9: 49 | K9: 2823 | L9: 7755 | M9: 75103 | N9: 179.24 | P9: =P10+1 -> 46076 | Q9: 4673.82 | R9: 75103 | S9: 67348 | T9: 419 | U9: 94 | V9: 7755 | W9: 0 | X9: 0 | Y9: 1245.56 | Z9: -1245.56 | AA9: 767010.59 | AB9: 719505.38 | AC9: 740575.58 | AD9: 7095.2 | AE9: 5099.51 | AF9: 56.636 | AG9: 0 | AH9: 0 | AI9: 0 | AJ9: 0 | AK9: 14183.664 | AL9: 3935 | AM9: 3935 | AN9: 4190 | AO9: 0 | AP9: 307.42 | AQ9: 0 | AR9: 0 | AS9: 0 | AT9: 0 | AU9: 0 | AV9: -562.42 | AW9: 0 | AX9: 0 | AY9: 0 | AZ9: 0 | BA9: 0 | BB9: 0 | BC9: 0 | BD9: 0 | BE9: 0 | BF9: 0 | BG9: 0 | BH9: 0 | BI9: 0 | BJ9: 0 | BK9: 0 | BL9: 0 | BM9: 0 | BN9: 0 | BO9: 0 | BP9: 0 | BQ9: 0 | BR9: 0 | BS9: 0 | BT9: 27093.9 | BU9: 27093.9 | BV9: 28727.6 | BW9: 0 | BX9: 0 | BY9: 0 | BZ9: 0 | CA9: 0 | CB9: 0 | CC9: 0 | CD9: -1633.7 | CE9: 1495.1 | CF9: 1416.1 | CG9: 981.32 | CH9: 0 | CI9: 0 | CJ9: 0 | CK9: 0 | CL9: 0 | CM9: 0 | CN9: 0 | CO9: 513.78 | CP9: 6 | CQ9: 6 | CR9: 1080 | CS9: 0 | CT9: 0 | CU9: 0 | CV9: 0 | CW9: 0 | CX9: 0 | CY9: 0 | CZ9: 0 | DA9: -1074 | DB9: 0 | DC9: 0 | DD9: 5106.9 | DE9: 0 | DF9: 0 | DG9: 0 | DH9: 360 | DI9: 35 | DJ9: 6.044 | DK9: 0 | DL9: 0 | DM9: -5507.944 | DN9: 87680.771 | DO9: 482503.45 | DP9: 87680.771 | DQ9: 88711.731 | DR9: 488188.25 | DS9: 88711.731
A10: =A11+1 -> 46075 | B10: 41171 | C10: 3650 | D10: 2691 | E10: 509 | F10: 117 | G10: 600 | H10: 445 | I10: 208 | J10: 73 | K10: 3089 | L10: 31371 | M10: 123790 | N10: 243.2 | P10: =P11+1 -> 46075 | Q10: 25652.215 | R10: 123790 | S10: 92419 | T10: 509 | U10: 117 | V10: 31371 | W10: 0 | X10: 0 | Y10: 2017.75 | Z10: -2017.75 | AA10: 1282834.1 | AB10: 1205444.1 | AC10: 1257340 | AD10: 8814.4 | AE10: 2430.01 | AF10: 52.5976 | AG10: 0 | AH10: 0 | AI10: 0 | AJ10: 0 | AK10: 14197.057 | AL10: 75223 | AM10: 74523 | AN10: 55475.5 | AO10: 0 | AP10: 157.01 | AQ10: 0 | AR10: 0 | AS10: 0 | AT10: 0 | AU10: 0 | AV10: 19590.49 | AW10: 0 | AX10: 0 | AY10: 0 | AZ10: 0 | BA10: 0 | BB10: 0 | BC10: 0 | BD10: 0 | BE10: 0 | BF10: 0 | BG10: 0 | BH10: 0 | BI10: 0 | BJ10: 0 | BK10: 0 | BL10: 0 | BM10: 0 | BN10: 0 | BO10: 0 | BP10: 0 | BQ10: 0 | BR10: 0 | BS10: 0 | BT10: 9369.9 | BU10: 9369.9 | BV10: 9514.16 | BW10: 0 | BX10: 0 | BY10: 0 | BZ10: 0 | CA10: 0 | CB10: 0 | CC10: 0 | CD10: -144.26 | CE10: 100 | CF10: 100 | CG10: 0 | CH10: 0 | CI10: 0 | CJ10: 0 | CK10: 0 | CL10: 0 | CM10: 0 | CN10: 0 | CO10: 100 | CP10: 9 | CQ10: 9 | CR10: 0 | CS10: 0 | CT10: 0 | CU10: 0 | CV10: 0 | CW10: 0 | CX10: 0 | CY10: 0 | CZ10: 0 | DA10: 9 | DB10: 0 | DC10: 0 | DD10: 5699.75 | DE10: 0 | DF10: 0 | DG10: 0 | DH10: 360 | DI10: 15 | DJ10: 7.572 | DK10: 0 | DL10: 0 | DM10: -6082.322 | DN10: 90410.522 | DO10: 487873.45 | DP10: 90410.522 | DQ10: 87680.771 | DR10: 482503.45 | DS10: 87680.771
A11: =A12+1 -> 46074 | B11: 40581 | C11: 3808 | D11: 2628 | E11: 554 | F11: 106 | G11: 676 | H11: 438 | I11: 227 | J11: 48 | K11: 3124 | L11: 58693 | M11: 128243 | N11: 231.48 | P11: =P12+1 -> 46074 | Q11: 45803.051 | R11: 128243 | S11: 69550 | T11: 554 | U11: 106 | V11: 58693 | W11: 0 | X11: 0 | Y11: 2030.24 | Z11: -2030.24 | AA11: 910332.01 | AB11: 853371.16 | AC11: 856643.71 | AD11: 10132 | AE11: 3998.37 | AF11: 45.0094 | AG11: 0 | AH11: 0 | AI11: 0 | AJ11: 0 | AK11: 39512.921 | AL11: 42245 | AM11: 41881 | AN11: 28142.5 | AO11: 0 | AP11: 16.42 | AQ11: 0.06 | AR11: 0 | AS11: 0 | AT11: 0 | AU11: 0 | AV11: 14086.02 | AW11: 0 | AX11: 0 | AY11: 0 | AZ11: 0 | BA11: 0 | BB11: 0 | BC11: 0 | BD11: 0 | BE11: 0 | BF11: 0 | BG11: 0 | BH11: 0 | BI11: 0 | BJ11: 0 | BK11: 0 | BL11: 0 | BM11: 0 | BN11: 0 | BO11: 0 | BP11: 0 | BQ11: 0 | BR11: 0 | BS11: 0 | BT11: 15435.25 | BU11: 15435.25 | BV11: 15335.42 | BW11: 0 | BX11: 0 | BY11: 0 | BZ11: 0 | CA11: 0 | CB11: 0 | CC11: 0 | CD11: 99.83 | CE11: 200 | CF11: 200 | CG11: 115 | CH11: 0 | CI11: 0 | CJ11: 0 | CK11: 0 | CL11: 0 | CM11: 0 | CN11: 0 | CO11: 85 | CP11: 2 | CQ11: 2 | CR11: 0 | CS11: 0 | CT11: 0 | CU11: 0 | CV11: 0 | CW11: 0 | CX11: 0 | CY11: 0 | CZ11: 0 | DA11: 2 | DB11: 0 | DC11: 0 | DD11: 5590.83 | DE11: 0 | DF11: 0 | DG11: 0 | DH11: 330 | DI11: 25 | DJ11: 6.65 | DK11: 0 | DL11: 0 | DM11: -5952.48 | DN11: 92945.162 | DO11: 482420.09 | DP11: 92945.162 | DQ11: 90410.522 | DR11: 487873.45 | DS11: 90410.522
A12: =A13+1 -> 46073 | B12: 39911 | C12: 4200 | D12: 2965 | E12: 625 | F12: 126 | G12: 739 | H12: 512 | I12: 272 | J12: 62 | K12: 3459 | L12: 34543 | M12: 139268 | N12: 222.82 | P12: =P13+1 -> 46073 | Q12: 11486.965 | R12: 139268 | S12: 104725 | T12: 625 | U12: 126 | V12: 34543 | W12: 0 | X12: 0 | Y12: 2285.87 | Z12: -2285.87 | AA12: 1259267.6 | AB12: 1158886.3 | AC12: 1233542.8 | AD12: 13097.1 | AE12: 4704.36 | AF12: 63.9716 | AG12: 0 | AH12: 0 | AI12: 0 | AJ12: 0 | AK12: 7859.384 | AL12: 7031.44 | AM12: 6418.44 | AN12: 5330.46 | AO12: 0 | AP12: 23.94 | AQ12: 0.31 | AR12: 0 | AS12: 0 | AT12: 0 | AU12: 0 | AV12: 1676.73 | AW12: 0 | AX12: 0 | AY12: 0 | AZ12: 0 | BA12: 0 | BB12: 0 | BC12: 0 | BD12: 0 | BE12: 0 | BF12: 0 | BG12: 0 | BH12: 0 | BI12: 0 | BJ12: 0 | BK12: 0 | BL12: 0 | BM12: 1.06 | BN12: 0 | BO12: 0 | BP12: 0 | BQ12: 0 | BR12: 0 | BS12: -1.06 | BT12: 31820.1 | BU12: 31820.1 | BV12: 20901.79 | BW12: 0 | BX12: 0 | BY12: 0 | BZ12: 0 | CA12: 0 | CB12: 0 | CC12: 0 | CD12: 10918.31 | CE12: 200 | CF12: 200 | CG12: 0 | CH12: 0 | CI12: 0 | CJ12: 0 | CK12: 0 | CL12: 0 | CM12: 0 | CN12: 0 | CO12: 200 | CP12: 17 | CQ12: 17 | CR12: 0 | CS12: 0 | CT12: 0 | CU12: 0 | CV12: 0 | CW12: 0 | CX12: 0 | CY12: 0 | CZ12: 0 | DA12: 17 | DB12: 0 | DC12: 0 | DD12: 6505.83 | DE12: 0 | DF12: 0 | DG12: 0 | DH12: 270 | DI12: 115 | DJ12: 6.699 | DK12: 0 | DL12: 0 | DM12: -6897.529 | DN12: 84574.532 | DO12: 470218.93 | DP12: 84574.532 | DQ12: 92945.162 | DR12: 482420.09 | DS12: 92945.162
A13: =A14+1 -> 46072 | B13: 39300 | C13: 4710 | D13: 3204 | E13: 667 | F13: 147 | G13: 1186 | H13: 753 | I13: 344 | J13: 89 | K13: 3798 | L13: 44346 | M13: 146521 | N13: 219.67 | P13: =P14+1 -> 46072 | Q13: -23378.276 | R13: 146521 | S13: 102175 | T13: 667 | U13: 147 | V13: 44346 | W13: 0 | X13: 0 | Y13: 2374.79 | Z13: -2374.79 | AA13: 1445994.2 | AB13: 1337299.5 | AC13: 1441145.2 | AD13: 15475.8 | AE13: 3475.02 | AF13: 49.71 | AG13: 0 | AH13: 0 | AI13: 0 | AJ13: 0 | AK13: -14151.52 | AL13: 11203.77 | AM13: 10895.77 | AN13: 10535.2 | AO13: 0 | AP13: 2.28 | AQ13: 0 | AR13: 0 | AS13: 0 | AT13: 0 | AU13: 0 | AV13: 666.29 | AW13: 0 | AX13: 0 | AY13: 0 | AZ13: 0 | BA13: 0 | BB13: 0 | BC13: 0 | BD13: 0 | BE13: 0 | BF13: 0 | BG13: 0 | BH13: 0 | BI13: 358 | BJ13: 358 | BK13: 366 | BL13: 0 | BM13: 0.63 | BN13: 0 | BO13: 0 | BP13: 0 | BQ13: 0 | BR13: 0 | BS13: -8.63 | BT13: 11893 | BU13: 11851 | BV13: 11878.7 | BW13: 0 | BX13: 0 | BY13: 0 | BZ13: 0 | CA13: 0 | CB13: 0 | CC13: 0 | CD13: 14.3 | CE13: 1079 | CF13: 1079 | CG13: 1224.31 | CH13: 0 | CI13: 0 | CJ13: 0 | CK13: 0 | CL13: 0 | CM13: 0 | CN13: 0 | CO13: -145.31 | CP13: 26 | CQ13: 26 | CR13: 180 | CS13: 0 | CT13: 0 | CU13: 0 | CV13: 0 | CW13: 0 | CX13: 0 | CY13: 0 | CZ13: 0 | DA13: -154 | DB13: 0 | DC13: 0 | DD13: 6847.96 | DE13: 0 | DF13: 0 | DG13: 0 | DH13: 330 | DI13: 40 | DJ13: 6.656 | DK13: 0 | DL13: 0 | DM13: -7224.616 | DN13: 81187.696 | DO13: 416200.2 | DP13: 81187.696 | DQ13: 84574.532 | DR13: 470218.93 | DS13: 84574.532
A14: =A15+1 -> 46071 | B14: 37987 | C14: 4444 | D14: 3251 | E14: 670 | F14: 151 | G14: 829 | H14: 598 | I14: 291 | J14: 92 | K14: 3747 | L14: 23017 | M14: 131088 | N14: 195.65 | P14: =P15+1 -> 46071 | Q14: 38224.337 | R14: 131088 | S14: 108071 | T14: 670 | U14: 151 | V14: 23017 | W14: 0 | X14: 0 | Y14: 2120.79 | Z14: -2120.79 | AA14: 1227872.2 | AB14: 1112240.7 | AC14: 1158142.1 | AD14: 16912.3 | AE14: 4534.93 | AF14: 73.8911 | AG14: 0 | AH14: 0 | AI14: 0 | AJ14: 0 | AK14: 48208.994 | AL14: 900 | AM14: 777 | AN14: 663 | AO14: 0 | AP14: 3.74 | AQ14: 0.33 | AR14: 0 | AS14: 0 | AT14: 0 | AU14: 0 | AV14: 232.93 | AW14: 0 | AX14: 0 | AY14: 0 | AZ14: 0 | BA14: 0 | BB14: 0 | BC14: 0 | BD14: 0 | BE14: 0 | BF14: 0 | BG14: 0 | BH14: 0 | BI14: 216 | BJ14: 214 | BK14: 12 | BL14: 0 | BM14: 0.17 | BN14: 0 | BO14: 0 | BP14: 0 | BQ14: 0 | BR14: 0 | BS14: 203.83 | BT14: 5999.37 | BU14: 5999.37 | BV14: 6058.81 | BW14: 0 | BX14: 0 | BY14: 0 | BZ14: 0 | CA14: 0 | CB14: 0 | CC14: 0 | CD14: -59.44 | CE14: 0 | CF14: 0 | CG14: 0 | CH14: 0 | CI14: 0 | CJ14: 0 | CK14: 0 | CL14: 0 | CM14: 0 | CN14: 0 | CO14: 0 | CP14: 13 | CQ14: 13 | CR14: 0 | CS14: 0 | CT14: 0 | CU14: 0 | CV14: 0 | CW14: 0 | CX14: 0 | CY14: 0 | CZ14: 0 | DA14: 13 | DB14: 0 | DC14: 0 | DD14: 7810.81 | DE14: 0 | DF14: 0 | DG14: 0 | DH14: 420 | DI14: 15 | DJ14: 8.377 | DK14: 0 | DL14: 0 | DM14: -8254.187 | DN14: 85921.388 | DO14: 419731.53 | DP14: 85921.388 | DQ14: 81187.696 | DR14: 416200.2 | DS14: 81187.696
A15: =A16+1 -> 46070 | B15: 37169 | C15: 5216 | D15: 3764 | E15: 787 | F15: 180 | G15: 881 | H15: 723 | I15: 378 | J15: 119 | K15: 4379 | L15: 49826 | M15: 165666 | N15: 210.5 | P15: =P16+1 -> 46070 | Q15: 24432.924 | R15: 165666 | S15: 115840 | T15: 787 | U15: 180 | V15: 49826 | W15: 0 | X15: 0 | Y15: 2652.23 | Z15: -2652.23 | AA15: 1509509.3 | AB15: 1401706 | AC15: 1449055.7 | AD15: 21277.1 | AE15: 4494.99 | AF15: 61.7902 | AG15: 0 | AH15: 0 | AI15: 0 | AJ15: 0 | AK15: 34619.67 | AL15: 2993 | AM15: 2811.5 | AN15: 2564.5 | AO15: 0 | AP15: 6.78 | AQ15: 0.03 | AR15: 0 | AS15: 0 | AT15: 0 | AU15: 0 | AV15: 421.69 | AW15: 0 | AX15: 0 | AY15: 0 | AZ15: 0 | BA15: 0 | BB15: 0 | BC15: 0 | BD15: 0 | BE15: 0 | BF15: 0 | BG15: 0 | BH15: 0 | BI15: 63 | BJ15: 61.5 | BK15: 119.72 | BL15: 0 | BM15: 0 | BN15: 0 | BO15: 0 | BP15: 0 | BQ15: 0 | BR15: 0 | BS15: -56.72 | BT15: 9362 | BU15: 9292.8 | BV15: 8367.69 | BW15: 0 | BX15: 0 | BY15: 0 | BZ15: 0 | CA15: 0 | CB15: 0 | CC15: 0 | CD15: 994.31 | CE15: 1000 | CF15: 50 | CG15: 950 | CH15: 0 | CI15: 0 | CJ15: 0 | CK15: 0 | CL15: 0 | CM15: 0 | CN15: 0 | CO15: 50 | CP15: 9 | CQ15: 9 | CR15: 90 | CS15: 0 | CT15: 0 | CU15: 0 | CV15: 0 | CW15: 0 | CX15: 0 | CY15: 0 | CZ15: 0 | DA15: -81 | DB15: 0 | DC15: 0 | DD15: 8379.8 | DE15: 0 | DF15: 0 | DG15: 0 | DH15: 390 | DI15: 85 | DJ15: 7.996 | DK15: 0 | DL15: 0 | DM15: -8862.796 | DN15: 83755.852 | DO15: 398227.72 | DP15: 83755.852 | DQ15: 85921.388 | DR15: 419731.53 | DS15: 85921.388
... A22: =A23+1 -> 46063 | B22: 16 | C22: 4 | D22: 0 | E22: 0 | F22: 0 | G22: 1 | H22: 0 | I22: 0 | J22: 0 | K22: 3 | L22: 0 | M22: 0 | N22: 0 | P22: =P23+1 -> 46063 | Q22: -39 | R22: 0 | S22: 0 | T22: 0 | U22: 0 | V22: 0 | W22: 0 | X22: 0 | Y22: 0 | Z22: 0 | AA22: 0 | AB22: 0 | AC22: 0 | AD22: 8 | AE22: 0 | AF22: 0 | AG22: 0 | AH22: 0 | AI22: 0 | AJ22: 0 | AK22: -8 | AL22: 0 | AM22: 0 | AN22: 0 | AO22: 0 | AP22: 0 | AQ22: 0 | AR22: 0 | AS22: 0 | AT22: 0 | AU22: 0 | AV22: 0 | AW22: 0 | AX22: 0 | AY22: 0 | AZ22: 0 | BA22: 0 | BB22: 0 | BC22: 0 | BD22: 0 | BE22: 0 | BF22: 0 | BG22: 0 | BH22: 0 | BI22: 0 | BJ22: 0 | BK22: 0 | BL22: 0 | BM22: 0 | BN22: 0 | BO22: 0 | BP22: 0 | BQ22: 0 | BR22: 0 | BS22: 0 | BT22: 0 | BU22: 0 | BV22: 0 | BW22: 0 | BX22: 0 | BY22: 0 | BZ22: 0 | CA22: 0 | CB22: 0 | CC22: 0 | CD22: 0 | CE22: 0 | CF22: 0 | CG22: 0 | CH22: 0 | CI22: 0 | CJ22: 0 | CK22: 0 | CL22: 0 | CM22: 0 | CN22: 0 | CO22: 0 | CP22: 0 | CQ22: 0 | CR22: 0 | CS22: 0 | CT22: 0 | CU22: 0 | CV22: 0 | CW22: 0 | CX22: 0 | CY22: 0 | CZ22: 0 | DA22: 0 | DB22: 0 | DC22: 0 | DD22: 31 | DE22: 0 | DF22: 0 | DG22: 0 | DH22: 0 | DI22: 0 | DJ22: 0 | DK22: 0 | DL22: 0 | DM22: -31 | DN22: 0 | DO22: 0 | DP22: 0 | DQ22: 619 | DR22: 0 | DS22: 619
A23: =A24+1 -> 46062 | P23: =P24+1 -> 46062
A24: =A25+1 -> 46061 | P24: =P25+1 -> 46061
A25: =A26+1 -> 46060 | P25: =P26+1 -> 46060
A26: =A27+1 -> 46059 | P26: =P27+1 -> 46059
A27: =A28+1 -> 46058 | P27: =P28+1 -> 46058
A28: =A29+1 -> 46057 | P28: =P29+1 -> 46057
A29: =A30+1 -> 46056 | P29: =P30+1 -> 46056
A30: =A31+1 -> 46055 | P30: =P31+1 -> 46055
A31: 46054 | P31: =A31 -> 46054

Sheet jiliarena
A1: jiliarena | W1: 净输/投注 | Z1: 净赢/中奖 | BW1: 8月 | BX1: 手续费费率 | BY1: 0.0241 | BZ1: 0.002
B2: 报表管理-平台损益总表 | C2: 报表管理-平台损益总表 | D2: 报表管理-平台损益总表 | E2: 报表管理-留存用户分析 | F2: 报表管理-平台损益总表 | G2: 报表管理-平台损益-充值 | H2: 报表管理-平台损益总表 | J2: 报表管理-平台损益总表 | L2: 报表管理-平台损益总表 | M2: 报表管理-平台损益总表 | W2: 报表管理-游戏玩家分析 | X2: 报表管理-游戏玩家分析 | Y2: 报表管理-游戏玩家分析 | Z2: 报表管理-游戏玩家分析 | AT2: GAME_REBATE | AU2: APP_DOWNLOAD | AV2: DEPOSIT | AW2: LOGIN | AX2: UPGRADE_BONUS | AY2: MANUAL | BA2: PROMO_CODE | BB2: 邀请返佣 | BC2: LOGIN_TASK | BD2: DEPOSIT_BET_BONUS | BE2: SAVIOR | BF2: MISSION | BG2: RANK_SALARY | BH2: SECOND_DEPOSIT | BI2: THIRD_DEPOSIT | BJ2: FIRST_DEPOSIT | BY2: 报表管理-平台损益-手续费 | BZ2: 报表管理-平台损益-手续费 | CF2: 报表管理-平台损益-平台毛利 | CG2: 报表管理-平台损益-平台毛利 | CH2: 报表管理-平台损益-平台毛利
B3: 注册人数 | C3: 首充人数 | D3: 登录人数 | E3: 报表管理-留存用户分析 | F3: 存款人数 | G3: 存款次数 | H3: 提款人数 | I3: 出款笔数 | J3: 投注人数 | K3: 总首存 | L3: 日充值 | M3: 提款金额 | N3: 公式 | O3: 公式 | P3: 公式 | Q3: 公式 | R3: 公式 | S3: 公式 | T3: 公式 | U3: 公式 | V3: 公式 | W3: 投注 | X3: 有效投注 | Y3: 公司输赢 | Z3: 派彩 | AA3: 公式 | AB3: 棋牌输额 | AC3: 棋牌赢额 | AD3: 公式 | AE3: 电子投注 | AF3: 电子中奖 | AG3: 公式 | AH3: 真人投注 | AI3: 真人中奖 | AJ3: 公式 | AK3: 捕鱼投注 | AL3: 捕鱼中奖 | AM3: 公式 | AN3: 体育投注 | AO3: 体育中奖 | AP3: 公式 | AQ3: 盘口彩票投注 | AR3: 盘口彩票中奖 | AS3: 公式 | AT3: 玩家返水 | AU3: APP下载 | AV3: 笔笔存送 | AW3: 签到奖励 | AX3: 升级奖励 | AY3: 手动红利 | AZ3: 红利扣除 | BA3: 优惠码 | BB3: 邀请返佣 | BC3: 登录任务 | BD3: 存款达标奖励 | BE3: 关怀援助金 | BF3: 任务排行榜 | BG3: VIP俸禄 | BH3: 二次存送 | BI3: 三次存送 | BJ3: 首存 | BK3: 新手任务奖励 | BL3: 注册奖励 | BM3: 四次存送 | BN3: 五次存送 | BQ3: 总优惠 | BR3: 返点 | BS3: 代理贡献层级 | BT3: 公式 | BW3: 公式 | BY3: 渠道手续费 | BZ3: 玩家提现手续费 | CA3: 公式 | CB3: 公式 | CD3: 代理佣金（周） | CE3: 代理佣金（月 | CF3: 开分 | CG3: 洗分 | CH3: 结算余额
A4: 时间 Date | B4: 平台新注册人数 Total New Users | C4: 总首充人数 first depositor / no of first time depositors | D4: 总登录人数 Login Head Count | E4: 续存人数 Number of survivors | F4: 总存款人数 no of total depositors | G4: 总存款次数 deposit times / total deposit counts | H4: 总取款人数 no of total withdrawer | I4: 总取款次数 withdrawal times / total withdrawal counts | J4: 总投注人数 no of bettors / No of bet | K4: 首存金额 First deposit amount | L4: 总存款额度 total deposit amount | M4: 总取款额度 total withdrawal amount | N4: 平台转化率 Conversion rate | O4: 人均首存金额 | P4: 首存比例存款 First deposit ratio total deposit | Q4: 人均次数 Per capita times | R4: 人均入款 Per capita deposit | S4: 單次人均入款 | T4: 續存/首存 比 | U4: 人均提款 Withdrawal per capita | V4: 存提差 Deposit/withdrawal difference | W4: 投注 Betting | X4: 有效投注额 Valid bet | Y4: 公司输赢 Win or lose | Z4: 派彩 Payouts | AA4: 杀率 kill rate | AB4: 棋牌投注 PVP Bet | AC4: 棋牌赢额 PVP Win | AD4: 棋牌杀率 PVP kill rate | AE4: 電子投注 RNG Bet | AF4: 電子中獎 RNG Win | AG4: 電子杀率 RNG kill rate | AH4: 真人投注 LIVE Bet | AI4: 真人中獎 LIVE Win | AJ4: 真人杀率 LIVE kill rate | AK4: 捕魚投注 FISH Bet | AL4: 捕魚中獎 FISH Win | AM4: 捕魚杀率 FISH kill rate | AN4: 體育投注 SPORTS Bet | AO4: 體育中獎 SPORTS Win | AP4: 體育杀率 SPORTS kill rate | AQ4: 盘口彩票投注 ELOTT Bet | AR4: 盘口彩票中獎 ELOTT Win | AS4: 盘口彩票 ELOTT kill rate | AT4: 玩家返水 | AU4: APP下载 | AV4: 笔笔存送 | AW4: 签到奖励 | AX4: 升级奖励 | AY4: 手动红利 | AZ4: 红利扣除 | BA4: 优惠码 | BB4: 邀请返佣 | BC4: 登录任务 | BD4: 存款达标奖励 | BE4: 关怀援助金 | BF4: 任务排行榜 | BG4: VIP俸禄 | BH4: 二次存送 | BI4: 三次存送 | BJ4: 首存 | BK4: 新手任务奖励 | BL4: 注册奖励 | BM4: 四次存送 | BN4: 五次存送 | BP4: 其他奖励 Other Bonus | BQ4: 总优惠 （Z+...+AH） Total Bonus | BR4: 返点 Rebates | BS4: 邀请返佣 Referral rebates | BT4: 优惠占比投注 Preferential ratio bet | BU4: 优惠占比充值 Bonus rebates | BV4: 优惠占比游戏亏损 Preferential astio loss | BW4: 公司净利 company net profit | BX4: 優惠/ 淨利 | BY4: 存款手续费 Deposit fees | BZ4: 提款手续费 Withdrawal fees | CA4: 支付手续费 service fees (Payment Channel Fee) | CB4: 预估平台费9% Estimate platform fee | CC4: 支付費用/淨利 | CD4: 代理佣金（周） Affiliate Commission (Weekly) | CE4: 代理佣金（月） Affiliate Commission (Monthly) | CF4: 開分 Credit Adjustment | CG4: 洗分 Debit Adjustment | CH4: 平台余额 Platform balance | CI4: 平台毛利 3 GP3 | CJ4: 月份 | CK4: 日期
A5: 46054 | B5: {=INDEX('jiliarena_日报_底稿'!$A$3:$N$31,MATCH($A5,'jiliarena_日报_底稿'!$A$3:$A$31,0),MATCH(B$3,'jiliarena_日报_底稿'!$A$3:$N$3,0))} | C5: {=INDEX('jiliarena_日报_底稿'!$A$3:$N$31,MATCH($A5,'jiliarena_日报_底稿'!$A$3:$A$31,0),MATCH(C$3,'jiliarena_日报_底稿'!$A$3:$N$3,0))} | D5: {=INDEX('jiliarena_日报_底稿'!$A$3:$N$31,MATCH($A5,'jiliarena_日报_底稿'!$A$3:$A$31,0),MATCH(D$3,'jiliarena_日报_底稿'!$A$3:$N$3,0))} | E5: 18 | F5: {=INDEX('jiliarena_日报_底稿'!$A$3:$N$31,MATCH($A5,'jiliarena_日报_底稿'!$A$3:$A$31,0),MATCH(F$3,'jiliarena_日报_底稿'!$A$3:$N$3,0))} | G5: =SUMIFS('渠道充值成功率_底稿'!$F:$F,'渠道充值成功率_底稿'!$A:$A,A5) -> 0 | H5: {=INDEX('jiliarena_日报_底稿'!$A$3:$N$31,MATCH($A5,'jiliarena_日报_底稿'!$A$3:$A$31,0),MATCH(H$3,'jiliarena_日报_底稿'!$A$3:$N$3,0))} | I5: 814 | J5: {=INDEX('jiliarena_日报_底稿'!$A$3:$N$31,MATCH($A5,'jiliarena_日报_底稿'!$A$3:$A$31,0),MATCH(J$3,'jiliarena_日报_底稿'!$A$3:$N$3,0))} | K5: =SUMIFS('渠道充值成功率_底稿'!$J:$J,'渠道充值成功率_底稿'!$A:$A,$A5) -> 0 | L5: {=INDEX('jiliarena_日报_底稿'!$A$3:$N$31,MATCH($A5,'jiliarena_日报_底稿'!$A$3:$A$31,0),MATCH(L$3,'jiliarena_日报_底稿'!$A$3:$N$3,0))} | M5: {=INDEX('jiliarena_日报_底稿'!$P$2:$DS$31,MATCH($A5,'jiliarena_日报_底稿'!$P$2:$P$31,0),MATCH($M$3,'jiliarena_日报_底稿'!$P$3:$DS$3,0))} | N5: =IF(C5="","",ROUND(C5/B5,4)) | O5: =IF(K5="","",ROUND(K5/C5,0)) -> #DIV/0! | P5: =IF(L5="","",ROUND(K5/L5,6)) | Q5: =IF(G5="","",ROUND(G5/F5,1)) -> #DIV/0! | R5: =IF(L5="","",ROUND(L5/F5,0)) | S5: =IF(L5="","",ROUND(L5/G5,0)) | T5: =IF(S5="","",ROUND(S5/O5,1)) | U5: =IF(M5="","",ROUND(M5/H5,0)) | V5: =IF(M5="","",L5-M5) | W5: =AB5+AE5+AH5+AK5+AN5+AQ5 -> 0 | X5: {=index('jiliarena_日报_底稿'!$P$2:$DS$31,match($A5,'jiliarena_日报_底稿'!$P$2:$P$31,0),match("电子有效投注",'jiliarena_日报_底稿'!$P$3:$DS$3,0))+index('jiliarena_日报_底稿'!$P$2:$DS$31,match($A5,'jiliarena_日报_底稿'!$P$2:$P$31,0),match("真人有效投注",'jiliarena_日报_底稿'!$P$3:$DS$3,0))+index('jiliarena_日报_底稿'!$P$2:$DS$31,match($A5,'jiliarena_日报_底稿'!$P$2:$P$31,0),match("彩票有效投注",'jiliarena_日报_底稿'!$P$3:$DS$3,0))+index('jiliarena_日报_底稿'!$P$2:$DS$31,match($A5,'jiliarena_日报_底稿'!$P$2:$P$31,0),match("棋牌有效投注",'jiliarena_日报_底稿'!$P$3:$DS$3,0))+index('jiliarena_日报_底稿'!$P$2:$DS$31,match($A5,'jiliarena_日报_底稿'!$P$2:$P$31,0),match("捕鱼有效投注",'jiliarena_日报_底稿'!$P$3:$DS$3,0))+index('jiliarena_日报_底稿'!$P$2:$DS$31,match($A5,'jiliarena_日报_底稿'!$P$2:$P$31,0),match("体育有效投注",'jiliarena_日报_底稿'!$P$3:$DS$3,0))+index('jiliarena_日报_底稿'!$P$2:$DS$31,match($A5,'jiliarena_日报_底稿'!$P$2:$P$31,0),match("盘口彩票有效投注",'jiliarena_日报_底稿'!$P$3:$DS$3,0))} -> 0 | Y5: =AB5+AE5+AH5+AK5+AN5+AQ5-AR5-AO5-AL5-AI5-AF5-AC5 -> 0 | Z5: =AC5+AF5+AI5+AL5+AO5+AR5 -> 0 | AA5: =IFERROR(ROUND(1-(Z5/W5),6),"") | AB5: {=INDEX('jiliarena_日报_底稿'!$P$2:$DS$31,MATCH($A5,'jiliarena_日报_底稿'!$P$2:$P$31,0),MATCH(AB$3,'jiliarena_日报_底稿'!$P$3:$DS$3,0))} | AC5: {=INDEX('jiliarena_日报_底稿'!$P$2:$DS$31,MATCH($A5,'jiliarena_日报_底稿'!$P$2:$P$31,0),MATCH(AC$3,'jiliarena_日报_底稿'!$P$3:$DS$3,0))} | AD5: =IF(AC5="","",ROUND((1-(AC5/AB5)),6)) | AE5: {=INDEX('jiliarena_日报_底稿'!$P$2:$DS$31,MATCH($A5,'jiliarena_日报_底稿'!$P$2:$P$31,0),MATCH(AE$3,'jiliarena_日报_底稿'!$P$3:$DS$3,0))} | AF5: {=INDEX('jiliarena_日报_底稿'!$P$2:$DS$31,MATCH($A5,'jiliarena_日报_底稿'!$P$2:$P$31,0),MATCH(AF$3,'jiliarena_日报_底稿'!$P$3:$DS$3,0))} | AG5: =IF(AF5="","",ROUND((1-(AF5/AE5)),6)) | AH5: {=INDEX('jiliarena_日报_底稿'!$P$2:$DS$31,MATCH($A5,'jiliarena_日报_底稿'!$P$2:$P$31,0),MATCH(AH$3,'jiliarena_日报_底稿'!$P$3:$DS$3,0))} | AI5: {=INDEX('jiliarena_日报_底稿'!$P$2:$DS$31,MATCH($A5,'jiliarena_日报_底稿'!$P$2:$P$31,0),MATCH(AI$3,'jiliarena_日报_底稿'!$P$3:$DS$3,0))} | AJ5: =IF(AI5="","",ROUND((1-(AI5/AH5)),6)) | AK5: {=INDEX('jiliarena_日报_底稿'!$P$2:$DS$31,MATCH($A5,'jiliarena_日报_底稿'!$P$2:$P$31,0),MATCH(AK$3,'jiliarena_日报_底稿'!$P$3:$DS$3,0))} | AL5: {=INDEX('jiliarena_日报_底稿'!$P$2:$DS$31,MATCH($A5,'jiliarena_日报_底稿'!$P$2:$P$31,0),MATCH(AL$3,'jiliarena_日报_底稿'!$P$3:$DS$3,0))} | AM5: =IF(AL5="","",ROUND((1-(AL5/AK5)),6)) | AN5: {=INDEX('jiliarena_日报_底稿'!$P$2:$DS$31,MATCH($A5,'jiliarena_日报_底稿'!$P$2:$P$31,0),MATCH(AN$3,'jiliarena_日报_底稿'!$P$3:$DS$3,0))} | AO5: {=INDEX('jiliarena_日报_底稿'!$P$2:$DS$31,MATCH($A5,'jiliarena_日报_底稿'!$P$2:$P$31,0),MATCH(AO$3,'jiliarena_日报_底稿'!$P$3:$DS$3,0))} | AP5: =IF(AO5="","",ROUND((1-(AO5/AN5)),6)) | AQ5: {=INDEX('jiliarena_日报_底稿'!$P$2:$DS$31,MATCH($A5,'jiliarena_日报_底稿'!$P$2:$P$31,0),MATCH(AQ$3,'jiliarena_日报_底稿'!$P$3:$DS$3,0))} | AR5: {=INDEX('jiliarena_日报_底稿'!$P$2:$DS$31,MATCH($A5,'jiliarena_日报_底稿'!$P$2:$P$31,0),MATCH(AR$3,'jiliarena_日报_底稿'!$P$3:$DS$3,0))} | AS5: =IF(AR5="","",ROUND((1-(AR5/AQ5)),6)) | AT5: =SUMIFS('jiliarena_活动分析数据_底稿'!$K:$K,'jiliarena_活动分析数据_底稿'!$B:$B,$A5,'jiliarena_活动分析数据_底稿'!$L:$L,AT$3) -> 0 | AU5: =SUMIFS('jiliarena_活动分析数据_底稿'!$K:$K,'jiliarena_活动分析数据_底稿'!$B:$B,$A5,'jiliarena_活动分析数据_底稿'!$L:$L,AU$3) -> 0 | AV5: =SUMIFS('jiliarena_活动分析数据_底稿'!$K:$K,'jiliarena_活动分析数据_底稿'!$B:$B,$A5,'jiliarena_活动分析数据_底稿'!$L:$L,AV$3) -> 0 | AW5: =SUMIFS('jiliarena_活动分析数据_底稿'!$K:$K,'jiliarena_活动分析数据_底稿'!$B:$B,$A5,'jiliarena_活动分析数据_底稿'!$L:$L,AW$3) -> 0 | AX5: =SUMIFS('jiliarena_活动分析数据_底稿'!$K:$K,'jiliarena_活动分析数据_底稿'!$B:$B,$A5,'jiliarena_活动分析数据_底稿'!$L:$L,AX$3) -> 0 | AY5: =SUMIFS('jiliarena_活动分析数据_底稿'!$K:$K,'jiliarena_活动分析数据_底稿'!$B:$B,$A5,'jiliarena_活动分析数据_底稿'!$L:$L,AY$3) -> 0 | AZ5: =SUMIFS('jiliarena_活动分析数据_底稿'!$K:$K,'jiliarena_活动分析数据_底稿'!$B:$B,$A5,'jiliarena_活动分析数据_底稿'!$L:$L,AZ$3) -> 0 | BA5: =SUMIFS('jiliarena_活动分析数据_底稿'!$K:$K,'jiliarena_活动分析数据_底稿'!$B:$B,$A5,'jiliarena_活动分析数据_底稿'!$L:$L,BA$3) -> 0 | ... BP5: =SUMIFS('jiliarena_活动分析数据_底稿'!$K:$K,'jiliarena_活动分析数据_底稿'!$B:$B,$A5,'jiliarena_活动分析数据_底稿'!$L:$L,BP$3) -> 0 | BQ5: =SUM(AT5:BP5) -> 0 | BR5: =AT5 -> 0 | BS5: =BB5 -> 0 | BT5: =iferror(IF(BQ5="","",ROUND(BQ5/X5,6)),"") | BU5: =iferror(BQ5/L5,"") | BV5: =iferror(BQ5/Y5,"") | BW5: =IF(BQ5="","",Y5-BQ5) -> 0 | BX5: =iferror(BQ5/BW5,"") | BY5: =L5*$BY$1 -> 0 | BZ5: =M5*$BZ$1 -> 0 | CA5: =BY5+BZ5 -> 0 | CB5: =IF(Y5="","",ROUND(Y5*9%,0)) -> 0 | CC5: =iferror(CA5/BW5,"") | CD5: {=index('jiliarena_日报_底稿'!$P$3:$DS$31,match(A5,'jiliarena_日报_底稿'!$P$3:$P$31,0),match("综合性分红",'jiliarena_日报_底稿'!$P$3:$DS$3,0))} | CF5: {=INDEX('jiliarena_日报_底稿'!$P$2:$DS$31,MATCH($A5,'jiliarena_日报_底稿'!$P$2:$P$31,0),MATCH(CF$3,'jiliarena_日报_底稿'!$P$3:$DS$3,0))} | CG5: {=-INDEX('jiliarena_日报_底稿'!$P$2:$DS$31,MATCH($A5,'jiliarena_日报_底稿'!$P$2:$P$31,0),MATCH(CG$3,'jiliarena_日报_底稿'!$P$3:$DS$3,0))} -> 0 | CH5: {=INDEX('jiliarena_日报_底稿'!$P$2:$DS$31,MATCH($A5,'jiliarena_日报_底稿'!$P$2:$P$31,0),MATCH(CH$3,'jiliarena_日报_底稿'!$P$3:$DS$3,0))} | CI5: =IF(CA5="","",BW5-CA5-CD5-CB5) -> 0 | CJ5: =IFERROR(month(A5),"") -> 2 | CK5: =IFERROR(DAY(A5),"") -> 1
A6: SUB total | B6: =SUM(B5) -> 0 | C6: =SUM(C5) -> 0 | D6: =SUM(D5) -> 0 | E6: =SUM(E5) -> 18 | F6: =SUM(F5) -> 0 | G6: =SUM(G5) -> 0 | H6: =SUM(H5) -> 0 | I6: =SUM(I5) -> 814 | ... M6: =SUM(M5) -> 0 | N6: =IF(C6="","",ROUND(C6/B6,4)) -> #DIV/0! | O6: =IF(K6="","",ROUND(K6/C6,0)) -> #DIV/0! | P6: =IF(L6="","",ROUND(K6/L6,6)) -> #DIV/0! | Q6: =IF(G6="","",ROUND(G6/F6,1)) -> #DIV/0! | R6: =IF(L6="","",ROUND(L6/F6,0)) -> #DIV/0! | S6: =IF(L6="","",ROUND(L6/G6,0)) -> #DIV/0! | T6: =IF(S6="","",ROUND(S6/O6,1)) -> #DIV/0! | U6: =IF(M6="","",ROUND(M6/H6,0)) -> #DIV/0! | V6: =IF(M6="","",L6-M6) -> 0 | W6: =SUM(W5) -> 0 | X6: =SUM(X5) -> 0 | Y6: =SUM(Y5) -> 0 | Z6: =SUM(Z5) -> 0 | AA6: =IFERROR(ROUND(1-(Z6/W6),6),"") | AB6: =SUM(AB5) -> 0 | AC6: =SUM(AC5) -> 0 | AD6: =IF(AC6="","",ROUND((1-(AC6/AB6)),6)) -> #DIV/0! | AE6: =SUM(AE5) -> 0 | AF6: =SUM(AF5) -> 0 | AG6: =IF(AF6="","",ROUND((1-(AF6/AE6)),6)) -> #DIV/0! | AH6: =SUM(AH5) -> 0 | AI6: =SUM(AI5) -> 0 | AJ6: =IF(AI6="","",ROUND((1-(AI6/AH6)),6)) -> #DIV/0! | AK6: =SUM(AK5) -> 0 | AL6: =SUM(AL5) -> 0 | AM6: =IF(AL6="","",ROUND((1-(AL6/AK6)),6)) -> #DIV/0! | AN6: =SUM(AN5) -> 0 | AO6: =SUM(AO5) -> 0 | AP6: =IF(AO6="","",ROUND((1-(AO6/AN6)),6)) -> #DIV/0! | AQ6: =SUM(AQ5) -> 0 | AR6: =SUM(AR5) -> 0 | AS6: =IF(AR6="","",ROUND((1-(AR6/AQ6)),6)) -> #DIV/0! | AT6: =SUM(AT5) -> 0 | AU6: =SUM(AU5) -> 0 | AV6: =SUM(AV5) -> 0 | AW6: =SUM(AW5) -> 0 | AX6: =SUM(AX5) -> 0 | AY6: =SUM(AY5) -> 0 | AZ6: =SUM(AZ5) -> 0 | BA6: =SUM(BA5) -> 0 | ... BS6: =SUM(BS5) -> 0 | BT6: =iferror(IF(BQ6="","",ROUND(BQ6/X6,6)),"") | BU6: =iferror(BQ6/L6,"") | BV6: =iferror(BQ6/Y6,"") | BW6: =IF(BQ6="","",Y6-BQ6) -> 0 | BX6: =iferror(BQ6/BW6,"") | BY6: =L6*$BY$1 -> 0 | BZ6: =M6*$BZ$1 -> 0 | CA6: =BY6+BZ6 -> 0 | CB6: =IF(Y6="","",ROUND(Y6*9%,0)) -> 0 | CC6: =iferror(CA6/BW6,"") | CD6: =SUM(CD5) -> 0 | CE6: =SUM(CE5) -> 0 | CF6: =SUM(CF5) -> 0 | CG6: =SUM(CG5) -> 0 | CH6: =SUM(CH5) -> 0 | CI6: =IF(CA6="","",BW6-CA6-CD6-CB6) -> 0 | CJ6: =IFERROR(month(A6),"") | CK6: =IFERROR(DAY(A6),"")
A7: =A5+1 -> 46055 | B7: {=INDEX('jiliarena_日报_底稿'!$A$3:$N$31,MATCH($A7,'jiliarena_日报_底稿'!$A$3:$A$31,0),MATCH(B$3,'jiliarena_日报_底稿'!$A$3:$N$3,0))} | C7: {=INDEX('jiliarena_日报_底稿'!$A$3:$N$31,MATCH($A7,'jiliarena_日报_底稿'!$A$3:$A$31,0),MATCH(C$3,'jiliarena_日报_底稿'!$A$3:$N$3,0))} | D7: {=INDEX('jiliarena_日报_底稿'!$A$3:$N$31,MATCH($A7,'jiliarena_日报_底稿'!$A$3:$A$31,0),MATCH(D$3,'jiliarena_日报_底稿'!$A$3:$N$3,0))} | E7: 21 | F7: {=INDEX('jiliarena_日报_底稿'!$A$3:$N$31,MATCH($A7,'jiliarena_日报_底稿'!$A$3:$A$31,0),MATCH(F$3,'jiliarena_日报_底稿'!$A$3:$N$3,0))} | G7: =SUMIFS('渠道充值成功率_底稿'!$F:$F,'渠道充值成功率_底稿'!$A:$A,A7) -> 0 | H7: {=INDEX('jiliarena_日报_底稿'!$A$3:$N$31,MATCH($A7,'jiliarena_日报_底稿'!$A$3:$A$31,0),MATCH(H$3,'jiliarena_日报_底稿'!$A$3:$N$3,0))} | I7: 893 | J7: {=INDEX('jiliarena_日报_底稿'!$A$3:$N$31,MATCH($A7,'jiliarena_日报_底稿'!$A$3:$A$31,0),MATCH(J$3,'jiliarena_日报_底稿'!$A$3:$N$3,0))} | K7: =SUMIFS('渠道充值成功率_底稿'!$J:$J,'渠道充值成功率_底稿'!$A:$A,$A7) -> 0 | L7: {=INDEX('jiliarena_日报_底稿'!$A$3:$N$31,MATCH($A7,'jiliarena_日报_底稿'!$A$3:$A$31,0),MATCH(L$3,'jiliarena_日报_底稿'!$A$3:$N$3,0))} | M7: {=INDEX('jiliarena_日报_底稿'!$P$2:$DS$31,MATCH($A7,'jiliarena_日报_底稿'!$P$2:$P$31,0),MATCH($M$3,'jiliarena_日报_底稿'!$P$3:$DS$3,0))} | N7: =IF(C7="","",ROUND(C7/B7,4)) | O7: =IF(K7="","",ROUND(K7/C7,0)) -> #DIV/0! | P7: =IF(L7="","",ROUND(K7/L7,6)) | Q7: =IF(G7="","",ROUND(G7/F7,1)) -> #DIV/0! | R7: =IF(L7="","",ROUND(L7/F7,0)) | S7: =IF(L7="","",ROUND(L7/G7,0)) | T7: =IF(S7="","",ROUND(S7/O7,1)) | U7: =IF(M7="","",ROUND(M7/H7,0)) | V7: =IF(M7="","",L7-M7) | W7: =AB7+AE7+AH7+AK7+AN7+AQ7 -> 0 | X7: {=index('jiliarena_日报_底稿'!$P$2:$DS$31,match($A7,'jiliarena_日报_底稿'!$P$2:$P$31,0),match("电子有效投注",'jiliarena_日报_底稿'!$P$3:$DS$3,0))+index('jiliarena_日报_底稿'!$P$2:$DS$31,match($A7,'jiliarena_日报_底稿'!$P$2:$P$31,0),match("真人有效投注",'jiliarena_日报_底稿'!$P$3:$DS$3,0))+index('jiliarena_日报_底稿'!$P$2:$DS$31,match($A7,'jiliarena_日报_底稿'!$P$2:$P$31,0),match("彩票有效投注",'jiliarena_日报_底稿'!$P$3:$DS$3,0))+index('jiliarena_日报_底稿'!$P$2:$DS$31,match($A7,'jiliarena_日报_底稿'!$P$2:$P$31,0),match("棋牌有效投注",'jiliarena_日报_底稿'!$P$3:$DS$3,0))+index('jiliarena_日报_底稿'!$P$2:$DS$31,match($A7,'jiliarena_日报_底稿'!$P$2:$P$31,0),match("捕鱼有效投注",'jiliarena_日报_底稿'!$P$3:$DS$3,0))+index('jiliarena_日报_底稿'!$P$2:$DS$31,match($A7,'jiliarena_日报_底稿'!$P$2:$P$31,0),match("体育有效投注",'jiliarena_日报_底稿'!$P$3:$DS$3,0))+index('jiliarena_日报_底稿'!$P$2:$DS$31,match($A7,'jiliarena_日报_底稿'!$P$2:$P$31,0),match("盘口彩票有效投注",'jiliarena_日报_底稿'!$P$3:$DS$3,0))} -> 0 | Y7: =AB7+AE7+AH7+AK7+AN7+AQ7-AR7-AO7-AL7-AI7-AF7-AC7 -> 0 | Z7: =AC7+AF7+AI7+AL7+AO7+AR7 -> 0 | AA7: =IFERROR(ROUND(1-(Z7/W7),6),"") | AB7: {=INDEX('jiliarena_日报_底稿'!$P$2:$DS$31,MATCH($A7,'jiliarena_日报_底稿'!$P$2:$P$31,0),MATCH(AB$3,'jiliarena_日报_底稿'!$P$3:$DS$3,0))} | AC7: {=INDEX('jiliarena_日报_底稿'!$P$2:$DS$31,MATCH($A7,'jiliarena_日报_底稿'!$P$2:$P$31,0),MATCH(AC$3,'jiliarena_日报_底稿'!$P$3:$DS$3,0))} | AD7: =IF(AC7="","",ROUND((1-(AC7/AB7)),6)) | AE7: {=INDEX('jiliarena_日报_底稿'!$P$2:$DS$31,MATCH($A7,'jiliarena_日报_底稿'!$P$2:$P$31,0),MATCH(AE$3,'jiliarena_日报_底稿'!$P$3:$DS$3,0))} | AF7: {=INDEX('jiliarena_日报_底稿'!$P$2:$DS$31,MATCH($A7,'jiliarena_日报_底稿'!$P$2:$P$31,0),MATCH(AF$3,'jiliarena_日报_底稿'!$P$3:$DS$3,0))} | AG7: =IF(AF7="","",ROUND((1-(AF7/AE7)),6)) | AH7: {=INDEX('jiliarena_日报_底稿'!$P$2:$DS$31,MATCH($A7,'jiliarena_日报_底稿'!$P$2:$P$31,0),MATCH(AH$3,'jiliarena_日报_底稿'!$P$3:$DS$3,0))} | AI7: {=INDEX('jiliarena_日报_底稿'!$P$2:$DS$31,MATCH($A7,'jiliarena_日报_底稿'!$P$2:$P$31,0),MATCH(AI$3,'jiliarena_日报_底稿'!$P$3:$DS$3,0))} | AJ7: =IF(AI7="","",ROUND((1-(AI7/AH7)),6)) | AK7: {=INDEX('jiliarena_日报_底稿'!$P$2:$DS$31,MATCH($A7,'jiliarena_日报_底稿'!$P$2:$P$31,0),MATCH(AK$3,'jiliarena_日报_底稿'!$P$3:$DS$3,0))} | AL7: {=INDEX('jiliarena_日报_底稿'!$P$2:$DS$31,MATCH($A7,'jiliarena_日报_底稿'!$P$2:$P$31,0),MATCH(AL$3,'jiliarena_日报_底稿'!$P$3:$DS$3,0))} | AM7: =IF(AL7="","",ROUND((1-(AL7/AK7)),6)) | AN7: {=INDEX('jiliarena_日报_底稿'!$P$2:$DS$31,MATCH($A7,'jiliarena_日报_底稿'!$P$2:$P$31,0),MATCH(AN$3,'jiliarena_日报_底稿'!$P$3:$DS$3,0))} | AO7: {=INDEX('jiliarena_日报_底稿'!$P$2:$DS$31,MATCH($A7,'jiliarena_日报_底稿'!$P$2:$P$31,0),MATCH(AO$3,'jiliarena_日报_底稿'!$P$3:$DS$3,0))} | AP7: =IF(AO7="","",ROUND((1-(AO7/AN7)),6)) | AQ7: {=INDEX('jiliarena_日报_底稿'!$P$2:$DS$31,MATCH($A7,'jiliarena_日报_底稿'!$P$2:$P$31,0),MATCH(AQ$3,'jiliarena_日报_底稿'!$P$3:$DS$3,0))} | AR7: {=INDEX('jiliarena_日报_底稿'!$P$2:$DS$31,MATCH($A7,'jiliarena_日报_底稿'!$P$2:$P$31,0),MATCH(AR$3,'jiliarena_日报_底稿'!$P$3:$DS$3,0))} | AS7: =IF(AR7="","",ROUND((1-(AR7/AQ7)),6)) | AT7: =SUMIFS('jiliarena_活动分析数据_底稿'!$K:$K,'jiliarena_活动分析数据_底稿'!$B:$B,$A7,'jiliarena_活动分析数据_底稿'!$L:$L,AT$3) -> 0 | AU7: =SUMIFS('jiliarena_活动分析数据_底稿'!$K:$K,'jiliarena_活动分析数据_底稿'!$B:$B,$A7,'jiliarena_活动分析数据_底稿'!$L:$L,AU$3) -> 0 | AV7: =SUMIFS('jiliarena_活动分析数据_底稿'!$K:$K,'jiliarena_活动分析数据_底稿'!$B:$B,$A7,'jiliarena_活动分析数据_底稿'!$L:$L,AV$3) -> 0 | AW7: =SUMIFS('jiliarena_活动分析数据_底稿'!$K:$K,'jiliarena_活动分析数据_底稿'!$B:$B,$A7,'jiliarena_活动分析数据_底稿'!$L:$L,AW$3) -> 0 | AX7: =SUMIFS('jiliarena_活动分析数据_底稿'!$K:$K,'jiliarena_活动分析数据_底稿'!$B:$B,$A7,'jiliarena_活动分析数据_底稿'!$L:$L,AX$3) -> 0 | AY7: =SUMIFS('jiliarena_活动分析数据_底稿'!$K:$K,'jiliarena_活动分析数据_底稿'!$B:$B,$A7,'jiliarena_活动分析数据_底稿'!$L:$L,AY$3) -> 0 | AZ7: =SUMIFS('jiliarena_活动分析数据_底稿'!$K:$K,'jiliarena_活动分析数据_底稿'!$B:$B,$A7,'jiliarena_活动分析数据_底稿'!$L:$L,AZ$3) -> 0 | BA7: =SUMIFS('jiliarena_活动分析数据_底稿'!$K:$K,'jiliarena_活动分析数据_底稿'!$B:$B,$A7,'jiliarena_活动分析数据_底稿'!$L:$L,BA$3) -> 0 | ... BP7: =SUMIFS('jiliarena_活动分析数据_底稿'!$K:$K,'jiliarena_活动分析数据_底稿'!$B:$B,$A7,'jiliarena_活动分析数据_底稿'!$L:$L,BP$3) -> 0 | BQ7: =SUM(AT7:BP7) -> 0 | BR7: =AT7 -> 0 | BS7: =BB7 -> 0 | BT7: =iferror(IF(BQ7="","",ROUND(BQ7/X7,6)),"") | BU7: =iferror(BQ7/L7,"") | BV7: =iferror(BQ7/Y7,"") | BW7: =IF(BQ7="","",Y7-BQ7) -> 0 | BX7: =iferror(BQ7/BW7,"") | BY7: =L7*$BY$1 -> 0 | BZ7: =M7*$BZ$1 -> 0 | CA7: =BY7+BZ7 -> 0 | CB7: =IF(Y7="","",ROUND(Y7*9%,0)) -> 0 | CC7: =iferror(CA7/BW7,"") | CD7: {=index('jiliarena_日报_底稿'!$P$3:$DS$31,match(A7,'jiliarena_日报_底稿'!$P$3:$P$31,0),match("综合性分红",'jiliarena_日报_底稿'!$P$3:$DS$3,0))} | CF7: {=INDEX('jiliarena_日报_底稿'!$P$2:$DS$31,MATCH($A7,'jiliarena_日报_底稿'!$P$2:$P$31,0),MATCH(CF$3,'jiliarena_日报_底稿'!$P$3:$DS$3,0))} | CG7: {=-INDEX('jiliarena_日报_底稿'!$P$2:$DS$31,MATCH($A7,'jiliarena_日报_底稿'!$P$2:$P$31,0),MATCH(CG$3,'jiliarena_日报_底稿'!$P$3:$DS$3,0))} -> 0 | CH7: {=INDEX('jiliarena_日报_底稿'!$P$2:$DS$31,MATCH($A7,'jiliarena_日报_底稿'!$P$2:$P$31,0),MATCH(CH$3,'jiliarena_日报_底稿'!$P$3:$DS$3,0))} | CI7: =IF(CA7="","",BW7-CA7-CD7-CB7) -> 0 | CJ7: =IFERROR(month(A7),"") -> 2 | CK7: =IFERROR(DAY(A7),"") -> 2
A8: =A7+1 -> 46056 | B8: {=INDEX('jiliarena_日报_底稿'!$A$3:$N$31,MATCH($A8,'jiliarena_日报_底稿'!$A$3:$A$31,0),MATCH(B$3,'jiliarena_日报_底稿'!$A$3:$N$3,0))} | C8: {=INDEX('jiliarena_日报_底稿'!$A$3:$N$31,MATCH($A8,'jiliarena_日报_底稿'!$A$3:$A$31,0),MATCH(C$3,'jiliarena_日报_底稿'!$A$3:$N$3,0))} | D8: {=INDEX('jiliarena_日报_底稿'!$A$3:$N$31,MATCH($A8,'jiliarena_日报_底稿'!$A$3:$A$31,0),MATCH(D$3,'jiliarena_日报_底稿'!$A$3:$N$3,0))} | E8: 14 | F8: {=INDEX('jiliarena_日报_底稿'!$A$3:$N$31,MATCH($A8,'jiliarena_日报_底稿'!$A$3:$A$31,0),MATCH(F$3,'jiliarena_日报_底稿'!$A$3:$N$3,0))} | G8: =SUMIFS('渠道充值成功率_底稿'!$F:$F,'渠道充值成功率_底稿'!$A:$A,A8) -> 0 | H8: {=INDEX('jiliarena_日报_底稿'!$A$3:$N$31,MATCH($A8,'jiliarena_日报_底稿'!$A$3:$A$31,0),MATCH(H$3,'jiliarena_日报_底稿'!$A$3:$N$3,0))} | I8: 850 | J8: {=INDEX('jiliarena_日报_底稿'!$A$3:$N$31,MATCH($A8,'jiliarena_日报_底稿'!$A$3:$A$31,0),MATCH(J$3,'jiliarena_日报_底稿'!$A$3:$N$3,0))} | K8: =SUMIFS('渠道充值成功率_底稿'!$J:$J,'渠道充值成功率_底稿'!$A:$A,$A8) -> 0 | L8: {=INDEX('jiliarena_日报_底稿'!$A$3:$N$31,MATCH($A8,'jiliarena_日报_底稿'!$A$3:$A$31,0),MATCH(L$3,'jiliarena_日报_底稿'!$A$3:$N$3,0))} | M8: {=INDEX('jiliarena_日报_底稿'!$P$2:$DS$31,MATCH($A8,'jiliarena_日报_底稿'!$P$2:$P$31,0),MATCH($M$3,'jiliarena_日报_底稿'!$P$3:$DS$3,0))} | N8: =IF(C8="","",ROUND(C8/B8,4)) | O8: =IF(K8="","",ROUND(K8/C8,0)) -> #DIV/0! | P8: =IF(L8="","",ROUND(K8/L8,6)) | Q8: =IF(G8="","",ROUND(G8/F8,1)) -> #DIV/0! | R8: =IF(L8="","",ROUND(L8/F8,0)) | S8: =IF(L8="","",ROUND(L8/G8,0)) | T8: =IF(S8="","",ROUND(S8/O8,1)) | U8: =IF(M8="","",ROUND(M8/H8,0)) | V8: =IF(M8="","",L8-M8) | W8: =AB8+AE8+AH8+AK8+AN8+AQ8 -> 0 | X8: {=index('jiliarena_日报_底稿'!$P$2:$DS$31,match($A8,'jiliarena_日报_底稿'!$P$2:$P$31,0),match("电子有效投注",'jiliarena_日报_底稿'!$P$3:$DS$3,0))+index('jiliarena_日报_底稿'!$P$2:$DS$31,match($A8,'jiliarena_日报_底稿'!$P$2:$P$31,0),match("真人有效投注",'jiliarena_日报_底稿'!$P$3:$DS$3,0))+index('jiliarena_日报_底稿'!$P$2:$DS$31,match($A8,'jiliarena_日报_底稿'!$P$2:$P$31,0),match("彩票有效投注",'jiliarena_日报_底稿'!$P$3:$DS$3,0))+index('jiliarena_日报_底稿'!$P$2:$DS$31,match($A8,'jiliarena_日报_底稿'!$P$2:$P$31,0),match("棋牌有效投注",'jiliarena_日报_底稿'!$P$3:$DS$3,0))+index('jiliarena_日报_底稿'!$P$2:$DS$31,match($A8,'jiliarena_日报_底稿'!$P$2:$P$31,0),match("捕鱼有效投注",'jiliarena_日报_底稿'!$P$3:$DS$3,0))+index('jiliarena_日报_底稿'!$P$2:$DS$31,match($A8,'jiliarena_日报_底稿'!$P$2:$P$31,0),match("体育有效投注",'jiliarena_日报_底稿'!$P$3:$DS$3,0))+index('jiliarena_日报_底稿'!$P$2:$DS$31,match($A8,'jiliarena_日报_底稿'!$P$2:$P$31,0),match("盘口彩票有效投注",'jiliarena_日报_底稿'!$P$3:$DS$3,0))} -> 0 | Y8: =AB8+AE8+AH8+AK8+AN8+AQ8-AR8-AO8-AL8-AI8-AF8-AC8 -> 0 | Z8: =AC8+AF8+AI8+AL8+AO8+AR8 -> 0 | AA8: =IFERROR(ROUND(1-(Z8/W8),6),"") | AB8: {=INDEX('jiliarena_日报_底稿'!$P$2:$DS$31,MATCH($A8,'jiliarena_日报_底稿'!$P$2:$P$31,0),MATCH(AB$3,'jiliarena_日报_底稿'!$P$3:$DS$3,0))} | AC8: {=INDEX('jiliarena_日报_底稿'!$P$2:$DS$31,MATCH($A8,'jiliarena_日报_底稿'!$P$2:$P$31,0),MATCH(AC$3,'jiliarena_日报_底稿'!$P$3:$DS$3,0))} | AD8: =IF(AC8="","",ROUND((1-(AC8/AB8)),6)) | AE8: {=INDEX('jiliarena_日报_底稿'!$P$2:$DS$31,MATCH($A8,'jiliarena_日报_底稿'!$P$2:$P$31,0),MATCH(AE$3,'jiliarena_日报_底稿'!$P$3:$DS$3,0))} | AF8: {=INDEX('jiliarena_日报_底稿'!$P$2:$DS$31,MATCH($A8,'jiliarena_日报_底稿'!$P$2:$P$31,0),MATCH(AF$3,'jiliarena_日报_底稿'!$P$3:$DS$3,0))} | AG8: =IF(AF8="","",ROUND((1-(AF8/AE8)),6)) | AH8: {=INDEX('jiliarena_日报_底稿'!$P$2:$DS$31,MATCH($A8,'jiliarena_日报_底稿'!$P$2:$P$31,0),MATCH(AH$3,'jiliarena_日报_底稿'!$P$3:$DS$3,0))} | AI8: {=INDEX('jiliarena_日报_底稿'!$P$2:$DS$31,MATCH($A8,'jiliarena_日报_底稿'!$P$2:$P$31,0),MATCH(AI$3,'jiliarena_日报_底稿'!$P$3:$DS$3,0))} | AJ8: =IF(AI8="","",ROUND((1-(AI8/AH8)),6)) | AK8: {=INDEX('jiliarena_日报_底稿'!$P$2:$DS$31,MATCH($A8,'jiliarena_日报_底稿'!$P$2:$P$31,0),MATCH(AK$3,'jiliarena_日报_底稿'!$P$3:$DS$3,0))} | AL8: {=INDEX('jiliarena_日报_底稿'!$P$2:$DS$31,MATCH($A8,'jiliarena_日报_底稿'!$P$2:$P$31,0),MATCH(AL$3,'jiliarena_日报_底稿'!$P$3:$DS$3,0))} | AM8: =IF(AL8="","",ROUND((1-(AL8/AK8)),6)) | AN8: {=INDEX('jiliarena_日报_底稿'!$P$2:$DS$31,MATCH($A8,'jiliarena_日报_底稿'!$P$2:$P$31,0),MATCH(AN$3,'jiliarena_日报_底稿'!$P$3:$DS$3,0))} | AO8: {=INDEX('jiliarena_日报_底稿'!$P$2:$DS$31,MATCH($A8,'jiliarena_日报_底稿'!$P$2:$P$31,0),MATCH(AO$3,'jiliarena_日报_底稿'!$P$3:$DS$3,0))} | AP8: =IF(AO8="","",ROUND((1-(AO8/AN8)),6)) | AQ8: {=INDEX('jiliarena_日报_底稿'!$P$2:$DS$31,MATCH($A8,'jiliarena_日报_底稿'!$P$2:$P$31,0),MATCH(AQ$3,'jiliarena_日报_底稿'!$P$3:$DS$3,0))} | AR8: {=INDEX('jiliarena_日报_底稿'!$P$2:$DS$31,MATCH($A8,'jiliarena_日报_底稿'!$P$2:$P$31,0),MATCH(AR$3,'jiliarena_日报_底稿'!$P$3:$DS$3,0))} | AS8: =IF(AR8="","",ROUND((1-(AR8/AQ8)),6)) | AT8: =SUMIFS('jiliarena_活动分析数据_底稿'!$K:$K,'jiliarena_活动分析数据_底稿'!$B:$B,$A8,'jiliarena_活动分析数据_底稿'!$L:$L,AT$3) -> 0 | AU8: =SUMIFS('jiliarena_活动分析数据_底稿'!$K:$K,'jiliarena_活动分析数据_底稿'!$B:$B,$A8,'jiliarena_活动分析数据_底稿'!$L:$L,AU$3) -> 0 | AV8: =SUMIFS('jiliarena_活动分析数据_底稿'!$K:$K,'jiliarena_活动分析数据_底稿'!$B:$B,$A8,'jiliarena_活动分析数据_底稿'!$L:$L,AV$3) -> 0 | AW8: =SUMIFS('jiliarena_活动分析数据_底稿'!$K:$K,'jiliarena_活动分析数据_底稿'!$B:$B,$A8,'jiliarena_活动分析数据_底稿'!$L:$L,AW$3) -> 0 | AX8: =SUMIFS('jiliarena_活动分析数据_底稿'!$K:$K,'jiliarena_活动分析数据_底稿'!$B:$B,$A8,'jiliarena_活动分析数据_底稿'!$L:$L,AX$3) -> 0 | AY8: =SUMIFS('jiliarena_活动分析数据_底稿'!$K:$K,'jiliarena_活动分析数据_底稿'!$B:$B,$A8,'jiliarena_活动分析数据_底稿'!$L:$L,AY$3) -> 0 | AZ8: =SUMIFS('jiliarena_活动分析数据_底稿'!$K:$K,'jiliarena_活动分析数据_底稿'!$B:$B,$A8,'jiliarena_活动分析数据_底稿'!$L:$L,AZ$3) -> 0 | BA8: =SUMIFS('jiliarena_活动分析数据_底稿'!$K:$K,'jiliarena_活动分析数据_底稿'!$B:$B,$A8,'jiliarena_活动分析数据_底稿'!$L:$L,BA$3) -> 0 | ... BP8: =SUMIFS('jiliarena_活动分析数据_底稿'!$K:$K,'jiliarena_活动分析数据_底稿'!$B:$B,$A8,'jiliarena_活动分析数据_底稿'!$L:$L,BP$3) -> 0 | BQ8: =SUM(AT8:BP8) -> 0 | BR8: =AT8 -> 0 | BS8: =BB8 -> 0 | BT8: =iferror(IF(BQ8="","",ROUND(BQ8/X8,6)),"") | BU8: =iferror(BQ8/L8,"") | BV8: =iferror(BQ8/Y8,"") | BW8: =IF(BQ8="","",Y8-BQ8) -> 0 | BX8: =iferror(BQ8/BW8,"") | BY8: =L8*$BY$1 -> 0 | BZ8: =M8*$BZ$1 -> 0 | CA8: =BY8+BZ8 -> 0 | CB8: =IF(Y8="","",ROUND(Y8*9%,0)) -> 0 | CC8: =iferror(CA8/BW8,"") | CD8: {=index('jiliarena_日报_底稿'!$P$3:$DS$31,match(A8,'jiliarena_日报_底稿'!$P$3:$P$31,0),match("综合性分红",'jiliarena_日报_底稿'!$P$3:$DS$3,0))} | CF8: {=INDEX('jiliarena_日报_底稿'!$P$2:$DS$31,MATCH($A8,'jiliarena_日报_底稿'!$P$2:$P$31,0),MATCH(CF$3,'jiliarena_日报_底稿'!$P$3:$DS$3,0))} | CG8: {=-INDEX('jiliarena_日报_底稿'!$P$2:$DS$31,MATCH($A8,'jiliarena_日报_底稿'!$P$2:$P$31,0),MATCH(CG$3,'jiliarena_日报_底稿'!$P$3:$DS$3,0))} -> 0 | CH8: {=INDEX('jiliarena_日报_底稿'!$P$2:$DS$31,MATCH($A8,'jiliarena_日报_底稿'!$P$2:$P$31,0),MATCH(CH$3,'jiliarena_日报_底稿'!$P$3:$DS$3,0))} | CI8: =IF(CA8="","",BW8-CA8-CD8-CB8) -> 0 | CJ8: =IFERROR(month(A8),"") -> 2 | CK8: =IFERROR(DAY(A8),"") -> 3
