Workbook

Sheet 全平台汇总
A1: 46093 | F1: 全平台关键数据报表 | P1: 平台详细数据填制区
A2: 日期 | B2: 充值 | C2: 首存金额 | D2: 提款 | E2: 充提差 | F2: GP1 | G2: GP2 | H2: GP3 | I2: 登录人数 | J2: 投注人数 | K2: 注册人数 | L2: 首充人数 | M2: 续存人数 | N2: 存款人数 | O2: 存款次数 | P2: 投注 | Q2: 有效投注 | R2: 派彩 | S2: 综合优惠比 | T2: 活动红利 | U2: 返点 | V2: 邀请返佣 | W2: GP1 | X2: GP1杀率 | Y2: 游戏杀率 | Z2: 平台余额 | AA2: 周结&月结佣金 | AB2: 周结代理佣金 | AC2: 月结代理佣金 | AD2: GP2 | AE2: GP2杀率 | AF2: 存提手续费 | AG2: 存款手续费 | AH2: 提款手续费 | AI2: 平台费 | AJ2: 包网费(U） | AK2: 汇率 | AL2: 换算P | AM2: GP3 | AN2: GP3杀率 | AO2: 开分 | AP2: 洗分 | AQ2: 核对 | AR2: 差额
A3: 46082 | B3: =WP!L9+GJP!L9+SBET!L9+Sugarplay!L9 -> 10012561 | C3: =WP!K9+GJP!K9+SBET!K9+Sugarplay!K9 -> 101494 | D3: =WP!M9+GJP!M9+SBET!M9+Sugarplay!N9 -> 9438631 | E3: =B3-D3 -> 573929.6 | F3: =W3 -> 1023619.1 | G3: =AD3 -> 1023619.1 | H3: =AM3 -> 677871.75 | I3: =WP!D9+GJP!D9+SBET!D9+Sugarplay!D9 -> 37276 | J3: =WP!J9+GJP!J9+SBET!J9+Sugarplay!J9 -> 23624 | K3: =WP!B9+GJP!B9+SBET!B9+Sugarplay!B9 -> 1333 | L3: =WP!C9+GJP!C9+SBET!C9+Sugarplay!C9 -> 410 | M3: =WP!E9+GJP!E9+SBET!E9+Sugarplay!E9 -> 992 | N3: =WP!F9+GJP!F9+SBET!F9+Sugarplay!F9 -> 5857 | O3: =WP!G9+GJP!G9+SBET!G9+Sugarplay!G9 -> 12355 | P3: =WP!O9+GJP!O9+SBET!O9+Sugarplay!P9 -> 67076153 | Q3: =WP!P9+GJP!P9+SBET!P9+Sugarplay!Q9 -> 62681990 | R3: =WP!R9+GJP!R9+SBET!R9+Sugarplay!S9 -> 65320984 | S3: =T3/Q3 -> 0.011670818 | T3: =WP!S9+GJP!S9+SBET!S9+Sugarplay!T9 -> 731550.07 | U3: =WP!T9+GJP!T9+SBET!T9+Sugarplay!U9 -> 284236.48 | V3: =WP!U9+GJP!U9+SBET!U9+Sugarplay!V9 -> 29250.28 | W3: =P3-R3-T3 -> 1023619.1 | X3: =W3/P3 -> 0.015260552 | Y3: =(P3-R3)/P3 -> 0.026166814 | Z3: =WP!AE9+GJP!AE9+SBET!AF9+Sugarplay!AG9 -> 1965001.1 | AA3: =AB3+AC3 -> 0 | AB3: =WP!AA9+GJP!AA9+SBET!AB9+Sugarplay!AC9 -> 0 | AC3: =WP!AB9+GJP!AB9+SBET!AC9+Sugarplay!AD9 -> 0 | AD3: =W3-AB3-AC3 -> 1023619.1 | AE3: =AD3/P3 -> 0.015260552 | AF3: =AG3+AH3 -> 253621.64 | AG3: =WP!W9+GJP!W9+SBET!W9+Sugarplay!X9 -> 234744.3 | AH3: =WP!X9+GJP!X9+SBET!X9+Sugarplay!Y9 -> 18877.34 | AI3: =W3*0.09 -> 92125.72 | AJ3: 0 | AK3: 0 | AL3: 0 | AM3: =W3-AB3-AC3-AG3-AH3-AI3 -> 677871.75 | AN3: =AM3/P3 -> 0.010106002 | AO3: =WP!AC9+GJP!AC9+SBET!AD9+Sugarplay!AE9 -> 100 | AP3: =WP!AD9+GJP!AD9+SBET!AE9+Sugarplay!AF9 -> -2554.33 | AQ3: =AD3-AG3-AH3-AI3 -> 677871.75 | AR3: =AM3-AQ3 -> 0
A4: =A3+1 -> 46083 | B4: =WP!L10+GJP!L10+SBET!L10+Sugarplay!L10 -> 8816812.6 | C4: =WP!K10+GJP!K10+SBET!K10+Sugarplay!K10 -> 88437 | D4: =WP!M10+GJP!M10+SBET!M10+Sugarplay!N10 -> 8989445 | E4: =B4-D4 -> -172632.43 | F4: =W4 -> 817069.84 | G4: =AD4 -> -209948.92 | H4: =AM4 -> -508126 | I4: =WP!D10+GJP!D10+SBET!D10+Sugarplay!D10 -> 30062 | J4: =WP!J10+GJP!J10+SBET!J10+Sugarplay!J10 -> 19932 | K4: =WP!B10+GJP!B10+SBET!B10+Sugarplay!B10 -> 1326 | L4: =WP!C10+GJP!C10+SBET!C10+Sugarplay!C10 -> 384 | M4: =WP!E10+GJP!E10+SBET!E10+Sugarplay!E10 -> 903 | N4: =WP!F10+GJP!F10+SBET!F10+Sugarplay!F10 -> 4985 | O4: =WP!G10+GJP!G10+SBET!G10+Sugarplay!G10 -> 10948 | P4: =WP!O10+GJP!O10+SBET!O10+Sugarplay!P10 -> 57155008 | Q4: =WP!P10+GJP!P10+SBET!P10+Sugarplay!Q10 -> 53233162 | R4: =WP!R10+GJP!R10+SBET!R10+Sugarplay!S10 -> 55716597 | S4: =T4/Q4 -> 0.011672072 | T4: =WP!S10+GJP!S10+SBET!S10+Sugarplay!T10 -> 621341.32 | U4: =WP!T10+GJP!T10+SBET!T10+Sugarplay!U10 -> 249517.97 | V4: =WP!U10+GJP!U10+SBET!U10+Sugarplay!V10 -> 40804.38 | W4: =P4-R4-T4 -> 817069.84 | X4: =W4/P4 -> 0.014295682 | Y4: =(P4-R4)/P4 -> 0.025166844 | Z4: =WP!AE10+GJP!AE10+SBET!AF10+Sugarplay!AG10 -> 1882353.4 | AA4: =AB4+AC4 -> 1027018.8 | AB4: =WP!AA10+GJP!AA10+SBET!AB10+Sugarplay!AC10 -> 1027018.8 | AC4: =WP!AB10+GJP!AB10+SBET!AC10+Sugarplay!AD10 -> 0 | AD4: =W4-AB4-AC4 -> -209948.92 | AE4: =AD4/P4 -> -0.003673325 | AF4: =AG4+AH4 -> 224640.79 | AG4: =WP!W10+GJP!W10+SBET!W10+Sugarplay!X10 -> 206662.07 | AH4: =WP!X10+GJP!X10+SBET!X10+Sugarplay!Y10 -> 17978.72 | AI4: =W4*0.09 -> 73536.286 | AM4: =W4-AB4-AC4-AG4-AH4-AI4 -> -508126 | AN4: =AM4/P4 -> -0.0088903145 | AO4: =WP!AC10+GJP!AC10+SBET!AD10+Sugarplay!AE10 -> 24934.69 | AP4: =WP!AD10+GJP!AD10+SBET!AE10+Sugarplay!AF10 -> -5158.46 | AQ4: =AD4-AG4-AH4-AI4 -> -508126 | AR4: =AM4-AQ4 -> 0
A5: =A4+1 -> 46084 | B5: =WP!L11+GJP!L11+SBET!L11+Sugarplay!L11 -> 9493443 | C5: =WP!K11+GJP!K11+SBET!K11+Sugarplay!K11 -> 81720 | D5: =WP!M11+GJP!M11+SBET!M11+Sugarplay!N11 -> 7971259 | E5: =B5-D5 -> 1522184 | F5: =W5 -> 1120695 | G5: =AD5 -> 1116040 | H5: =AM5 -> 777674.26 | I5: =WP!D11+GJP!D11+SBET!D11+Sugarplay!D11 -> 32603 | J5: =WP!J11+GJP!J11+SBET!J11+Sugarplay!J11 -> 20872 | K5: =WP!B11+GJP!B11+SBET!B11+Sugarplay!B11 -> 1273 | L5: =WP!C11+GJP!C11+SBET!C11+Sugarplay!C11 -> 385 | M5: =WP!E11+GJP!E11+SBET!E11+Sugarplay!E11 -> 840 | N5: =WP!F11+GJP!F11+SBET!F11+Sugarplay!F11 -> 4859 | O5: =WP!G11+GJP!G11+SBET!G11+Sugarplay!G11 -> 10981 | P5: =WP!O11+GJP!O11+SBET!O11+Sugarplay!P11 -> 68808339 | Q5: =WP!P11+GJP!P11+SBET!P11+Sugarplay!Q11 -> 64088379 | R5: =WP!R11+GJP!R11+SBET!R11+Sugarplay!S11 -> 67156074 | S5: =T5/Q5 -> 0.00829434 | T5: =WP!S11+GJP!S11+SBET!S11+Sugarplay!T11 -> 531570.81 | U5: =WP!T11+GJP!T11+SBET!T11+Sugarplay!U11 -> 220355.21 | V5: =WP!U11+GJP!U11+SBET!U11+Sugarplay!V11 -> 31186.92 | W5: =P5-R5-T5 -> 1120695 | X5: =W5/P5 -> 0.016287197 | Y5: =(P5-R5)/P5 -> 0.024012581 | Z5: =WP!AE11+GJP!AE11+SBET!AF11+Sugarplay!AG11 -> 1834307.9 | AA5: =AB5+AC5 -> 4655 | AB5: =WP!AA11+GJP!AA11+SBET!AB11+Sugarplay!AC11 -> 4655 | AC5: =WP!AB11+GJP!AB11+SBET!AC11+Sugarplay!AD11 -> 0 | AD5: =W5-AB5-AC5 -> 1116040 | AE5: =AD5/P5 -> 0.016219545 | AF5: =AG5+AH5 -> 237503.17 | AG5: =WP!W11+GJP!W11+SBET!W11+Sugarplay!X11 -> 221560.78 | AH5: =WP!X11+GJP!X11+SBET!X11+Sugarplay!Y11 -> 15942.39 | AI5: =W5*0.09 -> 100862.55 | AM5: =W5-AB5-AC5-AG5-AH5-AI5 -> 777674.26 | AN5: =AM5/P5 -> 0.011302035 | AO5: =WP!AC11+GJP!AC11+SBET!AD11+Sugarplay!AE11 -> 14094.8 | AP5: =WP!AD11+GJP!AD11+SBET!AE11+Sugarplay!AF11 -> -56452.86 | AQ5: =AD5-AG5-AH5-AI5 -> 777674.26 | AR5: =AM5-AQ5 -> 0
A6: =A5+1 -> 46085 | B6: =WP!L12+GJP!L12+SBET!L12+Sugarplay!L12 -> 11799989 | C6: =WP!K12+GJP!K12+SBET!K12+Sugarplay!K12 -> 108144 | D6: =WP!M12+GJP!M12+SBET!M12+Sugarplay!N12 -> 9658460 | E6: =B6-D6 -> 2141529.1 | F6: =W6 -> 1836446 | G6: =AD6 -> 1836288 | H6: =AM6 -> 1375940.2 | I6: =WP!D12+GJP!D12+SBET!D12+Sugarplay!D12 -> 36056 | J6: =WP!J12+GJP!J12+SBET!J12+Sugarplay!J12 -> 22720 | K6: =WP!B12+GJP!B12+SBET!B12+Sugarplay!B12 -> 1133 | L6: =WP!C12+GJP!C12+SBET!C12+Sugarplay!C12 -> 456 | M6: =WP!E12+GJP!E12+SBET!E12+Sugarplay!E12 -> 857 | N6: =WP!F12+GJP!F12+SBET!F12+Sugarplay!F12 -> 5303 | O6: =WP!G12+GJP!G12+SBET!G12+Sugarplay!G12 -> 11724 | P6: =WP!O12+GJP!O12+SBET!O12+Sugarplay!P12 -> 81349421 | Q6: =WP!P12+GJP!P12+SBET!P12+Sugarplay!Q12 -> 75596780 | R6: =WP!R12+GJP!R12+SBET!R12+Sugarplay!S12 -> 78804731 | S6: =T6/Q6 -> 0.0093686982 | T6: =WP!S12+GJP!S12+SBET!S12+Sugarplay!T12 -> 708243.42 | U6: =WP!T12+GJP!T12+SBET!T12+Sugarplay!U12 -> 318389.11 | V6: =WP!U12+GJP!U12+SBET!U12+Sugarplay!V12 -> 39667.62 | W6: =P6-R6-T6 -> 1836446 | X6: =W6/P6 -> 0.022574789 | Y6: =(P6-R6)/P6 -> 0.031280978 | Z6: =WP!AE12+GJP!AE12+SBET!AF12+Sugarplay!AG12 -> 2275472.5 | AA6: =AB6+AC6 -> 158 | AB6: =WP!AA12+GJP!AA12+SBET!AB12+Sugarplay!AC12 -> 158 | AC6: =WP!AB12+GJP!AB12+SBET!AC12+Sugarplay!AD12 -> 0 | AD6: =W6-AB6-AC6 -> 1836288 | AE6: =AD6/P6 -> 0.022572847 | AF6: =AG6+AH6 -> 295067.71 | AG6: =WP!W12+GJP!W12+SBET!W12+Sugarplay!X12 -> 275750.39 | AH6: =WP!X12+GJP!X12+SBET!X12+Sugarplay!Y12 -> 19317.32 | AI6: =W6*0.09 -> 165280.14 | AM6: =W6-AB6-AC6-AG6-AH6-AI6 -> 1375940.2 | AN6: =AM6/P6 -> 0.016913952 | AO6: =WP!AC12+GJP!AC12+SBET!AD12+Sugarplay!AE12 -> 0 | AP6: =WP!AD12+GJP!AD12+SBET!AE12+Sugarplay!AF12 -> -693.1 | AQ6: =AD6-AG6-AH6-AI6 -> 1375940.2 | AR6: =AM6-AQ6 -> 0
A7: =A6+1 -> 46086 | B7: =WP!L13+GJP!L13+SBET!L13+Sugarplay!L13 -> 11070696 | C7: =WP!K13+GJP!K13+SBET!K13+Sugarplay!K13 -> 104683 | D7: =WP!M13+GJP!M13+SBET!M13+Sugarplay!N13 -> 9393354 | E7: =B7-D7 -> 1677341.8 | F7: =W7 -> 1716183.1 | G7: =AD7 -> 1715683.1 | H7: =AM7 -> 1283730.2 | I7: =WP!D13+GJP!D13+SBET!D13+Sugarplay!D13 -> 30390 | J7: =WP!J13+GJP!J13+SBET!J13+Sugarplay!J13 -> 20570 | K7: =WP!B13+GJP!B13+SBET!B13+Sugarplay!B13 -> 1126 | L7: =WP!C13+GJP!C13+SBET!C13+Sugarplay!C13 -> 373 | M7: =WP!E13+GJP!E13+SBET!E13+Sugarplay!E13 -> 843 | N7: =WP!F13+GJP!F13+SBET!F13+Sugarplay!F13 -> 4861 | O7: =WP!G13+GJP!G13+SBET!G13+Sugarplay!G13 -> 11389 | P7: =WP!O13+GJP!O13+SBET!O13+Sugarplay!P13 -> 74995038 | Q7: =WP!P13+GJP!P13+SBET!P13+Sugarplay!Q13 -> 70418491 | R7: =WP!R13+GJP!R13+SBET!R13+Sugarplay!S13 -> 72621807 | S7: =T7/Q7 -> 0.0093306258 | T7: =WP!S13+GJP!S13+SBET!S13+Sugarplay!T13 -> 657048.59 | U7: =WP!T13+GJP!T13+SBET!T13+Sugarplay!U13 -> 279745.75 | V7: =WP!U13+GJP!U13+SBET!U13+Sugarplay!V13 -> 36585.53 | W7: =P7-R7-T7 -> 1716183.1 | X7: =W7/P7 -> 0.022883956 | Y7: =(P7-R7)/P7 -> 0.031645183 | Z7: =WP!AE13+GJP!AE13+SBET!AF13+Sugarplay!AG13 -> 2290627.3 | AA7: =AB7+AC7 -> 500 | AB7: =WP!AA13+GJP!AA13+SBET!AB13+Sugarplay!AC13 -> 500 | AC7: =WP!AB13+GJP!AB13+SBET!AC13+Sugarplay!AD13 -> 0 | AD7: =W7-AB7-AC7 -> 1715683.1 | AE7: =AD7/P7 -> 0.022877288 | AF7: =AG7+AH7 -> 277496.43 | AG7: =WP!W13+GJP!W13+SBET!W13+Sugarplay!X13 -> 258709.75 | AH7: =WP!X13+GJP!X13+SBET!X13+Sugarplay!Y13 -> 18786.68 | AI7: =W7*0.09 -> 154456.48 | AM7: =W7-AB7-AC7-AG7-AH7-AI7 -> 1283730.2 | AN7: =AM7/P7 -> 0.017117535 | AO7: =WP!AC13+GJP!AC13+SBET!AD13+Sugarplay!AE13 -> 0 | AP7: =WP!AD13+GJP!AD13+SBET!AE13+Sugarplay!AF13 -> -15883.11 | AQ7: =AD7-AG7-AH7-AI7 -> 1283730.2 | AR7: =AM7-AQ7 -> 0
A8: =A7+1 -> 46087 | B8: =WP!L14+GJP!L14+SBET!L14+Sugarplay!L14 -> 11336766 | C8: =WP!K14+GJP!K14+SBET!K14+Sugarplay!K14 -> 102748 | D8: =WP!M14+GJP!M14+SBET!M14+Sugarplay!N14 -> 9913747 | E8: =B8-D8 -> 1423019 | F8: =W8 -> 2163495.7 | G8: =AD8 -> 2162895.7 | H8: =AM8 -> 1684159.8 | I8: =WP!D14+GJP!D14+SBET!D14+Sugarplay!D14 -> 34834 | J8: =WP!J14+GJP!J14+SBET!J14+Sugarplay!J14 -> 25291 | K8: =WP!B14+GJP!B14+SBET!B14+Sugarplay!B14 -> 1211 | L8: =WP!C14+GJP!C14+SBET!C14+Sugarplay!C14 -> 418 | M8: =WP!E14+GJP!E14+SBET!E14+Sugarplay!E14 -> 855 | N8: =WP!F14+GJP!F14+SBET!F14+Sugarplay!F14 -> 5432 | O8: =WP!G14+GJP!G14+SBET!G14+Sugarplay!G14 -> 12047 | P8: =WP!O14+GJP!O14+SBET!O14+Sugarplay!P14 -> 76693220 | Q8: =WP!P14+GJP!P14+SBET!P14+Sugarplay!Q14 -> 71420335 | R8: =WP!R14+GJP!R14+SBET!R14+Sugarplay!S14 -> 73651319 | S8: =T8/Q8 -> 0.012299094 | T8: =WP!S14+GJP!S14+SBET!S14+Sugarplay!T14 -> 878405.45 | U8: =WP!T14+GJP!T14+SBET!T14+Sugarplay!U14 -> 355546.15 | V8: =WP!U14+GJP!U14+SBET!U14+Sugarplay!V14 -> 27739.37 | W8: =P8-R8-T8 -> 2163495.7 | X8: =W8/P8 -> 0.028209739 | Y8: =(P8-R8)/P8 -> 0.039663234 | Z8: =WP!AE14+GJP!AE14+SBET!AF14+Sugarplay!AG14 -> 1772925.9 | AA8: =AB8+AC8 -> 600 | AB8: =WP!AA14+GJP!AA14+SBET!AB14+Sugarplay!AC14 -> 600 | AC8: =WP!AB14+GJP!AB14+SBET!AC14+Sugarplay!AD14 -> 0 | AD8: =W8-AB8-AC8 -> 2162895.7 | AE8: =AD8/P8 -> 0.028201915 | AF8: =AG8+AH8 -> 284021.27 | AG8: =WP!W14+GJP!W14+SBET!W14+Sugarplay!X14 -> 264193.49 | AH8: =WP!X14+GJP!X14+SBET!X14+Sugarplay!Y14 -> 19827.78 | AI8: =W8*0.09 -> 194714.61 | AM8: =W8-AB8-AC8-AG8-AH8-AI8 -> 1684159.8 | AN8: =AM8/P8 -> 0.021959696 | AO8: =WP!AC14+GJP!AC14+SBET!AD14+Sugarplay!AE14 -> 0 | AP8: =WP!AD14+GJP!AD14+SBET!AE14+Sugarplay!AF14 -> -22828.95 | AQ8: =AD8-AG8-AH8-AI8 -> 1684159.8 | AR8: =AM8-AQ8 -> 0
A9: =A8+1 -> 46088 | B9: =WP!L15+GJP!L15+SBET!L15+Sugarplay!L15 -> 9146001.2 | C9: =WP!K15+GJP!K15+SBET!K15+Sugarplay!K15 -> 80548 | D9: =WP!M15+GJP!M15+SBET!M15+Sugarplay!N15 -> 7388477 | E9: =B9-D9 -> 1757524.2 | F9: =W9 -> 2096383 | G9: =AD9 -> 2092285 | H9: =AM9 -> 1674812.2 | I9: =WP!D15+GJP!D15+SBET!D15+Sugarplay!D15 -> 31535 | J9: =WP!J15+GJP!J15+SBET!J15+Sugarplay!J15 -> 22766 | K9: =WP!B15+GJP!B15+SBET!B15+Sugarplay!B15 -> 1187 | L9: =WP!C15+GJP!C15+SBET!C15+Sugarplay!C15 -> 429 | M9: =WP!E15+GJP!E15+SBET!E15+Sugarplay!E15 -> 890 | N9: =WP!F15+GJP!F15+SBET!F15+Sugarplay!F15 -> 5370 | O9: =WP!G15+GJP!G15+SBET!G15+Sugarplay!G15 -> 12128 | P9: =WP!O15+GJP!O15+SBET!O15+Sugarplay!P15 -> 61440169 | Q9: =WP!P15+GJP!P15+SBET!P15+Sugarplay!Q15 -> 57446216 | R9: =WP!R15+GJP!R15+SBET!R15+Sugarplay!S15 -> 58710718 | S9: =T9/Q9 -> 0.011020182 | T9: =WP!S15+GJP!S15+SBET!S15+Sugarplay!T15 -> 633067.76 | U9: =WP!T15+GJP!T15+SBET!T15+Sugarplay!U15 -> 238979.64 | V9: =WP!U15+GJP!U15+SBET!U15+Sugarplay!V15 -> 44748.36 | W9: =P9-R9-T9 -> 2096383 | X9: =W9/P9 -> 0.034120723 | Y9: =(P9-R9)/P9 -> 0.044424531 | Z9: =WP!AE15+GJP!AE15+SBET!AF15+Sugarplay!AG15 -> 1822697.1 | AA9: =AB9+AC9 -> 4098 | AB9: =WP!AA15+GJP!AA15+SBET!AB15+Sugarplay!AC15 -> 4098 | AC9: =WP!AB15+GJP!AB15+SBET!AC15+Sugarplay!AD15 -> 0 | AD9: =W9-AB9-AC9 -> 2092285 | AE9: =AD9/P9 -> 0.034054023 | AF9: =AG9+AH9 -> 228798.32 | AG9: =WP!W15+GJP!W15+SBET!W15+Sugarplay!X15 -> 214021.57 | AH9: =WP!X15+GJP!X15+SBET!X15+Sugarplay!Y15 -> 14776.75 | AI9: =W9*0.09 -> 188674.47 | AM9: =W9-AB9-AC9-AG9-AH9-AI9 -> 1674812.2 | AN9: =AM9/P9 -> 0.027259238 | AO9: =WP!AC15+GJP!AC15+SBET!AD15+Sugarplay!AE15 -> 0 | AP9: =WP!AD15+GJP!AD15+SBET!AE15+Sugarplay!AF15 -> -6039.02 | AQ9: =AD9-AG9-AH9-AI9 -> 1674812.2 | AR9: =AM9-AQ9 -> 0
A10: =A9+1 -> 46089 | B10: =WP!L16+GJP!L16+SBET!L16+Sugarplay!L16 -> 8743030.4 | C10: =WP!K16+GJP!K16+SBET!K16+Sugarplay!K16 -> 89151 | D10: =WP!M16+GJP!M16+SBET!M16+Sugarplay!N16 -> 7021701 | E10: =B10-D10 -> 1721329.4 | F10: =W10 -> 1430284.9 | G10: =AD10 -> 1430284.9 | H10: =AM10 -> 1083093 | I10: =WP!D16+GJP!D16+SBET!D16+Sugarplay!D16 -> 44452 | J10: =WP!J16+GJP!J16+SBET!J16+Sugarplay!J16 -> 35587 | K10: =WP!B16+GJP!B16+SBET!B16+Sugarplay!B16 -> 1495 | L10: =WP!C16+GJP!C16+SBET!C16+Sugarplay!C16 -> 475 | M10: =WP!E16+GJP!E16+SBET!E16+Sugarplay!E16 -> 861 | N10: =WP!F16+GJP!F16+SBET!F16+Sugarplay!F16 -> 5524 | O10: =WP!G16+GJP!G16+SBET!G16+Sugarplay!G16 -> 11873 | P10: =WP!O16+GJP!O16+SBET!O16+Sugarplay!P16 -> 59518719 | Q10: =WP!P16+GJP!P16+SBET!P16+Sugarplay!Q16 -> 55414312 | R10: =WP!R16+GJP!R16+SBET!R16+Sugarplay!S16 -> 57454100 | S10: =T10/Q10 -> 0.011447123 | T10: =WP!S16+GJP!S16+SBET!S16+Sugarplay!T16 -> 634334.47 | U10: =WP!T16+GJP!T16+SBET!T16+Sugarplay!U16 -> 219316.17 | V10: =WP!U16+GJP!U16+SBET!U16+Sugarplay!V16 -> 35016.34 | W10: =P10-R10-T10 -> 1430284.9 | X10: =W10/P10 -> 0.024030841 | Y10: =(P10-R10)/P10 -> 0.034688571 | Z10: =WP!AE16+GJP!AE16+SBET!AF16+Sugarplay!AG16 -> 1959603.2 | AA10: =AB10+AC10 -> 0 | AB10: =WP!AA16+GJP!AA16+SBET!AB16+Sugarplay!AC16 -> 0 | AC10: =WP!AB16+GJP!AB16+SBET!AC16+Sugarplay!AD16 -> 0 | AD10: =W10-AB10-AC10 -> 1430284.9 | AE10: =AD10/P10 -> 0.024030841 | AF10: =AG10+AH10 -> 218466.26 | AG10: =WP!W16+GJP!W16+SBET!W16+Sugarplay!X16 -> 204422.46 | AH10: =WP!X16+GJP!X16+SBET!X16+Sugarplay!Y16 -> 14043.8 | AI10: =W10*0.09 -> 128725.64 | AM10: =W10-AB10-AC10-AG10-AH10-AI10 -> 1083093 | AN10: =AM10/P10 -> 0.018197518 | AO10: =WP!AC16+GJP!AC16+SBET!AD16+Sugarplay!AE16 -> 0 | AP10: =WP!AD16+GJP!AD16+SBET!AE16+Sugarplay!AF16 -> -32070.54 | AQ10: =AD10-AG10-AH10-AI10 -> 1083093 | AR10: =AM10-AQ10 -> 0
A11: =A10+1 -> 46090 | B11: =WP!L17+GJP!L17+SBET!L17+Sugarplay!L17 -> 8998021.2 | C11: =WP!K17+GJP!K17+SBET!K17+Sugarplay!K17 -> 84741 | D11: =WP!M17+GJP!M17+SBET!M17+Sugarplay!N17 -> 9075963 | E11: =B11-D11 -> -77941.79 | F11: =W11 -> 1168422.1 | G11: =AD11 -> -189137.81 | H11: =AM11 -> -522932.01 | I11: =WP!D17+GJP!D17+SBET!D17+Sugarplay!D17 -> 35036 | J11: =WP!J17+GJP!J17+SBET!J17+Sugarplay!J17 -> 26675 | K11: =WP!B17+GJP!B17+SBET!B17+Sugarplay!B17 -> 1324 | L11: =WP!C17+GJP!C17+SBET!C17+Sugarplay!C17 -> 465 | M11: =WP!E17+GJP!E17+SBET!E17+Sugarplay!E17 -> 812 | N11: =WP!F17+GJP!F17+SBET!F17+Sugarplay!F17 -> 4866 | O11: =WP!G17+GJP!G17+SBET!G17+Sugarplay!G17 -> 11121 | P11: =WP!O17+GJP!O17+SBET!O17+Sugarplay!P17 -> 62418180 | Q11: =WP!P17+GJP!P17+SBET!P17+Sugarplay!Q17 -> 57490214 | R11: =WP!R17+GJP!R17+SBET!R17+Sugarplay!S17 -> 60604634 | S11: =T11/Q11 -> 0.011221456 | T11: =WP!S17+GJP!S17+SBET!S17+Sugarplay!T17 -> 645123.92 | U11: =WP!T17+GJP!T17+SBET!T17+Sugarplay!U17 -> 251060.31 | V11: =WP!U17+GJP!U17+SBET!U17+Sugarplay!V17 -> 32777.63 | W11: =P11-R11-T11 -> 1168422.1 | X11: =W11/P11 -> 0.01871926 | Y11: =(P11-R11)/P11 -> 0.029054773 | Z11: =WP!AE17+GJP!AE17+SBET!AF17+Sugarplay!AG17 -> 2770004.3 | AA11: =AB11+AC11 -> 1357560 | AB11: =WP!AA17+GJP!AA17+SBET!AB17+Sugarplay!AC17 -> 1357560 | AC11: =WP!AB17+GJP!AB17+SBET!AC17+Sugarplay!AD17 -> 0 | AD11: =W11-AB11-AC11 -> -189137.81 | AE11: =AD11/P11 -> -0.0030301718 | AF11: =AG11+AH11 -> 228636.21 | AG11: =WP!W17+GJP!W17+SBET!W17+Sugarplay!X17 -> 210483.81 | AH11: =WP!X17+GJP!X17+SBET!X17+Sugarplay!Y17 -> 18152.4 | AI11: =W11*0.09 -> 105157.99 | AM11: =W11-AB11-AC11-AG11-AH11-AI11 -> -522932.01 | AN11: =AM11/P11 -> -0.0083778798 | AO11: =WP!AC17+GJP!AC17+SBET!AD17+Sugarplay!AE17 -> 123737.11 | AP11: =WP!AD17+GJP!AD17+SBET!AE17+Sugarplay!AF17 -> -147358.45 | AQ11: =AD11-AG11-AH11-AI11 -> -522932.01 | AR11: =AM11-AQ11 -> 0
A12: =A11+1 -> 46091 | B12: =WP!L18+GJP!L18+SBET!L18+Sugarplay!L18 -> 8656049.1 | C12: =WP!K18+GJP!K18+SBET!K18+Sugarplay!K18 -> 65052 | D12: =WP!M18+GJP!M18+SBET!M18+Sugarplay!N18 -> 7894537 | E12: =B12-D12 -> 761512.14 | F12: =W12 -> 1049437.1 | G12: =AD12 -> 1005714.1 | H12: =AM12 -> 693346.95 | I12: =WP!D18+GJP!D18+SBET!D18+Sugarplay!D18 -> 33657 | J12: =WP!J18+GJP!J18+SBET!J18+Sugarplay!J18 -> 24070 | K12: =WP!B18+GJP!B18+SBET!B18+Sugarplay!B18 -> 1282 | L12: =WP!C18+GJP!C18+SBET!C18+Sugarplay!C18 -> 394 | M12: =WP!E18+GJP!E18+SBET!E18+Sugarplay!E18 -> 850 | N12: =WP!F18+GJP!F18+SBET!F18+Sugarplay!F18 -> 4877 | O12: =WP!G18+GJP!G18+SBET!G18+Sugarplay!G18 -> 10991 | P12: =WP!O18+GJP!O18+SBET!O18+Sugarplay!P18 -> 60320102 | Q12: =WP!P18+GJP!P18+SBET!P18+Sugarplay!Q18 -> 56307616 | R12: =WP!R18+GJP!R18+SBET!R18+Sugarplay!S18 -> 58750252 | S12: =T12/Q12 -> 0.0092423188 | T12: =WP!S18+GJP!S18+SBET!S18+Sugarplay!T18 -> 520412.94 | U12: =WP!T18+GJP!T18+SBET!T18+Sugarplay!U18 -> 217343.52 | V12: =WP!U18+GJP!U18+SBET!U18+Sugarplay!V18 -> 29775.73 | W12: =P12-R12-T12 -> 1049437.1 | X12: =W12/P12 -> 0.0173978 | Y12: =(P12-R12)/P12 -> 0.02602532 | Z12: =WP!AE18+GJP!AE18+SBET!AF18+Sugarplay!AG18 -> 1998999.8 | AA12: =AB12+AC12 -> 43723 | AB12: =WP!AA18+GJP!AA18+SBET!AB18+Sugarplay!AC18 -> 43723 | AC12: =WP!AB18+GJP!AB18+SBET!AC18+Sugarplay!AD18 -> 0 | AD12: =W12-AB12-AC12 -> 1005714.1 | AE12: =AD12/P12 -> 0.01667295 | AF12: =AG12+AH12 -> 217917.77 | AG12: =WP!W18+GJP!W18+SBET!W18+Sugarplay!X18 -> 202128.61 | AH12: =WP!X18+GJP!X18+SBET!X18+Sugarplay!Y18 -> 15789.16 | AI12: =W12*0.09 -> 94449.335 | AM12: =W12-AB12-AC12-AG12-AH12-AI12 -> 693346.95 | AN12: =AM12/P12 -> 0.011494459 | AO12: =WP!AC18+GJP!AC18+SBET!AD18+Sugarplay!AE18 -> 3100 | AP12: =WP!AD18+GJP!AD18+SBET!AE18+Sugarplay!AF18 -> -11420.41 | AQ12: =AD12-AG12-AH12-AI12 -> 693346.95 | AR12: =AM12-AQ12 -> 0
A13: =A12+1 -> 46092 | B13: =WP!L19+GJP!L19+SBET!L19+Sugarplay!L19 -> 9771389.9 | C13: =WP!K19+GJP!K19+SBET!K19+Sugarplay!K19 -> 62776.89 | D13: =WP!M19+GJP!M19+SBET!M19+Sugarplay!N19 -> 7339569 | E13: =B13-D13 -> 2431820.9 | F13: =W13 -> 1578360.4 | G13: =AD13 -> 1578024.4 | H13: =AM13 -> 1193323.2 | I13: =WP!D19+GJP!D19+SBET!D19+Sugarplay!D19 -> 35220 | J13: =WP!J19+GJP!J19+SBET!J19+Sugarplay!J19 -> 25573 | K13: =WP!B19+GJP!B19+SBET!B19+Sugarplay!B19 -> 1043 | L13: =WP!C19+GJP!C19+SBET!C19+Sugarplay!C19 -> 340 | M13: =WP!E19+GJP!E19+SBET!E19+Sugarplay!E19 -> 793 | N13: =WP!F19+GJP!F19+SBET!F19+Sugarplay!F19 -> 4878 | O13: =WP!G19+GJP!G19+SBET!G19+Sugarplay!G19 -> 11239 | P13: =WP!O19+GJP!O19+SBET!O19+Sugarplay!P19 -> 57537374 | Q13: =WP!P19+GJP!P19+SBET!P19+Sugarplay!Q19 -> 53706677 | R13: =WP!R19+GJP!R19+SBET!R19+Sugarplay!S19 -> 55368621 | S13: =T13/Q13 -> 0.010992913 | T13: =WP!S19+GJP!S19+SBET!S19+Sugarplay!T19 -> 590392.81 | U13: =WP!T19+GJP!T19+SBET!T19+Sugarplay!U19 -> 242227.65 | V13: =WP!U19+GJP!U19+SBET!U19+Sugarplay!V19 -> 27742.02 | W13: =P13-R13-T13 -> 1578360.4 | X13: =W13/P13 -> 0.027431916 | Y13: =(P13-R13)/P13 -> 0.037692947 | Z13: =WP!AE19+GJP!AE19+SBET!AF19+Sugarplay!AG19 -> 2716736.4 | AA13: =AB13+AC13 -> 336 | AB13: =WP!AA19+GJP!AA19+SBET!AB19+Sugarplay!AC19 -> 336 | AC13: =WP!AB19+GJP!AB19+SBET!AC19+Sugarplay!AD19 -> 0 | AD13: =W13-AB13-AC13 -> 1578024.4 | AE13: =AD13/P13 -> 0.027426076 | AF13: =AG13+AH13 -> 242648.76 | AG13: =WP!W19+GJP!W19+SBET!W19+Sugarplay!X19 -> 227970.11 | AH13: =WP!X19+GJP!X19+SBET!X19+Sugarplay!Y19 -> 14678.65 | AI13: =W13*0.09 -> 142052.44 | AM13: =W13-AB13-AC13-AG13-AH13-AI13 -> 1193323.2 | AN13: =AM13/P13 -> 0.020739966 | AO13: =WP!AC19+GJP!AC19+SBET!AD19+Sugarplay!AE19 -> 0 | AP13: =WP!AD19+GJP!AD19+SBET!AE19+Sugarplay!AF19 -> -4601.87 | AQ13: =AD13-AG13-AH13-AI13 -> 1193323.2 | AR13: =AM13-AQ13 -> 0
A14: =A13+1 -> 46093 | B14: =WP!L20+GJP!L20+SBET!L20+Sugarplay!L20 -> 9124174.9 | C14: =WP!K20+GJP!K20+SBET!K20+Sugarplay!K20 -> 60659 | D14: =WP!M20+GJP!M20+SBET!M20+Sugarplay!N20 -> 8123782 | E14: =B14-D14 -> 1000392.9 | F14: =W14 -> 1754210.2 | G14: =AD14 -> 1754018.2 | H14: =AM14 -> 1367157.9 | I14: =WP!D20+GJP!D20+SBET!D20+Sugarplay!D20 -> 32710 | J14: =WP!J20+GJP!J20+SBET!J20+Sugarplay!J20 -> 22464 | K14: =WP!B20+GJP!B20+SBET!B20+Sugarplay!B20 -> 980 | L14: =WP!C20+GJP!C20+SBET!C20+Sugarplay!C20 -> 342 | M14: =WP!E20+GJP!E20+SBET!E20+Sugarplay!E20 -> 776 | N14: =WP!F20+GJP!F20+SBET!F20+Sugarplay!F20 -> 4825 | O14: =WP!G20+GJP!G20+SBET!G20+Sugarplay!G20 -> 11006 | P14: =WP!O20+GJP!O20+SBET!O20+Sugarplay!P20 -> 59989236 | Q14: =WP!P20+GJP!P20+SBET!P20+Sugarplay!Q20 -> 55758780 | R14: =WP!R20+GJP!R20+SBET!R20+Sugarplay!S20 -> 57642732 | S14: =T14/Q14 -> 0.010622436 | T14: =WP!S20+GJP!S20+SBET!S20+Sugarplay!T20 -> 592294.08 | U14: =WP!T20+GJP!T20+SBET!T20+Sugarplay!U20 -> 243554.97 | V14: =WP!U20+GJP!U20+SBET!U20+Sugarplay!V20 -> 26864.98 | W14: =P14-R14-T14 -> 1754210.2 | X14: =W14/P14 -> 0.029242082 | Y14: =(P14-R14)/P14 -> 0.039115421 | Z14: =WP!AE20+GJP!AE20+SBET!AF20+Sugarplay!AG20 -> 1808352.5 | AA14: =AB14+AC14 -> 192 | AB14: =WP!AA20+GJP!AA20+SBET!AB20+Sugarplay!AC20 -> 192 | AC14: =WP!AB20+GJP!AB20+SBET!AC20+Sugarplay!AD20 -> 0 | AD14: =W14-AB14-AC14 -> 1754018.2 | AE14: =AD14/P14 -> 0.029238881 | AF14: =AG14+AH14 -> 228981.39 | AG14: =WP!W20+GJP!W20+SBET!W20+Sugarplay!X20 -> 212733.99 | AH14: =WP!X20+GJP!X20+SBET!X20+Sugarplay!Y20 -> 16247.4 | AI14: =W14*0.09 -> 157878.91 | AM14: =W14-AB14-AC14-AG14-AH14-AI14 -> 1367157.9 | AN14: =AM14/P14 -> 0.022790053 | AO14: =WP!AC20+GJP!AC20+SBET!AD20+Sugarplay!AE20 -> 2100 | AP14: =WP!AD20+GJP!AD20+SBET!AE20+Sugarplay!AF20 -> -17213.99 | AQ14: =AD14-AG14-AH14-AI14 -> 1367157.9 | AR14: =AM14-AQ14 -> 0
A15: =A14+1 -> 46094 | B15: =WP!L21+GJP!L21+SBET!L21+Sugarplay!L21 -> 0 | C15: =WP!K21+GJP!K21+SBET!K21+Sugarplay!K21 -> 0 | D15: =WP!M21+GJP!M21+SBET!M21+Sugarplay!N21 -> 0 | E15: =B15-D15 -> 0 | F15: =W15 -> 0 | G15: =AD15 -> 0 | H15: =AM15 -> 0 | I15: =WP!D21+GJP!D21+SBET!D21+Sugarplay!D21 -> 0 | J15: =WP!J21+GJP!J21+SBET!J21+Sugarplay!J21 -> 0 | K15: =WP!B21+GJP!B21+SBET!B21+Sugarplay!B21 -> 0 | L15: =WP!C21+GJP!C21+SBET!C21+Sugarplay!C21 -> 0 | M15: =WP!E21+GJP!E21+SBET!E21+Sugarplay!E21 -> 0 | N15: =WP!F21+GJP!F21+SBET!F21+Sugarplay!F21 -> 0 | O15: =WP!G21+GJP!G21+SBET!G21+Sugarplay!G21 -> 0 | P15: =WP!O21+GJP!O21+SBET!O21+Sugarplay!P21 -> 0 | Q15: =WP!P21+GJP!P21+SBET!P21+Sugarplay!Q21 -> 0 | R15: =WP!R21+GJP!R21+SBET!R21+Sugarplay!S21 -> 0 | S15: =T15/Q15 -> #DIV/0! | T15: =WP!S21+GJP!S21+SBET!S21+Sugarplay!T21 -> 0 | U15: =WP!T21+GJP!T21+SBET!T21+Sugarplay!U21 -> 0 | V15: =WP!U21+GJP!U21+SBET!U21+Sugarplay!V21 -> 0 | W15: =P15-R15-T15 -> 0 | X15: =W15/P15 -> #DIV/0! | Y15: =(P15-R15)/P15 -> #DIV/0! | Z15: =WP!AE21+GJP!AE21+SBET!AF21+Sugarplay!AG21 -> 0 | AA15: =AB15+AC15 -> 0 | AB15: =WP!AA21+GJP!AA21+SBET!AB21+Sugarplay!AC21 -> 0 | AC15: =WP!AB21+GJP!AB21+SBET!AC21+Sugarplay!AD21 -> 0 | AD15: =W15-AB15-AC15 -> 0 | AE15: =AD15/P15 -> #DIV/0! | AF15: =AG15+AH15 -> 0 | AG15: =WP!W21+GJP!W21+SBET!W21+Sugarplay!X21 -> 0 | AH15: =WP!X21+GJP!X21+SBET!X21+Sugarplay!Y21 -> 0 | AI15: =W15*0.09 -> 0 | AM15: =W15-AB15-AC15-AG15-AH15-AI15 -> 0 | AN15: =AM15/P15 -> #DIV/0! | AO15: =WP!AC21+GJP!AC21+SBET!AD21+Sugarplay!AE21 -> 0 | AP15: =WP!AD21+GJP!AD21+SBET!AE21+Sugarplay!AF21 -> 0 | AQ15: =AD15-AG15-AH15-AI15 -> 0 | AR15: =AM15-AQ15 -> 0
... A33: =A32+1 -> 46112 | B33: =WP!L39+GJP!L39+SBET!L39+Sugarplay!L39 -> 0 | C33: =WP!K39+GJP!K39+SBET!K39+Sugarplay!K39 -> 0 | D33: =WP!M39+GJP!M39+SBET!M39+Sugarplay!N39 -> 0 | E33: =B33-D33 -> 0 | F33: =W33 -> 0 | G33: =AD33 -> 0 | H33: =AM33 -> 0 | I33: =WP!D39+GJP!D39+SBET!D39+Sugarplay!D39 -> 0 | J33: =WP!J39+GJP!J39+SBET!J39+Sugarplay!J39 -> 0 | K33: =WP!B39+GJP!B39+SBET!B39+Sugarplay!B39 -> 0 | L33: =WP!C39+GJP!C39+SBET!C39+Sugarplay!C39 -> 0 | M33: =WP!E39+GJP!E39+SBET!E39+Sugarplay!E39 -> 0 | N33: =WP!F39+GJP!F39+SBET!F39+Sugarplay!F39 -> 0 | O33: =WP!G39+GJP!G39+SBET!G39+Sugarplay!G39 -> 0 | P33: =WP!O39+GJP!O39+SBET!O39+Sugarplay!P39 -> 0 | Q33: =WP!P39+GJP!P39+SBET!P39+Sugarplay!Q39 -> 0 | R33: =WP!R39+GJP!R39+SBET!R39+Sugarplay!S39 -> 0 | S33: =T33/Q33 -> #DIV/0! | T33: =WP!S39+GJP!S39+SBET!S39+Sugarplay!T39 -> 0 | U33: =WP!T39+GJP!T39+SBET!T39+Sugarplay!U39 -> 0 | V33: =WP!U39+GJP!U39+SBET!U39+Sugarplay!V39 -> 0 | W33: =P33-R33-T33 -> 0 | X33: =W33/P33 -> #DIV/0! | Y33: =(P33-R33)/P33 -> #DIV/0! | Z33: =WP!AE39+GJP!AE39+SBET!AF39+Sugarplay!AG39 -> 0 | AA33: =AB33+AC33 -> 0 | AB33: =WP!AA39+GJP!AA39+SBET!AB39+Sugarplay!AC39 -> 0 | AC33: =WP!AB39+GJP!AB39+SBET!AC39+Sugarplay!AD39 -> 0 | AD33: =W33-AB33-AC33 -> 0 | AE33: =AD33/P33 -> #DIV/0! | AF33: =AG33+AH33 -> 0 | AG33: =WP!W39+GJP!W39+SBET!W39+Sugarplay!X39 -> 0 | AH33: =WP!X39+GJP!X39+SBET!X39+Sugarplay!Y39 -> 0 | AI33: =W33*0.09 -> 0 | AM33: =W33-AB33-AC33-AG33-AH33-AI33 -> 0 | AN33: =AM33/P33 -> #DIV/0! | AO33: =WP!AC39+GJP!AC39+SBET!AD39+Sugarplay!AE39 -> 0 | AP33: =WP!AD39+GJP!AD39+SBET!AE39+Sugarplay!AF39 -> 0 | AQ33: =AD33-AG33-AH33-AI33 -> 0 | AR33: =AM33-AQ33 -> 0
A34: 日均 | B34: =AVERAGE(B3:B14) -> 9747411.2 | C34: =AVERAGE(C3:C14) -> 85846.158 | D34: =AVERAGE(D3:D14) -> 8517410.4 | E34: =AVERAGE(E3:E14) -> 1230000.7 | F34: =AVERAGE(F3:F14) -> 1479550.5 | G34: =AVERAGE(G3:G14) -> 1276313.8 | H34: =AVERAGE(H3:H14) -> 898337.61 | I34: =AVERAGE(I3:I14) -> 34485.917 | ... R34: =AVERAGE(R3:R14) -> 63483547 | S34: =T312/Q312 -> #DIV/0! | T34: =AVERAGE(T3:T14) -> 645315.47 | U34: =AVERAGE(U3:U14) -> 260022.74 | V34: =AVERAGE(V3:V14) -> 33513.263 | W34: =AVERAGE(W3:W14) -> 1479550.5 | X34: =W312/P312 -> #DIV/0! | Y34: =(P312-R312)/P312 -> #DIV/0! | Z34: =AVERAGE(Z3:Z14) -> 2091423.5 | AA34: =AVERAGE(AA3:AA14) -> 203236.73 | AB34: =AVERAGE(AB3:AB14) -> 203236.73 | AC34: =AVERAGE(AC3:AC14) -> 0 | AD34: =AVERAGE(AD3:AD14) -> 1276313.8 | AE34: =AD312/P312 -> #DIV/0! | AF34: =AVERAGE(AF3:AF14) -> 244816.64 | AG34: =AVERAGE(AG3:AG14) -> 227781.78 | AH34: =AVERAGE(AH3:AH14) -> 17034.866 | AI34: =AVERAGE(AI3:AI14) -> 133159.55 | AJ34: =AVERAGE(AJ3:AJ14) -> 0 | AK34: =AVERAGE(AK3:AK14) -> 0 | AL34: =AVERAGE(AL3:AL14) -> 0 | AM34: =AVERAGE(AM3:AM14) -> 898337.61 | AN34: =AM312/P312 -> #DIV/0! | AO34: =AVERAGE(AO3:AO14) -> 14005.55 | AP34: =AVERAGE(AP3:AP14) -> -26856.257 | AQ34: =AVERAGE(AQ3:AQ14) -> 898337.61 | AR34: =AVERAGE(AR3:AR14) -> 0
A35: 汇总 | B35: =SUM(B3:B33) -> 1.1696893e+08 | C35: =SUM(C3:C33) -> 1030153.9 | D35: =SUM(D3:D33) -> 102208925 | E35: =SUM(E3:E33) -> 14760009 | F35: =SUM(F3:F33) -> 17754606 | G35: =SUM(G3:G33) -> 15315766 | H35: =SUM(H3:H33) -> 10780051 | I35: =SUM(I3:I33) -> 413831 | ... R35: =SUM(R3:R33) -> 7.6180257e+08 | S35: =T35/Q35 -> 0.010556402 | T35: =SUM(T3:T33) -> 7743785.6 | U35: =SUM(U3:U33) -> 3120272.9 | V35: =SUM(V3:V33) -> 402159.16 | W35: =SUM(W3:W33) -> 17754606 | X35: =W35/P35 -> 0.022551232 | Y35: =(P35-R35)/P35 -> 0.032387096 | Z35: =SUM(Z3:Z33) -> 25097081 | AA35: =SUM(AA3:AA33) -> 2438840.7 | AB35: =SUM(AB3:AB33) -> 2438840.7 | AC35: =SUM(AC3:AC33) -> 0 | AD35: =SUM(AD3:AD33) -> 15315766 | AE35: =AD35/P35 -> 0.019453508 | AF35: =SUM(AF3:AF33) -> 2937799.7 | AG35: =SUM(AG3:AG33) -> 2733381.3 | AH35: =SUM(AH3:AH33) -> 204418.39 | AI35: =SUM(AI3:AI33) -> 1597914.6 | AJ35: =SUM(AJ3:AJ33) -> 0 | AK35: =SUM(AK3:AK33) -> 0 | AL35: =SUM(AL3:AL33) -> 0 | AM35: =SUM(AM3:AM33) -> 10780051 | AN35: =AM35/P35 -> 0.013692415 | AO35: =SUM(AO3:AO33) -> 168066.6 | AP35: =SUM(AP3:AP33) -> -322275.09 | AQ35: =SUM(AQ3:AQ33) -> 10780051 | AR35: =SUM(AR3:AR33) -> 0
A36: 核对 | B36: =WP!L40+GJP!L40+SBET!L40+Sugarplay!L40 -> 1.1696893e+08 | C36: =WP!K40+GJP!K40+SBET!K40+Sugarplay!K40 -> 1030153.9 | D36: =WP!M40+GJP!M40+SBET!M40+Sugarplay!N40 -> 102208925 | E36: =E35 -> 14760009 | F36: =F35 -> 17754606 | G36: =G35 -> 15315766 | H36: =H35 -> 10780051 | I36: =WP!D40+GJP!D40+SBET!D40+Sugarplay!D40 -> 413831 | J36: =WP!J40+GJP!J40+SBET!J40+Sugarplay!J40 -> 290144 | K36: =WP!B40+GJP!B40+SBET!B40+Sugarplay!B40 -> 14713 | L36: =WP!C40+GJP!C40+SBET!C40+Sugarplay!C40 -> 4871 | M36: =WP!E40+GJP!E40+SBET!E40+Sugarplay!E40 -> 10272 | N36: =WP!F40+GJP!F40+SBET!F40+Sugarplay!F40 -> 61637 | O36: =WP!G40+GJP!G40+SBET!G40+Sugarplay!G40 -> 137802 | P36: =WP!O40+GJP!O40+SBET!O40+Sugarplay!P40 -> 7.8730096e+08 | Q36: =WP!P40+GJP!P40+SBET!P40+Sugarplay!Q40 -> 7.3356295e+08 | R36: =WP!R40+GJP!R40+SBET!R40+Sugarplay!S40 -> 7.6180257e+08 | S36: =T36/Q36 -> 0.010556402 | T36: =WP!S40+GJP!S40+SBET!S40+Sugarplay!T40 -> 7743785.6 | U36: =WP!T40+GJP!T40+SBET!T40+Sugarplay!U40 -> 3120272.9 | V36: =WP!U40+GJP!U40+SBET!U40+Sugarplay!V40 -> 402159.16 | W36: =W35 -> 17754606 | X36: =W36/P36 -> 0.022551232 | Y36: =(P36-R36)/P36 -> 0.032387096 | Z36: =WP!AE40+GJP!AE40+SBET!AF40+Sugarplay!AG40 -> 25097081 | AA36: =AA35 -> 2438840.7 | AB36: =WP!AA40+GJP!AA40+SBET!AB40+Sugarplay!AC40 -> 2438840.7 | AC36: =WP!AB40+GJP!AB40+SBET!AC40+Sugarplay!AD40 -> 0 | AD36: =AD35 -> 15315766 | AE36: =AD36/P36 -> 0.019453508 | AF36: =AF35 -> 2937799.7 | AG36: =WP!W40+GJP!W40+SBET!W40+Sugarplay!X40 -> 2733381.3 | AH36: =WP!X40+GJP!X40+SBET!X40+Sugarplay!Y40 -> 204418.39 | AI36: =AI35 -> 1597914.6 | AM36: =AM35 -> 10780051 | AN36: =AM36/P36 -> 0.013692415 | AO36: =WP!AC40+GJP!AC40+SBET!AD40+Sugarplay!AE40 -> 168066.6 | AP36: =WP!AD40+GJP!AD40+SBET!AE40+Sugarplay!AF40 -> -322275.09 | AQ36: =AQ35 -> 10780051
A37: 差额 | B37: =B35-B36 -> 0 | D37: =D35-D36 -> 0 | E37: =E35-E36 -> 0 | F37: =F35-F36 -> 0 | G37: =G35-G36 -> 0 | H37: =H35-H36 -> 0 | I37: =I35-I36 -> 0 | J37: =J35-J36 -> 0 | K37: =K35-K36 -> 0 | ... AR37: =AR35-AR36 -> 0

Sheet 2025全年数据走势图
A1: 日期（2026） | B1: 充值 | C1: 提款 | D1: 充提差 | E1: GP1 | F1: GP2 | G1: GP3 | H1: 登录人数 | I1: 投注人数 | J1: 注册人数 | K1: 首充人数 | L1: 续存人数 | M1: 存款人数 | N1: 存款次数
A2: 1月 | B2: 2.7291086e+08 | C2: 236484767 | D2: 36426090 | E2: 41032556 | F2: 35740695 | G2: 25206321 | H2: 1086977 | I2: 726629 | J2: 43787 | K2: 12835 | L2: 28958 | M2: 179147 | N2: 383067
A3: 2月 | B3: 2.2760305e+08 | C3: 199641810 | D3: 27961236 | E3: 36628676 | F3: 29814588 | G3: 20795632 | H3: 819553 | I3: 576036 | J3: 25813 | K3: 8691 | L3: 21438 | M3: 133324 | N3: 291800
A4: 3月 | B4: =全平台汇总!$B$35 -> 1.1696893e+08 | C4: =全平台汇总!$D$35 -> 102208925 | D4: =全平台汇总!$E$35 -> 14760009 | E4: =全平台汇总!$F$35 -> 17754606 | F4: =全平台汇总!$G$35 -> 15315766 | G4: =全平台汇总!$H$35 -> 10780051 | H4: =全平台汇总!$I$35 -> 413831 | I4: =全平台汇总!$J$35 -> 290144 | J4: =全平台汇总!$K$35 -> 14713 | K4: =全平台汇总!$L$35 -> 4871 | L4: =全平台汇总!$M$35 -> 10272 | M4: =全平台汇总!$N$35 -> 61637 | N4: =全平台汇总!$O$35 -> 137802
A5: 5月
A6: 5月
A7: 6月
A8: 7月
A9: 8月
A10: 9月
A11: 10月
A12: 11月
A13: 12月
A14: 月均 | B14: =AVERAGE(B2:B13) -> 2.0582761e+08 | C14: =AVERAGE(C2:C13) -> 1.7944517e+08 | D14: =AVERAGE(D2:D13) -> 26382445 | E14: =AVERAGE(E2:E13) -> 31805280 | F14: =AVERAGE(F2:F13) -> 26957016 | G14: =AVERAGE(G2:G13) -> 18927335 | H14: =AVERAGE(H2:H13) -> 773453.67 | I14: =AVERAGE(I2:I13) -> 530936.33 | ... N14: =AVERAGE(N2:N13) -> 270889.67
A15: 求和 | B15: =SUM(B2:B13) -> 6.1748284e+08 | C15: =SUM(C2:C13) -> 538335502 | D15: =SUM(D2:D13) -> 79147334 | E15: =SUM(E2:E13) -> 95415839 | F15: =SUM(F2:F13) -> 80871048 | G15: =SUM(G2:G13) -> 56782005 | H15: =SUM(H2:H13) -> 2320361 | I15: =SUM(I2:I13) -> 1592809 | ... N15: =SUM(N2:N13) -> 812669

Sheet 天成系统
A1: =全平台汇总!A1 -> 46093 | F1: Winplus / Go Jackpot / SBET / Sugarplay 平台关键数据报表 | P1: 平台详细数据填制区
A2: 日期 | B2: 充值 | C2: 首存金额 | D2: 提款 | E2: 充提差 | F2: GP1 | G2: GP2 | H2: GP3 | I2: 登录人数 | J2: 投注人数 | K2: 注册人数 | L2: 首充人数 | M2: 续存人数 | N2: 存款人数 | O2: 存款次数 | P2: 投注 | Q2: 有效投注 | R2: 派彩 | S2: 综合优惠比 | T2: 活动红利 | U2: 返点 | V2: 邀请返佣 | W2: GP1 | X2: GP1杀率 | Y2: 游戏杀率 | Z2: 平台余额 | AA2: 周结&月结佣金 | AB2: 周结代理佣金 | AC2: 月结代理佣金 | AD2: GP2 | AE2: GP2杀率 | AF2: 存提手续费 | AG2: 存款手续费 | AH2: 提款手续费 | AI2: 平台费 | AJ2: 包网费(U） | AK2: 汇率 | AL2: 换算P | AM2: GP3 | AN2: GP3杀率 | AO2: 开分 | AP2: 洗分 | AQ2: 核对 | AR2: 差额
A3: =全平台汇总!A3 -> 46082 | B3: =WP!L9+GJP!L9+SBET!L9+Sugarplay!L9 -> 10012561 | C3: =WP!K9+GJP!K9+SBET!K9+Sugarplay!K9 -> 101494 | D3: =WP!M9+GJP!M9+SBET!M9+Sugarplay!N9 -> 9438631 | E3: =B3-D3 -> 573929.6 | F3: =W3 -> 1023619.1 | G3: =AD3 -> 1023619.1 | H3: =AM3 -> 677871.75 | I3: =WP!D9+GJP!D9+SBET!D9+Sugarplay!D9 -> 37276 | J3: =WP!J9+GJP!J9+SBET!J9+Sugarplay!J9 -> 23624 | K3: =WP!B9+GJP!B9+SBET!B9+Sugarplay!B9 -> 1333 | L3: =WP!C9+GJP!C9+SBET!C9+Sugarplay!C9 -> 410 | M3: =WP!E9+GJP!E9+SBET!E9+Sugarplay!E9 -> 992 | N3: =WP!F9+GJP!F9+SBET!F9+Sugarplay!F9 -> 5857 | O3: =WP!G9+GJP!G9+SBET!G9+Sugarplay!G9 -> 12355 | P3: =WP!O9+GJP!O9+SBET!O9+Sugarplay!P9 -> 67076153 | Q3: =WP!P9+GJP!P9+SBET!P9+Sugarplay!Q9 -> 62681990 | R3: =WP!R9+GJP!R9+SBET!R9+Sugarplay!S9 -> 65320984 | S3: =T3/Q3 -> 0.011670818 | T3: =WP!S9+GJP!S9+SBET!S9+Sugarplay!T9 -> 731550.07 | U3: =WP!T9+GJP!T9+SBET!T9+Sugarplay!U9 -> 284236.48 | V3: =WP!U9+GJP!U9+SBET!U9+Sugarplay!V9 -> 29250.28 | W3: =P3-R3-T3 -> 1023619.1 | X3: =W3/P3 -> 0.015260552 | Y3: =(P3-R3)/P3 -> 0.026166814 | Z3: =WP!AE9+GJP!AE9+SBET!AF9+Sugarplay!AG9 -> 1965001.1 | AA3: =AB3+AC3 -> 0 | AB3: =WP!AA9+GJP!AA9+SBET!AB9+Sugarplay!AC9 -> 0 | AC3: =WP!AB9+GJP!AB9+SBET!AC9+Sugarplay!AD9 -> 0 | AD3: =W3-AB3-AC3 -> 1023619.1 | AE3: =AD3/P3 -> 0.015260552 | AF3: =AG3+AH3 -> 253621.64 | AG3: =WP!W9+GJP!W9+SBET!W9+Sugarplay!X9 -> 234744.3 | AH3: =WP!X9+GJP!X9+SBET!X9+Sugarplay!Y9 -> 18877.34 | AI3: =W3*0.09 -> 92125.72 | AJ3: 0 | AK3: 0 | AL3: 0 | AM3: =W3-AB3-AC3-AG3-AH3-AI3 -> 677871.75 | AN3: =AM3/P3 -> 0.010106002 | AO3: =WP!AC9+GJP!AC9+SBET!AD9+Sugarplay!AE9 -> 100 | AP3: =WP!AD9+GJP!AD9+SBET!AE9+Sugarplay!AF9 -> -2554.33 | AQ3: =AD3-AG3-AH3-AI3 -> 677871.75 | AR3: =AM3-AQ3 -> 0
A4: =全平台汇总!A4 -> 46083 | B4: =WP!L10+GJP!L10+SBET!L10+Sugarplay!L10 -> 8816812.6 | C4: =WP!K10+GJP!K10+SBET!K10+Sugarplay!K10 -> 88437 | D4: =WP!M10+GJP!M10+SBET!M10+Sugarplay!N10 -> 8989445 | E4: =B4-D4 -> -172632.43 | F4: =W4 -> 817069.84 | G4: =AD4 -> -209948.92 | H4: =AM4 -> -508126 | I4: =WP!D10+GJP!D10+SBET!D10+Sugarplay!D10 -> 30062 | J4: =WP!J10+GJP!J10+SBET!J10+Sugarplay!J10 -> 19932 | K4: =WP!B10+GJP!B10+SBET!B10+Sugarplay!B10 -> 1326 | L4: =WP!C10+GJP!C10+SBET!C10+Sugarplay!C10 -> 384 | M4: =WP!E10+GJP!E10+SBET!E10+Sugarplay!E10 -> 903 | N4: =WP!F10+GJP!F10+SBET!F10+Sugarplay!F10 -> 4985 | O4: =WP!G10+GJP!G10+SBET!G10+Sugarplay!G10 -> 10948 | P4: =WP!O10+GJP!O10+SBET!O10+Sugarplay!P10 -> 57155008 | Q4: =WP!P10+GJP!P10+SBET!P10+Sugarplay!Q10 -> 53233162 | R4: =WP!R10+GJP!R10+SBET!R10+Sugarplay!S10 -> 55716597 | S4: =T4/Q4 -> 0.011672072 | T4: =WP!S10+GJP!S10+SBET!S10+Sugarplay!T10 -> 621341.32 | U4: =WP!T10+GJP!T10+SBET!T10+Sugarplay!U10 -> 249517.97 | V4: =WP!U10+GJP!U10+SBET!U10+Sugarplay!V10 -> 40804.38 | W4: =P4-R4-T4 -> 817069.84 | X4: =W4/P4 -> 0.014295682 | Y4: =(P4-R4)/P4 -> 0.025166844 | Z4: =WP!AE10+GJP!AE10+SBET!AF10+Sugarplay!AG10 -> 1882353.4 | AA4: =AB4+AC4 -> 1027018.8 | AB4: =WP!AA10+GJP!AA10+SBET!AB10+Sugarplay!AC10 -> 1027018.8 | AC4: =WP!AB10+GJP!AB10+SBET!AC10+Sugarplay!AD10 -> 0 | AD4: =W4-AB4-AC4 -> -209948.92 | AE4: =AD4/P4 -> -0.003673325 | AF4: =AG4+AH4 -> 224640.79 | AG4: =WP!W10+GJP!W10+SBET!W10+Sugarplay!X10 -> 206662.07 | AH4: =WP!X10+GJP!X10+SBET!X10+Sugarplay!Y10 -> 17978.72 | AI4: =W4*0.09 -> 73536.286 | AM4: =W4-AB4-AC4-AG4-AH4-AI4 -> -508126 | AN4: =AM4/P4 -> -0.0088903145 | AO4: =WP!AC10+GJP!AC10+SBET!AD10+Sugarplay!AE10 -> 24934.69 | AP4: =WP!AD10+GJP!AD10+SBET!AE10+Sugarplay!AF10 -> -5158.46 | AQ4: =AD4-AG4-AH4-AI4 -> -508126 | AR4: =AM4-AQ4 -> 0
A5: =全平台汇总!A5 -> 46084 | B5: =WP!L11+GJP!L11+SBET!L11+Sugarplay!L11 -> 9493443 | C5: =WP!K11+GJP!K11+SBET!K11+Sugarplay!K11 -> 81720 | D5: =WP!M11+GJP!M11+SBET!M11+Sugarplay!N11 -> 7971259 | E5: =B5-D5 -> 1522184 | F5: =W5 -> 1120695 | G5: =AD5 -> 1116040 | H5: =AM5 -> 777674.26 | I5: =WP!D11+GJP!D11+SBET!D11+Sugarplay!D11 -> 32603 | J5: =WP!J11+GJP!J11+SBET!J11+Sugarplay!J11 -> 20872 | K5: =WP!B11+GJP!B11+SBET!B11+Sugarplay!B11 -> 1273 | L5: =WP!C11+GJP!C11+SBET!C11+Sugarplay!C11 -> 385 | M5: =WP!E11+GJP!E11+SBET!E11+Sugarplay!E11 -> 840 | N5: =WP!F11+GJP!F11+SBET!F11+Sugarplay!F11 -> 4859 | O5: =WP!G11+GJP!G11+SBET!G11+Sugarplay!G11 -> 10981 | P5: =WP!O11+GJP!O11+SBET!O11+Sugarplay!P11 -> 68808339 | Q5: =WP!P11+GJP!P11+SBET!P11+Sugarplay!Q11 -> 64088379 | R5: =WP!R11+GJP!R11+SBET!R11+Sugarplay!S11 -> 67156074 | S5: =T5/Q5 -> 0.00829434 | T5: =WP!S11+GJP!S11+SBET!S11+Sugarplay!T11 -> 531570.81 | U5: =WP!T11+GJP!T11+SBET!T11+Sugarplay!U11 -> 220355.21 | V5: =WP!U11+GJP!U11+SBET!U11+Sugarplay!V11 -> 31186.92 | W5: =P5-R5-T5 -> 1120695 | X5: =W5/P5 -> 0.016287197 | Y5: =(P5-R5)/P5 -> 0.024012581 | Z5: =WP!AE11+GJP!AE11+SBET!AF11+Sugarplay!AG11 -> 1834307.9 | AA5: =AB5+AC5 -> 4655 | AB5: =WP!AA11+GJP!AA11+SBET!AB11+Sugarplay!AC11 -> 4655 | AC5: =WP!AB11+GJP!AB11+SBET!AC11+Sugarplay!AD11 -> 0 | AD5: =W5-AB5-AC5 -> 1116040 | AE5: =AD5/P5 -> 0.016219545 | AF5: =AG5+AH5 -> 237503.17 | AG5: =WP!W11+GJP!W11+SBET!W11+Sugarplay!X11 -> 221560.78 | AH5: =WP!X11+GJP!X11+SBET!X11+Sugarplay!Y11 -> 15942.39 | AI5: =W5*0.09 -> 100862.55 | AM5: =W5-AB5-AC5-AG5-AH5-AI5 -> 777674.26 | AN5: =AM5/P5 -> 0.011302035 | AO5: =WP!AC11+GJP!AC11+SBET!AD11+Sugarplay!AE11 -> 14094.8 | AP5: =WP!AD11+GJP!AD11+SBET!AE11+Sugarplay!AF11 -> -56452.86 | AQ5: =AD5-AG5-AH5-AI5 -> 777674.26 | AR5: =AM5-AQ5 -> 0
A6: =全平台汇总!A6 -> 46085 | B6: =WP!L12+GJP!L12+SBET!L12+Sugarplay!L12 -> 11799989 | C6: =WP!K12+GJP!K12+SBET!K12+Sugarplay!K12 -> 108144 | D6: =WP!M12+GJP!M12+SBET!M12+Sugarplay!N12 -> 9658460 | E6: =B6-D6 -> 2141529.1 | F6: =W6 -> 1836446 | G6: =AD6 -> 1836288 | H6: =AM6 -> 1375940.2 | I6: =WP!D12+GJP!D12+SBET!D12+Sugarplay!D12 -> 36056 | J6: =WP!J12+GJP!J12+SBET!J12+Sugarplay!J12 -> 22720 | K6: =WP!B12+GJP!B12+SBET!B12+Sugarplay!B12 -> 1133 | L6: =WP!C12+GJP!C12+SBET!C12+Sugarplay!C12 -> 456 | M6: =WP!E12+GJP!E12+SBET!E12+Sugarplay!E12 -> 857 | N6: =WP!F12+GJP!F12+SBET!F12+Sugarplay!F12 -> 5303 | O6: =WP!G12+GJP!G12+SBET!G12+Sugarplay!G12 -> 11724 | P6: =WP!O12+GJP!O12+SBET!O12+Sugarplay!P12 -> 81349421 | Q6: =WP!P12+GJP!P12+SBET!P12+Sugarplay!Q12 -> 75596780 | R6: =WP!R12+GJP!R12+SBET!R12+Sugarplay!S12 -> 78804731 | S6: =T6/Q6 -> 0.0093686982 | T6: =WP!S12+GJP!S12+SBET!S12+Sugarplay!T12 -> 708243.42 | U6: =WP!T12+GJP!T12+SBET!T12+Sugarplay!U12 -> 318389.11 | V6: =WP!U12+GJP!U12+SBET!U12+Sugarplay!V12 -> 39667.62 | W6: =P6-R6-T6 -> 1836446 | X6: =W6/P6 -> 0.022574789 | Y6: =(P6-R6)/P6 -> 0.031280978 | Z6: =WP!AE12+GJP!AE12+SBET!AF12+Sugarplay!AG12 -> 2275472.5 | AA6: =AB6+AC6 -> 158 | AB6: =WP!AA12+GJP!AA12+SBET!AB12+Sugarplay!AC12 -> 158 | AC6: =WP!AB12+GJP!AB12+SBET!AC12+Sugarplay!AD12 -> 0 | AD6: =W6-AB6-AC6 -> 1836288 | AE6: =AD6/P6 -> 0.022572847 | AF6: =AG6+AH6 -> 295067.71 | AG6: =WP!W12+GJP!W12+SBET!W12+Sugarplay!X12 -> 275750.39 | AH6: =WP!X12+GJP!X12+SBET!X12+Sugarplay!Y12 -> 19317.32 | AI6: =W6*0.09 -> 165280.14 | AM6: =W6-AB6-AC6-AG6-AH6-AI6 -> 1375940.2 | AN6: =AM6/P6 -> 0.016913952 | AO6: =WP!AC12+GJP!AC12+SBET!AD12+Sugarplay!AE12 -> 0 | AP6: =WP!AD12+GJP!AD12+SBET!AE12+Sugarplay!AF12 -> -693.1 | AQ6: =AD6-AG6-AH6-AI6 -> 1375940.2 | AR6: =AM6-AQ6 -> 0
A7: =全平台汇总!A7 -> 46086 | B7: =WP!L13+GJP!L13+SBET!L13+Sugarplay!L13 -> 11070696 | C7: =WP!K13+GJP!K13+SBET!K13+Sugarplay!K13 -> 104683 | D7: =WP!M13+GJP!M13+SBET!M13+Sugarplay!N13 -> 9393354 | E7: =B7-D7 -> 1677341.8 | F7: =W7 -> 1716183.1 | G7: =AD7 -> 1715683.1 | H7: =AM7 -> 1283730.2 | I7: =WP!D13+GJP!D13+SBET!D13+Sugarplay!D13 -> 30390 | J7: =WP!J13+GJP!J13+SBET!J13+Sugarplay!J13 -> 20570 | K7: =WP!B13+GJP!B13+SBET!B13+Sugarplay!B13 -> 1126 | L7: =WP!C13+GJP!C13+SBET!C13+Sugarplay!C13 -> 373 | M7: =WP!E13+GJP!E13+SBET!E13+Sugarplay!E13 -> 843 | N7: =WP!F13+GJP!F13+SBET!F13+Sugarplay!F13 -> 4861 | O7: =WP!G13+GJP!G13+SBET!G13+Sugarplay!G13 -> 11389 | P7: =WP!O13+GJP!O13+SBET!O13+Sugarplay!P13 -> 74995038 | Q7: =WP!P13+GJP!P13+SBET!P13+Sugarplay!Q13 -> 70418491 | R7: =WP!R13+GJP!R13+SBET!R13+Sugarplay!S13 -> 72621807 | S7: =T7/Q7 -> 0.0093306258 | T7: =WP!S13+GJP!S13+SBET!S13+Sugarplay!T13 -> 657048.59 | U7: =WP!T13+GJP!T13+SBET!T13+Sugarplay!U13 -> 279745.75 | V7: =WP!U13+GJP!U13+SBET!U13+Sugarplay!V13 -> 36585.53 | W7: =P7-R7-T7 -> 1716183.1 | X7: =W7/P7 -> 0.022883956 | Y7: =(P7-R7)/P7 -> 0.031645183 | Z7: =WP!AE13+GJP!AE13+SBET!AF13+Sugarplay!AG13 -> 2290627.3 | AA7: =AB7+AC7 -> 500 | AB7: =WP!AA13+GJP!AA13+SBET!AB13+Sugarplay!AC13 -> 500 | AC7: =WP!AB13+GJP!AB13+SBET!AC13+Sugarplay!AD13 -> 0 | AD7: =W7-AB7-AC7 -> 1715683.1 | AE7: =AD7/P7 -> 0.022877288 | AF7: =AG7+AH7 -> 277496.43 | AG7: =WP!W13+GJP!W13+SBET!W13+Sugarplay!X13 -> 258709.75 | AH7: =WP!X13+GJP!X13+SBET!X13+Sugarplay!Y13 -> 18786.68 | AI7: =W7*0.09 -> 154456.48 | AM7: =W7-AB7-AC7-AG7-AH7-AI7 -> 1283730.2 | AN7: =AM7/P7 -> 0.017117535 | AO7: =WP!AC13+GJP!AC13+SBET!AD13+Sugarplay!AE13 -> 0 | AP7: =WP!AD13+GJP!AD13+SBET!AE13+Sugarplay!AF13 -> -15883.11 | AQ7: =AD7-AG7-AH7-AI7 -> 1283730.2 | AR7: =AM7-AQ7 -> 0
A8: =全平台汇总!A8 -> 46087 | B8: =WP!L14+GJP!L14+SBET!L14+Sugarplay!L14 -> 11336766 | C8: =WP!K14+GJP!K14+SBET!K14+Sugarplay!K14 -> 102748 | D8: =WP!M14+GJP!M14+SBET!M14+Sugarplay!N14 -> 9913747 | E8: =B8-D8 -> 1423019 | F8: =W8 -> 2163495.7 | G8: =AD8 -> 2162895.7 | H8: =AM8 -> 1684159.8 | I8: =WP!D14+GJP!D14+SBET!D14+Sugarplay!D14 -> 34834 | J8: =WP!J14+GJP!J14+SBET!J14+Sugarplay!J14 -> 25291 | K8: =WP!B14+GJP!B14+SBET!B14+Sugarplay!B14 -> 1211 | L8: =WP!C14+GJP!C14+SBET!C14+Sugarplay!C14 -> 418 | M8: =WP!E14+GJP!E14+SBET!E14+Sugarplay!E14 -> 855 | N8: =WP!F14+GJP!F14+SBET!F14+Sugarplay!F14 -> 5432 | O8: =WP!G14+GJP!G14+SBET!G14+Sugarplay!G14 -> 12047 | P8: =WP!O14+GJP!O14+SBET!O14+Sugarplay!P14 -> 76693220 | Q8: =WP!P14+GJP!P14+SBET!P14+Sugarplay!Q14 -> 71420335 | R8: =WP!R14+GJP!R14+SBET!R14+Sugarplay!S14 -> 73651319 | S8: =T8/Q8 -> 0.012299094 | T8: =WP!S14+GJP!S14+SBET!S14+Sugarplay!T14 -> 878405.45 | U8: =WP!T14+GJP!T14+SBET!T14+Sugarplay!U14 -> 355546.15 | V8: =WP!U14+GJP!U14+SBET!U14+Sugarplay!V14 -> 27739.37 | W8: =P8-R8-T8 -> 2163495.7 | X8: =W8/P8 -> 0.028209739 | Y8: =(P8-R8)/P8 -> 0.039663234 | Z8: =WP!AE14+GJP!AE14+SBET!AF14+Sugarplay!AG14 -> 1772925.9 | AA8: =AB8+AC8 -> 600 | AB8: =WP!AA14+GJP!AA14+SBET!AB14+Sugarplay!AC14 -> 600 | AC8: =WP!AB14+GJP!AB14+SBET!AC14+Sugarplay!AD14 -> 0 | AD8: =W8-AB8-AC8 -> 2162895.7 | AE8: =AD8/P8 -> 0.028201915 | AF8: =AG8+AH8 -> 284021.27 | AG8: =WP!W14+GJP!W14+SBET!W14+Sugarplay!X14 -> 264193.49 | AH8: =WP!X14+GJP!X14+SBET!X14+Sugarplay!Y14 -> 19827.78 | AI8: =W8*0.09 -> 194714.61 | AM8: =W8-AB8-AC8-AG8-AH8-AI8 -> 1684159.8 | AN8: =AM8/P8 -> 0.021959696 | AO8: =WP!AC14+GJP!AC14+SBET!AD14+Sugarplay!AE14 -> 0 | AP8: =WP!AD14+GJP!AD14+SBET!AE14+Sugarplay!AF14 -> -22828.95 | AQ8: =AD8-AG8-AH8-AI8 -> 1684159.8 | AR8: =AM8-AQ8 -> 0
A9: =全平台汇总!A9 -> 46088 | B9: =WP!L15+GJP!L15+SBET!L15+Sugarplay!L15 -> 9146001.2 | C9: =WP!K15+GJP!K15+SBET!K15+Sugarplay!K15 -> 80548 | D9: =WP!M15+GJP!M15+SBET!M15+Sugarplay!N15 -> 7388477 | E9: =B9-D9 -> 1757524.2 | F9: =W9 -> 2096383 | G9: =AD9 -> 2092285 | H9: =AM9 -> 1674812.2 | I9: =WP!D15+GJP!D15+SBET!D15+Sugarplay!D15 -> 31535 | J9: =WP!J15+GJP!J15+SBET!J15+Sugarplay!J15 -> 22766 | K9: =WP!B15+GJP!B15+SBET!B15+Sugarplay!B15 -> 1187 | L9: =WP!C15+GJP!C15+SBET!C15+Sugarplay!C15 -> 429 | M9: =WP!E15+GJP!E15+SBET!E15+Sugarplay!E15 -> 890 | N9: =WP!F15+GJP!F15+SBET!F15+Sugarplay!F15 -> 5370 | O9: =WP!G15+GJP!G15+SBET!G15+Sugarplay!G15 -> 12128 | P9: =WP!O15+GJP!O15+SBET!O15+Sugarplay!P15 -> 61440169 | Q9: =WP!P15+GJP!P15+SBET!P15+Sugarplay!Q15 -> 57446216 | R9: =WP!R15+GJP!R15+SBET!R15+Sugarplay!S15 -> 58710718 | S9: =T9/Q9 -> 0.011020182 | T9: =WP!S15+GJP!S15+SBET!S15+Sugarplay!T15 -> 633067.76 | U9: =WP!T15+GJP!T15+SBET!T15+Sugarplay!U15 -> 238979.64 | V9: =WP!U15+GJP!U15+SBET!U15+Sugarplay!V15 -> 44748.36 | W9: =P9-R9-T9 -> 2096383 | X9: =W9/P9 -> 0.034120723 | Y9: =(P9-R9)/P9 -> 0.044424531 | Z9: =WP!AE15+GJP!AE15+SBET!AF15+Sugarplay!AG15 -> 1822697.1 | AA9: =AB9+AC9 -> 4098 | AB9: =WP!AA15+GJP!AA15+SBET!AB15+Sugarplay!AC15 -> 4098 | AC9: =WP!AB15+GJP!AB15+SBET!AC15+Sugarplay!AD15 -> 0 | AD9: =W9-AB9-AC9 -> 2092285 | AE9: =AD9/P9 -> 0.034054023 | AF9: =AG9+AH9 -> 228798.32 | AG9: =WP!W15+GJP!W15+SBET!W15+Sugarplay!X15 -> 214021.57 | AH9: =WP!X15+GJP!X15+SBET!X15+Sugarplay!Y15 -> 14776.75 | AI9: =W9*0.09 -> 188674.47 | AM9: =W9-AB9-AC9-AG9-AH9-AI9 -> 1674812.2 | AN9: =AM9/P9 -> 0.027259238 | AO9: =WP!AC15+GJP!AC15+SBET!AD15+Sugarplay!AE15 -> 0 | AP9: =WP!AD15+GJP!AD15+SBET!AE15+Sugarplay!AF15 -> -6039.02 | AQ9: =AD9-AG9-AH9-AI9 -> 1674812.2 | AR9: =AM9-AQ9 -> 0
A10: =全平台汇总!A10 -> 46089 | B10: =WP!L16+GJP!L16+SBET!L16+Sugarplay!L16 -> 8743030.4 | C10: =WP!K16+GJP!K16+SBET!K16+Sugarplay!K16 -> 89151 | D10: =WP!M16+GJP!M16+SBET!M16+Sugarplay!N16 -> 7021701 | E10: =B10-D10 -> 1721329.4 | F10: =W10 -> 1430284.9 | G10: =AD10 -> 1430284.9 | H10: =AM10 -> 1083093 | I10: =WP!D16+GJP!D16+SBET!D16+Sugarplay!D16 -> 44452 | J10: =WP!J16+GJP!J16+SBET!J16+Sugarplay!J16 -> 35587 | K10: =WP!B16+GJP!B16+SBET!B16+Sugarplay!B16 -> 1495 | L10: =WP!C16+GJP!C16+SBET!C16+Sugarplay!C16 -> 475 | M10: =WP!E16+GJP!E16+SBET!E16+Sugarplay!E16 -> 861 | N10: =WP!F16+GJP!F16+SBET!F16+Sugarplay!F16 -> 5524 | O10: =WP!G16+GJP!G16+SBET!G16+Sugarplay!G16 -> 11873 | P10: =WP!O16+GJP!O16+SBET!O16+Sugarplay!P16 -> 59518719 | Q10: =WP!P16+GJP!P16+SBET!P16+Sugarplay!Q16 -> 55414312 | R10: =WP!R16+GJP!R16+SBET!R16+Sugarplay!S16 -> 57454100 | S10: =T10/Q10 -> 0.011447123 | T10: =WP!S16+GJP!S16+SBET!S16+Sugarplay!T16 -> 634334.47 | U10: =WP!T16+GJP!T16+SBET!T16+Sugarplay!U16 -> 219316.17 | V10: =WP!U16+GJP!U16+SBET!U16+Sugarplay!V16 -> 35016.34 | W10: =P10-R10-T10 -> 1430284.9 | X10: =W10/P10 -> 0.024030841 | Y10: =(P10-R10)/P10 -> 0.034688571 | Z10: =WP!AE16+GJP!AE16+SBET!AF16+Sugarplay!AG16 -> 1959603.2 | AA10: =AB10+AC10 -> 0 | AB10: =WP!AA16+GJP!AA16+SBET!AB16+Sugarplay!AC16 -> 0 | AC10: =WP!AB16+GJP!AB16+SBET!AC16+Sugarplay!AD16 -> 0 | AD10: =W10-AB10-AC10 -> 1430284.9 | AE10: =AD10/P10 -> 0.024030841 | AF10: =AG10+AH10 -> 218466.26 | AG10: =WP!W16+GJP!W16+SBET!W16+Sugarplay!X16 -> 204422.46 | AH10: =WP!X16+GJP!X16+SBET!X16+Sugarplay!Y16 -> 14043.8 | AI10: =W10*0.09 -> 128725.64 | AM10: =W10-AB10-AC10-AG10-AH10-AI10 -> 1083093 | AN10: =AM10/P10 -> 0.018197518 | AO10: =WP!AC16+GJP!AC16+SBET!AD16+Sugarplay!AE16 -> 0 | AP10: =WP!AD16+GJP!AD16+SBET!AE16+Sugarplay!AF16 -> -32070.54 | AQ10: =AD10-AG10-AH10-AI10 -> 1083093 | AR10: =AM10-AQ10 -> 0
A11: =全平台汇总!A11 -> 46090 | B11: =WP!L17+GJP!L17+SBET!L17+Sugarplay!L17 -> 8998021.2 | C11: =WP!K17+GJP!K17+SBET!K17+Sugarplay!K17 -> 84741 | D11: =WP!M17+GJP!M17+SBET!M17+Sugarplay!N17 -> 9075963 | E11: =B11-D11 -> -77941.79 | F11: =W11 -> 1168422.1 | G11: =AD11 -> -189137.81 | H11: =AM11 -> -522932.01 | I11: =WP!D17+GJP!D17+SBET!D17+Sugarplay!D17 -> 35036 | J11: =WP!J17+GJP!J17+SBET!J17+Sugarplay!J17 -> 26675 | K11: =WP!B17+GJP!B17+SBET!B17+Sugarplay!B17 -> 1324 | L11: =WP!C17+GJP!C17+SBET!C17+Sugarplay!C17 -> 465 | M11: =WP!E17+GJP!E17+SBET!E17+Sugarplay!E17 -> 812 | N11: =WP!F17+GJP!F17+SBET!F17+Sugarplay!F17 -> 4866 | O11: =WP!G17+GJP!G17+SBET!G17+Sugarplay!G17 -> 11121 | P11: =WP!O17+GJP!O17+SBET!O17+Sugarplay!P17 -> 62418180 | Q11: =WP!P17+GJP!P17+SBET!P17+Sugarplay!Q17 -> 57490214 | R11: =WP!R17+GJP!R17+SBET!R17+Sugarplay!S17 -> 60604634 | S11: =T11/Q11 -> 0.011221456 | T11: =WP!S17+GJP!S17+SBET!S17+Sugarplay!T17 -> 645123.92 | U11: =WP!T17+GJP!T17+SBET!T17+Sugarplay!U17 -> 251060.31 | V11: =WP!U17+GJP!U17+SBET!U17+Sugarplay!V17 -> 32777.63 | W11: =P11-R11-T11 -> 1168422.1 | X11: =W11/P11 -> 0.01871926 | Y11: =(P11-R11)/P11 -> 0.029054773 | Z11: =WP!AE17+GJP!AE17+SBET!AF17+Sugarplay!AG17 -> 2770004.3 | AA11: =AB11+AC11 -> 1357560 | AB11: =WP!AA17+GJP!AA17+SBET!AB17+Sugarplay!AC17 -> 1357560 | AC11: =WP!AB17+GJP!AB17+SBET!AC17+Sugarplay!AD17 -> 0 | AD11: =W11-AB11-AC11 -> -189137.81 | AE11: =AD11/P11 -> -0.0030301718 | AF11: =AG11+AH11 -> 228636.21 | AG11: =WP!W17+GJP!W17+SBET!W17+Sugarplay!X17 -> 210483.81 | AH11: =WP!X17+GJP!X17+SBET!X17+Sugarplay!Y17 -> 18152.4 | AI11: =W11*0.09 -> 105157.99 | AM11: =W11-AB11-AC11-AG11-AH11-AI11 -> -522932.01 | AN11: =AM11/P11 -> -0.0083778798 | AO11: =WP!AC17+GJP!AC17+SBET!AD17+Sugarplay!AE17 -> 123737.11 | AP11: =WP!AD17+GJP!AD17+SBET!AE17+Sugarplay!AF17 -> -147358.45 | AQ11: =AD11-AG11-AH11-AI11 -> -522932.01 | AR11: =AM11-AQ11 -> 0
A12: =全平台汇总!A12 -> 46091 | B12: =WP!L18+GJP!L18+SBET!L18+Sugarplay!L18 -> 8656049.1 | C12: =WP!K18+GJP!K18+SBET!K18+Sugarplay!K18 -> 65052 | D12: =WP!M18+GJP!M18+SBET!M18+Sugarplay!N18 -> 7894537 | E12: =B12-D12 -> 761512.14 | F12: =W12 -> 1049437.1 | G12: =AD12 -> 1005714.1 | H12: =AM12 -> 693346.95 | I12: =WP!D18+GJP!D18+SBET!D18+Sugarplay!D18 -> 33657 | J12: =WP!J18+GJP!J18+SBET!J18+Sugarplay!J18 -> 24070 | K12: =WP!B18+GJP!B18+SBET!B18+Sugarplay!B18 -> 1282 | L12: =WP!C18+GJP!C18+SBET!C18+Sugarplay!C18 -> 394 | M12: =WP!E18+GJP!E18+SBET!E18+Sugarplay!E18 -> 850 | N12: =WP!F18+GJP!F18+SBET!F18+Sugarplay!F18 -> 4877 | O12: =WP!G18+GJP!G18+SBET!G18+Sugarplay!G18 -> 10991 | P12: =WP!O18+GJP!O18+SBET!O18+Sugarplay!P18 -> 60320102 | Q12: =WP!P18+GJP!P18+SBET!P18+Sugarplay!Q18 -> 56307616 | R12: =WP!R18+GJP!R18+SBET!R18+Sugarplay!S18 -> 58750252 | S12: =T12/Q12 -> 0.0092423188 | T12: =WP!S18+GJP!S18+SBET!S18+Sugarplay!T18 -> 520412.94 | U12: =WP!T18+GJP!T18+SBET!T18+Sugarplay!U18 -> 217343.52 | V12: =WP!U18+GJP!U18+SBET!U18+Sugarplay!V18 -> 29775.73 | W12: =P12-R12-T12 -> 1049437.1 | X12: =W12/P12 -> 0.0173978 | Y12: =(P12-R12)/P12 -> 0.02602532 | Z12: =WP!AE18+GJP!AE18+SBET!AF18+Sugarplay!AG18 -> 1998999.8 | AA12: =AB12+AC12 -> 43723 | AB12: =WP!AA18+GJP!AA18+SBET!AB18+Sugarplay!AC18 -> 43723 | AC12: =WP!AB18+GJP!AB18+SBET!AC18+Sugarplay!AD18 -> 0 | AD12: =W12-AB12-AC12 -> 1005714.1 | AE12: =AD12/P12 -> 0.01667295 | AF12: =AG12+AH12 -> 217917.77 | AG12: =WP!W18+GJP!W18+SBET!W18+Sugarplay!X18 -> 202128.61 | AH12: =WP!X18+GJP!X18+SBET!X18+Sugarplay!Y18 -> 15789.16 | AI12: =W12*0.09 -> 94449.335 | AM12: =W12-AB12-AC12-AG12-AH12-AI12 -> 693346.95 | AN12: =AM12/P12 -> 0.011494459 | AO12: =WP!AC18+GJP!AC18+SBET!AD18+Sugarplay!AE18 -> 3100 | AP12: =WP!AD18+GJP!AD18+SBET!AE18+Sugarplay!AF18 -> -11420.41 | AQ12: =AD12-AG12-AH12-AI12 -> 693346.95 | AR12: =AM12-AQ12 -> 0
A13: =全平台汇总!A13 -> 46092 | B13: =WP!L19+GJP!L19+SBET!L19+Sugarplay!L19 -> 9771389.9 | C13: =WP!K19+GJP!K19+SBET!K19+Sugarplay!K19 -> 62776.89 | D13: =WP!M19+GJP!M19+SBET!M19+Sugarplay!N19 -> 7339569 | E13: =B13-D13 -> 2431820.9 | F13: =W13 -> 1578360.4 | G13: =AD13 -> 1578024.4 | H13: =AM13 -> 1193323.2 | I13: =WP!D19+GJP!D19+SBET!D19+Sugarplay!D19 -> 35220 | J13: =WP!J19+GJP!J19+SBET!J19+Sugarplay!J19 -> 25573 | K13: =WP!B19+GJP!B19+SBET!B19+Sugarplay!B19 -> 1043 | L13: =WP!C19+GJP!C19+SBET!C19+Sugarplay!C19 -> 340 | M13: =WP!E19+GJP!E19+SBET!E19+Sugarplay!E19 -> 793 | N13: =WP!F19+GJP!F19+SBET!F19+Sugarplay!F19 -> 4878 | O13: =WP!G19+GJP!G19+SBET!G19+Sugarplay!G19 -> 11239 | P13: =WP!O19+GJP!O19+SBET!O19+Sugarplay!P19 -> 57537374 | Q13: =WP!P19+GJP!P19+SBET!P19+Sugarplay!Q19 -> 53706677 | R13: =WP!R19+GJP!R19+SBET!R19+Sugarplay!S19 -> 55368621 | S13: =T13/Q13 -> 0.010992913 | T13: =WP!S19+GJP!S19+SBET!S19+Sugarplay!T19 -> 590392.81 | U13: =WP!T19+GJP!T19+SBET!T19+Sugarplay!U19 -> 242227.65 | V13: =WP!U19+GJP!U19+SBET!U19+Sugarplay!V19 -> 27742.02 | W13: =P13-R13-T13 -> 1578360.4 | X13: =W13/P13 -> 0.027431916 | Y13: =(P13-R13)/P13 -> 0.037692947 | Z13: =WP!AE19+GJP!AE19+SBET!AF19+Sugarplay!AG19 -> 2716736.4 | AA13: =AB13+AC13 -> 336 | AB13: =WP!AA19+GJP!AA19+SBET!AB19+Sugarplay!AC19 -> 336 | AC13: =WP!AB19+GJP!AB19+SBET!AC19+Sugarplay!AD19 -> 0 | AD13: =W13-AB13-AC13 -> 1578024.4 | AE13: =AD13/P13 -> 0.027426076 | AF13: =AG13+AH13 -> 242648.76 | AG13: =WP!W19+GJP!W19+SBET!W19+Sugarplay!X19 -> 227970.11 | AH13: =WP!X19+GJP!X19+SBET!X19+Sugarplay!Y19 -> 14678.65 | AI13: =W13*0.09 -> 142052.44 | AM13: =W13-AB13-AC13-AG13-AH13-AI13 -> 1193323.2 | AN13: =AM13/P13 -> 0.020739966 | AO13: =WP!AC19+GJP!AC19+SBET!AD19+Sugarplay!AE19 -> 0 | AP13: =WP!AD19+GJP!AD19+SBET!AE19+Sugarplay!AF19 -> -4601.87 | AQ13: =AD13-AG13-AH13-AI13 -> 1193323.2 | AR13: =AM13-AQ13 -> 0
A14: =全平台汇总!A14 -> 46093 | B14: =WP!L20+GJP!L20+SBET!L20+Sugarplay!L20 -> 9124174.9 | C14: =WP!K20+GJP!K20+SBET!K20+Sugarplay!K20 -> 60659 | D14: =WP!M20+GJP!M20+SBET!M20+Sugarplay!N20 -> 8123782 | E14: =B14-D14 -> 1000392.9 | F14: =W14 -> 1754210.2 | G14: =AD14 -> 1754018.2 | H14: =AM14 -> 1367157.9 | I14: =WP!D20+GJP!D20+SBET!D20+Sugarplay!D20 -> 32710 | J14: =WP!J20+GJP!J20+SBET!J20+Sugarplay!J20 -> 22464 | K14: =WP!B20+GJP!B20+SBET!B20+Sugarplay!B20 -> 980 | L14: =WP!C20+GJP!C20+SBET!C20+Sugarplay!C20 -> 342 | M14: =WP!E20+GJP!E20+SBET!E20+Sugarplay!E20 -> 776 | N14: =WP!F20+GJP!F20+SBET!F20+Sugarplay!F20 -> 4825 | O14: =WP!G20+GJP!G20+SBET!G20+Sugarplay!G20 -> 11006 | P14: =WP!O20+GJP!O20+SBET!O20+Sugarplay!P20 -> 59989236 | Q14: =WP!P20+GJP!P20+SBET!P20+Sugarplay!Q20 -> 55758780 | R14: =WP!R20+GJP!R20+SBET!R20+Sugarplay!S20 -> 57642732 | S14: =T14/Q14 -> 0.010622436 | T14: =WP!S20+GJP!S20+SBET!S20+Sugarplay!T20 -> 592294.08 | U14: =WP!T20+GJP!T20+SBET!T20+Sugarplay!U20 -> 243554.97 | V14: =WP!U20+GJP!U20+SBET!U20+Sugarplay!V20 -> 26864.98 | W14: =P14-R14-T14 -> 1754210.2 | X14: =W14/P14 -> 0.029242082 | Y14: =(P14-R14)/P14 -> 0.039115421 | Z14: =WP!AE20+GJP!AE20+SBET!AF20+Sugarplay!AG20 -> 1808352.5 | AA14: =AB14+AC14 -> 192 | AB14: =WP!AA20+GJP!AA20+SBET!AB20+Sugarplay!AC20 -> 192 | AC14: =WP!AB20+GJP!AB20+SBET!AC20+Sugarplay!AD20 -> 0 | AD14: =W14-AB14-AC14 -> 1754018.2 | AE14: =AD14/P14 -> 0.029238881 | AF14: =AG14+AH14 -> 228981.39 | AG14: =WP!W20+GJP!W20+SBET!W20+Sugarplay!X20 -> 212733.99 | AH14: =WP!X20+GJP!X20+SBET!X20+Sugarplay!Y20 -> 16247.4 | AI14: =W14*0.09 -> 157878.91 | AM14: =W14-AB14-AC14-AG14-AH14-AI14 -> 1367157.9 | AN14: =AM14/P14 -> 0.022790053 | AO14: =WP!AC20+GJP!AC20+SBET!AD20+Sugarplay!AE20 -> 2100 | AP14: =WP!AD20+GJP!AD20+SBET!AE20+Sugarplay!AF20 -> -17213.99 | AQ14: =AD14-AG14-AH14-AI14 -> 1367157.9 | AR14: =AM14-AQ14 -> 0
A15: =全平台汇总!A15 -> 46094 | B15: =WP!L21+GJP!L21+SBET!L21+Sugarplay!L21 -> 0 | C15: =WP!K21+GJP!K21+SBET!K21+Sugarplay!K21 -> 0 | D15: =WP!M21+GJP!M21+SBET!M21+Sugarplay!N21 -> 0 | E15: =B15-D15 -> 0 | F15: =W15 -> 0 | G15: =AD15 -> 0 | H15: =AM15 -> 0 | I15: =WP!D21+GJP!D21+SBET!D21+Sugarplay!D21 -> 0 | J15: =WP!J21+GJP!J21+SBET!J21+Sugarplay!J21 -> 0 | K15: =WP!B21+GJP!B21+SBET!B21+Sugarplay!B21 -> 0 | L15: =WP!C21+GJP!C21+SBET!C21+Sugarplay!C21 -> 0 | M15: =WP!E21+GJP!E21+SBET!E21+Sugarplay!E21 -> 0 | N15: =WP!F21+GJP!F21+SBET!F21+Sugarplay!F21 -> 0 | O15: =WP!G21+GJP!G21+SBET!G21+Sugarplay!G21 -> 0 | P15: =WP!O21+GJP!O21+SBET!O21+Sugarplay!P21 -> 0 | Q15: =WP!P21+GJP!P21+SBET!P21+Sugarplay!Q21 -> 0 | R15: =WP!R21+GJP!R21+SBET!R21+Sugarplay!S21 -> 0 | S15: =T15/Q15 -> #DIV/0! | T15: =WP!S21+GJP!S21+SBET!S21+Sugarplay!T21 -> 0 | U15: =WP!T21+GJP!T21+SBET!T21+Sugarplay!U21 -> 0 | V15: =WP!U21+GJP!U21+SBET!U21+Sugarplay!V21 -> 0 | W15: =P15-R15-T15 -> 0 | X15: =W15/P15 -> #DIV/0! | Y15: =(P15-R15)/P15 -> #DIV/0! | Z15: =WP!AE21+GJP!AE21+SBET!AF21+Sugarplay!AG21 -> 0 | AA15: =AB15+AC15 -> 0 | AB15: =WP!AA21+GJP!AA21+SBET!AB21+Sugarplay!AC21 -> 0 | AC15: =WP!AB21+GJP!AB21+SBET!AC21+Sugarplay!AD21 -> 0 | AD15: =W15-AB15-AC15 -> 0 | AE15: =AD15/P15 -> #DIV/0! | AF15: =AG15+AH15 -> 0 | AG15: =WP!W21+GJP!W21+SBET!W21+Sugarplay!X21 -> 0 | AH15: =WP!X21+GJP!X21+SBET!X21+Sugarplay!Y21 -> 0 | AI15: =W15*0.09 -> 0 | AM15: =W15-AB15-AC15-AG15-AH15-AI15 -> 0 | AN15: =AM15/P15 -> #DIV/0! | AO15: =WP!AC21+GJP!AC21+SBET!AD21+Sugarplay!AE21 -> 0 | AP15: =WP!AD21+GJP!AD21+SBET!AE21+Sugarplay!AF21 -> 0 | AQ15: =AD15-AG15-AH15-AI15 -> 0 | AR15: =AM15-AQ15 -> 0
... A33: =全平台汇总!A33 -> 46112 | B33: =WP!L39+GJP!L39+SBET!L39+Sugarplay!L39 -> 0 | C33: =WP!K39+GJP!K39+SBET!K39+Sugarplay!K39 -> 0 | D33: =WP!M39+GJP!M39+SBET!M39+Sugarplay!N39 -> 0 | E33: =B33-D33 -> 0 | F33: =W33 -> 0 | G33: =AD33 -> 0 | H33: =AM33 -> 0 | I33: =WP!D39+GJP!D39+SBET!D39+Sugarplay!D39 -> 0 | J33: =WP!J39+GJP!J39+SBET!J39+Sugarplay!J39 -> 0 | K33: =WP!B39+GJP!B39+SBET!B39+Sugarplay!B39 -> 0 | L33: =WP!C39+GJP!C39+SBET!C39+Sugarplay!C39 -> 0 | M33: =WP!E39+GJP!E39+SBET!E39+Sugarplay!E39 -> 0 | N33: =WP!F39+GJP!F39+SBET!F39+Sugarplay!F39 -> 0 | O33: =WP!G39+GJP!G39+SBET!G39+Sugarplay!G39 -> 0 | P33: =WP!O39+GJP!O39+SBET!O39+Sugarplay!P39 -> 0 | Q33: =WP!P39+GJP!P39+SBET!P39+Sugarplay!Q39 -> 0 | R33: =WP!R39+GJP!R39+SBET!R39+Sugarplay!S39 -> 0 | S33: =T33/Q33 -> #DIV/0! | T33: =WP!S39+GJP!S39+SBET!S39+Sugarplay!T39 -> 0 | U33: =WP!T39+GJP!T39+SBET!T39+Sugarplay!U39 -> 0 | V33: =WP!U39+GJP!U39+SBET!U39+Sugarplay!V39 -> 0 | W33: =P33-R33-T33 -> 0 | X33: =W33/P33 -> #DIV/0! | Y33: =(P33-R33)/P33 -> #DIV/0! | Z33: =WP!AE39+GJP!AE39+SBET!AF39+Sugarplay!AG39 -> 0 | AA33: =AB33+AC33 -> 0 | AB33: =WP!AA39+GJP!AA39+SBET!AB39+Sugarplay!AC39 -> 0 | AC33: =WP!AB39+GJP!AB39+SBET!AC39+Sugarplay!AD39 -> 0 | AD33: =W33-AB33-AC33 -> 0 | AE33: =AD33/P33 -> #DIV/0! | AF33: =AG33+AH33 -> 0 | AG33: =WP!W39+GJP!W39+SBET!W39+Sugarplay!X39 -> 0 | AH33: =WP!X39+GJP!X39+SBET!X39+Sugarplay!Y39 -> 0 | AI33: =W33*0.09 -> 0 | AM33: =W33-AB33-AC33-AG33-AH33-AI33 -> 0 | AN33: =AM33/P33 -> #DIV/0! | AO33: =WP!AC39+GJP!AC39+SBET!AD39+Sugarplay!AE39 -> 0 | AP33: =WP!AD39+GJP!AD39+SBET!AE39+Sugarplay!AF39 -> 0 | AQ33: =AD33-AG33-AH33-AI33 -> 0 | AR33: =AM33-AQ33 -> 0
A34: 日均 | B34: =AVERAGE(B3:B14) -> 9747411.2 | C34: =AVERAGE(C3:C14) -> 85846.158 | D34: =AVERAGE(D3:D14) -> 8517410.4 | E34: =AVERAGE(E3:E14) -> 1230000.7 | F34: =AVERAGE(F3:F14) -> 1479550.5 | G34: =AVERAGE(G3:G14) -> 1276313.8 | H34: =AVERAGE(H3:H14) -> 898337.61 | I34: =AVERAGE(I3:I14) -> 34485.917 | ... R34: =AVERAGE(R3:R14) -> 63483547 | S34: =T312/Q312 -> #DIV/0! | T34: =AVERAGE(T3:T14) -> 645315.47 | U34: =AVERAGE(U3:U14) -> 260022.74 | V34: =AVERAGE(V3:V14) -> 33513.263 | W34: =AVERAGE(W3:W14) -> 1479550.5 | X34: =W312/P312 -> #DIV/0! | Y34: =(P312-R312)/P312 -> #DIV/0! | Z34: =AVERAGE(Z3:Z14) -> 2091423.5 | AA34: =AVERAGE(AA3:AA14) -> 203236.73 | AB34: =AVERAGE(AB3:AB14) -> 203236.73 | AC34: =AVERAGE(AC3:AC14) -> 0 | AD34: =AVERAGE(AD3:AD14) -> 1276313.8 | AE34: =AVERAGE(AE3:AE14) -> 0.019154285 | AF34: =AVERAGE(AF3:AF14) -> 244816.64 | AG34: =AVERAGE(AG3:AG14) -> 227781.78 | ... AM34: =AVERAGE(AM3:AM14) -> 898337.61 | AN34: =AM312/P312 -> #DIV/0! | AO34: =AVERAGE(AO3:AO14) -> 14005.55 | AP34: =AVERAGE(AP3:AP14) -> -26856.257 | AQ34: =AVERAGE(AQ3:AQ14) -> 898337.61 | AR34: =AVERAGE(AR3:AR14) -> 0
A35: 汇总 | B35: =SUM(B3:B33) -> 1.1696893e+08 | C35: =SUM(C3:C33) -> 1030153.9 | D35: =SUM(D3:D33) -> 102208925 | E35: =SUM(E3:E33) -> 14760009 | F35: =SUM(F3:F33) -> 17754606 | G35: =SUM(G3:G33) -> 15315766 | H35: =SUM(H3:H33) -> 10780051 | I35: =SUM(I3:I33) -> 413831 | ... R35: =SUM(R3:R33) -> 7.6180257e+08 | S35: =T35/Q35 -> 0.010556402 | T35: =SUM(T3:T33) -> 7743785.6 | U35: =SUM(U3:U33) -> 3120272.9 | V35: =SUM(V3:V33) -> 402159.16 | W35: =SUM(W3:W33) -> 17754606 | X35: =W35/P35 -> 0.022551232 | Y35: =(P35-R35)/P35 -> 0.032387096 | Z35: =SUM(Z3:Z33) -> 25097081 | AA35: =SUM(AA3:AA33) -> 2438840.7 | AB35: =SUM(AB3:AB33) -> 2438840.7 | AC35: =SUM(AC3:AC33) -> 0 | AD35: =SUM(AD3:AD33) -> 15315766 | AE35: =AD35/P35 -> 0.019453508 | AF35: =SUM(AF3:AF33) -> 2937799.7 | AG35: =SUM(AG3:AG33) -> 2733381.3 | AH35: =SUM(AH3:AH33) -> 204418.39 | AI35: =SUM(AI3:AI33) -> 1597914.6 | AJ35: =SUM(AJ3:AJ33) -> 0 | AK35: =SUM(AK3:AK33) -> 0 | AL35: =SUM(AL3:AL33) -> 0 | AM35: =SUM(AM3:AM33) -> 10780051 | AN35: =AM35/P35 -> 0.013692415 | AO35: =SUM(AO3:AO33) -> 168066.6 | AP35: =SUM(AP3:AP33) -> -322275.09 | AQ35: =SUM(AQ3:AQ33) -> 10780051 | AR35: =SUM(AR3:AR33) -> 0
A36: 核对 | B36: =WP!L40+GJP!L40+SBET!L40+Sugarplay!L40 -> 1.1696893e+08 | C36: =WP!K40+GJP!K40+SBET!K40+Sugarplay!K40 -> 1030153.9 | D36: =WP!M40+GJP!M40+SBET!M40+Sugarplay!N40 -> 102208925 | E36: =E35 -> 14760009 | F36: =F35 -> 17754606 | G36: =G35 -> 15315766 | H36: =H35 -> 10780051 | I36: =WP!D40+GJP!D40+SBET!D40+Sugarplay!D40 -> 413831 | J36: =WP!J40+GJP!J40+SBET!J40+Sugarplay!J40 -> 290144 | K36: =WP!B40+GJP!B40+SBET!B40+Sugarplay!B40 -> 14713 | L36: =WP!C40+GJP!C40+SBET!C40+Sugarplay!C40 -> 4871 | M36: =WP!E40+GJP!E40+SBET!E40+Sugarplay!E40 -> 10272 | N36: =WP!F40+GJP!F40+SBET!F40+Sugarplay!F40 -> 61637 | O36: =WP!G40+GJP!G40+SBET!G40+Sugarplay!G40 -> 137802 | P36: =WP!O40+GJP!O40+SBET!O40+Sugarplay!P40 -> 7.8730096e+08 | Q36: =WP!P40+GJP!P40+SBET!P40+Sugarplay!Q40 -> 7.3356295e+08 | R36: =WP!R40+GJP!R40+SBET!R40+Sugarplay!S40 -> 7.6180257e+08 | S36: =T36/Q36 -> 0.010556402 | T36: =WP!S40+GJP!S40+SBET!S40+Sugarplay!T40 -> 7743785.6 | U36: =WP!T40+GJP!T40+SBET!T40+Sugarplay!U40 -> 3120272.9 | V36: =WP!U40+GJP!U40+SBET!U40+Sugarplay!V40 -> 402159.16 | W36: =W35 -> 17754606 | X36: =X35 -> 0.022551232 | Y36: =(P36-R36)/P36 -> 0.032387096 | Z36: =WP!AE40+GJP!AE40+SBET!AF40+Sugarplay!AG40 -> 25097081 | AA36: =AA35 -> 2438840.7 | AB36: =WP!AA40+GJP!AA40+SBET!AB40+Sugarplay!AC40 -> 2438840.7 | AC36: =WP!AB40+GJP!AB40+SBET!AC40+Sugarplay!AD40 -> 0 | AD36: =AD35 -> 15315766 | AE36: =AD36/P36 -> 0.019453508 | AF36: =AF35 -> 2937799.7 | AG36: =WP!W40+GJP!W40+SBET!W40+Sugarplay!X40 -> 2733381.3 | AH36: =WP!X40+GJP!X40+SBET!X40+Sugarplay!Y40 -> 204418.39 | AI36: =AI35 -> 1597914.6 | AM36: =AM35 -> 10780051 | AN36: =AM36/P36 -> 0.013692415 | AO36: =WP!AC40+GJP!AC40+SBET!AD40+Sugarplay!AE40 -> 168066.6 | AP36: =WP!AD40+GJP!AD40+SBET!AE40+Sugarplay!AF40 -> -322275.09 | AQ36: =AQ35 -> 10780051
A37: 差额 | B37: =B35-B36 -> 0 | D37: =D35-D36 -> 0 | E37: =E35-E36 -> 0 | F37: =F35-F36 -> 0 | G37: =G35-G36 -> 0 | H37: =H35-H36 -> 0 | I37: =I35-I36 -> 0 | J37: =J35-J36 -> 0 | K37: =K35-K36 -> 0 | ... AR37: =AR35-AR36 -> 0

Sheet WP
A2: 3月 | B2: 注册人数 | C2: 首充人数 | D2: 总登录人数 | L2: 总存款 | M2: 总取款 | N2: 存取差 | O2: 投注 | P2: 投注额 | Q2: 结算 | R2: 派彩 | S2: 优惠 | T2: 返点 | U2: 邀请返佣 | V2: 损益 | W2: 存款手续费 | X2: 提款手续费 | Y2: 手续费 | Z2: 平台费 | AA2: 周代理支出 | AB2: 月代理支出 | AC2: 开分 | AD2: 洗分 | AE2: 平台余额 | AF2: 总收益
A3: 合计 | B3: =SUM(B9:B39) -> 2952 | C3: =SUM(C9:C39) -> 1389 | D3: =SUM(D9:D39) -> 106269 | L3: =SUM(L9:L39) -> 45815747 | M3: =SUM(M9:M39) -> 42235825 | N3: =SUM(N9:N39) -> 3579922.5 | O3: =SUM(O9:O39) -> 2.8927637e+08 | P3: =SUM(P9:P39) -> 2.6722344e+08 | Q3: =SUM(Q9:Q39) -> 7537441.1 | R3: =SUM(R9:R39) -> 2.8173892e+08 | S3: =SUM(S9:S39) -> 2988721.4 | ... AF3: =SUM(AF9:AF39) -> 1668301
A4: 日均 | B4: =AVERAGE(B9:B39) -> 246 | C4: =AVERAGE(C9:C39) -> 115.75 | D4: =AVERAGE(D9:D39) -> 8855.75 | L4: =AVERAGE(L9:L39) -> 3817979 | M4: =AVERAGE(M9:M39) -> 3519652.1 | N4: =AVERAGE(N9:N39) -> 298326.87 | O4: =AVERAGE(O9:O39) -> 24106364 | P4: =AVERAGE(P9:P39) -> 22268620 | Q4: =AVERAGE(Q9:Q39) -> 628120.09 | R4: =AVERAGE(R9:R39) -> 23478244 | S4: =AVERAGE(S9:S39) -> 249060.11 | ... AF4: =AVERAGE(AF9:AF39) -> 139025.08
A6: Winning Plus 每日数据
A7: 日期 | B7: 总新注册人数 | C7: 总首充人数 | D7: 总登录人数 | E7: 续存人数 | F7: 总存款人数 | G7: 总存款次数 | H7: 总取款人数 | I7: 总取款次数 | J7: 总投注人数 | K7: 总首存 | L7: 总存款额度 | M7: 总取款额度 | N7: 存提差* | O7: 投注 | P7: 有效投注 | Q7: 公司輸贏 (淨贏-淨輸) | R7: 派彩 | S7: 优惠金额 | T7: 返点 | U7: 邀请返佣 | V7: 损益金额* | W7: 存款手续费 | X7: 提款手续费 | Y7: 手续费 | Z7: 平台费9% | AA7: 综合性分红 周代理支出 | AB7: 综合性分红 月代理支出 | AC7: 开分 | AD7: 洗分 | AE7: 平台余额 | AF7: 总收益 | AH7: 每人平均存款额 | AI7: 每人平均投注额 | AJ7: 每人平均投注次数
A8: date | B8: Total New Users | C8: no of first time depositors | D8: Login Head Count | E8: Number of survivors | F8: no of total depositors | G8: total deposit counts | H8: no of total withdrawer | I8: total withdrawal counts | J8: no of bettors | K8: total first deposit amount | L8: total deposit amount | M8: total withdrawal amount | N8: Deposit Withdrawal Difference | O8: Betting | P8: valid bet amount | Q8: Company Win/Loss | R8: Payouts | S8: promotion fees | T8: Rebates | U8: Referral rebates | V8: win/loss amount | W8: Deposit fees | X8: Withdrawal fees | Y8: service fees | Z8: Platform fees | AA8: Affiliate Commission (Weekly) | AB8: Affiliate Commission (Monthly) | AC8: Credit Adjustment | AD8: Debit Adjustment | AE8: Platform balance | AF8: Gross Profit | AH8: ave. deposit amount per person | AI8: ave. bet amount per person | AJ8: ave. no. of bets per person
A9: =全平台汇总!A3 -> 46082 | B9: 206 | C9: 94 | D9: 7540 | E9: 26 | F9: 1784 | G9: 4263 | H9: 487 | I9: 873 | J9: 3233 | K9: 17244 | L9: 4327032 | M9: 4332776 | N9: =IF(M9="","",L9-M9) -> -5744 | O9: 25435957 | P9: 23387437 | Q9: 314286.96 | R9: 25121670 | S9: 295220.25 | T9: 119755.52 | U9: 7496.69 | V9: =IF(S9="","",Q9-S9) -> 19066.71 | W9: 104281 | X9: 8666 | Y9: =W9+X9 -> 112947 | Z9: =IF(Q9="","",Q9*9%) -> 28285.826 | AA9: 0 | AC9: 0 | AD9: 0 | AE9: 149579.23 | AF9: =IF(V9="","",V9-Y9-AA9-Z9) -> -122166.12 | AH9: =L9/F9 -> 2425.4664 | AI9: =P9/J9 -> 7233.9736 | AJ9: =J9/F9 -> 1.8122197
A10: =全平台汇总!A4 -> 46083 | B10: 201 | C10: 104 | D10: 5841 | E10: 23 | F10: 1445 | G10: 3649 | H10: 502 | I10: 872 | J10: 2660 | K10: 26550 | L10: 4018268 | M10: 4321480 | N10: =IF(M10="","",L10-M10) -> -303212 | O10: 23804988 | P10: 21901078 | Q10: 397706.99 | R10: 23407281 | S10: 254626.16 | T10: 128495.2 | U10: 14478.44 | V10: =IF(S10="","",Q10-S10) -> 143080.83 | W10: 96840 | X10: 8643 | Y10: =W10+X10 -> 105483 | Z10: =IF(Q10="","",Q10*9%) -> 35793.629 | AA10: 431728.03 | AC10: 0 | AD10: -200.53 | AE10: 175077.02 | AF10: =IF(V10="","",V10-Y10-AA10-Z10) -> -429923.83 | AH10: =L10/F10 -> 2780.8083 | AI10: =P10/J10 -> 8233.488 | AJ10: =J10/F10 -> 1.8408304
A11: =全平台汇总!A5 -> 46084 | B11: 181 | C11: 73 | D11: 8837 | E11: 14 | F11: 1418 | G11: 3572 | H11: 396 | I11: 718 | J11: 3625 | K11: 28891 | L11: 3401851 | M11: 2965047 | N11: =IF(M11="","",L11-M11) -> 436804 | O11: 22837828 | P11: 20978277 | Q11: 613103.09 | R11: 22224724 | S11: 224541.9 | T11: 117284.58 | U11: 7959.32 | V11: =IF(S11="","",Q11-S11) -> 388561.19 | W11: 81985 | X11: 5930 | Y11: =W11+X11 -> 87915 | Z11: =IF(Q11="","",Q11*9%) -> 55179.278 | AA11: 0 | AC11: 0 | AD11: -48676.99 | AE11: 110172.04 | AF11: =IF(V11="","",V11-Y11-AA11-Z11) -> 245466.91 | AH11: =L11/F11 -> 2399.0487 | AI11: =P11/J11 -> 5787.111 | AJ11: =J11/F11 -> 2.5564175
A12: =全平台汇总!A6 -> 46085 | B12: 236 | C12: 102 | D12: 11208 | E12: 19 | F12: 1561 | G12: 3858 | H12: 446 | I12: 817 | J12: 4374 | K12: 26710 | L12: 4415840 | M12: 4143447 | N12: =IF(M12="","",L12-M12) -> 272393 | O12: 30123112 | P12: 27978341 | Q12: 515375.76 | R12: 29607737 | S12: 264906.87 | T12: 146456.63 | U12: 9715.15 | V12: =IF(S12="","",Q12-S12) -> 250468.89 | W12: 106422 | X12: 8287 | Y12: =W12+X12 -> 114709 | Z12: =IF(Q12="","",Q12*9%) -> 46383.818 | AA12: 0 | AC12: 0 | AD12: -102 | AE12: 129901.85 | AF12: =IF(V12="","",V12-Y12-AA12-Z12) -> 89376.072 | AH12: =L12/F12 -> 2828.8533 | AI12: =P12/J12 -> 6396.5115 | AJ12: =J12/F12 -> 2.80205
A13: =全平台汇总!A7 -> 46086 | B13: 200 | C13: 111 | D13: 6623 | E13: 26 | F13: 1399 | G13: 3686 | H13: 391 | I13: 753 | J13: 2991 | K13: 34717 | L13: 4465269 | M13: 4274465 | N13: =IF(M13="","",L13-M13) -> 190804 | O13: 29256885 | P13: 27024541 | Q13: 389842.95 | R13: 28867043 | S13: 266638.61 | T13: 149409.79 | U13: 16229.85 | V13: =IF(S13="","",Q13-S13) -> 123204.34 | W13: 107613 | X13: 8549 | Y13: =W13+X13 -> 116162 | Z13: =IF(Q13="","",Q13*9%) -> 35085.865 | AA13: 0 | AC13: 0 | AD13: -7252.75 | AE13: 110511.55 | AF13: =IF(V13="","",V13-Y13-AA13-Z13) -> -28043.525 | AH13: =L13/F13 -> 3191.7577 | AI13: =P13/J13 -> 9035.2861 | AJ13: =J13/F13 -> 2.1379557
A14: =全平台汇总!A8 -> 46087 | B14: 225 | C14: 106 | D14: 7154 | E14: 28 | F14: 1397 | G14: 3647 | H14: 390 | I14: 685 | J14: 3513 | K14: 24958 | L14: 3585506 | M14: 3024016 | N14: =IF(M14="","",L14-M14) -> 561490 | O14: 22867764 | P14: 21272462 | Q14: 1061968.4 | R14: 21805795 | S14: 254950.47 | T14: 147395.31 | U14: 12341.28 | V14: =IF(S14="","",Q14-S14) -> 807017.93 | W14: 86411 | X14: 6048 | Y14: =W14+X14 -> 92459 | Z14: =IF(Q14="","",Q14*9%) -> 95577.156 | AA14: 0 | AC14: 0 | AD14: -19602 | AE14: 136000.65 | AF14: =IF(V14="","",V14-Y14-AA14-Z14) -> 618981.77 | AH14: =L14/F14 -> 2566.5755 | AI14: =P14/J14 -> 6055.3549 | AJ14: =J14/F14 -> 2.5146743
A15: =全平台汇总!A9 -> 46088 | B15: 215 | C15: 124 | D15: 6230 | E15: 30 | F15: 1666 | G15: 4076 | H15: 447 | I15: 836 | J15: 3363 | K15: 30298 | L15: 3807281.5 | M15: 3430469 | N15: =IF(M15="","",L15-M15) -> 376812.48 | O15: 24946078 | P15: 23253030 | Q15: 705155.16 | R15: 24240922 | S15: 297408.46 | T15: 129678.43 | U15: 14845.09 | V15: =IF(S15="","",Q15-S15) -> 407746.7 | W15: 91755 | X15: 6861 | Y15: =W15+X15 -> 98616 | Z15: =IF(Q15="","",Q15*9%) -> 63463.964 | AA15: 0 | AC15: 0 | AD15: -4833.09 | AE15: 86171.3 | AF15: =IF(V15="","",V15-Y15-AA15-Z15) -> 245666.74 | AH15: =L15/F15 -> 2285.283 | AI15: =P15/J15 -> 6914.371 | AJ15: =J15/F15 -> 2.0186074
A16: =全平台汇总!A10 -> 46089 | B16: 411 | C16: 169 | D16: 16504 | E16: 22 | F16: 1762 | G16: 3913 | H16: 553 | I16: 934 | J16: 13870 | K16: 29889 | L16: 3574513 | M16: 2876306 | N16: =IF(M16="","",L16-M16) -> 698207 | O16: 23239251 | P16: 21368089 | Q16: 804174.15 | R16: 22435077 | S16: 273399.53 | T16: 107378.6 | U16: 10960.62 | V16: =IF(S16="","",Q16-S16) -> 530774.62 | W16: 86146 | X16: 5753 | Y16: =W16+X16 -> 91899 | Z16: =IF(Q16="","",Q16*9%) -> 72375.674 | AA16: 0 | AC16: 0 | AD16: -28870.49 | AE16: 218271.85 | AF16: =IF(V16="","",V16-Y16-AA16-Z16) -> 366499.95 | AH16: =L16/F16 -> 2028.668 | AI16: =P16/J16 -> 1540.5976 | AJ16: =J16/F16 -> 7.8717367
A17: =全平台汇总!A11 -> 46090 | B17: 329 | C17: 173 | D17: 10216 | E17: 18 | F17: 1485 | G17: 3713 | H17: 551 | I17: 900 | J17: 7731 | K17: 28088 | L17: 3774887 | M17: 3535997 | N17: =IF(M17="","",L17-M17) -> 238890 | O17: 23864570 | P17: 22149541 | Q17: 1037721.3 | R17: 22826849 | S17: 235169.41 | T17: 133185.2 | U17: 9214.15 | V17: =IF(S17="","",Q17-S17) -> 802551.94 | W17: 90975 | X17: 7072 | Y17: =W17+X17 -> 98047 | Z17: =IF(Q17="","",Q17*9%) -> 93394.921 | AA17: 581688.01 | AC17: 0 | AD17: -135163.09 | AE17: 227447.03 | AF17: =IF(V17="","",V17-Y17-AA17-Z17) -> 29422.008 | AH17: =L17/F17 -> 2542.0114 | AI17: =P17/J17 -> 2865.0292 | AJ17: =J17/F17 -> 5.2060606
A18: =全平台汇总!A12 -> 46091 | B18: 324 | C18: 137 | D18: 8709 | E18: 28 | F18: 1465 | G18: 3565 | H18: 428 | I18: 762 | J18: 5672 | K18: 21766 | L18: 3371495 | M18: 3044849 | N18: =IF(M18="","",L18-M18) -> 326646 | O18: 22774903 | P18: 21109571 | Q18: 630264.42 | R18: 22144639 | S18: 206804.26 | T18: 110287.02 | U18: 11268.16 | V18: =IF(S18="","",Q18-S18) -> 423460.16 | W18: 81253 | X18: 6090 | Y18: =W18+X18 -> 87343 | Z18: =IF(Q18="","",Q18*9%) -> 56723.798 | AA18: 0 | AC18: 3100 | AD18: -4765.84 | AE18: 158995.28 | AF18: =IF(V18="","",V18-Y18-AA18-Z18) -> 279393.36 | AH18: =L18/F18 -> 2301.3618 | AI18: =P18/J18 -> 3721.7155 | AJ18: =J18/F18 -> 3.8716724
A19: =全平台汇总!A13 -> 46092 | B19: 240 | C19: 111 | D19: 9678 | E19: 13 | F19: 1454 | G19: 3806 | H19: 446 | I19: 808 | J19: 6651 | K19: 18246 | L19: 3618631 | M19: 2655116 | N19: =IF(M19="","",L19-M19) -> 963515 | O19: 20652279 | P19: 18790973 | Q19: 1161479 | R19: 19490800 | S19: 216808.55 | T19: 113394.62 | U19: 10365.48 | V19: =IF(S19="","",Q19-S19) -> 944670.46 | W19: 87209 | X19: 5310 | Y19: =W19+X19 -> 92519 | Z19: =IF(Q19="","",Q19*9%) -> 104533.11 | AA19: 0 | AC19: 0 | AD19: -2801.85 | AE19: 114045.12 | AF19: =IF(V19="","",V19-Y19-AA19-Z19) -> 747618.35 | AH19: =L19/F19 -> 2488.7421 | AI19: =P19/J19 -> 2825.2854 | AJ19: =J19/F19 -> 4.5742779
A20: =全平台汇总!A14 -> 46093 | B20: 184 | C20: 85 | D20: 7729 | E20: 11 | F20: 1437 | G20: 3615 | H20: 443 | I20: 811 | J20: 4112 | K20: 14507 | L20: 3455174 | M20: 3631857 | N20: =IF(M20="","",L20-M20) -> -176683 | O20: 19472751 | P20: 18010102 | Q20: -93637.11 | R20: 19566388 | S20: 198246.91 | T20: 101638.92 | U20: 9773.56 | V20: =IF(S20="","",Q20-S20) -> -291884.02 | W20: 83270 | X20: 7264 | Y20: =W20+X20 -> 90534 | Z20: =IF(Q20="","",Q20*9%) -> -8427.3399 | AA20: 0 | AC20: 0 | AD20: -3302.2 | AE20: 75949.59 | AF20: =IF(V20="","",V20-Y20-AA20-Z20) -> -373990.68 | AH20: =L20/F20 -> 2404.4356 | AI20: =P20/J20 -> 4379.8886 | AJ20: =J20/F20 -> 2.861517
A21: =全平台汇总!A15 -> 46094 | N21: =IF(M21="","",L21-M21) | V21: =IF(S21="","",Q21-S21) | Y21: =W21+X21 -> 0 | Z21: =IF(Q21="","",Q21*9%) | AF21: =IF(V21="","",V21-Y21-AA21-Z21) | AH21: =L21/F21 -> #DIV/0! | AI21: =P21/J21 -> #DIV/0! | AJ21: =J21/F21 -> #DIV/0!
A22: =全平台汇总!A16 -> 46095 | N22: =IF(M22="","",L22-M22) | V22: =IF(S22="","",Q22-S22) | Y22: =W22+X22 -> 0 | Z22: =IF(Q22="","",Q22*9%) | AF22: =IF(V22="","",V22-Y22-AA22-Z22) | AH22: =L22/F22 -> #DIV/0! | AI22: =P22/J22 -> #DIV/0! | AJ22: =J22/F22 -> #DIV/0!
A23: =全平台汇总!A17 -> 46096 | N23: =IF(M23="","",L23-M23) | V23: =IF(S23="","",Q23-S23) | Y23: =W23+X23 -> 0 | Z23: =IF(Q23="","",Q23*9%) | AF23: =IF(V23="","",V23-Y23-AA23-Z23) | AH23: =L23/F23 -> #DIV/0! | AI23: =P23/J23 -> #DIV/0! | AJ23: =J23/F23 -> #DIV/0!
A24: =全平台汇总!A18 -> 46097 | N24: =IF(M24="","",L24-M24) | V24: =IF(S24="","",Q24-S24) | Y24: =W24+X24 -> 0 | Z24: =IF(Q24="","",Q24*9%) | AF24: =IF(V24="","",V24-Y24-AA24-Z24) | AH24: =L24/F24 -> #DIV/0! | AI24: =P24/J24 -> #DIV/0! | AJ24: =J24/F24 -> #DIV/0!
A25: =全平台汇总!A19 -> 46098 | N25: =IF(M25="","",L25-M25) | V25: =IF(S25="","",Q25-S25) | Y25: =W25+X25 -> 0 | Z25: =IF(Q25="","",Q25*9%) | AF25: =IF(V25="","",V25-Y25-AA25-Z25) | AH25: =L25/F25 -> #DIV/0! | AI25: =P25/J25 -> #DIV/0! | AJ25: =J25/F25 -> #DIV/0!
A26: =全平台汇总!A20 -> 46099 | N26: =IF(M26="","",L26-M26) | V26: =IF(S26="","",Q26-S26) | Y26: =W26+X26 -> 0 | Z26: =IF(Q26="","",Q26*9%) | AF26: =IF(V26="","",V26-Y26-AA26-Z26) | AH26: =L26/F26 -> #DIV/0! | AI26: =P26/J26 -> #DIV/0! | AJ26: =J26/F26 -> #DIV/0!
A27: =全平台汇总!A21 -> 46100 | N27: =IF(M27="","",L27-M27) | V27: =IF(S27="","",Q27-S27) | Y27: =W27+X27 -> 0 | Z27: =IF(Q27="","",Q27*9%) | AF27: =IF(V27="","",V27-Y27-AA27-Z27) | AH27: =L27/F27 -> #DIV/0! | AI27: =P27/J27 -> #DIV/0! | AJ27: =J27/F27 -> #DIV/0!
A28: =全平台汇总!A22 -> 46101 | N28: =IF(M28="","",L28-M28) | V28: =IF(S28="","",Q28-S28) | Y28: =W28+X28 -> 0 | Z28: =IF(Q28="","",Q28*9%) | AF28: =IF(V28="","",V28-Y28-AA28-Z28) | AH28: =L28/F28 -> #DIV/0! | AI28: =P28/J28 -> #DIV/0! | AJ28: =J28/F28 -> #DIV/0!
A29: =全平台汇总!A23 -> 46102 | N29: =IF(M29="","",L29-M29) | V29: =IF(S29="","",Q29-S29) | Y29: =W29+X29 -> 0 | Z29: =IF(Q29="","",Q29*9%) | AF29: =IF(V29="","",V29-Y29-AA29-Z29) | AH29: =L29/F29 -> #DIV/0! | AI29: =P29/J29 -> #DIV/0! | AJ29: =J29/F29 -> #DIV/0!
A30: =全平台汇总!A24 -> 46103 | N30: =IF(M30="","",L30-M30) | V30: =IF(S30="","",Q30-S30) | Y30: =W30+X30 -> 0 | Z30: =IF(Q30="","",Q30*9%) | AF30: =IF(V30="","",V30-Y30-AA30-Z30) | AH30: =L30/F30 -> #DIV/0! | AI30: =P30/J30 -> #DIV/0! | AJ30: =J30/F30 -> #DIV/0!
A31: =全平台汇总!A25 -> 46104 | N31: =IF(M31="","",L31-M31) | V31: =IF(S31="","",Q31-S31) | Y31: =W31+X31 -> 0 | Z31: =IF(Q31="","",Q31*9%) | AF31: =IF(V31="","",V31-Y31-AA31-Z31) | AH31: =L31/F31 -> #DIV/0! | AI31: =P31/J31 -> #DIV/0! | AJ31: =J31/F31 -> #DIV/0!
A32: =全平台汇总!A26 -> 46105 | N32: =IF(M32="","",L32-M32) | V32: =IF(S32="","",Q32-S32) | Y32: =W32+X32 -> 0 | Z32: =IF(Q32="","",Q32*9%) | AF32: =IF(V32="","",V32-Y32-AA32-Z32) | AH32: =L32/F32 -> #DIV/0! | AI32: =P32/J32 -> #DIV/0! | AJ32: =J32/F32 -> #DIV/0!
A33: =全平台汇总!A27 -> 46106 | N33: =IF(M33="","",L33-M33) | V33: =IF(S33="","",Q33-S33) | Y33: =W33+X33 -> 0 | Z33: =IF(Q33="","",Q33*9%) | AF33: =IF(V33="","",V33-Y33-AA33-Z33) | AH33: =L33/F33 -> #DIV/0! | AI33: =P33/J33 -> #DIV/0! | AJ33: =J33/F33 -> #DIV/0!
A34: =全平台汇总!A28 -> 46107 | N34: =IF(M34="","",L34-M34) | V34: =IF(S34="","",Q34-S34) | Y34: =W34+X34 -> 0 | Z34: =IF(Q34="","",Q34*9%) | AF34: =IF(V34="","",V34-Y34-AA34-Z34) | AH34: =M34/G34 -> #DIV/0! | AI34: =P34/K34 -> #DIV/0! | AJ34: =K34/G34 -> #DIV/0!
A35: =全平台汇总!A29 -> 46108 | N35: =IF(M35="","",L35-M35) | V35: =IF(S35="","",Q35-S35) | Y35: =W35+X35 -> 0 | Z35: =IF(Q35="","",Q35*9%) | AF35: =IF(V35="","",V35-Y35-AA35-Z35) | AH35: =M35/G35 -> #DIV/0! | AI35: =P35/K35 -> #DIV/0! | AJ35: =K35/G35 -> #DIV/0!
A36: =全平台汇总!A30 -> 46109 | N36: =IF(M36="","",L36-M36) | V36: =IF(S36="","",Q36-S36) | Y36: =W36+X36 -> 0 | Z36: =IF(Q36="","",Q36*9%) | AF36: =IF(V36="","",V36-Y36-AA36-Z36) | AH36: =L36/F36 -> #DIV/0! | AI36: =P36/J36 -> #DIV/0! | AJ36: =J36/F36 -> #DIV/0!
A37: =全平台汇总!A31 -> 46110 | N37: =IF(M37="","",L37-M37) | V37: =IF(S37="","",Q37-S37) | Y37: =W37+X37 -> 0 | Z37: =IF(Q37="","",Q37*9%) | AF37: =IF(V37="","",V37-Y37-AA37-Z37) | AH37: =L37/F37 -> #DIV/0! | AI37: =P37/J37 -> #DIV/0! | AJ37: =J37/F37 -> #DIV/0!
A38: =全平台汇总!A32 -> 46111 | N38: =IF(M38="","",L38-M38) | V38: =IF(S38="","",Q38-S38) | Y38: =W38+X38 -> 0 | Z38: =IF(Q38="","",Q38*9%) | AF38: =IF(V38="","",V38-Y38-AA38-Z38) | AH38: =L38/F38 -> #DIV/0! | AI38: =P38/J38 -> #DIV/0! | AJ38: =J38/F38 -> #DIV/0!
A39: =全平台汇总!A33 -> 46112 | N39: =IF(M39="","",L39-M39) | V39: =IF(S39="","",Q39-S39) | Y39: =W39+X39 -> 0 | Z39: =IF(Q39="","",Q39*9%) | AF39: =IF(V39="","",V39-Y39-AA39-Z39) | AH39: =L39/F39 -> #DIV/0! | AI39: =P39/J39 -> #DIV/0! | AJ39: =J39/F39 -> #DIV/0!
A40: 总额 total | B40: =SUM(B9:B39) -> 2952 | C40: =SUM(C9:C39) -> 1389 | D40: =SUM(D9:D39) -> 106269 | E40: =SUM(E9:E39) -> 258 | F40: =SUM(F9:F39) -> 18273 | G40: =SUM(G9:G39) -> 45363 | H40: =SUM(H9:H39) -> 5480 | I40: =SUM(I9:I39) -> 9769 | ... AF40: =SUM(AF9:AF39) -> 1668301 | AH40: =L40/F40 -> 2507.292 | AI40: =P40/J40 -> 4324.3538 | AJ40: =J40/F40 -> 3.3817654
A41: 备注：Exchange rate difference (only Dragonpay) 4%計
W42: 次月初5号更改

Sheet GJP
A2: =WP!A2 -> 3月 | B2: 注册人数 | C2: 首充人数 | D2: 总登录人数 | L2: 总存款 | M2: 总取款 | N2: 存取差 | O2: 投注 | P2: 投注额 | Q2: 结算 | R2: 派彩 | S2: 优惠 | T2: 返点 | U2: 邀请返佣 | V2: 损益 | W2: 存款手续费 | X2: 提款手续费 | Y2: 支付手续费 | Z2: 平台费 | AA2: 周代理支出 | AB2: 月代理支出 | AC2: 开分 | AD2: 洗分 | AE2: 平台余额 | AF2: 总收益
A3: 合计 | B3: =SUM(B9:B39) -> 8462 | C3: =SUM(C9:C39) -> 2539 | D3: =SUM(D9:D39) -> 214720 | L3: =SUM(L9:L39) -> 39679481 | M3: =SUM(M9:M39) -> 33057087 | N3: =SUM(N9:N39) -> 6622394.4 | O3: =SUM(O9:O39) -> 2.766108e+08 | P3: =SUM(P9:P39) -> 2.5251256e+08 | Q3: =SUM(Q9:Q39) -> 10408532 | R3: =SUM(R9:R39) -> 2.6620227e+08 | S3: =SUM(S9:S39) -> 2433010.1 | ... AF3: =SUM(AF9:AF39) -> 5316303.6
A4: 日均 | B4: =AVERAGE(B9:B39) -> 705.16667 | C4: =AVERAGE(C9:C39) -> 211.58333 | D4: =AVERAGE(D9:D39) -> 17893.333 | L4: =AVERAGE(L9:L39) -> 3306623.5 | M4: =AVERAGE(M9:M39) -> 2754757.2 | N4: =AVERAGE(N9:N39) -> 551866.2 | O4: =AVERAGE(O9:O39) -> 23050900 | P4: =AVERAGE(P9:P39) -> 21042713 | Q4: =AVERAGE(Q9:Q39) -> 867377.66 | R4: =AVERAGE(R9:R39) -> 22183523 | S4: =AVERAGE(S9:S39) -> 202750.84 | ... AF4: =AVERAGE(AF9:AF39) -> 443025.3
A6: Go JackPot 每日数据
A7: 日期 | B7: 总新注册人数 | C7: 总首充人数 | D7: 总登录人数 | E7: 续存人数 | F7: 总存款人数 | G7: 总存款次数 | H7: 总取款人数 | I7: 总取款次数 | J7: 总投注人数 | K7: 总首存 | L7: 总存款额度 | M7: 总取款额度 | N7: 存提差* | O7: 投注 | P7: 有效投注 | Q7: 公司輸贏 (淨贏-淨輸) | R7: 派彩 | S7: 优惠金额 | T7: 返点 | U7: 邀请返佣 | V7: 损益金额* | W7: 存款手续费 | X7: 提款手续费 | Y7: 手续费 | Z7: 平台费9% | AA7: 综合性分红 周代理支出 | AB7: 综合性分红 月代理支出 | AC7: 开分 | AD7: 洗分 | AE7: 平台余额 | AF7: 总收益 | AH7: 每人平均存款额 | AI7: 每人平均投注额 | AJ7: 每人平均投注次数
A8: date | B8: Total New Users | C8: no of first time depositors | D8: Login Head Count | E8: Number of survivors | F8: no of total depositors | G8: total deposit counts | H8: no of total withdrawer | I8: total withdrawal counts | J8: no of bettors | K8: total first deposit amount | L8: total deposit amount | M8: total withdrawal amount | N8: Deposit Withdrawal Difference | O8: Betting | P8: valid bet amount | Q8: Company Win/Loss | R8: Payouts | S8: promotion fees | T8: Rebates | U8: Referral rebates | V8: Company net profit | W8: Deposit fees | X8: Withdrawal fees | Y8: service fees | Z8: Platform fees | AA8: Affiliate Commission (Weekly) | AB8: Affiliate Commission (Monthly) | AC8: Credit Adjustment | AD8: Debit Adjustment | AE8: Platform balance | AF8: Gross Profit | AH8: ave. deposit amount per person | AI8: ave. bet amount per person | AJ8: ave. no. of bets per person
A9: =全平台汇总!A3 -> 46082 | B9: 734 | C9: 200 | D9: 19170 | E9: 60 | F9: 2361 | G9: 4778 | H9: 665 | I9: 988 | J9: 13551 | K9: 32342 | L9: 3452835.6 | M9: 2765137 | N9: =IF(M9="","",L9-M9) -> 687698.6 | O9: 25905807 | P9: 23941465 | Q9: 1187358.9 | R9: 24718448 | S9: 218250.96 | T9: 109661.98 | U9: 20671.34 | V9: =IF(S9="","",Q9-S9) -> 969107.9 | W9: 79760.5 | X9: 5530.27 | Y9: =W9+X9 -> 85290.77 | Z9: =IF(Q9="","",Q9*9%) -> 106862.3 | AA9: 0 | AC9: 100 | AD9: -1615.16 | AE9: 313349 | AF9: =IF(V9="","",V9-Y9-AA9-Z9) -> 776954.83 | AH9: =L9/F9 -> 1462.4463 | AI9: =P9/J9 -> 1766.7674 | AJ9: =J9/F9 -> 5.7395172
A10: =全平台汇总!A4 -> 46083 | B10: 682 | C10: 194 | D10: 16191 | E10: 45 | F10: 2036 | G10: 4246 | H10: 643 | I10: 985 | J10: 11724 | K10: 30152 | L10: 2617217.6 | M10: 2515136 | N10: =IF(M10="","",L10-M10) -> 102081.57 | O10: 18589943 | P10: 17044340 | Q10: 679017.64 | R10: 17910926 | S10: 188873.5 | T10: 75653.67 | U10: 25629.54 | V10: =IF(S10="","",Q10-S10) -> 490144.14 | W10: 60457.73 | X10: 5030.27 | Y10: =W10+X10 -> 65488 | Z10: =IF(Q10="","",Q10*9%) -> 61111.588 | AA10: 355968.37 | AC10: 24934.69 | AD10: -3857.93 | AE10: 279967 | AF10: =IF(V10="","",V10-Y10-AA10-Z10) -> 7576.1824 | AH10: =L10/F10 -> 1285.4703 | AI10: =P10/J10 -> 1453.799 | AJ10: =J10/F10 -> 5.7583497
A11: =全平台汇总!A5 -> 46084 | B11: 774 | C11: 243 | D11: 16353 | E11: 64 | F11: 2106 | G11: 4583 | H11: 622 | I11: 1026 | J11: 12145 | K11: 36262 | L11: 3512576 | M11: 3024609 | N11: =IF(M11="","",L11-M11) -> 487967 | O11: 24992677 | P11: 22759687 | Q11: 575710.5 | R11: 24416966 | S11: 174668.1 | T11: 62966.58 | U11: 22174.02 | V11: =IF(S11="","",Q11-S11) -> 401042.4 | W11: 81140.51 | X11: 6049.22 | Y11: =W11+X11 -> 87189.73 | Z11: =IF(Q11="","",Q11*9%) -> 51813.945 | AA11: 0 | AC11: 0 | AD11: -4037.8 | AE11: 254465 | AF11: =IF(V11="","",V11-Y11-AA11-Z11) -> 262038.73 | AH11: =L11/F11 -> 1667.8898 | AI11: =P11/J11 -> 1873.9965 | AJ11: =J11/F11 -> 5.7668566
A12: =全平台汇总!A6 -> 46085 | B12: 678 | C12: 269 | D12: 17627 | E12: 51 | F12: 2317 | G12: 4885 | H12: 677 | I12: 1068 | J12: 13428 | K12: 65672 | L12: 4296188.1 | M12: 2684064 | N12: =IF(M12="","",L12-M12) -> 1612124.1 | O12: 26659660 | P12: 24304693 | Q12: 1626751 | R12: 25032909 | S12: 242140.14 | T12: 106399.04 | U12: 29396.48 | V12: =IF(S12="","",Q12-S12) -> 1384610.9 | W12: 99241.94 | X12: 5368.13 | Y12: =W12+X12 -> 104610.07 | Z12: =IF(Q12="","",Q12*9%) -> 146407.59 | AA12: 0 | AC12: 0 | AD12: -591.1 | AE12: 460845 | AF12: =IF(V12="","",V12-Y12-AA12-Z12) -> 1133593.2 | AH12: =L12/F12 -> 1854.2029 | AI12: =P12/J12 -> 1810.0009 | AJ12: =J12/F12 -> 5.7954251
A13: =全平台汇总!A7 -> 46086 | B13: 697 | C13: 185 | D13: 16507 | E13: 36 | F13: 2081 | G13: 4610 | H13: 572 | I13: 979 | J13: 12528 | K13: 56468 | L13: 3307678.8 | M13: 2573118 | N13: =IF(M13="","",L13-M13) -> 734560.82 | O13: 20240554 | P13: 18651346 | Q13: 997982.34 | R13: 19242572 | S13: 164772.48 | T13: 63136.27 | U13: 19647.81 | V13: =IF(S13="","",Q13-S13) -> 833209.86 | W13: 76407.38 | X13: 5146.24 | Y13: =W13+X13 -> 81553.62 | Z13: =IF(Q13="","",Q13*9%) -> 89818.411 | AA13: 0 | AC13: 0 | AD13: -4178.69 | AE13: 429751 | AF13: =IF(V13="","",V13-Y13-AA13-Z13) -> 661837.83 | AH13: =L13/F13 -> 1589.466 | AI13: =P13/J13 -> 1488.7729 | AJ13: =J13/F13 -> 6.0201826
A14: =全平台汇总!A8 -> 46087 | B14: 627 | C14: 224 | D14: 18920 | E14: 33 | F14: 2663 | G14: 5349 | H14: 819 | I14: 1222 | J14: 15273 | K14: 59567 | L14: 4434477 | M14: 3827157 | N14: =IF(M14="","",L14-M14) -> 607320.04 | O14: 29714037 | P14: 27038275 | Q14: 1029884 | R14: 28684153 | S14: 319868.17 | T14: 122278 | U14: 14870.64 | V14: =IF(S14="","",Q14-S14) -> 710015.84 | W14: 102436.42 | X14: 7654.31 | Y14: =W14+X14 -> 110090.73 | Z14: =IF(Q14="","",Q14*9%) -> 92689.561 | AA14: 0 | AC14: 0 | AD14: -1201.95 | AE14: 211513 | AF14: =IF(V14="","",V14-Y14-AA14-Z14) -> 507235.55 | AH14: =L14/F14 -> 1665.2186 | AI14: =P14/J14 -> 1770.3316 | AJ14: =J14/F14 -> 5.735261
A15: =全平台汇总!A9 -> 46088 | B15: 728 | C15: 216 | D15: 17714 | E15: 43 | F15: 2264 | G15: 4952 | H15: 723 | I15: 1124 | J15: 13942 | K15: 31207 | L15: 2882752.7 | M15: 2293915 | N15: =IF(M15="","",L15-M15) -> 588837.71 | O15: 19693332 | P15: 17981849 | Q15: 923435.5 | R15: 18769896 | S15: 154590.86 | T15: 47701.51 | U15: 29209.05 | V15: =IF(S15="","",Q15-S15) -> 768844.64 | W15: 66591.59 | X15: 4587.83 | Y15: =W15+X15 -> 71179.42 | Z15: =IF(Q15="","",Q15*9%) -> 83109.195 | AA15: 0 | AC15: 0 | AD15: -1205.93 | AE15: 320396 | AF15: =IF(V15="","",V15-Y15-AA15-Z15) -> 614556.03 | AH15: =L15/F15 -> 1273.3007 | AI15: =P15/J15 -> 1289.7611 | AJ15: =J15/F15 -> 6.1581272
A16: =全平台汇总!A10 -> 46089 | B16: 866 | C16: 238 | D16: 20396 | E16: 35 | F16: 2380 | G16: 5013 | H16: 828 | I16: 1242 | J16: 16424 | K16: 43884 | L16: 3035120.4 | M16: 2331966 | N16: =IF(M16="","",L16-M16) -> 703154.43 | O16: 21822369 | P16: 19857974 | Q16: 804857.27 | R16: 21017512 | S16: 185529.99 | T16: 67982.01 | U16: 23384.16 | V16: =IF(S16="","",Q16-S16) -> 619327.28 | W16: 70111.28 | X16: 4663.93 | Y16: =W16+X16 -> 74775.21 | Z16: =IF(Q16="","",Q16*9%) -> 72437.154 | AA16: 0 | AC16: 0 | AD16: -3200.05 | AE16: 194641 | AF16: =IF(V16="","",V16-Y16-AA16-Z16) -> 472114.92 | AH16: =L16/F16 -> 1275.2607 | AI16: =P16/J16 -> 1209.0827 | AJ16: =J16/F16 -> 6.9008403
A17: =全平台汇总!A11 -> 46090 | B17: 740 | C17: 213 | D17: 17599 | E17: 40 | F17: 2084 | G17: 4434 | H17: 712 | I17: 1137 | J17: 13828 | K17: 33869 | L17: 2872139.2 | M17: 3330527 | N17: =IF(M17="","",L17-M17) -> -458387.79 | O17: 22455785 | P17: 19917885 | Q17: 350599.83 | R17: 22105185 | S17: 217925.06 | T17: 78080.73 | U17: 22614.28 | V17: =IF(S17="","",Q17-S17) -> 132674.77 | W17: 66346.42 | X17: 6661.05 | Y17: =W17+X17 -> 73007.47 | Z17: =IF(Q17="","",Q17*9%) -> 31553.985 | AA17: 383771.82 | AC17: 115207.41 | AD17: -10181.36 | AE17: 936537 | AF17: =IF(V17="","",V17-Y17-AA17-Z17) -> -355658.5 | AH17: =L17/F17 -> 1378.1858 | AI17: =P17/J17 -> 1440.4025 | AJ17: =J17/F17 -> 6.6353167
A18: =全平台汇总!A12 -> 46091 | B18: 740 | C18: 198 | D18: 17963 | E18: 40 | F18: 2097 | G18: 4530 | H18: 612 | I18: 1029 | J18: 13487 | K18: 29433 | L18: 2765674.1 | M18: 2674693 | N18: =IF(M18="","",L18-M18) -> 90981.14 | O18: 21144182 | P18: 19425608 | Q18: 313364.37 | R18: 20830818 | S18: 156062.21 | T18: 60242.54 | U18: 17950.2 | V18: =IF(S18="","",Q18-S18) -> 157302.16 | W18: 63887.07 | X18: 5349.39 | Y18: =W18+X18 -> 69236.46 | Z18: =IF(Q18="","",Q18*9%) -> 28202.793 | AA18: 0 | AC18: 0 | AD18: -4654.57 | AE18: 348015 | AF18: =IF(V18="","",V18-Y18-AA18-Z18) -> 59862.907 | AH18: =L18/F18 -> 1318.8718 | AI18: =P18/J18 -> 1440.3209 | AJ18: =J18/F18 -> 6.4315689
A19: =全平台汇总!A13 -> 46092 | B19: 598 | C19: 173 | D19: 18579 | E19: 21 | F19: 2112 | G19: 4593 | H19: 602 | I19: 992 | J19: 13990 | K19: 36245.89 | L19: 3503445.9 | M19: 2520988 | N19: =IF(M19="","",L19-M19) -> 982457.94 | O19: 19485775 | P19: 18083907 | Q19: 85086.62 | R19: 19400688 | S19: 201761.47 | T19: 86347.47 | U19: 16909.8 | V19: =IF(S19="","",Q19-S19) -> -116674.85 | W19: 80929.6 | X19: 5041.98 | Y19: =W19+X19 -> 85971.58 | Z19: =IF(Q19="","",Q19*9%) -> 7657.7958 | AA19: 0 | AC19: 0 | AD19: 0 | AE19: 1132865 | AF19: =IF(V19="","",V19-Y19-AA19-Z19) -> -210304.23 | AH19: =L19/F19 -> 1658.8286 | AI19: =P19/J19 -> 1292.6309 | AJ19: =J19/F19 -> 6.624053
A20: =全平台汇总!A14 -> 46093 | B20: 598 | C20: 186 | D20: 17701 | E20: 32 | F20: 2047 | G20: 4415 | H20: 594 | I20: 940 | J20: 13313 | K20: 27492 | L20: 2999375.9 | M20: 2515777 | N20: =IF(M20="","",L20-M20) -> 483598.88 | O20: 25906681 | P20: 23505528 | Q20: 1834483.9 | R20: 24072197 | S20: 208567.13 | T20: 104908.57 | U20: 16534.57 | V20: =IF(S20="","",Q20-S20) -> 1625916.8 | W20: 69285.58 | X20: 5031.55 | Y20: =W20+X20 -> 74317.13 | Z20: =IF(Q20="","",Q20*9%) -> 165103.55 | AA20: 0 | AC20: 2100 | AD20: -3807.13 | AE20: 175479 | AF20: =IF(V20="","",V20-Y20-AA20-Z20) -> 1386496.1 | AH20: =L20/F20 -> 1465.2545 | AI20: =P20/J20 -> 1765.6072 | AJ20: =J20/F20 -> 6.5036639
A21: =全平台汇总!A15 -> 46094 | N21: =IF(M21="","",L21-M21) | V21: =IF(S21="","",Q21-S21) | Y21: =W21+X21 -> 0 | Z21: =IF(Q21="","",Q21*9%) | AF21: =IF(V21="","",V21-Y21-AA21-Z21) | AH21: =L21/F21 -> #DIV/0! | AI21: =P21/J21 -> #DIV/0! | AJ21: =J21/F21 -> #DIV/0!
A22: =全平台汇总!A16 -> 46095 | N22: =IF(M22="","",L22-M22) | V22: =IF(S22="","",Q22-S22) | Y22: =W22+X22 -> 0 | Z22: =IF(Q22="","",Q22*9%) | AF22: =IF(V22="","",V22-Y22-AA22-Z22) | AH22: =L22/F22 -> #DIV/0! | AI22: =P22/J22 -> #DIV/0! | AJ22: =J22/F22 -> #DIV/0!
A23: =全平台汇总!A17 -> 46096 | N23: =IF(M23="","",L23-M23) | V23: =IF(S23="","",Q23-S23) | Y23: =W23+X23 -> 0 | Z23: =IF(Q23="","",Q23*9%) | AF23: =IF(V23="","",V23-Y23-AA23-Z23) | AH23: =L23/F23 -> #DIV/0! | AI23: =P23/J23 -> #DIV/0! | AJ23: =J23/F23 -> #DIV/0!
A24: =全平台汇总!A18 -> 46097 | N24: =IF(M24="","",L24-M24) | V24: =IF(S24="","",Q24-S24) | Y24: =W24+X24 -> 0 | Z24: =IF(Q24="","",Q24*9%) | AF24: =IF(V24="","",V24-Y24-AA24-Z24) | AH24: =L24/F24 -> #DIV/0! | AI24: =P24/J24 -> #DIV/0! | AJ24: =J24/F24 -> #DIV/0!
A25: =全平台汇总!A19 -> 46098 | N25: =IF(M25="","",L25-M25) | V25: =IF(S25="","",Q25-S25) | Y25: =W25+X25 -> 0 | Z25: =IF(Q25="","",Q25*9%) | AF25: =IF(V25="","",V25-Y25-AA25-Z25) | AH25: =L25/F25 -> #DIV/0! | AI25: =P25/J25 -> #DIV/0! | AJ25: =J25/F25 -> #DIV/0!
A26: =全平台汇总!A20 -> 46099 | N26: =IF(M26="","",L26-M26) | V26: =IF(S26="","",Q26-S26) | Y26: =W26+X26 -> 0 | Z26: =IF(Q26="","",Q26*9%) | AF26: =IF(V26="","",V26-Y26-AA26-Z26) | AH26: =L26/F26 -> #DIV/0! | AI26: =P26/J26 -> #DIV/0! | AJ26: =J26/F26 -> #DIV/0!
A27: =全平台汇总!A21 -> 46100 | N27: =IF(M27="","",L27-M27) | V27: =IF(S27="","",Q27-S27) | Y27: =W27+X27 -> 0 | Z27: =IF(Q27="","",Q27*9%) | AF27: =IF(V27="","",V27-Y27-AA27-Z27) | AH27: =L27/F27 -> #DIV/0! | AI27: =P27/J27 -> #DIV/0! | AJ27: =J27/F27 -> #DIV/0!
A28: =全平台汇总!A22 -> 46101 | N28: =IF(M28="","",L28-M28) | V28: =IF(S28="","",Q28-S28) | Y28: =W28+X28 -> 0 | Z28: =IF(Q28="","",Q28*9%) | AF28: =IF(V28="","",V28-Y28-AA28-Z28) | AH28: =L28/F28 -> #DIV/0! | AI28: =P28/J28 -> #DIV/0! | AJ28: =J28/F28 -> #DIV/0!
A29: =全平台汇总!A23 -> 46102 | N29: =IF(M29="","",L29-M29) | V29: =IF(S29="","",Q29-S29) | Y29: =W29+X29 -> 0 | Z29: =IF(Q29="","",Q29*9%) | AF29: =IF(V29="","",V29-Y29-AA29-Z29) | AH29: =L29/F29 -> #DIV/0! | AI29: =P29/J29 -> #DIV/0! | AJ29: =J29/F29 -> #DIV/0!
A30: =全平台汇总!A24 -> 46103 | N30: =IF(M30="","",L30-M30) | V30: =IF(S30="","",Q30-S30) | Y30: =W30+X30 -> 0 | Z30: =IF(Q30="","",Q30*9%) | AF30: =IF(V30="","",V30-Y30-AA30-Z30) | AH30: =L30/F30 -> #DIV/0! | AI30: =P30/J30 -> #DIV/0! | AJ30: =J30/F30 -> #DIV/0!
A31: =全平台汇总!A25 -> 46104 | N31: =IF(M31="","",L31-M31) | V31: =IF(S31="","",Q31-S31) | Y31: =W31+X31 -> 0 | Z31: =IF(Q31="","",Q31*9%) | AF31: =IF(V31="","",V31-Y31-AA31-Z31) | AH31: =L31/F31 -> #DIV/0! | AI31: =P31/J31 -> #DIV/0! | AJ31: =J31/F31 -> #DIV/0!
A32: =全平台汇总!A26 -> 46105 | N32: =IF(M32="","",L32-M32) | V32: =IF(S32="","",Q32-S32) | Y32: =W32+X32 -> 0 | Z32: =IF(Q32="","",Q32*9%) | AF32: =IF(V32="","",V32-Y32-AA32-Z32) | AH32: =L32/F32 -> #DIV/0! | AI32: =P32/J32 -> #DIV/0! | AJ32: =J32/F32 -> #DIV/0!
... A39: =全平台汇总!A33 -> 46112 | N39: =IF(M39="","",L39-M39) | V39: =IF(S39="","",Q39-S39) | Y39: =W39+X39 -> 0 | Z39: =IF(Q39="","",Q39*9%) | AF39: =IF(V39="","",V39-Y39-AA39-Z39) | AH39: =L39/F39 -> #DIV/0! | AI39: =P39/J39 -> #DIV/0! | AJ39: =J39/F39 -> #DIV/0!
A40: 总额 total | B40: =SUM(B9:B39) -> 8462 | C40: =SUM(C9:C39) -> 2539 | D40: =SUM(D9:D39) -> 214720 | E40: =SUM(E9:E39) -> 500 | F40: =SUM(F9:F39) -> 26548 | G40: =SUM(G9:G39) -> 56388 | H40: =SUM(H9:H39) -> 8069 | I40: =SUM(I9:I39) -> 12732 | ... AF40: =SUM(AF9:AF39) -> 5316303.6 | AH40: =L40/F40 -> 1494.6317 | AI40: =P40/J40 -> 1543.164 | AJ40: =J40/F40 -> 6.1636658
A41: 备注：Exchange rate difference (only Dragonpay) 4%計
W42: 次月初5号更改

Sheet SBET
A2: =WP!A2 -> 3月 | B2: 注册人数 | C2: 首充人数 | D2: 总登录人数 | L2: 总存款 | M2: 总取款 | N2: 存取差 | O2: 投注 | P2: 投注额 | Q2: 结算 | R2: 派彩 | S2: 优惠 | T2: 返点 | U2: 邀请返佣 | V2: 损益 | W2: 存款手续费 | X2: 提款手续费 | Y2: 手续费 | Z2: 平台费 | AA2: 日代理支出 | AB2: 周代理支出 | AC2: 月代理支出 | AD2: 开分 | AE2: 洗分 | AF2: 平台余额 | AG2: 总收益
A3: 合计 | B3: =SUM(B9:B39) -> 1794 | C3: =SUM(C9:C39) -> 555 | D3: =SUM(D9:D39) -> 57872 | L3: =SUM(L9:L39) -> 11590056 | M3: =SUM(M9:M39) -> 10542104 | N3: =SUM(N9:N39) -> 1047952 | O3: =SUM(O9:O39) -> 72902039 | P3: =SUM(P9:P39) -> 66733616 | Q3: =SUM(Q9:Q39) -> 1798392.3 | R3: =SUM(R9:R39) -> 71103646 | S3: =SUM(S9:S39) -> 614296.18 | ... AG3: =SUM(AG9:AG39) -> 518706.76
A4: 日均 | B4: =AVERAGE(B9:B39) -> 149.5 | C4: =AVERAGE(C9:C39) -> 46.25 | D4: =AVERAGE(D9:D39) -> 4822.6667 | L4: =AVERAGE(L9:L39) -> 965838 | M4: =AVERAGE(M9:M39) -> 878508.67 | N4: =AVERAGE(N9:N39) -> 87329.333 | O4: =AVERAGE(O9:O39) -> 6075169.9 | P4: =AVERAGE(P9:P39) -> 5561134.7 | Q4: =AVERAGE(Q9:Q39) -> 149866.02 | R4: =AVERAGE(R9:R39) -> 5925303.9 | S4: =AVERAGE(S9:S39) -> 51191.348 | ... AG4: =AVERAGE(AG9:AG39) -> 43225.564
A6: SBET 每日数据
A7: 日期 | B7: 总新注册人数 | C7: 总首充人数 | D7: 总登录人数 | E7: 续存人数 | F7: 总存款人数 | G7: 总存款次数 | H7: 总取款人数 | I7: 总取款次数 | J7: 总投注人数 | K7: 总首存 | L7: 总存款额度 | M7: 总取款额度 | N7: 存提差* | O7: 投注 | P7: 有效投注 | Q7: 公司輸贏 (淨贏-淨輸) | R7: 派彩 | S7: 优惠金额 | T7: 返点 | U7: 邀请返佣 | V7: 损益金额* | W7: 存款手续费 | X7: 提款手续费 | Y7: 手续费 | Z7: 平台费10% | AA7: 代理佣金（日） | AB7: 综合性分红 周代理支出 | AC7: 综合性分红 月代理支出 | AD7: 开分 | AE7: 洗分 | AF7: 平台余额 | AG7: 总收益 | AI7: 每人平均存款额 | AJ7: 每人平均投注额 | AK7: 每人平均投注次数
A8: date | B8: Total New Users | C8: no of first time depositors | D8: Login Head Count | E8: Number of survivors | F8: no of total depositors | G8: total deposit counts | H8: no of total withdrawer | I8: total withdrawal counts | J8: no of bettors | K8: total first deposit amount | L8: total deposit amount | M8: total withdrawal amount | N8: Deposit Withdrawal Difference | O8: Betting | P8: valid bet amount | Q8: Company Win/Loss | R8: Payouts | S8: promotion fees | T8: Rebates | U8: Referral rebates | V8: win/loss amount | W8: Deposit fees | X8: Withdrawal fees | Y8: service fees | Z8: Platform fees | AA8: Affiliate Commission (Daily) | AB8: Affiliate Commission (Weekly) | AC8: Affiliate Commission (Monthly) | AD8: Credit Adjustment | AE8: Debit Adjustment | AF8: Platform balance | AG8: Gross Profit | AI8: ave. deposit amount per person | AJ8: ave. bet amount per person | AK8: ave. no. of bets per person
A9: =全平台汇总!A3 -> 46082 | B9: 210 | C9: 68 | D9: 7062 | E9: 9 | F9: 778 | G9: 1471 | H9: 188 | I9: 302 | J9: 3380 | K9: 10500 | L9: 947342 | M9: 986536 | N9: =IF(M9="","",L9-M9) -> -39194 | O9: 4811426.7 | P9: 4453956.1 | Q9: 24190.82 | R9: 4787235.8 | S9: 52918.54 | T9: 12677.43 | U9: 1012.25 | V9: =IF(S9="","",Q9-S9) -> -28727.72 | W9: 22167.8 | X9: 1973.07 | Y9: =W9+X9 -> 24140.87 | Z9: =IF(Q9="","",Q9*10%) -> 2419.082 | AA9: 4450.05 | AB9: 0 | AC9: 0 | AD9: 0 | AE9: -939.17 | AF9: 146987.7 | AG9: =IF(V9="","",V9-Y9-Z9-AB9-AA9) -> -59737.722 | AI9: =L9/F9 -> 1217.6632 | AJ9: =P9/J9 -> 1317.7385 | AK9: =J9/F9 -> 4.344473
A10: =全平台汇总!A4 -> 46083 | B10: 344 | C10: 49 | D10: 5232 | E10: 7 | F10: 645 | G10: 1217 | H10: 142 | I10: 226 | J10: 2828 | K10: 8770 | L10: 782194 | M10: 676723 | N10: =IF(M10="","",L10-M10) -> 105471 | O10: 3876910.4 | P10: 3585660.1 | Q10: 183208.78 | R10: 3693701.6 | S10: 48625.89 | T10: 11728.24 | U10: 596.4 | V10: =IF(S10="","",Q10-S10) -> 134582.89 | W10: 18303.34 | X10: 1353.45 | Y10: =W10+X10 -> 19656.79 | Z10: =IF(Q10="","",Q10*10%) -> 18320.878 | AA10: 6715.34 | AB10: 20006.36 | AC10: 0 | AD10: 0 | AE10: -1100 | AF10: 148203.42 | AG10: =IF(V10="","",V10-Y10-Z10-AB10-AA10) -> 69883.522 | AI10: =L10/F10 -> 1212.7039 | AJ10: =P10/J10 -> 1267.9137 | AK10: =J10/F10 -> 4.3844961
A11: =全平台汇总!A5 -> 46084 | B11: 215 | C11: 42 | D11: 4772 | E11: 3 | F11: 553 | G11: 1128 | H11: 113 | I11: 187 | J11: 2526 | K11: 5717 | L11: 984114 | M11: 917585 | N11: =IF(M11="","",L11-M11) -> 66529 | O11: 6196559.6 | P11: 5642258.8 | Q11: -68531.44 | R11: 6265091 | S11: 39375.5 | T11: 9805.62 | U11: 953.58 | V11: =IF(S11="","",Q11-S11) -> -107906.94 | W11: 23028.27 | X11: 1835.17 | Y11: =W11+X11 -> 24863.44 | Z11: =IF(Q11="","",Q11*10%) -> -6853.144 | AA11: 6443.38 | AB11: 0 | AC11: 0 | AD11: 4094.8 | AE11: -3738.07 | AF11: 211886.15 | AG11: =IF(V11="","",V11-Y11-Z11-AB11-AA11) -> -132360.62 | AI11: =L11/F11 -> 1779.5913 | AJ11: =P11/J11 -> 2233.6733 | AK11: =J11/F11 -> 4.5678119
A12: =全平台汇总!A6 -> 46085 | B12: 126 | C12: 52 | D12: 4716 | E12: 4 | F12: 619 | G12: 1176 | H12: 147 | I12: 227 | J12: 2459 | K12: 8703 | L12: 1277797 | M12: 1271594 | N12: =IF(M12="","",L12-M12) -> 6203 | O12: 11440405 | P12: 10283811 | Q12: 100434.64 | R12: 11339970 | S12: 57690.62 | T12: 11665.14 | U12: 405.99 | V12: =IF(S12="","",Q12-S12) -> 42744.02 | W12: 29900.45 | X12: 2543.19 | Y12: =W12+X12 -> 32443.64 | Z12: =IF(Q12="","",Q12*10%) -> 10043.464 | AA12: 22002.59 | AB12: 0 | AC12: 0 | AD12: 0 | AE12: 0 | AF12: 224591.53 | AG12: =IF(V12="","",V12-Y12-Z12-AB12-AA12) -> -21745.674 | AI12: =L12/F12 -> 2064.2924 | AJ12: =P12/J12 -> 4182.111 | AK12: =J12/F12 -> 3.9725363
A13: =全平台汇总!A7 -> 46086 | B13: 104 | C13: 52 | D13: 4616 | E13: 10 | F13: 590 | G13: 1212 | H13: 149 | I13: 225 | J13: 2480 | K13: 9773 | L13: 1232751 | M13: 1150222 | N13: =IF(M13="","",L13-M13) -> 82529 | O13: 7480831 | P13: 6855643.9 | Q13: 385283.8 | R13: 7095547.2 | S13: 76595.5 | T13: 33059.98 | U13: 607.87 | V13: =IF(S13="","",Q13-S13) -> 308688.3 | W13: 28846.37 | X13: 2300.44 | Y13: =W13+X13 -> 31146.81 | Z13: =IF(Q13="","",Q13*10%) -> 38528.38 | AA13: 33229.8 | AB13: 0 | AC13: 0 | AD13: 0 | AE13: -4451.67 | AF13: 151086.55 | AG13: =IF(V13="","",V13-Y13-Z13-AB13-AA13) -> 205783.31 | AI13: =L13/F13 -> 2089.4085 | AJ13: =P13/J13 -> 2764.3725 | AK13: =J13/F13 -> 4.2033898
A14: =全平台汇总!A8 -> 46087 | B14: 159 | C14: 49 | D14: 4623 | E14: 9 | F14: 557 | G14: 1206 | H14: 133 | I14: 218 | J14: 2485 | K14: 9173 | L14: 1427909 | M14: 1293733 | N14: =IF(M14="","",L14-M14) -> 134176 | O14: 7066722.2 | P14: 6426251.3 | Q14: 108577.25 | R14: 6958145 | S14: 61620.74 | T14: 14878.24 | U14: 477.45 | V14: =IF(S14="","",Q14-S14) -> 46956.51 | W14: 33413.07 | X14: 2587.47 | Y14: =W14+X14 -> 36000.54 | Z14: =IF(Q14="","",Q14*10%) -> 10857.725 | AA14: 22526.98 | AB14: 0 | AC14: 0 | AD14: 0 | AE14: -2025 | AF14: 167292.2 | AG14: =IF(V14="","",V14-Y14-Z14-AB14-AA14) -> -22428.735 | AI14: =L14/F14 -> 2563.5709 | AJ14: =P14/J14 -> 2586.0166 | AK14: =J14/F14 -> 4.4614004
A15: =全平台汇总!A9 -> 46088 | B15: 113 | C15: 53 | D15: 4469 | E15: 8 | F15: 597 | G15: 1196 | H15: 122 | I15: 213 | J15: 2378 | K15: 9236 | L15: 960042 | M15: 817460 | N15: =IF(M15="","",L15-M15) -> 142582 | O15: 5396638 | P15: 5012565.5 | Q15: 231589.85 | R15: 5165048.1 | S15: 49638.91 | T15: 10525.71 | U15: 544.22 | V15: =IF(S15="","",Q15-S15) -> 181950.94 | W15: 22464.98 | X15: 1634.92 | Y15: =W15+X15 -> 24099.9 | Z15: =IF(Q15="","",Q15*10%) -> 23158.985 | AA15: 27825.07 | AB15: 0 | AC15: 0 | AD15: 0 | AE15: 0 | AF15: 183224.91 | AG15: =IF(V15="","",V15-Y15-Z15-AB15-AA15) -> 106866.98 | AI15: =L15/F15 -> 1608.1106 | AJ15: =P15/J15 -> 2107.8913 | AK15: =J15/F15 -> 3.9832496
A16: =全平台汇总!A10 -> 46089 | B16: 113 | C16: 35 | D16: 4681 | E16: 5 | F16: 557 | G16: 1126 | H16: 118 | I16: 211 | J16: 2496 | K16: 5749 | L16: 670093 | M16: 644933 | N16: =IF(M16="","",L16-M16) -> 25160 | O16: 4115104.6 | P16: 3864503.1 | Q16: 180660.32 | R16: 3934444.3 | S16: 46047.27 | T16: 15508.11 | U16: 501.56 | V16: =IF(S16="","",Q16-S16) -> 134613.05 | W16: 15680.18 | X16: 1289.87 | Y16: =W16+X16 -> 16970.05 | Z16: =IF(Q16="","",Q16*10%) -> 18066.032 | AA16: 21037.81 | AB16: 0 | AC16: 0 | AD16: 0 | AE16: 0 | AF16: 173938.86 | AG16: =IF(V16="","",V16-Y16-Z16-AB16-AA16) -> 78539.158 | AI16: =L16/F16 -> 1203.0395 | AJ16: =P16/J16 -> 1548.2785 | AK16: =J16/F16 -> 4.481149
A17: =全平台汇总!A11 -> 46090 | B17: 109 | C17: 37 | D17: 4386 | E17: 3 | F17: 523 | G17: 1162 | H17: 129 | I17: 207 | J17: 2329 | K17: 7409 | L17: 808692 | M17: 646173 | N17: =IF(M17="","",L17-M17) -> 162519 | O17: 5259203 | P17: 4658099.6 | Q17: -67604.49 | R17: 5326807.5 | S17: 46869.78 | T17: 15696.23 | U17: 799.2 | V17: =IF(S17="","",Q17-S17) -> -114474.27 | W17: 18923.39 | X17: 1292.35 | Y17: =W17+X17 -> 20215.74 | Z17: =IF(Q17="","",Q17*10%) -> -6760.449 | AA17: 3918.16 | AB17: 6364.12 | AC17: 0 | AD17: 8529.7 | AE17: 0 | AF17: 305442.97 | AG17: =IF(V17="","",V17-Y17-Z17-AB17-AA17) -> -138211.84 | AI17: =L17/F17 -> 1546.2562 | AJ17: =P17/J17 -> 2000.0428 | AK17: =J17/F17 -> 4.4531549
A18: =全平台汇总!A12 -> 46091 | B18: 109 | C18: 31 | D18: 4330 | E18: 1 | F18: 510 | G18: 1153 | H18: 115 | I18: 207 | J18: 2326 | K18: 6473 | L18: 891305 | M18: 817884 | N18: =IF(M18="","",L18-M18) -> 73421 | O18: 5755020.7 | P18: 5243589.8 | Q18: 336358.45 | R18: 5418662.3 | S18: 45537.02 | T18: 19014.87 | U18: 557.37 | V18: =IF(S18="","",Q18-S18) -> 290821.43 | W18: 20856.54 | X18: 1635.77 | Y18: =W18+X18 -> 22492.31 | Z18: =IF(Q18="","",Q18*10%) -> 33635.845 | AA18: 10151.28 | AB18: 0 | AC18: 0 | AD18: 0 | AE18: 0 | AF18: 195595.06 | AG18: =IF(V18="","",V18-Y18-Z18-AB18-AA18) -> 224541.99 | AI18: =L18/F18 -> 1747.6569 | AJ18: =P18/J18 -> 2254.3378 | AK18: =J18/F18 -> 4.5607843
A19: =全平台汇总!A13 -> 46092 | B19: 102 | C19: 42 | D19: 4288 | E19: 6 | F19: 548 | G19: 1163 | H19: 128 | I19: 215 | J19: 2326 | K19: 6219 | L19: 846902 | M19: 818834 | N19: =IF(M19="","",L19-M19) -> 28068 | O19: 6706426 | P19: 6259857 | Q19: 178647.73 | R19: 6527778.3 | S19: 40993.87 | T19: 15976.25 | U19: 366.74 | V19: =IF(S19="","",Q19-S19) -> 137653.86 | W19: 19817.51 | X19: 1637.67 | Y19: =W19+X19 -> 21455.18 | Z19: =IF(Q19="","",Q19*10%) -> 17864.773 | AA19: 3174.24 | AB19: 0 | AC19: 0 | AD19: 0 | AE19: -1800.02 | AF19: 231270.97 | AG19: =IF(V19="","",V19-Y19-Z19-AB19-AA19) -> 95159.667 | AI19: =L19/F19 -> 1545.4416 | AJ19: =P19/J19 -> 2691.2541 | AK19: =J19/F19 -> 4.2445255
A20: =全平台汇总!A14 -> 46093 | B20: 90 | C20: 45 | D20: 4697 | E20: 2 | F20: 588 | G20: 1218 | H20: 129 | I20: 213 | J20: 2516 | K20: 13211 | L20: 760915 | M20: 500427 | N20: =IF(M20="","",L20-M20) -> 260488 | O20: 4796791.5 | P20: 4447420.3 | Q20: 205576.56 | R20: 4591214.9 | S20: 48382.54 | T20: 10286 | U20: 406.85 | V20: =IF(S20="","",Q20-S20) -> 157194.02 | W20: 17805.41 | X20: 1000.85 | Y20: =W20+X20 -> 18806.26 | Z20: =IF(Q20="","",Q20*10%) -> 20557.656 | AA20: 5413.39 | AB20: 0 | AC20: 0 | AD20: 0 | AE20: -10104.66 | AF20: 229354.65 | AG20: =IF(V20="","",V20-Y20-Z20-AB20-AA20) -> 112416.71 | AI20: =L20/F20 -> 1294.0731 | AJ20: =P20/J20 -> 1767.6551 | AK20: =J20/F20 -> 4.2789116
A21: =全平台汇总!A15 -> 46094 | N21: =IF(M21="","",L21-M21) | V21: =IF(S21="","",Q21-S21) | Y21: =W21+X21 -> 0 | Z21: =IF(Q21="","",Q21*10%) | AG21: =IF(V21="","",V21-Y21-Z21-AB21-AA21) | AI21: =L21/F21 -> #DIV/0! | AJ21: =P21/J21 -> #DIV/0! | AK21: =J21/F21 -> #DIV/0!
A22: =全平台汇总!A16 -> 46095 | N22: =IF(M22="","",L22-M22) | V22: =IF(S22="","",Q22-S22) | Y22: =W22+X22 -> 0 | Z22: =IF(Q22="","",Q22*10%) | AG22: =IF(V22="","",V22-Y22-Z22-AB22-AA22) | AI22: =L22/F22 -> #DIV/0! | AJ22: =P22/J22 -> #DIV/0! | AK22: =J22/F22 -> #DIV/0!
A23: =全平台汇总!A17 -> 46096 | N23: =IF(M23="","",L23-M23) | V23: =IF(S23="","",Q23-S23) | Y23: =W23+X23 -> 0 | Z23: =IF(Q23="","",Q23*10%) | AG23: =IF(V23="","",V23-Y23-Z23-AB23-AA23) | AI23: =L23/F23 -> #DIV/0! | AJ23: =P23/J23 -> #DIV/0! | AK23: =J23/F23 -> #DIV/0!
A24: =全平台汇总!A18 -> 46097 | N24: =IF(M24="","",L24-M24) | V24: =IF(S24="","",Q24-S24) | Y24: =W24+X24 -> 0 | Z24: =IF(Q24="","",Q24*10%) | AG24: =IF(V24="","",V24-Y24-Z24-AB24-AA24) | AI24: =L24/F24 -> #DIV/0! | AJ24: =P24/J24 -> #DIV/0! | AK24: =J24/F24 -> #DIV/0!
A25: =全平台汇总!A19 -> 46098 | N25: =IF(M25="","",L25-M25) | V25: =IF(S25="","",Q25-S25) | Y25: =W25+X25 -> 0 | Z25: =IF(Q25="","",Q25*10%) | AG25: =IF(V25="","",V25-Y25-Z25-AB25-AA25) | AI25: =L25/F25 -> #DIV/0! | AJ25: =P25/J25 -> #DIV/0! | AK25: =J25/F25 -> #DIV/0!
A26: =全平台汇总!A20 -> 46099 | N26: =IF(M26="","",L26-M26) | V26: =IF(S26="","",Q26-S26) | Y26: =W26+X26 -> 0 | Z26: =IF(Q26="","",Q26*10%) | AG26: =IF(V26="","",V26-Y26-Z26-AB26-AA26) | AI26: =L26/F26 -> #DIV/0! | AJ26: =P26/J26 -> #DIV/0! | AK26: =J26/F26 -> #DIV/0!
A27: =全平台汇总!A21 -> 46100 | N27: =IF(M27="","",L27-M27) | V27: =IF(S27="","",Q27-S27) | Y27: =W27+X27 -> 0 | Z27: =IF(Q27="","",Q27*10%) | AG27: =IF(V27="","",V27-Y27-Z27-AB27-AA27) | AI27: =L27/F27 -> #DIV/0! | AJ27: =P27/J27 -> #DIV/0! | AK27: =J27/F27 -> #DIV/0!
A28: =全平台汇总!A22 -> 46101 | N28: =IF(M28="","",L28-M28) | V28: =IF(S28="","",Q28-S28) | Y28: =W28+X28 -> 0 | Z28: =IF(Q28="","",Q28*10%) | AG28: =IF(V28="","",V28-Y28-Z28-AB28-AA28) | AI28: =L28/F28 -> #DIV/0! | AJ28: =P28/J28 -> #DIV/0! | AK28: =J28/F28 -> #DIV/0!
A29: =全平台汇总!A23 -> 46102 | N29: =IF(M29="","",L29-M29) | V29: =IF(S29="","",Q29-S29) | Y29: =W29+X29 -> 0 | Z29: =IF(Q29="","",Q29*10%) | AG29: =IF(V29="","",V29-Y29-Z29-AB29-AA29) | AI29: =L29/F29 -> #DIV/0! | AJ29: =P29/J29 -> #DIV/0! | AK29: =J29/F29 -> #DIV/0!
A30: =全平台汇总!A24 -> 46103 | N30: =IF(M30="","",L30-M30) | V30: =IF(S30="","",Q30-S30) | Y30: =W30+X30 -> 0 | Z30: =IF(Q30="","",Q30*10%) | AG30: =IF(V30="","",V30-Y30-Z30-AB30-AA30) | AI30: =L30/F30 -> #DIV/0! | AJ30: =P30/J30 -> #DIV/0! | AK30: =J30/F30 -> #DIV/0!
A31: =全平台汇总!A25 -> 46104 | N31: =IF(M31="","",L31-M31) | V31: =IF(S31="","",Q31-S31) | Y31: =W31+X31 -> 0 | Z31: =IF(Q31="","",Q31*10%) | AG31: =IF(V31="","",V31-Y31-Z31-AB31-AA31) | AI31: =L31/F31 -> #DIV/0! | AJ31: =P31/J31 -> #DIV/0! | AK31: =J31/F31 -> #DIV/0!
A32: =全平台汇总!A26 -> 46105 | N32: =IF(M32="","",L32-M32) | V32: =IF(S32="","",Q32-S32) | Y32: =W32+X32 -> 0 | Z32: =IF(Q32="","",Q32*10%) | AG32: =IF(V32="","",V32-Y32-Z32-AB32-AA32) | AI32: =L32/F32 -> #DIV/0! | AJ32: =P32/J32 -> #DIV/0! | AK32: =J32/F32 -> #DIV/0!
... A39: =全平台汇总!A33 -> 46112 | N39: =IF(M39="","",L39-M39) | V39: =IF(S39="","",Q39-S39) | Y39: =W39+X39 -> 0 | Z39: =IF(Q39="","",Q39*10%) | AG39: =IF(V39="","",V39-Y39-Z39-AB39-AA39) | AI39: =L39/F39 -> #DIV/0! | AJ39: =P39/J39 -> #DIV/0! | AK39: =J39/F39 -> #DIV/0!
A40: 总额 total | B40: =SUM(B9:B39) -> 1794 | C40: =SUM(C9:C39) -> 555 | D40: =SUM(D9:D39) -> 57872 | E40: =SUM(E9:E39) -> 67 | F40: =SUM(F9:F39) -> 7065 | G40: =SUM(G9:G39) -> 14428 | H40: =SUM(H9:H39) -> 1613 | I40: =SUM(I9:I39) -> 2651 | ... AG40: =SUM(AG9:AG39) -> 518706.76 | AI40: =L40/F40 -> 1640.4892 | AJ40: =P40/J40 -> 2185.909 | AK40: =J40/F40 -> 4.3211607
A41: 备注：手續費以入款5.5%, 出款0.25%計算
W42: 次月初5号更改

Sheet Sugarplay
A2: =WP!A2 -> 3月 | B2: 注册人数 | C2: 首充人数 | D2: 总登录人数 | L2: 总存款 | N2: 总取款 | O2: 存取差 | P2: 投注 | Q2: 投注额 | R2: 结算 | S2: 派彩 | T2: 优惠 | U2: 返点 | V2: 邀请返佣 | W2: 损益 | X2: 存款手续费 | Y2: 提款手续费 | Z2: 支付手续费 | AA2: 平台费 | AB2: 日返水 | AC2: 周代理支出 | AD2: 月代理支出 | AE2: 开分 | AF2: 洗分 | AG2: 平台余额 | AH2: 总收益
A3: 合计 | B3: =SUM(B9:B39) -> 1505 | C3: =SUM(C9:C39) -> 388 | D3: =SUM(D9:D39) -> 34970 | L3: =SUM(L9:L39) -> 19883649 | N3: =SUM(N9:N39) -> 16373909 | O3: =SUM(O9:O39) -> 3509740 | P3: =SUM(P9:P39) -> 1.4851175e+08 | Q3: =SUM(Q9:Q39) -> 1.4709334e+08 | R3: =SUM(R9:R39) -> 5754026.7 | S3: =SUM(S9:S39) -> 1.4275773e+08 | T3: =SUM(T9:T39) -> 1707758 | U3: =SUM(U9:U39) -> 449732.92 | ... AH3: =SUM(AH9:AH39) -> 2222306.5
A4: 日均 | B4: =AVERAGE(B9:B39) -> 125.41667 | C4: =AVERAGE(C9:C39) -> 32.333333 | D4: =AVERAGE(D9:D39) -> 2914.1667 | L4: =AVERAGE(L9:L39) -> 1656970.8 | N4: =AVERAGE(N9:N39) -> 528190.61 | O4: =AVERAGE(O9:O39) -> 113217.42 | P4: =AVERAGE(P9:P39) -> 12375979 | Q4: =AVERAGE(Q9:Q39) -> 12257778 | R4: =AVERAGE(R9:R39) -> 479502.22 | S4: =AVERAGE(S9:S39) -> 11896477 | T4: =AVERAGE(T9:T39) -> 142313.17 | U4: =AVERAGE(U9:U39) -> 37477.743 | ... AH4: =AVERAGE(AH9:AH39) -> 185192.2
A6: SUGARPLAY 每日数据
A7: 日期 | B7: 总新注册人数 | C7: 总首充人数 | D7: 总登录人数 | E7: 续存人数 | F7: 总存款人数 | G7: 总存款次数 | H7: 总取款人数 | I7: 总取款次数 | J7: 总投注人数 | K7: 总首存 | L7: 总存款额度 | N7: 总取款额度 | O7: 存提差* | P7: 投注 | Q7: 有效投注 | R7: 公司輸贏 (淨贏-淨輸) | S7: 派彩 | T7: 优惠金额 | U7: 返点 | V7: 邀请返佣 | W7: 损益金额* | X7: 存款手续费 | Y7: 提款手续费 | Z7: 支付手续费 | AA7: 平台费12% | AB7: 日返水 | AC7: 综合性分红 日代理支出 | AD7: 综合性分红 月代理支出 | AE7: 开分 | AF7: 洗分 | AG7: 平台余额 | AH7: 总收益 | AJ7: 每人平均存款额 | AK7: 每人平均投注额 | AL7: 每人平均投注次数
A8: date | B8: Total New Users | C8: first depositor / no of first time depositors | D8: Login Head Count | E8: Number of survivors | F8: no of total depositors | G8: depsoit times / total deposit counts | H8: no of total withdrawer | I8: withdrawal times / total withdrawal counts | J8: no of bettors / No of bet | K8: total first deposit amount | L8: total deposit amount | N8: total withdrawal amount | O8: Deposit Withdrawal Difference | P8: Betting | Q8: valid bet amount | R8: Company Win/Loss | S8: Payouts | T8: promotion fees / Total Bonus | U8: Rebates | V8: Referral rebates | W8: win/loss amount,Company Net Profit | X8: Deposit fees | Y8: Withdrawal fees | Z8: service fees (Payment Channel Fee) | AA8: Platform fees | AB8: Daily rebate | AC8: Affiliate Commission (Day) | AD8: Affiliate Commission (Monthly) | AE8: Credit Adjustment | AF8: Debit Adjustment | AG8: Platform balance | AH8: Gross Profit | AJ8: ave. deposit amount per person | AK8: ave. bet amount per person | AL8: ave. no. of bets per person
A9: =全平台汇总!A3 -> 46082 | B9: 183 | C9: 48 | D9: 3504 | E9: 897 | F9: 934 | G9: 1843 | H9: 244 | I9: 371 | J9: 3460 | K9: 41408 | L9: 1285351 | M9: 1354182 | N9: =M9+AC9+AB9 -> 1354182 | O9: =IF(N9="","",L9-N9) -> -68831 | P9: 10922963 | Q9: 10899132 | R9: 229332.53 | S9: 10693630 | T9: 165160.32 | U9: 42141.55 | V9: 70 | W9: =IF(T9="","",R9-T9) -> 64172.21 | X9: 28535 | Y9: 2708 | Z9: =X9+Y9 -> 31243 | AA9: =IF(R9="","",R9*12%) -> 27519.904 | AB9: 0 | AC9: 0 | AD9: 0 | AE9: 0 | AF9: 0 | AG9: 1355085.2 | AH9: =IF(W9="","",W9-Z9-AC9-AA9-AB9) -> 5409.3064 | AJ9: =L9/F9 -> 1376.1788 | AK9: =Q9/J9 -> 3150.0382 | AL9: =J9/F9 -> 3.7044968
A10: =全平台汇总!A4 -> 46083 | B10: 99 | C10: 37 | D10: 2798 | E10: 828 | F10: 859 | G10: 1836 | H10: 210 | I10: 320 | J10: 2720 | K10: 22965 | L10: 1399133 | M10: 1256790 | N10: =M10+AC10+AB10 -> 1476106 | O10: =IF(N10="","",L10-N10) -> -76973 | P10: 10883167 | Q10: 10702084 | R10: 178477.74 | S10: 10704689 | T10: 129215.77 | U10: 33640.86 | V10: 100 | W10: =IF(T10="","",R10-T10) -> 49261.97 | X10: 31061 | Y10: 2952 | Z10: =X10+Y10 -> 34013 | AA10: =IF(R10="","",R10*12%) -> 21417.329 | AB10: 0 | AC10: 219316 | AD10: 0 | AE10: 0 | AF10: 0 | AG10: 1279106 | AH10: =IF(W10="","",W10-Z10-AC10-AA10-AB10) -> -225484.36 | AJ10: =L10/F10 -> 1628.7928 | AK10: =Q10/J10 -> 3934.5896 | AL10: =J10/F10 -> 3.1664726
A11: =全平台汇总!A5 -> 46084 | B11: 103 | C11: 27 | D11: 2641 | E11: 759 | F11: 782 | G11: 1698 | H11: 186 | I11: 282 | J11: 2576 | K11: 10850 | L11: 1594902 | M11: 1059363 | N11: =M11+AC11+AB11 -> 1064018 | O11: =IF(N11="","",L11-N11) -> 530884 | P11: 14781276 | Q11: 14708156 | R11: 531983.63 | S11: 14249292 | T11: 92985.31 | U11: 30298.43 | V11: 100 | W11: =IF(T11="","",R11-T11) -> 438998.32 | X11: 35407 | Y11: 2128 | Z11: =X11+Y11 -> 37535 | AA11: =IF(R11="","",R11*12%) -> 63838.036 | AB11: 0 | AC11: 4655 | AD11: 0 | AE11: 10000 | AF11: 0 | AG11: 1257784.7 | AH11: =IF(W11="","",W11-Z11-AC11-AA11-AB11) -> 332970.28 | AJ11: =L11/F11 -> 2039.5166 | AK11: =Q11/J11 -> 5709.6879 | AL11: =J11/F11 -> 3.2941176
A12: =全平台汇总!A6 -> 46085 | B12: 93 | C12: 33 | D12: 2505 | E12: 783 | F12: 806 | G12: 1805 | H12: 209 | I12: 328 | J12: 2459 | K12: 7059 | L12: 1810164 | M12: 1559197 | N12: =M12+AC12+AB12 -> 1559355 | O12: =IF(N12="","",L12-N12) -> 250809 | P12: 13126243 | Q12: 13029935 | R12: 302128.05 | S12: 12824115 | T12: 143505.79 | U12: 53868.3 | V12: 150 | W12: =IF(T12="","",R12-T12) -> 158622.26 | X12: 40186 | Y12: 3119 | Z12: =X12+Y12 -> 43305 | AA12: =IF(R12="","",R12*12%) -> 36255.366 | AB12: 0 | AC12: 158 | AD12: 0 | AE12: 0 | AF12: 0 | AG12: 1460134.1 | AH12: =IF(W12="","",W12-Z12-AC12-AA12-AB12) -> 78903.894 | AJ12: =L12/F12 -> 2245.861 | AK12: =Q12/J12 -> 5298.8757 | AL12: =J12/F12 -> 3.0508685
A13: =全平台汇总!A7 -> 46086 | B13: 125 | C13: 25 | D13: 2644 | E13: 771 | F13: 791 | G13: 1881 | H13: 202 | I13: 330 | J13: 2571 | K13: 3725 | L13: 2064997 | M13: 1395049 | N13: =M13+AC13+AB13 -> 1395549 | O13: =IF(N13="","",L13-N13) -> 669448 | P13: 18016768 | Q13: 17886960 | R13: 600122.63 | S13: 17416645 | T13: 149042 | U13: 34139.71 | V13: 100 | W13: =IF(T13="","",R13-T13) -> 451080.63 | X13: 45843 | Y13: 2791 | Z13: =X13+Y13 -> 48634 | AA13: =IF(R13="","",R13*12%) -> 72014.716 | AB13: 0 | AC13: 500 | AD13: 0 | AE13: 0 | AF13: 0 | AG13: 1599278.2 | AH13: =IF(W13="","",W13-Z13-AC13-AA13-AB13) -> 329931.91 | AJ13: =L13/F13 -> 2610.6157 | AK13: =Q13/J13 -> 6957.1995 | AL13: =J13/F13 -> 3.2503161
A14: =全平台汇总!A8 -> 46087 | B14: 200 | C14: 39 | D14: 4137 | E14: 785 | F14: 815 | G14: 1845 | H14: 247 | I14: 379 | J14: 4020 | K14: 9050 | L14: 1888874 | M14: 1768241 | N14: =M14+AC14+AB14 -> 1768841 | O14: =IF(N14="","",L14-N14) -> 120033 | P14: 17044697 | Q14: 16683347 | R14: 841471.48 | S14: 16203225 | T14: 241966.07 | U14: 70994.6 | V14: 50 | W14: =IF(T14="","",R14-T14) -> 599505.41 | X14: 41933 | Y14: 3538 | Z14: =X14+Y14 -> 45471 | AA14: =IF(R14="","",R14*12%) -> 100976.58 | AB14: 0 | AC14: 600 | AD14: 0 | AE14: 0 | AF14: 0 | AG14: 1258120 | AH14: =IF(W14="","",W14-Z14-AC14-AA14-AB14) -> 452457.83 | AJ14: =L14/F14 -> 2317.6368 | AK14: =Q14/J14 -> 4150.0864 | AL14: =J14/F14 -> 4.9325153
A15: =全平台汇总!A9 -> 46088 | B15: 131 | C15: 36 | D15: 3122 | E15: 809 | F15: 843 | G15: 1904 | H15: 230 | I15: 333 | J15: 3083 | K15: 9807 | L15: 1495925 | M15: 842535 | N15: =M15+AC15+AB15 -> 846633 | O15: =IF(N15="","",L15-N15) -> 649292 | P15: 11404122 | Q15: 11198771 | R15: 869270.22 | S15: 10534852 | T15: 131429.53 | U15: 51073.99 | V15: 150 | W15: =IF(T15="","",R15-T15) -> 737840.69 | X15: 33210 | Y15: 1693 | Z15: =X15+Y15 -> 34903 | AA15: =IF(R15="","",R15*12%) -> 104312.43 | AB15: 0 | AC15: 4098 | AD15: 0 | AE15: 0 | AF15: 0 | AG15: 1232904.9 | AH15: =IF(W15="","",W15-Z15-AC15-AA15-AB15) -> 594527.26 | AJ15: =L15/F15 -> 1774.5255 | AK15: =Q15/J15 -> 3632.4266 | AL15: =J15/F15 -> 3.6571767
A16: =全平台汇总!A10 -> 46089 | B16: 105 | C16: 33 | D16: 2871 | E16: 799 | F16: 825 | G16: 1821 | H16: 214 | I16: 320 | J16: 2797 | K16: 9629 | L16: 1463304 | M16: 1168496 | N16: =M16+AC16+AB16 -> 1168496 | O16: =IF(N16="","",L16-N16) -> 294808 | P16: 10341994 | Q16: 10323746 | R16: 274927.59 | S16: 10067067 | T16: 129357.68 | U16: 28447.45 | V16: 170 | W16: =IF(T16="","",R16-T16) -> 145569.91 | X16: 32485 | Y16: 2337 | Z16: =X16+Y16 -> 34822 | AA16: =IF(R16="","",R16*12%) -> 32991.311 | AB16: 0 | AC16: 0 | AD16: 0 | AE16: 0 | AF16: 0 | AG16: 1372751.5 | AH16: =IF(W16="","",W16-Z16-AC16-AA16-AB16) -> 77756.599 | AJ16: =L16/F16 -> 1773.7018 | AK16: =Q16/J16 -> 3691.0069 | AL16: =J16/F16 -> 3.390303
A17: =全平台汇总!A11 -> 46090 | B17: 146 | C17: 42 | D17: 2835 | E17: 751 | F17: 774 | G17: 1812 | H17: 228 | I17: 355 | J17: 2787 | K17: 15375 | L17: 1542303 | M17: 1177530 | N17: =M17+AC17+AB17 -> 1563266 | O17: =IF(N17="","",L17-N17) -> -20963 | P17: 10838622 | Q17: 10764688 | R17: 492829.36 | S17: 10345793 | T17: 145159.67 | U17: 24098.15 | V17: 150 | W17: =IF(T17="","",R17-T17) -> 347669.69 | X17: 34239 | Y17: 3127 | Z17: =X17+Y17 -> 37366 | AA17: =IF(R17="","",R17*12%) -> 59139.523 | AB17: 0 | AC17: 385736 | AD17: 0 | AE17: 0 | AF17: -2014 | AG17: 1300577.3 | AH17: =IF(W17="","",W17-Z17-AC17-AA17-AB17) -> -134571.83 | AJ17: =L17/F17 -> 1992.6395 | AK17: =Q17/J17 -> 3862.4644 | AL17: =J17/F17 -> 3.6007752
A18: =全平台汇总!A12 -> 46091 | B18: 109 | C18: 28 | D18: 2655 | E18: 781 | F18: 805 | G18: 1743 | H18: 196 | I18: 307 | J18: 2585 | K18: 7380 | L18: 1627575 | M18: 1313388 | N18: =M18+AC18+AB18 -> 1357111 | O18: =IF(N18="","",L18-N18) -> 270464 | P18: 10645996 | Q18: 10528848 | R18: 289862.74 | S18: 10356133 | T18: 112009.45 | U18: 27799.09 | V18: 0 | W18: =IF(T18="","",R18-T18) -> 177853.29 | X18: 36132 | Y18: 2714 | Z18: =X18+Y18 -> 38846 | AA18: =IF(R18="","",R18*12%) -> 34783.529 | AB18: 0 | AC18: 43723 | AD18: 0 | AE18: 0 | AF18: -2000 | AG18: 1296394.5 | AH18: =IF(W18="","",W18-Z18-AC18-AA18-AB18) -> 60500.761 | AJ18: =L18/F18 -> 2021.8323 | AK18: =Q18/J18 -> 4073.0551 | AL18: =J18/F18 -> 3.2111801
A19: =全平台汇总!A13 -> 46092 | B19: 103 | C19: 14 | D19: 2675 | E19: 753 | F19: 764 | G19: 1677 | H19: 193 | I19: 306 | J19: 2606 | K19: 2066 | L19: 1802411 | M19: 1344295 | N19: =M19+AC19+AB19 -> 1344631 | O19: =IF(N19="","",L19-N19) -> 457780 | P19: 10692893 | Q19: 10571941 | R19: 743539.83 | S19: 9949353.6 | T19: 130828.92 | U19: 26509.31 | V19: 100 | W19: =IF(T19="","",R19-T19) -> 612710.91 | X19: 40014 | Y19: 2689 | Z19: =X19+Y19 -> 42703 | AA19: =IF(R19="","",R19*12%) -> 89224.78 | AB19: 0 | AC19: 336 | AD19: 0 | AE19: 0 | AF19: 0 | AG19: 1238555.3 | AH19: =IF(W19="","",W19-Z19-AC19-AA19-AB19) -> 480447.13 | AJ19: =L19/F19 -> 2359.1767 | AK19: =Q19/J19 -> 4056.7693 | AL19: =J19/F19 -> 3.4109948
A20: =全平台汇总!A14 -> 46093 | B20: 108 | C20: 26 | D20: 2583 | E20: 731 | F20: 753 | G20: 1758 | H20: 212 | I20: 339 | J20: 2523 | K20: 5449 | L20: 1908710 | M20: 1475529 | N20: =M20+AC20+AB20 -> 1475721 | O20: =IF(N20="","",L20-N20) -> 432989 | P20: 9813012.6 | Q20: 9795730.1 | R20: 400080.86 | S20: 9412931.7 | T20: 137097.5 | U20: 26721.48 | V20: 150 | W20: =IF(T20="","",R20-T20) -> 262983.36 | X20: 42373 | Y20: 2951 | Z20: =X20+Y20 -> 45324 | AA20: =IF(R20="","",R20*12%) -> 48009.703 | AB20: 0 | AC20: 192 | AD20: 0 | AE20: 0 | AF20: 0 | AG20: 1327569.3 | AH20: =IF(W20="","",W20-Z20-AC20-AA20-AB20) -> 169457.66 | AJ20: =L20/F20 -> 2534.8074 | AK20: =Q20/J20 -> 3882.5724 | AL20: =J20/F20 -> 3.3505976
A21: =全平台汇总!A15 -> 46094 | N21: =M21+AC21+AB21 -> 0 | O21: =IF(N21="","",L21-N21) -> 0 | W21: =IF(T21="","",R21-T21) | Z21: =X21+Y21 -> 0 | AA21: =IF(R21="","",R21*12%) | AH21: =IF(W21="","",W21-Z21-AC21-AA21-AB21) | AJ21: =L21/F21 -> #DIV/0! | AK21: =Q21/J21 -> #DIV/0! | AL21: =J21/F21 -> #DIV/0!
A22: =全平台汇总!A16 -> 46095 | N22: =M22+AC22+AB22 -> 0 | O22: =IF(N22="","",L22-N22) -> 0 | W22: =IF(T22="","",R22-T22) | Z22: =X22+Y22 -> 0 | AA22: =IF(R22="","",R22*12%) | AH22: =IF(W22="","",W22-Z22-AC22-AA22-AB22) | AJ22: =L22/F22 -> #DIV/0! | AK22: =Q22/J22 -> #DIV/0! | AL22: =J22/F22 -> #DIV/0!
A23: =全平台汇总!A17 -> 46096 | N23: =M23+AC23+AB23 -> 0 | O23: =IF(N23="","",L23-N23) -> 0 | W23: =IF(T23="","",R23-T23) | Z23: =X23+Y23 -> 0 | AA23: =IF(R23="","",R23*12%) | AH23: =IF(W23="","",W23-Z23-AC23-AA23-AB23) | AJ23: =L23/F23 -> #DIV/0! | AK23: =Q23/J23 -> #DIV/0! | AL23: =J23/F23 -> #DIV/0!
A24: =全平台汇总!A18 -> 46097 | N24: =M24+AC24+AB24 -> 0 | O24: =IF(N24="","",L24-N24) -> 0 | W24: =IF(T24="","",R24-T24) | Z24: =X24+Y24 -> 0 | AA24: =IF(R24="","",R24*12%) | AH24: =IF(W24="","",W24-Z24-AC24-AA24-AB24) | AJ24: =L24/F24 -> #DIV/0! | AK24: =Q24/J24 -> #DIV/0! | AL24: =J24/F24 -> #DIV/0!
A25: =全平台汇总!A19 -> 46098 | N25: =M25+AC25+AB25 -> 0 | O25: =IF(N25="","",L25-N25) -> 0 | W25: =IF(T25="","",R25-T25) | Z25: =X25+Y25 -> 0 | AA25: =IF(R25="","",R25*12%) | AH25: =IF(W25="","",W25-Z25-AC25-AA25-AB25) | AJ25: =L25/F25 -> #DIV/0! | AK25: =Q25/J25 -> #DIV/0! | AL25: =J25/F25 -> #DIV/0!
A26: =全平台汇总!A20 -> 46099 | N26: =M26+AC26+AB26 -> 0 | O26: =IF(N26="","",L26-N26) -> 0 | W26: =IF(T26="","",R26-T26) | Z26: =X26+Y26 -> 0 | AA26: =IF(R26="","",R26*12%) | AH26: =IF(W26="","",W26-Z26-AC26-AA26-AB26) | AJ26: =L26/F26 -> #DIV/0! | AK26: =Q26/J26 -> #DIV/0! | AL26: =J26/F26 -> #DIV/0!
A27: =全平台汇总!A21 -> 46100 | N27: =M27+AC27+AB27 -> 0 | O27: =IF(N27="","",L27-N27) -> 0 | W27: =IF(T27="","",R27-T27) | Z27: =X27+Y27 -> 0 | AA27: =IF(R27="","",R27*12%) | AH27: =IF(W27="","",W27-Z27-AC27-AA27-AB27) | AJ27: =L27/F27 -> #DIV/0! | AK27: =Q27/J27 -> #DIV/0! | AL27: =J27/F27 -> #DIV/0!
A28: =全平台汇总!A22 -> 46101 | N28: =M28+AC28+AB28 -> 0 | O28: =IF(N28="","",L28-N28) -> 0 | W28: =IF(T28="","",R28-T28) | Z28: =X28+Y28 -> 0 | AA28: =IF(R28="","",R28*12%) | AH28: =IF(W28="","",W28-Z28-AC28-AA28-AB28) | AJ28: =L28/F28 -> #DIV/0! | AK28: =Q28/J28 -> #DIV/0! | AL28: =J28/F28 -> #DIV/0!
A29: =全平台汇总!A23 -> 46102 | N29: =M29+AC29+AB29 -> 0 | O29: =IF(N29="","",L29-N29) -> 0 | W29: =IF(T29="","",R29-T29) | Z29: =X29+Y29 -> 0 | AA29: =IF(R29="","",R29*12%) | AH29: =IF(W29="","",W29-Z29-AC29-AA29-AB29) | AJ29: =L29/F29 -> #DIV/0! | AK29: =Q29/J29 -> #DIV/0! | AL29: =J29/F29 -> #DIV/0!
A30: =全平台汇总!A24 -> 46103 | N30: =M30+AC30+AB30 -> 0 | O30: =IF(N30="","",L30-N30) -> 0 | W30: =IF(T30="","",R30-T30) | Z30: =X30+Y30 -> 0 | AA30: =IF(R30="","",R30*12%) | AH30: =IF(W30="","",W30-Z30-AC30-AA30-AB30) | AJ30: =L30/F30 -> #DIV/0! | AK30: =Q30/J30 -> #DIV/0! | AL30: =J30/F30 -> #DIV/0!
A31: =全平台汇总!A25 -> 46104 | N31: =M31+AC31+AB31 -> 0 | O31: =IF(N31="","",L31-N31) -> 0 | W31: =IF(T31="","",R31-T31) | Z31: =X31+Y31 -> 0 | AA31: =IF(R31="","",R31*12%) | AH31: =IF(W31="","",W31-Z31-AC31-AA31-AB31) | AJ31: =L31/F31 -> #DIV/0! | AK31: =Q31/J31 -> #DIV/0! | AL31: =J31/F31 -> #DIV/0!
A32: =全平台汇总!A26 -> 46105 | N32: =M32+AC32+AB32 -> 0 | O32: =IF(N32="","",L32-N32) -> 0 | W32: =IF(T32="","",R32-T32) | Z32: =X32+Y32 -> 0 | AA32: =IF(R32="","",R32*12%) | AH32: =IF(W32="","",W32-Z32-AC32-AA32-AB32) | AJ32: =L32/F32 -> #DIV/0! | AK32: =Q32/J32 -> #DIV/0! | AL32: =J32/F32 -> #DIV/0!
... A39: =全平台汇总!A33 -> 46112 | N39: =M39+AC39+AB39 -> 0 | O39: =IF(N39="","",L39-N39) -> 0 | W39: =IF(T39="","",R39-T39) | Z39: =X39+Y39 -> 0 | AA39: =IF(R39="","",R39*12%) | AH39: =IF(W39="","",W39-Z39-AC39-AA39-AB39) | AJ39: =L39/F39 -> #DIV/0! | AK39: =Q39/J39 -> #DIV/0! | AL39: =J39/F39 -> #DIV/0!
A40: 总额 total | B40: =SUM(B9:B39) -> 1505 | C40: =SUM(C9:C39) -> 388 | D40: =SUM(D9:D39) -> 34970 | E40: =SUM(E9:E39) -> 9447 | F40: =SUM(F9:F39) -> 9751 | G40: =SUM(G9:G39) -> 21623 | H40: =SUM(H9:H39) -> 2571 | I40: =SUM(I9:I39) -> 3970 | ... AH40: =SUM(AH9:AH39) -> 2222306.5 | AJ40: =L40/F40 -> 2039.1395 | AK40: =Q40/J40 -> 4302.6103 | AL40: =J40/F40 -> 3.5059994
A41: 备注：支付手續費以收款 4%計/ 出款 0.5%
X42: 次月初5号更改

Sheet WP_ro
A1: WP财务报表
A2: 日期 | B2: 总登录人数 | E2: 总新注册人数 | H2: 总首充人数 | K2: 总存款人数 | N2: 总存款次数 | Q2: 总首存 | T2: 总存款额度 | W2: 当月 每人平均存款额 | X2: 总投注人数 | AA2: 有效投注 | AD2: 当月 每人平均投注额 | AE2: 当月 每人平均投注次数 | AF2: 总取款人数 | AI2: 总取款次数 | AL2: 总取款额度 | AO2: 公司輸贏 (淨贏-淨輸) | AR2: 总收益
A3: date | B3: Login Head Count | E3: Total New Users | H3: no of first time depositors | K3: no of total depositors | N3: total deposit counts | Q3: total first deposit amount | T3: total deposit amount | W3: ave. deposit amount per person | X3: no of bettors | AA3: valid bet amount | AD3: ave. bet amount per person | AE3: ave. no. of bets per person | AF3: no of total withdrawer | AI3: total withdrawal counts | AL3: total withdrawal amount | AO3: Company Win/Loss | AR3: Gross Profit
B4: 本月日数据 | C4: 上月日数据 | D4: 同比增长率 | E4: 本月数据 | F4: 上月数据 | G4: 增长率 | H4: 本月数据 | I4: 上月数据 | J4: 增长率 | K4: 本月数据 | L4: 上月数据 | M4: 增长率 | N4: 本月数据 | O4: 上月数据 | P4: 增长率 | Q4: 本月数据 | R4: 上月数据 | S4: 增长率 | T4: 本月数据 | U4: 上月数据 | V4: 增长率 | X4: 本月数据 | Y4: 上月数据 | Z4: 增长率 | AA4: 本月数据 | AB4: 上月数据 | AC4: 增长率 | AF4: 本月数据 | AG4: 上月数据 | AH4: 增长率 | AI4: 本月数据 | AJ4: 上月数据 | AK4: 增长率 | AL4: 本月数据 | AM4: 上月数据 | AN4: 增长率 | AO4: 本月数据 | AP4: 上月数据 | AQ4: 增长率 | AR4: 本月数据 | AS4: 上月数据 | AT4: 增长率
A5: =全平台汇总!A3 -> 46082 | B5: =WP!D9 -> 7540 | C5: ='2026年2月WP'!D9 -> 6426 | D5: =(B5-C5)/C5 -> 0.17335823 | E5: =WP!B9 -> 206 | F5: ='2026年2月WP'!B9 -> 264 | G5: =(E5-F5)/F5 -> -0.21969697 | H5: =WP!C9 -> 94 | I5: ='2026年2月WP'!C9 -> 106 | J5: =(H5-I5)/I5 -> -0.11320755 | K5: =WP!F9 -> 1784 | L5: ='2026年2月WP'!F9 -> 1719 | M5: =(K5-L5)/L5 -> 0.037812682 | N5: =WP!G9 -> 4263 | O5: ='2026年2月WP'!G9 -> 4115 | P5: =(N5-O5)/O5 -> 0.035965978 | Q5: =WP!K9 -> 17244 | R5: ='2026年2月WP'!K9 -> 28594 | S5: =(Q5-R5)/R5 -> -0.39693642 | T5: =WP!L9 -> 4327032 | U5: ='2026年2月WP'!L9 -> 4559838 | V5: =(T5-U5)/U5 -> -0.051055761 | W5: =WP!AH9 -> 2425.4664 | X5: =WP!J9 -> 3233 | Y5: ='2026年2月WP'!J9 -> 3080 | Z5: =(X5-Y5)/Y5 -> 0.049675325 | AA5: =WP!P9 -> 23387437 | AB5: ='2026年2月WP'!P9 -> 24158527 | AC5: =(AA5-AB5)/AB5 -> -0.031917932 | AD5: =WP!AI9 -> 7233.9736 | AE5: =WP!AJ9 -> 1.8122197 | AF5: =WP!H9 -> 487 | AG5: ='2026年2月WP'!H9 -> 444 | AH5: =(AF5-AG5)/AG5 -> 0.096846847 | AI5: =WP!I9 -> 873 | AJ5: ='2026年2月WP'!I9 -> 814 | AK5: =(AI5-AJ5)/AJ5 -> 0.072481572 | AL5: =WP!M9 -> 4332776 | AM5: ='2026年2月WP'!M9 -> 4259980 | AN5: =(AL5-AM5)/AM5 -> 0.017088343 | AO5: =WP!Q9 -> 314286.96 | AP5: ='2026年2月WP'!Q9 -> 550919.06 | AQ5: =(AO5-AP5)/AP5 -> -0.42952244 | AR5: =WP!AF9 -> -122166.12 | AS5: ='2026年2月WP'!AF9 -> -129161.56 | AT5: =(AR5-AS5)/AS5 -> -0.054160381
A6: =全平台汇总!A4 -> 46083 | B6: =WP!D10 -> 5841 | C6: ='2026年2月WP'!D10 -> 6681 | D6: =(B6-C6)/C6 -> -0.12572968 | E6: =WP!B10 -> 201 | F6: ='2026年2月WP'!B10 -> 295 | G6: =(E6-F6)/F6 -> -0.31864407 | H6: =WP!C10 -> 104 | I6: ='2026年2月WP'!C10 -> 103 | J6: =(H6-I6)/I6 -> 0.0097087379 | K6: =WP!F10 -> 1445 | L6: ='2026年2月WP'!F10 -> 1561 | M6: =(K6-L6)/L6 -> -0.074311339 | N6: =WP!G10 -> 3649 | O6: ='2026年2月WP'!G10 -> 3901 | P6: =(N6-O6)/O6 -> -0.064598821 | Q6: =WP!K10 -> 26550 | R6: ='2026年2月WP'!K10 -> 26492 | S6: =(Q6-R6)/R6 -> 0.0021893402 | T6: =WP!L10 -> 4018268 | U6: ='2026年2月WP'!L10 -> 4112965 | V6: =(T6-U6)/U6 -> -0.023024023 | W6: =WP!AH10 -> 2780.8083 | X6: =WP!J10 -> 2660 | Y6: ='2026年2月WP'!J10 -> 2877 | Z6: =(X6-Y6)/Y6 -> -0.075425791 | AA6: =WP!P10 -> 21901078 | AB6: ='2026年2月WP'!P10 -> 24522315 | AC6: =(AA6-AB6)/AB6 -> -0.10689192 | AD6: =WP!AI10 -> 8233.488 | AE6: =WP!AJ10 -> 1.8408304 | AF6: =WP!H10 -> 502 | AG6: ='2026年2月WP'!H10 -> 490 | AH6: =(AF6-AG6)/AG6 -> 0.024489796 | AI6: =WP!I10 -> 872 | AJ6: ='2026年2月WP'!I10 -> 893 | AK6: =(AI6-AJ6)/AJ6 -> -0.023516237 | AL6: =WP!M10 -> 4321480 | AM6: ='2026年2月WP'!M10 -> 4118277 | AN6: =(AL6-AM6)/AM6 -> 0.049341751 | AO6: =WP!Q10 -> 397706.99 | AP6: ='2026年2月WP'!Q10 -> 895758.62 | AQ6: =(AO6-AP6)/AP6 -> -0.55601098 | AR6: =WP!AF10 -> -429923.83 | AS6: ='2026年2月WP'!AF10 -> 75839.384 | AT6: =(AR6-AS6)/AS6 -> -6.6688729
A7: =全平台汇总!A5 -> 46084 | B7: =WP!D11 -> 8837 | C7: ='2026年2月WP'!D11 -> 7336 | D7: =(B7-C7)/C7 -> 0.20460742 | E7: =WP!B11 -> 181 | F7: ='2026年2月WP'!B11 -> 281 | G7: =(E7-F7)/F7 -> -0.35587189 | H7: =WP!C11 -> 73 | I7: ='2026年2月WP'!C11 -> 91 | J7: =(H7-I7)/I7 -> -0.1978022 | K7: =WP!F11 -> 1418 | L7: ='2026年2月WP'!F11 -> 1526 | M7: =(K7-L7)/L7 -> -0.070773263 | N7: =WP!G11 -> 3572 | O7: ='2026年2月WP'!G11 -> 3817 | P7: =(N7-O7)/O7 -> -0.064186534 | Q7: =WP!K11 -> 28891 | R7: ='2026年2月WP'!K11 -> 34755 | S7: =(Q7-R7)/R7 -> -0.16872392 | T7: =WP!L11 -> 3401851 | U7: ='2026年2月WP'!L11 -> 3505630 | V7: =(T7-U7)/U7 -> -0.029603523 | W7: =WP!AH11 -> 2399.0487 | X7: =WP!J11 -> 3625 | Y7: ='2026年2月WP'!J11 -> 3787 | Z7: =(X7-Y7)/Y7 -> -0.042777924 | AA7: =WP!P11 -> 20978277 | AB7: ='2026年2月WP'!P11 -> 25622893 | AC7: =(AA7-AB7)/AB7 -> -0.18126821 | AD7: =WP!AI11 -> 5787.111 | AE7: =WP!AJ11 -> 2.5564175 | AF7: =WP!H11 -> 396 | AG7: ='2026年2月WP'!H11 -> 451 | AH7: =(AF7-AG7)/AG7 -> -0.12195122 | AI7: =WP!I11 -> 718 | AJ7: ='2026年2月WP'!I11 -> 850 | AK7: =(AI7-AJ7)/AJ7 -> -0.15529412 | AL7: =WP!M11 -> 2965047 | AM7: ='2026年2月WP'!M11 -> 4167594 | AN7: =(AL7-AM7)/AM7 -> -0.28854706 | AO7: =WP!Q11 -> 613103.09 | AP7: ='2026年2月WP'!Q11 -> -695169.36 | AQ7: =(AO7-AP7)/AP7 -> -1.8819478 | AR7: =WP!AF11 -> 245466.91 | AS7: ='2026年2月WP'!AF11 -> -1007119.2 | AT7: =(AR7-AS7)/AS7 -> -1.2437317
A8: =全平台汇总!A6 -> 46085 | B8: =WP!D12 -> 11208 | C8: ='2026年2月WP'!D12 -> 6664 | D8: =(B8-C8)/C8 -> 0.68187275 | E8: =WP!B12 -> 236 | F8: ='2026年2月WP'!B12 -> 256 | G8: =(E8-F8)/F8 -> -0.078125 | H8: =WP!C12 -> 102 | I8: ='2026年2月WP'!C12 -> 98 | J8: =(H8-I8)/I8 -> 0.040816327 | K8: =WP!F12 -> 1561 | L8: ='2026年2月WP'!F12 -> 1464 | M8: =(K8-L8)/L8 -> 0.066256831 | N8: =WP!G12 -> 3858 | O8: ='2026年2月WP'!G12 -> 3827 | P8: =(N8-O8)/O8 -> 0.0081003397 | Q8: =WP!K12 -> 26710 | R8: ='2026年2月WP'!K12 -> 74394 | S8: =(Q8-R8)/R8 -> -0.64096567 | T8: =WP!L12 -> 4415840 | U8: ='2026年2月WP'!L12 -> 3665493 | V8: =(T8-U8)/U8 -> 0.20470562 | W8: =WP!AH12 -> 2828.8533 | X8: =WP!J12 -> 4374 | Y8: ='2026年2月WP'!J12 -> 3350 | Z8: =(X8-Y8)/Y8 -> 0.30567164 | AA8: =WP!P12 -> 27978341 | AB8: ='2026年2月WP'!P12 -> 24137137 | AC8: =(AA8-AB8)/AB8 -> 0.15914082 | AD8: =WP!AI12 -> 6396.5115 | AE8: =WP!AJ12 -> 2.80205 | AF8: =WP!H12 -> 446 | AG8: ='2026年2月WP'!H12 -> 416 | AH8: =(AF8-AG8)/AG8 -> 0.072115385 | AI8: =WP!I12 -> 817 | AJ8: ='2026年2月WP'!I12 -> 781 | AK8: =(AI8-AJ8)/AJ8 -> 0.04609475 | AL8: =WP!M12 -> 4143447 | AM8: ='2026年2月WP'!M12 -> 3365963 | AN8: =(AL8-AM8)/AM8 -> 0.23098412 | AO8: =WP!Q12 -> 515375.76 | AP8: ='2026年2月WP'!Q12 -> 1038064.5 | AQ8: =(AO8-AP8)/AP8 -> -0.50352241 | AR8: =WP!AF12 -> 89376.072 | AS8: ='2026年2月WP'!AF12 -> 607572.2 | AT8: =(AR8-AS8)/AS8 -> -0.85289638
A9: =全平台汇总!A7 -> 46086 | B9: =WP!D13 -> 6623 | C9: ='2026年2月WP'!D13 -> 6548 | D9: =(B9-C9)/C9 -> 0.011453879 | E9: =WP!B13 -> 200 | F9: ='2026年2月WP'!B13 -> 464 | G9: =(E9-F9)/F9 -> -0.56896552 | H9: =WP!C13 -> 111 | I9: ='2026年2月WP'!C13 -> 154 | J9: =(H9-I9)/I9 -> -0.27922078 | K9: =WP!F13 -> 1399 | L9: ='2026年2月WP'!F13 -> 1474 | M9: =(K9-L9)/L9 -> -0.050881954 | N9: =WP!G13 -> 3686 | O9: ='2026年2月WP'!G13 -> 3505 | P9: =(N9-O9)/O9 -> 0.051640514 | Q9: =WP!K13 -> 34717 | R9: ='2026年2月WP'!K13 -> 46544 | S9: =(Q9-R9)/R9 -> -0.25410364 | T9: =WP!L13 -> 4465269 | U9: ='2026年2月WP'!L13 -> 3260211 | V9: =(T9-U9)/U9 -> 0.36962577 | W9: =WP!AH13 -> 3191.7577 | X9: =WP!J13 -> 2991 | Y9: ='2026年2月WP'!J13 -> 3090 | Z9: =(X9-Y9)/Y9 -> -0.032038835 | AA9: =WP!P13 -> 27024541 | AB9: ='2026年2月WP'!P13 -> 19975471 | AC9: =(AA9-AB9)/AB9 -> 0.35288625 | AD9: =WP!AI13 -> 9035.2861 | AE9: =WP!AJ13 -> 2.1379557 | AF9: =WP!H13 -> 391 | AG9: ='2026年2月WP'!H13 -> 392 | AH9: =(AF9-AG9)/AG9 -> -0.0025510204 | AI9: =WP!I13 -> 753 | AJ9: ='2026年2月WP'!I13 -> 678 | AK9: =(AI9-AJ9)/AJ9 -> 0.11061947 | AL9: =WP!M13 -> 4274465 | AM9: ='2026年2月WP'!M13 -> 3076105 | AN9: =(AL9-AM9)/AM9 -> 0.38957058 | AO9: =WP!Q13 -> 389842.95 | AP9: ='2026年2月WP'!Q13 -> 593330.82 | AQ9: =(AO9-AP9)/AP9 -> -0.34295854 | AR9: =WP!AF13 -> -28043.525 | AS9: ='2026年2月WP'!AF13 -> 214371 | AT9: =(AR9-AS9)/AS9 -> -1.1308177
A10: =全平台汇总!A8 -> 46087 | B10: =WP!D14 -> 7154 | C10: ='2026年2月WP'!D14 -> 5689 | D10: =(B10-C10)/C10 -> 0.2575145 | E10: =WP!B14 -> 225 | F10: ='2026年2月WP'!B14 -> 297 | G10: =(E10-F10)/F10 -> -0.24242424 | H10: =WP!C14 -> 106 | I10: ='2026年2月WP'!C14 -> 101 | J10: =(H10-I10)/I10 -> 0.04950495 | K10: =WP!F14 -> 1397 | L10: ='2026年2月WP'!F14 -> 1392 | M10: =(K10-L10)/L10 -> 0.003591954 | N10: =WP!G14 -> 3647 | O10: ='2026年2月WP'!G14 -> 3542 | P10: =(N10-O10)/O10 -> 0.029644269 | Q10: =WP!K14 -> 24958 | R10: ='2026年2月WP'!K14 -> 22128 | S10: =(Q10-R10)/R10 -> 0.12789226 | T10: =WP!L14 -> 3585506 | U10: ='2026年2月WP'!L14 -> 3132617 | V10: =(T10-U10)/U10 -> 0.14457209 | W10: =WP!AH14 -> 2566.5755 | X10: =WP!J14 -> 3513 | Y10: ='2026年2月WP'!J14 -> 2546 | Z10: =(X10-Y10)/Y10 -> 0.37981147 | AA10: =WP!P14 -> 21272462 | AB10: ='2026年2月WP'!P14 -> 16139967 | AC10: =(AA10-AB10)/AB10 -> 0.31799909 | AD10: =WP!AI14 -> 6055.3549 | AE10: =WP!AJ14 -> 2.5146743 | AF10: =WP!H14 -> 390 | AG10: ='2026年2月WP'!H14 -> 381 | AH10: =(AF10-AG10)/AG10 -> 0.023622047 | AI10: =WP!I14 -> 685 | AJ10: ='2026年2月WP'!I14 -> 664 | AK10: =(AI10-AJ10)/AJ10 -> 0.031626506 | AL10: =WP!M14 -> 3024016 | AM10: ='2026年2月WP'!M14 -> 2438172 | AN10: =(AL10-AM10)/AM10 -> 0.24028001 | AO10: =WP!Q14 -> 1061968.4 | AP10: ='2026年2月WP'!Q14 -> 1070705.7 | AQ10: =(AO10-AP10)/AP10 -> -0.0081603282 | AR10: =WP!AF14 -> 618981.77 | AS10: ='2026年2月WP'!AF14 -> 723030.34 | AT10: =(AR10-AS10)/AS10 -> -0.14390622
A11: =全平台汇总!A9 -> 46088 | B11: =WP!D15 -> 6230 | C11: ='2026年2月WP'!D15 -> 6632 | D11: =(B11-C11)/C11 -> -0.060615199 | E11: =WP!B15 -> 215 | F11: ='2026年2月WP'!B15 -> 313 | G11: =(E11-F11)/F11 -> -0.31309904 | H11: =WP!C15 -> 124 | I11: ='2026年2月WP'!C15 -> 131 | J11: =(H11-I11)/I11 -> -0.053435115 | K11: =WP!F15 -> 1666 | L11: ='2026年2月WP'!F15 -> 1588 | M11: =(K11-L11)/L11 -> 0.049118388 | N11: =WP!G15 -> 4076 | O11: ='2026年2月WP'!G15 -> 3726 | P11: =(N11-O11)/O11 -> 0.093934514 | Q11: =WP!K15 -> 30298 | R11: ='2026年2月WP'!K15 -> 36561 | S11: =(Q11-R11)/R11 -> -0.17130275 | T11: =WP!L15 -> 3807281.5 | U11: ='2026年2月WP'!L15 -> 3660906 | V11: =(T11-U11)/U11 -> 0.039983403 | W11: =WP!AH15 -> 2285.283 | X11: =WP!J15 -> 3363 | Y11: ='2026年2月WP'!J15 -> 2727 | Z11: =(X11-Y11)/Y11 -> 0.23322332 | AA11: =WP!P15 -> 23253030 | AB11: ='2026年2月WP'!P15 -> 23553932 | AC11: =(AA11-AB11)/AB11 -> -0.012775029 | AD11: =WP!AI15 -> 6914.371 | AE11: =WP!AJ15 -> 2.0186074 | AF11: =WP!H15 -> 447 | AG11: ='2026年2月WP'!H15 -> 423 | AH11: =(AF11-AG11)/AG11 -> 0.056737589 | AI11: =WP!I15 -> 836 | AJ11: ='2026年2月WP'!I15 -> 704 | AK11: =(AI11-AJ11)/AJ11 -> 0.1875 | AL11: =WP!M15 -> 3430469 | AM11: ='2026年2月WP'!M15 -> 2863977 | AN11: =(AL11-AM11)/AM11 -> 0.19779907 | AO11: =WP!Q15 -> 705155.16 | AP11: ='2026年2月WP'!Q15 -> 907805.48 | AQ11: =(AO11-AP11)/AP11 -> -0.22323099 | AR11: =WP!AF15 -> 245666.74 | AS11: ='2026年2月WP'!AF15 -> 413683.59 | AT11: =(AR11-AS11)/AS11 -> -0.40614822
A12: =全平台汇总!A10 -> 46089 | B12: =WP!D16 -> 16504 | C12: ='2026年2月WP'!D16 -> 5979 | D12: =(B12-C12)/C12 -> 1.7603278 | E12: =WP!B16 -> 411 | F12: ='2026年2月WP'!B16 -> 251 | G12: =(E12-F12)/F12 -> 0.6374502 | H12: =WP!C16 -> 169 | I12: ='2026年2月WP'!C16 -> 116 | J12: =(H12-I12)/I12 -> 0.45689655 | K12: =WP!F16 -> 1762 | L12: ='2026年2月WP'!F16 -> 1583 | M12: =(K12-L12)/L12 -> 0.11307644 | N12: =WP!G16 -> 3913 | O12: ='2026年2月WP'!G16 -> 3745 | P12: =(N12-O12)/O12 -> 0.044859813 | Q12: =WP!K16 -> 29889 | R12: ='2026年2月WP'!K16 -> 19368 | S12: =(Q12-R12)/R12 -> 0.54321561 | T12: =WP!L16 -> 3574513 | U12: ='2026年2月WP'!L16 -> 3393231 | V12: =(T12-U12)/U12 -> 0.053424597 | W12: =WP!AH16 -> 2028.668 | X12: =WP!J16 -> 13870 | Y12: ='2026年2月WP'!J16 -> 2723 | Z12: =(X12-Y12)/Y12 -> 4.0936467 | AA12: =WP!P16 -> 21368089 | AB12: ='2026年2月WP'!P16 -> 21426698 | AC12: =(AA12-AB12)/AB12 -> -0.0027353175 | AD12: =WP!AI16 -> 1540.5976 | AE12: =WP!AJ16 -> 7.8717367 | AF12: =WP!H16 -> 553 | AG12: ='2026年2月WP'!H16 -> 411 | AH12: =(AF12-AG12)/AG12 -> 0.34549878 | AI12: =WP!I16 -> 934 | AJ12: ='2026年2月WP'!I16 -> 693 | AK12: =(AI12-AJ12)/AJ12 -> 0.34776335 | AL12: =WP!M16 -> 2876306 | AM12: ='2026年2月WP'!M16 -> 2208030 | AN12: =(AL12-AM12)/AM12 -> 0.30265712 | AO12: =WP!Q16 -> 804174.15 | AP12: ='2026年2月WP'!Q16 -> 1660163.1 | AQ12: =(AO12-AP12)/AP12 -> -0.51560534 | AR12: =WP!AF16 -> 366499.95 | AS12: ='2026年2月WP'!AF16 -> 1089133 | AT12: =(AR12-AS12)/AS12 -> -0.66349386
A13: =全平台汇总!A11 -> 46090 | B13: =WP!D17 -> 10216 | C13: ='2026年2月WP'!D17 -> 8284 | D13: =(B13-C13)/C13 -> 0.23322067 | E13: =WP!B17 -> 329 | F13: ='2026年2月WP'!B17 -> 189 | G13: =(E13-F13)/F13 -> 0.74074074 | H13: =WP!C17 -> 173 | I13: ='2026年2月WP'!C17 -> 70 | J13: =(H13-I13)/I13 -> 1.4714286 | K13: =WP!F17 -> 1485 | L13: ='2026年2月WP'!F17 -> 1400 | M13: =(K13-L13)/L13 -> 0.060714286 | N13: =WP!G17 -> 3713 | O13: ='2026年2月WP'!G17 -> 3415 | P13: =(N13-O13)/O13 -> 0.087262079 | Q13: =WP!K17 -> 28088 | R13: ='2026年2月WP'!K17 -> 16708 | S13: =(Q13-R13)/R13 -> 0.68111085 | T13: =WP!L17 -> 3774887 | U13: ='2026年2月WP'!L17 -> 3114749 | V13: =(T13-U13)/U13 -> 0.21193939 | W13: =WP!AH17 -> 2542.0114 | X13: =WP!J17 -> 7731 | Y13: ='2026年2月WP'!J17 -> 5953 | Z13: =(X13-Y13)/Y13 -> 0.29867294 | AA13: =WP!P17 -> 22149541 | AB13: ='2026年2月WP'!P17 -> 17483443 | AC13: =(AA13-AB13)/AB13 -> 0.26688669 | AD13: =WP!AI17 -> 2865.0292 | AE13: =WP!AJ17 -> 5.2060606 | AF13: =WP!H17 -> 551 | AG13: ='2026年2月WP'!H17 -> 514 | AH13: =(AF13-AG13)/AG13 -> 0.071984436 | AI13: =WP!I17 -> 900 | AJ13: ='2026年2月WP'!I17 -> 827 | AK13: =(AI13-AJ13)/AJ13 -> 0.088270859 | AL13: =WP!M17 -> 3535997 | AM13: ='2026年2月WP'!M17 -> 2753924 | AN13: =(AL13-AM13)/AM13 -> 0.28398496 | AO13: =WP!Q17 -> 1037721.3 | AP13: ='2026年2月WP'!Q17 -> 966888.11 | AQ13: =(AO13-AP13)/AP13 -> 0.073258983 | AR13: =WP!AF17 -> 29422.008 | AS13: ='2026年2月WP'!AF17 -> 145444.91 | AT13: =(AR13-AS13)/AS13 -> -0.79771029
A14: =全平台汇总!A12 -> 46091 | B14: =WP!D18 -> 8709 | C14: ='2026年2月WP'!D18 -> 6744 | D14: =(B14-C14)/C14 -> 0.29137011 | E14: =WP!B18 -> 324 | F14: ='2026年2月WP'!B18 -> 244 | G14: =(E14-F14)/F14 -> 0.32786885 | H14: =WP!C18 -> 137 | I14: ='2026年2月WP'!C18 -> 99 | J14: =(H14-I14)/I14 -> 0.38383838 | K14: =WP!F18 -> 1465 | L14: ='2026年2月WP'!F18 -> 1459 | M14: =(K14-L14)/L14 -> 0.0041124058 | N14: =WP!G18 -> 3565 | O14: ='2026年2月WP'!G18 -> 3543 | P14: =(N14-O14)/O14 -> 0.006209427 | Q14: =WP!K18 -> 21766 | R14: ='2026年2月WP'!K18 -> 46275 | S14: =(Q14-R14)/R14 -> -0.52963803 | T14: =WP!L18 -> 3371495 | U14: ='2026年2月WP'!L18 -> 2864090 | V14: =(T14-U14)/U14 -> 0.17716098 | W14: =WP!AH18 -> 2301.3618 | X14: =WP!J18 -> 5672 | Y14: ='2026年2月WP'!J18 -> 4550 | Z14: =(X14-Y14)/Y14 -> 0.24659341 | AA14: =WP!P18 -> 21109571 | AB14: ='2026年2月WP'!P18 -> 19122360 | AC14: =(AA14-AB14)/AB14 -> 0.10392076 | AD14: =WP!AI18 -> 3721.7155 | AE14: =WP!AJ18 -> 3.8716724 | AF14: =WP!H18 -> 428 | AG14: ='2026年2月WP'!H18 -> 466 | AH14: =(AF14-AG14)/AG14 -> -0.081545064 | AI14: =WP!I18 -> 762 | AJ14: ='2026年2月WP'!I18 -> 768 | AK14: =(AI14-AJ14)/AJ14 -> -0.0078125 | AL14: =WP!M18 -> 3044849 | AM14: ='2026年2月WP'!M18 -> 2471644 | AN14: =(AL14-AM14)/AM14 -> 0.23191244 | AO14: =WP!Q18 -> 630264.42 | AP14: ='2026年2月WP'!Q18 -> 506405.76 | AQ14: =(AO14-AP14)/AP14 -> 0.24458383 | AR14: =WP!AF18 -> 279393.36 | AS14: ='2026年2月WP'!AF18 -> 172994.1 | AT14: =(AR14-AS14)/AS14 -> 0.6150456
A15: =全平台汇总!A13 -> 46092 | B15: =WP!D19 -> 9678 | C15: ='2026年2月WP'!D19 -> 8903 | D15: =(B15-C15)/C15 -> 0.087049309 | E15: =WP!B19 -> 240 | F15: ='2026年2月WP'!B19 -> 208 | G15: =(E15-F15)/F15 -> 0.15384615 | H15: =WP!C19 -> 111 | I15: ='2026年2月WP'!C19 -> 78 | J15: =(H15-I15)/I15 -> 0.42307692 | K15: =WP!F19 -> 1454 | L15: ='2026年2月WP'!F19 -> 1483 | M15: =(K15-L15)/L15 -> -0.019554956 | N15: =WP!G19 -> 3806 | O15: ='2026年2月WP'!G19 -> 3625 | P15: =(N15-O15)/O15 -> 0.049931034 | Q15: =WP!K19 -> 18246 | R15: ='2026年2月WP'!K19 -> 26989 | S15: =(Q15-R15)/R15 -> -0.32394679 | T15: =WP!L19 -> 3618631 | U15: ='2026年2月WP'!L19 -> 2710493 | V15: =(T15-U15)/U15 -> 0.33504532 | W15: =WP!AH19 -> 2488.7421 | X15: =WP!J19 -> 6651 | Y15: ='2026年2月WP'!J19 -> 6518 | Z15: =(X15-Y15)/Y15 -> 0.020405032 | AA15: =WP!P19 -> 18790973 | AB15: ='2026年2月WP'!P19 -> 16138642 | AC15: =(AA15-AB15)/AB15 -> 0.16434663 | AD15: =WP!AI19 -> 2825.2854 | AE15: =WP!AJ19 -> 4.5742779 | AF15: =WP!H19 -> 446 | AG15: ='2026年2月WP'!H19 -> 488 | AH15: =(AF15-AG15)/AG15 -> -0.086065574 | AI15: =WP!I19 -> 808 | AJ15: ='2026年2月WP'!I19 -> 755 | AK15: =(AI15-AJ15)/AJ15 -> 0.070198675 | AL15: =WP!M19 -> 2655116 | AM15: ='2026年2月WP'!M19 -> 2117690 | AN15: =(AL15-AM15)/AM15 -> 0.25377935 | AO15: =WP!Q19 -> 1161479 | AP15: ='2026年2月WP'!Q19 -> 933179.35 | AQ15: =(AO15-AP15)/AP15 -> 0.24464714 | AR15: =WP!AF19 -> 747618.35 | AS15: ='2026年2月WP'!AF19 -> 616260.56 | AT15: =(AR15-AS15)/AS15 -> 0.21315301
A16: =全平台汇总!A14 -> 46093 | B16: =WP!D20 -> 7729 | C16: ='2026年2月WP'!D20 -> 6462 | D16: =(B16-C16)/C16 -> 0.19606933 | E16: =WP!B20 -> 184 | F16: ='2026年2月WP'!B20 -> 209 | G16: =(E16-F16)/F16 -> -0.11961722 | H16: =WP!C20 -> 85 | I16: ='2026年2月WP'!C20 -> 72 | J16: =(H16-I16)/I16 -> 0.18055556 | K16: =WP!F20 -> 1437 | L16: ='2026年2月WP'!F20 -> 1344 | M16: =(K16-L16)/L16 -> 0.069196429 | N16: =WP!G20 -> 3615 | O16: ='2026年2月WP'!G20 -> 3361 | P16: =(N16-O16)/O16 -> 0.075572746 | Q16: =WP!K20 -> 14507 | R16: ='2026年2月WP'!K20 -> 17121 | S16: =(Q16-R16)/R16 -> -0.152678 | T16: =WP!L20 -> 3455174 | U16: ='2026年2月WP'!L20 -> 2595745 | V16: =(T16-U16)/U16 -> 0.33109146 | W16: =WP!AH20 -> 2404.4356 | X16: =WP!J20 -> 4112 | Y16: ='2026年2月WP'!J20 -> 4250 | Z16: =(X16-Y16)/Y16 -> -0.032470588 | AA16: =WP!P20 -> 18010102 | AB16: ='2026年2月WP'!P20 -> 17796196 | AC16: =(AA16-AB16)/AB16 -> 0.012019737 | AD16: =WP!AI20 -> 4379.8886 | AE16: =WP!AJ20 -> 2.861517 | AF16: =WP!H20 -> 443 | AG16: ='2026年2月WP'!H20 -> 411 | AH16: =(AF16-AG16)/AG16 -> 0.077858881 | AI16: =WP!I20 -> 811 | AJ16: ='2026年2月WP'!I20 -> 754 | AK16: =(AI16-AJ16)/AJ16 -> 0.075596817 | AL16: =WP!M20 -> 3631857 | AM16: ='2026年2月WP'!M20 -> 2860777 | AN16: =(AL16-AM16)/AM16 -> 0.26953516 | AO16: =WP!Q20 -> -93637.11 | AP16: ='2026年2月WP'!Q20 -> -72915.72 | AQ16: =(AO16-AP16)/AP16 -> 0.28418275 | AR16: =WP!AF20 -> -373990.68 | AS16: ='2026年2月WP'!AF20 -> -308956.42 | AT16: =(AR16-AS16)/AS16 -> 0.21049657
... A35: =全平台汇总!A33 -> 46112 | B35: =WP!D39 -> 0 | C35: ='2026年2月WP'!D39 -> 0 | D35: =(B35-C35)/C35 -> #DIV/0! | E35: =WP!B39 -> 0 | F35: ='2026年2月WP'!B39 -> 0 | G35: =(E35-F35)/F35 -> #DIV/0! | H35: =WP!C39 -> 0 | I35: ='2026年2月WP'!C39 -> 0 | J35: =(H35-I35)/I35 -> #DIV/0! | K35: =WP!F39 -> 0 | L35: ='2026年2月WP'!F39 -> 0 | M35: =(K35-L35)/L35 -> #DIV/0! | N35: =WP!G39 -> 0 | O35: ='2026年2月WP'!G39 -> 0 | P35: =(N35-O35)/O35 -> #DIV/0! | Q35: =WP!K39 -> 0 | R35: ='2026年2月WP'!K39 -> 0 | S35: =(Q35-R35)/R35 -> #DIV/0! | T35: =WP!L39 -> 0 | U35: ='2026年2月WP'!L39 -> 0 | V35: =(T35-U35)/U35 -> #DIV/0! | W35: =WP!AH39 -> #DIV/0! | X35: =WP!J39 -> 0 | Y35: ='2026年2月WP'!J39 -> 0 | Z35: =(X35-Y35)/Y35 -> #DIV/0! | AA35: =WP!P39 -> 0 | AB35: ='2026年2月WP'!P39 -> 0 | AC35: =(AA35-AB35)/AB35 -> #DIV/0! | AD35: =WP!AI39 -> #DIV/0! | AE35: =WP!AJ39 -> #DIV/0! | AF35: =WP!H39 -> 0 | AG35: ='2026年2月WP'!H39 -> 0 | AH35: =(AF35-AG35)/AG35 -> #DIV/0! | AI35: =WP!I39 -> 0 | AJ35: ='2026年2月WP'!I39 -> 0 | AK35: =(AI35-AJ35)/AJ35 -> #DIV/0! | AL35: =WP!M39 -> 0 | AM35: ='2026年2月WP'!M39 -> 0 | AN35: =(AL35-AM35)/AM35 -> #DIV/0! | AO35: =WP!Q39 -> 0 | AP35: ='2026年2月WP'!Q39 -> 0 | AQ35: =(AO35-AP35)/AP35 -> #DIV/0! | AR35: =WP!AF39 | AS35: ='2026年2月WP'!AF39 | AT35: =(AR35-AS35)/AS35 -> #VALUE!
A36: 日均值 | B36: 本月日均值数据 | C36: 上月日均值数据 | D36: 日均值同比增长率 | E36: 本月日均值数据 | F36: 上月日均值数据 | G36: 日均值同比增长率 | H36: 本月日均值数据 | I36: 上月日均值数据 | J36: 日均值同比增长率 | K36: 本月日均值数据 | L36: 上月日均值数据 | M36: 日均值同比增长率 | N36: 本月日均值数据 | O36: 上月日均值数据 | P36: 日均值同比增长率 | Q36: 本月日均值数据 | R36: 上月日均值数据 | S36: 日均值同比增长率 | T36: 本月日均值数据 | U36: 上月日均值数据 | V36: 日均值同比增长率 | X36: 本月日均值数据 | Y36: 上月日均值数据 | Z36: 日均值同比增长率 | AA36: 本月日均值数据 | AB36: 上月日均值数据 | AC36: 日均值同比增长率 | AF36: 本月日均值数据 | AG36: 上月日均值数据 | AH36: 日均值同比增长率 | AI36: 本月日均值数据 | AJ36: 上月日均值数据 | AK36: 日均值同比增长率 | AL36: 本月日均值数据 | AM36: 上月日均值数据 | AN36: 日均值同比增长率 | AO36: 本月日均值数据 | AP36: 上月日均值数据 | AQ36: 日均值同比增长率 | AR36: 本月日均值数据 | AS36: 上月日均值数据 | AT36: 日均值同比增长率
A37: =A5 -> 46082 | B37: =B5/1 -> 7540 | C37: =C5/1 -> 6426 | D37: =(B37-C37)/C37 -> 0.17335823 | E37: =E5/1 -> 206 | F37: =F5/1 -> 264 | G37: =(E37-F37)/F37 -> -0.21969697 | H37: =H5/1 -> 94 | I37: =I5/1 -> 106 | J37: =(H37-I37)/I37 -> -0.11320755 | K37: =K5/1 -> 1784 | L37: =L5/1 -> 1719 | M37: =(K37-L37)/L37 -> 0.037812682 | N37: =N5/1 -> 4263 | O37: =O5/1 -> 4115 | P37: =(N37-O37)/O37 -> 0.035965978 | Q37: =Q5/1 -> 17244 | R37: =R5/1 -> 28594 | S37: =(Q37-R37)/R37 -> -0.39693642 | T37: =T5/1 -> 4327032 | U37: =U5/1 -> 4559838 | V37: =(T37-U37)/U37 -> -0.051055761 | X37: =X5/1 -> 3233 | Y37: =Y5/1 -> 3080 | Z37: =(X37-Y37)/Y37 -> 0.049675325 | AA37: =AA5/1 -> 23387437 | AB37: =AB5/1 -> 24158527 | AC37: =(AA37-AB37)/AB37 -> -0.031917932 | AF37: =AF5/1 -> 487 | AG37: =AG5/1 -> 444 | AH37: =(AF37-AG37)/AG37 -> 0.096846847 | AI37: =AI5/1 -> 873 | AJ37: =AJ5/1 -> 814 | AK37: =(AI37-AJ37)/AJ37 -> 0.072481572 | AL37: =AL5/1 -> 4332776 | AM37: =AM5/1 -> 4259980 | AN37: =(AL37-AM37)/AM37 -> 0.017088343 | AO37: =AO5/1 -> 314286.96 | AP37: =AVERAGE($AP$5:AP5) -> 550919.06 | AQ37: =(AO37-AP37)/AP37 -> -0.42952244 | AR37: =AR5/1 -> -122166.12 | AS37: =AVERAGE($AS$5:AS5) -> -129161.56 | AT37: =(AR37-AS37)/AS37 -> -0.054160381
A38: =A6 -> 46083 | B38: =AVERAGE($B$5:B6) -> 6690.5 | C38: =AVERAGE($C$5:C6) -> 6553.5 | D38: =(B38-C38)/C38 -> 0.02090486 | E38: =AVERAGE($E$5:E6) -> 203.5 | F38: =AVERAGE($F$5:F6) -> 279.5 | G38: =(E38-F38)/F38 -> -0.27191413 | H38: =AVERAGE($H$5:H6) -> 99 | I38: =AVERAGE($I$5:I6) -> 104.5 | J38: =(H38-I38)/I38 -> -0.052631579 | K38: =AVERAGE($K$5:K6) -> 1614.5 | L38: =AVERAGE($L$5:L6) -> 1640 | M38: =(K38-L38)/L38 -> -0.01554878 | N38: =AVERAGE($N$5:N6) -> 3956 | O38: =AVERAGE($O$5:O6) -> 4008 | P38: =(N38-O38)/O38 -> -0.012974052 | Q38: =AVERAGE($Q$5:Q6) -> 21897 | R38: =AVERAGE($R$5:R6) -> 27543 | S38: =(Q38-R38)/R38 -> -0.20498856 | T38: =AVERAGE($T$5:T6) -> 4172650 | U38: =AVERAGE($U$5:U6) -> 4336401.5 | V38: =(T38-U38)/U38 -> -0.037762071 | X38: =AVERAGE($X$5:X6) -> 2946.5 | Y38: =AVERAGE($Y$5:Y6) -> 2978.5 | Z38: =(X38-Y38)/Y38 -> -0.010743663 | AA38: =AVERAGE($AA$5:AA6) -> 22644257 | AB38: =AVERAGE($AB$5:AB6) -> 24340421 | AC38: =(AA38-AB38)/AB38 -> -0.069685064 | AF38: =AVERAGE($AF$5:AF6) -> 494.5 | AG38: =AVERAGE($AG$5:AG6) -> 467 | AH38: =(AF38-AG38)/AG38 -> 0.05888651 | AI38: =AVERAGE($AI$5:AI6) -> 872.5 | AJ38: =AVERAGE($AJ$5:AJ6) -> 853.5 | AK38: =(AI38-AJ38)/AJ38 -> 0.022261277 | AL38: =AVERAGE($AL$5:AL6) -> 4327128 | AM38: =AVERAGE($AM$5:AM6) -> 4189128.5 | AN38: =(AL38-AM38)/AM38 -> 0.032942293 | AO38: =AVERAGE($AO$5:AO6) -> 355996.97 | AP38: =AVERAGE($AP$5:AP6) -> 723338.84 | AQ38: =(AO38-AP38)/AP38 -> -0.50784203 | AR38: =AVERAGE($AR$5:AR6) -> -276044.97 | AS38: =AVERAGE($AS$5:AS6) -> -26661.086 | AT38: =(AR38-AS38)/AS38 -> 9.3538534
A39: =A7 -> 46084 | B39: =AVERAGE($B$5:B7) -> 7406 | C39: =AVERAGE($C$5:C7) -> 6814.3333 | D39: =(B39-C39)/C39 -> 0.086826787 | E39: =AVERAGE($E$5:E7) -> 196 | F39: =AVERAGE($F$5:F7) -> 280 | G39: =(E39-F39)/F39 -> -0.3 | H39: =AVERAGE($H$5:H7) -> 90.333333 | I39: =AVERAGE($I$5:I7) -> 100 | J39: =(H39-I39)/I39 -> -0.096666667 | K39: =AVERAGE($K$5:K7) -> 1549 | L39: =AVERAGE($L$5:L7) -> 1602 | M39: =(K39-L39)/L39 -> -0.033083645 | N39: =AVERAGE($N$5:N7) -> 3828 | O39: =AVERAGE($O$5:O7) -> 3944.3333 | P39: =(N39-O39)/O39 -> -0.029493789 | Q39: =AVERAGE($Q$5:Q7) -> 24228.333 | R39: =AVERAGE($R$5:R7) -> 29947 | S39: =(Q39-R39)/R39 -> -0.19095958 | T39: =AVERAGE($T$5:T7) -> 3915717 | U39: =AVERAGE($U$5:U7) -> 4059477.7 | V39: =(T39-U39)/U39 -> -0.035413587 | X39: =AVERAGE($X$5:X7) -> 3172.6667 | Y39: =AVERAGE($Y$5:Y7) -> 3248 | Z39: =(X39-Y39)/Y39 -> -0.02319376 | AA39: =AVERAGE($AA$5:AA7) -> 22088931 | AB39: =AVERAGE($AB$5:AB7) -> 24767912 | AC39: =(AA39-AB39)/AB39 -> -0.10816339 | AF39: =AVERAGE($AF$5:AF7) -> 461.66667 | AG39: =AVERAGE($AG$5:AG7) -> 461.66667 | AH39: =(AF39-AG39)/AG39 -> 0 | AI39: =AVERAGE($AI$5:AI7) -> 821 | AJ39: =AVERAGE($AJ$5:AJ7) -> 852.33333 | AK39: =(AI39-AJ39)/AJ39 -> -0.03676183 | AL39: =AVERAGE($AL$5:AL7) -> 3873101 | AM39: =AVERAGE($AM$5:AM7) -> 4181950.3 | AN39: =(AL39-AM39)/AM39 -> -0.073852942 | AO39: =AVERAGE($AO$5:AO7) -> 441699.01 | AP39: =AVERAGE($AP$5:AP7) -> 250502.77 | AQ39: =(AO39-AP39)/AP39 -> 0.76324999 | AR39: =AVERAGE($AR$5:AR7) -> -102207.68 | AS39: =AVERAGE($AS$5:AS7) -> -353480.45 | AT39: =(AR39-AS39)/AS39 -> -0.71085338
A40: =A8 -> 46085 | B40: =AVERAGE($B$5:B8) -> 8356.5 | C40: =AVERAGE($C$5:C8) -> 6776.75 | D40: =(B40-C40)/C40 -> 0.23311322 | E40: =AVERAGE($E$5:E8) -> 206 | F40: =AVERAGE($F$5:F8) -> 274 | G40: =(E40-F40)/F40 -> -0.24817518 | H40: =AVERAGE($H$5:H8) -> 93.25 | I40: =AVERAGE($I$5:I8) -> 99.5 | J40: =(H40-I40)/I40 -> -0.06281407 | K40: =AVERAGE($K$5:K8) -> 1552 | L40: =AVERAGE($L$5:L8) -> 1567.5 | M40: =(K40-L40)/L40 -> -0.0098883573 | N40: =AVERAGE($N$5:N8) -> 3835.5 | O40: =AVERAGE($O$5:O8) -> 3915 | P40: =(N40-O40)/O40 -> -0.020306513 | Q40: =AVERAGE($Q$5:Q8) -> 24848.75 | R40: =AVERAGE($R$5:R8) -> 41058.75 | S40: =(Q40-R40)/R40 -> -0.39480013 | T40: =AVERAGE($T$5:T8) -> 4040747.8 | U40: =AVERAGE($U$5:U8) -> 3960981.5 | V40: =(T40-U40)/U40 -> 0.020138001 | X40: =AVERAGE($X$5:X8) -> 3473 | Y40: =AVERAGE($Y$5:Y8) -> 3273.5 | Z40: =(X40-Y40)/Y40 -> 0.060943944 | AA40: =AVERAGE($AA$5:AA8) -> 23561283 | AB40: =AVERAGE($AB$5:AB8) -> 24610218 | AC40: =(AA40-AB40)/AB40 -> -0.042621929 | AF40: =AVERAGE($AF$5:AF8) -> 457.75 | AG40: =AVERAGE($AG$5:AG8) -> 450.25 | AH40: =(AF40-AG40)/AG40 -> 0.016657413 | AI40: =AVERAGE($AI$5:AI8) -> 820 | AJ40: =AVERAGE($AJ$5:AJ8) -> 834.5 | AK40: =(AI40-AJ40)/AJ40 -> -0.017375674 | AL40: =AVERAGE($AL$5:AL8) -> 3940687.5 | AM40: =AVERAGE($AM$5:AM8) -> 3977953.5 | AN40: =(AL40-AM40)/AM40 -> -0.0093681336 | AO40: =AVERAGE($AO$5:AO8) -> 460118.2 | AP40: =AVERAGE($AP$5:AP8) -> 447393.21 | AQ40: =(AO40-AP40)/AP40 -> 0.028442531 | AR40: =AVERAGE($AR$5:AR8) -> -54311.741 | AS40: =AVERAGE($AS$5:AS8) -> -113217.29 | AT40: =(AR40-AS40)/AS40 -> -0.52028756
A41: =A9 -> 46086 | B41: =AVERAGE($B$5:B9) -> 8009.8 | C41: =AVERAGE($C$5:C9) -> 6731 | D41: =(B41-C41)/C41 -> 0.18998663 | E41: =AVERAGE($E$5:E9) -> 204.8 | F41: =AVERAGE($F$5:F9) -> 312 | G41: =(E41-F41)/F41 -> -0.34358974 | H41: =AVERAGE($H$5:H9) -> 96.8 | I41: =AVERAGE($I$5:I9) -> 110.4 | J41: =(H41-I41)/I41 -> -0.12318841 | K41: =AVERAGE($K$5:K9) -> 1521.4 | L41: =AVERAGE($L$5:L9) -> 1548.8 | M41: =(K41-L41)/L41 -> -0.017691116 | N41: =AVERAGE($N$5:N9) -> 3805.6 | O41: =AVERAGE($O$5:O9) -> 3833 | P41: =(N41-O41)/O41 -> -0.0071484477 | Q41: =AVERAGE($Q$5:Q9) -> 26822.4 | R41: =AVERAGE($R$5:R9) -> 42155.8 | S41: =(Q41-R41)/R41 -> -0.36373168 | T41: =AVERAGE($T$5:T9) -> 4125652 | U41: =AVERAGE($U$5:U9) -> 3820827.4 | V41: =(T41-U41)/U41 -> 0.079779736 | X41: =AVERAGE($X$5:X9) -> 3376.6 | Y41: =AVERAGE($Y$5:Y9) -> 3236.8 | Z41: =(X41-Y41)/Y41 -> 0.043190806 | AA41: =AVERAGE($AA$5:AA9) -> 24253935 | AB41: =AVERAGE($AB$5:AB9) -> 23683269 | AC41: =(AA41-AB41)/AB41 -> 0.02409574 | AF41: =AVERAGE($AF$5:AF9) -> 444.4 | AG41: =AVERAGE($AG$5:AG9) -> 438.6 | AH41: =(AF41-AG41)/AG41 -> 0.013223894 | AI41: =AVERAGE($AI$5:AI9) -> 806.6 | AJ41: =AVERAGE($AJ$5:AJ9) -> 803.2 | AK41: =(AI41-AJ41)/AJ41 -> 0.0042330677 | AL41: =AVERAGE($AL$5:AL9) -> 4007443 | AM41: =AVERAGE($AM$5:AM9) -> 3797583.8 | AN41: =(AL41-AM41)/AM41 -> 0.055261243 | AO41: =AVERAGE($AO$5:AO9) -> 446063.15 | AP41: =AVERAGE($AP$5:AP9) -> 476580.73 | AQ41: =(AO41-AP41)/AP41 -> -0.064034436 | AR41: =AVERAGE($AR$5:AR9) -> -49058.098 | AS41: =AVERAGE($AS$5:AS9) -> -47699.63 | AT41: =(AR41-AS41)/AS41 -> 0.028479634
A42: =A10 -> 46087 | B42: =AVERAGE($B$5:B10) -> 7867.1667 | C42: =AVERAGE($C$5:C10) -> 6557.3333 | D42: =(B42-C42)/C42 -> 0.19975092 | E42: =AVERAGE($E$5:E10) -> 208.16667 | F42: =AVERAGE($F$5:F10) -> 309.5 | G42: =(E42-F42)/F42 -> -0.3274098 | H42: =AVERAGE($H$5:H10) -> 98.333333 | I42: =AVERAGE($I$5:I10) -> 108.83333 | J42: =(H42-I42)/I42 -> -0.096477795 | K42: =AVERAGE($K$5:K10) -> 1500.6667 | L42: =AVERAGE($L$5:L10) -> 1522.6667 | M42: =(K42-L42)/L42 -> -0.014448336 | N42: =AVERAGE($N$5:N10) -> 3779.1667 | O42: =AVERAGE($O$5:O10) -> 3784.5 | P42: =(N42-O42)/O42 -> -0.0014092571 | Q42: =AVERAGE($Q$5:Q10) -> 26511.667 | R42: =AVERAGE($R$5:R10) -> 38817.833 | S42: =(Q42-R42)/R42 -> -0.31702353 | T42: =AVERAGE($T$5:T10) -> 4035627.7 | U42: =AVERAGE($U$5:U10) -> 3706125.7 | V42: =(T42-U42)/U42 -> 0.088907401 | X42: =AVERAGE($X$5:X10) -> 3399.3333 | Y42: =AVERAGE($Y$5:Y10) -> 3121.6667 | Z42: =(X42-Y42)/Y42 -> 0.088948211 | AA42: =AVERAGE($AA$5:AA10) -> 23757023 | AB42: =AVERAGE($AB$5:AB10) -> 22426052 | AC42: =(AA42-AB42)/AB42 -> 0.05934931 | AF42: =AVERAGE($AF$5:AF10) -> 435.33333 | AG42: =AVERAGE($AG$5:AG10) -> 429 | AH42: =(AF42-AG42)/AG42 -> 0.014763015 | AI42: =AVERAGE($AI$5:AI10) -> 786.33333 | AJ42: =AVERAGE($AJ$5:AJ10) -> 780 | AK42: =(AI42-AJ42)/AJ42 -> 0.0081196581 | AL42: =AVERAGE($AL$5:AL10) -> 3843538.5 | AM42: =AVERAGE($AM$5:AM10) -> 3571015.2 | AN42: =(AL42-AM42)/AM42 -> 0.076315367 | AO42: =AVERAGE($AO$5:AO10) -> 548714.03 | AP42: =AVERAGE($AP$5:AP10) -> 575601.56 | AQ42: =(AO42-AP42)/AP42 -> -0.046712058 | AR42: =AVERAGE($AR$5:AR10) -> 62281.881 | AS42: =AVERAGE($AS$5:AS10) -> 80755.365 | AT42: =(AR42-AS42)/AS42 -> -0.22875859
A43: =A11 -> 46088 | B43: =AVERAGE($B$5:B11) -> 7633.2857 | C43: =AVERAGE($C$5:C11) -> 6568 | D43: =(B43-C43)/C43 -> 0.16219332 | E43: =AVERAGE($E$5:E11) -> 209.14286 | F43: =AVERAGE($F$5:F11) -> 310 | G43: =(E43-F43)/F43 -> -0.32534562 | H43: =AVERAGE($H$5:H11) -> 102 | I43: =AVERAGE($I$5:I11) -> 112 | J43: =(H43-I43)/I43 -> -0.089285714 | K43: =AVERAGE($K$5:K11) -> 1524.2857 | L43: =AVERAGE($L$5:L11) -> 1532 | M43: =(K43-L43)/L43 -> -0.0050354345 | N43: =AVERAGE($N$5:N11) -> 3821.5714 | O43: =AVERAGE($O$5:O11) -> 3776.1429 | P43: =(N43-O43)/O43 -> 0.012030417 | Q43: =AVERAGE($Q$5:Q11) -> 27052.571 | R43: =AVERAGE($R$5:R11) -> 38495.429 | S43: =(Q43-R43)/R43 -> -0.29725236 | T43: =AVERAGE($T$5:T11) -> 4003006.8 | U43: =AVERAGE($U$5:U11) -> 3699665.7 | V43: =(T43-U43)/U43 -> 0.08199148 | X43: =AVERAGE($X$5:X11) -> 3394.1429 | Y43: =AVERAGE($Y$5:Y11) -> 3065.2857 | Z43: =(X43-Y43)/Y43 -> 0.10728434 | AA43: =AVERAGE($AA$5:AA11) -> 23685024 | AB43: =AVERAGE($AB$5:AB11) -> 22587178 | AC43: =(AA43-AB43)/AB43 -> 0.048604834 | AF43: =AVERAGE($AF$5:AF11) -> 437 | AG43: =AVERAGE($AG$5:AG11) -> 428.14286 | AH43: =(AF43-AG43)/AG43 -> 0.020687354 | AI43: =AVERAGE($AI$5:AI11) -> 793.42857 | AJ43: =AVERAGE($AJ$5:AJ11) -> 769.14286 | AK43: =(AI43-AJ43)/AJ43 -> 0.031575037 | AL43: =AVERAGE($AL$5:AL11) -> 3784528.6 | AM43: =AVERAGE($AM$5:AM11) -> 3470009.7 | AN43: =(AL43-AM43)/AM43 -> 0.090639186 | AO43: =AVERAGE($AO$5:AO11) -> 571062.76 | AP43: =AVERAGE($AP$5:AP11) -> 623059.26 | AQ43: =(AO43-AP43)/AP43 -> -0.083453543 | AR43: =AVERAGE($AR$5:AR11) -> 88479.717 | AS43: =AVERAGE($AS$5:AS11) -> 128316.54 | AT43: =(AR43-AS43)/AS43 -> -0.31045742
A44: =A12 -> 46089 | B44: =AVERAGE($B$5:B12) -> 8742.125 | C44: =AVERAGE($C$5:C12) -> 6494.375 | D44: =(B44-C44)/C44 -> 0.34610721 | E44: =AVERAGE($E$5:E12) -> 234.375 | F44: =AVERAGE($F$5:F12) -> 302.625 | G44: =(E44-F44)/F44 -> -0.22552664 | H44: =AVERAGE($H$5:H12) -> 110.375 | I44: =AVERAGE($I$5:I12) -> 112.5 | J44: =(H44-I44)/I44 -> -0.018888889 | K44: =AVERAGE($K$5:K12) -> 1554 | L44: =AVERAGE($L$5:L12) -> 1538.375 | M44: =(K44-L44)/L44 -> 0.010156821 | N44: =AVERAGE($N$5:N12) -> 3833 | O44: =AVERAGE($O$5:O12) -> 3772.25 | P44: =(N44-O44)/O44 -> 0.016104447 | Q44: =AVERAGE($Q$5:Q12) -> 27407.125 | R44: =AVERAGE($R$5:R12) -> 36104.5 | S44: =(Q44-R44)/R44 -> -0.24089449 | T44: =AVERAGE($T$5:T12) -> 3949445.1 | U44: =AVERAGE($U$5:U12) -> 3661361.4 | V44: =(T44-U44)/U44 -> 0.078682123 | X44: =AVERAGE($X$5:X12) -> 4703.625 | Y44: =AVERAGE($Y$5:Y12) -> 3022.5 | Z44: =(X44-Y44)/Y44 -> 0.55620347 | AA44: =AVERAGE($AA$5:AA12) -> 23395407 | AB44: =AVERAGE($AB$5:AB12) -> 22442118 | AC44: =(AA44-AB44)/AB44 -> 0.042477683 | AF44: =AVERAGE($AF$5:AF12) -> 451.5 | AG44: =AVERAGE($AG$5:AG12) -> 426 | AH44: =(AF44-AG44)/AG44 -> 0.059859155 | AI44: =AVERAGE($AI$5:AI12) -> 811 | AJ44: =AVERAGE($AJ$5:AJ12) -> 759.625 | AK44: =(AI44-AJ44)/AJ44 -> 0.067632055 | AL44: =AVERAGE($AL$5:AL12) -> 3671000.8 | AM44: =AVERAGE($AM$5:AM12) -> 3312262.2 | AN44: =(AL44-AM44)/AM44 -> 0.10830619 | AO44: =AVERAGE($AO$5:AO12) -> 600201.68 | AP44: =AVERAGE($AP$5:AP12) -> 752697.24 | AQ44: =(AO44-AP44)/AP44 -> -0.2025988 | AR44: =AVERAGE($AR$5:AR12) -> 123232.25 | AS44: =AVERAGE($AS$5:AS12) -> 248418.6 | AT44: =(AR44-AS44)/AS44 -> -0.50393309
A45: =A13 -> 46090 | B45: =AVERAGE($B$5:B13) -> 8905.8889 | C45: =AVERAGE($C$5:C13) -> 6693.2222 | D45: =(B45-C45)/C45 -> 0.33058318 | E45: =AVERAGE($E$5:E13) -> 244.88889 | F45: =AVERAGE($F$5:F13) -> 290 | G45: =(E45-F45)/F45 -> -0.15555556 | H45: =AVERAGE($H$5:H13) -> 117.33333 | I45: =AVERAGE($I$5:I13) -> 107.77778 | J45: =(H45-I45)/I45 -> 0.088659794 | K45: =AVERAGE($K$5:K13) -> 1546.3333 | L45: =AVERAGE($L$5:L13) -> 1523 | M45: =(K45-L45)/L45 -> 0.015320639 | N45: =AVERAGE($N$5:N13) -> 3819.6667 | O45: =AVERAGE($O$5:O13) -> 3732.5556 | P45: =(N45-O45)/O45 -> 0.023338195 | Q45: =AVERAGE($Q$5:Q13) -> 27482.778 | R45: =AVERAGE($R$5:R13) -> 33949.333 | S45: =(Q45-R45)/R45 -> -0.19047666 | T45: =AVERAGE($T$5:T13) -> 3930049.7 | U45: =AVERAGE($U$5:U13) -> 3600626.7 | V45: =(T45-U45)/U45 -> 0.091490478 | X45: =AVERAGE($X$5:X13) -> 5040 | Y45: =AVERAGE($Y$5:Y13) -> 3348.1111 | Z45: =(X45-Y45)/Y45 -> 0.50532639 | AA45: =AVERAGE($AA$5:AA13) -> 23256977 | AB45: =AVERAGE($AB$5:AB13) -> 21891154 | AC45: =(AA45-AB45)/AB45 -> 0.062391572 | AF45: =AVERAGE($AF$5:AF13) -> 462.55556 | AG45: =AVERAGE($AG$5:AG13) -> 435.77778 | AH45: =(AF45-AG45)/AG45 -> 0.061448241 | AI45: =AVERAGE($AI$5:AI13) -> 820.88889 | AJ45: =AVERAGE($AJ$5:AJ13) -> 767.11111 | AK45: =(AI45-AJ45)/AJ45 -> 0.070104287 | AL45: =AVERAGE($AL$5:AL13) -> 3656000.3 | AM45: =AVERAGE($AM$5:AM13) -> 3250224.7 | AN45: =(AL45-AM45)/AM45 -> 0.12484542 | AO45: =AVERAGE($AO$5:AO13) -> 648814.98 | AP45: =AVERAGE($AP$5:AP13) -> 776496.23 | AQ45: =(AO45-AP45)/AP45 -> -0.16443254 | AR45: =AVERAGE($AR$5:AR13) -> 112808.89 | AS45: =AVERAGE($AS$5:AS13) -> 236977.08 | AT45: =(AR45-AS45)/AS45 -> -0.5239671
A46: =A14 -> 46091 | B46: =AVERAGE($B$5:B14) -> 8886.2 | C46: =AVERAGE($C$5:C14) -> 6698.3 | D46: =(B46-C46)/C46 -> 0.32663512 | E46: =AVERAGE($E$5:E14) -> 252.8 | F46: =AVERAGE($F$5:F14) -> 285.4 | G46: =(E46-F46)/F46 -> -0.11422565 | H46: =AVERAGE($H$5:H14) -> 119.3 | I46: =AVERAGE($I$5:I14) -> 106.9 | J46: =(H46-I46)/I46 -> 0.11599626 | K46: =AVERAGE($K$5:K14) -> 1538.2 | L46: =AVERAGE($L$5:L14) -> 1516.6 | M46: =(K46-L46)/L46 -> 0.014242384 | N46: =AVERAGE($N$5:N14) -> 3794.2 | O46: =AVERAGE($O$5:O14) -> 3713.6 | P46: =(N46-O46)/O46 -> 0.021704007 | Q46: =AVERAGE($Q$5:Q14) -> 26911.1 | R46: =AVERAGE($R$5:R14) -> 35181.9 | S46: =(Q46-R46)/R46 -> -0.23508679 | T46: =AVERAGE($T$5:T14) -> 3874194.2 | U46: =AVERAGE($U$5:U14) -> 3526973 | V46: =(T46-U46)/U46 -> 0.098447379 | X46: =AVERAGE($X$5:X14) -> 5103.2 | Y46: =AVERAGE($Y$5:Y14) -> 3468.3 | Z46: =(X46-Y46)/Y46 -> 0.47138367 | AA46: =AVERAGE($AA$5:AA14) -> 23042237 | AB46: =AVERAGE($AB$5:AB14) -> 21614274 | AC46: =(AA46-AB46)/AB46 -> 0.0660657 | AF46: =AVERAGE($AF$5:AF14) -> 459.1 | AG46: =AVERAGE($AG$5:AG14) -> 438.8 | AH46: =(AF46-AG46)/AG46 -> 0.046262534 | AI46: =AVERAGE($AI$5:AI14) -> 815 | AJ46: =AVERAGE($AJ$5:AJ14) -> 767.2 | AK46: =(AI46-AJ46)/AJ46 -> 0.062304484 | AL46: =AVERAGE($AL$5:AL14) -> 3594885.2 | AM46: =AVERAGE($AM$5:AM14) -> 3172366.6 | AN46: =(AL46-AM46)/AM46 -> 0.13318719 | AO46: =AVERAGE($AO$5:AO14) -> 646959.92 | AP46: =AVERAGE($AP$5:AP14) -> 749487.18 | AQ46: =(AO46-AP46)/AP46 -> -0.13679655 | AR46: =AVERAGE($AR$5:AR14) -> 129467.33 | AS46: =AVERAGE($AS$5:AS14) -> 230578.78 | AT46: =(AR46-AS46)/AS46 -> -0.4385115
A47: =A15 -> 46092 | B47: =AVERAGE($B$5:B15) -> 8958.1818 | C47: =AVERAGE($C$5:C15) -> 6898.7273 | D47: =(B47-C47)/C47 -> 0.29852674 | E47: =AVERAGE($E$5:E15) -> 251.63636 | F47: =AVERAGE($F$5:F15) -> 278.36364 | G47: =(E47-F47)/F47 -> -0.096015676 | H47: =AVERAGE($H$5:H15) -> 118.54545 | I47: =AVERAGE($I$5:I15) -> 104.27273 | J47: =(H47-I47)/I47 -> 0.13687881 | K47: =AVERAGE($K$5:K15) -> 1530.5455 | L47: =AVERAGE($L$5:L15) -> 1513.5455 | M47: =(K47-L47)/L47 -> 0.011231906 | N47: =AVERAGE($N$5:N15) -> 3795.2727 | O47: =AVERAGE($O$5:O15) -> 3705.5455 | P47: =(N47-O47)/O47 -> 0.024214323 | Q47: =AVERAGE($Q$5:Q15) -> 26123.364 | R47: =AVERAGE($R$5:R15) -> 34437.091 | S47: =(Q47-R47)/R47 -> -0.24141782 | T47: =AVERAGE($T$5:T15) -> 3850961.2 | U47: =AVERAGE($U$5:U15) -> 3452747.5 | V47: =(T47-U47)/U47 -> 0.11533241 | X47: =AVERAGE($X$5:X15) -> 5243.9091 | Y47: =AVERAGE($Y$5:Y15) -> 3745.5455 | Z47: =(X47-Y47)/Y47 -> 0.40003883 | AA47: =AVERAGE($AA$5:AA15) -> 22655758 | AB47: =AVERAGE($AB$5:AB15) -> 21116490 | AC47: =(AA47-AB47)/AB47 -> 0.072894145 | AF47: =AVERAGE($AF$5:AF15) -> 457.90909 | AG47: =AVERAGE($AG$5:AG15) -> 443.27273 | AH47: =(AF47-AG47)/AG47 -> 0.033018868 | AI47: =AVERAGE($AI$5:AI15) -> 814.36364 | AJ47: =AVERAGE($AJ$5:AJ15) -> 766.09091 | AK47: =(AI47-AJ47)/AJ47 -> 0.063011748 | AL47: =AVERAGE($AL$5:AL15) -> 3509451.6 | AM47: =AVERAGE($AM$5:AM15) -> 3076486.9 | AN47: =(AL47-AM47)/AM47 -> 0.14073349 | AO47: =AVERAGE($AO$5:AO15) -> 693734.39 | AP47: =AVERAGE($AP$5:AP15) -> 766186.47 | AQ47: =(AO47-AP47)/AP47 -> -0.094561947 | AR47: =AVERAGE($AR$5:AR15) -> 185662.88 | AS47: =AVERAGE($AS$5:AS15) -> 265640.76 | AT47: =(AR47-AS47)/AS47 -> -0.30107533
A48: =A16 -> 46093 | B48: =AVERAGE($B$5:B16) -> 8855.75 | C48: =AVERAGE($C$5:C16) -> 6862.3333 | D48: =(B48-C48)/C48 -> 0.29048671 | E48: =AVERAGE($E$5:E16) -> 246 | F48: =AVERAGE($F$5:F16) -> 272.58333 | G48: =(E48-F48)/F48 -> -0.097523693 | H48: =AVERAGE($H$5:H16) -> 115.75 | I48: =AVERAGE($I$5:I16) -> 101.58333 | J48: =(H48-I48)/I48 -> 0.13945857 | K48: =AVERAGE($K$5:K16) -> 1522.75 | L48: =AVERAGE($L$5:L16) -> 1499.4167 | M48: =(K48-L48)/L48 -> 0.015561607 | N48: =AVERAGE($N$5:N16) -> 3780.25 | O48: =AVERAGE($O$5:O16) -> 3676.8333 | P48: =(N48-O48)/O48 -> 0.028126558 | Q48: =AVERAGE($Q$5:Q16) -> 25155.333 | R48: =AVERAGE($R$5:R16) -> 32994.083 | S48: =(Q48-R48)/R48 -> -0.23758048 | T48: =AVERAGE($T$5:T16) -> 3817979 | U48: =AVERAGE($U$5:U16) -> 3381330.7 | V48: =(T48-U48)/U48 -> 0.12913505 | X48: =AVERAGE($X$5:X16) -> 5149.5833 | Y48: =AVERAGE($Y$5:Y16) -> 3787.5833 | Z48: =(X48-Y48)/Y48 -> 0.35959605 | AA48: =AVERAGE($AA$5:AA16) -> 22268620 | AB48: =AVERAGE($AB$5:AB16) -> 20839798 | AC48: =(AA48-AB48)/AB48 -> 0.068562158 | AF48: =AVERAGE($AF$5:AF16) -> 456.66667 | AG48: =AVERAGE($AG$5:AG16) -> 440.58333 | AH48: =(AF48-AG48)/AG48 -> 0.036504634 | AI48: =AVERAGE($AI$5:AI16) -> 814.08333 | AJ48: =AVERAGE($AJ$5:AJ16) -> 765.08333 | AK48: =(AI48-AJ48)/AJ48 -> 0.064045311 | AL48: =AVERAGE($AL$5:AL16) -> 3519652.1 | AM48: =AVERAGE($AM$5:AM16) -> 3058511.1 | AN48: =(AL48-AM48)/AM48 -> 0.15077304 | AO48: =AVERAGE($AO$5:AO16) -> 628120.09 | AP48: =AVERAGE($AP$5:AP16) -> 696261.29 | AQ48: =(AO48-AP48)/AP48 -> -0.097867273 | AR48: =AVERAGE($AR$5:AR16) -> 139025.08 | AS48: =AVERAGE($AS$5:AS16) -> 217757.66 | AT48: =(AR48-AS48)/AS48 -> -0.36156054
A49: =A17 -> 46094 | B49: =AVERAGE($B$5:B17) -> 8174.5385 | C49: =AVERAGE($C$5:C17) -> 6822.6923 | D49: =(B49-C49)/C49 -> 0.19813969 | E49: =AVERAGE($E$5:E17) -> 227.07692 | F49: =AVERAGE($F$5:F17) -> 266.38462 | G49: =(E49-F49)/F49 -> -0.14755992 | H49: =AVERAGE($H$5:H17) -> 106.84615 | I49: =AVERAGE($I$5:I17) -> 100.15385 | J49: =(H49-I49)/I49 -> 0.066820276 | K49: =AVERAGE($K$5:K17) -> 1405.6154 | L49: =AVERAGE($L$5:L17) -> 1492.6923 | M49: =(K49-L49)/L49 -> -0.058335481 | N49: =AVERAGE($N$5:N17) -> 3489.4615 | O49: =AVERAGE($O$5:O17) -> 3665.2308 | P49: =(N49-O49)/O49 -> -0.047955843 | Q49: =AVERAGE($Q$5:Q17) -> 23220.308 | R49: =AVERAGE($R$5:R17) -> 32370.231 | S49: =(Q49-R49)/R49 -> -0.28266475 | T49: =AVERAGE($T$5:T17) -> 3524288.3 | U49: =AVERAGE($U$5:U17) -> 3331475.8 | V49: =(T49-U49)/U49 -> 0.057875978 | X49: =AVERAGE($X$5:X17) -> 4753.4615 | Y49: =AVERAGE($Y$5:Y17) -> 3776.7692 | Z49: =(X49-Y49)/Y49 -> 0.25860524 | AA49: =AVERAGE($AA$5:AA17) -> 20555649 | AB49: =AVERAGE($AB$5:AB17) -> 20506312 | AC49: =(AA49-AB49)/AB49 -> 0.0024059504 | AF49: =AVERAGE($AF$5:AF17) -> 421.53846 | AG49: =AVERAGE($AG$5:AG17) -> 437.84615 | AH49: =(AF49-AG49)/AG49 -> -0.037245257 | AI49: =AVERAGE($AI$5:AI17) -> 751.46154 | AJ49: =AVERAGE($AJ$5:AJ17) -> 758.15385 | AK49: =(AI49-AJ49)/AJ49 -> -0.0088271104 | AL49: =AVERAGE($AL$5:AL17) -> 3248909.6 | AM49: =AVERAGE($AM$5:AM17) -> 2960950.6 | AN49: =(AL49-AM49)/AM49 -> 0.097252213 | AO49: =AVERAGE($AO$5:AO17) -> 579803.16 | AP49: =AVERAGE($AP$5:AP17) -> 720885.8 | AQ49: =(AO49-AP49)/AP49 -> -0.19570733 | AR49: =AVERAGE($AR$5:AR17) -> 139025.08 | AS49: =AVERAGE($AS$5:AS17) -> 254807.18 | AT49: =(AR49-AS49)/AS49 -> -0.45439102
... A67: =A35 -> 46112 | B67: =AVERAGE($B$5:B35) -> 3428.0323 | C67: =AVERAGE($C$5:C35) -> 6262.2903 | D67: =(B67-C67)/C67 -> -0.45259129 | E67: =AVERAGE($E$5:E35) -> 95.225806 | F67: =AVERAGE($F$5:F35) -> 217.70968 | G67: =(E67-F67)/F67 -> -0.56260187 | H67: =AVERAGE($H$5:H35) -> 44.806452 | I67: =AVERAGE($I$5:I35) -> 91.225806 | J67: =(H67-I67)/I67 -> -0.50884017 | K67: =AVERAGE($K$5:K35) -> 589.45161 | L67: =AVERAGE($L$5:L35) -> 1358 | M67: =(K67-L67)/L67 -> -0.56594137 | N67: =AVERAGE($N$5:N35) -> 1463.3226 | O67: =AVERAGE($O$5:O35) -> 3295.5161 | P67: =(N67-O67)/O67 -> -0.55596558 | Q67: =AVERAGE($Q$5:Q35) -> 9737.5484 | R67: =AVERAGE($R$5:R35) -> 26498.452 | S67: =(Q67-R67)/R67 -> -0.63252387 | T67: =AVERAGE($T$5:T35) -> 1477927.3 | U67: =AVERAGE($U$5:U35) -> 3086549.6 | V67: =(T67-U67)/U67 -> -0.52117169 | X67: =AVERAGE($X$5:X35) -> 1993.3871 | Y67: =AVERAGE($Y$5:Y35) -> 3568.7419 | Z67: =(X67-Y67)/Y67 -> -0.44143143 | AA67: =AVERAGE($AA$5:AA35) -> 8620111 | AB67: =AVERAGE($AB$5:AB35) -> 18877385 | AC67: =(AA67-AB67)/AB67 -> -0.54336309 | AF67: =AVERAGE($AF$5:AF35) -> 176.77419 | AG67: =AVERAGE($AG$5:AG35) -> 397.35484 | AH67: =(AF67-AG67)/AG67 -> -0.55512258 | AI67: =AVERAGE($AI$5:AI35) -> 315.12903 | AJ67: =AVERAGE($AJ$5:AJ35) -> 690.12903 | AK67: =(AI67-AJ67)/AJ67 -> -0.54337665 | AL67: =AVERAGE($AL$5:AL35) -> 1362446 | AM67: =AVERAGE($AM$5:AM35) -> 2828986.7 | AN67: =(AL67-AM67)/AM67 -> -0.51839788 | AO67: =AVERAGE($AO$5:AO35) -> 243143.26 | AP67: =AVERAGE($AP$5:AP35) -> 596744.26 | AQ67: =(AO67-AP67)/AP67 -> -0.59255032 | AR67: =AVERAGE($AR$5:AR35) -> 139025.08 | AS67: =AVERAGE($AS$5:AS35) -> 168428.44 | AT67: =(AR67-AS67)/AS67 -> -0.17457478
A68: 日环比 | B68: 本月日环比数据 | E68: 本月日环比数据 | H68: 本月日环比数据 | K68: 本月日环比数据 | N68: 本月日环比数据 | Q68: 本月日环比数据 | T68: 本月日环比数据 | X68: 本月日环比数据 | AA68: 本月日环比数据 | AF68: 本月日环比数据 | AI68: 本月日环比数据 | AL68: 本月日环比数据 | AO68: 本月日环比数据 | AR68: 本月日环比数据
A69: =A37 -> 46082 | B69: =+B5-'2026年2月WP'!D39 -> 7540 | E69: =+E5-'2026年2月WP'!B36 -> -46 | H69: =+H5-'2026年2月WP'!C36 -> 6 | K69: =+K5-'2026年2月WP'!F36 -> -3 | N69: =+N5-'2026年2月WP'!G36 -> 285 | Q69: =+Q5-'2026年2月WP'!K36 -> 125 | T69: =+T5-'2026年2月WP'!L36 -> 797407.01 | X69: =+X5-'2026年2月WP'!J36 -> -4414 | AA69: =+AA5-'2026年2月WP'!P36 -> 929930.01 | AF69: =+AF5-'2026年2月WP'!H36 -> -75 | AI69: =+AI5-'2026年2月WP'!I36 -> -39 | AL69: =+AL5-'2026年2月WP'!M36 -> 1225368 | AO69: =+AO5-'2026年2月WP'!Q36 -> -613812.91 | AR69: =+AR5-'2026年2月WP'!AF36 -> -575578.68
A70: =A38 -> 46083 | B70: =+B6-B5 -> -1699 | E70: =+E6-E5 -> -5 | H70: =+H6-H5 -> 10 | K70: =+K6-K5 -> -339 | N70: =+N6-N5 -> -614 | Q70: =+Q6-Q5 -> 9306 | T70: =+T6-T5 -> -308764 | X70: =+X6-X5 -> -573 | AA70: =+AA6-AA5 -> -1486358.5 | AF70: =+AF6-AF5 -> 15 | AI70: =+AI6-AI5 -> -1 | AL70: =+AL6-AL5 -> -11296 | AO70: =+AO6-AO5 -> 83420.03 | AR70: =+AR6-AR5 -> -307757.71
A71: =A39 -> 46084 | B71: =+B7-B6 -> 2996 | E71: =+E7-E6 -> -20 | H71: =+H7-H6 -> -31 | K71: =+K7-K6 -> -27 | N71: =+N7-N6 -> -77 | Q71: =+Q7-Q6 -> 2341 | T71: =+T7-T6 -> -616417 | X71: =+X7-X6 -> 965 | AA71: =+AA7-AA6 -> -922800.71 | AF71: =+AF7-AF6 -> -106 | AI71: =+AI7-AI6 -> -154 | AL71: =+AL7-AL6 -> -1356433 | AO71: =+AO7-AO6 -> 215396.1 | AR71: =+AR7-AR6 -> 675390.74
A72: =A40 -> 46085 | B72: =+B8-B7 -> 2371 | E72: =+E8-E7 -> 55 | H72: =+H8-H7 -> 29 | K72: =+K8-K7 -> 143 | N72: =+N8-N7 -> 286 | Q72: =+Q8-Q7 -> -2181 | T72: =+T8-T7 -> 1013989 | X72: =+X8-X7 -> 749 | AA72: =+AA8-AA7 -> 7000063.8 | AF72: =+AF8-AF7 -> 50 | AI72: =+AI8-AI7 -> 99 | AL72: =+AL8-AL7 -> 1178400 | AO72: =+AO8-AO7 -> -97727.33 | AR72: =+AR8-AR7 -> -156090.84
A73: =A41 -> 46086 | B73: =+B9-B8 -> -4585 | E73: =+E9-E8 -> -36 | H73: =+H9-H8 -> 9 | K73: =+K9-K8 -> -162 | N73: =+N9-N8 -> -172 | Q73: =+Q9-Q8 -> 8007 | T73: =+T9-T8 -> 49429 | X73: =+X9-X8 -> -1383 | AA73: =+AA9-AA8 -> -953800.45 | AF73: =+AF9-AF8 -> -55 | AI73: =+AI9-AI8 -> -64 | AL73: =+AL9-AL8 -> 131018 | AO73: =+AO9-AO8 -> -125532.81 | AR73: =+AR9-AR8 -> -117419.6
A74: =A42 -> 46087 | B74: =+B10-B9 -> 531 | E74: =+E10-E9 -> 25 | H74: =+H10-H9 -> -5 | K74: =+K10-K9 -> -2 | N74: =+N10-N9 -> -39 | Q74: =+Q10-Q9 -> -9759 | T74: =+T10-T9 -> -879763 | X74: =+X10-X9 -> 522 | AA74: =+AA10-AA9 -> -5752078.8 | AF74: =+AF10-AF9 -> -1 | AI74: =+AI10-AI9 -> -68 | AL74: =+AL10-AL9 -> -1250449 | AO74: =+AO10-AO9 -> 672125.45 | AR74: =+AR10-AR9 -> 647025.3
A75: =A43 -> 46088 | B75: =+B11-B10 -> -924 | E75: =+E11-E10 -> -10 | H75: =+H11-H10 -> 18 | K75: =+K11-K10 -> 269 | N75: =+N11-N10 -> 429 | Q75: =+Q11-Q10 -> 5340 | T75: =+T11-T10 -> 221775.48 | X75: =+X11-X10 -> -150 | AA75: =+AA11-AA10 -> 1980567.8 | AF75: =+AF11-AF10 -> 57 | AI75: =+AI11-AI10 -> 151 | AL75: =+AL11-AL10 -> 406453 | AO75: =+AO11-AO10 -> -356813.24 | AR75: =+AR11-AR10 -> -373315.04
A76: =A44 -> 46089 | B76: =+B12-B11 -> 10274 | E76: =+E12-E11 -> 196 | H76: =+H12-H11 -> 45 | K76: =+K12-K11 -> 96 | N76: =+N12-N11 -> -163 | Q76: =+Q12-Q11 -> -409 | T76: =+T12-T11 -> -232768.48 | X76: =+X12-X11 -> 10507 | AA76: =+AA12-AA11 -> -1884940.9 | AF76: =+AF12-AF11 -> 106 | AI76: =+AI12-AI11 -> 98 | AL76: =+AL12-AL11 -> -554163 | AO76: =+AO12-AO11 -> 99018.99 | AR76: =+AR12-AR11 -> 120833.21
A77: =A45 -> 46090 | B77: =+B13-B12 -> -6288 | E77: =+E13-E12 -> -82 | H77: =+H13-H12 -> 4 | K77: =+K13-K12 -> -277 | N77: =+N13-N12 -> -200 | Q77: =+Q13-Q12 -> -1801 | T77: =+T13-T12 -> 200374 | X77: =+X13-X12 -> -6139 | AA77: =+AA13-AA12 -> 781452.15 | AF77: =+AF13-AF12 -> -2 | AI77: =+AI13-AI12 -> -34 | AL77: =+AL13-AL12 -> 659691 | AO77: =+AO13-AO12 -> 233547.2 | AR77: =+AR13-AR12 -> -337077.94
A78: =A46 -> 46091 | B78: =+B14-B13 -> -1507 | E78: =+E14-E13 -> -5 | H78: =+H14-H13 -> -36 | K78: =+K14-K13 -> -20 | N78: =+N14-N13 -> -148 | Q78: =+Q14-Q13 -> -6322 | T78: =+T14-T13 -> -403392 | X78: =+X14-X13 -> -2059 | AA78: =+AA14-AA13 -> -1039970.3 | AF78: =+AF14-AF13 -> -123 | AI78: =+AI14-AI13 -> -138 | AL78: =+AL14-AL13 -> -491148 | AO78: =+AO14-AO13 -> -407456.93 | AR78: =+AR14-AR13 -> 249971.35
A79: =A47 -> 46092 | B79: =+B15-B14 -> 969 | E79: =+E15-E14 -> -84 | H79: =+H15-H14 -> -26 | K79: =+K15-K14 -> -11 | N79: =+N15-N14 -> 241 | Q79: =+Q15-Q14 -> -3520 | T79: =+T15-T14 -> 247136 | X79: =+X15-X14 -> 979 | AA79: =+AA15-AA14 -> -2318597.6 | AF79: =+AF15-AF14 -> 18 | AI79: =+AI15-AI14 -> 46 | AL79: =+AL15-AL14 -> -389733 | AO79: =+AO15-AO14 -> 531214.59 | AR79: =+AR15-AR14 -> 468224.99
A80: =A48 -> 46093 | B80: =+B16-B15 -> -1949 | E80: =+E16-E15 -> -56 | H80: =+H16-H15 -> -26 | K80: =+K16-K15 -> -17 | N80: =+N16-N15 -> -191 | Q80: =+Q16-Q15 -> -3739 | T80: =+T16-T15 -> -163457 | X80: =+X16-X15 -> -2539 | AA80: =+AA16-AA15 -> -780871.12 | AF80: =+AF16-AF15 -> -3 | AI80: =+AI16-AI15 -> 3 | AL80: =+AL16-AL15 -> 976741 | AO80: =+AO16-AO15 -> -1255116.1 | AR80: =+AR16-AR15 -> -1121609
A81: =A49 -> 46094 | B81: =+B17-B16 -> -7729 | E81: =+E17-E16 -> -184 | H81: =+H17-H16 -> -85 | K81: =+K17-K16 -> -1437 | N81: =+N17-N16 -> -3615 | Q81: =+Q17-Q16 -> -14507 | T81: =+T17-T16 -> -3455174 | X81: =+X17-X16 -> -4112 | AA81: =+AA17-AA16 -> -18010102 | AF81: =+AF17-AF16 -> -443 | AI81: =+AI17-AI16 -> -811 | AL81: =+AL17-AL16 -> -3631857 | AO81: =+AO17-AO16 -> 93637.11 | AR81: =+AR17-AR16 -> #VALUE!
... A99: =A67 -> 46112 | B99: =+B35-B34 -> 0 | E99: =+E35-E34 -> 0 | H99: =+H35-H34 -> 0 | K99: =+K35-K34 -> 0 | N99: =+N35-N34 -> 0 | Q99: =+Q35-Q34 -> 0 | T99: =+T35-T34 -> 0 | X99: =+X35-X34 -> 0 | AA99: =+AA35-AA34 -> 0 | AF99: =+AF35-AF34 -> 0 | AI99: =+AI35-AI34 -> 0 | AL99: =+AL35-AL34 -> 0 | AO99: =+AO35-AO34 -> 0 | AR99: =+AR35-AR34 -> #VALUE!
A100: 日均值 | B100: 本月日均值数据 | C100: 上月日均值数据 | D100: 营业日日均值同比上月日均值增长率 | E100: 本月日均值数据 | F100: 上月日均值数据 | G100: 营业日日均值同比上月日均值增长率 | H100: 本月日均值数据 | I100: 上月日均值数据 | J100: 营业日日均值同比上月日均值增长率 | K100: 本月日均值数据 | L100: 上月日均值数据 | M100: 营业日日均值同比上月日均值增长率 | N100: 本月日均值数据 | O100: 上月日均值数据 | P100: 营业日日均值同比上月日均值增长率 | Q100: 本月日均值数据 | R100: 上月日均值数据 | S100: 营业日日均值同比上月日均值增长率 | T100: 本月日均值数据 | U100: 上月日均值数据 | V100: 营业日日均值同比上月日均值增长率 | X100: 本月日均值数据 | Y100: 上月日均值数据 | Z100: 营业日日均值同比上月日均值增长率 | AA100: 本月日均值数据 | AB100: 上月日均值数据 | AC100: 营业日日均值同比上月日均值增长率 | AF100: 本月日均值数据 | AG100: 上月日均值数据 | AH100: 营业日日均值同比上月日均值增长率 | AI100: 本月日均值数据 | AJ100: 上月日均值数据 | AK100: 营业日日均值同比上月日均值增长率 | AL100: 本月日均值数据 | AM100: 上月日均值数据 | AN100: 营业日日均值同比上月日均值增长率 | AO100: 本月日均值数据 | AP100: 上月日均值数据 | AQ100: 营业日日均值同比上月日均值增长率 | AR100: 本月日均值数据 | AS100: 上月日均值数据 | AT100: 营业日日均值同比上月日均值增长率
A101: =A69 -> 46082 | B101: =B5/1 -> 7540 | C101: =AVERAGE($C$5:$C$35) -> 6262.2903 | D101: =(B101-C101)/C101 -> 0.20403233 | E101: =E5/1 -> 206 | F101: =AVERAGE($F$5:$F$35) -> 217.70968 | G101: =(E101-F101)/F101 -> -0.053785746 | H101: =H5/1 -> 94 | I101: =AVERAGE($I$5:$I$35) -> 91.225806 | J101: =(H101-I101)/I101 -> 0.030410184 | K101: =K5/1 -> 1784 | L101: =AVERAGE($L$5:$L$35) -> 1358 | M101: =(K101-L101)/L101 -> 0.31369661 | N101: =N5/1 -> 4263 | O101: =AVERAGE($O$5:$O$35) -> 3295.5161 | P101: =(N101-O101)/O101 -> 0.29357583 | Q101: =Q5/1 -> 17244 | R101: =AVERAGE($R$5:$R$35) -> 26498.452 | S101: =(Q101-R101)/R101 -> -0.349245 | T101: =T5/1 -> 4327032 | U101: =AVERAGE($U$5:$U$35) -> 3086549.6 | V101: =(T101-U101)/U101 -> 0.40189939 | X101: =X5/1 -> 3233 | Y101: =AVERAGE($Y$5:$Y$35) -> 3568.7419 | Z101: =(X101-Y101)/Y101 -> -0.094078513 | AA101: =AA5/1 -> 23387437 | AB101: =AVERAGE($AB$5:$AB$35) -> 18877385 | AC101: =(AA101-AB101)/AB101 -> 0.23891291 | AF101: =AF5/1 -> 487 | AG101: =AVERAGE($AG$5:$AG$35) -> 397.35484 | AH101: =(AF101-AG101)/AG101 -> 0.22560481 | AI101: =AI5/1 -> 873 | AJ101: =AVERAGE($AJ$5:$AJ$35) -> 690.12903 | AK101: =(AI101-AJ101)/AJ101 -> 0.26498084 | AL101: =AL5/1 -> 4332776 | AM101: =AVERAGE($AM$5:$AM$35) -> 2828986.7 | AN101: =(AL101-AM101)/AM101 -> 0.53156465 | AO101: =AO5/1 -> 314286.96 | AP101: =AVERAGE($AP$5:$AP$35) -> 596744.26 | AQ101: =(AO101-AP101)/AP101 -> -0.47333057 | AR101: =AR5/1 -> -122166.12 | AS101: =AVERAGE($AS$5:$AS$35) -> 168428.44 | AT101: =(AR101-AS101)/AS101 -> -1.7253295
A102: =A70 -> 46083 | B102: =AVERAGE($B$5:B6) -> 6690.5 | C102: =AVERAGE($C$5:$C$35) -> 6262.2903 | D102: =(B102-C102)/C102 -> 0.068379084 | E102: =AVERAGE($E$5:E6) -> 203.5 | F102: =AVERAGE($F$5:$F$35) -> 217.70968 | G102: =(E102-F102)/F102 -> -0.065268929 | H102: =AVERAGE($H$5:H6) -> 99 | I102: =AVERAGE($I$5:$I$35) -> 91.225806 | J102: =(H102-I102)/I102 -> 0.085219236 | K102: =AVERAGE($K$5:K6) -> 1614.5 | L102: =AVERAGE($L$5:$L$35) -> 1358 | M102: =(K102-L102)/L102 -> 0.18888071 | N102: =AVERAGE($N$5:N6) -> 3956 | O102: =AVERAGE($O$5:$O$35) -> 3295.5161 | P102: =(N102-O102)/O102 -> 0.20041895 | Q102: =AVERAGE($Q$5:Q6) -> 21897 | R102: =AVERAGE($R$5:$R$35) -> 26498.452 | S102: =(Q102-R102)/R102 -> -0.17364983 | T102: =AVERAGE($T$5:T6) -> 4172650 | U102: =AVERAGE($U$5:$U$35) -> 3086549.6 | V102: =(T102-U102)/U102 -> 0.35188173 | X102: =AVERAGE($X$5:X6) -> 2946.5 | Y102: =AVERAGE($Y$5:$Y$35) -> 3568.7419 | Z102: =(X102-Y102)/Y102 -> -0.1743589 | AA102: =AVERAGE($AA$5:AA6) -> 22644257 | AB102: =AVERAGE($AB$5:$AB$35) -> 18877385 | AC102: =(AA102-AB102)/AB102 -> 0.19954415 | AF102: =AVERAGE($AF$5:AF6) -> 494.5 | AG102: =AVERAGE($AG$5:$AG$35) -> 397.35484 | AH102: =(AF102-AG102)/AG102 -> 0.24447962 | AI102: =AVERAGE($AI$5:AI6) -> 872.5 | AJ102: =AVERAGE($AJ$5:$AJ$35) -> 690.12903 | AK102: =(AI102-AJ102)/AJ102 -> 0.26425633 | AL102: =AVERAGE($AL$5:AL6) -> 4327128 | AM102: =AVERAGE($AM$5:$AM$35) -> 2828986.7 | AN102: =(AL102-AM102)/AM102 -> 0.52956818 | AO102: =AVERAGE($AO$5:AO6) -> 355996.97 | AP102: =AVERAGE($AP$5:$AP$35) -> 596744.26 | AQ102: =(AO102-AP102)/AP102 -> -0.40343461 | AR102: =AVERAGE($AR$5:AR6) -> -276044.97 | AS102: =AVERAGE($AS$5:$AS$35) -> 168428.44 | AT102: =(AR102-AS102)/AS102 -> -2.6389451
A103: =A71 -> 46084 | B103: =AVERAGE($B$5:B7) -> 7406 | C103: =AVERAGE($C$5:$C$35) -> 6262.2903 | D103: =(B103-C103)/C103 -> 0.18263441 | E103: =AVERAGE($E$5:E7) -> 196 | F103: =AVERAGE($F$5:$F$35) -> 217.70968 | G103: =(E103-F103)/F103 -> -0.099718477 | H103: =AVERAGE($H$5:H7) -> 90.333333 | I103: =AVERAGE($I$5:$I$35) -> 91.225806 | J103: =(H103-I103)/I103 -> -0.0097831212 | K103: =AVERAGE($K$5:K7) -> 1549 | L103: =AVERAGE($L$5:$L$35) -> 1358 | M103: =(K103-L103)/L103 -> 0.14064801 | N103: =AVERAGE($N$5:N7) -> 3828 | O103: =AVERAGE($O$5:$O$35) -> 3295.5161 | P103: =(N103-O103)/O103 -> 0.16157829 | Q103: =AVERAGE($Q$5:Q7) -> 24228.333 | R103: =AVERAGE($R$5:$R$35) -> 26498.452 | S103: =(Q103-R103)/R103 -> -0.085669846 | T103: =AVERAGE($T$5:T7) -> 3915717 | U103: =AVERAGE($U$5:$U$35) -> 3086549.6 | V103: =(T103-U103)/U103 -> 0.26863894 | X103: =AVERAGE($X$5:X7) -> 3172.6667 | Y103: =AVERAGE($Y$5:$Y$35) -> 3568.7419 | Z103: =(X103-Y103)/Y103 -> -0.11098456 | AA103: =AVERAGE($AA$5:AA7) -> 22088931 | AB103: =AVERAGE($AB$5:$AB$35) -> 18877385 | AC103: =(AA103-AB103)/AB103 -> 0.17012659 | AF103: =AVERAGE($AF$5:AF7) -> 461.66667 | AG103: =AVERAGE($AG$5:$AG$35) -> 397.35484 | AH103: =(AF103-AG103)/AG103 -> 0.16184987 | AI103: =AVERAGE($AI$5:AI7) -> 821 | AJ103: =AVERAGE($AJ$5:$AJ$35) -> 690.12903 | AK103: =(AI103-AJ103)/AJ103 -> 0.18963261 | AL103: =AVERAGE($AL$5:AL7) -> 3873101 | AM103: =AVERAGE($AM$5:$AM$35) -> 2828986.7 | AN103: =(AL103-AM103)/AM103 -> 0.36907714 | AO103: =AVERAGE($AO$5:AO7) -> 441699.01 | AP103: =AVERAGE($AP$5:$AP$35) -> 596744.26 | AQ103: =(AO103-AP103)/AP103 -> -0.25981859 | AR103: =AVERAGE($AR$5:AR7) -> -102207.68 | AS103: =AVERAGE($AS$5:$AS$35) -> 168428.44 | AT103: =(AR103-AS103)/AS103 -> -1.6068315
A104: =A72 -> 46085 | B104: =AVERAGE($B$5:B8) -> 8356.5 | C104: =AVERAGE($C$5:$C$35) -> 6262.2903 | D104: =(B104-C104)/C104 -> 0.33441594 | E104: =AVERAGE($E$5:E8) -> 206 | F104: =AVERAGE($F$5:$F$35) -> 217.70968 | G104: =(E104-F104)/F104 -> -0.053785746 | H104: =AVERAGE($H$5:H8) -> 93.25 | I104: =AVERAGE($I$5:$I$35) -> 91.225806 | J104: =(H104-I104)/I104 -> 0.022188826 | K104: =AVERAGE($K$5:K8) -> 1552 | L104: =AVERAGE($L$5:$L$35) -> 1358 | M104: =(K104-L104)/L104 -> 0.14285714 | N104: =AVERAGE($N$5:N8) -> 3835.5 | O104: =AVERAGE($O$5:$O$35) -> 3295.5161 | P104: =(N104-O104)/O104 -> 0.16385411 | Q104: =AVERAGE($Q$5:Q8) -> 24848.75 | R104: =AVERAGE($R$5:$R$35) -> 26498.452 | S104: =(Q104-R104)/R104 -> -0.062256529 | T104: =AVERAGE($T$5:T8) -> 4040747.8 | U104: =AVERAGE($U$5:$U$35) -> 3086549.6 | V104: =(T104-U104)/U104 -> 0.3091472 | X104: =AVERAGE($X$5:X8) -> 3473 | Y104: =AVERAGE($Y$5:$Y$35) -> 3568.7419 | Z104: =(X104-Y104)/Y104 -> -0.026827923 | AA104: =AVERAGE($AA$5:AA8) -> 23561283 | AB104: =AVERAGE($AB$5:$AB$35) -> 18877385 | AC104: =(AA104-AB104)/AB104 -> 0.24812217 | AF104: =AVERAGE($AF$5:AF8) -> 457.75 | AG104: =AVERAGE($AG$5:$AG$35) -> 397.35484 | AH104: =(AF104-AG104)/AG104 -> 0.15199302 | AI104: =AVERAGE($AI$5:AI8) -> 820 | AJ104: =AVERAGE($AJ$5:$AJ$35) -> 690.12903 | AK104: =(AI104-AJ104)/AJ104 -> 0.1881836 | AL104: =AVERAGE($AL$5:AL8) -> 3940687.5 | AM104: =AVERAGE($AM$5:$AM$35) -> 2828986.7 | AN104: =(AL104-AM104)/AM104 -> 0.39296785 | AO104: =AVERAGE($AO$5:AO8) -> 460118.2 | AP104: =AVERAGE($AP$5:$AP$35) -> 596744.26 | AQ104: =(AO104-AP104)/AP104 -> -0.22895246 | AR104: =AVERAGE($AR$5:AR8) -> -54311.741 | AS104: =AVERAGE($AS$5:$AS$35) -> 168428.44 | AT104: =(AR104-AS104)/AS104 -> -1.3224618
A105: =A73 -> 46086 | B105: =AVERAGE($B$5:B9) -> 8009.8 | C105: =AVERAGE($C$5:$C$35) -> 6262.2903 | D105: =(B105-C105)/C105 -> 0.2790528 | E105: =AVERAGE($E$5:E9) -> 204.8 | F105: =AVERAGE($F$5:$F$35) -> 217.70968 | G105: =(E105-F105)/F105 -> -0.059297674 | H105: =AVERAGE($H$5:H9) -> 96.8 | I105: =AVERAGE($I$5:$I$35) -> 91.225806 | J105: =(H105-I105)/I105 -> 0.061103253 | K105: =AVERAGE($K$5:K9) -> 1521.4 | L105: =AVERAGE($L$5:$L$35) -> 1358 | M105: =(K105-L105)/L105 -> 0.12032401 | N105: =AVERAGE($N$5:N9) -> 3805.6 | O105: =AVERAGE($O$5:$O$35) -> 3295.5161 | P105: =(N105-O105)/O105 -> 0.15478118 | Q105: =AVERAGE($Q$5:Q9) -> 26822.4 | R105: =AVERAGE($R$5:$R$35) -> 26498.452 | S105: =(Q105-R105)/R105 -> 0.012225182 | T105: =AVERAGE($T$5:T9) -> 4125652 | U105: =AVERAGE($U$5:$U$35) -> 3086549.6 | V105: =(T105-U105)/U105 -> 0.33665502 | X105: =AVERAGE($X$5:X9) -> 3376.6 | Y105: =AVERAGE($Y$5:$Y$35) -> 3568.7419 | Z105: =(X105-Y105)/Y105 -> -0.053840244 | AA105: =AVERAGE($AA$5:AA9) -> 24253935 | AB105: =AVERAGE($AB$5:$AB$35) -> 18877385 | AC105: =(AA105-AB105)/AB105 -> 0.2848143 | AF105: =AVERAGE($AF$5:AF9) -> 444.4 | AG105: =AVERAGE($AG$5:$AG$35) -> 397.35484 | AH105: =(AF105-AG105)/AG105 -> 0.11839584 | AI105: =AVERAGE($AI$5:AI9) -> 806.6 | AJ105: =AVERAGE($AJ$5:$AJ$35) -> 690.12903 | AK105: =(AI105-AJ105)/AJ105 -> 0.16876694 | AL105: =AVERAGE($AL$5:AL9) -> 4007443 | AM105: =AVERAGE($AM$5:$AM$35) -> 2828986.7 | AN105: =(AL105-AM105)/AM105 -> 0.41656482 | AO105: =AVERAGE($AO$5:AO9) -> 446063.15 | AP105: =AVERAGE($AP$5:$AP$35) -> 596744.26 | AQ105: =(AO105-AP105)/AP105 -> -0.25250534 | AR105: =AVERAGE($AR$5:AR9) -> -49058.098 | AS105: =AVERAGE($AS$5:$AS$35) -> 168428.44 | AT105: =(AR105-AS105)/AS105 -> -1.2912697
A106: =A74 -> 46087 | B106: =AVERAGE($B$5:B10) -> 7867.1667 | C106: =AVERAGE($C$5:$C$35) -> 6262.2903 | D106: =(B106-C106)/C106 -> 0.25627626 | E106: =AVERAGE($E$5:E10) -> 208.16667 | F106: =AVERAGE($F$5:$F$35) -> 217.70968 | G106: =(E106-F106)/F106 -> -0.043833654 | H106: =AVERAGE($H$5:H10) -> 98.333333 | I106: =AVERAGE($I$5:$I$35) -> 91.225806 | J106: =(H106-I106)/I106 -> 0.077911363 | K106: =AVERAGE($K$5:K10) -> 1500.6667 | L106: =AVERAGE($L$5:$L$35) -> 1358 | M106: =(K106-L106)/L106 -> 0.10505646 | N106: =AVERAGE($N$5:N10) -> 3779.1667 | O106: =AVERAGE($O$5:$O$35) -> 3295.5161 | P106: =(N106-O106)/O106 -> 0.14676018 | Q106: =AVERAGE($Q$5:Q10) -> 26511.667 | R106: =AVERAGE($R$5:$R$35) -> 26498.452 | S106: =(Q106-R106)/R106 -> 0.00049871041 | T106: =AVERAGE($T$5:T10) -> 4035627.7 | U106: =AVERAGE($U$5:$U$35) -> 3086549.6 | V106: =(T106-U106)/U106 -> 0.30748836 | X106: =AVERAGE($X$5:X10) -> 3399.3333 | Y106: =AVERAGE($Y$5:$Y$35) -> 3568.7419 | Z106: =(X106-Y106)/Y106 -> -0.047470118 | AA106: =AVERAGE($AA$5:AA10) -> 23757023 | AB106: =AVERAGE($AB$5:$AB$35) -> 18877385 | AC106: =(AA106-AB106)/AB106 -> 0.25849115 | AF106: =AVERAGE($AF$5:AF10) -> 435.33333 | AG106: =AVERAGE($AG$5:$AG$35) -> 397.35484 | AH106: =(AF106-AG106)/AG106 -> 0.095578287 | AI106: =AVERAGE($AI$5:AI10) -> 786.33333 | AJ106: =AVERAGE($AJ$5:$AJ$35) -> 690.12903 | AK106: =(AI106-AJ106)/AJ106 -> 0.13940045 | AL106: =AVERAGE($AL$5:AL10) -> 3843538.5 | AM106: =AVERAGE($AM$5:$AM$35) -> 2828986.7 | AN106: =(AL106-AM106)/AM106 -> 0.35862729 | AO106: =AVERAGE($AO$5:AO10) -> 548714.03 | AP106: =AVERAGE($AP$5:$AP$35) -> 596744.26 | AQ106: =(AO106-AP106)/AP106 -> -0.080487141 | AR106: =AVERAGE($AR$5:AR10) -> 62281.881 | AS106: =AVERAGE($AS$5:$AS$35) -> 168428.44 | AT106: =(AR106-AS106)/AS106 -> -0.63021756
A107: =A75 -> 46088 | B107: =AVERAGE($B$5:B11) -> 7633.2857 | C107: =AVERAGE($C$5:$C$35) -> 6262.2903 | D107: =(B107-C107)/C107 -> 0.21892875 | E107: =AVERAGE($E$5:E11) -> 209.14286 | F107: =AVERAGE($F$5:$F$35) -> 217.70968 | G107: =(E107-F107)/F107 -> -0.039349745 | H107: =AVERAGE($H$5:H11) -> 102 | I107: =AVERAGE($I$5:$I$35) -> 91.225806 | J107: =(H107-I107)/I107 -> 0.11810467 | K107: =AVERAGE($K$5:K11) -> 1524.2857 | L107: =AVERAGE($L$5:$L$35) -> 1358 | M107: =(K107-L107)/L107 -> 0.12244898 | N107: =AVERAGE($N$5:N11) -> 3821.5714 | O107: =AVERAGE($O$5:$O$35) -> 3295.5161 | P107: =(N107-O107)/O107 -> 0.15962759 | Q107: =AVERAGE($Q$5:Q11) -> 27052.571 | R107: =AVERAGE($R$5:$R$35) -> 26498.452 | S107: =(Q107-R107)/R107 -> 0.020911404 | T107: =AVERAGE($T$5:T11) -> 4003006.8 | U107: =AVERAGE($U$5:$U$35) -> 3086549.6 | V107: =(T107-U107)/U107 -> 0.29691964 | X107: =AVERAGE($X$5:X11) -> 3394.1429 | Y107: =AVERAGE($Y$5:$Y$35) -> 3568.7419 | Z107: =(X107-Y107)/Y107 -> -0.048924546 | AA107: =AVERAGE($AA$5:AA11) -> 23685024 | AB107: =AVERAGE($AB$5:$AB$35) -> 18877385 | AC107: =(AA107-AB107)/AB107 -> 0.25467712 | AF107: =AVERAGE($AF$5:AF11) -> 437 | AG107: =AVERAGE($AG$5:$AG$35) -> 397.35484 | AH107: =(AF107-AG107)/AG107 -> 0.09977269 | AI107: =AVERAGE($AI$5:AI11) -> 793.42857 | AJ107: =AVERAGE($AJ$5:$AJ$35) -> 690.12903 | AK107: =(AI107-AJ107)/AJ107 -> 0.14968149 | AL107: =AVERAGE($AL$5:AL11) -> 3784528.6 | AM107: =AVERAGE($AM$5:$AM$35) -> 2828986.7 | AN107: =(AL107-AM107)/AM107 -> 0.33776826 | AO107: =AVERAGE($AO$5:AO11) -> 571062.76 | AP107: =AVERAGE($AP$5:$AP$35) -> 596744.26 | AQ107: =(AO107-AP107)/AP107 -> -0.043036034 | AR107: =AVERAGE($AR$5:AR11) -> 88479.717 | AS107: =AVERAGE($AS$5:$AS$35) -> 168428.44 | AT107: =(AR107-AS107)/AS107 -> -0.47467473
A108: =A76 -> 46089 | B108: =AVERAGE($B$5:B12) -> 8742.125 | C108: =AVERAGE($C$5:$C$35) -> 6262.2903 | D108: =(B108-C108)/C108 -> 0.39599484 | E108: =AVERAGE($E$5:E12) -> 234.375 | F108: =AVERAGE($F$5:$F$35) -> 217.70968 | G108: =(E108-F108)/F108 -> 0.076548378 | H108: =AVERAGE($H$5:H12) -> 110.375 | I108: =AVERAGE($I$5:$I$35) -> 91.225806 | J108: =(H108-I108)/I108 -> 0.20990983 | K108: =AVERAGE($K$5:K12) -> 1554 | L108: =AVERAGE($L$5:$L$35) -> 1358 | M108: =(K108-L108)/L108 -> 0.1443299 | N108: =AVERAGE($N$5:N12) -> 3833 | O108: =AVERAGE($O$5:$O$35) -> 3295.5161 | P108: =(N108-O108)/O108 -> 0.16309551 | Q108: =AVERAGE($Q$5:Q12) -> 27407.125 | R108: =AVERAGE($R$5:$R$35) -> 26498.452 | S108: =(Q108-R108)/R108 -> 0.034291565 | T108: =AVERAGE($T$5:T12) -> 3949445.1 | U108: =AVERAGE($U$5:$U$35) -> 3086549.6 | V108: =(T108-U108)/U108 -> 0.27956637 | X108: =AVERAGE($X$5:X12) -> 4703.625 | Y108: =AVERAGE($Y$5:$Y$35) -> 3568.7419 | Z108: =(X108-Y108)/Y108 -> 0.31800648 | AA108: =AVERAGE($AA$5:AA12) -> 23395407 | AB108: =AVERAGE($AB$5:$AB$35) -> 18877385 | AC108: =(AA108-AB108)/AB108 -> 0.23933512 | AF108: =AVERAGE($AF$5:AF12) -> 451.5 | AG108: =AVERAGE($AG$5:$AG$35) -> 397.35484 | AH108: =(AF108-AG108)/AG108 -> 0.136264 | AI108: =AVERAGE($AI$5:AI12) -> 811 | AJ108: =AVERAGE($AJ$5:$AJ$35) -> 690.12903 | AK108: =(AI108-AJ108)/AJ108 -> 0.17514256 | AL108: =AVERAGE($AL$5:AL12) -> 3671000.8 | AM108: =AVERAGE($AM$5:$AM$35) -> 2828986.7 | AN108: =(AL108-AM108)/AM108 -> 0.29763805 | AO108: =AVERAGE($AO$5:AO12) -> 600201.68 | AP108: =AVERAGE($AP$5:$AP$35) -> 596744.26 | AQ108: =(AO108-AP108)/AP108 -> 0.0057938012 | AR108: =AVERAGE($AR$5:AR12) -> 123232.25 | AS108: =AVERAGE($AS$5:$AS$35) -> 168428.44 | AT108: =(AR108-AS108)/AS108 -> -0.26834064
A109: =A77 -> 46090 | B109: =AVERAGE($B$5:B13) -> 8905.8889 | C109: =AVERAGE($C$5:$C$35) -> 6262.2903 | D109: =(B109-C109)/C109 -> 0.42214564 | E109: =AVERAGE($E$5:E13) -> 244.88889 | F109: =AVERAGE($F$5:$F$35) -> 217.70968 | G109: =(E109-F109)/F109 -> 0.12484154 | H109: =AVERAGE($H$5:H13) -> 117.33333 | I109: =AVERAGE($I$5:$I$35) -> 91.225806 | J109: =(H109-I109)/I109 -> 0.28618576 | K109: =AVERAGE($K$5:K13) -> 1546.3333 | L109: =AVERAGE($L$5:$L$35) -> 1358 | M109: =(K109-L109)/L109 -> 0.13868434 | N109: =AVERAGE($N$5:N13) -> 3819.6667 | O109: =AVERAGE($O$5:$O$35) -> 3295.5161 | P109: =(N109-O109)/O109 -> 0.1590496 | Q109: =AVERAGE($Q$5:Q13) -> 27482.778 | R109: =AVERAGE($R$5:$R$35) -> 26498.452 | S109: =(Q109-R109)/R109 -> 0.037146554 | T109: =AVERAGE($T$5:T13) -> 3930049.7 | U109: =AVERAGE($U$5:$U$35) -> 3086549.6 | V109: =(T109-U109)/U109 -> 0.27328254 | X109: =AVERAGE($X$5:X13) -> 5040 | Y109: =AVERAGE($Y$5:$Y$35) -> 3568.7419 | Z109: =(X109-Y109)/Y109 -> 0.41226239 | AA109: =AVERAGE($AA$5:AA13) -> 23256977 | AB109: =AVERAGE($AB$5:$AB$35) -> 18877385 | AC109: =(AA109-AB109)/AB109 -> 0.23200203 | AF109: =AVERAGE($AF$5:AF13) -> 462.55556 | AG109: =AVERAGE($AG$5:$AG$35) -> 397.35484 | AH109: =(AF109-AG109)/AG109 -> 0.16408688 | AI109: =AVERAGE($AI$5:AI13) -> 820.88889 | AJ109: =AVERAGE($AJ$5:$AJ$35) -> 690.12903 | AK109: =(AI109-AJ109)/AJ109 -> 0.18947161 | AL109: =AVERAGE($AL$5:AL13) -> 3656000.3 | AM109: =AVERAGE($AM$5:$AM$35) -> 2828986.7 | AN109: =(AL109-AM109)/AM109 -> 0.29233565 | AO109: =AVERAGE($AO$5:AO13) -> 648814.98 | AP109: =AVERAGE($AP$5:$AP$35) -> 596744.26 | AQ109: =(AO109-AP109)/AP109 -> 0.087258005 | AR109: =AVERAGE($AR$5:AR13) -> 112808.89 | AS109: =AVERAGE($AS$5:$AS$35) -> 168428.44 | AT109: =(AR109-AS109)/AS109 -> -0.33022663
A110: =A78 -> 46091 | B110: =AVERAGE($B$5:B14) -> 8886.2 | C110: =AVERAGE($C$5:$C$35) -> 6262.2903 | D110: =(B110-C110)/C110 -> 0.4190016 | E110: =AVERAGE($E$5:E14) -> 252.8 | F110: =AVERAGE($F$5:$F$35) -> 217.70968 | G110: =(E110-F110)/F110 -> 0.16117943 | H110: =AVERAGE($H$5:H14) -> 119.3 | I110: =AVERAGE($I$5:$I$35) -> 91.225806 | J110: =(H110-I110)/I110 -> 0.30774399 | K110: =AVERAGE($K$5:K14) -> 1538.2 | L110: =AVERAGE($L$5:$L$35) -> 1358 | M110: =(K110-L110)/L110 -> 0.13269514 | N110: =AVERAGE($N$5:N14) -> 3794.2 | O110: =AVERAGE($O$5:$O$35) -> 3295.5161 | P110: =(N110-O110)/O110 -> 0.15132193 | Q110: =AVERAGE($Q$5:Q14) -> 26911.1 | R110: =AVERAGE($R$5:$R$35) -> 26498.452 | S110: =(Q110-R110)/R110 -> 0.015572547 | T110: =AVERAGE($T$5:T14) -> 3874194.2 | U110: =AVERAGE($U$5:$U$35) -> 3086549.6 | V110: =(T110-U110)/U110 -> 0.25518613 | X110: =AVERAGE($X$5:X14) -> 5103.2 | Y110: =AVERAGE($Y$5:$Y$35) -> 3568.7419 | Z110: =(X110-Y110)/Y110 -> 0.42997171 | AA110: =AVERAGE($AA$5:AA14) -> 23042237 | AB110: =AVERAGE($AB$5:$AB$35) -> 18877385 | AC110: =(AA110-AB110)/AB110 -> 0.22062648 | AF110: =AVERAGE($AF$5:AF14) -> 459.1 | AG110: =AVERAGE($AG$5:$AG$35) -> 397.35484 | AH110: =(AF110-AG110)/AG110 -> 0.15539049 | AI110: =AVERAGE($AI$5:AI14) -> 815 | AJ110: =AVERAGE($AJ$5:$AJ$35) -> 690.12903 | AK110: =(AI110-AJ110)/AJ110 -> 0.18093858 | AL110: =AVERAGE($AL$5:AL14) -> 3594885.2 | AM110: =AVERAGE($AM$5:$AM$35) -> 2828986.7 | AN110: =(AL110-AM110)/AM110 -> 0.27073246 | AO110: =AVERAGE($AO$5:AO14) -> 646959.92 | AP110: =AVERAGE($AP$5:$AP$35) -> 596744.26 | AQ110: =(AO110-AP110)/AP110 -> 0.084149377 | AR110: =AVERAGE($AR$5:AR14) -> 129467.33 | AS110: =AVERAGE($AS$5:$AS$35) -> 168428.44 | AT110: =(AR110-AS110)/AS110 -> -0.23132143
A111: =A79 -> 46092 | B111: =AVERAGE($B$5:B15) -> 8958.1818 | C111: =AVERAGE($C$5:$C$35) -> 6262.2903 | D111: =(B111-C111)/C111 -> 0.43049609 | E111: =AVERAGE($E$5:E15) -> 251.63636 | F111: =AVERAGE($F$5:$F$35) -> 217.70968 | G111: =(E111-F111)/F111 -> 0.15583453 | H111: =AVERAGE($H$5:H15) -> 118.54545 | I111: =AVERAGE($I$5:$I$35) -> 91.225806 | J111: =(H111-I111)/I111 -> 0.2994728 | K111: =AVERAGE($K$5:K15) -> 1530.5455 | L111: =AVERAGE($L$5:$L$35) -> 1358 | M111: =(K111-L111)/L111 -> 0.12705851 | N111: =AVERAGE($N$5:N15) -> 3795.2727 | O111: =AVERAGE($O$5:$O$35) -> 3295.5161 | P111: =(N111-O111)/O111 -> 0.15164744 | Q111: =AVERAGE($Q$5:Q15) -> 26123.364 | R111: =AVERAGE($R$5:$R$35) -> 26498.452 | S111: =(Q111-R111)/R111 -> -0.01415509 | T111: =AVERAGE($T$5:T15) -> 3850961.2 | U111: =AVERAGE($U$5:$U$35) -> 3086549.6 | V111: =(T111-U111)/U111 -> 0.24765895 | X111: =AVERAGE($X$5:X15) -> 5243.9091 | Y111: =AVERAGE($Y$5:$Y$35) -> 3568.7419 | Z111: =(X111-Y111)/Y111 -> 0.46939991 | AA111: =AVERAGE($AA$5:AA15) -> 22655758 | AB111: =AVERAGE($AB$5:$AB$35) -> 18877385 | AC111: =(AA111-AB111)/AB111 -> 0.20015338 | AF111: =AVERAGE($AF$5:AF15) -> 457.90909 | AG111: =AVERAGE($AG$5:$AG$35) -> 397.35484 | AH111: =(AF111-AG111)/AG111 -> 0.15239339 | AI111: =AVERAGE($AI$5:AI15) -> 814.36364 | AJ111: =AVERAGE($AJ$5:$AJ$35) -> 690.12903 | AK111: =(AI111-AJ111)/AJ111 -> 0.18001649 | AL111: =AVERAGE($AL$5:AL15) -> 3509451.6 | AM111: =AVERAGE($AM$5:$AM$35) -> 2828986.7 | AN111: =(AL111-AM111)/AM111 -> 0.24053311 | AO111: =AVERAGE($AO$5:AO15) -> 693734.39 | AP111: =AVERAGE($AP$5:$AP$35) -> 596744.26 | AQ111: =(AO111-AP111)/AP111 -> 0.16253214 | AR111: =AVERAGE($AR$5:AR15) -> 185662.88 | AS111: =AVERAGE($AS$5:$AS$35) -> 168428.44 | AT111: =(AR111-AS111)/AS111 -> 0.10232498
A112: =A80 -> 46093 | B112: =AVERAGE($B$5:B16) -> 8855.75 | C112: =AVERAGE($C$5:$C$35) -> 6262.2903 | D112: =(B112-C112)/C112 -> 0.41413916 | E112: =AVERAGE($E$5:E16) -> 246 | F112: =AVERAGE($F$5:$F$35) -> 217.70968 | G112: =(E112-F112)/F112 -> 0.12994518 | H112: =AVERAGE($H$5:H16) -> 115.75 | I112: =AVERAGE($I$5:$I$35) -> 91.225806 | J112: =(H112-I112)/I112 -> 0.26882956 | K112: =AVERAGE($K$5:K16) -> 1522.75 | L112: =AVERAGE($L$5:$L$35) -> 1358 | M112: =(K112-L112)/L112 -> 0.12131811 | N112: =AVERAGE($N$5:N16) -> 3780.25 | O112: =AVERAGE($O$5:$O$35) -> 3295.5161 | P112: =(N112-O112)/O112 -> 0.14708891 | Q112: =AVERAGE($Q$5:Q16) -> 25155.333 | R112: =AVERAGE($R$5:$R$35) -> 26498.452 | S112: =(Q112-R112)/R112 -> -0.05068667 | T112: =AVERAGE($T$5:T16) -> 3817979 | U112: =AVERAGE($U$5:$U$35) -> 3086549.6 | V112: =(T112-U112)/U112 -> 0.23697314 | X112: =AVERAGE($X$5:X16) -> 5149.5833 | Y112: =AVERAGE($Y$5:$Y$35) -> 3568.7419 | Z112: =(X112-Y112)/Y112 -> 0.44296882 | AA112: =AVERAGE($AA$5:AA16) -> 22268620 | AB112: =AVERAGE($AB$5:$AB$35) -> 18877385 | AC112: =(AA112-AB112)/AB112 -> 0.17964535 | AF112: =AVERAGE($AF$5:AF16) -> 456.66667 | AG112: =AVERAGE($AG$5:$AG$35) -> 397.35484 | AH112: =(AF112-AG112)/AG112 -> 0.14926666 | AI112: =AVERAGE($AI$5:AI16) -> 814.08333 | AJ112: =AVERAGE($AJ$5:$AJ$35) -> 690.12903 | AK112: =(AI112-AJ112)/AJ112 -> 0.17961033 | AL112: =AVERAGE($AL$5:AL16) -> 3519652.1 | AM112: =AVERAGE($AM$5:$AM$35) -> 2828986.7 | AN112: =(AL112-AM112)/AM112 -> 0.2441388 | AO112: =AVERAGE($AO$5:AO16) -> 628120.09 | AP112: =AVERAGE($AP$5:$AP$35) -> 596744.26 | AQ112: =(AO112-AP112)/AP112 -> 0.052578351 | AR112: =AVERAGE($AR$5:AR16) -> 139025.08 | AS112: =AVERAGE($AS$5:$AS$35) -> 168428.44 | AT112: =(AR112-AS112)/AS112 -> -0.17457478
A113: =A81 -> 46094 | B113: =AVERAGE($B$5:B17) -> 8174.5385 | C113: =AVERAGE($C$5:$C$35) -> 6262.2903 | D113: =(B113-C113)/C113 -> 0.30535923 | E113: =AVERAGE($E$5:E17) -> 227.07692 | F113: =AVERAGE($F$5:$F$35) -> 217.70968 | G113: =(E113-F113)/F113 -> 0.043026317 | H113: =AVERAGE($H$5:H17) -> 106.84615 | I113: =AVERAGE($I$5:$I$35) -> 91.225806 | J113: =(H113-I113)/I113 -> 0.17122729 | K113: =AVERAGE($K$5:K17) -> 1405.6154 | L113: =AVERAGE($L$5:$L$35) -> 1358 | M113: =(K113-L113)/L113 -> 0.035062875 | N113: =AVERAGE($N$5:N17) -> 3489.4615 | O113: =AVERAGE($O$5:$O$35) -> 3295.5161 | P113: =(N113-O113)/O113 -> 0.0588513 | Q113: =AVERAGE($Q$5:Q17) -> 23220.308 | R113: =AVERAGE($R$5:$R$35) -> 26498.452 | S113: =(Q113-R113)/R113 -> -0.12371077 | T113: =AVERAGE($T$5:T17) -> 3524288.3 | U113: =AVERAGE($U$5:$U$35) -> 3086549.6 | V113: =(T113-U113)/U113 -> 0.14182136 | X113: =AVERAGE($X$5:X17) -> 4753.4615 | Y113: =AVERAGE($Y$5:$Y$35) -> 3568.7419 | Z113: =(X113-Y113)/Y113 -> 0.33197122 | AA113: =AVERAGE($AA$5:AA17) -> 20555649 | AB113: =AVERAGE($AB$5:$AB$35) -> 18877385 | AC113: =(AA113-AB113)/AB113 -> 0.0889034 | AF113: =AVERAGE($AF$5:AF17) -> 421.53846 | AG113: =AVERAGE($AG$5:$AG$35) -> 397.35484 | AH113: =(AF113-AG113)/AG113 -> 0.060861528 | AI113: =AVERAGE($AI$5:AI17) -> 751.46154 | AJ113: =AVERAGE($AJ$5:$AJ$35) -> 690.12903 | AK113: =(AI113-AJ113)/AJ113 -> 0.088871071 | AL113: =AVERAGE($AL$5:AL17) -> 3248909.6 | AM113: =AVERAGE($AM$5:$AM$35) -> 2828986.7 | AN113: =(AL113-AM113)/AM113 -> 0.14843581 | AO113: =AVERAGE($AO$5:AO17) -> 579803.16 | AP113: =AVERAGE($AP$5:$AP$35) -> 596744.26 | AQ113: =(AO113-AP113)/AP113 -> -0.028389215 | AR113: =AVERAGE($AR$5:AR17) -> 139025.08 | AS113: =AVERAGE($AS$5:$AS$35) -> 168428.44 | AT113: =(AR113-AS113)/AS113 -> -0.17457478
... A131: =A99 -> 46112 | B131: =AVERAGE($B$5:B35) -> 3428.0323 | C131: =AVERAGE($C$5:$C$35) -> 6262.2903 | D131: =(B131-C131)/C131 -> -0.45259129 | E131: =AVERAGE($E$5:E35) -> 95.225806 | F131: =AVERAGE($F$5:$F$35) -> 217.70968 | G131: =(E131-F131)/F131 -> -0.56260187 | H131: =AVERAGE($H$5:H35) -> 44.806452 | I131: =AVERAGE($I$5:$I$35) -> 91.225806 | J131: =(H131-I131)/I131 -> -0.50884017 | K131: =AVERAGE($K$5:K35) -> 589.45161 | L131: =AVERAGE($L$5:$L$35) -> 1358 | M131: =(K131-L131)/L131 -> -0.56594137 | N131: =AVERAGE($N$5:N35) -> 1463.3226 | O131: =AVERAGE($O$5:$O$35) -> 3295.5161 | P131: =(N131-O131)/O131 -> -0.55596558 | Q131: =AVERAGE($Q$5:Q35) -> 9737.5484 | R131: =AVERAGE($R$5:$R$35) -> 26498.452 | S131: =(Q131-R131)/R131 -> -0.63252387 | T131: =AVERAGE($T$5:T35) -> 1477927.3 | U131: =AVERAGE($U$5:$U$35) -> 3086549.6 | V131: =(T131-U131)/U131 -> -0.52117169 | X131: =AVERAGE($X$5:X35) -> 1993.3871 | Y131: =AVERAGE($Y$5:$Y$35) -> 3568.7419 | Z131: =(X131-Y131)/Y131 -> -0.44143143 | AA131: =AVERAGE($AA$5:AA35) -> 8620111 | AB131: =AVERAGE($AB$5:$AB$35) -> 18877385 | AC131: =(AA131-AB131)/AB131 -> -0.54336309 | AF131: =AVERAGE($AF$5:AF35) -> 176.77419 | AG131: =AVERAGE($AG$5:$AG$35) -> 397.35484 | AH131: =(AF131-AG131)/AG131 -> -0.55512258 | AI131: =AVERAGE($AI$5:AI35) -> 315.12903 | AJ131: =AVERAGE($AJ$5:$AJ$35) -> 690.12903 | AK131: =(AI131-AJ131)/AJ131 -> -0.54337665 | AL131: =AVERAGE($AL$5:AL35) -> 1362446 | AM131: =AVERAGE($AM$5:$AM$35) -> 2828986.7 | AN131: =(AL131-AM131)/AM131 -> -0.51839788 | AO131: =AVERAGE($AO$5:AO35) -> 243143.26 | AP131: =AVERAGE($AP$5:$AP$35) -> 596744.26 | AQ131: =(AO131-AP131)/AP131 -> -0.59255032 | AR131: =AVERAGE($AR$5:AR35) -> 139025.08 | AS131: =AVERAGE($AS$5:$AS$35) -> 168428.44 | AT131: =(AR131-AS131)/AS131 -> -0.17457478

Sheet GJP_ro
A1: GJP财务报表
A2: 日期 | B2: 总登录人数 | E2: 总新注册人数 | H2: 总首充人数 | K2: 总存款人数 | N2: 总存款次数 | Q2: 总首存 | T2: 总存款额度 | W2: 当月 每人平均存款额 | X2: 总投注人数 | AA2: 有效投注 | AD2: 当月 每人平均投注额 | AE2: 当月 每人平均投注次数 | AF2: 总取款人数 | AI2: 总取款次数 | AL2: 总取款额度 | AO2: 公司輸贏 (淨贏-淨輸) | AR2: 总收益
A3: date | B3: Login Head Count | E3: Total New Users | H3: no of first time depositors | K3: no of total depositors | N3: total deposit counts | Q3: total first deposit amount | T3: total deposit amount | W3: ave. deposit amount per person | X3: no of bettors | AA3: valid bet amount | AD3: ave. bet amount per person | AE3: ave. no. of bets per person | AF3: no of total withdrawer | AI3: total withdrawal counts | AL3: total withdrawal amount | AO3: Company Win/Loss | AR3: Gross Profit
B4: 本月日数据 | C4: 上月日数据 | D4: 同比增长率 | E4: 本月数据 | F4: 上月数据 | G4: 增长率 | H4: 本月数据 | I4: 上月数据 | J4: 增长率 | K4: 本月数据 | L4: 上月数据 | M4: 增长率 | N4: 本月数据 | O4: 上月数据 | P4: 增长率 | Q4: 本月数据 | R4: 上月数据 | S4: 增长率 | T4: 本月数据 | U4: 上月数据 | V4: 增长率 | X4: 本月数据 | Y4: 上月数据 | Z4: 增长率 | AA4: 本月数据 | AB4: 上月数据 | AC4: 增长率 | AF4: 本月数据 | AG4: 上月数据 | AH4: 增长率 | AI4: 本月数据 | AJ4: 上月数据 | AK4: 增长率 | AL4: 本月数据 | AM4: 上月数据 | AN4: 增长率 | AO4: 本月数据 | AP4: 上月数据 | AQ4: 增长率 | AR4: 本月数据 | AS4: 上月数据 | AT4: 增长率
A5: =全平台汇总!A3 -> 46082 | B5: =GJP!D9 -> 19170 | C5: ='2026年2月GJP'!D9 -> 18208 | D5: =(B5-C5)/C5 -> 0.052833919 | E5: =GJP!B9 -> 734 | F5: ='2026年2月GJP'!B9 -> 931 | G5: =(E5-F5)/F5 -> -0.21160043 | H5: =GJP!C9 -> 200 | I5: ='2026年2月GJP'!C9 -> 204 | J5: =(H5-I5)/I5 -> -0.019607843 | K5: =GJP!F9 -> 2361 | L5: ='2026年2月GJP'!F9 -> 2508 | M5: =(K5-L5)/L5 -> -0.05861244 | N5: =GJP!G9 -> 4778 | O5: ='2026年2月GJP'!G9 -> 4989 | P5: =(N5-O5)/O5 -> -0.042293045 | Q5: =GJP!K9 -> 32342 | R5: ='2026年2月GJP'!K9 -> 44897 | S5: =(Q5-R5)/R5 -> -0.27964007 | T5: =GJP!L9 -> 3452835.6 | U5: ='2026年2月GJP'!L9 -> 3106771.4 | V5: =(T5-U5)/U5 -> 0.11139031 | W5: =GJP!AH9 -> 1462.4463 | X5: =GJP!J9 -> 13551 | Y5: ='2026年2月GJP'!J9 -> 13162 | Z5: =(X5-Y5)/Y5 -> 0.029554779 | AA5: =GJP!P9 -> 23941465 | AB5: ='2026年2月GJP'!P9 -> 25422361 | AC5: =(AA5-AB5)/AB5 -> -0.058251713 | AD5: =GJP!AI9 -> 1766.7674 | AE5: =GJP!AJ9 -> 5.7395172 | AF5: =GJP!H9 -> 665 | AG5: ='2026年2月GJP'!H9 -> 648 | AH5: =(AF5-AG5)/AG5 -> 0.026234568 | AI5: =GJP!I9 -> 988 | AJ5: ='2026年2月GJP'!I9 -> 1005 | AK5: =(AI5-AJ5)/AJ5 -> -0.016915423 | AL5: =GJP!M9 -> 2765137 | AM5: ='2026年2月GJP'!M9 -> 2958057 | AN5: =(AL5-AM5)/AM5 -> -0.065218486 | AO5: =GJP!Q9 -> 1187358.9 | AP5: ='2026年2月GJP'!Q9 -> -64018.34 | AQ5: =(AO5-AP5)/AP5 -> -19.547167 | AR5: =GJP!AF9 -> 776954.83 | AS5: ='2026年2月GJP'!AF9 -> -587140.95 | AT5: =(AR5-AS5)/AS5 -> -2.323285
